Workbook

Sheet Front Page
M6: Please contact this email for any model-specific questions:
M7: modelsupport@alpha-sense.com | N7: mailto:support@canalyst.com?subject=Canalyst%20Support:%20ASML%20Holdings%20N.V.%20ASML%20US&body=Model%20Version:%20Q2-2019.20 | O7: mailto:support@canalyst.com?subject=Canalyst%20Support:%20ASML%20Holdings%20N.V.%20ASML%20US&body=Model%20Version:%20Q2-2019.20
C9: Company Model: | H9: =Model!A1 -> ASML Holdings N.V.
C11: Updated: | H11: =OFFSET('Update Log'!$C$10,1,0,1,1) -> 46049
M12: Comments on Model:
C13: For: | H13: =OFFSET('Update Log'!$E$10,1,0,1,1) -> Initial (Press Release)
C15: Consensus Data and Real-Time Stock Price: | H15: Bloomberg
H16: =IF(FP.DataSourceName="Bloomberg",1,IF(FP.DataSourceName="Capital IQ",2,IF(FP.DataSourceName="FactSet",3,IF(FP.DataSourceName="Refinitiv",4)))) -> 1
C18: Real-Time Stock Price: | H18: OFF
C20: Stock Price Override: | F20: 46049 | H20: 1217.6
C22: DISCLAIMER Access to and use of this model, including the data contained herein (this "Model") is subject to Tegus, Inc.'s (a successor entity to Canalyst Financial Modeling Corporation) ("Company") Terms of Use that you accepted prior to accessing this Model, the applicable Service Agreement between the Company and you (or a corporate entity that has authorized you to access and use this Model on its behalf in accordance with the terms of such Service Agreement) or other similar agreement between you and the Company. BY CONTINUING TO ACCESS OR USE THIS MODEL, YOU EXPRESSLY AGREE TO THE TERMS AND CONDITIONS OF SUCH AGREEMENTS. The Company and certain of its licensors have exclusive proprietary rights in this Model. This Model is being provided for internal use only. Unless prior written consent by the Company and its licensors has been provided to you, you may not distribute or otherwise furnish this Model to any third party, nor use or permit anyone to use this Model for any unlawful or unauthorized purpose. IF YOU HAVE UNLAWFULLY OBTAINED, OR ARE NOT AUTHORIZED TO USE THIS MODEL, YOU ARE OBLIGATED TO PROMPTLY: (I) RETURN THIS MODEL (AND ANY DERIVATIVE WORKS ARISING FROM OR RELATING THERETO) TO THE AUTHORIZED USER OF THIS MODEL; (II) PROVIDE NOTICE TO THE COMPANY AT LEGAL@TEGUS.COM OF SUCH UNLAWFUL OR UNAUTHORIZED ACCESS AND USE; AND, (III) CERTIFY THAT YOU HAVE DESTROYED THIS MODEL (AND ANY DERIVATIVE WORKS ARISING FROM OR RELATING THERETO) AND ANY COPIES FROM YOUR SYSTEMS SO AS TO ENSURE THEY ARE INCAPABLE OF RETRIEVAL. A portion of the data contained in this Model may be powered by third party contributors and their respective licensors, or derived from data provided by such contributors, including (but not limited to): (i) QuoteMedia Inc.: A portion of the market data is powered by Quotemedia.com. All rights reserved. Data delayed 15 minutes unless otherwise indicated; (ii) S&P Global Market Intelligence LLC: Copyright (c) {{YEAR}} S&P Global Market Intelligence LLC (and its affiliates as applicable). All rights reserved. Reproduction of any information, opinions, views, data or material, including ratings ("Content") in any form is prohibited except with the prior written permission of the relevant party. Such party, its affiliates and suppliers ("Content Providers") do not guarantee the accuracy, adequacy, completeness, timeliness or availability of any Content and are not responsible for any errors or omissions (negligent or otherwise), regardless of the cause, or for the results obtained from the use of such Content. In no event shall Content Providers be liable for any damages, costs, expenses, legal fees, or losses (including lost income or lost profit and opportunity costs) in connection with any use of the Content. A reference to a particular investment or security, a rating or any observation concerning an investment that is part of the Content is not a recommendation to buy, sell or hold such investment or security, does not address the suitability of an investment or security and should not be relied on as investment advice. Credit ratings are statements of opinions and are not statements of fact; and, (iii) Refinitiv Canada Holdings Limited: A portion of the information may be provided by or derived from data provided by Refinitiv. By accessing or using this Model (including any portion of the data contained herein) you expressly represent that such access or use does not constitute a violation of any applicable law or regulation to which you or the securities are subject. This Model does not constitute investment advice by the Company or any of its licensors. Reference to a particular investment or security, credit rating or any observation concerning a security or investment in this Model is not a recommendation or solicitation to buy, sell or hold such investment or security or make any other investment decisions. For greater certainty, any forecasts or forward-looking information expressed herein are for illustrative purposes only and do not purport to express any view on what may transpire. Neither the Company nor any of its licensors have performed company-specific research on any projected information, as such, it is your responsibility to express your own views on projected results. This Model does not guarantee future performance and undue reliance should not be placed on such. You are solely responsible for evaluating the merits and risks of any investment based on your own business and financial expertise, the business and financial expertise of professional advisors with whom you have consulted, your financial situation and risk tolerance. Neither the Company, nor any of its licensors, undertake any liability with respect to your reliance on this Model. This Model is a quantitative tool with no investment views. The Company and its respective directors, officers, employees, agents, contractors, and affiliates may hold long or short positions in the security to which this Model relates, based on their personal views, and may initiate or close out any positions in such security at any time without any notice. THIS MODEL IS PROVIDED "AS IS" AND ON AN "AS AVAILABLE" BASIS ONLY, WITHOUT WARRANTIES OR CONDITIONS OF ANY KIND. NEITHER THE COMPANY NOR ANY OF ITS LICENSORS NOR THEIR RESPECTIVE AFFILIATES OR SUPPLIERS HAVE LIABILITY FOR THE ACCURACY, TIMELINESS OR COMPLETENESS OF THIS MODEL, OR FOR DELAYS, INTERRUPTIONS OR OMISSIONS HEREIN, NOR FOR ANY LOST PROFITS, INDIRECT, SPECIAL OR CONSEQUENTIAL DAMAGES. Access to data in this Model that is sourced from third party contributors is subject to termination in the event that any agreement between the Company and such third party contributors terminates for any reason. Copyright 2023 Tegus. All rights reserved.

Sheet Multiples Valuation
B1: ASML Holdings N.V. (ASML)
B2: Comprehensive Multiples-Based Valuation
B3: Stock Price Override: | C3: ='Front Page'!H20 -> 1217.6
B5: EPS DRIVERS — NON-GAAP INCOME STATEMENT WATERFALL
B6: ($ in millions, except per share & margins) | C6: FY2024 | D6: FY2025 | E6: FY2026E | F6: FY2027E
B7: Total Revenue | C7: =Model!C329 -> 1596.063 | D7: =Model!D329 -> 4507.938 | E7: =Model!E329 -> 5651.035 | F7: =Model!F329 -> 4731.555
B8: Y/Y Revenue Growth % | D8: =IFERROR(D7/C7-1,"-") -> 1.8244111 | E8: =IFERROR(E7/D7-1,"-") -> 0.25357425 | F8: =IFERROR(F7/E7-1,"-") -> -0.16271002
B9: Non-GAAP COGS | C9: =Model!C332 -> 1137.671 | D9: =Model!D332 -> 2552.768 | E9: =Model!E332 -> 3201.645 | F9: =Model!F332 -> 2726.298
B10: Non-GAAP Gross Profit | C10: =Model!C333 -> 458.392 | D10: =Model!D333 -> 1955.17 | E10: =Model!E333 -> 2449.39 | F10: =Model!F333 -> 2005.257
B11: Gross Margin % | C11: =IFERROR(C10/C7,"-") -> 0.2872017 | D11: =IFERROR(D10/D7,"-") -> 0.43371715 | E11: =IFERROR(E10/E7,"-") -> 0.43344095 | F11: =IFERROR(F10/F7,"-") -> 0.42380507
B12: Non-GAAP R&D Expense | C12: =Model!C335 -> 466.761 | D12: =Model!D335 -> 523.426 | E12: =Model!E335 -> 590.27 | F12: =Model!F335 -> 589.182
B13: R&D as % of Revenue | C13: =IFERROR(C12/C7,"-") -> 0.29244522 | D13: =IFERROR(D12/D7,"-") -> 0.11611207 | E13: =IFERROR(E12/E7,"-") -> 0.10445343 | F13: =IFERROR(F12/F7,"-") -> 0.12452185
B14: Non-GAAP SG&A Expense | C14: =Model!C336 -> 154.756 | D14: =Model!D336 -> 181.045 | E14: =Model!E336 -> 217.904 | F14: =Model!F336 -> 259.301
B15: SG&A as % of Revenue | C15: =IFERROR(C14/C7,"-") -> 0.096961085 | D15: =IFERROR(D14/D7,"-") -> 0.040161378 | E15: =IFERROR(E14/E7,"-") -> 0.038560016 | F15: =IFERROR(F14/F7,"-") -> 0.054802491
B16: Non-GAAP Other OPEX | C16: =Model!C337 -> 0 | D16: =Model!D337 -> 0 | E16: =Model!E337 -> 0 | F16: =Model!F337 -> 0
B17: Non-GAAP Operating Income (EBIT) | C17: =Model!C338 -> -163.125 | D17: =Model!D338 -> 1250.699 | E17: =Model!E338 -> 1641.216 | F17: =Model!F338 -> 1156.774
B18: EBIT Margin % | C18: =IFERROR(C17/C7,"-") -> -0.10220461 | D18: =IFERROR(D17/D7,"-") -> 0.2774437 | E18: =IFERROR(E17/E7,"-") -> 0.29042751 | F18: =IFERROR(F17/F7,"-") -> 0.24448073
B19: Non-GAAP Net Interest Expense | C19: =Model!C348 -> 8.425 | D19: =Model!D348 -> 8.176 | E19: =Model!E348 -> -7.419 | F19: =Model!F348 -> 6.196
B20: Other Non-Operating Items | C20: =Model!C349 -> 0 | D20: =Model!D349 -> 0 | E20: =Model!E349 -> 0 | F20: =Model!F349 -> 0
B21: Non-GAAP Earnings Before Taxes | C21: =C17+C19+C20 -> -154.7 | D21: =D17+D19+D20 -> 1258.875 | E21: =E17+E19+E20 -> 1633.797 | F21: =F17+F19+F20 -> 1162.97
B22: Non-GAAP Tax Provision | C22: =Model!C354 -> 28.798 | D22: =Model!D354 -> 192.65 | E22: =Model!E354 -> 118.425 | F22: =Model!F354 -> 76.636
B23: Tax Rate % | C23: =IFERROR(C22/C21,"-") -> -0.18615385 | D23: =IFERROR(D22/D21,"-") -> 0.15303346 | E23: =IFERROR(E22/E21,"-") -> 0.072484525 | F23: =IFERROR(F22/F21,"-") -> 0.065896799
B24: Non-GAAP Net Income | C24: =Model!C365 -> -150.925 | D24: =Model!D365 -> 1021.82 | E24: =Model!E365 -> 1466.96 | F24: =Model!F365 -> 1146.316
B25: Diluted Shares Outstanding (mm) | C25: =Model!C394 -> 433.63898 | D25: =Model!D394 -> 440.42097 | E25: =Model!E394 -> 417.10426 | F25: =Model!F394 -> 410.05522
B26: Non-GAAP EPS (Diluted) | C26: =IFERROR(C24/C25,"-") -> -0.34804298 | D26: =IFERROR(D24/D25,"-") -> 2.3200984 | E26: =IFERROR(E24/E25,"-") -> 3.5170104 | F26: =IFERROR(F24/F25,"-") -> 2.7955162
B27: Y/Y EPS Growth % | D27: =IFERROR(D26/C26-1,"-") -> -7.6661262 | E27: =IFERROR(E26/D26-1,"-") -> 0.51588844 | F27: =IFERROR(F26/E26-1,"-") -> -0.20514418
B29: EBITDA DRIVERS — NON-GAAP EBITDA BUILD
B30: ($ in millions) | C30: FY2024 | D30: FY2025 | E30: FY2026E | F30: FY2027E
B31: Company Reported Non-GAAP EBIT | C31: =Model!C338 -> -163.125 | D31: =Model!D338 -> 1250.699 | E31: =Model!E338 -> 1641.216 | F31: =Model!F338 -> 1156.774
B32: EBIT Margin % | C32: =IFERROR(C31/C7,"-") -> -0.10220461 | D32: =IFERROR(D31/D7,"-") -> 0.2774437 | E32: =IFERROR(E31/E7,"-") -> 0.29042751 | F32: =IFERROR(F31/F7,"-") -> 0.24448073
B33: Plus: Depreciation | C33: =Model!C107 -> 131.1 | D33: =Model!D107 -> 144.6 | E33: =Model!E107 -> 158 | F33: =Model!F107 -> 179.3
B34: Plus: Amortization | C34: =Model!C111 -> 8.8 | D34: =Model!D111 -> 5.5 | E34: =Model!E111 -> 5.3 | F34: =Model!F111 -> 6.1
B35: Total D&A | C35: =C33+C34 -> 139.9 | D35: =D33+D34 -> 150.1 | E35: =E33+E34 -> 163.3 | F35: =F33+F34 -> 185.4
B36: Non-GAAP EBITDA | C36: =Model!C344 -> -8.1 | D36: =Model!D344 -> 1414.252 | E36: =Model!E344 -> 1818.831 | F36: =Model!F344 -> 1362.108
B37: EBITDA Margin % | C37: =IFERROR(C36/C7,"-") -> -0.0050749876 | D37: =IFERROR(D36/D7,"-") -> 0.31372481 | E37: =IFERROR(E36/E7,"-") -> 0.32185803 | F37: =IFERROR(F36/F7,"-") -> 0.28787745
B38: Y/Y EBITDA Growth % | D38: =IFERROR(D36/C36-1,"-") -> -175.59901 | E38: =IFERROR(E36/D36-1,"-") -> 0.28607278 | F38: =IFERROR(F36/E36-1,"-") -> -0.25110799
B40: MEMO: KEY ADJUSTMENTS
B41: Stock-Based Compensation | C41: =Model!C343 -> 13.394 | D41: =Model!D343 -> 12.109 | E41: =Model!E343 -> 12.43 | F41: =Model!F343 -> 18.714
B42: SBC as % of Revenue | C42: =IFERROR(C41/C7,"-") -> 0.0083918993 | D42: =IFERROR(D41/D7,"-") -> 0.0026861505 | E42: =IFERROR(E41/E7,"-") -> 0.0021995971 | F42: =IFERROR(F41/F7,"-") -> 0.0039551479
B43: Capital Expenditures | C43: =Model!C403 -> -104.959 | D43: =Model!D403 -> -128.728 | E43: =Model!E403 -> -300.898 | F43: =Model!F403 -> -179.536
B44: Free Cash Flow | C44: =Model!C326 -> -5.765 | D44: =Model!D326 -> 811.32 | E44: =Model!E326 -> 1769.542 | F44: =Model!F326 -> 523.942
B45: FCF Margin % | C45: =IFERROR(C44/C7,"-") -> -0.0036120128 | D45: =IFERROR(D44/D7,"-") -> 0.17997586 | E45: =IFERROR(E44/E7,"-") -> 0.31313591 | F45: =IFERROR(F44/F7,"-") -> 0.11073357
B47: ENTERPRISE VALUE BRIDGE
B49: Current Stock Price ($) | C49: ='Front Page'!H20 -> 1217.6
B50: Diluted Shares Outstanding (mm) | C50: =Model!D394 -> 440.42097
B51: Market Capitalization ($M) | C51: =C49*C50 -> 536256.58
B52: Plus: Total Debt ($M) | C52: =Model!D430 -> 710.06
B53: Plus: Operating Lease Liabilities ($M) | C53: 0
B54: Less: Cash & Equivalents ($M) | C54: =-Model!D427 -> -1949.834
B55: Enterprise Value ($M) | C55: =SUM(C51:C54) -> 535016.8
B57: CURRENT TRADING MULTIPLES
B58: Based on current stock price / EV | C58: FY2024 | D58: FY2025 | E58: FY2026E | F58: FY2027E
B59: P/E (Non-GAAP) | C59: =IFERROR(IF(C26<=0,"NM",C51/C26),"NM") -> NM | D59: =IFERROR(IF(D26<=0,"NM",C51/D26),"NM") -> 231135.27 | E59: =IFERROR(IF(E26<=0,"NM",C51/E26),"NM") -> 152475.12 | F59: =IFERROR(IF(F26<=0,"NM",C51/F26),"NM") -> 191827.39
B60: EV / Revenue | C60: =IFERROR(IF(C7<=0,"NM",C55/C7),"NM") -> 335.21033 | D60: =IFERROR(IF(D7<=0,"NM",C55/D7),"NM") -> 118.68327 | E60: =IFERROR(IF(E7<=0,"NM",C55/E7),"NM") -> 94.675896 | F60: =IFERROR(IF(F7<=0,"NM",C55/F7),"NM") -> 113.0742
B61: EV / EBITDA (Non-GAAP) | C61: =IFERROR(IF(C36<=0,"NM",C55/C36),"NM") -> NM | D61: =IFERROR(IF(D36<=0,"NM",C55/D36),"NM") -> 378.30373 | E61: =IFERROR(IF(E36<=0,"NM",C55/E36),"NM") -> 294.15421 | F61: =IFERROR(IF(F36<=0,"NM",C55/F36),"NM") -> 392.78589
B63: IMPLIED VALUATION — TARGET MULTIPLES
B64: Apply target multiples to NTM estimates | C64: Target Multiple | D64: Metric (NTM) | E64: Implied Price/Share
B65: P/E (Non-GAAP NTM EPS) | C65: 30 | D65: =IFERROR(E26/E25,"-") -> 0.0084319695 | E65: =IFERROR(C65*D65,"N/A") -> 0.25295909
B66: EV / Revenue (NTM) | C66: 6.5 | D66: =E7 -> 5651.035 | E66: =IFERROR((C66*D66-(C52+C53)+ABS(C54))/C50,"N/A") -> 86.216379
B67: EV / EBITDA (NTM) | C67: 28 | D67: =E36 -> 1818.831 | E67: =IFERROR((C67*D67-(C52+C53)+ABS(C54))/C50,"N/A") -> 118.44813
B68: Price / FCF (NTM) | C68: 40 | D68: =IFERROR(E44/E25,"-") -> 4.2424453 | E68: =IFERROR(C68*D68,"N/A") -> 169.69781
B70: VALUATION SUMMARY
B71: P/E (Non-GAAP) | C71: =F65 -> 0 | D71: =IFERROR(C71/C49-1,"N/A") -> -1 | E71: 0.3
B72: EV / Revenue | C72: =F66 -> 0 | D72: =IFERROR(C72/C49-1,"N/A") -> -1 | E72: 0.1
B73: EV / EBITDA | C73: =F67 -> 0 | D73: =IFERROR(C73/C49-1,"N/A") -> -1 | E73: 0.35
B74: Price / FCF | C74: =F68 -> 0 | D74: =IFERROR(C74/C49-1,"N/A") -> -1 | E74: 0.25
B75: Weighted Average Implied Price | C75: =C71*E71+C72*E72+C73*E73+C74*E74 -> 0 | D75: =IFERROR(C75/C49-1,"N/A") -> -1 | E75: =SUM(E71:E74) -> 1
B76: Current Stock Price | C76: =C49 -> 1217.6
B78: REVENUE MIX BY SEGMENT
B79: ($ in millions) | C79: FY2024 | D79: FY2025 | E79: FY2026E | F79: FY2027E
B80: EUV systems | C80: =Model!C61 -> 0 | D80: =Model!D61 -> 0 | E80: =Model!E61 -> 119.3 | F80: =Model!F61 -> 43.7
B81: Y/Y EUV Growth % | C81: =Model!C63 -> 0 | D81: =Model!D63 -> 0 | E81: =Model!E63 -> 4764.613 | F81: =Model!F63 -> 3757.932
B82: DUV systems | C82: =Model!C64 -> 0 | D82: =Model!D64 -> 0 | E82: =Model!E64 -> 0 | F82: =Model!F64 -> -0.21128285
B83: Y/Y DUV Growth % | C83: =Model!C66 -> 0 | D83: =Model!D66 -> 0 | E83: =Model!E66 -> 0 | F83: =Model!F66 -> 0
B84: Installed Base Management | C84: =Model!C154 -> 421 | D84: =Model!D154 -> 613 | E84: =Model!E154 -> 767 | F84: =Model!F154 -> 930
B85: Y/Y IBM Growth % | C85: =Model!C166 -> 993.26 | D85: =Model!D166 -> 3704.29 | E85: =Model!E166 -> 4780.72 | F85: =Model!F166 -> 3620.26
B86: Total Revenue | C86: =C7 -> 1596.063 | D86: =D7 -> 4507.938 | E86: =E7 -> 5651.035 | F86: =F7 -> 4731.555
B87: EUV % of Total Revenue | C87: =IFERROR(C80/C7,"-") -> 0 | D87: =IFERROR(D80/D7,"-") -> 0 | E87: =IFERROR(E80/E7,"-") -> 0.021111177 | F87: =IFERROR(F80/F7,"-") -> 0.0092358643
B88: DUV % of Total Revenue | C88: =IFERROR(C82/C7,"-") -> 0 | D88: =IFERROR(D82/D7,"-") -> 0 | E88: =IFERROR(E82/E7,"-") -> 0 | F88: =IFERROR(F82/F7,"-") -> -4.4653998e-05
B89: IBM % of Total Revenue | C89: =IFERROR(C84/C7,"-") -> 0.26377405 | D89: =IFERROR(D84/D7,"-") -> 0.13598235 | E89: =IFERROR(E84/E7,"-") -> 0.13572735 | F89: =IFERROR(F84/F7,"-") -> 0.19655272

Sheet DCF
A1: ASML DCF Valuation Analysis
A4: Period | F4: FY2025 | G4: FY2026 | H4: FY2027 | I4: FY2028 | J4: FY2029
A6: REVENUE BUILD
A7: EUV Revenue | F7: =Model!L45 -> -0.14224467 | G7: =Model!Q45 -> 2.2971083 | H7: =Model!V45 -> 0.08721936 | I7: =Model!AA45 -> 0.79897348 | J7: =Model!AF45 -> 0.30432715
A8: ArFi Revenue | F8: =Model!L48 -> 0 | G8: =Model!Q48 -> 0 | H8: =Model!V48 -> 0 | I8: =Model!AA48 -> 1.7430556 | J8: =Model!AF48 -> 0.22640145
A9: ArF Revenue | F9: =Model!L51 -> 0.11647532 | G9: =Model!Q51 -> 0.07361298 | H9: =Model!V51 -> 0.080705382 | I9: =Model!AA51 -> 0.33231295 | J9: =Model!AF51 -> 0.20890774
A10: KrF Revenue | F10: =Model!L54 -> 0.81967715 | G10: =Model!Q54 -> 0.76429364 | H10: =Model!V54 -> 0.7531464 | I10: =Model!AA54 -> 0.63030893 | J10: =Model!AF54 -> 0.58201257
A11: i-line Revenue | F11: =Model!L57 -> 0.012062817 | G11: =Model!Q57 -> 0.017227483 | H11: =Model!V57 -> 0.016695205 | I11: =Model!AA57 -> 0.013288984 | J11: =Model!AF57 -> 0.011938347
A12: Metrology Revenue | F12: =Model!L60 -> 0 | G12: =Model!Q60 -> 0 | H12: =Model!V60 -> 0 | I12: =Model!AA60 -> 0 | J12: =Model!AF60 -> 0
A13: Total Revenue | F13: =SUM(F7:F12) -> 0.80597061 | G13: =SUM(G7:G12) -> 3.1522424 | H13: =SUM(H7:H12) -> 0.93776635 | I13: =SUM(I7:I12) -> 3.5179399 | J13: =SUM(J7:J12) -> 1.3335873
A14: Y/Y Growth % | G14: =G13/F13 - 1 -> 2.9111134 | H14: =H13/G13 - 1 -> -0.70250818 | I14: =I13/H13 - 1 -> 2.7514034 | J14: =J13/I13 - 1 -> -0.62091812
A16: OPERATING MARGINS
A17: Gross Margin % | F17: =Model!L74 -> 0.44334891 | G17: =Model!Q74 -> 0.46056486 | H17: =Model!V74 -> 0.44806322 | I17: =Model!AA74 -> 0.45032476 | J17: =Model!AF74 -> 0.45953947
A18: Operating Margin % | F18: =Model!L89/Model!L67 -> #DIV/0! | G18: =Model!Q89/Model!Q67 -> #DIV/0! | H18: =Model!V89/Model!V67 -> #DIV/0! | I18: =Model!AA89/Model!AA67 -> #DIV/0! | J18: =Model!AF89/Model!AF67 -> #DIV/0!
A21: UFCF BUILD
A22: Revenue | F22: =F13 -> 0.80597061 | G22: =G13 -> 3.1522424 | H22: =H13 -> 0.93776635 | I22: =I13 -> 3.5179399 | J22: =J13 -> 1.3335873
A23: EBIT | F23: =Model!L89 -> 1282.235 | G23: =Model!Q89 -> 1565.135 | H23: =Model!V89 -> 1657.7 | I23: =Model!AA89 -> 2496.2 | J23: =Model!AF89 -> 2965.3
A24: Tax Rate % | F24: 0.14 | G24: 0.14 | H24: 0.14 | I24: 0.14 | J24: 0.14
A25: NOPAT | F25: =F23 * (1 - F24) -> 1102.7221 | G25: =G23 * (1 - G24) -> 1346.0161 | H25: =H23 * (1 - H24) -> 1425.622 | I25: =I23 * (1 - I24) -> 2146.732 | J25: =J23 * (1 - J24) -> 2550.158
A26: D&A | F26: =Model!L113 -> 254.644 | G26: =Model!Q113 -> 296.884 | H26: =Model!V113 -> 356.9 | I26: =Model!AA113 -> 417.5 | J26: =Model!AF113 -> 422.7
A27: CapEx | F27: =F22 * 0.03 -> 0.024179118 | G27: =G22 * 0.03 -> 0.094567273 | H27: =H22 * 0.03 -> 0.028132991 | I27: =I22 * 0.03 -> 0.1055382 | J27: =J22 * 0.03 -> 0.040007618
A28: Change in Working Capital | F28: =F22 * 0.05 -> 0.040298531 | G28: =G22 * 0.05 -> 0.15761212 | H28: =H22 * 0.05 -> 0.046888318 | I28: =I22 * 0.05 -> 0.17589699 | J28: =J22 * 0.05 -> 0.066679363
A29: Unlevered FCF | F29: =F25 + F26 - F27 - F28 -> 1357.3016 | G29: =G25 + G26 - G27 - G28 -> 1642.6479 | H29: =H25 + H26 - H27 - H28 -> 1782.447 | I29: =I25 + I26 - I27 - I28 -> 2563.9506 | J29: =J25 + J26 - J27 - J28 -> 2972.7513
A31: DISCOUNTING
A32: WACC % | F32: 0.085 | G32: 0.085 | H32: 0.085 | I32: 0.085 | J32: 0.085
A33: Discount Factor | F33: =1 / (1 + F32)^1 -> 0.92165899 | G33: =1 / (1 + G32)^2 -> 0.84945529 | H33: =1 / (1 + H32)^3 -> 0.7829081 | I33: =1 / (1 + I32)^4 -> 0.72157428 | J33: =1 / (1 + J32)^5 -> 0.66504542
A34: PV of UFCF | F34: =F29 * F33 -> 1250.9692 | G34: =G29 * G33 -> 1395.356 | H34: =H29 * H33 -> 1395.4922 | I34: =I29 * I33 -> 1850.0808 | J34: =J29 * J33 -> 1977.0147
A36: TERMINAL VALUE
A37: Terminal Growth % | F37: 0.02
A38: Terminal Value | F38: =F29 * (1 + F37) / (F32 - F37) -> 21299.195
A39: PV of TV | F39: =F38 * F33 -> 19630.594
A41: VALUATION
A42: Sum PV UFCF | F42: =SUM(F34:J34) -> 7868.9128
A43: PV Terminal Value | F43: =F39 -> 19630.594
A44: Enterprise Value | F44: =F42 + F43 -> 27499.507
A45: Less: Net Debt | F45: =Model!L700 - Model!L650 -> 0
A46: Equity Value | F46: =F44 - F45 -> 27499.507
A47: Shares Outstanding (mm) | F47: =Model!L750 -> 0
A48: Implied Price | F48: =F46 / F47 -> #DIV/0!
A49: Current Price | F49: ='Front Page'!H20 -> 1217.6
A50: Upside % | F50: =F48 / F49 - 1 -> #DIV/0!

Sheet Model
A1: ASML Holdings N.V.
A2: =CHOOSE(MO.DataSourceIndex,MO.Ticker.Bloomberg,MO.Ticker.CapIQ,MO.Ticker.FactSet,MO.Ticker.Thomson) -> ASML NA | C2: =EOMONTH(C4,-12) -> 39813 | BN2: Partial | BO2: Partial
A3: =HP.TradeCurrency -> EUR | B3: =IF(MO.RealTime="OFF",MO.LastPriceHardcoded,MO.LastPriceFormula) -> 1217.6 | C3: =C4-C2 -> 365 | D3: =D4-C4 -> 365 | E3: =E4-D4 -> 365 | F3: =F4-E4 -> 366 | G3: =G4-F4 -> 365 | H3: =H4-G4 -> 89 | I3: =I4-H4 -> 91 | J3: =J4-I4 -> 91 | K3: =K4-J4 -> 94 | L3: =L4-G4 -> 365 | M3: =M4-L4 -> 88 | N3: =N4-M4 -> 91 | O3: =O4-N4 -> 91 | P3: =P4-O4 -> 95 | Q3: =Q4-L4 -> 365 | R3: =R4-Q4 -> 94 | S3: =S4-R4 -> 91 | T3: =T4-S4 -> 91 | U3: =U4-T4 -> 90 | V3: =V4-Q4 -> 366 | W3: =W4-V4 -> 92 | X3: =X4-W4 -> 91 | Y3: =Y4-X4 -> 91 | Z3: =Z4-Y4 -> 91 | AA3: =AA4-V4 -> 365 | AB3: =AB4-AA4 -> 91 | AC3: =AC4-AB4 -> 91 | AD3: =AD4-AC4 -> 91 | AE3: =AE4-AD4 -> 92 | AF3: =AF4-AA4 -> 365 | AG3: =AG4-AF4 -> 90 | AH3: =AH4-AG4 -> 91 | AI3: =AI4-AH4 -> 91 | AJ3: =AJ4-AI4 -> 93 | AK3: =AK4-AF4 -> 365 | AL3: =AL4-AK4 -> 89 | AM3: =AM4-AL4 -> 91 | AN3: =AN4-AM4 -> 91 | AO3: =AO4-AN4 -> 95 | AP3: =AP4-AK4 -> 366 | AQ3: =AQ4-AP4 -> 94 | AR3: =AR4-AQ4 -> 91 | AS3: =AS4-AR4 -> 91 | AT3: =AT4-AS4 -> 89 | AU3: =AU4-AP4 -> 365 | AV3: =AV4-AU4 -> 93 | AW3: =AW4-AV4 -> 91 | AX3: =AX4-AW4 -> 91 | AY3: =AY4-AX4 -> 90 | AZ3: =AZ4-AU4 -> 365 | BA3: =BA4-AZ4 -> 92 | BB3: =BB4-BA4 -> 91 | BC3: =BC4-BB4 -> 91 | BD3: =BD4-BC4 -> 91 | BE3: =BE4-AZ4 -> 365 | BF3: =BF4-BE4 -> 91 | BG3: =BG4-BF4 -> 91 | BH3: =BH4-BG4 -> 91 | BI3: =BI4-BH4 -> 93 | BJ3: =BJ4-BE4 -> 366 | BK3: =BK4-BJ4 -> 89 | BL3: =BL4-BK4 -> 91 | BM3: =BM4-BL4 -> 91 | BN3: =BN4-BM4 -> 94 | BO3: =BO4-BJ4 -> 365 | BP3: =BP4-BO4 -> 90 | BQ3: =BQ4-BP4 -> 91 | BR3: =BR4-BQ4 -> 92 | BS3: =BS4-BR4 -> 92 | BT3: =BT4-BO4 -> 365 | BU3: =BU4-BT4 -> 90 | BV3: =BV4-BU4 -> 91 | BW3: =BW4-BV4 -> 92 | BX3: =BX4-BW4 -> 92 | BY3: =BY4-BT4 -> 365 | BZ3: =BZ4-BY4 -> 366 | CA3: =CA4-BZ4 -> 365 | CB3: =CB4-CA4 -> 365
A4: =FP.DataSourceName -> Bloomberg | B4: =IF(AND(MO.RealTimeStockPriceToggle,MO.LastPriceFormula<>"N/A"),"ON","OFF") -> OFF | C4: 40178 | D4: 40543 | E4: 40908 | F4: 41274 | G4: 41639 | H4: 41728 | I4: 41819 | J4: 41910 | K4: =L4 -> 42004 | L4: 42004 | M4: 42092 | N4: 42183 | O4: 42274 | P4: =Q4 -> 42369 | Q4: 42369 | R4: 42463 | S4: 42554 | T4: 42645 | U4: =V4 -> 42735 | V4: 42735 | W4: 42827 | X4: 42918 | Y4: 43009 | Z4: =AA4 -> 43100 | AA4: 43100 | AB4: 43191 | AC4: 43282 | AD4: 43373 | AE4: =AF4 -> 43465 | AF4: 43465 | AG4: 43555 | AH4: 43646 | AI4: 43737 | AJ4: =AK4 -> 43830 | AK4: 43830 | AL4: 43919 | AM4: 44010 | AN4: 44101 | AO4: =AP4 -> 44196 | AP4: 44196 | AQ4: 44290 | AR4: 44381 | AS4: 44472 | AT4: =AU4 -> 44561 | AU4: 44561 | AV4: 44654 | AW4: 44745 | AX4: 44836 | AY4: =AZ4 -> 44926 | AZ4: 44926 | BA4: 45018 | BB4: 45109 | BC4: 45200 | BD4: =BE4 -> 45291 | BE4: 45291 | BF4: 45382 | BG4: 45473 | BH4: 45564 | BI4: =BJ4 -> 45657 | BJ4: 45657 | BK4: 45746 | BL4: 45837 | BM4: 45928 | BN4: =BO4 -> 46022 | BO4: 46022 | BP4: =+EDATE(BO4,3) -> 46112 | BQ4: =+EDATE(BP4,3) -> 46203 | BR4: =+EDATE(BQ4,3) -> 46295 | BS4: =DATE(YEAR(BR4),12,31) -> 46387 | BT4: =BS4 -> 46387 | BU4: =+EDATE(BT4,3) -> 46477 | BV4: =+EDATE(BU4,3) -> 46568 | BW4: =+EDATE(BV4,3) -> 46660 | BX4: =DATE(YEAR(BW4),12,31) -> 46752 | BY4: =BX4 -> 46752 | BZ4: =EOMONTH(BY4,12) -> 47118 | CA4: =EOMONTH(BZ4,12) -> 47483 | CB4: =EOMONTH(CA4,12) -> 47848
A5: =MO.ReportCurrency -> EUR | C5: FY2009 | D5: =CONCATENATE("FY",RIGHT(C5,4)+1) -> FY2010 | E5: =CONCATENATE("FY",RIGHT(D5,4)+1) -> FY2011 | F5: =CONCATENATE("FY",RIGHT(E5,4)+1) -> FY2012 | G5: =CONCATENATE("FY",RIGHT(F5,4)+1) -> FY2013 | H5: =CONCATENATE("Q1","-",RIGHT(G5,4)+1) -> Q1-2014 | I5: =CONCATENATE("Q2","-",RIGHT(H5,4)) -> Q2-2014 | J5: =CONCATENATE("Q3","-",RIGHT(I5,4)) -> Q3-2014 | K5: =CONCATENATE("Q4","-",RIGHT(J5,4)) -> Q4-2014 | L5: =CONCATENATE("FY",RIGHT(G5,4)+1) -> FY2014 | M5: =CONCATENATE("Q1","-",RIGHT(L5,4)+1) -> Q1-2015 | N5: =CONCATENATE("Q2","-",RIGHT(M5,4)) -> Q2-2015 | O5: =CONCATENATE("Q3","-",RIGHT(N5,4)) -> Q3-2015 | P5: =CONCATENATE("Q4","-",RIGHT(O5,4)) -> Q4-2015 | Q5: =CONCATENATE("FY",RIGHT(L5,4)+1) -> FY2015 | R5: =CONCATENATE("Q1","-",RIGHT(Q5,4)+1) -> Q1-2016 | S5: =CONCATENATE("Q2","-",RIGHT(R5,4)) -> Q2-2016 | T5: =CONCATENATE("Q3","-",RIGHT(S5,4)) -> Q3-2016 | U5: =CONCATENATE("Q4","-",RIGHT(T5,4)) -> Q4-2016 | V5: =CONCATENATE("FY",RIGHT(Q5,4)+1) -> FY2016 | W5: =CONCATENATE("Q1","-",RIGHT(V5,4)+1) -> Q1-2017 | X5: =CONCATENATE("Q2","-",RIGHT(W5,4)) -> Q2-2017 | Y5: =CONCATENATE("Q3","-",RIGHT(X5,4)) -> Q3-2017 | Z5: =CONCATENATE("Q4","-",RIGHT(Y5,4)) -> Q4-2017 | AA5: =CONCATENATE("FY",RIGHT(V5,4)+1) -> FY2017 | AB5: =CONCATENATE("Q1","-",RIGHT(AA5,4)+1) -> Q1-2018 | AC5: =CONCATENATE("Q2","-",RIGHT(AB5,4)) -> Q2-2018 | AD5: =CONCATENATE("Q3","-",RIGHT(AC5,4)) -> Q3-2018 | AE5: =CONCATENATE("Q4","-",RIGHT(AD5,4)) -> Q4-2018 | AF5: =CONCATENATE("FY",RIGHT(AA5,4)+1) -> FY2018 | AG5: =CONCATENATE("Q1","-",RIGHT(AF5,4)+1) -> Q1-2019 | AH5: =CONCATENATE("Q2","-",RIGHT(AG5,4)) -> Q2-2019 | AI5: =CONCATENATE("Q3","-",RIGHT(AH5,4)) -> Q3-2019 | AJ5: =CONCATENATE("Q4","-",RIGHT(AI5,4)) -> Q4-2019 | AK5: =CONCATENATE("FY",RIGHT(AF5,4)+1) -> FY2019 | AL5: =CONCATENATE("Q1","-",RIGHT(AK5,4)+1) -> Q1-2020 | AM5: =CONCATENATE("Q2","-",RIGHT(AL5,4)) -> Q2-2020 | AN5: =CONCATENATE("Q3","-",RIGHT(AM5,4)) -> Q3-2020 | AO5: =CONCATENATE("Q4","-",RIGHT(AN5,4)) -> Q4-2020 | AP5: =CONCATENATE("FY",RIGHT(AK5,4)+1) -> FY2020 | AQ5: =CONCATENATE("Q1","-",RIGHT(AP5,4)+1) -> Q1-2021 | AR5: =CONCATENATE("Q2","-",RIGHT(AQ5,4)) -> Q2-2021 | AS5: =CONCATENATE("Q3","-",RIGHT(AR5,4)) -> Q3-2021 | AT5: =CONCATENATE("Q4","-",RIGHT(AS5,4)) -> Q4-2021 | AU5: =CONCATENATE("FY",RIGHT(AP5,4)+1) -> FY2021 | AV5: =CONCATENATE("Q1","-",RIGHT(AU5,4)+1) -> Q1-2022 | AW5: =CONCATENATE("Q2","-",RIGHT(AV5,4)) -> Q2-2022 | AX5: =CONCATENATE("Q3","-",RIGHT(AW5,4)) -> Q3-2022 | AY5: =CONCATENATE("Q4","-",RIGHT(AX5,4)) -> Q4-2022 | AZ5: =CONCATENATE("FY",RIGHT(AU5,4)+1) -> FY2022 | BA5: =CONCATENATE("Q1","-",RIGHT(AZ5,4)+1) -> Q1-2023 | BB5: =CONCATENATE("Q2","-",RIGHT(BA5,4)) -> Q2-2023 | BC5: =CONCATENATE("Q3","-",RIGHT(BB5,4)) -> Q3-2023 | BD5: =CONCATENATE("Q4","-",RIGHT(BC5,4)) -> Q4-2023 | BE5: =CONCATENATE("FY",RIGHT(AZ5,4)+1) -> FY2023 | BF5: =CONCATENATE("Q1","-",RIGHT(BE5,4)+1) -> Q1-2024 | BG5: =CONCATENATE("Q2","-",RIGHT(BF5,4)) -> Q2-2024 | BH5: =CONCATENATE("Q3","-",RIGHT(BG5,4)) -> Q3-2024 | BI5: =CONCATENATE("Q4","-",RIGHT(BH5,4)) -> Q4-2024 | BJ5: =CONCATENATE("FY",RIGHT(BE5,4)+1) -> FY2024 | BK5: =CONCATENATE("Q1","-",RIGHT(BJ5,4)+1) -> Q1-2025 | BL5: =CONCATENATE("Q2","-",RIGHT(BK5,4)) -> Q2-2025 | BM5: =CONCATENATE("Q3","-",RIGHT(BL5,4)) -> Q3-2025 | BN5: =CONCATENATE("Q4","-",RIGHT(BM5,4)) -> Q4-2025 | BO5: =CONCATENATE("FY",RIGHT(BJ5,4)+1) -> FY2025 | BP5: =CONCATENATE("Q1","-",RIGHT(BO5,4)+1) -> Q1-2026 | BQ5: =CONCATENATE("Q2","-",RIGHT(BP5,4)) -> Q2-2026 | BR5: =CONCATENATE("Q3","-",RIGHT(BQ5,4)) -> Q3-2026 | BS5: =CONCATENATE("Q4","-",RIGHT(BR5,4)) -> Q4-2026 | BT5: =CONCATENATE("FY",RIGHT(BO5,4)+1) -> FY2026 | BU5: =CONCATENATE("Q1","-",RIGHT(BT5,4)+1) -> Q1-2027 | BV5: =CONCATENATE("Q2","-",RIGHT(BU5,4)) -> Q2-2027 | BW5: =CONCATENATE("Q3","-",RIGHT(BV5,4)) -> Q3-2027 | BX5: =CONCATENATE("Q4","-",RIGHT(BW5,4)) -> Q4-2027 | BY5: =CONCATENATE("FY",RIGHT(BT5,4)+1) -> FY2027 | BZ5: =CONCATENATE("FY",RIGHT(BY5,4)+1) -> FY2028 | CA5: =CONCATENATE("FY",RIGHT(BZ5,4)+1) -> FY2029 | CB5: =CONCATENATE("FY",RIGHT(CA5,4)+1) -> FY2030
A6: Revenue Build
A7: EUV 3400C units sold, # of units | AI7: 3 | AJ7: 6 | AK7: 9
A8: EUV 3400B units sold, # of units | AG8: 4 | AH8: 7 | AI8: =AI11-AI7 -> 4 | AJ8: =+AJ11-AJ7 -> 2 | AK8: =+AK11-AK7 -> 17
A9: High NA EUV, # of units | BI9: 2 | BJ9: 2 | BK9: 3 | BN9: 2 | BO9: =SUM(BK9,BL9,BM9,BN9) -> 5
A10: Low NA EUV, # of units | BH10: =BH11-BH9 -> 11 | BI10: =BI11-BI9 -> 12 | BJ10: =BJ11-BJ9 -> 42 | BK10: =BK11-BK9 -> 11 | BN10: =BN11-BN9 -> 12 | BO10: =BO11-BO9 -> 43
A11: EUV units sold, # of units | E11: 3 | F11: 1 | G11: 1 | H11: 1 | I11: 1 | J11: 2 | K11: 1 | L11: 5 | M11: 0 | N11: 1 | O11: 0 | P11: 0 | Q11: 1 | R11: 0 | S11: 2 | T11: 1 | U11: 1 | V11: 4 | W11: 0 | X11: 2 | Y11: 4 | Z11: 5 | AA11: 11 | AB11: 1 | AC11: 7 | AD11: 5 | AE11: 5 | AF11: 18 | AG11: =SUM(AG7:AG8) -> 4 | AH11: =SUM(AH7:AH8) -> 7 | AI11: 7 | AJ11: 8 | AK11: 26 | AL11: 2 | AM11: 7 | AN11: 14 | AO11: 8 | AP11: 31 | AQ11: 7 | AR11: 9 | AS11: 15 | AT11: 11 | AU11: 42 | AV11: 3 | AW11: 12 | AX11: 12 | AY11: 13 | AZ11: 40 | BA11: 17 | BB11: 12 | BC11: 11 | BD11: 13 | BE11: 53 | BF11: 11 | BG11: 8 | BH11: 11 | BI11: 14 | BJ11: 44 | BK11: 14 | BL11: 11 | BM11: 9 | BN11: 14 | BO11: 48 | BP11: 13 | BQ11: 13 | BR11: 15 | BS11: 15 | BT11: =SUM(BP11,BQ11,BR11,BS11) -> 56 | BU11: 13 | BV11: 13 | BW11: 15 | BX11: 15 | BY11: =SUM(BU11,BV11,BW11,BX11) -> 56 | BZ11: 65 | CA11: 65 | CB11: 65
A12: ArFi units sold, # of units | E12: 101 | F12: 72 | G12: 77 | H12: 19 | I12: 24 | J12: 13 | K12: 20 | L12: 76 | M12: 23 | N12: 19 | O12: 14 | P12: 11 | Q12: 67 | R12: 15 | S12: 19 | T12: 19 | U12: 17 | V12: 70 | W12: 18 | X12: 16 | Y12: 22 | Z12: 20 | AA12: 76 | AB12: 21 | AC12: 19 | AD12: 22 | AE12: 24 | AF12: 86 | AG12: 17 | AH12: 13 | AI12: 21 | AJ12: 31 | AK12: 82 | AL12: 16 | AM12: 17 | AN12: 11 | AO12: 24 | AP12: 68 | AQ12: 24 | AR12: 16 | AS12: 21 | AT12: 20 | AU12: 81 | AV12: 18 | AW12: 21 | AX12: 20 | AY12: 22 | AZ12: 81 | BA12: 25 | BB12: 39 | BC12: 32 | BD12: 29 | BE12: 125 | BF12: 20 | BG12: 32 | BH12: 38 | BI12: 39 | BJ12: 129 | BK12: 25 | BL12: 31 | BM12: 38 | BN12: 37 | BO12: 131 | BP12: 20 | BQ12: 20 | BR12: 21 | BS12: 20 | BT12: =SUM(BP12,BQ12,BR12,BS12) -> 81 | BU12: 20 | BV12: 20 | BW12: 21 | BX12: 20 | BY12: =SUM(BU12,BV12,BW12,BX12) -> 81 | BZ12: 80 | CA12: 80 | CB12: 80
A13: ArF units sold, # of units | E13: 11 | F13: 4 | G13: 2 | H13: 0 | I13: 2 | J13: 0 | K13: 1 | L13: 3 | M13: 2 | N13: 2 | O13: 2 | P13: 3 | Q13: 9 | R13: 2 | S13: 2 | T13: 1 | U13: 1 | V13: 6 | W13: 4 | X13: 3 | Y13: 2 | Z13: 5 | AA13: 14 | AB13: 3 | AC13: 5 | AD13: 3 | AE13: 5 | AF13: 16 | AG13: 4 | AH13: 3 | AI13: 9 | AJ13: 6 | AK13: 22 | AL13: 6 | AM13: 7 | AN13: 2 | AO13: 7 | AP13: 22 | AQ13: 4 | AR13: 7 | AS13: 6 | AT13: 5 | AU13: 22 | AV13: 6 | AW13: 8 | AX13: 6 | AY13: 8 | AZ13: 28 | BA13: 7 | BB13: 6 | BC13: 9 | BD13: 10 | BE13: 32 | BF13: 4 | BG13: 11 | BH13: 7 | BI13: 6 | BJ13: 28 | BK13: 3 | BL13: 4 | BM13: 4 | BN13: 5 | BO13: 16 | BP13: 8 | BQ13: 8 | BR13: 8 | BS13: 8 | BT13: =SUM(BP13,BQ13,BR13,BS13) -> 32 | BU13: 8 | BV13: 8 | BW13: 8 | BX13: 8 | BY13: =SUM(BU13,BV13,BW13,BX13) -> 32 | BZ13: 32 | CA13: 32 | CB13: 32
A14: KrF units sold, # of units | E14: 87 | F14: 78 | G14: 64 | H14: 17 | I14: 2 | J14: 10 | K14: 10 | L14: 38 | M14: 16 | N14: 14 | O14: 24 | P14: 20 | Q14: 74 | R14: 12 | S14: 16 | T14: 14 | U14: 15 | V14: 57 | W14: 19 | X14: 14 | Y14: 18 | Z14: 20 | AA14: 71 | AB14: 19 | AC14: 19 | AD14: 18 | AE14: 22 | AF14: 78 | AG14: 14 | AH14: 19 | AI14: 14 | AJ14: 18 | AK14: 65 | AL14: 22 | AM14: 23 | AN14: 23 | AO14: 35 | AP14: 103 | AQ14: 35 | AR14: 31 | AS14: 30 | AT14: 35 | AU14: 131 | AV14: 26 | AW14: 38 | AX14: 38 | AY14: 49 | AZ14: 151 | BA14: 43 | BB14: 43 | BC14: 44 | BD14: 54 | BE14: 184 | BF14: 25 | BG14: 33 | BH14: 42 | BI14: 52 | BJ14: 152 | BK14: 22 | BL14: 16 | BM14: 11 | BN14: 29 | BO14: 78 | BP14: 40 | BQ14: 40 | BR14: 40 | BS14: 40 | BT14: =SUM(BP14,BQ14,BR14,BS14) -> 160 | BU14: 40 | BV14: 40 | BW14: 40 | BX14: 40 | BY14: =SUM(BU14,BV14,BW14,BX14) -> 160 | BZ14: 160 | CA14: 160 | CB14: 160
A15: i-line units sold, # of units | E15: 20 | F15: 15 | G15: 13 | H15: 3 | I15: 2 | J15: 5 | K15: 3 | L15: 14 | M15: 6 | N15: 5 | O15: 4 | P15: 3 | Q15: 18 | R15: 4 | S15: 7 | T15: 5 | U15: 4 | V15: 20 | W15: 3 | X15: 7 | Y15: 9 | Z15: 7 | AA15: 26 | AB15: 5 | AC15: 8 | AD15: 5 | AE15: 8 | AF15: 26 | AG15: 9 | AH15: 6 | AI15: 6 | AJ15: 13 | AK15: 34 | AL15: 11 | AM15: 7 | AN15: 10 | AO15: 6 | AP15: 34 | AQ15: 6 | AR15: 9 | AS15: 7 | AT15: 11 | AU15: 33 | AV15: 9 | AW15: 12 | AX15: 10 | AY15: 14 | AZ15: 45 | BA15: 8 | BB15: 13 | BC15: 16 | BD15: 18 | BE15: 55 | BF15: 10 | BG15: 16 | BH15: 18 | BI15: 21 | BJ15: 65 | BK15: 13 | BL15: 14 | BM15: 10 | BN15: 17 | BO15: 54 | BP15: 8 | BQ15: 8 | BR15: 8 | BS15: 8 | BT15: =SUM(BP15,BQ15,BR15,BS15) -> 32 | BU15: 8 | BV15: 8 | BW15: 8 | BX15: 8 | BY15: =SUM(BU15,BV15,BW15,BX15) -> 32 | BZ15: 32 | CA15: 32 | CB15: 32
A16: Total net lithography systems sold, # of units | C16: 70 | D16: 197 | E16: =SUM(E11:E15) -> 222 | F16: =SUM(F11:F15) -> 170 | G16: =SUM(G11:G15) -> 157 | H16: =SUM(H11:H15) -> 40 | I16: =SUM(I11:I15) -> 31 | J16: =SUM(J11:J15) -> 30 | K16: =SUM(K11:K15) -> 35 | L16: =SUM(L11:L15) -> 136 | ... CB16: =SUM(CB11:CB15) -> 369
A17: Metrology & Inspection units sold, # of units | Q17: 45 | V17: 55 | AA17: 95 | AF17: 114 | AK17: 115 | AP17: 137 | AU17: 196 | AZ17: 216 | BA17: 37 | BB17: 37 | BC17: 37 | BD17: =BE17-SUM(BA17,BB17,BC17) -> 40 | BE17: 151 | BF17: 40 | BG17: 40 | BH17: 40 | BI17: =BJ17-SUM(BF17,BG17,BH17) -> 45 | BJ17: 165 | BK17: 45 | BL17: 45 | BM17: 45 | BN17: =BO17-SUM(BK17,BL17,BM17) -> 45 | BO17: 180 | BP17: 50 | BQ17: 50 | BR17: 50 | BS17: 50 | BT17: =IF(OR(ISBLANK(BP17),ISBLANK(BQ17),ISBLANK(BR17),ISBLANK(BS17)),"n/a",SUM(BP17,BQ17,BR17,BS17)) -> 200 | BU17: 50 | BV17: 50 | BW17: 50 | BX17: 50 | BY17: =IF(OR(ISBLANK(BU17),ISBLANK(BV17),ISBLANK(BW17),ISBLANK(BX17)),"n/a",SUM(BU17,BV17,BW17,BX17)) -> 200 | BZ17: 200 | CA17: 200 | CB17: 200
A18: Total net system sold, # of units | Q18: =Q16+Q17 -> 214 | V18: =V16+V17 -> 212 | AA18: =AA16+AA17 -> 293 | AF18: =AF16+AF17 -> 338 | AK18: =AK16+AK17 -> 344 | AP18: =AP16+AP17 -> 395 | AU18: =AU16+AU17 -> 505 | AZ18: =AZ16+AZ17 -> 561 | BA18: =BA16+BA17 -> 137 | BB18: =BB16+BB17 -> 150 | BC18: =BC16+BC17 -> 149 | BD18: =BD16+BD17 -> 164 | BE18: =BE16+BE17 -> 600 | BF18: =BF16+BF17 -> 110 | BG18: =BG16+BG17 -> 140 | ... CB18: =CB16+CB17 -> 569
A20: EUV unit price, 000 EUR/unit | E20: =IFERROR(+E33*1000/E11,"n/a") -> 39766.667 | F20: =IFERROR(+F33*1000/F11,"n/a") -> 43700 | G20: =IFERROR(+G33*1000/G11,"n/a") -> 60100 | H20: =IFERROR(+H33*1000/H11,"n/a") -> 61800 | I20: =IFERROR(+I33*1000/I11,"n/a") -> 62150 | J20: =IFERROR(+J33*1000/J11,"n/a") -> 61915 | K20: =IFERROR(+K33*1000/K11,"n/a") -> 65118 | L20: =IFERROR(+L33*1000/L11,"n/a") -> 59969 | ... BO20: =IFERROR(+BO33*1000/BO11,"n/a") -> 242739.92 | BP20: =BK20*(1+BP21) -> 252577.6 | BQ20: =BL20*(1+BQ21) -> 293032.15 | BR20: =BM20*(1+BR21) -> 281392.53 | BS20: =BN20*(1+BS21) -> 312027.43 | BT20: =IFERROR(+BT33*1000/BT11,"n/a") -> 285611.18 | BU20: =BP20*(1+BU21) -> 290464.24 | BV20: =BQ20*(1+BV21) -> 322335.36 | BW20: =BR20*(1+BW21) -> 309531.79 | BX20: =BS20*(1+BX21) -> 343230.17 | BY20: =IFERROR(+BY33*1000/BY11,"n/a") -> 317104 | BZ20: =BY20*(1+BZ21) -> 380524.8 | CA20: =BZ20*(1+CA21) -> 399551.04 | CB20: =CA20*(1+CB21) -> 419528.6
A21: Y/Y EUV unit price growth, % | F21: =F20/E20-1 -> 0.09891031 | G21: =G20/F20-1 -> 0.37528604 | L21: =L20/G20-1 -> -0.0021797005 | N21: =N20/I20-1 -> 0.095253419 | Q21: =Q20/L20-1 -> 0.17515716 | S21: =S20/N20-1 -> -0.25641252 | V21: =V20/Q20-1 -> 0.15256907 | X21: =X20/S20-1 -> 1.1876087 | Y21: =Y20/T20-1 -> 0.084658504 | Z21: =Z20/U20-1 -> -0.31068892 | AA21: =AA20/V20-1 -> 0.23282688 | AC21: =AC20/X20-1 -> -0.13858412 | AD21: =AD20/Y20-1 -> 0.089407779 | AE21: =AE20/Z20-1 -> 0.19051 | AF21: =AF20/AA20-1 -> 0.043077621 | AG21: =AG20/AB20-1 -> -0.20425051 | AH21: =AH20/AC20-1 -> 0.1365145 | AI21: =AI20/AD20-1 -> 0.021946966 | AJ21: =AJ20/AE20-1 -> -0.024705585 | ... BO21: =BO20/BJ20-1 -> 0.28350474 | BP21: 0.1 | BQ21: 0.2 | BR21: 0.2 | BS21: 0.2 | BT21: =BT20/BO20-1 -> 0.17661399 | BU21: 0.15 | BV21: 0.1 | BW21: 0.1 | BX21: 0.1 | BY21: =BY20/BT20-1 -> 0.11026467 | BZ21: 0.2 | CA21: 0.05 | CB21: 0.05
A22: ArFi unit price, 000 EUR/unit | E22: =IFERROR(+E34*1000/E12,"n/a") -> 35139.822 | F22: =IFERROR(+F34*1000/F12,"n/a") -> 37711.403 | G22: =IFERROR(+G34*1000/G12,"n/a") -> 40528.818 | H22: =IFERROR(+H34*1000/H12,"n/a") -> 41200 | I22: =IFERROR(+I34*1000/I12,"n/a") -> 47130.417 | J22: =IFERROR(+J34*1000/J12,"n/a") -> 48987.692 | K22: =IFERROR(+K34*1000/K12,"n/a") -> 45039.95 | L22: =IFERROR(+L34*1000/L12,"n/a") -> 45759.447 | ... BO22: =IFERROR(+BO34*1000/BO12,"n/a") -> 78032.298 | BP22: =BK22*(1+BP23) -> 87139.272 | BQ22: =BL22*(1+BQ23) -> 89266.821 | BR22: =BM22*(1+BR23) -> 87399.274 | BS22: =BN22*(1+BS23) -> 94287.568 | BT22: =IFERROR(+BT34*1000/BT12,"n/a") -> 89497.012 | BU22: =BP22*(1+BU23) -> 78425.345 | BV22: =BQ22*(1+BV23) -> 80340.139 | BW22: =BR22*(1+BW23) -> 94391.216 | BX22: =BS22*(1+BX23) -> 101830.57 | BY22: =IFERROR(+BY34*1000/BY12,"n/a") -> 88816.502 | BZ22: =BY22*(1+BZ23) -> 96272.405 | CA22: =BZ22*(1+CA23) -> 104354.21 | CB22: =CA22*(1+CB23) -> 113114.46
A23: Y/Y ArFi unit price growth, % | F23: =F22/E22-1 -> 0.07318139 | G23: =G22/F22-1 -> 0.074709907 | L23: =L22/G22-1 -> 0.1290595 | M23: =M22/H22-1 -> 0.091805614 | N23: =N22/I22-1 -> 0.00086778615 | O23: =O22/J22-1 -> -0.032987429 | P23: =P22/K22-1 -> 0.28017258 | Q23: =Q22/L22-1 -> 0.056286893 | R23: =R22/M22-1 -> 0.0066783621 | S23: =S22/N22-1 -> 0.073024976 | ... BO23: =BO22/BJ22-1 -> 0.041291652 | BP23: 0.15 | BQ23: 0.15 | BR23: 0.15 | BS23: 0.15 | BT23: =BT22/BO22-1 -> 0.14692268 | BU23: -0.1 | BV23: -0.1 | BW23: 0.08 | BX23: 0.08 | BY23: =BY22/BT22-1 -> -0.0076037159 | BZ23: 0.083947268 | CA23: 0.083947268 | CB23: 0.083947268
A24: ArF unit price, 000 EUR/unit | E24: =IFERROR(+E35*1000/E13,"n/a") -> 20809.909 | F24: =IFERROR(+F35*1000/F13,"n/a") -> 20357 | G24: =IFERROR(+G35*1000/G13,"n/a") -> 19009.5 | H24: =IFERROR(+H35*1000/H13,"n/a") -> n/a | I24: =IFERROR(+I35*1000/I13,"n/a") -> 6215 | J24: =IFERROR(+J35*1000/J13,"n/a") -> n/a | K24: =IFERROR(+K35*1000/K13,"n/a") -> 10853 | L24: =IFERROR(+L35*1000/L13,"n/a") -> 10870.333 | ... BO24: =IFERROR(+BO35*1000/BO13,"n/a") -> 30592.875 | BP24: =BK24*(1+BP25) -> 42096.267 | BQ24: =BL24*(1+BQ25) -> 32177.575 | BR24: =BM24*(1+BR25) -> 31934.35 | BS24: =BN24*(1+BS25) -> 34886.4 | BT24: =IFERROR(+BT35*1000/BT13,"n/a") -> 35273.648 | BU24: =BP24*(1+BU25) -> 42306.748 | BV24: =BQ24*(1+BV25) -> 32338.463 | BW24: =BR24*(1+BW25) -> 32094.022 | BX24: =BS24*(1+BX25) -> 35060.832 | BY24: =IFERROR(+BY35*1000/BY13,"n/a") -> 35450.016 | BZ24: =BY24*(1+BZ25) -> 35661.364 | CA24: =BZ24*(1+CA25) -> 35873.973 | CB24: =CA24*(1+CB25) -> 36087.848
A25: Y/Y ArF unit price growth, % | F25: =F24/E24-1 -> -0.021764107 | G25: =G24/F24-1 -> -0.066193447 | L25: =L24/G24-1 -> -0.42816311 | N25: =N24/I24-1 -> -0.087288817 | P25: =P24/K24-1 -> -0.18833502 | Q25: =Q24/L24-1 -> 0.099036113 | R25: =R24/M24-1 -> 0.14961893 | S25: =S24/N24-1 -> 2.3461437 | T25: =T24/O24-1 -> 0.71940258 | U25: =U24/P24-1 -> 1.9267794 | V25: =V24/Q24-1 -> 0.63082904 | W25: =W24/R24-1 -> -0.29297511 | ... BO25: =BO24/BJ24-1 -> 0.10614734 | BP25: 0.1 | BQ25: 0.15 | BR25: 0.15 | BS25: 0.15 | BT25: =BT24/BO24-1 -> 0.15300206 | BU25: 0.005 | BV25: 0.005 | BW25: 0.005 | BX25: 0.005 | BY25: =BY24/BT24-1 -> 0.005 | BZ25: 0.005961866 | CA25: 0.005961866 | CB25: 0.005961866
A26: KrF unit price, 000 EUR/unit | E26: =IFERROR(+E36*1000/E14,"n/a") -> 10650.253 | F26: =IFERROR(+F36*1000/F14,"n/a") -> 11644.154 | G26: =IFERROR(+G36*1000/G14,"n/a") -> 11250.828 | H26: =IFERROR(+H36*1000/H14,"n/a") -> 10300 | I26: =IFERROR(+I36*1000/I14,"n/a") -> 12430 | J26: =IFERROR(+J36*1000/J14,"n/a") -> 10614 | K26: =IFERROR(+K36*1000/K14,"n/a") -> 9767.7 | L26: =IFERROR(+L36*1000/L14,"n/a") -> 10037.789 | ... BO26: =IFERROR(+BO36*1000/BO14,"n/a") -> 13547.154 | BP26: =BK26*(1+BP27) -> 14351 | BQ26: =BL26*(1+BQ27) -> 16088.788 | BR26: =BM26*(1+BR27) -> 17418.736 | BS26: =BN26*(1+BS27) -> 15037.241 | BT26: =IFERROR(+BT36*1000/BT14,"n/a") -> 15723.941 | BU26: =BP26*(1+BU27) -> 12915.9 | BV26: =BQ26*(1+BV27) -> 14479.909 | BW26: =BR26*(1+BW27) -> 16547.8 | BX26: =BS26*(1+BX27) -> 14285.379 | BY26: =IFERROR(+BY36*1000/BY14,"n/a") -> 14557.247 | BZ26: =BY26*(1+BZ27) -> 15744.006 | CA26: =BZ26*(1+CA27) -> 17027.515 | CB26: =CA26*(1+CB27) -> 18415.659
A27: Y/Y KrF unit price growth, % | F27: =F26/E26-1 -> 0.093321819 | G27: =G26/F26-1 -> -0.033778815 | L27: =L26/G26-1 -> -0.10781772 | M27: =M26/H26-1 -> -0.092354369 | N27: =N26/I26-1 -> -0.21767613 | O27: =O26/J26-1 -> 0.033740814 | P27: =P26/K26-1 -> 0.037127471 | Q27: =Q26/L26-1 -> 0.0066553618 | R27: =R26/M26-1 -> 0.072977671 | S27: =S26/N26-1 -> -0.10537131 | ... BO27: =BO26/BJ26-1 -> 0.034133881 | BP27: 0.1 | BQ27: 0.15 | BR27: 0.15 | BS27: 0.15 | BT27: =BT26/BO26-1 -> 0.16068227 | BU27: -0.1 | BV27: -0.1 | BW27: -0.05 | BX27: -0.05 | BY27: =BY26/BT26-1 -> -0.074198599 | BZ27: 0.081523618 | CA27: 0.081523618 | CB27: 0.081523618
A28: i-line unit price, 000 EUR/unit | E28: =IFERROR(+E37*1000/E15,"n/a") -> 3000.5 | F28: =IFERROR(+F37*1000/F15,"n/a") -> 3535.9333 | G28: =IFERROR(+G37*1000/G15,"n/a") -> 4172.1538 | H28: =IFERROR(+H37*1000/H15,"n/a") -> 3433.3333 | I28: =IFERROR(+I37*1000/I15,"n/a") -> 6215 | J28: =IFERROR(+J37*1000/J15,"n/a") -> 3538 | K28: =IFERROR(+K37*1000/K15,"n/a") -> 3617.6667 | L28: =IFERROR(+L37*1000/L15,"n/a") -> 3655.7143 | ... BO28: =IFERROR(+BO37*1000/BO15,"n/a") -> 4532.2778 | BP28: =BK28*(1+BP29) -> 5078.0462 | BQ28: =BL28*(1+BQ29) -> 4596.7964 | BR28: =BM28*(1+BR29) -> 6386.87 | BS28: =BN28*(1+BS29) -> 5130.3529 | BT28: =IFERROR(+BT37*1000/BT15,"n/a") -> 5298.0164 | BU28: =BP28*(1+BU29) -> 5839.7531 | BV28: =BQ28*(1+BV29) -> 5286.3159 | BW28: =BR28*(1+BW29) -> 7344.9005 | BX28: =BS28*(1+BX29) -> 5899.9059 | BY28: =IFERROR(+BY37*1000/BY15,"n/a") -> 6092.7188 | BZ28: =BY28*(1+BZ29) -> 7006.6267 | CA28: =BZ28*(1+CA29) -> 8057.6207 | CB28: =CA28*(1+CB29) -> 9266.2638
A29: Y/Y i-line unit price growth, % | F29: =F28/E28-1 -> 0.17844804 | G29: =G28/F28-1 -> 0.17993001 | L29: =L28/G28-1 -> -0.12378248 | M29: =M28/H28-1 -> 0.21019417 | N29: =N28/I28-1 -> -0.26983105 | O29: =O28/J28-1 -> 0.37832109 | P29: =P28/K28-1 -> 0.62332995 | Q29: =Q28/L28-1 -> 0.10931353 | R29: =R28/M28-1 -> 0.03465704 | S29: =S28/N28-1 -> -0.20329912 | ... BO29: =BO28/BJ28-1 -> -0.20206377 | BP29: 0.15 | BQ29: 0.15 | BR29: 0.15 | BS29: 0.15 | BT29: =BT28/BO28-1 -> 0.16895227 | BU29: 0.15 | BV29: 0.15 | BW29: 0.15 | BX29: 0.15 | BY29: =BY28/BT28-1 -> 0.15 | BZ29: 0.15 | CA29: 0.15 | CB29: 0.15
A30: Metrology & Inspection unit price, 000 EUR/unit | V30: =IFERROR(+V38/V17*1000,"n/a") -> 1832.7273 | AA30: =IFERROR(+AA38/AA17*1000,"n/a") -> 2910.5263 | AF30: =IFERROR(+AF38/AF17*1000,"n/a") -> 2974.5614 | AK30: =IFERROR(+AK38/AK17*1000,"n/a") -> 2386.087 | AP30: =IFERROR(+AP38/AP17*1000,"n/a") -> 2555.4745 | AU30: =IFERROR(+AU38/AU17*1000,"n/a") -> 2620.9184 | AZ30: =IFERROR(+AZ38/AZ17*1000,"n/a") -> 3053.7037 | BA30: =BA38/BA17*1000 -> 4331.1892 | BB30: =BB38/BB17*1000 -> 3030.3243 | BC30: =BC38/BC17*1000 -> 2869.2973 | BD30: =BD38/BD17*1000 -> 4261.875 | BE30: =IFERROR(+BE38/BE17*1000,"n/a") -> 3550.3311 | BF30: =BF38/BF17*1000 -> 2974.425 | BG30: =BG38/BG17*1000 -> 1190.225 | BH30: =BH38/BH17*1000 -> 2963 | BI30: =BI38/BI17*1000 -> 6325.2444 | BJ30: =IFERROR(+BJ38/BJ17*1000,"n/a") -> 3912.1212 | BK30: =BK38/BK17*1000 -> 3826.9333 | BL30: =BL38/BL17*1000 -> 2487.1556 | BM30: =BM38/BM17*1000 -> 4936.7111 | BN30: =BN38/BN17*1000 -> 6741.3333 | BO30: =IFERROR(+BO38/BO17*1000,"n/a") -> 4498.0333 | BP30: =BK30*(1+BP31) -> 4209.6267 | BQ30: =BL30*(1+BQ31) -> 2611.5133 | BR30: =BM30*(1+BR31) -> 5183.5467 | BS30: =BN30*(1+BS31) -> 7078.4 | BT30: =IFERROR(+BT38/BT17*1000,"n/a") -> 4770.7717 | BU30: =BP30*(1+BU31) -> 4420.108 | BV30: =BQ30*(1+BV31) -> 2742.089 | BW30: =BR30*(1+BW31) -> 5442.724 | BX30: =BS30*(1+BX31) -> 7432.32 | BY30: =IFERROR(+BY38/BY17*1000,"n/a") -> 5009.3103 | BZ30: =BY30*(1+BZ31) -> 5259.7758 | CA30: =BZ30*(1+CA31) -> 5522.7646 | CB30: =CA30*(1+CB31) -> 5798.9028
A31: Metrology & Inspection unit price growth, % | AA31: =AA30/V30-1 -> 0.5880848 | AF31: =AF30/AA30-1 -> 0.022001206 | AK31: =AK30/AF30-1 -> -0.1978357 | AP31: =AP30/AK30-1 -> 0.070989658 | AU31: =AU30/AP30-1 -> 0.025609301 | AZ31: =AZ30/AU30-1 -> 0.16512736 | BE31: =BE30/AZ30-1 -> 0.16263118 | BF31: =BF30/BA30-1 -> -0.31325443 | BG31: =BG30/BB30-1 -> -0.60722851 | BH31: =BH30/BC30-1 -> 0.032657021 | BI31: =BI30/BD30-1 -> 0.48414593 | BJ31: =BJ30/BE30-1 -> 0.1019032 | BK31: =BK30/BF30-1 -> 0.28661282 | BL31: =BL30/BG30-1 -> 1.0896516 | ... BO31: =BO30/BJ30-1 -> 0.1497684 | BP31: 0.1 | BQ31: 0.05 | BR31: 0.05 | BS31: 0.05 | BT31: =BT30/BO30-1 -> 0.060635018 | BU31: 0.05 | BV31: 0.05 | BW31: 0.05 | BX31: 0.05 | BY31: =BY30/BT30-1 -> 0.05 | BZ31: 0.05 | CA31: 0.05 | CB31: 0.05
A33: EUV sales, mm | E33: 119.3 | F33: 43.7 | G33: 60.1 | H33: =H53*H$39 -> 61.8 | I33: =I53*I$39 -> 62.15 | J33: =J53*J$39 -> 123.83 | K33: =K53*K$39 -> 65.118 | L33: 299.845 | M33: =M53*M$39 -> 0 | N33: =N53*N$39 -> 68.07 | O33: =O53*O$39 -> 0 | P33: =P53*P$39 -> 0 | Q33: 70.473 | R33: =R53*R$39 -> 0 | S33: =S53*S$39 -> 101.232 | T33: =T53*T$39 -> 88.039 | U33: =U53*U$39 -> 141.801 | V33: 324.9 | W33: =W53*W$39 -> 0 | X33: =X53*X$39 -> 221.456 | Y33: =Y53*Y$39 -> 381.969 | Z33: =Z53*Z$39 -> 488.725 | AA33: 1101.5 | AB33: =AB53*AB$39 -> 116.739 | AC33: =AC53*AC$39 -> 667.68 | AD33: =AD53*AD$39 -> 520.15 | AE33: =AE53*AE$39 -> 581.832 | AF33: 1880.1 | AG33: =AG53*AG$39 -> 371.58 | AH33: =AH53*AH$39 -> 758.828 | AI33: =AI53*AI$39 -> 744.192 | AJ33: =AJ53*AJ$39 -> 907.932 | AK33: 2799.7 | AL33: =AL53*AL$39 -> 348.48 | AM33: =AM53*AM$39 -> 951.054 | AN33: =AN53*AN$39 -> 2043.096 | AO33: =AO53*AO$39 -> 1151.424 | AP33: 4463.8 | AQ33: =AQ53*AQ$39 -> 1126.368 | AR33: =AR53*AR$39 -> 1327.32 | AS33: =AS53*AS$39 -> 2219.994 | AT33: =AT53*AT$39 -> 1593.118 | AU33: 6284 | AV33: =AV53*AV$39 -> 594.672 | AW33: =AW53*AW$39 -> 1987.44 | AX33: =AX53*AX$39 -> 2169.897 | AY33: =AY53*AY$39 -> 2326.471 | AZ33: 7045.3 | BA33: =BA53*BA$39 -> 2884.572 | BB33: =BB53*BB$39 -> 2074.257 | BC33: =BC53*BC$39 -> 1857.87 | BD33: =BD53*BD$39 -> 2273 | BE33: 9124 | BF33: =BF53*BF$39 -> 1824.314 | BG33: =BG53*BG$39 -> 1475.879 | BH33: =BH53*BH$39 -> 2074.1 | BI33: =BI53*BI$39 -> 2988.678 | BJ33: =7856.4+465 -> 8321.4 | BK33: =BK53*BK$39 -> 3214.624 | BL33: =BL53*BL$39 -> 2686.128 | BM33: =BM53*BM$39 -> 2110.444 | BN33: =BN53*BN$39 -> 3640.32 | BO33: =SUM(BK33,BL33,BM33,BN33) -> 11651.516 | BP33: =BP11*BP20/1000 -> 3283.5088 | BQ33: =BQ11*BQ20/1000 -> 3809.4179 | BR33: =BR11*BR20/1000 -> 4220.888 | BS33: =BS11*BS20/1000 -> 4680.4114 | BT33: =SUM(BP33,BQ33,BR33,BS33) -> 15994.226 | BU33: =BU11*BU20/1000 -> 3776.0351 | BV33: =BV11*BV20/1000 -> 4190.3597 | BW33: =BW11*BW20/1000 -> 4642.9768 | BX33: =BX11*BX20/1000 -> 5148.4526 | BY33: =SUM(BU33,BV33,BW33,BX33) -> 17757.824 | BZ33: =BZ11*BZ20/1000 -> 24734.112 | CA33: =CA11*CA20/1000 -> 25970.818 | CB33: =CB11*CB20/1000 -> 27269.359
A34: ArFi sales, mm | E34: 3549.122 | F34: 2715.221 | G34: 3120.719 | H34: =H54*H$39 -> 782.8 | I34: =I54*I$39 -> 1131.13 | J34: =J54*J$39 -> 636.84 | K34: =K54*K$39 -> 900.799 | L34: 3477.718 | M34: =M54*M$39 -> 1034.595 | N34: =N54*N$39 -> 896.255 | O34: =O54*O$39 -> 663.204 | P34: =P54*P$39 -> 634.248 | Q34: 3238.452 | R34: =R54*R$39 -> 679.242 | S34: =S54*S$39 -> 961.704 | T34: =T54*T$39 -> 968.429 | U34: =U54*U$39 -> 915.261 | V34: 3518.7 | W34: =W54*W$39 -> 899.692 | X34: =X54*X$39 -> 885.824 | Y34: =Y54*Y$39 -> 1145.907 | Z34: =Z54*Z$39 -> 1094.744 | AA34: 4017.4 | AB34: =AB54*AB$39 -> 1200.744 | AC34: =AC54*AC$39 -> 1022.385 | AD34: =AD54*AD$39 -> 1206.748 | AE34: =AE54*AE$39 -> 1381.851 | AF34: 4806.9 | AG34: =AG54*AG$39 -> 1013.4 | AH34: =AH54*AH$39 -> 758.828 | AI34: =AI54*AI$39 -> 1186.056 | AJ34: =AJ54*AJ$39 -> 1753.248 | AK34: 4707.7 | AL34: =AL54*AL$39 -> 823.68 | AM34: =AM54*AM$39 -> 999.826 | AN34: =AN54*AN$39 -> 650.076 | AO34: =AO54*AO$39 -> 1439.28 | AP34: 3917 | AQ34: =AQ54*AQ$39 -> 1470.536 | AR34: =AR54*AR$39 -> 1002.864 | AS34: =AS54*AS$39 -> 1315.552 | AT34: =AT54*AT$39 -> 1212.155 | AU34: 4959.6 | AV34: =AV54*AV$39 -> 1074.984 | AW34: =AW54*AW$39 -> 1366.365 | AX34: =AX54*AX$39 -> 1318.957 | AY34: =AY54*AY$39 -> 1471.849 | AZ34: 5236.5 | BA34: =BA54*BA$39 -> 1602.54 | BB34: =BB54*BB$39 -> 2746.989 | BC34: =BC54*BC$39 -> 2547.936 | BD34: =BD54*BD$39 -> 2159.35 | BE34: 9017.4 | BF34: =BF54*BF$39 -> 1546.701 | BG34: =BG54*BG$39 -> 2380.45 | BH34: =BH54*BH$39 -> 2844.48 | BI34: =BI54*BI$39 -> 2917.519 | BJ34: 9667 | BK34: =BK54*BK$39 -> 1894.332 | BL34: =BL54*BL$39 -> 2406.323 | BM34: =BM54*BM$39 -> 2887.976 | BN34: =BN54*BN$39 -> 3033.6 | BO34: =SUM(BK34,BL34,BM34,BN34) -> 10222.231 | BP34: =BP12*BP22/1000 -> 1742.7854 | BQ34: =BQ12*BQ22/1000 -> 1785.3364 | BR34: =BR12*BR22/1000 -> 1835.3847 | BS34: =BS12*BS22/1000 -> 1885.7514 | BT34: =SUM(BP34,BQ34,BR34,BS34) -> 7249.258 | BU34: =BU12*BU22/1000 -> 1568.5069 | BV34: =BV12*BV22/1000 -> 1606.8028 | BW34: =BW12*BW22/1000 -> 1982.2155 | BX34: =BX12*BX22/1000 -> 2036.6115 | BY34: =SUM(BU34,BV34,BW34,BX34) -> 7194.1367 | BZ34: =BZ12*BZ22/1000 -> 7701.7924 | CA34: =CA12*CA22/1000 -> 8348.3368 | CB34: =CB12*CB22/1000 -> 9049.1569
A35: ArF sales, mm | E35: 228.909 | F35: 81.428 | G35: 38.019 | H35: =H55*H$39 -> 0 | I35: =I55*I$39 -> 12.43 | J35: =J55*J$39 -> 0 | K35: =K55*K$39 -> 10.853 | L35: 32.611 | M35: =M55*M$39 -> 37.395 | N35: =N55*N$39 -> 11.345 | O35: =O55*O$39 -> 29.259 | P35: =P55*P$39 -> 26.427 | Q35: 107.522 | R35: =R55*R$39 -> 42.99 | S35: =S55*S$39 -> 37.962 | T35: =T55*T$39 -> 25.154 | U35: =U55*U$39 -> 25.782 | V35: 116.9 | W35: =W55*W$39 -> 60.79 | X35: =X55*X$39 -> 41.523 | Y35: =Y55*Y$39 -> 36.378 | Z35: =Z55*Z$39 -> 78.196 | AA35: 210.3 | AB35: =AB55*AB$39 -> 66.708 | AC35: =AC55*AC$39 -> 83.46 | AD35: =AD55*AD$39 -> 62.418 | AE35: =AE55*AE$39 -> 72.729 | AF35: 274.3 | AG35: =AG55*AG$39 -> 67.56 | AH35: =AH55*AH$39 -> 37.016 | AI35: =AI55*AI$39 -> 162.792 | AJ35: =AJ55*AJ$39 -> 125.232 | AK35: 401.2 | AL35: =AL55*AL$39 -> 110.88 | AM35: =AM55*AM$39 -> 121.93 | AN35: =AN55*AN$39 -> 30.956 | AO35: =AO55*AO$39 -> 127.936 | AP35: 427 | AQ35: =AQ55*AQ$39 -> 62.576 | AR35: =AR55*AR$39 -> 147.48 | AS35: =AS55*AS$39 -> 123.333 | AT35: =AT55*AT$39 -> 103.899 | AU35: 431.9 | AV35: =AV55*AV$39 -> 137.232 | AW35: =AW55*AW$39 -> 165.62 | AX35: =AX55*AX$39 -> 127.641 | AY35: =AY55*AY$39 -> 189.916 | AZ35: 623.7 | BA35: =BA55*BA$39 -> 160.254 | BB35: =BB55*BB$39 -> 112.122 | BC35: =BC55*BC$39 -> 212.328 | BD35: =BD55*BD$39 -> 284.125 | BE35: 780.2 | BF35: =BF55*BF$39 -> 118.977 | BG35: =BG55*BG$39 -> 333.263 | BH35: =BH55*BH$39 -> 177.78 | BI35: =BI55*BI$39 -> 142.318 | BJ35: 774.4 | BK35: =BK55*BK$39 -> 114.808 | BL35: =BL55*BL$39 -> 111.922 | BM35: =BM55*BM$39 -> 111.076 | BN35: =BN55*BN$39 -> 151.68 | BO35: =SUM(BK35,BL35,BM35,BN35) -> 489.486 | BP35: =BP13*BP24/1000 -> 336.77013 | BQ35: =BQ13*BQ24/1000 -> 257.4206 | BR35: =BR13*BR24/1000 -> 255.4748 | BS35: =BS13*BS24/1000 -> 279.0912 | BT35: =SUM(BP35,BQ35,BR35,BS35) -> 1128.7567 | BU35: =BU13*BU24/1000 -> 338.45398 | BV35: =BV13*BV24/1000 -> 258.7077 | BW35: =BW13*BW24/1000 -> 256.75217 | BX35: =BX13*BX24/1000 -> 280.48666 | BY35: =SUM(BU35,BV35,BW35,BX35) -> 1134.4005 | BZ35: =BZ13*BZ24/1000 -> 1141.1637 | CA35: =CA13*CA24/1000 -> 1147.9671 | CB35: =CB13*CB24/1000 -> 1154.8112
A36: KrF sales, mm | E36: 926.572 | F36: 908.244 | G36: 720.053 | H36: =H56*H$39 -> 175.1 | I36: =I56*I$39 -> 24.86 | J36: =J56*J$39 -> 106.14 | K36: =K56*K$39 -> 97.677 | L36: 381.436 | M36: =M56*M$39 -> 149.58 | N36: =N56*N$39 -> 136.14 | O36: =O56*O$39 -> 263.331 | P36: =P56*P$39 -> 202.607 | Q36: 747.74 | R36: =R56*R$39 -> 120.372 | S36: =S56*S$39 -> 139.194 | T36: =T56*T$39 -> 150.924 | U36: =U56*U$39 -> 128.91 | V36: 532.7 | W36: =W56*W$39 -> 182.37 | X36: =X56*X$39 -> 124.569 | Y36: =Y56*Y$39 -> 181.89 | Z36: =Z56*Z$39 -> 195.49 | AA36: 683.3 | AB36: =AB56*AB$39 -> 233.478 | AC36: =AC56*AC$39 -> 208.65 | AD36: =AD56*AD$39 -> 187.254 | AE36: =AE56*AE$39 -> 242.43 | AF36: 860.1 | AG36: =AG56*AG$39 -> 152.01 | AH36: =AH56*AH$39 -> 203.588 | AI36: =AI56*AI$39 -> 139.536 | AJ36: =AJ56*AJ$39 -> 187.848 | AK36: 679.7 | AL36: =AL56*AL$39 -> 205.92 | AM36: =AM56*AM$39 -> 243.86 | AN36: =AN56*AN$39 -> 247.648 | AO36: =AO56*AO$39 -> 351.824 | AP36: 1012.3 | AQ36: =AQ56*AQ$39 -> 344.168 | AR36: =AR56*AR$39 -> 324.456 | AS36: =AS56*AS$39 -> 287.777 | AT36: =AT56*AT$39 -> 346.33 | AU36: 1321.3 | AV36: =AV56*AV$39 -> 274.464 | AW36: =AW56*AW$39 -> 414.05 | AX36: =AX56*AX$39 -> 425.47 | AY36: =AY56*AY$39 -> 569.748 | AZ36: 1653.7 | BA36: =BA56*BA$39 -> 480.762 | BB36: =BB56*BB$39 -> 504.549 | BC36: =BC56*BC$39 -> 530.82 | BD36: =BD56*BD$39 -> 681.9 | BE36: 2202.5 | BF36: =BF56*BF$39 -> 317.272 | BG36: =BG56*BG$39 -> 428.481 | BH36: =BH56*BH$39 -> 592.6 | BI36: =BI56*BI$39 -> 640.431 | BJ36: 1991.2 | BK36: =BK56*BK$39 -> 287.02 | BL36: =BL56*BL$39 -> 223.844 | BM36: =BM56*BM$39 -> 166.614 | BN36: =BN56*BN$39 -> 379.2 | BO36: =SUM(BK36,BL36,BM36,BN36) -> 1056.678 | BP36: =BP14*BP26/1000 -> 574.04 | BQ36: =BQ14*BQ26/1000 -> 643.5515 | BR36: =BR14*BR26/1000 -> 696.74945 | BS36: =BS14*BS26/1000 -> 601.48966 | BT36: =SUM(BP36,BQ36,BR36,BS36) -> 2515.8306 | BU36: =BU14*BU26/1000 -> 516.636 | BV36: =BV14*BV26/1000 -> 579.19635 | BW36: =BW14*BW26/1000 -> 661.91198 | BX36: =BX14*BX26/1000 -> 571.41517 | BY36: =SUM(BU36,BV36,BW36,BX36) -> 2329.1595 | BZ36: =BZ14*BZ26/1000 -> 2519.041 | CA36: =CA14*CA26/1000 -> 2724.4024 | CB36: =CB14*CB26/1000 -> 2946.5055
A37: i-line sales, mm | E37: 60.01 | F37: 53.039 | G37: 54.238 | H37: =H57*H$39 -> 10.3 | I37: =I57*I$39 -> 12.43 | J37: =J57*J$39 -> 17.69 | K37: =K57*K$39 -> 10.853 | L37: 51.18 | M37: =M57*M$39 -> 24.93 | N37: =N57*N$39 -> 22.69 | O37: =O57*O$39 -> 19.506 | P37: =P57*P$39 -> 17.618 | Q37: 72.996 | R37: =R57*R$39 -> 17.196 | S37: =S57*S$39 -> 25.308 | T37: =T57*T$39 -> 25.154 | U37: =U57*U$39 -> 12.891 | V37: 78 | W37: =W57*W$39 -> 12.158 | X37: =X57*X$39 -> 27.682 | Y37: =Y57*Y$39 -> 18.189 | Z37: =Z57*Z$39 -> 19.549 | AA37: 84.7 | AB37: =AB57*AB$39 -> 16.677 | AC37: =AC57*AC$39 -> 20.865 | AD37: =AD57*AD$39 -> 20.806 | AE37: =AE57*AE$39 -> 24.243 | AF37: 98.6 | AG37: =AG57*AG$39 -> 33.78 | AH37: =AH57*AH$39 -> 18.508 | AI37: =AI57*AI$39 -> 23.256 | AJ37: =AJ57*AJ$39 -> 62.616 | AK37: 133.5 | AL37: =AL57*AL$39 -> 47.52 | AM37: =AM57*AM$39 -> 24.386 | AN37: =AN57*AN$39 -> 30.956 | AO37: =AO57*AO$39 -> 31.984 | AP37: 146.4 | AQ37: =AQ57*AQ$39 -> 31.288 | AR37: =AR57*AR$39 -> 29.496 | AS37: =AS57*AS$39 -> 41.111 | AT37: =AT57*AT$39 -> 34.633 | AU37: 142.3 | AV37: =AV57*AV$39 -> 45.744 | AW37: =AW57*AW$39 -> 41.405 | AX37: =AX57*AX$39 -> 42.547 | AY37: =AY57*AY$39 -> 47.479 | AZ37: 211.5 | BA37: =BA57*BA$39 -> 53.418 | BB37: =BB57*BB$39 -> 56.061 | BC37: =BC57*BC$39 -> 53.082 | BD37: =BD57*BD$39 -> 113.65 | BE37: 278.4 | BF37: =BF57*BF$39 -> 39.659 | BG37: =BG57*BG$39 -> 95.218 | BH37: =BH57*BH$39 -> 118.52 | BI37: =BI57*BI$39 -> 142.318 | BJ37: 369.2 | BK37: =BK57*BK$39 -> 57.404 | BL37: =BL57*BL$39 -> 55.961 | BM37: =BM57*BM$39 -> 55.538 | BN37: =BN57*BN$39 -> 75.84 | BO37: =SUM(BK37,BL37,BM37,BN37) -> 244.743 | BP37: =BP15*BP28/1000 -> 40.624369 | BQ37: =BQ15*BQ28/1000 -> 36.774371 | BR37: =BR15*BR28/1000 -> 51.09496 | BS37: =BS15*BS28/1000 -> 41.042824 | BT37: =SUM(BP37,BQ37,BR37,BS37) -> 169.53652 | BU37: =BU15*BU28/1000 -> 46.718025 | BV37: =BV15*BV28/1000 -> 42.290527 | BW37: =BW15*BW28/1000 -> 58.759204 | BX37: =BX15*BX28/1000 -> 47.199247 | BY37: =SUM(BU37,BV37,BW37,BX37) -> 194.967 | BZ37: =BZ15*BZ28/1000 -> 224.21205 | CA37: =CA15*CA28/1000 -> 257.84386 | CB37: =CB15*CB28/1000 -> 296.52044
A38: Metrology & Inspection sales, mm | U38: =U58*U$39 -> 0 | V38: 100.8 | W38: =W58*W$39 -> 60.79 | X38: =X58*X$39 -> 83.046 | Y38: =Y58*Y$39 -> 54.567 | Z38: =Z58*Z$39 -> 78.196 | AA38: 276.5 | AB38: =AB58*AB$39 -> 33.354 | AC38: =AC58*AC$39 -> 83.46 | AD38: =AD58*AD$39 -> 83.224 | AE38: =AE58*AE$39 -> 121.215 | AF38: 339.1 | AG38: =AG58*AG$39 -> 50.67 | AH38: =AH58*AH$39 -> 74.032 | AI38: =AI58*AI$39 -> 69.768 | AJ38: =AJ58*AJ$39 -> 93.924 | AK38: 274.4 | AL38: =AL58*AL$39 -> 47.52 | AM38: =AM58*AM$39 -> 97.544 | AN38: =AN58*AN$39 -> 92.868 | AO38: =AO58*AO$39 -> 95.952 | AP38: 350.1 | AQ38: =AQ58*AQ$39 -> 93.864 | AR38: =AR58*AR$39 -> 117.984 | AS38: =AS58*AS$39 -> 123.333 | AT38: =AT58*AT$39 -> 173.165 | AU38: 513.7 | AV38: =AV58*AV$39 -> 160.104 | AW38: =AW58*AW$39 -> 165.62 | AX38: =AX58*AX$39 -> 170.188 | AY38: =AY58*AY$39 -> 142.437 | AZ38: 659.6 | BA38: =BA58*BA$39 -> 160.254 | BB38: =BB58*BB$39 -> 112.122 | BC38: =BC58*BC$39 -> 106.164 | BD38: =BD58*BD$39 -> 170.475 | BE38: 536.1 | BF38: =BF58*BF$39 -> 118.977 | BG38: =BG58*BG$39 -> 47.609 | BH38: =BH58*BH$39 -> 118.52 | BI38: =BI58*BI$39 -> 284.636 | BJ38: 645.5 | BK38: =BK58*BK$39 -> 172.212 | BL38: =BL58*BL$39 -> 111.922 | BM38: =BM58*BM$39 -> 222.152 | BN38: =BN58*BN$39 -> 303.36 | BO38: =SUM(BK38,BL38,BM38,BN38) -> 809.646 | BP38: =BP17*BP30/1000 -> 210.48133 | BQ38: =BQ17*BQ30/1000 -> 130.57567 | BR38: =BR17*BR30/1000 -> 259.17733 | BS38: =BS17*BS30/1000 -> 353.92 | BT38: =SUM(BP38,BQ38,BR38,BS38) -> 954.15433 | BU38: =BU17*BU30/1000 -> 221.0054 | BV38: =BV17*BV30/1000 -> 137.10445 | BW38: =BW17*BW30/1000 -> 272.1362 | BX38: =BX17*BX30/1000 -> 371.616 | BY38: =SUM(BU38,BV38,BW38,BX38) -> 1001.862 | BZ38: =BZ17*BZ30/1000 -> 1051.9552 | CA38: =CA17*CA30/1000 -> 1104.5529 | CB38: =CB17*CB30/1000 -> 1159.7806
A39: Total net system sales, mm | C39: =C298 -> 1174.858 | D39: =D298 -> 3894.742 | E39: =E33+E34+E35+E36+E37+E38 -> 4883.913 | F39: =F33+F34+F35+F36+F37+F38 -> 3801.632 | G39: =G33+G34+G35+G36+G37+G38 -> 3993.129 | H39: =H298 -> 1030 | I39: =I298 -> 1243 | J39: =J298 -> 884.5 | K39: =K298 -> 1085.3 | L39: =L33+L34+L35+L36+L37+L38 -> 4242.79 | M39: =M298 -> 1246.5 | N39: =N298 -> 1134.5 | O39: =O298 -> 975.3 | P39: =P298 -> 880.9 | Q39: =Q33+Q34+Q35+Q36+Q37+Q38 -> 4237.183 | R39: =R298 -> 859.8 | S39: =S298 -> 1265.4 | T39: =T298 -> 1257.7 | U39: =U298 -> 1289.1 | V39: =V33+V34+V35+V36+V37+V38 -> 4672 | W39: =W298 -> 1215.8 | X39: =X298 -> 1384.1 | Y39: =Y298 -> 1818.9 | Z39: =Z298 -> 1954.9 | AA39: =AA33+AA34+AA35+AA36+AA37+AA38 -> 6373.7 | AB39: =AB298 -> 1667.7 | AC39: =AC298 -> 2086.5 | AD39: =AD298 -> 2080.6 | AE39: =AE298 -> 2424.3 | AF39: =AF33+AF34+AF35+AF36+AF37+AF38 -> 8259.1 | AG39: =AG298 -> 1689 | AH39: =AH298 -> 1850.8 | AI39: =AI298 -> 2325.6 | AJ39: =AJ298 -> 3130.8 | AK39: =AK33+AK34+AK35+AK36+AK37+AK38 -> 8996.2 | AL39: =AL298 -> 1584 | AM39: =AM298 -> 2438.6 | AN39: =AN298 -> 3095.6 | AO39: =AO298 -> 3198.4 | AP39: =AP33+AP34+AP35+AP36+AP37+AP38 -> 10316.6 | AQ39: =AQ298 -> 3128.8 | AR39: =AR298 -> 2949.6 | AS39: =AS298 -> 4111.1 | AT39: =AT298 -> 3463.3 | AU39: =AU33+AU34+AU35+AU36+AU37+AU38 -> 13652.8 | AV39: =AV298 -> 2287.2 | AW39: =AW298 -> 4140.5 | AX39: =AX298 -> 4254.7 | AY39: =AY298 -> 4747.9 | AZ39: =AZ33+AZ34+AZ35+AZ36+AZ37+AZ38 -> 15430.3 | BA39: =BA298 -> 5341.8 | BB39: =BB298 -> 5606.1 | BC39: =BC298 -> 5308.2 | BD39: =BD298 -> 5682.5 | BE39: =BE33+BE34+BE35+BE36+BE37+BE38 -> 21938.6 | BF39: =BF298 -> 3965.9 | BG39: =BG298 -> 4760.9 | BH39: =BH298 -> 5926 | BI39: =BI298 -> 7115.9 | BJ39: =BJ33+BJ34+BJ35+BJ36+BJ37+BJ38 -> 21768.7 | BK39: =BK298 -> 5740.4 | BL39: =BL298 -> 5596.1 | BM39: =BM298 -> 5553.8 | BN39: =BN298 -> 7584 | BO39: =BO33+BO34+BO35+BO36+BO37+BO38 -> 24474.3 | BP39: =BP33+BP34+BP35+BP36+BP37+BP38 -> 6188.2101 | BQ39: =BQ33+BQ34+BQ35+BQ36+BQ37+BQ38 -> 6663.0764 | BR39: =BR33+BR34+BR35+BR36+BR37+BR38 -> 7318.7693 | BS39: =BS33+BS34+BS35+BS36+BS37+BS38 -> 7841.7065 | BT39: =BT33+BT34+BT35+BT36+BT37+BT38 -> 28011.762 | BU39: =BU33+BU34+BU35+BU36+BU37+BU38 -> 6467.3554 | BV39: =BV33+BV34+BV35+BV36+BV37+BV38 -> 6814.4615 | ... CB39: =CB33+CB34+CB35+CB36+CB37+CB38 -> 41876.133
A40: Net service and field option sales, mm | C40: =C299 -> 421.205 | D40: =D299 -> 613.196 | E40: =E299 -> 767.122 | F40: =F299 -> 929.923 | G40: =G299 -> 1252.197 | H40: =H299 -> 366.5 | I40: =I299 -> 400.6 | J40: =J299 -> 437.7 | ... BO40: =BO299 -> 8193 | BP40: =BK40*(1+BP50) -> 2401.32 | BQ40: =BL40*(1+BQ50) -> 2200.38 | BR40: =BM40*(1+BR50) -> 2060.31 | BS40: =BN40*(1+BS50) -> 2240.805 | BT40: =SUM(BP40,BQ40,BR40,BS40) -> 8902.815 | BU40: =BP40*(1+BU50) -> 2425.3332 | BV40: =BQ40*(1+BV50) -> 2222.3838 | BW40: =BR40*(1+BW50) -> 2080.9131 | BX40: =BS40*(1+BX50) -> 2263.213 | BY40: =SUM(BU40,BV40,BW40,BX40) -> 8991.8432 | BZ40: =BY40*(1+BZ50) -> 9171.68 | CA40: =BZ40*(1+CA50) -> 9355.1136 | CB40: =CA40*(1+CB50) -> 9542.2159
A41: Total revenue, mm | C41: =C39+C40 -> 1596.063 | D41: =D39+D40 -> 4507.938 | E41: =E39+E40 -> 5651.035 | F41: =F39+F40 -> 4731.555 | G41: =G39+G40 -> 5245.326 | H41: =H39+H40 -> 1396.5 | I41: =I39+I40 -> 1643.6 | J41: =J39+J40 -> 1322.2 | ... CB41: =CB39+CB40 -> 51418.349
A43: Y/Y EUV sales growth, % | F43: =IFERROR(F33/E33-1,"n/a") -> -0.63369656 | G43: =IFERROR(G33/F33-1,"n/a") -> 0.37528604 | L43: =IFERROR(L33/G33-1,"n/a") -> 3.9891015 | M43: =IFERROR(M33/H33-1,"n/a") -> -1 | N43: =IFERROR(N33/I33-1,"n/a") -> 0.095253419 | O43: =IFERROR(O33/J33-1,"n/a") -> -1 | P43: =IFERROR(P33/K33-1,"n/a") -> -1 | Q43: =IFERROR(Q33/L33-1,"n/a") -> -0.76496857 | R43: =IFERROR(R33/M33-1,"n/a") -> n/a | S43: =IFERROR(S33/N33-1,"n/a") -> 0.48717497 | ... BY43: =IFERROR(BY33/BT33-1,"n/a") -> 0.11026467 | BZ43: =IFERROR(BZ33/BY33-1,"n/a") -> 0.39285714 | CA43: =IFERROR(CA33/BZ33-1,"n/a") -> 0.05 | CB43: =IFERROR(CB33/CA33-1,"n/a") -> 0.05
A44: Y/Y ArFi sales growth, % | F44: =IFERROR(F34/E34-1,"n/a") -> -0.2349598 | G44: =IFERROR(G34/F34-1,"n/a") -> 0.14934254 | L44: =IFERROR(L34/G34-1,"n/a") -> 0.11439639 | M44: =IFERROR(M34/H34-1,"n/a") -> 0.32165943 | N44: =IFERROR(N34/I34-1,"n/a") -> -0.20764634 | O44: =IFERROR(O34/J34-1,"n/a") -> 0.041398153 | P44: =IFERROR(P34/K34-1,"n/a") -> -0.29590508 | Q44: =IFERROR(Q34/L34-1,"n/a") -> -0.068799713 | R44: =IFERROR(R34/M34-1,"n/a") -> -0.34347063 | S44: =IFERROR(S34/N34-1,"n/a") -> 0.073024976 | ... BY44: =IFERROR(BY34/BT34-1,"n/a") -> -0.0076037159 | BZ44: =IFERROR(BZ34/BY34-1,"n/a") -> 0.070565203 | CA44: =IFERROR(CA34/BZ34-1,"n/a") -> 0.083947268 | CB44: =IFERROR(CB34/CA34-1,"n/a") -> 0.083947268
A45: Y/Y ArF sales growth, % | F45: =IFERROR(F35/E35-1,"n/a") -> -0.64427786 | G45: =IFERROR(G35/F35-1,"n/a") -> -0.53309672 | L45: =IFERROR(L35/G35-1,"n/a") -> -0.14224467 | M45: =IFERROR(M35/H35-1,"n/a") -> n/a | N45: =IFERROR(N35/I35-1,"n/a") -> -0.087288817 | O45: =IFERROR(O35/J35-1,"n/a") -> n/a | P45: =IFERROR(P35/K35-1,"n/a") -> 1.4349949 | Q45: =IFERROR(Q35/L35-1,"n/a") -> 2.2971083 | R45: =IFERROR(R35/M35-1,"n/a") -> 0.14961893 | S45: =IFERROR(S35/N35-1,"n/a") -> 2.3461437 | ... BY45: =IFERROR(BY35/BT35-1,"n/a") -> 0.005 | BZ45: =IFERROR(BZ35/BY35-1,"n/a") -> 0.005961866 | CA45: =IFERROR(CA35/BZ35-1,"n/a") -> 0.005961866 | CB45: =IFERROR(CB35/CA35-1,"n/a") -> 0.005961866
A46: Y/Y KrF sales growth, % | F46: =IFERROR(F36/E36-1,"n/a") -> -0.019780438 | G46: =IFERROR(G36/F36-1,"n/a") -> -0.20720313 | L46: =IFERROR(L36/G36-1,"n/a") -> -0.47026677 | M46: =IFERROR(M36/H36-1,"n/a") -> -0.14574529 | N46: =IFERROR(N36/I36-1,"n/a") -> 4.4762671 | O46: =IFERROR(O36/J36-1,"n/a") -> 1.480978 | P46: =IFERROR(P36/K36-1,"n/a") -> 1.0742549 | Q46: =IFERROR(Q36/L36-1,"n/a") -> 0.96032886 | R46: =IFERROR(R36/M36-1,"n/a") -> -0.19526675 | S46: =IFERROR(S36/N36-1,"n/a") -> 0.02243279 | ... BY46: =IFERROR(BY36/BT36-1,"n/a") -> -0.074198599 | BZ46: =IFERROR(BZ36/BY36-1,"n/a") -> 0.081523618 | CA46: =IFERROR(CA36/BZ36-1,"n/a") -> 0.081523618 | CB46: =IFERROR(CB36/CA36-1,"n/a") -> 0.081523618
A47: Y/Y i-line sales growth, % | F47: =IFERROR(F37/E37-1,"n/a") -> -0.11616397 | G47: =IFERROR(G37/F37-1,"n/a") -> 0.022606007 | L47: =IFERROR(L37/G37-1,"n/a") -> -0.056381135 | M47: =IFERROR(M37/H37-1,"n/a") -> 1.4203883 | N47: =IFERROR(N37/I37-1,"n/a") -> 0.82542237 | O47: =IFERROR(O37/J37-1,"n/a") -> 0.10265687 | P47: =IFERROR(P37/K37-1,"n/a") -> 0.62332995 | Q47: =IFERROR(Q37/L37-1,"n/a") -> 0.42626026 | R47: =IFERROR(R37/M37-1,"n/a") -> -0.31022864 | S47: =IFERROR(S37/N37-1,"n/a") -> 0.11538123 | ... BY47: =IFERROR(BY37/BT37-1,"n/a") -> 0.15 | BZ47: =IFERROR(BZ37/BY37-1,"n/a") -> 0.15 | CA47: =IFERROR(CA37/BZ37-1,"n/a") -> 0.15 | CB47: =IFERROR(CB37/CA37-1,"n/a") -> 0.15
A48: Y/Y Metrology & Inspection sales growth, % | Z48: =IFERROR(Z38/U38-1,"n/a") -> n/a | AA48: =IFERROR(AA38/V38-1,"n/a") -> 1.7430556 | AB48: =IFERROR(AB38/W38-1,"n/a") -> -0.45132423 | AC48: =IFERROR(AC38/X38-1,"n/a") -> 0.0049851889 | AD48: =IFERROR(AD38/Y38-1,"n/a") -> 0.52517089 | AE48: =IFERROR(AE38/Z38-1,"n/a") -> 0.55014323 | AF48: =IFERROR(AF38/AA38-1,"n/a") -> 0.22640145 | AG48: =IFERROR(AG38/AB38-1,"n/a") -> 0.51915812 | ... BY48: =IFERROR(BY38/BT38-1,"n/a") -> 0.05 | BZ48: =IFERROR(BZ38/BY38-1,"n/a") -> 0.05 | CA48: =IFERROR(CA38/BZ38-1,"n/a") -> 0.05 | CB48: =IFERROR(CB38/CA38-1,"n/a") -> 0.05
A49: Y/Y Total net system sales growth, % | D49: =IFERROR(D39/C39-1,"n/a") -> 2.3150747 | E49: =IFERROR(E39/D39-1,"n/a") -> 0.253976 | F49: =IFERROR(F39/E39-1,"n/a") -> -0.2216012 | G49: =IFERROR(G39/F39-1,"n/a") -> 0.050372314 | L49: =IFERROR(L39/G39-1,"n/a") -> 0.062522648 | M49: =IFERROR(M39/H39-1,"n/a") -> 0.21019417 | N49: =IFERROR(N39/I39-1,"n/a") -> -0.087288817 | O49: =IFERROR(O39/J39-1,"n/a") -> 0.10265687 | P49: =IFERROR(P39/K39-1,"n/a") -> -0.18833502 | Q49: =IFERROR(Q39/L39-1,"n/a") -> -0.0013215361 | R49: =IFERROR(R39/M39-1,"n/a") -> -0.31022864 | S49: =IFERROR(S39/N39-1,"n/a") -> 0.11538123 | ... BY49: =IFERROR(BY39/BT39-1,"n/a") -> 0.05713984 | BZ49: =IFERROR(BZ39/BY39-1,"n/a") -> 0.26205035 | CA49: =IFERROR(CA39/BZ39-1,"n/a") -> 0.058376011 | CB49: =IFERROR(CB39/CA39-1,"n/a") -> 0.058710042
A50: Y/Y Net service and field option sales growth, % | D50: =IFERROR(D40/C40-1,"n/a") -> 0.45581368 | E50: =IFERROR(E40/D40-1,"n/a") -> 0.25102251 | F50: =IFERROR(F40/E40-1,"n/a") -> 0.21222309 | G50: =IFERROR(G40/F40-1,"n/a") -> 0.34655988 | L50: =IFERROR(L40/G40-1,"n/a") -> 0.28852489 | M50: =IFERROR(M40/H40-1,"n/a") -> 0.10068213 | N50: =IFERROR(N40/I40-1,"n/a") -> 0.29705442 | O50: =IFERROR(O40/J40-1,"n/a") -> 0.31117204 | P50: =IFERROR(P40/K40-1,"n/a") -> 0.35380475 | Q50: =IFERROR(Q40/L40-1,"n/a") -> 0.27065914 | R50: =IFERROR(R40/M40-1,"n/a") -> 0.17352504 | S50: =IFERROR(S40/N40-1,"n/a") -> -0.087374904 | ... BO50: =IFERROR(BO40/BJ40-1,"n/a") -> 0.26158726 | BP50: 0.2 | BQ50: 0.05 | BR50: 0.05 | BS50: 0.05 | BT50: =IFERROR(BT40/BO40-1,"n/a") -> 0.086636763 | BU50: 0.01 | BV50: 0.01 | BW50: 0.01 | BX50: 0.01 | BY50: =IFERROR(BY40/BT40-1,"n/a") -> 0.01 | BZ50: 0.02 | CA50: 0.02 | CB50: 0.02
A51: Y/Y Total revenue growth, % | D51: =D41/C41-1 -> 1.8244111 | E51: =E41/D41-1 -> 0.25357425 | F51: =F41/E41-1 -> -0.16271002 | G51: =G41/F41-1 -> 0.10858396 | L51: =L41/G41-1 -> 0.11647532 | M51: =M41/H41-1 -> 0.18145363 | N51: =N41/I41-1 -> 0.0063884157 | O51: =O41/J41-1 -> 0.17168356 | P51: =P41/K41-1 -> -0.040026774 | Q51: =Q41/L41-1 -> 0.07361298 | R51: =R41/M41-1 -> -0.19195103 | S51: =S41/N41-1 -> 0.051689741 | ... BY51: =BY41/BT41-1 -> 0.045770964 | BZ51: =BZ41/BY41-1 -> 0.20567101 | CA51: =CA41/BZ41-1 -> 0.050813858 | CB51: =CB41/CA41-1 -> 0.051305748
A53: EUV sales as % of total net system sales, % | E53: =E33/E$39 -> 0.024427135 | F53: =F33/F$39 -> 0.011495063 | G53: =G33/G$39 -> 0.015050854 | H53: 0.06 | I53: 0.05 | J53: 0.14 | K53: 0.06 | L53: =L33/L$39 -> 0.070671657 | M53: 0 | N53: 0.06 | O53: 0 | P53: 0 | Q53: =Q33/Q$39 -> 0.016632041 | R53: 0 | S53: 0.08 | T53: 0.07 | U53: 0.11 | V53: =V33/V$39 -> 0.069541952 | W53: 0 | X53: 0.16 | Y53: 0.21 | Z53: 0.25 | AA53: =AA33/AA$39 -> 0.17281956 | AB53: 0.07 | AC53: 0.32 | AD53: 0.25 | AE53: 0.24 | AF53: =AF33/AF$39 -> 0.22763982 | AG53: 0.22 | AH53: 0.41 | AI53: 0.32 | AJ53: 0.29 | AK53: =AK33/AK39 -> 0.31120918 | AL53: 0.22 | AM53: 0.39 | AN53: 0.66 | AO53: 0.36 | AP53: =AP33/AP39 -> 0.43268131 | AQ53: 0.36 | AR53: 0.45 | AS53: 0.54 | AT53: 0.46 | AU53: =AU33/AU39 -> 0.46027189 | AV53: 0.26 | AW53: 0.48 | AX53: 0.51 | AY53: 0.49 | AZ53: =AZ33/AZ39 -> 0.45658866 | BA53: 0.54 | BB53: 0.37 | BC53: 0.35 | BD53: 0.4 | BE53: =BE33/BE39 -> 0.41588798 | BF53: 0.46 | BG53: 0.31 | BH53: 0.35 | BI53: 0.42 | BJ53: =BJ33/BJ39 -> 0.38226444 | BK53: 0.56 | BL53: 0.48 | BM53: 0.38 | BN53: 0.48 | BO53: =BO33/BO39 -> 0.47607147 | BP53: =+BP33/BP$39 -> 0.5306072 | BQ53: =+BQ33/BQ$39 -> 0.57172057 | BR53: =+BR33/BR$39 -> 0.57672101 | BS53: =+BS33/BS$39 -> 0.59686134 | BT53: =+BT33/BT$39 -> 0.5709825 | BU53: =+BU33/BU$39 -> 0.58386077 | BV53: =+BV33/BV$39 -> 0.61492162 | BW53: =+BW33/BW$39 -> 0.58960293 | ... BY53: =+BY33/BY$39 -> 0.59967629 | BZ53: =+BZ33/BZ39 -> 0.66183049 | CA53: =+CA33/CA39 -> 0.65659275 | CB53: =+CB33/CB39 -> 0.65119094
A54: ArFi sales as % of total net system sales, % | E54: =E34/E$39 -> 0.7266964 | F54: =F34/F$39 -> 0.7142251 | G54: =G34/G$39 -> 0.78152221 | H54: 0.76 | I54: 0.91 | J54: 0.72 | K54: 0.83 | L54: =L34/L$39 -> 0.81967715 | M54: 0.83 | N54: 0.79 | O54: 0.68 | P54: 0.72 | Q54: =Q34/Q$39 -> 0.76429364 | R54: 0.79 | S54: 0.76 | T54: 0.77 | U54: 0.71 | V54: =V34/V$39 -> 0.7531464 | W54: 0.74 | X54: 0.64 | Y54: 0.63 | Z54: 0.56 | AA54: =AA34/AA$39 -> 0.63030893 | AB54: 0.72 | AC54: 0.49 | AD54: 0.58 | AE54: 0.57 | AF54: =AF34/AF$39 -> 0.58201257 | AG54: 0.6 | AH54: 0.41 | AI54: 0.51 | AJ54: 0.56 | AK54: =AK34/AK39 -> 0.52329873 | AL54: 0.52 | AM54: 0.41 | AN54: 0.21 | AO54: 0.45 | AP54: =AP34/AP39 -> 0.37967935 | AQ54: 0.47 | AR54: 0.34 | AS54: 0.32 | AT54: 0.35 | AU54: =AU34/AU39 -> 0.36326614 | AV54: 0.47 | AW54: 0.33 | AX54: 0.31 | AY54: 0.31 | AZ54: =AZ34/AZ39 -> 0.33936476 | BA54: 0.3 | BB54: 0.49 | BC54: 0.48 | BD54: 0.38 | BE54: =BE34/BE39 -> 0.41102896 | BF54: 0.39 | BG54: 0.5 | BH54: 0.48 | BI54: 0.41 | BJ54: =BJ34/BJ39 -> 0.44407797 | BK54: 0.33 | BL54: 0.43 | BM54: 0.52 | BN54: 0.4 | BO54: =BO34/BO39 -> 0.41767205 | BP54: =+BP34/BP$39 -> 0.28162997 | BQ54: =+BQ34/BQ$39 -> 0.26794476 | BR54: =+BR34/BR$39 -> 0.25077778 | BS54: =+BS34/BS$39 -> 0.24047717 | BT54: =+BT34/BT$39 -> 0.25879336 | BU54: =+BU34/BU$39 -> 0.24252678 | BV54: =+BV34/BV$39 -> 0.23579307 | BW54: =+BW34/BW$39 -> 0.25171784 | ... BY54: =+BY34/BY$39 -> 0.24294379 | BZ54: =+BZ34/BZ39 -> 0.20608304 | CA54: =+CA34/CA39 -> 0.21106218 | CB54: =+CB34/CB39 -> 0.21609342
A55: ArF sales as % of total net system sales, % | E55: =E35/E$39 -> 0.04687 | F55: =F35/F$39 -> 0.021419222 | G55: =G35/G$39 -> 0.0095211049 | H55: 0 | I55: 0.01 | J55: 0 | K55: 0.01 | L55: =L35/L$39 -> 0.0076862159 | M55: 0.03 | N55: 0.01 | O55: 0.03 | P55: 0.03 | Q55: =Q35/Q$39 -> 0.025375822 | R55: 0.05 | S55: 0.03 | T55: 0.02 | U55: 0.02 | V55: =V35/V$39 -> 0.025021404 | W55: 0.05 | X55: 0.03 | Y55: 0.02 | Z55: 0.04 | AA55: =AA35/AA$39 -> 0.032994964 | AB55: 0.04 | AC55: 0.04 | AD55: 0.03 | AE55: 0.03 | AF55: =AF35/AF$39 -> 0.033211851 | AG55: 0.04 | AH55: 0.02 | AI55: 0.07 | AJ55: 0.04 | AK55: =AK35/AK39 -> 0.044596607 | AL55: 0.07 | AM55: 0.05 | AN55: 0.01 | AO55: 0.04 | AP55: =AP35/AP39 -> 0.041389605 | AQ55: 0.02 | AR55: 0.05 | AS55: 0.03 | AT55: 0.03 | AU55: =AU35/AU39 -> 0.031634537 | AV55: 0.06 | AW55: 0.04 | AX55: 0.03 | AY55: 0.04 | AZ55: =AZ35/AZ39 -> 0.040420471 | BA55: 0.03 | BB55: 0.02 | BC55: 0.04 | BD55: 0.05 | BE55: =BE35/BE39 -> 0.035562889 | BF55: 0.03 | BG55: 0.07 | BH55: 0.03 | BI55: 0.02 | BJ55: =BJ35/BJ39 -> 0.035574012 | BK55: 0.02 | BL55: 0.02 | BM55: 0.02 | BN55: 0.02 | BO55: =BO35/BO39 -> 0.02 | BP55: =+BP35/BP$39 -> 0.054421251 | BQ55: =+BQ35/BQ$39 -> 0.038633896 | BR55: =+BR35/BR$39 -> 0.034906798 | BS55: =+BS35/BS$39 -> 0.035590621 | BT55: =+BT35/BT$39 -> 0.040295813 | BU55: =+BU35/BU$39 -> 0.052332671 | BV55: =+BV35/BV$39 -> 0.037964512 | BW55: =+BW35/BW$39 -> 0.032604478 | ... BY55: =+BY35/BY$39 -> 0.038308359 | BZ55: =+BZ35/BZ39 -> 0.030535032 | CA55: =+CA35/CA39 -> 0.02902284 | CB55: =+CB35/CB39 -> 0.027576833
A56: KrF sales as % of total net system sales, % | E56: =E36/E$39 -> 0.18971919 | F56: =F36/F$39 -> 0.23890897 | G56: =G36/G$39 -> 0.180323 | H56: 0.17 | I56: 0.02 | J56: 0.12 | K56: 0.09 | L56: =L36/L$39 -> 0.089902163 | M56: 0.12 | N56: 0.12 | O56: 0.27 | P56: 0.23 | Q56: =Q36/Q$39 -> 0.17647102 | R56: 0.14 | S56: 0.11 | T56: 0.12 | U56: 0.1 | V56: =V36/V$39 -> 0.11401969 | W56: 0.15 | X56: 0.09 | Y56: 0.1 | Z56: 0.1 | AA56: =AA36/AA$39 -> 0.10720618 | AB56: 0.14 | AC56: 0.1 | AD56: 0.09 | AE56: 0.1 | AF56: =AF36/AF$39 -> 0.10413968 | AG56: 0.09 | AH56: 0.11 | AI56: 0.06 | AJ56: 0.06 | AK56: =AK36/AK39 -> 0.075554123 | AL56: 0.13 | AM56: 0.1 | AN56: 0.08 | AO56: 0.11 | AP56: =AP36/AP39 -> 0.098123413 | AQ56: 0.11 | AR56: 0.11 | AS56: 0.07 | AT56: 0.1 | AU56: =AU36/AU39 -> 0.096778683 | AV56: 0.12 | AW56: 0.1 | AX56: 0.1 | AY56: 0.12 | AZ56: =AZ36/AZ39 -> 0.10717225 | BA56: 0.09 | BB56: 0.09 | BC56: 0.1 | BD56: 0.12 | BE56: =BE36/BE39 -> 0.10039383 | BF56: 0.08 | BG56: 0.09 | BH56: 0.1 | BI56: 0.09 | BJ56: =BJ36/BJ39 -> 0.091470781 | BK56: 0.05 | BL56: 0.04 | BM56: 0.03 | BN56: 0.05 | BO56: =BO36/BO39 -> 0.043175004 | BP56: =+BP36/BP$39 -> 0.092763496 | BQ56: =+BQ36/BQ$39 -> 0.096584739 | BR56: =+BR36/BR$39 -> 0.095200358 | BS56: =+BS36/BS$39 -> 0.076703924 | BT56: =+BT36/BT$39 -> 0.089813364 | BU56: =+BU36/BU$39 -> 0.079883657 | BV56: =+BV36/BV$39 -> 0.084995175 | BW56: =+BW36/BW$39 -> 0.084054963 | ... BY56: =+BY36/BY$39 -> 0.078655004 | BZ56: =+BZ36/BZ39 -> 0.067404002 | CA56: =+CA36/CA39 -> 0.068878187 | CB56: =+CB36/CB39 -> 0.070362406
A57: i-line sales as % of total net system sales, % | E57: =E37/E$39 -> 0.012287279 | F57: =F37/F$39 -> 0.01395164 | G57: =G37/G$39 -> 0.013582832 | H57: 0.01 | I57: 0.01 | J57: 0.02 | K57: 0.01 | L57: =L37/L$39 -> 0.012062817 | M57: 0.02 | N57: 0.02 | O57: 0.02 | P57: 0.02 | Q57: =Q37/Q$39 -> 0.017227483 | R57: 0.02 | S57: 0.02 | T57: 0.02 | U57: 0.01 | V57: =V37/V$39 -> 0.016695205 | W57: 0.01 | X57: 0.02 | Y57: 0.01 | Z57: 0.01 | AA57: =AA37/AA$39 -> 0.013288984 | AB57: 0.01 | AC57: 0.01 | AD57: 0.01 | AE57: 0.01 | AF57: =AF37/AF$39 -> 0.011938347 | AG57: 0.02 | AH57: 0.01 | AI57: 0.01 | AJ57: 0.02 | AK57: =AK37/AK39 -> 0.014839599 | AL57: 0.03 | AM57: 0.01 | AN57: 0.01 | AO57: 0.01 | AP57: =AP37/AP39 -> 0.014190722 | AQ57: 0.01 | AR57: 0.01 | AS57: 0.01 | AT57: 0.01 | AU57: =AU37/AU39 -> 0.01042277 | AV57: 0.02 | AW57: 0.01 | AX57: 0.01 | AY57: 0.01 | AZ57: =AZ37/AZ39 -> 0.013706798 | BA57: 0.01 | BB57: 0.01 | BC57: 0.01 | BD57: 0.02 | BE57: =BE37/BE39 -> 0.012689962 | BF57: 0.01 | BG57: 0.02 | BH57: 0.02 | BI57: 0.02 | BJ57: =BJ37/BJ39 -> 0.016960131 | BK57: 0.01 | BL57: 0.01 | BM57: 0.01 | BN57: 0.01 | BO57: =BO37/BO39 -> 0.01 | BP57: =+BP37/BP$39 -> 0.0065648012 | BQ57: =+BQ37/BQ$39 -> 0.0055191279 | BR57: =+BR37/BR$39 -> 0.0069813596 | BS57: =+BS37/BS$39 -> 0.0052339148 | BT57: =+BT37/BT$39 -> 0.0060523334 | BU57: =+BU37/BU$39 -> 0.0072236674 | BV57: =+BV37/BV$39 -> 0.0062059969 | BW57: =+BW37/BW$39 -> 0.0074617213 | ... BY57: =+BY37/BY$39 -> 0.0065839761 | BZ57: =+BZ37/BZ39 -> 0.0059994219 | CA57: =+CA37/CA39 -> 0.006518794 | CB57: =+CB37/CB39 -> 0.0070808935
A58: Metrology & Inspection sales as % of total net system sales, % | E58: =E38/E$39 -> 0 | F58: =F38/F$39 -> 0 | G58: =G38/G$39 -> 0 | H58: 0 | I58: 0 | J58: 0 | K58: 0 | L58: =L38/L$39 -> 0 | M58: 0 | N58: 0 | O58: 0 | P58: 0 | Q58: =Q38/Q$39 -> 0 | R58: 0 | S58: 0 | T58: 0 | U58: 0 | V58: =V38/V$39 -> 0.021575342 | W58: 0.05 | X58: 0.06 | Y58: 0.03 | Z58: 0.04 | AA58: =AA38/AA$39 -> 0.043381395 | AB58: 0.02 | AC58: 0.04 | AD58: 0.04 | AE58: 0.05 | AF58: =AF38/AF$39 -> 0.041057742 | AG58: 0.03 | AH58: 0.04 | AI58: 0.03 | AJ58: 0.03 | AK58: =AK38/AK39 -> 0.030501767 | AL58: 0.03 | AM58: 0.04 | AN58: 0.03 | AO58: 0.03 | AP58: =AP38/AP39 -> 0.033935599 | AQ58: 0.03 | AR58: 0.04 | AS58: 0.03 | AT58: 0.05 | AU58: =AU38/AU39 -> 0.037625981 | AV58: 0.07 | AW58: 0.04 | AX58: 0.04 | AY58: 0.03 | AZ58: =AZ38/AZ39 -> 0.042747063 | BA58: 0.03 | BB58: 0.02 | BC58: 0.02 | BD58: 0.03 | BE58: =BE38/BE39 -> 0.024436382 | BF58: 0.03 | BG58: 0.01 | BH58: 0.02 | BI58: 0.04 | BJ58: =BJ38/BJ39 -> 0.029652666 | BK58: 0.03 | BL58: 0.02 | BM58: 0.04 | BN58: 0.04 | BO58: =BO38/BO39 -> 0.033081477 | BP58: =+BP38/BP$39 -> 0.034013282 | BQ58: =+BQ38/BQ$39 -> 0.019596904 | BR58: =+BR38/BR$39 -> 0.035412693 | BS58: =+BS38/BS$39 -> 0.045133033 | BT58: =+BT38/BT$39 -> 0.034062631 | BU58: =+BU38/BU$39 -> 0.034172453 | BV58: =+BV38/BV$39 -> 0.020119631 | BW58: =+BW38/BW$39 -> 0.034558067 | ... BY58: =+BY38/BY$39 -> 0.033832575 | BZ58: =+BZ38/BZ39 -> 0.028148008 | CA58: =+CA38/CA39 -> 0.027925244 | CB58: =+CB38/CB39 -> 0.027695503
A59: Total net system sales, % | E59: =SUM(E53:E58) -> 1 | F59: =SUM(F53:F58) -> 1 | G59: =SUM(G53:G58) -> 1 | H59: =SUM(H53:H58) -> 1 | I59: =SUM(I53:I58) -> 1 | J59: =SUM(J53:J58) -> 1 | K59: =SUM(K53:K58) -> 1 | L59: =SUM(L53:L58) -> 1 | ... CB59: =SUM(CB53:CB58) -> 1
A61: EUV sales, mm | E61: =E33 -> 119.3 | F61: =F33 -> 43.7 | G61: =G33 -> 60.1 | H61: =H33 -> 61.8 | I61: =I33 -> 62.15 | J61: =J33 -> 123.83 | K61: =K33 -> 65.118 | L61: =L33 -> 299.845 | ... CB61: =CB33 -> 27269.359
A62: Y/Y EUV sales growth, % | F62: =F61/E61-1 -> -0.63369656 | G62: =G61/F61-1 -> 0.37528604 | L62: =IFERROR(L61/G61-1,"N/A") -> 3.9891015 | M62: =IFERROR(M61/H61-1,"N/A") -> -1 | N62: =IFERROR(N61/I61-1,"N/A") -> 0.095253419 | O62: =IFERROR(O61/J61-1,"N/A") -> -1 | P62: =IFERROR(P61/K61-1,"N/A") -> -1 | Q62: =IFERROR(Q61/L61-1,"N/A") -> -0.76496857 | R62: =IFERROR(R61/M61-1,"N/A") -> N/A | S62: =IFERROR(S61/N61-1,"N/A") -> 0.48717497 | ... AF62: =IFERROR(AF61/AA61-1,"N/A") -> 0.70685429 | AG62: =AG61/AB61-1 -> 2.182998 | AH62: =AH61/AC61-1 -> 0.1365145 | AI62: =AI61/AD61-1 -> 0.43072575 | AJ62: =AJ61/AE61-1 -> 0.56047106 | AK62: =AK61/AF61-1 -> 0.48912292 | AL62: =AL61/AG61-1 -> -0.062166963 | AM62: =AM61/AH61-1 -> 0.25331959 | AN62: =AN61/AI61-1 -> 1.7453883 | ... BY62: =BY61/BT61-1 -> 0.11026467 | BZ62: =BZ61/BY61-1 -> 0.39285714 | CA62: =CA61/BZ61-1 -> 0.05 | CB62: =CB61/CA61-1 -> 0.05
A63: DUV sales, mm | E63: =E34+E35+E36+E37 -> 4764.613 | F63: =F34+F35+F36+F37 -> 3757.932 | G63: =G34+G35+G36+G37 -> 3933.029 | H63: =H34+H35+H36+H37 -> 968.2 | I63: =I34+I35+I36+I37 -> 1180.85 | J63: =J34+J35+J36+J37 -> 760.67 | K63: =K34+K35+K36+K37 -> 1020.182 | L63: =L34+L35+L36+L37 -> 3942.945 | ... CB63: =CB34+CB35+CB36+CB37 -> 13446.994
A64: Y/Y DUV sales growth, % | F64: =F63/E63-1 -> -0.21128285 | G64: =G63/F63-1 -> 0.046593978 | L64: =L63/G63-1 -> 0.002521212 | M64: =M63/H63-1 -> 0.28744061 | N64: =N63/I63-1 -> -0.096896304 | O64: =O63/J63-1 -> 0.28215915 | P64: =P63/K63-1 -> -0.13652662 | Q64: =Q63/L63-1 -> 0.056750728 | R64: =R63/M63-1 -> -0.31022864 | S64: =S63/N63-1 -> 0.09164971 | ... BY64: =BY63/BT63-1 -> -0.019046449 | BZ64: =BZ63/BY63-1 -> 0.067591279 | CA64: =CA63/BZ63-1 -> 0.077017515 | CB64: =CB63/CA63-1 -> 0.07760868
A66: Net deferred revenue from fast shipment, mm | AV66: 1400 | AW66: 300 | AX66: 200 | AY66: 1000 | AZ66: 2800
A67: Normalized revenue, mm | AV67: 4900 | AW67: 5700 | AX67: 6000 | AY67: 7400 | AZ67: 24000
A69: Operating Expense Forecasting
A70: Revenue, mm | C70: =C329 -> 1596.063 | D70: =D329 -> 4507.938 | E70: =E329 -> 5651.035 | F70: =F329 -> 4731.555 | G70: =G329 -> 5245.326 | H70: =H329 -> 1396.5 | I70: =I329 -> 1643.6 | J70: =J329 -> 1322.2 | ... BO70: =BO329 -> 32667.3 | BP70: =BP41 -> 8589.5301 | BQ70: =BQ41 -> 8863.4564 | BR70: =BR41 -> 9379.0793 | BS70: =BS41 -> 10082.511 | BT70: =BT41 -> 36914.577 | BU70: =BU41 -> 8892.6886 | BV70: =BV41 -> 9036.8453 | BW70: =BW41 -> 9955.665 | ... CB70: =CB41 -> 51418.349
A71: COGS, mm | C71: =C70-C72 -> 1137.671 | D71: =D70-D72 -> 2552.768 | E71: =E70-E72 -> 3201.645 | F71: =F70-F72 -> 2726.298 | G71: =G70-G72 -> 3068.064 | H71: =H70-H72 -> 787 | I71: =I70-I72 -> 891.7 | J71: =J70-J72 -> 744.1 | ... CB71: =CB70-CB72 -> 23433.696
A72: Gross profit, mm | C72: =C333 -> 458.392 | D72: =D333 -> 1955.17 | E72: =E333 -> 2449.39 | F72: =F333 -> 2005.257 | G72: =G333 -> 2177.262 | H72: =H333 -> 609.5 | I72: =I333 -> 751.9 | J72: =J333 -> 578.1 | ... BO72: =BO333 -> 17258 | BP72: =BP70*BP74 -> 4465.7679 | BQ72: =BQ70*BQ74 -> 4776.3165 | BR72: =BR70*BR74 -> 4860.9137 | BS72: =BS70*BS74 -> 5278.7248 | BT72: =BS72+BR72+BQ72+BP72 -> 19381.723 | BU72: =BU70*BU74 -> 4641.1679 | BV72: =BV70*BV74 -> 5095.6729 | BW72: =BW70*BW74 -> 5408.6336 | BX72: =BX70*BX74 -> 5633.3949 | BY72: =BX72+BW72+BV72+BU72 -> 20778.869 | BZ72: =BZ70*BZ74 -> 25145.568 | CA72: =CA70*CA74 -> 26521.13 | CB72: =CB70*CB74 -> 27984.653
A73: Y/Y Gross Profit growth, % | D73: =D72/C72-1 -> 3.2652795 | E73: =E72/D72-1 -> 0.25277597 | F73: =F72/E72-1 -> -0.18132392 | G73: =G72/F72-1 -> 0.085777035 | L73: =L72/G72-1 -> 0.19249498 | M73: =M72/H72-1 -> 0.27744053 | N73: =N72/I72-1 -> 0.0025269318 | O73: =O72/J72-1 -> 0.21691749 | P73: =P72/K72-1 -> 0.004414675 | Q73: =Q72/L72-1 -> 0.11530311 | R73: =R72/M72-1 -> -0.27035705 | S73: =S72/N72-1 -> -0.016449987 | ... BY73: =BY72/BT72-1 -> 0.072085771 | BZ73: =BZ72/BY72-1 -> 0.21015094 | CA73: =CA72/BZ72-1 -> 0.05470393 | CB73: =CB72/CA72-1 -> 0.055183287
A74: Gross Margin, % | C74: =C72/C70 -> 0.2872017 | D74: =D72/D70 -> 0.43371715 | E74: =E72/E70 -> 0.43344095 | F74: =F72/F70 -> 0.42380507 | G74: =G72/G70 -> 0.41508612 | H74: =H72/H70 -> 0.43644826 | I74: =I72/I70 -> 0.4574714 | J74: =J72/J70 -> 0.43722584 | ... BO74: =BO72/BO70 -> 0.52829588 | BP74: =BK74+BP76/10000 -> 0.51990829 | BQ74: =BL74+BQ76/10000 -> 0.53887741 | BR74: =BM74+BR76/10000 -> 0.51827195 | BS74: =BN74+BS76/10000 -> 0.52355257 | BT74: =BT72/BT70 -> 0.52504252 | BU74: =BP74+BU76/10000 -> 0.52190829 | BV74: =BQ74+BV76/10000 -> 0.56387741 | BW74: =BR74+BW76/10000 -> 0.54327195 | BX74: =BS74+BX76/10000 -> 0.52555257 | BY74: =BY72/BY70 -> 0.53825421 | BZ74: =BY74+BZ76/10000 -> 0.54025421 | CA74: =BZ74+CA76/10000 -> 0.54225421 | CB74: =CA74+CB76/10000 -> 0.54425421
A75: =A282 -> Consensus Estimates - Gross Margin, % | BP75: =BP282 -> N/A | BQ75: =BQ282 -> N/A | BR75: =BR282 -> N/A | BS75: =BS282 -> N/A | BT75: =BT282 -> N/A | BU75: =BU282 -> N/A | BV75: =BV282 -> N/A | BW75: =BW282 -> N/A | ... CB75: =CB282 -> N/A
A76: Y/Y Gross Margin improvement, bps | D76: =(D74-C74)*10000 -> 1465.1545 | E76: =(E74-D74)*10000 -> -2.7619144 | F76: =(F74-E74)*10000 -> -96.358833 | G76: =(G74-F74)*10000 -> -87.189538 | L76: =(L74-G74)*10000 -> 282.62789 | M76: =(M74-H74)*10000 -> 354.59125 | N76: =(N74-I74)*10000 -> -17.553048 | O76: =(O74-J74)*10000 -> 168.79509 | P76: =(P74-K74)*10000 -> 203.55311 | Q76: =(Q74-L74)*10000 -> 172.15956 | R76: =(R74-M74)*10000 -> -457.89777 | S76: =(S74-N74)*10000 -> -295.26171 | ... BO76: =(BO74-BJ74)*10000 -> 155.38873 | BP76: -200 | BQ76: 20 | BR76: 20 | BS76: 20 | BT76: =(BT74-BO74)*10000 -> -32.533554 | BU76: 20 | BV76: 250 | BW76: 250 | BX76: 20 | BY76: =(BY74-BT74)*10000 -> 132.11681 | BZ76: 20 | CA76: 20 | CB76: 20
A78: R&D, mm | C78: =C335 -> 466.761 | D78: =D335 -> 523.426 | E78: =E335 -> 590.27 | F78: =F335 -> 589.182 | G78: =G335 -> 882.029 | H78: =H335 -> 279.1 | I78: =I335 -> 266.9 | J78: =J335 -> 260.1 | ... BO78: =BO335 -> 4698.8 | BP78: =BP80*BP70 -> 1202.3955 | BQ78: =BQ80*BQ70 -> 954.44343 | BR78: =BR80*BR70 -> 1242.8403 | BS78: =BS80*BS70 -> 1289.469 | BT78: =BS78+BR78+BQ78+BP78 -> 4689.1482 | BU78: =BU80*BU70 -> 1227.0474 | BV78: =BV80*BV70 -> 575.49326 | BW78: =BW80*BW70 -> 1169.9098 | BX78: =BX80*BX70 -> 1349.4318 | BY78: =BX78+BW78+BV78+BU78 -> 4321.8824 | BZ78: =BZ80*BZ70 -> 5117.6804 | CA78: =CA80*CA70 -> 5279.9114 | CB78: =CB80*CB70 -> 5447.9645
A79: Y/Y R&D growth, % | D79: =D78/C78-1 -> 0.12140046 | E79: =E78/D78-1 -> 0.12770478 | F79: =F78/E78-1 -> -0.0018432243 | G79: =G78/F78-1 -> 0.49703996 | L79: =L78/G78-1 -> 0.21768672 | M79: =M78/H78-1 -> -0.06341813 | N79: =N78/I78-1 -> 0.0018733608 | O79: =O78/J78-1 -> 0.023836986 | P79: =P78/K78-1 -> 0.018656716 | Q79: =Q78/L78-1 -> -0.0055473053 | R79: =R78/M78-1 -> 0.050879878 | S79: =S78/N78-1 -> 0.010845176 | ... BY79: =BY78/BT78-1 -> -0.078322513 | BZ79: =BZ78/BY78-1 -> 0.18413227 | CA79: =CA78/BZ78-1 -> 0.031700107 | CB79: =CB78/CA78-1 -> 0.031828774
A80: R&D margin, % | C80: =C78/C70 -> 0.29244522 | D80: =D78/D70 -> 0.11611207 | E80: =E78/E70 -> 0.10445343 | F80: =F78/F70 -> 0.12452185 | G80: =G78/G70 -> 0.16815523 | H80: =H78/H70 -> 0.19985678 | I80: =I78/I70 -> 0.16238744 | J80: =J78/J70 -> 0.19671759 | ... BO80: =BO78/BO70 -> 0.14383803 | BP80: =BK80-BP81/10000 -> 0.13998385 | BQ80: =BL80-BQ81/10000 -> 0.10768298 | BR80: =BM80-BR81/10000 -> 0.13251197 | BS80: =BN80-BS81/10000 -> 0.12789165 | BT80: =BT78/BT70 -> 0.12702701 | BU80: =BP80-BU81/10000 -> 0.13798385 | BV80: =BQ80-BV81/10000 -> 0.063682983 | BW80: =BR80-BW81/10000 -> 0.11751197 | BX80: =BS80-BX81/10000 -> 0.12589165 | BY80: =BY78/BY70 -> 0.1119537 | BZ80: =BY80-BZ81/10000 -> 0.1099537 | CA80: =BZ80-CA81/10000 -> 0.1079537 | CB80: =CA80-CB81/10000 -> 0.1059537
A81: Y/Y R&D margin improvement, bps | D81: =-(D80-C80)*10000 -> 1763.3316 | E81: =-(E80-D80)*10000 -> 116.58635 | F81: =-(F80-E80)*10000 -> -200.68422 | G81: =-(G80-F80)*10000 -> -436.33376 | L81: =-(L80-G80)*10000 -> -152.43711 | M81: =-(M80-H80)*10000 -> 414.2294 | N81: =-(N80-I80)*10000 -> 7.2853403 | O81: =-(O80-J80)*10000 -> 248.2242 | P81: =-(P80-K80)*10000 -> -109.65817 | Q81: =-(Q80-L80)*10000 -> 135.22482 | R81: =-(R80-M80)*10000 -> -476.1176 | S81: =-(S80-N80)*10000 -> 62.783609 | ... BO81: =-(BO80-BJ80)*10000 -> 84.358013 | BP81: 100 | BQ81: 440 | BR81: 150 | BS81: 20 | BT81: =-(BT80-BO80)*10000 -> 168.11021 | BU81: 20 | BV81: 440 | BW81: 150 | BX81: 20 | BY81: =-(BY80-BT80)*10000 -> 150.73303 | BZ81: 20 | CA81: 20 | CB81: 20
A83: SG&A, mm | C83: =C336 -> 154.756 | D83: =D336 -> 181.045 | E83: =E336 -> 217.904 | F83: =F336 -> 259.301 | G83: =G336 -> 311.741 | H83: =H336 -> 84.9 | I83: =I336 -> 79.9 | J83: =J336 -> 76.9 | ... BO83: =BO336 -> 1257.8 | BP83: =BP85*BP70 -> 302.8593 | BQ83: =BQ85*BQ70 -> 326.47716 | BR83: =BR85*BR70 -> 359.59959 | BS83: =BS85*BS70 -> 369.10431 | BT83: =BS83+BR83+BQ83+BP83 -> 1358.0404 | BU83: =BU85*BU70 -> 295.76302 | BV83: =BV85*BV70 -> 314.79008 | BW83: =BW85*BW70 -> 361.79491 | BX83: =BX85*BX70 -> 370.96692 | BY83: =BX83+BW83+BV83+BU83 -> 1343.3149 | BZ83: =BZ85*BZ70 -> 1526.508 | CA83: =CA85*CA70 -> 1506.2576 | CB83: =CB85*CB70 -> 1480.7006
A84: Y/Y SG&A growth, % | D84: =D83/C83-1 -> 0.16987387 | E84: =E83/D83-1 -> 0.20359027 | F84: =F83/E83-1 -> 0.18997816 | G84: =G83/F83-1 -> 0.20223601 | L84: =L83/G83-1 -> 0.030053795 | M84: =M83/H83-1 -> -0.030624264 | N84: =N83/I83-1 -> 0.10513141 | O84: =O83/J83-1 -> 0.11313394 | P84: =P83/K83-1 -> 0.12720403 | Q84: =Q83/L83-1 -> 0.076677774 | R84: =R83/M83-1 -> 0.078979344 | S84: =S83/N83-1 -> 0.023782559 | ... BY84: =BY83/BT83-1 -> -0.010843143 | BZ84: =BZ83/BY83-1 -> 0.13637385 | CA84: =CA83/BZ83-1 -> -0.013265774 | CB84: =CB83/CA83-1 -> -0.016967232
A85: SG&A margin, % | C85: =C83/C70 -> 0.096961085 | D85: =D83/D70 -> 0.040161378 | E85: =E83/E70 -> 0.038560016 | F85: =F83/F70 -> 0.054802491 | G85: =G83/G70 -> 0.05943215 | H85: =H83/H70 -> 0.060794844 | I85: =I83/I70 -> 0.048612801 | J85: =J83/J70 -> 0.058160641 | ... BO85: =BO83/BO70 -> 0.038503335 | BP85: =BK85-BP86/10000 -> 0.035259123 | BQ85: =BL85-BQ86/10000 -> 0.036834068 | BR85: =BM85-BR86/10000 -> 0.038340607 | BS85: =BN85-BS86/10000 -> 0.03660837 | BT85: =BT83/BT70 -> 0.036788728 | BU85: =BP85-BU86/10000 -> 0.033259123 | BV85: =BQ85-BV86/10000 -> 0.034834068 | BW85: =BR85-BW86/10000 -> 0.036340607 | BX85: =BS85-BX86/10000 -> 0.03460837 | BY85: =BY83/BY70 -> 0.034797125 | BZ85: =BY85-BZ86/10000 -> 0.032797125 | CA85: =BZ85-CA86/10000 -> 0.030797125 | CB85: =CA85-CB86/10000 -> 0.028797125
A86: Y/Y SG&A margin improvement, bps | D86: =-(D85-C85)*10000 -> 567.99707 | E86: =-(E85-D85)*10000 -> 16.013616 | F86: =-(F85-E85)*10000 -> -162.42475 | G86: =-(G85-F85)*10000 -> -46.296588 | L86: =-(L85-G85)*10000 -> 46.003854 | M86: =-(M85-H85)*10000 -> 109.13033 | N86: =-(N85-I85)*10000 -> -47.697029 | O86: =-(O85-J85)*10000 -> 29.063165 | P86: =-(P85-K85)*10000 -> -92.582107 | Q86: =-(Q85-L85)*10000 -> -1.5652575 | R86: =-(R85-M85)*10000 -> -167.2485 | S86: =-(S85-N85)*10000 -> 14.165349 | ... BO86: =-(BO85-BJ85)*10000 -> 27.415477 | BP86: 10 | BQ86: 20 | BR86: 20 | BS86: 20 | BT86: =-(BT85-BO85)*10000 -> 17.146069 | BU86: 20 | BV86: 20 | BW86: 20 | BX86: 20 | BY86: =-(BY85-BT85)*10000 -> 19.916034 | BZ86: 20 | CA86: 20 | CB86: 20
A88: Other, mm | C88: =C337 -> 0 | D88: =D337 -> 0 | E88: =E337 -> 0 | F88: =F337 -> 0 | G88: =G337 -> -64.456 | H88: =H337 -> -20.2 | I88: =I337 -> -20.3 | J88: =J337 -> -20.3 | ... BO88: =BO337 -> 0 | BP88: 0 | BQ88: 0 | BR88: 0 | BS88: 0 | BT88: =SUM(BP88,BQ88,BR88,BS88) -> 0 | BU88: 0 | BV88: 0 | BW88: 0 | BX88: 0 | BY88: =SUM(BU88,BV88,BW88,BX88) -> 0 | BZ88: 0 | CA88: 0 | CB88: 0
A89: EBIT, mm | C89: =C72-C78-C83-C88 -> -163.125 | D89: =D72-D78-D83-D88 -> 1250.699 | E89: =E72-E78-E83-E88 -> 1641.216 | F89: =F72-F78-F83-F88 -> 1156.774 | G89: =G72-G78-G83-G88 -> 1047.948 | H89: =H72-H78-H83-H88 -> 265.7 | I89: =I72-I78-I83-I88 -> 425.4 | J89: =J72-J78-J83-J88 -> 261.4 | ... CB89: =CB72-CB78-CB83-CB88 -> 21055.988
A90: =A340 -> Consensus Estimates - Adjusted EBIT | BP90: =BP340 -> N/A | BQ90: =BQ340 -> N/A | BR90: =BR340 -> N/A | BS90: =BS340 -> N/A | BT90: =BT340 -> N/A | BU90: =BU340 -> N/A | BV90: =BV340 -> N/A | BW90: =BW340 -> N/A | ... CB90: =CB340 -> N/A
A91: Y/Y EBIT growth, % | D91: =D89/C89-1 -> -8.6671203 | E91: =E89/D89-1 -> 0.312239 | F91: =F89/E89-1 -> -0.2951726 | G91: =G89/F89-1 -> -0.094077149 | L91: =L89/G89-1 -> 0.22356739 | M91: =M89/H89-1 -> 0.71509221 | N91: =N89/I89-1 -> -0.015279737 | O91: =O89/J89-1 -> 0.42463657 | P91: =P89/K89-1 -> -0.0351835 | Q91: =Q89/L89-1 -> 0.22063038 | R91: =R89/M89-1 -> -0.49967084 | S91: =S89/N89-1 -> -0.035091907 | ... BY91: =BY89/BT89-1 -> 0.13342331 | BZ91: =BZ89/BY89-1 -> 0.22414857 | CA91: =CA89/BZ89-1 -> 0.066675065 | CB91: =CB89/CA89-1 -> 0.066938417
A92: EBIT margin, % | C92: =C89/C70 -> -0.10220461 | D92: =D89/D70 -> 0.2774437 | E92: =E89/E70 -> 0.29042751 | F92: =F89/F70 -> 0.24448073 | G92: =G89/G70 -> 0.19978701 | H92: =H89/H70 -> 0.19026137 | I92: =I89/I70 -> 0.2588221 | J92: =J89/J70 -> 0.1977008 | ... CB92: =CB89/CB70 -> 0.40950338
A93: =A289 -> Consensus Estimates - Adjusted EBIT Margin, % | BP93: =BP289 -> 0 | BQ93: =BQ289 -> 0 | BR93: =BR289 -> 0 | BS93: =BS289 -> 0 | BT93: =BT289 -> 0 | BU93: =BU289 -> 0 | BV93: =BV289 -> 0 | BW93: =BW289 -> 0 | ... CB93: =CB289 -> 0
A94: Y/Y EBIT margin improvement, bps | D94: =(D92-C92)*10000 -> 3796.4831 | E94: =(E92-D92)*10000 -> 129.83805 | F94: =(F92-E92)*10000 -> -459.4678 | G94: =(G92-F92)*10000 -> -446.93715 | L94: =(L92-G92)*10000 -> 191.63528 | M94: =(M92-H92)*10000 -> 859.3719 | N94: =(N92-I92)*10000 -> -55.725966 | O94: =(O92-J92)*10000 -> 426.81331 | P94: =(P92-K92)*10000 -> 11.133924 | Q94: =(Q92-L92)*10000 -> 299.82443 | R94: =(R92-M92)*10000 -> -1051.8146 | S94: =(S92-N92)*10000 -> -208.97236 | ... BY94: =(BY92-BT92)*10000 -> 302.76588 | BZ94: =(BZ92-BY92)*10000 -> 60 | CA94: =(CA92-BZ92)*10000 -> 60 | CB94: =(CB92-CA92)*10000 -> 60
A96: Add back: D&A, mm | C96: =C342 -> 141.631 | D96: =D342 -> 151.444 | E96: =E342 -> 165.185 | F96: =F342 -> 186.62 | G96: =G342 -> 228.775 | H96: =H342 -> 64.7 | I96: =I342 -> 67 | J96: =J342 -> 60.4 | ... BO96: =BO342 -> 1025.9 | BP96: =BP113 -> 293.9746 | BQ96: =BQ113 -> 291.48383 | BR96: =BR113 -> 288.95586 | BS96: =BS113 -> 283.33153 | BT96: =SUM(BP96,BQ96,BR96,BS96) -> 1157.7458 | BU96: =BU113 -> 271.89839 | BV96: =BV113 -> 269.93903 | BW96: =BW113 -> 267.94062 | BX96: =BX113 -> 263.06376 | BY96: =SUM(BU96,BV96,BW96,BX96) -> 1072.8418 | BZ96: =BZ113 -> 1025.0655 | CA96: =CA113 -> 965.05207 | CB96: =CB113 -> 913.51616
A97: Add back: SBC, mm | C97: =C343 -> 13.394 | D97: =D343 -> 12.109 | E97: =E343 -> 12.43 | F97: =F343 -> 18.714 | G97: =G343 -> 52.371 | H97: =H343 -> 23.1 | I97: =I343 -> 13.5 | J97: =J343 -> 13.7 | ... BO97: =BO343 -> 202.3 | BP97: =BP414 -> 25.76859 | BQ97: =BQ414 -> 26.590369 | BR97: =BR414 -> 28.137238 | BS97: =BS414 -> 30.247534 | BT97: =SUM(BP97,BQ97,BR97,BS97) -> 110.74373 | BU97: =BU414 -> 26.678066 | BV97: =BV414 -> 27.110536 | BW97: =BW414 -> 29.866995 | BX97: =BX414 -> 32.156982 | BY97: =SUM(BU97,BV97,BW97,BX97) -> 115.81258 | BZ97: =BZ414 -> 139.63187 | CA97: =CA414 -> 146.7271 | CB97: =CB414 -> 154.25505
A98: EBITDA, mm | C98: =C89+C96+C97 -> -8.1 | D98: =D89+D96+D97 -> 1414.252 | E98: =E89+E96+E97 -> 1818.831 | F98: =F89+F96+F97 -> 1362.108 | G98: =G89+G96+G97 -> 1329.094 | H98: =H89+H96+H97 -> 353.5 | I98: =I89+I96+I97 -> 505.9 | J98: =J89+J96+J97 -> 335.5 | ... CB98: =CB89+CB96+CB97 -> 22123.759
A99: Y/Y EBITDA growth, % | D99: =D98/C98-1 -> -175.59901 | E99: =E98/D98-1 -> 0.28607278 | F99: =F98/E98-1 -> -0.25110799 | G99: =G98/F98-1 -> -0.024237432 | L99: =L98/G98-1 -> 0.20402244 | M99: =M98/H98-1 -> 0.51739745 | N99: =N98/I98-1 -> 0.0015813402 | O99: =O98/J98-1 -> 0.38509687 | P99: =P98/K98-1 -> 0.019564595 | Q99: =Q98/L98-1 -> 0.2004863 | R99: =R98/M98-1 -> -0.39746458 | S99: =S98/N98-1 -> -0.014801658 | ... BY99: =BY98/BT98-1 -> 0.11636649 | BZ99: =BZ98/BY98-1 -> 0.20633564 | CA99: =CA98/BZ98-1 -> 0.060035485 | CB99: =CB98/CA98-1 -> 0.061257494
A100: EBITDA margin, % | C100: =C98/C70 -> -0.0050749876 | D100: =D98/D70 -> 0.31372481 | E100: =E98/E70 -> 0.32185803 | F100: =F98/F70 -> 0.28787745 | G100: =G98/G70 -> 0.25338635 | H100: =H98/H70 -> 0.25313283 | I100: =I98/I70 -> 0.30779995 | J100: =J98/J70 -> 0.25374376 | ... CB100: =CB98/CB70 -> 0.43026972
A101: Y/Y EBITDA margin improvement, bps | D101: =(D100-C100)*10000 -> 3187.998 | E101: =(E100-D100)*10000 -> 81.332197 | F101: =(F100-E100)*10000 -> -339.80579 | G101: =(G100-F100)*10000 -> -344.91104 | L101: =(L100-G100)*10000 -> 198.68998 | M101: =(M100-H100)*10000 -> 719.77781 | N101: =(N100-I100)*10000 -> -14.702252 | O101: =(O100-J100)*10000 -> 462.1751 | P101: =(P100-K100)*10000 -> 168.41314 | Q101: =(Q100-L100)*10000 -> 322.91722 | R101: =(R100-M100)*10000 -> -826.8637 | S101: =(S100-N100)*10000 -> -193.67206 | ... BY101: =(BY100-BT100)*10000 -> 267.04563 | BZ101: =(BZ100-BY100)*10000 -> 2.327906 | CA101: =(CA100-BZ100)*10000 -> 37.0797 | CB101: =(CB100-CA100)*10000 -> 40.347748
A103: SBC and D&A Breakdown (FS)
A104: Depreciation related to cost of sales, mm | C104: 83.6 | D104: 108.7 | E104: 117.7 | F104: 147.7 | G104: 144.1 | L104: 153.9 | Q104: 191.7 | V104: 187.9 | AA104: 195.7 | AF104: 191.6 | AK104: 196.1 | AP104: 205.9 | AU104: 188.6 | AZ104: 248.2 | BE104: 330.4 | BJ104: 398.4
A105: Depreciation related to R&D costs, mm | C105: 21.9 | D105: 16.7 | E105: 24.9 | F105: 15.3 | G105: 35 | L105: 36.3 | Q105: 19.7 | V105: 76.8 | AA105: 101.7 | AF105: 105.9 | AK105: 117.2 | AP105: 119.9 | AU105: 101.4 | AZ105: 163.7 | BE105: 236.2 | BJ105: 340.5
A106: Depreciation related to SG&A, mm | C106: 25.6 | D106: 19.2 | E106: 15.4 | F106: 16.3 | G106: 18 | L106: 19.3 | Q106: 31.6 | V106: 26.1 | AA106: 10.8 | AF106: 17.9 | AK106: 12 | AP106: 25.9 | AU106: 31.6 | AZ106: 33.3 | BE106: 39 | BJ106: 48.4
A107: Depreciation of PPE, mm | C107: =SUM(C104:C106) -> 131.1 | D107: =SUM(D104:D106) -> 144.6 | E107: =SUM(E104:E106) -> 158 | F107: =SUM(F104:F106) -> 179.3 | G107: =SUM(G104:G106) -> 197.1 | H107: =H113-H111-H112 -> 53.414 | I107: =I113-I111-I112 -> 55.714 | J107: =J113-J111-J112 -> 49.114 | K107: =K113-K111-K112 -> 51.258 | L107: =SUM(L104:L106) -> 209.5 | M107: =M113-M111-M112 -> 52.629 | N107: =N113-N111-N112 -> 59.329 | O107: =O113-O111-O112 -> 64.029 | P107: =P113-P111-P112 -> 67.013 | Q107: =SUM(Q104:Q106) -> 243 | R107: =R113-R111-R112 -> 65.475 | S107: =S113-S111-S112 -> 67.575 | T107: =T113-T111-T112 -> 71.175 | U107: =U113-U111-U112 -> 86.575 | V107: =SUM(V104:V106) -> 290.8 | W107: =W113-W111-W112 -> 82.775 | X107: =X113-X111-X112 -> 76.575 | Y107: =Y113-Y111-Y112 -> 73.875 | Z107: =Z113-Z111-Z112 -> 74.975 | AA107: =SUM(AA104:AA106) -> 308.2 | AB107: =AB113-AB111-AB112 -> 75.775 | AC107: =AC113-AC111-AC112 -> 72.875 | AD107: =AD113-AD111-AD112 -> 83.175 | AE107: =AE113-AE111-AE112 -> 83.575 | AF107: =SUM(AF104:AF106) -> 315.4 | AG107: =AG113-AG111-AG112 -> 74 | AH107: =AH113-AH111-AH112 -> 77.6 | AI107: =AI113-AI111-AI112 -> 81.6 | AJ107: =AJ113-AJ111-AJ112 -> 92.1 | AK107: =SUM(AK104:AK106) -> 325.3 | AL107: =AL113-AL111-AL112 -> 83.525 | AM107: =AM113-AM111-AM112 -> 90.325 | AN107: =AN113-AN111-AN112 -> 87.225 | AO107: =AO113-AO111-AO112 -> 90.625 | AP107: =SUM(AP104:AP106) -> 351.7 | AQ107: =AQ113-AQ111-AQ112 -> 80.55 | AR107: =AR113-AR111-AR112 -> 75.35 | AS107: =AS113-AS111-AS112 -> 78.85 | AT107: =AT113-AT111-AT112 -> 86.85 | AU107: =SUM(AU104:AU106) -> 321.6 | AV107: =AV113-AV111-AV112 -> 96.4 | AW107: =AW113-AW111-AW112 -> 96.9 | AX107: =AX113-AX111-AX112 -> 103.3 | AY107: =AY113-AY111-AY112 -> 148.6 | AZ107: =SUM(AZ104:AZ106) -> 445.2 | BA107: =BA113-BA111-BA112 -> 136.75 | BB107: =BB113-BB111-BB112 -> 147.65 | BC107: =BC113-BC111-BC112 -> 142.65 | BD107: =BD113-BD111-BD112 -> 178.55 | BE107: =SUM(BE104:BE106) -> 605.6 | BF107: =BF113-BF111-BF112 -> 181.575 | BG107: =BG113-BG111-BG112 -> 194.675 | BH107: =BH113-BH111-BH112 -> 202.875 | BI107: =BI113-BI111-BI112 -> 208.175 | BJ107: =SUM(BJ104:BJ106) -> 787.3 | BK107: =BK113-BK111-BK112 -> 209.8 | BL107: =BL113-BL111-BL112 -> 223.4 | BM107: =BM113-BM111-BM112 -> 243.1 | BN107: =BN113-BN111-BN112 -> 223.6 | BO107: =SUM(BK107,BL107,BM107,BN107) -> 899.9 | BP107: =-BP584 -> 272.4983 | BQ107: =-BQ584 -> 270.43483 | BR107: =-BR584 -> 268.33228 | BS107: =-BS584 -> 263.33211 | BT107: =BS107+BR107+BQ107+BP107 -> 1074.5975 | BU107: =-BU584 -> 252.88864 | BV107: =-BV584 -> 251.29175 | BW107: =-BW584 -> 249.65435 | BX107: =-BX584 -> 245.31328 | BY107: =BX107+BW107+BV107+BU107 -> 999.14802 | BZ107: =-BZ584 -> 956.63882 | CA107: =-CA584 -> 904.18939 | CB107: =-CB584 -> 859.08287
A108: Amortization related to cost of sales, mm | C108: 8.8 | D108: 5.5 | E108: 5.3 | F108: 6 | G108: 27 | L108: 41.9 | Q108: 49.1 | V108: 59.5 | AA108: 99.7 | AF108: 97.2 | AK108: 97.4 | AP108: 101.8 | AU108: 107.8 | AZ108: 105.9 | BE108: 102.7 | BJ108: 103.8
A109: Amortization related to R&D costs, mm | D109: 0 | E109: 0 | F109: 0.1 | G109: 0.6 | L109: 2 | Q109: 2.1 | V109: 2.5 | AA109: 2.1 | AF109: 1.3 | AK109: 7.5 | AP109: 12 | AU109: 14.5 | AZ109: 18.2 | BE109: 19.5 | BJ109: 20.8
A110: Amortization related to SG&A, mm | L110: 0 | Q110: 0 | V110: 1.5 | AA110: 3.7 | AF110: 5.2 | AK110: 10.5 | AP110: 9.7 | AU110: 10.7 | AZ110: 11 | BE110: 5.4 | BJ110: 1.4
A111: Amortization of intangibles, mm | C111: =SUM(C108:C110) -> 8.8 | D111: =SUM(D108:D110) -> 5.5 | E111: =SUM(E108:E110) -> 5.3 | F111: =SUM(F108:F110) -> 6.1 | G111: =SUM(G108:G110) -> 27.6 | H111: =L111/4 -> 10.975 | I111: =L111/4 -> 10.975 | J111: =L111/4 -> 10.975 | K111: =L111/4 -> 10.975 | L111: =SUM(L108:L110) -> 43.9 | M111: =Q111/4 -> 12.8 | N111: =Q111/4 -> 12.8 | O111: =Q111/4 -> 12.8 | P111: =Q111/4 -> 12.8 | Q111: =SUM(Q108:Q110) -> 51.2 | R111: =V111/4 -> 15.875 | S111: =V111/4 -> 15.875 | T111: =V111/4 -> 15.875 | U111: =V111/4 -> 15.875 | V111: =SUM(V108:V110) -> 63.5 | W111: =AA111/4 -> 26.375 | X111: =AA111/4 -> 26.375 | Y111: =AA111/4 -> 26.375 | Z111: =AA111/4 -> 26.375 | AA111: =SUM(AA108:AA110) -> 105.5 | AB111: =AF111/4 -> 25.925 | AC111: =AF111/4 -> 25.925 | AD111: =AF111/4 -> 25.925 | AE111: =AF111/4 -> 25.925 | AF111: =SUM(AF108:AF110) -> 103.7 | AG111: =AK111/4 -> 28.85 | AH111: =AK111/4 -> 28.85 | AI111: =AK111/4 -> 28.85 | AJ111: =AK111/4 -> 28.85 | AK111: =SUM(AK108:AK110) -> 115.4 | AL111: =AP111/4 -> 30.875 | AM111: =AP111/4 -> 30.875 | AN111: =AP111/4 -> 30.875 | AO111: =AP111/4 -> 30.875 | AP111: =SUM(AP108:AP110) -> 123.5 | AQ111: =AU111/4 -> 33.25 | AR111: =AU111/4 -> 33.25 | AS111: =AU111/4 -> 33.25 | AT111: =AU111/4 -> 33.25 | AU111: =SUM(AU108:AU110) -> 133 | AV111: =AZ111/4 -> 33.775 | AW111: =AZ111/4 -> 33.775 | AX111: =AZ111/4 -> 33.775 | AY111: =AZ111/4 -> 33.775 | AZ111: =SUM(AZ108:AZ110) -> 135.1 | BA111: =BE111/4 -> 31.9 | BB111: =BE111/4 -> 31.9 | BC111: =BE111/4 -> 31.9 | BD111: =BE111/4 -> 31.9 | BE111: =SUM(BE108:BE110) -> 127.6 | BF111: =BJ111/4 -> 31.5 | BG111: =BJ111/4 -> 31.5 | BH111: =BJ111/4 -> 31.5 | BI111: =BJ111/4 -> 31.5 | BJ111: =SUM(BJ108:BJ110) -> 126 | BK111: 30 | BL111: 30 | BM111: 30 | BN111: 30 | BO111: =SUM(BK111,BL111,BM111,BN111) -> 120 | BP111: =-BP590 -> 19.976301 | BQ111: =-BQ590 -> 19.548995 | BR111: =-BR590 -> 19.123575 | BS111: =-BS590 -> 18.499415 | BT111: =BS111+BR111+BQ111+BP111 -> 77.148287 | BU111: =-BU590 -> 17.509748 | BV111: =-BV590 -> 17.147278 | BW111: =-BW590 -> 16.78627 | BX111: =-BX590 -> 16.25048 | BY111: =BX111+BW111+BV111+BU111 -> 67.693777 | BZ111: =-BZ590 -> 62.42669 | CA111: =-CA590 -> 54.862687 | CB111: =-CB590 -> 48.433284
A112: Other D&A, mm | C112: =C113-C107-C111 -> 1.731 | D112: =D113-D107-D111 -> 1.344 | E112: =E113-E107-E111 -> 1.885 | F112: =F113-F107-F111 -> 1.22 | G112: =G113-G107-G111 -> 4.075 | H112: =L112/4 -> 0.311 | I112: =L112/4 -> 0.311 | J112: =L112/4 -> 0.311 | K112: =L112/4 -> 0.311 | L112: =L113-L107-L111 -> 1.244 | M112: =Q112/4 -> 0.671 | N112: =Q112/4 -> 0.671 | O112: =Q112/4 -> 0.671 | P112: =Q112/4 -> 0.671 | Q112: =Q113-Q107-Q111 -> 2.684 | R112: =V112/4 -> 0.65 | S112: =V112/4 -> 0.65 | T112: =V112/4 -> 0.65 | U112: =V112/4 -> 0.65 | V112: =V113-V107-V111 -> 2.6 | W112: =AA112/4 -> 0.95 | X112: =AA112/4 -> 0.95 | Y112: =AA112/4 -> 0.95 | Z112: =AA112/4 -> 0.95 | AA112: =AA113-AA107-AA111 -> 3.8 | AB112: =AF112/4 -> 0.9 | AC112: =AF112/4 -> 0.9 | AD112: =AF112/4 -> 0.9 | AE112: =AF112/4 -> 0.9 | AF112: =AF113-AF107-AF111 -> 3.6 | AG112: =AK112/4 -> 1.95 | AH112: =AK112/4 -> 1.95 | AI112: =AK112/4 -> 1.95 | AJ112: =AK112/4 -> 1.95 | AK112: =AK113-AK107-AK111 -> 7.8 | AL112: =AP112/4 -> 3.9 | AM112: =AP112/4 -> 3.9 | AN112: =AP112/4 -> 3.9 | AO112: =AP112/4 -> 3.9 | AP112: =AP113-AP107-AP111 -> 15.6 | AQ112: =AU112/4 -> 4.1 | AR112: =AU112/4 -> 4.1 | AS112: =AU112/4 -> 4.1 | AT112: =AU112/4 -> 4.1 | AU112: =AU113-AU107-AU111 -> 16.4 | AV112: =AZ112/4 -> 0.825 | AW112: =AZ112/4 -> 0.825 | AX112: =AZ112/4 -> 0.825 | AY112: =AZ112/4 -> 0.825 | AZ112: =AZ113-AZ107-AZ111 -> 3.3 | BA112: =BE112/4 -> 1.65 | BB112: =BE112/4 -> 1.65 | BC112: =BE112/4 -> 1.65 | BD112: =BE112/4 -> 1.65 | BE112: =BE113-BE107-BE111 -> 6.6 | BF112: =BJ112/4 -> 1.325 | BG112: =BJ112/4 -> 1.325 | BH112: =BJ112/4 -> 1.325 | BI112: =BJ112/4 -> 1.325 | BJ112: =BJ113-BJ107-BJ111 -> 5.3 | BK112: 1.5 | BL112: 1.5 | BM112: 1.5 | BN112: 1.5 | BO112: =BO113-BO107-BO111 -> 6 | BP112: 1.5 | BQ112: 1.5 | BR112: 1.5 | BS112: 1.5 | BT112: =BS112+BR112+BQ112+BP112 -> 6 | BU112: 1.5 | BV112: 1.5 | BW112: 1.5 | BX112: 1.5 | BY112: =BX112+BW112+BV112+BU112 -> 6 | BZ112: 6 | CA112: 6 | CB112: 6
...

Sheet Guidance
B1: =MO.CompanyName -> ASML Holdings N.V.
B2: Most Recent Period: | F2: =UL.MRQ -> FY2025
I4: Guidance | M4: Model | P4: Difference vs. Mid | S4: Update Log
B5: Type | D5: Item | E5: Item Name | F5: Fiscal Period | G5: Base Period | I5: Low | J5: High | K5: Mid | M5: Type | N5: Output | P5: Absolute | Q5: Relative | S5: Date | T5: Link
A6: 288 | B6: =IF(INDEX(MO_SNA_IsHistoricalPeriod,,MATCH(F6,MO_Common_ColumnHeader,0)),"Historical","Forward") -> Forward | D6: =INDEX(INDIRECT(E6),0,COLUMN(MO_Common_Column_A)) -> Net Revenue | E6: MO_RIS_REV | F6: FY2026 | I6: 34000 | J6: 39000 | K6: =AVERAGE(I6:J6) -> 36500 | M6: =IF(INDEX(MO_SNA_IsHistoricalPeriod,,MATCH(F6,MO_Common_ColumnHeader,0)),"Actual","Estimate") -> Estimate | N6: =IFERROR(INDEX(INDIRECT(E6),0,MATCH(F6,MO_Common_ColumnHeader,0)),"N/A") -> 36914.577 | P6: =IF(ISNUMBER(N6),N6-K6,"N/A") -> 414.57728 | Q6: =IFERROR(IF(ISNUMBER(N6),(N6-K6)/ABS(K6),"N/A"),"N/A") -> 0.011358282 | S6: 46050 | T6: Investor Presentation
A7: 287 | B7: =IF(INDEX(MO_SNA_IsHistoricalPeriod,,MATCH(F7,MO_Common_ColumnHeader,0)),"Historical","Forward") -> Forward | D7: =INDEX(INDIRECT(E7),0,COLUMN(MO_Common_Column_A)) -> Gross Margin, % | E7: MO_MA_GM | F7: FY2026 | I7: 0.51 | J7: 0.53 | K7: =AVERAGE(I7:J7) -> 0.52 | M7: =IF(INDEX(MO_SNA_IsHistoricalPeriod,,MATCH(F7,MO_Common_ColumnHeader,0)),"Actual","Estimate") -> Estimate | N7: =IFERROR(INDEX(INDIRECT(E7),0,MATCH(F7,MO_Common_ColumnHeader,0)),"N/A") -> 0.52504252 | P7: =IF(ISNUMBER(N7),N7-K7,"N/A") -> 0.0050425246 | Q7: =IFERROR(IF(ISNUMBER(N7),(N7-K7)/ABS(K7),"N/A"),"N/A") -> 0.0096971626 | S7: 46050 | T7: Investor Presentation
A8: 286 | B8: =IF(INDEX(MO_SNA_IsHistoricalPeriod,,MATCH(F8,MO_Common_ColumnHeader,0)),"Historical","Forward") -> Forward | D8: Effective tax rate | F8: FY2026 | I8: 0.17 | J8: 0.17 | K8: =AVERAGE(I8:J8) -> 0.17 | M8: =IF(INDEX(MO_SNA_IsHistoricalPeriod,,MATCH(F8,MO_Common_ColumnHeader,0)),"Actual","Estimate") -> Estimate | N8: =INDEX(MO_RIS_TaxRate_Current,0,MATCH(F8,MO_Common_ColumnHeader,0))+INDEX(MO_RIS_TaxRate_Deferred,0,MATCH(F8,MO_Common_ColumnHeader,0)) -> 0.16891468 | P8: =IF(ISNUMBER(N8),N8-K8,"N/A") -> -0.0010853155 | Q8: =IFERROR(IF(ISNUMBER(N8),(N8-K8)/ABS(K8),"N/A"),"N/A") -> -0.0063842086 | S8: 46050 | T8: Investor Presentation
A9: 285
A10: 284 | B10: =IF(INDEX(MO_SNA_IsHistoricalPeriod,,MATCH(F10,MO_Common_ColumnHeader,0)),"Historical","Forward") -> Forward | D10: =INDEX(INDIRECT(E10),0,COLUMN(MO_Common_Column_A)) -> Net Revenue | E10: MO_RIS_REV | F10: Q1-2026 | I10: 8200 | J10: 8900 | K10: =AVERAGE(I10:J10) -> 8550 | M10: =IF(INDEX(MO_SNA_IsHistoricalPeriod,,MATCH(F10,MO_Common_ColumnHeader,0)),"Actual","Estimate") -> Estimate | N10: =IFERROR(INDEX(INDIRECT(E10),0,MATCH(F10,MO_Common_ColumnHeader,0)),"N/A") -> 8589.5301 | P10: =IF(ISNUMBER(N10),N10-K10,"N/A") -> 39.530076 | Q10: =IFERROR(IF(ISNUMBER(N10),(N10-K10)/ABS(K10),"N/A"),"N/A") -> 0.0046234007 | S10: 46050 | T10: Investor Presentation
A11: 283 | B11: =IF(INDEX(MO_SNA_IsHistoricalPeriod,,MATCH(F11,MO_Common_ColumnHeader,0)),"Historical","Forward") -> Forward | D11: Installed Base Management sales | E11: z_I9KH3H0125_MO_OS_Netserviceandfieldoptionsales | F11: Q1-2026 | I11: 2400 | J11: 2400 | K11: =AVERAGE(I11:J11) -> 2400 | M11: =IF(INDEX(MO_SNA_IsHistoricalPeriod,,MATCH(F11,MO_Common_ColumnHeader,0)),"Actual","Estimate") -> Estimate | N11: =IFERROR(INDEX(INDIRECT(E11),0,MATCH(F11,MO_Common_ColumnHeader,0)),"N/A") -> 2401.32 | P11: =IF(ISNUMBER(N11),N11-K11,"N/A") -> 1.32 | Q11: =IFERROR(IF(ISNUMBER(N11),(N11-K11)/ABS(K11),"N/A"),"N/A") -> 0.00055 | S11: 46050 | T11: Investor Presentation
A12: 282 | B12: =IF(INDEX(MO_SNA_IsHistoricalPeriod,,MATCH(F12,MO_Common_ColumnHeader,0)),"Historical","Forward") -> Forward | D12: =INDEX(INDIRECT(E12),0,COLUMN(MO_Common_Column_A)) -> Gross Margin, % | E12: MO_MA_GM | F12: Q1-2026 | I12: 0.51 | J12: 0.53 | K12: =AVERAGE(I12:J12) -> 0.52 | M12: =IF(INDEX(MO_SNA_IsHistoricalPeriod,,MATCH(F12,MO_Common_ColumnHeader,0)),"Actual","Estimate") -> Estimate | N12: =IFERROR(INDEX(INDIRECT(E12),0,MATCH(F12,MO_Common_ColumnHeader,0)),"N/A") -> 0.51990829 | P12: =IF(ISNUMBER(N12),N12-K12,"N/A") -> -9.1713492e-05 | Q12: =IFERROR(IF(ISNUMBER(N12),(N12-K12)/ABS(K12),"N/A"),"N/A") -> -0.0001763721 | S12: 46050 | T12: Investor Presentation
A13: 281 | B13: =IF(INDEX(MO_SNA_IsHistoricalPeriod,,MATCH(F13,MO_Common_ColumnHeader,0)),"Historical","Forward") -> Forward | D13: R&D Expense | E13: MO_RIS_RD | F13: Q1-2026 | I13: 1200 | J13: 1200 | K13: =AVERAGE(I13:J13) -> 1200 | M13: =IF(INDEX(MO_SNA_IsHistoricalPeriod,,MATCH(F13,MO_Common_ColumnHeader,0)),"Actual","Estimate") -> Estimate | N13: =IFERROR(INDEX(INDIRECT(E13),0,MATCH(F13,MO_Common_ColumnHeader,0)),"N/A") -> 1202.3955 | P13: =IF(ISNUMBER(N13),N13-K13,"N/A") -> 2.3955177 | Q13: =IFERROR(IF(ISNUMBER(N13),(N13-K13)/ABS(K13),"N/A"),"N/A") -> 0.0019962648 | S13: 46050 | T13: Investor Presentation
A14: 280 | B14: =IF(INDEX(MO_SNA_IsHistoricalPeriod,,MATCH(F14,MO_Common_ColumnHeader,0)),"Historical","Forward") -> Forward | D14: =INDEX(INDIRECT(E14),0,COLUMN(MO_Common_Column_A)) -> SG&A | E14: MO_RIS_SGA | F14: Q1-2026 | I14: 300 | J14: 300 | K14: =AVERAGE(I14:J14) -> 300 | M14: =IF(INDEX(MO_SNA_IsHistoricalPeriod,,MATCH(F14,MO_Common_ColumnHeader,0)),"Actual","Estimate") -> Estimate | N14: =IFERROR(INDEX(INDIRECT(E14),0,MATCH(F14,MO_Common_ColumnHeader,0)),"N/A") -> 302.8593 | P14: =IF(ISNUMBER(N14),N14-K14,"N/A") -> 2.8592967 | Q14: =IFERROR(IF(ISNUMBER(N14),(N14-K14)/ABS(K14),"N/A"),"N/A") -> 0.0095309889 | S14: 46050 | T14: Investor Presentation
A15: 279
A16: 278 | B16: =IF(INDEX(MO_SNA_IsHistoricalPeriod,,MATCH(F16,MO_Common_ColumnHeader,0)),"Historical","Forward") -> Historical | D16: =INDEX(INDIRECT(E16),0,COLUMN(MO_Common_Column_A)) -> Net Revenue | E16: MO_RIS_REV | F16: FY2025 | I16: =28262.9*1.15 -> 32502.335 | J16: =28262.9*1.15 -> 32502.335 | K16: =AVERAGE(I16:J16) -> 32502.335 | M16: =IF(INDEX(MO_SNA_IsHistoricalPeriod,,MATCH(F16,MO_Common_ColumnHeader,0)),"Actual","Estimate") -> Actual | N16: =IFERROR(INDEX(INDIRECT(E16),0,MATCH(F16,MO_Common_ColumnHeader,0)),"N/A") -> 32667.3 | P16: =IF(ISNUMBER(N16),N16-K16,"N/A") -> 164.965 | Q16: =IFERROR(IF(ISNUMBER(N16),(N16-K16)/ABS(K16),"N/A"),"N/A") -> 0.0050754815 | S16: 45945 | T16: Investor Presentation
A17: 277 | B17: =IF(INDEX(MO_SNA_IsHistoricalPeriod,,MATCH(F17,MO_Common_ColumnHeader,0)),"Historical","Forward") -> Historical | D17: =INDEX(INDIRECT(E17),0,COLUMN(MO_Common_Column_A)) -> Gross Margin, % | E17: MO_MA_GM | F17: FY2025 | I17: 0.52 | J17: 0.52 | K17: =AVERAGE(I17:J17) -> 0.52 | M17: =IF(INDEX(MO_SNA_IsHistoricalPeriod,,MATCH(F17,MO_Common_ColumnHeader,0)),"Actual","Estimate") -> Actual | N17: =IFERROR(INDEX(INDIRECT(E17),0,MATCH(F17,MO_Common_ColumnHeader,0)),"N/A") -> 0.52829588 | P17: =IF(ISNUMBER(N17),N17-K17,"N/A") -> 0.00829588 | Q17: =IFERROR(IF(ISNUMBER(N17),(N17-K17)/ABS(K17),"N/A"),"N/A") -> 0.015953615 | S17: 45945 | T17: Investor Presentation
A18: 276 | B18: =IF(INDEX(MO_SNA_IsHistoricalPeriod,,MATCH(F18,MO_Common_ColumnHeader,0)),"Historical","Forward") -> Historical | D18: Effective tax rate | F18: FY2025 | I18: 0.17 | J18: 0.17 | K18: =AVERAGE(I18:J18) -> 0.17 | M18: =IF(INDEX(MO_SNA_IsHistoricalPeriod,,MATCH(F18,MO_Common_ColumnHeader,0)),"Actual","Estimate") -> Actual | N18: =INDEX(MO_RIS_TaxRate_Current,0,MATCH(F18,MO_Common_ColumnHeader,0))+INDEX(MO_RIS_TaxRate_Deferred,0,MATCH(F18,MO_Common_ColumnHeader,0)) -> 0.17322848 | P18: =IF(ISNUMBER(N18),N18-K18,"N/A") -> 0.0032284819 | Q18: =IFERROR(IF(ISNUMBER(N18),(N18-K18)/ABS(K18),"N/A"),"N/A") -> 0.01899107 | S18: 45945 | T18: Investor Presentation
A19: 275
A20: 274 | B20: =IF(INDEX(MO_SNA_IsHistoricalPeriod,,MATCH(F20,MO_Common_ColumnHeader,0)),"Historical","Forward") -> Historical | D20: =INDEX(INDIRECT(E20),0,COLUMN(MO_Common_Column_A)) -> Net Revenue | E20: MO_RIS_REV | F20: Q4-2025 | I20: 9200 | J20: 9800 | K20: =AVERAGE(I20:J20) -> 9500 | M20: =IF(INDEX(MO_SNA_IsHistoricalPeriod,,MATCH(F20,MO_Common_ColumnHeader,0)),"Actual","Estimate") -> Actual | N20: =IFERROR(INDEX(INDIRECT(E20),0,MATCH(F20,MO_Common_ColumnHeader,0)),"N/A") -> 9718.1 | P20: =IF(ISNUMBER(N20),N20-K20,"N/A") -> 218.1 | Q20: =IFERROR(IF(ISNUMBER(N20),(N20-K20)/ABS(K20),"N/A"),"N/A") -> 0.022957895 | S20: 45945 | T20: Investor Presentation
A21: 273 | B21: =IF(INDEX(MO_SNA_IsHistoricalPeriod,,MATCH(F21,MO_Common_ColumnHeader,0)),"Historical","Forward") -> Historical | D21: Installed Base Management sales | E21: z_I9KH3H0125_MO_OS_Netserviceandfieldoptionsales | F21: Q4-2025 | I21: 2100 | J21: 2100 | K21: =AVERAGE(I21:J21) -> 2100 | M21: =IF(INDEX(MO_SNA_IsHistoricalPeriod,,MATCH(F21,MO_Common_ColumnHeader,0)),"Actual","Estimate") -> Actual | N21: =IFERROR(INDEX(INDIRECT(E21),0,MATCH(F21,MO_Common_ColumnHeader,0)),"N/A") -> 2134.1 | P21: =IF(ISNUMBER(N21),N21-K21,"N/A") -> 34.1 | Q21: =IFERROR(IF(ISNUMBER(N21),(N21-K21)/ABS(K21),"N/A"),"N/A") -> 0.016238095 | S21: 45945 | T21: Investor Presentation
A22: 272 | B22: =IF(INDEX(MO_SNA_IsHistoricalPeriod,,MATCH(F22,MO_Common_ColumnHeader,0)),"Historical","Forward") -> Historical | D22: =INDEX(INDIRECT(E22),0,COLUMN(MO_Common_Column_A)) -> Gross Margin, % | E22: MO_MA_GM | F22: Q4-2025 | I22: 0.51 | J22: 0.53 | K22: =AVERAGE(I22:J22) -> 0.52 | M22: =IF(INDEX(MO_SNA_IsHistoricalPeriod,,MATCH(F22,MO_Common_ColumnHeader,0)),"Actual","Estimate") -> Actual | N22: =IFERROR(INDEX(INDIRECT(E22),0,MATCH(F22,MO_Common_ColumnHeader,0)),"N/A") -> 0.52155257 | P22: =IF(ISNUMBER(N22),N22-K22,"N/A") -> 0.0015525669 | Q22: =IFERROR(IF(ISNUMBER(N22),(N22-K22)/ABS(K22),"N/A"),"N/A") -> 0.0029857055 | S22: 45945 | T22: Investor Presentation
A23: 271 | B23: =IF(INDEX(MO_SNA_IsHistoricalPeriod,,MATCH(F23,MO_Common_ColumnHeader,0)),"Historical","Forward") -> Historical | D23: R&D Expense | E23: MO_RIS_RD | F23: Q4-2025 | I23: 1200 | J23: 1200 | K23: =AVERAGE(I23:J23) -> 1200 | M23: =IF(INDEX(MO_SNA_IsHistoricalPeriod,,MATCH(F23,MO_Common_ColumnHeader,0)),"Actual","Estimate") -> Actual | N23: =IFERROR(INDEX(INDIRECT(E23),0,MATCH(F23,MO_Common_ColumnHeader,0)),"N/A") -> 1262.3 | P23: =IF(ISNUMBER(N23),N23-K23,"N/A") -> 62.3 | Q23: =IFERROR(IF(ISNUMBER(N23),(N23-K23)/ABS(K23),"N/A"),"N/A") -> 0.051916667 | S23: 45945 | T23: Investor Presentation
A24: 270 | B24: =IF(INDEX(MO_SNA_IsHistoricalPeriod,,MATCH(F24,MO_Common_ColumnHeader,0)),"Historical","Forward") -> Historical | D24: =INDEX(INDIRECT(E24),0,COLUMN(MO_Common_Column_A)) -> SG&A | E24: MO_RIS_SGA | F24: Q4-2025 | I24: 320 | J24: 320 | K24: =AVERAGE(I24:J24) -> 320 | M24: =IF(INDEX(MO_SNA_IsHistoricalPeriod,,MATCH(F24,MO_Common_ColumnHeader,0)),"Actual","Estimate") -> Actual | N24: =IFERROR(INDEX(INDIRECT(E24),0,MATCH(F24,MO_Common_ColumnHeader,0)),"N/A") -> 375.2 | P24: =IF(ISNUMBER(N24),N24-K24,"N/A") -> 55.2 | Q24: =IFERROR(IF(ISNUMBER(N24),(N24-K24)/ABS(K24),"N/A"),"N/A") -> 0.1725 | S24: 45945 | T24: Investor Presentation
A25: 269
A26: 268 | B26: =IF(INDEX(MO_SNA_IsHistoricalPeriod,,MATCH(F26,MO_Common_ColumnHeader,0)),"Historical","Forward") -> Historical | D26: =INDEX(INDIRECT(E26),0,COLUMN(MO_Common_Column_A)) -> Net Revenue | E26: MO_RIS_REV | F26: FY2025 | I26: =28262.9*1.15 -> 32502.335 | J26: =28262.9*1.15 -> 32502.335 | K26: =AVERAGE(I26:J26) -> 32502.335 | M26: =IF(INDEX(MO_SNA_IsHistoricalPeriod,,MATCH(F26,MO_Common_ColumnHeader,0)),"Actual","Estimate") -> Actual | N26: =IFERROR(INDEX(INDIRECT(E26),0,MATCH(F26,MO_Common_ColumnHeader,0)),"N/A") -> 32667.3 | P26: =IF(ISNUMBER(N26),N26-K26,"N/A") -> 164.965 | Q26: =IFERROR(IF(ISNUMBER(N26),(N26-K26)/ABS(K26),"N/A"),"N/A") -> 0.0050754815 | S26: 45853 | T26: Investor Presentation
A27: 267 | B27: =IF(INDEX(MO_SNA_IsHistoricalPeriod,,MATCH(F27,MO_Common_ColumnHeader,0)),"Historical","Forward") -> Historical | D27: =INDEX(INDIRECT(E27),0,COLUMN(MO_Common_Column_A)) -> Gross Margin, % | E27: MO_MA_GM | F27: FY2025 | I27: 0.52 | J27: 0.52 | K27: =AVERAGE(I27:J27) -> 0.52 | M27: =IF(INDEX(MO_SNA_IsHistoricalPeriod,,MATCH(F27,MO_Common_ColumnHeader,0)),"Actual","Estimate") -> Actual | N27: =IFERROR(INDEX(INDIRECT(E27),0,MATCH(F27,MO_Common_ColumnHeader,0)),"N/A") -> 0.52829588 | P27: =IF(ISNUMBER(N27),N27-K27,"N/A") -> 0.00829588 | Q27: =IFERROR(IF(ISNUMBER(N27),(N27-K27)/ABS(K27),"N/A"),"N/A") -> 0.015953615 | S27: 45853 | T27: Investor Presentation
A28: 266 | B28: =IF(INDEX(MO_SNA_IsHistoricalPeriod,,MATCH(F28,MO_Common_ColumnHeader,0)),"Historical","Forward") -> Historical | D28: Effective tax rate | F28: FY2025 | I28: 0.17 | J28: 0.17 | K28: =AVERAGE(I28:J28) -> 0.17 | M28: =IF(INDEX(MO_SNA_IsHistoricalPeriod,,MATCH(F28,MO_Common_ColumnHeader,0)),"Actual","Estimate") -> Actual | N28: =INDEX(MO_RIS_TaxRate_Current,0,MATCH(F28,MO_Common_ColumnHeader,0))+INDEX(MO_RIS_TaxRate_Deferred,0,MATCH(F28,MO_Common_ColumnHeader,0)) -> 0.17322848 | P28: =IF(ISNUMBER(N28),N28-K28,"N/A") -> 0.0032284819 | Q28: =IFERROR(IF(ISNUMBER(N28),(N28-K28)/ABS(K28),"N/A"),"N/A") -> 0.01899107 | S28: 45853 | T28: Investor Presentation
A29: 265
A30: 264 | B30: =IF(INDEX(MO_SNA_IsHistoricalPeriod,,MATCH(F30,MO_Common_ColumnHeader,0)),"Historical","Forward") -> Historical | D30: =INDEX(INDIRECT(E30),0,COLUMN(MO_Common_Column_A)) -> Net Revenue | E30: MO_RIS_REV | F30: Q3-2025 | I30: 7400 | J30: 7900 | K30: =AVERAGE(I30:J30) -> 7650 | M30: =IF(INDEX(MO_SNA_IsHistoricalPeriod,,MATCH(F30,MO_Common_ColumnHeader,0)),"Actual","Estimate") -> Actual | N30: =IFERROR(INDEX(INDIRECT(E30),0,MATCH(F30,MO_Common_ColumnHeader,0)),"N/A") -> 7516 | P30: =IF(ISNUMBER(N30),N30-K30,"N/A") -> -134 | Q30: =IFERROR(IF(ISNUMBER(N30),(N30-K30)/ABS(K30),"N/A"),"N/A") -> -0.01751634 | S30: 45853 | T30: Investor Presentation
A31: 263 | B31: =IF(INDEX(MO_SNA_IsHistoricalPeriod,,MATCH(F31,MO_Common_ColumnHeader,0)),"Historical","Forward") -> Historical | D31: Installed Base Management sales | E31: z_I9KH3H0125_MO_OS_Netserviceandfieldoptionsales | F31: Q3-2025 | I31: 2000 | J31: 2000 | K31: =AVERAGE(I31:J31) -> 2000 | M31: =IF(INDEX(MO_SNA_IsHistoricalPeriod,,MATCH(F31,MO_Common_ColumnHeader,0)),"Actual","Estimate") -> Actual | N31: =IFERROR(INDEX(INDIRECT(E31),0,MATCH(F31,MO_Common_ColumnHeader,0)),"N/A") -> 1962.2 | P31: =IF(ISNUMBER(N31),N31-K31,"N/A") -> -37.8 | Q31: =IFERROR(IF(ISNUMBER(N31),(N31-K31)/ABS(K31),"N/A"),"N/A") -> -0.0189 | S31: 45853 | T31: Investor Presentation
A32: 262 | B32: =IF(INDEX(MO_SNA_IsHistoricalPeriod,,MATCH(F32,MO_Common_ColumnHeader,0)),"Historical","Forward") -> Historical | D32: =INDEX(INDIRECT(E32),0,COLUMN(MO_Common_Column_A)) -> Gross Margin, % | E32: MO_MA_GM | F32: Q3-2025 | I32: 0.5 | J32: 0.52 | K32: =AVERAGE(I32:J32) -> 0.51 | M32: =IF(INDEX(MO_SNA_IsHistoricalPeriod,,MATCH(F32,MO_Common_ColumnHeader,0)),"Actual","Estimate") -> Actual | N32: =IFERROR(INDEX(INDIRECT(E32),0,MATCH(F32,MO_Common_ColumnHeader,0)),"N/A") -> 0.51627195 | P32: =IF(ISNUMBER(N32),N32-K32,"N/A") -> 0.0062719532 | Q32: =IFERROR(IF(ISNUMBER(N32),(N32-K32)/ABS(K32),"N/A"),"N/A") -> 0.012297947 | S32: 45853 | T32: Investor Presentation
A33: 261 | B33: =IF(INDEX(MO_SNA_IsHistoricalPeriod,,MATCH(F33,MO_Common_ColumnHeader,0)),"Historical","Forward") -> Historical | D33: R&D Expense | E33: MO_RIS_RD | F33: Q3-2025 | I33: 1200 | J33: 1200 | K33: =AVERAGE(I33:J33) -> 1200 | M33: =IF(INDEX(MO_SNA_IsHistoricalPeriod,,MATCH(F33,MO_Common_ColumnHeader,0)),"Actual","Estimate") -> Actual | N33: =IFERROR(INDEX(INDIRECT(E33),0,MATCH(F33,MO_Common_ColumnHeader,0)),"N/A") -> 1108.7 | P33: =IF(ISNUMBER(N33),N33-K33,"N/A") -> -91.3 | Q33: =IFERROR(IF(ISNUMBER(N33),(N33-K33)/ABS(K33),"N/A"),"N/A") -> -0.076083333 | S33: 45853 | T33: Investor Presentation
A34: 260 | B34: =IF(INDEX(MO_SNA_IsHistoricalPeriod,,MATCH(F34,MO_Common_ColumnHeader,0)),"Historical","Forward") -> Historical | D34: =INDEX(INDIRECT(E34),0,COLUMN(MO_Common_Column_A)) -> SG&A | E34: MO_RIS_SGA | F34: Q3-2025 | I34: 310 | J34: 310 | K34: =AVERAGE(I34:J34) -> 310 | M34: =IF(INDEX(MO_SNA_IsHistoricalPeriod,,MATCH(F34,MO_Common_ColumnHeader,0)),"Actual","Estimate") -> Actual | N34: =IFERROR(INDEX(INDIRECT(E34),0,MATCH(F34,MO_Common_ColumnHeader,0)),"N/A") -> 303.2 | P34: =IF(ISNUMBER(N34),N34-K34,"N/A") -> -6.8 | Q34: =IFERROR(IF(ISNUMBER(N34),(N34-K34)/ABS(K34),"N/A"),"N/A") -> -0.021935484 | S34: 45853 | T34: Investor Presentation
A35: 259
A36: 258 | B36: =IF(INDEX(MO_SNA_IsHistoricalPeriod,,MATCH(F36,MO_Common_ColumnHeader,0)),"Historical","Forward") -> Historical | D36: =INDEX(INDIRECT(E36),0,COLUMN(MO_Common_Column_A)) -> Net Revenue | E36: MO_RIS_REV | F36: FY2025 | I36: 30000 | J36: 35000 | K36: =AVERAGE(I36:J36) -> 32500 | M36: =IF(INDEX(MO_SNA_IsHistoricalPeriod,,MATCH(F36,MO_Common_ColumnHeader,0)),"Actual","Estimate") -> Actual | N36: =IFERROR(INDEX(INDIRECT(E36),0,MATCH(F36,MO_Common_ColumnHeader,0)),"N/A") -> 32667.3 | P36: =IF(ISNUMBER(N36),N36-K36,"N/A") -> 167.3 | Q36: =IFERROR(IF(ISNUMBER(N36),(N36-K36)/ABS(K36),"N/A"),"N/A") -> 0.0051476923 | S36: 45762 | T36: Investor Presentation
A37: 257 | B37: =IF(INDEX(MO_SNA_IsHistoricalPeriod,,MATCH(F37,MO_Common_ColumnHeader,0)),"Historical","Forward") -> Historical | D37: =INDEX(INDIRECT(E37),0,COLUMN(MO_Common_Column_A)) -> Gross Margin, % | E37: MO_MA_GM | F37: FY2025 | I37: 0.51 | J37: 0.53 | K37: =AVERAGE(I37:J37) -> 0.52 | M37: =IF(INDEX(MO_SNA_IsHistoricalPeriod,,MATCH(F37,MO_Common_ColumnHeader,0)),"Actual","Estimate") -> Actual | N37: =IFERROR(INDEX(INDIRECT(E37),0,MATCH(F37,MO_Common_ColumnHeader,0)),"N/A") -> 0.52829588 | P37: =IF(ISNUMBER(N37),N37-K37,"N/A") -> 0.00829588 | Q37: =IFERROR(IF(ISNUMBER(N37),(N37-K37)/ABS(K37),"N/A"),"N/A") -> 0.015953615 | S37: 45762 | T37: Investor Presentation
A38: 256 | B38: =IF(INDEX(MO_SNA_IsHistoricalPeriod,,MATCH(F38,MO_Common_ColumnHeader,0)),"Historical","Forward") -> Historical | D38: Effective tax rate | F38: FY2025 | I38: 0.17 | J38: 0.17 | K38: =AVERAGE(I38:J38) -> 0.17 | M38: =IF(INDEX(MO_SNA_IsHistoricalPeriod,,MATCH(F38,MO_Common_ColumnHeader,0)),"Actual","Estimate") -> Actual | N38: =INDEX(MO_RIS_TaxRate_Current,0,MATCH(F38,MO_Common_ColumnHeader,0))+INDEX(MO_RIS_TaxRate_Deferred,0,MATCH(F38,MO_Common_ColumnHeader,0)) -> 0.17322848 | P38: =IF(ISNUMBER(N38),N38-K38,"N/A") -> 0.0032284819 | Q38: =IFERROR(IF(ISNUMBER(N38),(N38-K38)/ABS(K38),"N/A"),"N/A") -> 0.01899107 | S38: 45762 | T38: Investor Presentation
A39: 255
A40: 254 | B40: =IF(INDEX(MO_SNA_IsHistoricalPeriod,,MATCH(F40,MO_Common_ColumnHeader,0)),"Historical","Forward") -> Historical | D40: =INDEX(INDIRECT(E40),0,COLUMN(MO_Common_Column_A)) -> Net Revenue | E40: MO_RIS_REV | F40: Q2-2025 | I40: 7200 | J40: 7700 | K40: =AVERAGE(I40:J40) -> 7450 | M40: =IF(INDEX(MO_SNA_IsHistoricalPeriod,,MATCH(F40,MO_Common_ColumnHeader,0)),"Actual","Estimate") -> Actual | N40: =IFERROR(INDEX(INDIRECT(E40),0,MATCH(F40,MO_Common_ColumnHeader,0)),"N/A") -> 7691.7 | P40: =IF(ISNUMBER(N40),N40-K40,"N/A") -> 241.7 | Q40: =IFERROR(IF(ISNUMBER(N40),(N40-K40)/ABS(K40),"N/A"),"N/A") -> 0.032442953 | S40: 45762 | T40: Investor Presentation
A41: 253 | B41: =IF(INDEX(MO_SNA_IsHistoricalPeriod,,MATCH(F41,MO_Common_ColumnHeader,0)),"Historical","Forward") -> Historical | D41: Installed Base Management sales | E41: z_I9KH3H0125_MO_OS_Netserviceandfieldoptionsales | F41: Q2-2025 | I41: 2000 | J41: 2000 | K41: =AVERAGE(I41:J41) -> 2000 | M41: =IF(INDEX(MO_SNA_IsHistoricalPeriod,,MATCH(F41,MO_Common_ColumnHeader,0)),"Actual","Estimate") -> Actual | N41: =IFERROR(INDEX(INDIRECT(E41),0,MATCH(F41,MO_Common_ColumnHeader,0)),"N/A") -> 2095.6 | P41: =IF(ISNUMBER(N41),N41-K41,"N/A") -> 95.6 | Q41: =IFERROR(IF(ISNUMBER(N41),(N41-K41)/ABS(K41),"N/A"),"N/A") -> 0.0478 | S41: 45762 | T41: Investor Presentation
A42: 252 | B42: =IF(INDEX(MO_SNA_IsHistoricalPeriod,,MATCH(F42,MO_Common_ColumnHeader,0)),"Historical","Forward") -> Historical | D42: =INDEX(INDIRECT(E42),0,COLUMN(MO_Common_Column_A)) -> Gross Margin, % | E42: MO_MA_GM | F42: Q2-2025 | I42: 0.5 | J42: 0.53 | K42: =AVERAGE(I42:J42) -> 0.515 | M42: =IF(INDEX(MO_SNA_IsHistoricalPeriod,,MATCH(F42,MO_Common_ColumnHeader,0)),"Actual","Estimate") -> Actual | N42: =IFERROR(INDEX(INDIRECT(E42),0,MATCH(F42,MO_Common_ColumnHeader,0)),"N/A") -> 0.53687741 | P42: =IF(ISNUMBER(N42),N42-K42,"N/A") -> 0.021877413 | Q42: =IFERROR(IF(ISNUMBER(N42),(N42-K42)/ABS(K42),"N/A"),"N/A") -> 0.042480414 | S42: 45762 | T42: Investor Presentation
A43: 251 | B43: =IF(INDEX(MO_SNA_IsHistoricalPeriod,,MATCH(F43,MO_Common_ColumnHeader,0)),"Historical","Forward") -> Historical | D43: R&D Expense | E43: MO_RIS_RD | F43: Q2-2025 | I43: 1200 | J43: 1200 | K43: =AVERAGE(I43:J43) -> 1200 | M43: =IF(INDEX(MO_SNA_IsHistoricalPeriod,,MATCH(F43,MO_Common_ColumnHeader,0)),"Actual","Estimate") -> Actual | N43: =IFERROR(INDEX(INDIRECT(E43),0,MATCH(F43,MO_Common_ColumnHeader,0)),"N/A") -> 1166.7 | P43: =IF(ISNUMBER(N43),N43-K43,"N/A") -> -33.3 | Q43: =IFERROR(IF(ISNUMBER(N43),(N43-K43)/ABS(K43),"N/A"),"N/A") -> -0.02775 | S43: 45762 | T43: Investor Presentation
A44: 250 | B44: =IF(INDEX(MO_SNA_IsHistoricalPeriod,,MATCH(F44,MO_Common_ColumnHeader,0)),"Historical","Forward") -> Historical | D44: =INDEX(INDIRECT(E44),0,COLUMN(MO_Common_Column_A)) -> SG&A | E44: MO_RIS_SGA | F44: Q2-2025 | I44: 300 | J44: 300 | K44: =AVERAGE(I44:J44) -> 300 | M44: =IF(INDEX(MO_SNA_IsHistoricalPeriod,,MATCH(F44,MO_Common_ColumnHeader,0)),"Actual","Estimate") -> Actual | N44: =IFERROR(INDEX(INDIRECT(E44),0,MATCH(F44,MO_Common_ColumnHeader,0)),"N/A") -> 298.7 | P44: =IF(ISNUMBER(N44),N44-K44,"N/A") -> -1.3 | Q44: =IFERROR(IF(ISNUMBER(N44),(N44-K44)/ABS(K44),"N/A"),"N/A") -> -0.0043333333 | S44: 45762 | T44: Investor Presentation
A45: 249
A46: 248 | B46: =IF(INDEX(MO_SNA_IsHistoricalPeriod,,MATCH(F46,MO_Common_ColumnHeader,0)),"Historical","Forward") -> Historical | D46: =INDEX(INDIRECT(E46),0,COLUMN(MO_Common_Column_A)) -> Net Revenue | E46: MO_RIS_REV | F46: FY2025 | I46: 30000 | J46: 35000 | K46: =AVERAGE(I46:J46) -> 32500 | M46: =IF(INDEX(MO_SNA_IsHistoricalPeriod,,MATCH(F46,MO_Common_ColumnHeader,0)),"Actual","Estimate") -> Actual | N46: =IFERROR(INDEX(INDIRECT(E46),0,MATCH(F46,MO_Common_ColumnHeader,0)),"N/A") -> 32667.3 | P46: =IF(ISNUMBER(N46),N46-K46,"N/A") -> 167.3 | Q46: =IFERROR(IF(ISNUMBER(N46),(N46-K46)/ABS(K46),"N/A"),"N/A") -> 0.0051476923 | S46: 45686 | T46: Investor Presentation
A47: 247 | B47: =IF(INDEX(MO_SNA_IsHistoricalPeriod,,MATCH(F47,MO_Common_ColumnHeader,0)),"Historical","Forward") -> Historical | D47: =INDEX(INDIRECT(E47),0,COLUMN(MO_Common_Column_A)) -> Gross Margin, % | E47: MO_MA_GM | F47: FY2025 | I47: 0.51 | J47: 0.53 | K47: =AVERAGE(I47:J47) -> 0.52 | M47: =IF(INDEX(MO_SNA_IsHistoricalPeriod,,MATCH(F47,MO_Common_ColumnHeader,0)),"Actual","Estimate") -> Actual | N47: =IFERROR(INDEX(INDIRECT(E47),0,MATCH(F47,MO_Common_ColumnHeader,0)),"N/A") -> 0.52829588 | P47: =IF(ISNUMBER(N47),N47-K47,"N/A") -> 0.00829588 | Q47: =IFERROR(IF(ISNUMBER(N47),(N47-K47)/ABS(K47),"N/A"),"N/A") -> 0.015953615 | S47: 45686 | T47: Investor Presentation
A48: 246 | B48: =IF(INDEX(MO_SNA_IsHistoricalPeriod,,MATCH(F48,MO_Common_ColumnHeader,0)),"Historical","Forward") -> Historical | D48: Effective tax rate | F48: FY2025 | I48: 0.17 | J48: 0.17 | K48: =AVERAGE(I48:J48) -> 0.17 | M48: =IF(INDEX(MO_SNA_IsHistoricalPeriod,,MATCH(F48,MO_Common_ColumnHeader,0)),"Actual","Estimate") -> Actual | N48: =INDEX(MO_RIS_TaxRate_Current,0,MATCH(F48,MO_Common_ColumnHeader,0))+INDEX(MO_RIS_TaxRate_Deferred,0,MATCH(F48,MO_Common_ColumnHeader,0)) -> 0.17322848 | P48: =IF(ISNUMBER(N48),N48-K48,"N/A") -> 0.0032284819 | Q48: =IFERROR(IF(ISNUMBER(N48),(N48-K48)/ABS(K48),"N/A"),"N/A") -> 0.01899107 | S48: 45686 | T48: Investor Presentation
A49: 245
A50: 244 | B50: =IF(INDEX(MO_SNA_IsHistoricalPeriod,,MATCH(F50,MO_Common_ColumnHeader,0)),"Historical","Forward") -> Historical | D50: =INDEX(INDIRECT(E50),0,COLUMN(MO_Common_Column_A)) -> Net Revenue | E50: MO_RIS_REV | F50: Q1-2025 | I50: 7500 | J50: 8000 | K50: =AVERAGE(I50:J50) -> 7750 | M50: =IF(INDEX(MO_SNA_IsHistoricalPeriod,,MATCH(F50,MO_Common_ColumnHeader,0)),"Actual","Estimate") -> Actual | N50: =IFERROR(INDEX(INDIRECT(E50),0,MATCH(F50,MO_Common_ColumnHeader,0)),"N/A") -> 7741.5 | P50: =IF(ISNUMBER(N50),N50-K50,"N/A") -> -8.5 | Q50: =IFERROR(IF(ISNUMBER(N50),(N50-K50)/ABS(K50),"N/A"),"N/A") -> -0.0010967742 | S50: 45686 | T50: Investor Presentation
A51: 243 | B51: =IF(INDEX(MO_SNA_IsHistoricalPeriod,,MATCH(F51,MO_Common_ColumnHeader,0)),"Historical","Forward") -> Historical | D51: Installed Base Management sales | E51: z_I9KH3H0125_MO_OS_Netserviceandfieldoptionsales | F51: Q1-2025 | I51: 2100 | J51: 2100 | K51: =AVERAGE(I51:J51) -> 2100 | M51: =IF(INDEX(MO_SNA_IsHistoricalPeriod,,MATCH(F51,MO_Common_ColumnHeader,0)),"Actual","Estimate") -> Actual | N51: =IFERROR(INDEX(INDIRECT(E51),0,MATCH(F51,MO_Common_ColumnHeader,0)),"N/A") -> 2001.1 | P51: =IF(ISNUMBER(N51),N51-K51,"N/A") -> -98.9 | Q51: =IFERROR(IF(ISNUMBER(N51),(N51-K51)/ABS(K51),"N/A"),"N/A") -> -0.047095238 | S51: 45686 | T51: Investor Presentation
A52: 242 | B52: =IF(INDEX(MO_SNA_IsHistoricalPeriod,,MATCH(F52,MO_Common_ColumnHeader,0)),"Historical","Forward") -> Historical | D52: =INDEX(INDIRECT(E52),0,COLUMN(MO_Common_Column_A)) -> Gross Margin, % | E52: MO_MA_GM | F52: Q1-2025 | I52: 0.52 | J52: 0.53 | K52: =AVERAGE(I52:J52) -> 0.525 | M52: =IF(INDEX(MO_SNA_IsHistoricalPeriod,,MATCH(F52,MO_Common_ColumnHeader,0)),"Actual","Estimate") -> Actual | N52: =IFERROR(INDEX(INDIRECT(E52),0,MATCH(F52,MO_Common_ColumnHeader,0)),"N/A") -> 0.53990829 | P52: =IF(ISNUMBER(N52),N52-K52,"N/A") -> 0.014908287 | Q52: =IFERROR(IF(ISNUMBER(N52),(N52-K52)/ABS(K52),"N/A"),"N/A") -> 0.028396736 | S52: 45686 | T52: Investor Presentation
A53: 241 | B53: =IF(INDEX(MO_SNA_IsHistoricalPeriod,,MATCH(F53,MO_Common_ColumnHeader,0)),"Historical","Forward") -> Historical | D53: R&D Expense | E53: MO_RIS_RD | F53: Q1-2025 | I53: 1140 | J53: 1140 | K53: =AVERAGE(I53:J53) -> 1140 | M53: =IF(INDEX(MO_SNA_IsHistoricalPeriod,,MATCH(F53,MO_Common_ColumnHeader,0)),"Actual","Estimate") -> Actual | N53: =IFERROR(INDEX(INDIRECT(E53),0,MATCH(F53,MO_Common_ColumnHeader,0)),"N/A") -> 1161.1 | P53: =IF(ISNUMBER(N53),N53-K53,"N/A") -> 21.1 | Q53: =IFERROR(IF(ISNUMBER(N53),(N53-K53)/ABS(K53),"N/A"),"N/A") -> 0.018508772 | S53: 45686 | T53: Investor Presentation
A54: 240 | B54: =IF(INDEX(MO_SNA_IsHistoricalPeriod,,MATCH(F54,MO_Common_ColumnHeader,0)),"Historical","Forward") -> Historical | D54: =INDEX(INDIRECT(E54),0,COLUMN(MO_Common_Column_A)) -> SG&A | E54: MO_RIS_SGA | F54: Q1-2025 | I54: 290 | J54: 290 | K54: =AVERAGE(I54:J54) -> 290 | M54: =IF(INDEX(MO_SNA_IsHistoricalPeriod,,MATCH(F54,MO_Common_ColumnHeader,0)),"Actual","Estimate") -> Actual | N54: =IFERROR(INDEX(INDIRECT(E54),0,MATCH(F54,MO_Common_ColumnHeader,0)),"N/A") -> 280.7 | P54: =IF(ISNUMBER(N54),N54-K54,"N/A") -> -9.3 | Q54: =IFERROR(IF(ISNUMBER(N54),(N54-K54)/ABS(K54),"N/A"),"N/A") -> -0.032068966 | S54: 45686 | T54: Investor Presentation
A55: 239
A56: 238 | B56: =IF(INDEX(MO_SNA_IsHistoricalPeriod,,MATCH(F56,MO_Common_ColumnHeader,0)),"Historical","Forward") -> Historical | D56: =INDEX(INDIRECT(E56),0,COLUMN(MO_Common_Column_A)) -> Net Revenue | E56: MO_RIS_REV | F56: FY2024 | I56: 28000 | J56: 28000 | K56: =AVERAGE(I56:J56) -> 28000 | M56: =IF(INDEX(MO_SNA_IsHistoricalPeriod,,MATCH(F56,MO_Common_ColumnHeader,0)),"Actual","Estimate") -> Actual | N56: =IFERROR(INDEX(INDIRECT(E56),0,MATCH(F56,MO_Common_ColumnHeader,0)),"N/A") -> 28262.9 | P56: =IF(ISNUMBER(N56),N56-K56,"N/A") -> 262.9 | Q56: =IFERROR(IF(ISNUMBER(N56),(N56-K56)/ABS(K56),"N/A"),"N/A") -> 0.0093892857 | S56: 45580 | T56: Investor Presentation
A57: 237 | B57: =IF(INDEX(MO_SNA_IsHistoricalPeriod,,MATCH(F57,MO_Common_ColumnHeader,0)),"Historical","Forward") -> Historical | D57: =INDEX(INDIRECT(E57),0,COLUMN(MO_Common_Column_A)) -> Gross Margin, % | E57: MO_MA_GM | F57: FY2024 | I57: 0.506 | J57: 0.506 | K57: =AVERAGE(I57:J57) -> 0.506 | M57: =IF(INDEX(MO_SNA_IsHistoricalPeriod,,MATCH(F57,MO_Common_ColumnHeader,0)),"Actual","Estimate") -> Actual | N57: =IFERROR(INDEX(INDIRECT(E57),0,MATCH(F57,MO_Common_ColumnHeader,0)),"N/A") -> 0.51275701 | P57: =IF(ISNUMBER(N57),N57-K57,"N/A") -> 0.0067570065 | Q57: =IFERROR(IF(ISNUMBER(N57),(N57-K57)/ABS(K57),"N/A"),"N/A") -> 0.013353768 | S57: 45580 | T57: Investor Presentation
A58: 236 | B58: =IF(INDEX(MO_SNA_IsHistoricalPeriod,,MATCH(F58,MO_Common_ColumnHeader,0)),"Historical","Forward") -> Historical | D58: Effective tax rate | F58: FY2024 | I58: 0.16 | J58: 0.17 | K58: =AVERAGE(I58:J58) -> 0.165 | M58: =IF(INDEX(MO_SNA_IsHistoricalPeriod,,MATCH(F58,MO_Common_ColumnHeader,0)),"Actual","Estimate") -> Actual | N58: =INDEX(MO_RIS_TaxRate_Current,0,MATCH(F58,MO_Common_ColumnHeader,0))+INDEX(MO_RIS_TaxRate_Deferred,0,MATCH(F58,MO_Common_ColumnHeader,0)) -> 0.18164328 | P58: =IF(ISNUMBER(N58),N58-K58,"N/A") -> 0.016643285 | Q58: =IFERROR(IF(ISNUMBER(N58),(N58-K58)/ABS(K58),"N/A"),"N/A") -> 0.10086839 | S58: 45580 | T58: Investor Presentation
A59: 235
A60: 234 | B60: =IF(INDEX(MO_SNA_IsHistoricalPeriod,,MATCH(F60,MO_Common_ColumnHeader,0)),"Historical","Forward") -> Historical | D60: =INDEX(INDIRECT(E60),0,COLUMN(MO_Common_Column_A)) -> Net Revenue | E60: MO_RIS_REV | F60: Q4-2024 | I60: 8800 | J60: 9200 | K60: =AVERAGE(I60:J60) -> 9000 | M60: =IF(INDEX(MO_SNA_IsHistoricalPeriod,,MATCH(F60,MO_Common_ColumnHeader,0)),"Actual","Estimate") -> Actual | N60: =IFERROR(INDEX(INDIRECT(E60),0,MATCH(F60,MO_Common_ColumnHeader,0)),"N/A") -> 9262.8 | P60: =IF(ISNUMBER(N60),N60-K60,"N/A") -> 262.8 | Q60: =IFERROR(IF(ISNUMBER(N60),(N60-K60)/ABS(K60),"N/A"),"N/A") -> 0.0292 | S60: 45580 | T60: Investor Presentation
A61: 233 | B61: =IF(INDEX(MO_SNA_IsHistoricalPeriod,,MATCH(F61,MO_Common_ColumnHeader,0)),"Historical","Forward") -> Historical | D61: Installed Base Management sales | E61: z_I9KH3H0125_MO_OS_Netserviceandfieldoptionsales | F61: Q4-2024 | I61: 1900 | J61: 1900 | K61: =AVERAGE(I61:J61) -> 1900 | M61: =IF(INDEX(MO_SNA_IsHistoricalPeriod,,MATCH(F61,MO_Common_ColumnHeader,0)),"Actual","Estimate") -> Actual | N61: =IFERROR(INDEX(INDIRECT(E61),0,MATCH(F61,MO_Common_ColumnHeader,0)),"N/A") -> 2146.9 | P61: =IF(ISNUMBER(N61),N61-K61,"N/A") -> 246.9 | Q61: =IFERROR(IF(ISNUMBER(N61),(N61-K61)/ABS(K61),"N/A"),"N/A") -> 0.12994737 | S61: 45580 | T61: Investor Presentation
A62: 232 | B62: =IF(INDEX(MO_SNA_IsHistoricalPeriod,,MATCH(F62,MO_Common_ColumnHeader,0)),"Historical","Forward") -> Historical | D62: =INDEX(INDIRECT(E62),0,COLUMN(MO_Common_Column_A)) -> Gross Margin, % | E62: MO_MA_GM | F62: Q4-2024 | I62: 0.49 | J62: 0.5 | K62: =AVERAGE(I62:J62) -> 0.495 | M62: =IF(INDEX(MO_SNA_IsHistoricalPeriod,,MATCH(F62,MO_Common_ColumnHeader,0)),"Actual","Estimate") -> Actual | N62: =IFERROR(INDEX(INDIRECT(E62),0,MATCH(F62,MO_Common_ColumnHeader,0)),"N/A") -> 0.51710066 | P62: =IF(ISNUMBER(N62),N62-K62,"N/A") -> 0.022100661 | Q62: =IFERROR(IF(ISNUMBER(N62),(N62-K62)/ABS(K62),"N/A"),"N/A") -> 0.044647799 | S62: 45580 | T62: Investor Presentation
A63: 231 | B63: =IF(INDEX(MO_SNA_IsHistoricalPeriod,,MATCH(F63,MO_Common_ColumnHeader,0)),"Historical","Forward") -> Historical | D63: R&D Expense | E63: MO_RIS_RD | F63: Q4-2024 | I63: 1090 | J63: 1090 | K63: =AVERAGE(I63:J63) -> 1090 | M63: =IF(INDEX(MO_SNA_IsHistoricalPeriod,,MATCH(F63,MO_Common_ColumnHeader,0)),"Actual","Estimate") -> Actual | N63: =IFERROR(INDEX(INDIRECT(E63),0,MATCH(F63,MO_Common_ColumnHeader,0)),"N/A") -> 1116 | P63: =IF(ISNUMBER(N63),N63-K63,"N/A") -> 26 | Q63: =IFERROR(IF(ISNUMBER(N63),(N63-K63)/ABS(K63),"N/A"),"N/A") -> 0.023853211 | S63: 45580 | T63: Investor Presentation
A64: 230 | B64: =IF(INDEX(MO_SNA_IsHistoricalPeriod,,MATCH(F64,MO_Common_ColumnHeader,0)),"Historical","Forward") -> Historical | D64: =INDEX(INDIRECT(E64),0,COLUMN(MO_Common_Column_A)) -> SG&A | E64: MO_RIS_SGA | F64: Q4-2024 | I64: 300 | J64: 300 | K64: =AVERAGE(I64:J64) -> 300 | M64: =IF(INDEX(MO_SNA_IsHistoricalPeriod,,MATCH(F64,MO_Common_ColumnHeader,0)),"Actual","Estimate") -> Actual | N64: =IFERROR(INDEX(INDIRECT(E64),0,MATCH(F64,MO_Common_ColumnHeader,0)),"N/A") -> 318.4 | P64: =IF(ISNUMBER(N64),N64-K64,"N/A") -> 18.4 | Q64: =IFERROR(IF(ISNUMBER(N64),(N64-K64)/ABS(K64),"N/A"),"N/A") -> 0.061333333 | S64: 45580 | T64: Investor Presentation
A65: 229
A66: 228 | B66: =IF(INDEX(MO_SNA_IsHistoricalPeriod,,MATCH(F66,MO_Common_ColumnHeader,0)),"Historical","Forward") -> Historical | D66: =INDEX(INDIRECT(E66),0,COLUMN(MO_Common_Column_A)) -> Y/Y Total revenue growth, % | E66: MO_GA_TotalRevenue | F66: FY2024 | I66: 0 | J66: 0 | K66: =AVERAGE(I66:J66) -> 0 | M66: =IF(INDEX(MO_SNA_IsHistoricalPeriod,,MATCH(F66,MO_Common_ColumnHeader,0)),"Actual","Estimate") -> Actual | N66: =IFERROR(INDEX(INDIRECT(E66),0,MATCH(F66,MO_Common_ColumnHeader,0)),"N/A") -> 0.025560172 | P66: =IF(ISNUMBER(N66),N66-K66,"N/A") -> 0.025560172 | Q66: =IFERROR(IF(ISNUMBER(N66),(N66-K66)/ABS(K66),"N/A"),"N/A") -> N/A | S66: 45490 | T66: Investor Presentation
A67: 227 | B67: =IF(INDEX(MO_SNA_IsHistoricalPeriod,,MATCH(F67,MO_Common_ColumnHeader,0)),"Historical","Forward") -> Historical | D67: Effective tax rate | F67: FY2024 | I67: 0.16 | J67: 0.17 | K67: =AVERAGE(I67:J67) -> 0.165 | M67: =IF(INDEX(MO_SNA_IsHistoricalPeriod,,MATCH(F67,MO_Common_ColumnHeader,0)),"Actual","Estimate") -> Actual | N67: =INDEX(MO_RIS_TaxRate_Current,0,MATCH(F67,MO_Common_ColumnHeader,0))+INDEX(MO_RIS_TaxRate_Deferred,0,MATCH(F67,MO_Common_ColumnHeader,0)) -> 0.18164328 | P67: =IF(ISNUMBER(N67),N67-K67,"N/A") -> 0.016643285 | Q67: =IFERROR(IF(ISNUMBER(N67),(N67-K67)/ABS(K67),"N/A"),"N/A") -> 0.10086839 | S67: 45490 | T67: Investor Presentation
A68: 226
A69: 225 | B69: =IF(INDEX(MO_SNA_IsHistoricalPeriod,,MATCH(F69,MO_Common_ColumnHeader,0)),"Historical","Forward") -> Historical | D69: =INDEX(INDIRECT(E69),0,COLUMN(MO_Common_Column_A)) -> Net Revenue | E69: MO_RIS_REV | F69: Q3-2024 | I69: 6700 | J69: 7300 | K69: =AVERAGE(I69:J69) -> 7000 | M69: =IF(INDEX(MO_SNA_IsHistoricalPeriod,,MATCH(F69,MO_Common_ColumnHeader,0)),"Actual","Estimate") -> Actual | N69: =IFERROR(INDEX(INDIRECT(E69),0,MATCH(F69,MO_Common_ColumnHeader,0)),"N/A") -> 7467.3 | P69: =IF(ISNUMBER(N69),N69-K69,"N/A") -> 467.3 | Q69: =IFERROR(IF(ISNUMBER(N69),(N69-K69)/ABS(K69),"N/A"),"N/A") -> 0.066757143 | S69: 45490 | T69: Investor Presentation
A70: 224 | B70: =IF(INDEX(MO_SNA_IsHistoricalPeriod,,MATCH(F70,MO_Common_ColumnHeader,0)),"Historical","Forward") -> Historical | D70: Installed Base Management sales | E70: z_I9KH3H0125_MO_OS_Netserviceandfieldoptionsales | F70: Q3-2024 | I70: 1400 | J70: 1400 | K70: =AVERAGE(I70:J70) -> 1400 | M70: =IF(INDEX(MO_SNA_IsHistoricalPeriod,,MATCH(F70,MO_Common_ColumnHeader,0)),"Actual","Estimate") -> Actual | N70: =IFERROR(INDEX(INDIRECT(E70),0,MATCH(F70,MO_Common_ColumnHeader,0)),"N/A") -> 1541.3 | P70: =IF(ISNUMBER(N70),N70-K70,"N/A") -> 141.3 | Q70: =IFERROR(IF(ISNUMBER(N70),(N70-K70)/ABS(K70),"N/A"),"N/A") -> 0.10092857 | S70: 45490 | T70: Investor Presentation
A71: 223 | B71: =IF(INDEX(MO_SNA_IsHistoricalPeriod,,MATCH(F71,MO_Common_ColumnHeader,0)),"Historical","Forward") -> Historical | D71: =INDEX(INDIRECT(E71),0,COLUMN(MO_Common_Column_A)) -> Gross Margin, % | E71: MO_MA_GM | F71: Q3-2024 | I71: 0.5 | J71: 0.51 | K71: =AVERAGE(I71:J71) -> 0.505 | M71: =IF(INDEX(MO_SNA_IsHistoricalPeriod,,MATCH(F71,MO_Common_ColumnHeader,0)),"Actual","Estimate") -> Actual | N71: =IFERROR(INDEX(INDIRECT(E71),0,MATCH(F71,MO_Common_ColumnHeader,0)),"N/A") -> 0.50800155 | P71: =IF(ISNUMBER(N71),N71-K71,"N/A") -> 0.0030015534 | Q71: =IFERROR(IF(ISNUMBER(N71),(N71-K71)/ABS(K71),"N/A"),"N/A") -> 0.0059436702 | S71: 45490 | T71: Investor Presentation
A72: 222 | B72: =IF(INDEX(MO_SNA_IsHistoricalPeriod,,MATCH(F72,MO_Common_ColumnHeader,0)),"Historical","Forward") -> Historical | D72: R&D Expense | E72: MO_RIS_RD | F72: Q3-2024 | I72: 1100 | J72: 1100 | K72: =AVERAGE(I72:J72) -> 1100 | M72: =IF(INDEX(MO_SNA_IsHistoricalPeriod,,MATCH(F72,MO_Common_ColumnHeader,0)),"Actual","Estimate") -> Actual | N72: =IFERROR(INDEX(INDIRECT(E72),0,MATCH(F72,MO_Common_ColumnHeader,0)),"N/A") -> 1055.2 | P72: =IF(ISNUMBER(N72),N72-K72,"N/A") -> -44.8 | Q72: =IFERROR(IF(ISNUMBER(N72),(N72-K72)/ABS(K72),"N/A"),"N/A") -> -0.040727273 | S72: 45490 | T72: Investor Presentation
A73: 221 | B73: =IF(INDEX(MO_SNA_IsHistoricalPeriod,,MATCH(F73,MO_Common_ColumnHeader,0)),"Historical","Forward") -> Historical | D73: =INDEX(INDIRECT(E73),0,COLUMN(MO_Common_Column_A)) -> SG&A | E73: MO_RIS_SGA | F73: Q3-2024 | I73: 295 | J73: 295 | K73: =AVERAGE(I73:J73) -> 295 | M73: =IF(INDEX(MO_SNA_IsHistoricalPeriod,,MATCH(F73,MO_Common_ColumnHeader,0)),"Actual","Estimate") -> Actual | N73: =IFERROR(INDEX(INDIRECT(E73),0,MATCH(F73,MO_Common_ColumnHeader,0)),"N/A") -> 297 | P73: =IF(ISNUMBER(N73),N73-K73,"N/A") -> 2 | Q73: =IFERROR(IF(ISNUMBER(N73),(N73-K73)/ABS(K73),"N/A"),"N/A") -> 0.006779661 | S73: 45490 | T73: Investor Presentation
A74: 220
A75: 219 | B75: =IF(INDEX(MO_SNA_IsHistoricalPeriod,,MATCH(F75,MO_Common_ColumnHeader,0)),"Historical","Forward") -> Historical | D75: =INDEX(INDIRECT(E75),0,COLUMN(MO_Common_Column_A)) -> Y/Y Total revenue growth, % | E75: MO_GA_TotalRevenue | F75: FY2024 | I75: 0 | J75: 0 | K75: =AVERAGE(I75:J75) -> 0 | M75: =IF(INDEX(MO_SNA_IsHistoricalPeriod,,MATCH(F75,MO_Common_ColumnHeader,0)),"Actual","Estimate") -> Actual | N75: =IFERROR(INDEX(INDIRECT(E75),0,MATCH(F75,MO_Common_ColumnHeader,0)),"N/A") -> 0.025560172 | P75: =IF(ISNUMBER(N75),N75-K75,"N/A") -> 0.025560172 | Q75: =IFERROR(IF(ISNUMBER(N75),(N75-K75)/ABS(K75),"N/A"),"N/A") -> N/A | S75: 45399 | T75: Investor Presentation
A76: 218 | B76: =IF(INDEX(MO_SNA_IsHistoricalPeriod,,MATCH(F76,MO_Common_ColumnHeader,0)),"Historical","Forward") -> Historical | D76: Effective tax rate | F76: FY2024 | I76: 0.16 | J76: 0.17 | K76: =AVERAGE(I76:J76) -> 0.165 | M76: =IF(INDEX(MO_SNA_IsHistoricalPeriod,,MATCH(F76,MO_Common_ColumnHeader,0)),"Actual","Estimate") -> Actual | N76: =INDEX(MO_RIS_TaxRate_Current,0,MATCH(F76,MO_Common_ColumnHeader,0))+INDEX(MO_RIS_TaxRate_Deferred,0,MATCH(F76,MO_Common_ColumnHeader,0)) -> 0.18164328 | P76: =IF(ISNUMBER(N76),N76-K76,"N/A") -> 0.016643285 | Q76: =IFERROR(IF(ISNUMBER(N76),(N76-K76)/ABS(K76),"N/A"),"N/A") -> 0.10086839 | S76: 45399 | T76: Investor Presentation
A77: 217
A78: 216 | B78: =IF(INDEX(MO_SNA_IsHistoricalPeriod,,MATCH(F78,MO_Common_ColumnHeader,0)),"Historical","Forward") -> Historical | D78: =INDEX(INDIRECT(E78),0,COLUMN(MO_Common_Column_A)) -> Net Revenue | E78: MO_RIS_REV | F78: Q2-2024 | I78: 5700 | J78: 6200 | K78: =AVERAGE(I78:J78) -> 5950 | M78: =IF(INDEX(MO_SNA_IsHistoricalPeriod,,MATCH(F78,MO_Common_ColumnHeader,0)),"Actual","Estimate") -> Actual | N78: =IFERROR(INDEX(INDIRECT(E78),0,MATCH(F78,MO_Common_ColumnHeader,0)),"N/A") -> 6242.8 | P78: =IF(ISNUMBER(N78),N78-K78,"N/A") -> 292.8 | Q78: =IFERROR(IF(ISNUMBER(N78),(N78-K78)/ABS(K78),"N/A"),"N/A") -> 0.049210084 | S78: 45399 | T78: Investor Presentation
A79: 215 | B79: =IF(INDEX(MO_SNA_IsHistoricalPeriod,,MATCH(F79,MO_Common_ColumnHeader,0)),"Historical","Forward") -> Historical | D79: Installed Base Management sales | E79: z_I9KH3H0125_MO_OS_Netserviceandfieldoptionsales | F79: Q2-2024 | I79: 1400 | J79: 1400 | K79: =AVERAGE(I79:J79) -> 1400 | M79: =IF(INDEX(MO_SNA_IsHistoricalPeriod,,MATCH(F79,MO_Common_ColumnHeader,0)),"Actual","Estimate") -> Actual | N79: =IFERROR(INDEX(INDIRECT(E79),0,MATCH(F79,MO_Common_ColumnHeader,0)),"N/A") -> 1481.9 | P79: =IF(ISNUMBER(N79),N79-K79,"N/A") -> 81.9 | Q79: =IFERROR(IF(ISNUMBER(N79),(N79-K79)/ABS(K79),"N/A"),"N/A") -> 0.0585 | S79: 45399 | T79: Investor Presentation
A80: 214 | B80: =IF(INDEX(MO_SNA_IsHistoricalPeriod,,MATCH(F80,MO_Common_ColumnHeader,0)),"Historical","Forward") -> Historical | D80: =INDEX(INDIRECT(E80),0,COLUMN(MO_Common_Column_A)) -> Gross Margin, % | E80: MO_MA_GM | F80: Q2-2024 | I80: 0.5 | J80: 0.51 | K80: =AVERAGE(I80:J80) -> 0.505 | M80: =IF(INDEX(MO_SNA_IsHistoricalPeriod,,MATCH(F80,MO_Common_ColumnHeader,0)),"Actual","Estimate") -> Actual | N80: =IFERROR(INDEX(INDIRECT(E80),0,MATCH(F80,MO_Common_ColumnHeader,0)),"N/A") -> 0.51454476 | P80: =IF(ISNUMBER(N80),N80-K80,"N/A") -> 0.0095447556 | Q80: =IFERROR(IF(ISNUMBER(N80),(N80-K80)/ABS(K80),"N/A"),"N/A") -> 0.018900506 | S80: 45399 | T80: Investor Presentation
A81: 213 | B81: =IF(INDEX(MO_SNA_IsHistoricalPeriod,,MATCH(F81,MO_Common_ColumnHeader,0)),"Historical","Forward") -> Historical | D81: R&D Expense | E81: MO_RIS_RD | F81: Q2-2024 | I81: 1070 | J81: 1070 | K81: =AVERAGE(I81:J81) -> 1070 | M81: =IF(INDEX(MO_SNA_IsHistoricalPeriod,,MATCH(F81,MO_Common_ColumnHeader,0)),"Actual","Estimate") -> Actual | N81: =IFERROR(INDEX(INDIRECT(E81),0,MATCH(F81,MO_Common_ColumnHeader,0)),"N/A") -> 1100.6 | P81: =IF(ISNUMBER(N81),N81-K81,"N/A") -> 30.6 | Q81: =IFERROR(IF(ISNUMBER(N81),(N81-K81)/ABS(K81),"N/A"),"N/A") -> 0.028598131 | S81: 45399 | T81: Investor Presentation
A82: 212 | B82: =IF(INDEX(MO_SNA_IsHistoricalPeriod,,MATCH(F82,MO_Common_ColumnHeader,0)),"Historical","Forward") -> Historical | D82: =INDEX(INDIRECT(E82),0,COLUMN(MO_Common_Column_A)) -> SG&A | E82: MO_RIS_SGA | F82: Q2-2024 | I82: 295 | J82: 295 | K82: =AVERAGE(I82:J82) -> 295 | M82: =IF(INDEX(MO_SNA_IsHistoricalPeriod,,MATCH(F82,MO_Common_ColumnHeader,0)),"Actual","Estimate") -> Actual | N82: =IFERROR(INDEX(INDIRECT(E82),0,MATCH(F82,MO_Common_ColumnHeader,0)),"N/A") -> 277 | P82: =IF(ISNUMBER(N82),N82-K82,"N/A") -> -18 | Q82: =IFERROR(IF(ISNUMBER(N82),(N82-K82)/ABS(K82),"N/A"),"N/A") -> -0.061016949 | S82: 45399 | T82: Investor Presentation
A83: 211
A84: 210 | B84: =IF(INDEX(MO_SNA_IsHistoricalPeriod,,MATCH(F84,MO_Common_ColumnHeader,0)),"Historical","Forward") -> Historical | D84: =INDEX(INDIRECT(E84),0,COLUMN(MO_Common_Column_A)) -> Y/Y Total revenue growth, % | E84: MO_GA_TotalRevenue | F84: FY2024 | I84: 0 | J84: 0 | K84: =AVERAGE(I84:J84) -> 0 | M84: =IF(INDEX(MO_SNA_IsHistoricalPeriod,,MATCH(F84,MO_Common_ColumnHeader,0)),"Actual","Estimate") -> Actual | N84: =IFERROR(INDEX(INDIRECT(E84),0,MATCH(F84,MO_Common_ColumnHeader,0)),"N/A") -> 0.025560172 | P84: =IF(ISNUMBER(N84),N84-K84,"N/A") -> 0.025560172 | Q84: =IFERROR(IF(ISNUMBER(N84),(N84-K84)/ABS(K84),"N/A"),"N/A") -> N/A | S84: 45315 | T84: Investor Presentation
A85: 209 | B85: =IF(INDEX(MO_SNA_IsHistoricalPeriod,,MATCH(F85,MO_Common_ColumnHeader,0)),"Historical","Forward") -> Historical | D85: Effective tax rate | F85: FY2024 | I85: 0.16 | J85: 0.17 | K85: =AVERAGE(I85:J85) -> 0.165 | M85: =IF(INDEX(MO_SNA_IsHistoricalPeriod,,MATCH(F85,MO_Common_ColumnHeader,0)),"Actual","Estimate") -> Actual | N85: =INDEX(MO_RIS_TaxRate_Current,0,MATCH(F85,MO_Common_ColumnHeader,0))+INDEX(MO_RIS_TaxRate_Deferred,0,MATCH(F85,MO_Common_ColumnHeader,0)) -> 0.18164328 | P85: =IF(ISNUMBER(N85),N85-K85,"N/A") -> 0.016643285 | Q85: =IFERROR(IF(ISNUMBER(N85),(N85-K85)/ABS(K85),"N/A"),"N/A") -> 0.10086839 | S85: 45315 | T85: Investor Presentation
A86: 208
A87: 207 | B87: =IF(INDEX(MO_SNA_IsHistoricalPeriod,,MATCH(F87,MO_Common_ColumnHeader,0)),"Historical","Forward") -> Historical | D87: =INDEX(INDIRECT(E87),0,COLUMN(MO_Common_Column_A)) -> Net Revenue | E87: MO_RIS_REV | F87: Q1-2024 | I87: 5000 | J87: 5500 | K87: =AVERAGE(I87:J87) -> 5250 | M87: =IF(INDEX(MO_SNA_IsHistoricalPeriod,,MATCH(F87,MO_Common_ColumnHeader,0)),"Actual","Estimate") -> Actual | N87: =IFERROR(INDEX(INDIRECT(E87),0,MATCH(F87,MO_Common_ColumnHeader,0)),"N/A") -> 5290 | P87: =IF(ISNUMBER(N87),N87-K87,"N/A") -> 40 | Q87: =IFERROR(IF(ISNUMBER(N87),(N87-K87)/ABS(K87),"N/A"),"N/A") -> 0.0076190476 | S87: 45315 | T87: Investor Presentation
A88: 206 | B88: =IF(INDEX(MO_SNA_IsHistoricalPeriod,,MATCH(F88,MO_Common_ColumnHeader,0)),"Historical","Forward") -> Historical | D88: Installed Base Management sales | E88: z_I9KH3H0125_MO_OS_Netserviceandfieldoptionsales | F88: Q1-2024 | I88: 1300 | J88: 1300 | K88: =AVERAGE(I88:J88) -> 1300 | M88: =IF(INDEX(MO_SNA_IsHistoricalPeriod,,MATCH(F88,MO_Common_ColumnHeader,0)),"Actual","Estimate") -> Actual | N88: =IFERROR(INDEX(INDIRECT(E88),0,MATCH(F88,MO_Common_ColumnHeader,0)),"N/A") -> 1324.1 | P88: =IF(ISNUMBER(N88),N88-K88,"N/A") -> 24.1 | Q88: =IFERROR(IF(ISNUMBER(N88),(N88-K88)/ABS(K88),"N/A"),"N/A") -> 0.018538462 | S88: 45315 | T88: Investor Presentation
A89: 205 | B89: =IF(INDEX(MO_SNA_IsHistoricalPeriod,,MATCH(F89,MO_Common_ColumnHeader,0)),"Historical","Forward") -> Historical | D89: =INDEX(INDIRECT(E89),0,COLUMN(MO_Common_Column_A)) -> Gross Margin, % | E89: MO_MA_GM | F89: Q1-2024 | I89: 0.48 | J89: 0.49 | K89: =AVERAGE(I89:J89) -> 0.485 | M89: =IF(INDEX(MO_SNA_IsHistoricalPeriod,,MATCH(F89,MO_Common_ColumnHeader,0)),"Actual","Estimate") -> Actual | N89: =IFERROR(INDEX(INDIRECT(E89),0,MATCH(F89,MO_Common_ColumnHeader,0)),"N/A") -> 0.50975425 | P89: =IF(ISNUMBER(N89),N89-K89,"N/A") -> 0.024754253 | Q89: =IFERROR(IF(ISNUMBER(N89),(N89-K89)/ABS(K89),"N/A"),"N/A") -> 0.051039698 | S89: 45315 | T89: Investor Presentation
A90: 204 | B90: =IF(INDEX(MO_SNA_IsHistoricalPeriod,,MATCH(F90,MO_Common_ColumnHeader,0)),"Historical","Forward") -> Historical | D90: R&D Expense | E90: MO_RIS_RD | F90: Q1-2024 | I90: 1070 | J90: 1070 | K90: =AVERAGE(I90:J90) -> 1070 | M90: =IF(INDEX(MO_SNA_IsHistoricalPeriod,,MATCH(F90,MO_Common_ColumnHeader,0)),"Actual","Estimate") -> Actual | N90: =IFERROR(INDEX(INDIRECT(E90),0,MATCH(F90,MO_Common_ColumnHeader,0)),"N/A") -> 1031.9 | P90: =IF(ISNUMBER(N90),N90-K90,"N/A") -> -38.1 | Q90: =IFERROR(IF(ISNUMBER(N90),(N90-K90)/ABS(K90),"N/A"),"N/A") -> -0.035607477 | S90: 45315 | T90: Investor Presentation
A91: 203 | B91: =IF(INDEX(MO_SNA_IsHistoricalPeriod,,MATCH(F91,MO_Common_ColumnHeader,0)),"Historical","Forward") -> Historical | D91: =INDEX(INDIRECT(E91),0,COLUMN(MO_Common_Column_A)) -> SG&A | E91: MO_RIS_SGA | F91: Q1-2024 | I91: 300 | J91: 300 | K91: =AVERAGE(I91:J91) -> 300 | M91: =IF(INDEX(MO_SNA_IsHistoricalPeriod,,MATCH(F91,MO_Common_ColumnHeader,0)),"Actual","Estimate") -> Actual | N91: =IFERROR(INDEX(INDIRECT(E91),0,MATCH(F91,MO_Common_ColumnHeader,0)),"N/A") -> 273.3 | P91: =IF(ISNUMBER(N91),N91-K91,"N/A") -> -26.7 | Q91: =IFERROR(IF(ISNUMBER(N91),(N91-K91)/ABS(K91),"N/A"),"N/A") -> -0.089 | S91: 45315 | T91: Investor Presentation
A92: 202
A93: 201 | B93: =IF(INDEX(MO_SNA_IsHistoricalPeriod,,MATCH(F93,MO_Common_ColumnHeader,0)),"Historical","Forward") -> Historical | D93: =INDEX(INDIRECT(E93),0,COLUMN(MO_Common_Column_A)) -> Y/Y Total revenue growth, % | E93: MO_GA_TotalRevenue | F93: FY2023 | I93: 0.3 | J93: 0.3 | K93: =AVERAGE(I93:J93) -> 0.3 | M93: =IF(INDEX(MO_SNA_IsHistoricalPeriod,,MATCH(F93,MO_Common_ColumnHeader,0)),"Actual","Estimate") -> Actual | N93: =IFERROR(INDEX(INDIRECT(E93),0,MATCH(F93,MO_Common_ColumnHeader,0)),"N/A") -> 0.30156234 | P93: =IF(ISNUMBER(N93),N93-K93,"N/A") -> 0.0015623377 | Q93: =IFERROR(IF(ISNUMBER(N93),(N93-K93)/ABS(K93),"N/A"),"N/A") -> 0.0052077922 | S93: 45217 | T93: Investor Presentation
A94: 200 | B94: =IF(INDEX(MO_SNA_IsHistoricalPeriod,,MATCH(F94,MO_Common_ColumnHeader,0)),"Historical","Forward") -> Historical | D94: Effective tax rate | F94: FY2023 | I94: 0.15 | J94: 0.16 | K94: =AVERAGE(I94:J94) -> 0.155 | M94: =IF(INDEX(MO_SNA_IsHistoricalPeriod,,MATCH(F94,MO_Common_ColumnHeader,0)),"Actual","Estimate") -> Actual | N94: =INDEX(MO_RIS_TaxRate_Current,0,MATCH(F94,MO_Common_ColumnHeader,0))+INDEX(MO_RIS_TaxRate_Deferred,0,MATCH(F94,MO_Common_ColumnHeader,0)) -> 0.15480657 | P94: =IF(ISNUMBER(N94),N94-K94,"N/A") -> -0.00019342735 | Q94: =IFERROR(IF(ISNUMBER(N94),(N94-K94)/ABS(K94),"N/A"),"N/A") -> -0.0012479184 | S94: 45217 | T94: Investor Presentation
A95: 199
A96: 198 | B96: =IF(INDEX(MO_SNA_IsHistoricalPeriod,,MATCH(F96,MO_Common_ColumnHeader,0)),"Historical","Forward") -> Historical | D96: =INDEX(INDIRECT(E96),0,COLUMN(MO_Common_Column_A)) -> Net Revenue | E96: MO_RIS_REV | F96: Q4-2023 | I96: 6700 | J96: 7100 | K96: =AVERAGE(I96:J96) -> 6900 | M96: =IF(INDEX(MO_SNA_IsHistoricalPeriod,,MATCH(F96,MO_Common_ColumnHeader,0)),"Actual","Estimate") -> Actual | N96: =IFERROR(INDEX(INDIRECT(E96),0,MATCH(F96,MO_Common_ColumnHeader,0)),"N/A") -> 7237 | P96: =IF(ISNUMBER(N96),N96-K96,"N/A") -> 337 | Q96: =IFERROR(IF(ISNUMBER(N96),(N96-K96)/ABS(K96),"N/A"),"N/A") -> 0.04884058 | S96: 45217 | T96: Investor Presentation
A97: 197 | B97: =IF(INDEX(MO_SNA_IsHistoricalPeriod,,MATCH(F97,MO_Common_ColumnHeader,0)),"Historical","Forward") -> Historical | D97: Installed Base Management sales | E97: z_I9KH3H0125_MO_OS_Netserviceandfieldoptionsales | F97: Q4-2023 | I97: 1400 | J97: 1400 | K97: =AVERAGE(I97:J97) -> 1400 | M97: =IF(INDEX(MO_SNA_IsHistoricalPeriod,,MATCH(F97,MO_Common_ColumnHeader,0)),"Actual","Estimate") -> Actual | N97: =IFERROR(INDEX(INDIRECT(E97),0,MATCH(F97,MO_Common_ColumnHeader,0)),"N/A") -> 1554.5 | P97: =IF(ISNUMBER(N97),N97-K97,"N/A") -> 154.5 | Q97: =IFERROR(IF(ISNUMBER(N97),(N97-K97)/ABS(K97),"N/A"),"N/A") -> 0.11035714 | S97: 45217 | T97: Investor Presentation
A98: 196 | B98: =IF(INDEX(MO_SNA_IsHistoricalPeriod,,MATCH(F98,MO_Common_ColumnHeader,0)),"Historical","Forward") -> Historical | D98: =INDEX(INDIRECT(E98),0,COLUMN(MO_Common_Column_A)) -> Gross Margin, % | E98: MO_MA_GM | F98: Q4-2023 | I98: 0.5 | J98: 0.51 | K98: =AVERAGE(I98:J98) -> 0.505 | M98: =IF(INDEX(MO_SNA_IsHistoricalPeriod,,MATCH(F98,MO_Common_ColumnHeader,0)),"Actual","Estimate") -> Actual | N98: =IFERROR(INDEX(INDIRECT(E98),0,MATCH(F98,MO_Common_ColumnHeader,0)),"N/A") -> 0.51365207 | P98: =IF(ISNUMBER(N98),N98-K98,"N/A") -> 0.0086520658 | Q98: =IFERROR(IF(ISNUMBER(N98),(N98-K98)/ABS(K98),"N/A"),"N/A") -> 0.017132804 | S98: 45217 | T98: Investor Presentation
A99: 195 | B99: =IF(INDEX(MO_SNA_IsHistoricalPeriod,,MATCH(F99,MO_Common_ColumnHeader,0)),"Historical","Forward") -> Historical | D99: R&D Expense | E99: MO_RIS_RD | F99: Q4-2023 | I99: 1030 | J99: 1030 | K99: =AVERAGE(I99:J99) -> 1030 | M99: =IF(INDEX(MO_SNA_IsHistoricalPeriod,,MATCH(F99,MO_Common_ColumnHeader,0)),"Actual","Estimate") -> Actual | N99: =IFERROR(INDEX(INDIRECT(E99),0,MATCH(F99,MO_Common_ColumnHeader,0)),"N/A") -> 1041.4 | P99: =IF(ISNUMBER(N99),N99-K99,"N/A") -> 11.4 | Q99: =IFERROR(IF(ISNUMBER(N99),(N99-K99)/ABS(K99),"N/A"),"N/A") -> 0.011067961 | S99: 45217 | T99: Investor Presentation
A100: 194 | B100: =IF(INDEX(MO_SNA_IsHistoricalPeriod,,MATCH(F100,MO_Common_ColumnHeader,0)),"Historical","Forward") -> Historical | D100: =INDEX(INDIRECT(E100),0,COLUMN(MO_Common_Column_A)) -> SG&A | E100: MO_RIS_SGA | F100: Q4-2023 | I100: 285 | J100: 285 | K100: =AVERAGE(I100:J100) -> 285 | M100: =IF(INDEX(MO_SNA_IsHistoricalPeriod,,MATCH(F100,MO_Common_ColumnHeader,0)),"Actual","Estimate") -> Actual | N100: =IFERROR(INDEX(INDIRECT(E100),0,MATCH(F100,MO_Common_ColumnHeader,0)),"N/A") -> 284 | P100: =IF(ISNUMBER(N100),N100-K100,"N/A") -> -1 | Q100: =IFERROR(IF(ISNUMBER(N100),(N100-K100)/ABS(K100),"N/A"),"N/A") -> -0.0035087719 | S100: 45217 | T100: Investor Presentation
A101: 193
...

Sheet Summary Page
A1: =MO.CompanyName -> ASML Holdings N.V. | C1: =INDEX(MO_Common_QEndDate,0,COLUMN()) -> 40178 | D1: =INDEX(MO_Common_QEndDate,0,COLUMN()) -> 40543 | E1: =INDEX(MO_Common_QEndDate,0,COLUMN()) -> 40908 | F1: =INDEX(MO_Common_QEndDate,0,COLUMN()) -> 41274 | G1: =INDEX(MO_Common_QEndDate,0,COLUMN()) -> 41639 | H1: =INDEX(MO_Common_QEndDate,0,COLUMN()) -> 41728 | I1: =INDEX(MO_Common_QEndDate,0,COLUMN()) -> 41819 | J1: =INDEX(MO_Common_QEndDate,0,COLUMN()) -> 41910 | ... CB1: =INDEX(MO_Common_QEndDate,0,COLUMN()) -> 47848
A2: Reports | B2: =MO.ReportFX -> EUR | C2: =INDEX(MO_Common_ColumnHeader,0,COLUMN()) -> FY2009 | D2: =INDEX(MO_Common_ColumnHeader,0,COLUMN()) -> FY2010 | E2: =INDEX(MO_Common_ColumnHeader,0,COLUMN()) -> FY2011 | F2: =INDEX(MO_Common_ColumnHeader,0,COLUMN()) -> FY2012 | G2: =INDEX(MO_Common_ColumnHeader,0,COLUMN()) -> FY2013 | H2: =INDEX(MO_Common_ColumnHeader,0,COLUMN()) -> Q1-2014 | I2: =INDEX(MO_Common_ColumnHeader,0,COLUMN()) -> Q2-2014 | J2: =INDEX(MO_Common_ColumnHeader,0,COLUMN()) -> Q3-2014 | ... CB2: =INDEX(MO_Common_ColumnHeader,0,COLUMN()) -> FY2030
A3: Capitalization Summary
A4: ="Stock Price - "&SP.ValuationToggle -> Stock Price - EoP | B4: EoP | C4: =IF(INDEX(MO_SNA_IsHistoricalPeriod,1,COLUMN())=FALSE(),MO.LastPrice/HP.MRFX,CHOOSE(VLOOKUP(SP.ValuationToggle,tb_ValuationToggle,COLUMNS(tb_ValuationToggle),FALSE()),INDEX(MO_SPT_StockHigh,1,COLUMN()),INDEX(MO_SPT_StockLow,1,COLUMN()),INDEX(MO_SPT_StockAverage,1,COLUMN()),INDEX(MO_SPT_StockEoP,1,COLUMN()))/IF(SP.ValuationToggle="EoP",IF(INDEX(MO_SPT_FXEoP,1,COLUMN())=0,1,INDEX(MO_SPT_FXEoP,1,COLUMN())),IF(INDEX(MO_SPT_FXAverage,1,COLUMN())=0,1,INDEX(MO_SPT_FXAverage,1,COLUMN())))) -> 31.103896 | D4: =IF(INDEX(MO_SNA_IsHistoricalPeriod,1,COLUMN())=FALSE(),MO.LastPrice/HP.MRFX,CHOOSE(VLOOKUP(SP.ValuationToggle,tb_ValuationToggle,COLUMNS(tb_ValuationToggle),FALSE()),INDEX(MO_SPT_StockHigh,1,COLUMN()),INDEX(MO_SPT_StockLow,1,COLUMN()),INDEX(MO_SPT_StockAverage,1,COLUMN()),INDEX(MO_SPT_StockEoP,1,COLUMN()))/IF(SP.ValuationToggle="EoP",IF(INDEX(MO_SPT_FXEoP,1,COLUMN())=0,1,INDEX(MO_SPT_FXEoP,1,COLUMN())),IF(INDEX(MO_SPT_FXAverage,1,COLUMN())=0,1,INDEX(MO_SPT_FXAverage,1,COLUMN())))) -> 37.668831 | E4: =IF(INDEX(MO_SNA_IsHistoricalPeriod,1,COLUMN())=FALSE(),MO.LastPrice/HP.MRFX,CHOOSE(VLOOKUP(SP.ValuationToggle,tb_ValuationToggle,COLUMNS(tb_ValuationToggle),FALSE()),INDEX(MO_SPT_StockHigh,1,COLUMN()),INDEX(MO_SPT_StockLow,1,COLUMN()),INDEX(MO_SPT_StockAverage,1,COLUMN()),INDEX(MO_SPT_StockEoP,1,COLUMN()))/IF(SP.ValuationToggle="EoP",IF(INDEX(MO_SPT_FXEoP,1,COLUMN())=0,1,INDEX(MO_SPT_FXEoP,1,COLUMN())),IF(INDEX(MO_SPT_FXAverage,1,COLUMN())=0,1,INDEX(MO_SPT_FXAverage,1,COLUMN())))) -> 42.175325 | F4: =IF(INDEX(MO_SNA_IsHistoricalPeriod,1,COLUMN())=FALSE(),MO.LastPrice/HP.MRFX,CHOOSE(VLOOKUP(SP.ValuationToggle,tb_ValuationToggle,COLUMNS(tb_ValuationToggle),FALSE()),INDEX(MO_SPT_StockHigh,1,COLUMN()),INDEX(MO_SPT_StockLow,1,COLUMN()),INDEX(MO_SPT_StockAverage,1,COLUMN()),INDEX(MO_SPT_StockEoP,1,COLUMN()))/IF(SP.ValuationToggle="EoP",IF(INDEX(MO_SPT_FXEoP,1,COLUMN())=0,1,INDEX(MO_SPT_FXEoP,1,COLUMN())),IF(INDEX(MO_SPT_FXAverage,1,COLUMN())=0,1,INDEX(MO_SPT_FXAverage,1,COLUMN())))) -> 47.885 | G4: =IF(INDEX(MO_SNA_IsHistoricalPeriod,1,COLUMN())=FALSE(),MO.LastPrice/HP.MRFX,CHOOSE(VLOOKUP(SP.ValuationToggle,tb_ValuationToggle,COLUMNS(tb_ValuationToggle),FALSE()),INDEX(MO_SPT_StockHigh,1,COLUMN()),INDEX(MO_SPT_StockLow,1,COLUMN()),INDEX(MO_SPT_StockAverage,1,COLUMN()),INDEX(MO_SPT_StockEoP,1,COLUMN()))/IF(SP.ValuationToggle="EoP",IF(INDEX(MO_SPT_FXEoP,1,COLUMN())=0,1,INDEX(MO_SPT_FXEoP,1,COLUMN())),IF(INDEX(MO_SPT_FXAverage,1,COLUMN())=0,1,INDEX(MO_SPT_FXAverage,1,COLUMN())))) -> 67.93 | H4: =IF(INDEX(MO_SNA_IsHistoricalPeriod,1,COLUMN())=FALSE(),MO.LastPrice/HP.MRFX,CHOOSE(VLOOKUP(SP.ValuationToggle,tb_ValuationToggle,COLUMNS(tb_ValuationToggle),FALSE()),INDEX(MO_SPT_StockHigh,1,COLUMN()),INDEX(MO_SPT_StockLow,1,COLUMN()),INDEX(MO_SPT_StockAverage,1,COLUMN()),INDEX(MO_SPT_StockEoP,1,COLUMN()))/IF(SP.ValuationToggle="EoP",IF(INDEX(MO_SPT_FXEoP,1,COLUMN())=0,1,INDEX(MO_SPT_FXEoP,1,COLUMN())),IF(INDEX(MO_SPT_FXAverage,1,COLUMN())=0,1,INDEX(MO_SPT_FXAverage,1,COLUMN())))) -> 67.15 | I4: =IF(INDEX(MO_SNA_IsHistoricalPeriod,1,COLUMN())=FALSE(),MO.LastPrice/HP.MRFX,CHOOSE(VLOOKUP(SP.ValuationToggle,tb_ValuationToggle,COLUMNS(tb_ValuationToggle),FALSE()),INDEX(MO_SPT_StockHigh,1,COLUMN()),INDEX(MO_SPT_StockLow,1,COLUMN()),INDEX(MO_SPT_StockAverage,1,COLUMN()),INDEX(MO_SPT_StockEoP,1,COLUMN()))/IF(SP.ValuationToggle="EoP",IF(INDEX(MO_SPT_FXEoP,1,COLUMN())=0,1,INDEX(MO_SPT_FXEoP,1,COLUMN())),IF(INDEX(MO_SPT_FXAverage,1,COLUMN())=0,1,INDEX(MO_SPT_FXAverage,1,COLUMN())))) -> 67.62 | J4: =IF(INDEX(MO_SNA_IsHistoricalPeriod,1,COLUMN())=FALSE(),MO.LastPrice/HP.MRFX,CHOOSE(VLOOKUP(SP.ValuationToggle,tb_ValuationToggle,COLUMNS(tb_ValuationToggle),FALSE()),INDEX(MO_SPT_StockHigh,1,COLUMN()),INDEX(MO_SPT_StockLow,1,COLUMN()),INDEX(MO_SPT_StockAverage,1,COLUMN()),INDEX(MO_SPT_StockEoP,1,COLUMN()))/IF(SP.ValuationToggle="EoP",IF(INDEX(MO_SPT_FXEoP,1,COLUMN())=0,1,INDEX(MO_SPT_FXEoP,1,COLUMN())),IF(INDEX(MO_SPT_FXAverage,1,COLUMN())=0,1,INDEX(MO_SPT_FXAverage,1,COLUMN())))) -> 78.56 | ... CB4: =IF(INDEX(MO_SNA_IsHistoricalPeriod,1,COLUMN())=FALSE(),MO.LastPrice/HP.MRFX,CHOOSE(VLOOKUP(SP.ValuationToggle,tb_ValuationToggle,COLUMNS(tb_ValuationToggle),FALSE()),INDEX(MO_SPT_StockHigh,1,COLUMN()),INDEX(MO_SPT_StockLow,1,COLUMN()),INDEX(MO_SPT_StockAverage,1,COLUMN()),INDEX(MO_SPT_StockEoP,1,COLUMN()))/IF(SP.ValuationToggle="EoP",IF(INDEX(MO_SPT_FXEoP,1,COLUMN())=0,1,INDEX(MO_SPT_FXEoP,1,COLUMN())),IF(INDEX(MO_SPT_FXAverage,1,COLUMN())=0,1,INDEX(MO_SPT_FXAverage,1,COLUMN())))) -> 1217.6
A5: =INDEX(MO_SCA_ShareCount_EoP_Diluted,0,COLUMN()) -> EoP Total Diluted Ordinary Shares Outstanding, mm shares | C5: =INDEX(MO_SCA_ShareCount_EoP_Diluted,0,COLUMN()) -> 433.63898 | D5: =INDEX(MO_SCA_ShareCount_EoP_Diluted,0,COLUMN()) -> 440.42097 | E5: =INDEX(MO_SCA_ShareCount_EoP_Diluted,0,COLUMN()) -> 417.10426 | F5: =INDEX(MO_SCA_ShareCount_EoP_Diluted,0,COLUMN()) -> 410.05522 | G5: =INDEX(MO_SCA_ShareCount_EoP_Diluted,0,COLUMN()) -> 444.52833 | H5: =INDEX(MO_SCA_ShareCount_EoP_Diluted,0,COLUMN()) -> 443.5 | I5: =INDEX(MO_SCA_ShareCount_EoP_Diluted,0,COLUMN()) -> 441.6 | J5: =INDEX(MO_SCA_ShareCount_EoP_Diluted,0,COLUMN()) -> 439 | ... CB5: =INDEX(MO_SCA_ShareCount_EoP_Diluted,0,COLUMN()) -> 389.57452
A6: ="Market Cap - "&SP.ValuationToggle -> Market Cap - EoP | C6: =INDEX(SP_CS_StockPrice,0,COLUMN())*INDEX(SP_CS_ShareCount_EoP_Diluted,0,COLUMN()) -> 13487.862 | D6: =INDEX(SP_CS_StockPrice,0,COLUMN())*INDEX(SP_CS_ShareCount_EoP_Diluted,0,COLUMN()) -> 16590.143 | E6: =INDEX(SP_CS_StockPrice,0,COLUMN())*INDEX(SP_CS_ShareCount_EoP_Diluted,0,COLUMN()) -> 17591.508 | F6: =INDEX(SP_CS_StockPrice,0,COLUMN())*INDEX(SP_CS_ShareCount_EoP_Diluted,0,COLUMN()) -> 19635.494 | G6: =INDEX(SP_CS_StockPrice,0,COLUMN())*INDEX(SP_CS_ShareCount_EoP_Diluted,0,COLUMN()) -> 30196.81 | H6: =INDEX(SP_CS_StockPrice,0,COLUMN())*INDEX(SP_CS_ShareCount_EoP_Diluted,0,COLUMN()) -> 29781.025 | I6: =INDEX(SP_CS_StockPrice,0,COLUMN())*INDEX(SP_CS_ShareCount_EoP_Diluted,0,COLUMN()) -> 29860.992 | J6: =INDEX(SP_CS_StockPrice,0,COLUMN())*INDEX(SP_CS_ShareCount_EoP_Diluted,0,COLUMN()) -> 34487.84 | ... CB6: =INDEX(SP_CS_StockPrice,0,COLUMN())*INDEX(SP_CS_ShareCount_EoP_Diluted,0,COLUMN()) -> 474345.94
A7: =INDEX(MO_BSS_Cash,0,COLUMN()) -> Cash | C7: =INDEX(MO_BSS_Cash,0,COLUMN()) -> 1037.074 | D7: =INDEX(MO_BSS_Cash,0,COLUMN()) -> 1949.834 | E7: =INDEX(MO_BSS_Cash,0,COLUMN()) -> 2731.782 | F7: =INDEX(MO_BSS_Cash,0,COLUMN()) -> 2697.601 | G7: =INDEX(MO_BSS_Cash,0,COLUMN()) -> 3010.578 | H7: =INDEX(MO_BSS_Cash,0,COLUMN()) -> 2997.8 | I7: =INDEX(MO_BSS_Cash,0,COLUMN()) -> 2710.7 | J7: =INDEX(MO_BSS_Cash,0,COLUMN()) -> 2684.6 | ... CB7: =INDEX(MO_BSS_Cash,0,COLUMN()) -> 75976.724
A8: =INDEX(MO_BSS_Debt,0,COLUMN()) -> Debt | C8: =INDEX(MO_BSS_Debt,0,COLUMN()) -> 699.756 | D8: =INDEX(MO_BSS_Debt,0,COLUMN()) -> 710.06 | E8: =INDEX(MO_BSS_Debt,0,COLUMN()) -> 736.368 | F8: =INDEX(MO_BSS_Debt,0,COLUMN()) -> 759.49 | G8: =INDEX(MO_BSS_Debt,0,COLUMN()) -> 1074.57 | H8: =INDEX(MO_BSS_Debt,0,COLUMN()) -> 1101.685 | I8: =INDEX(MO_BSS_Debt,0,COLUMN()) -> 1122.785 | J8: =INDEX(MO_BSS_Debt,0,COLUMN()) -> 1141.785 | ... CB8: =INDEX(MO_BSS_Debt,0,COLUMN()) -> 4759.136
A9: Other EV Components | C9: =INDEX(MO_VA_EVCalc_NCI,0,COLUMN())+INDEX(MO_VA_EVCalc_Prefs,0,COLUMN())+INDEX(MO_VA_EVCalc_Other,0,COLUMN()) -> 0 | D9: =INDEX(MO_VA_EVCalc_NCI,0,COLUMN())+INDEX(MO_VA_EVCalc_Prefs,0,COLUMN())+INDEX(MO_VA_EVCalc_Other,0,COLUMN()) -> 0 | E9: =INDEX(MO_VA_EVCalc_NCI,0,COLUMN())+INDEX(MO_VA_EVCalc_Prefs,0,COLUMN())+INDEX(MO_VA_EVCalc_Other,0,COLUMN()) -> 0 | F9: =INDEX(MO_VA_EVCalc_NCI,0,COLUMN())+INDEX(MO_VA_EVCalc_Prefs,0,COLUMN())+INDEX(MO_VA_EVCalc_Other,0,COLUMN()) -> 0 | G9: =INDEX(MO_VA_EVCalc_NCI,0,COLUMN())+INDEX(MO_VA_EVCalc_Prefs,0,COLUMN())+INDEX(MO_VA_EVCalc_Other,0,COLUMN()) -> 0 | H9: =INDEX(MO_VA_EVCalc_NCI,0,COLUMN())+INDEX(MO_VA_EVCalc_Prefs,0,COLUMN())+INDEX(MO_VA_EVCalc_Other,0,COLUMN()) -> 0 | I9: =INDEX(MO_VA_EVCalc_NCI,0,COLUMN())+INDEX(MO_VA_EVCalc_Prefs,0,COLUMN())+INDEX(MO_VA_EVCalc_Other,0,COLUMN()) -> 0 | J9: =INDEX(MO_VA_EVCalc_NCI,0,COLUMN())+INDEX(MO_VA_EVCalc_Prefs,0,COLUMN())+INDEX(MO_VA_EVCalc_Other,0,COLUMN()) -> 0 | ... CB9: =INDEX(MO_VA_EVCalc_NCI,0,COLUMN())+INDEX(MO_VA_EVCalc_Prefs,0,COLUMN())+INDEX(MO_VA_EVCalc_Other,0,COLUMN()) -> 0
A10: ="Enterprise Value - "&SP.ValuationToggle -> Enterprise Value - EoP | C10: =INDEX(SP_CS_MarketCap,0,COLUMN())-INDEX(SP_CS_Cash,0,COLUMN())+INDEX(SP_CS_Debt,0,COLUMN())+INDEX(SP_CS_EVCalc_Other,0,COLUMN()) -> 13150.544 | D10: =INDEX(SP_CS_MarketCap,0,COLUMN())-INDEX(SP_CS_Cash,0,COLUMN())+INDEX(SP_CS_Debt,0,COLUMN())+INDEX(SP_CS_EVCalc_Other,0,COLUMN()) -> 15350.369 | E10: =INDEX(SP_CS_MarketCap,0,COLUMN())-INDEX(SP_CS_Cash,0,COLUMN())+INDEX(SP_CS_Debt,0,COLUMN())+INDEX(SP_CS_EVCalc_Other,0,COLUMN()) -> 15596.094 | F10: =INDEX(SP_CS_MarketCap,0,COLUMN())-INDEX(SP_CS_Cash,0,COLUMN())+INDEX(SP_CS_Debt,0,COLUMN())+INDEX(SP_CS_EVCalc_Other,0,COLUMN()) -> 17697.383 | G10: =INDEX(SP_CS_MarketCap,0,COLUMN())-INDEX(SP_CS_Cash,0,COLUMN())+INDEX(SP_CS_Debt,0,COLUMN())+INDEX(SP_CS_EVCalc_Other,0,COLUMN()) -> 28260.802 | H10: =INDEX(SP_CS_MarketCap,0,COLUMN())-INDEX(SP_CS_Cash,0,COLUMN())+INDEX(SP_CS_Debt,0,COLUMN())+INDEX(SP_CS_EVCalc_Other,0,COLUMN()) -> 27884.91 | I10: =INDEX(SP_CS_MarketCap,0,COLUMN())-INDEX(SP_CS_Cash,0,COLUMN())+INDEX(SP_CS_Debt,0,COLUMN())+INDEX(SP_CS_EVCalc_Other,0,COLUMN()) -> 28273.077 | J10: =INDEX(SP_CS_MarketCap,0,COLUMN())-INDEX(SP_CS_Cash,0,COLUMN())+INDEX(SP_CS_Debt,0,COLUMN())+INDEX(SP_CS_EVCalc_Other,0,COLUMN()) -> 32945.025 | ... CB10: =INDEX(SP_CS_MarketCap,0,COLUMN())-INDEX(SP_CS_Cash,0,COLUMN())+INDEX(SP_CS_Debt,0,COLUMN())+INDEX(SP_CS_EVCalc_Other,0,COLUMN()) -> 403128.35
A12: Company-Specific Operational Data
A13: =Model!A43 -> Y/Y EUV sales growth, % | F13: =Model!F43 -> -0.63369656 | G13: =Model!G43 -> 0.37528604 | L13: =Model!L43 -> 3.9891015 | M13: =Model!M43 -> -1 | N13: =Model!N43 -> 0.095253419 | O13: =Model!O43 -> -1 | P13: =Model!P43 -> -1 | Q13: =Model!Q43 -> -0.76496857 | R13: =Model!R43 -> n/a | S13: =Model!S43 -> 0.48717497 | ... CB13: =Model!CB43 -> 0.05
A14: =Model!A44 -> Y/Y ArFi sales growth, % | F14: =Model!F44 -> -0.2349598 | G14: =Model!G44 -> 0.14934254 | L14: =Model!L44 -> 0.11439639 | M14: =Model!M44 -> 0.32165943 | N14: =Model!N44 -> -0.20764634 | O14: =Model!O44 -> 0.041398153 | P14: =Model!P44 -> -0.29590508 | Q14: =Model!Q44 -> -0.068799713 | R14: =Model!R44 -> -0.34347063 | S14: =Model!S44 -> 0.073024976 | ... CB14: =Model!CB44 -> 0.083947268
A15: =Model!A45 -> Y/Y ArF sales growth, % | F15: =Model!F45 -> -0.64427786 | G15: =Model!G45 -> -0.53309672 | L15: =Model!L45 -> -0.14224467 | M15: =Model!M45 -> n/a | N15: =Model!N45 -> -0.087288817 | O15: =Model!O45 -> n/a | P15: =Model!P45 -> 1.4349949 | Q15: =Model!Q45 -> 2.2971083 | R15: =Model!R45 -> 0.14961893 | S15: =Model!S45 -> 2.3461437 | ... CB15: =Model!CB45 -> 0.005961866
A16: =Model!A46 -> Y/Y KrF sales growth, % | F16: =Model!F46 -> -0.019780438 | G16: =Model!G46 -> -0.20720313 | L16: =Model!L46 -> -0.47026677 | M16: =Model!M46 -> -0.14574529 | N16: =Model!N46 -> 4.4762671 | O16: =Model!O46 -> 1.480978 | P16: =Model!P46 -> 1.0742549 | Q16: =Model!Q46 -> 0.96032886 | R16: =Model!R46 -> -0.19526675 | S16: =Model!S46 -> 0.02243279 | ... CB16: =Model!CB46 -> 0.081523618
A17: =Model!A47 -> Y/Y i-line sales growth, % | F17: =Model!F47 -> -0.11616397 | G17: =Model!G47 -> 0.022606007 | L17: =Model!L47 -> -0.056381135 | M17: =Model!M47 -> 1.4203883 | N17: =Model!N47 -> 0.82542237 | O17: =Model!O47 -> 0.10265687 | P17: =Model!P47 -> 0.62332995 | Q17: =Model!Q47 -> 0.42626026 | R17: =Model!R47 -> -0.31022864 | S17: =Model!S47 -> 0.11538123 | ... CB17: =Model!CB47 -> 0.15
A18: =Model!A48 -> Y/Y Metrology & Inspection sales growth, % | F18: =Model!F48 -> 0 | G18: =Model!G48 -> 0 | L18: =Model!L48 -> 0 | M18: =Model!M48 -> 0 | N18: =Model!N48 -> 0 | O18: =Model!O48 -> 0 | P18: =Model!P48 -> 0 | Q18: =Model!Q48 -> 0 | R18: =Model!R48 -> 0 | S18: =Model!S48 -> 0 | ... CB18: =Model!CB48 -> 0.05
A19: =Model!A49 -> Y/Y Total net system sales growth, % | D19: =Model!D49 -> 2.3150747 | E19: =Model!E49 -> 0.253976 | F19: =Model!F49 -> -0.2216012 | G19: =Model!G49 -> 0.050372314 | L19: =Model!L49 -> 0.062522648 | M19: =Model!M49 -> 0.21019417 | N19: =Model!N49 -> -0.087288817 | O19: =Model!O49 -> 0.10265687 | P19: =Model!P49 -> -0.18833502 | Q19: =Model!Q49 -> -0.0013215361 | R19: =Model!R49 -> -0.31022864 | S19: =Model!S49 -> 0.11538123 | ... CB19: =Model!CB49 -> 0.058710042
A20: =Model!A50 -> Y/Y Net service and field option sales growth, % | D20: =Model!D50 -> 0.45581368 | E20: =Model!E50 -> 0.25102251 | F20: =Model!F50 -> 0.21222309 | G20: =Model!G50 -> 0.34655988 | L20: =Model!L50 -> 0.28852489 | M20: =Model!M50 -> 0.10068213 | N20: =Model!N50 -> 0.29705442 | O20: =Model!O50 -> 0.31117204 | P20: =Model!P50 -> 0.35380475 | Q20: =Model!Q50 -> 0.27065914 | R20: =Model!R50 -> 0.17352504 | S20: =Model!S50 -> -0.087374904 | ... CB20: =Model!CB50 -> 0.02
A21: =Model!A51 -> Y/Y Total revenue growth, % | D21: =Model!D51 -> 1.8244111 | E21: =Model!E51 -> 0.25357425 | F21: =Model!F51 -> -0.16271002 | G21: =Model!G51 -> 0.10858396 | L21: =Model!L51 -> 0.11647532 | M21: =Model!M51 -> 0.18145363 | N21: =Model!N51 -> 0.0063884157 | O21: =Model!O51 -> 0.17168356 | P21: =Model!P51 -> -0.040026774 | Q21: =Model!Q51 -> 0.07361298 | R21: =Model!R51 -> -0.19195103 | S21: =Model!S51 -> 0.051689741 | ... CB21: =Model!CB51 -> 0.051305748
A23: GAAP Financials
A24: =INDEX(MO_RIS_REV,0,COLUMN()) -> Net Revenue | C24: =INDEX(MO_RIS_REV,0,COLUMN()) -> 1596.063 | D24: =INDEX(MO_RIS_REV,0,COLUMN()) -> 4507.938 | E24: =INDEX(MO_RIS_REV,0,COLUMN()) -> 5651.035 | F24: =INDEX(MO_RIS_REV,0,COLUMN()) -> 4731.555 | G24: =INDEX(MO_RIS_REV,0,COLUMN()) -> 5245.326 | H24: =INDEX(MO_RIS_REV,0,COLUMN()) -> 1396.5 | I24: =INDEX(MO_RIS_REV,0,COLUMN()) -> 1643.6 | J24: =INDEX(MO_RIS_REV,0,COLUMN()) -> 1322.2 | ... CB24: =INDEX(MO_RIS_REV,0,COLUMN()) -> 51418.349
A25: =INDEX(MO_RIS_COGS,0,COLUMN()) -> COGS | C25: =INDEX(MO_RIS_COGS,0,COLUMN()) -> 1137.671 | D25: =INDEX(MO_RIS_COGS,0,COLUMN()) -> 2552.768 | E25: =INDEX(MO_RIS_COGS,0,COLUMN()) -> 3201.645 | F25: =INDEX(MO_RIS_COGS,0,COLUMN()) -> 2726.298 | G25: =INDEX(MO_RIS_COGS,0,COLUMN()) -> 3068.064 | H25: =INDEX(MO_RIS_COGS,0,COLUMN()) -> 787 | I25: =INDEX(MO_RIS_COGS,0,COLUMN()) -> 891.7 | J25: =INDEX(MO_RIS_COGS,0,COLUMN()) -> 744.1 | ... CB25: =INDEX(MO_RIS_COGS,0,COLUMN()) -> 23433.696
A26: =INDEX(MO_RIS_SGA,0,COLUMN()) -> SG&A | C26: =INDEX(MO_RIS_SGA,0,COLUMN()) -> 154.756 | D26: =INDEX(MO_RIS_SGA,0,COLUMN()) -> 181.045 | E26: =INDEX(MO_RIS_SGA,0,COLUMN()) -> 217.904 | F26: =INDEX(MO_RIS_SGA,0,COLUMN()) -> 259.301 | G26: =INDEX(MO_RIS_SGA,0,COLUMN()) -> 311.741 | H26: =INDEX(MO_RIS_SGA,0,COLUMN()) -> 84.9 | I26: =INDEX(MO_RIS_SGA,0,COLUMN()) -> 79.9 | J26: =INDEX(MO_RIS_SGA,0,COLUMN()) -> 76.9 | ... CB26: =INDEX(MO_RIS_SGA,0,COLUMN()) -> 1480.7006
A27: =INDEX(MO_RIS_RD,0,COLUMN()) -> R&D | C27: =INDEX(MO_RIS_RD,0,COLUMN()) -> 466.761 | D27: =INDEX(MO_RIS_RD,0,COLUMN()) -> 523.426 | E27: =INDEX(MO_RIS_RD,0,COLUMN()) -> 590.27 | F27: =INDEX(MO_RIS_RD,0,COLUMN()) -> 589.182 | G27: =INDEX(MO_RIS_RD,0,COLUMN()) -> 882.029 | H27: =INDEX(MO_RIS_RD,0,COLUMN()) -> 279.1 | I27: =INDEX(MO_RIS_RD,0,COLUMN()) -> 266.9 | J27: =INDEX(MO_RIS_RD,0,COLUMN()) -> 260.1 | ... CB27: =INDEX(MO_RIS_RD,0,COLUMN()) -> 5447.9645
A28: =INDEX(MO_RIS_OI_Operating,0,COLUMN()) -> Other | C28: =INDEX(MO_RIS_OI_Operating,0,COLUMN()) -> 0 | D28: =INDEX(MO_RIS_OI_Operating,0,COLUMN()) -> 0 | E28: =INDEX(MO_RIS_OI_Operating,0,COLUMN()) -> 0 | F28: =INDEX(MO_RIS_OI_Operating,0,COLUMN()) -> 0 | G28: =INDEX(MO_RIS_OI_Operating,0,COLUMN()) -> -64.456 | H28: =INDEX(MO_RIS_OI_Operating,0,COLUMN()) -> -20.2 | I28: =INDEX(MO_RIS_OI_Operating,0,COLUMN()) -> -20.3 | J28: =INDEX(MO_RIS_OI_Operating,0,COLUMN()) -> -20.3 | ... CB28: =INDEX(MO_RIS_OI_Operating,0,COLUMN()) -> 0
A29: =INDEX(MO_RIS_EBIT,0,COLUMN()) -> EBIT | C29: =IFERROR(INDEX(SP_GF_Rev,0,COLUMN()),0)-IFERROR(INDEX(SP_GF_COGS,0,COLUMN()),0)-IFERROR(INDEX(SP_GF_SGA,0,COLUMN()),0)-IFERROR(INDEX(SP_GF_OI_Operating,0,COLUMN()),0)-IFERROR(INDEX(sp_gf_da_operating,0,COLUMN()),0)-IFERROR(INDEX(sp_gf_opex,0,COLUMN()),0)-IFERROR(INDEX(SP_GF_RD,0,COLUMN()),0) -> -163.125 | D29: =IFERROR(INDEX(SP_GF_Rev,0,COLUMN()),0)-IFERROR(INDEX(SP_GF_COGS,0,COLUMN()),0)-IFERROR(INDEX(SP_GF_SGA,0,COLUMN()),0)-IFERROR(INDEX(SP_GF_OI_Operating,0,COLUMN()),0)-IFERROR(INDEX(sp_gf_da_operating,0,COLUMN()),0)-IFERROR(INDEX(sp_gf_opex,0,COLUMN()),0)-IFERROR(INDEX(SP_GF_RD,0,COLUMN()),0) -> 1250.699 | E29: =IFERROR(INDEX(SP_GF_Rev,0,COLUMN()),0)-IFERROR(INDEX(SP_GF_COGS,0,COLUMN()),0)-IFERROR(INDEX(SP_GF_SGA,0,COLUMN()),0)-IFERROR(INDEX(SP_GF_OI_Operating,0,COLUMN()),0)-IFERROR(INDEX(sp_gf_da_operating,0,COLUMN()),0)-IFERROR(INDEX(sp_gf_opex,0,COLUMN()),0)-IFERROR(INDEX(SP_GF_RD,0,COLUMN()),0) -> 1641.216 | F29: =IFERROR(INDEX(SP_GF_Rev,0,COLUMN()),0)-IFERROR(INDEX(SP_GF_COGS,0,COLUMN()),0)-IFERROR(INDEX(SP_GF_SGA,0,COLUMN()),0)-IFERROR(INDEX(SP_GF_OI_Operating,0,COLUMN()),0)-IFERROR(INDEX(sp_gf_da_operating,0,COLUMN()),0)-IFERROR(INDEX(sp_gf_opex,0,COLUMN()),0)-IFERROR(INDEX(SP_GF_RD,0,COLUMN()),0) -> 1156.774 | G29: =IFERROR(INDEX(SP_GF_Rev,0,COLUMN()),0)-IFERROR(INDEX(SP_GF_COGS,0,COLUMN()),0)-IFERROR(INDEX(SP_GF_SGA,0,COLUMN()),0)-IFERROR(INDEX(SP_GF_OI_Operating,0,COLUMN()),0)-IFERROR(INDEX(sp_gf_da_operating,0,COLUMN()),0)-IFERROR(INDEX(sp_gf_opex,0,COLUMN()),0)-IFERROR(INDEX(SP_GF_RD,0,COLUMN()),0) -> 1047.948 | H29: =IFERROR(INDEX(SP_GF_Rev,0,COLUMN()),0)-IFERROR(INDEX(SP_GF_COGS,0,COLUMN()),0)-IFERROR(INDEX(SP_GF_SGA,0,COLUMN()),0)-IFERROR(INDEX(SP_GF_OI_Operating,0,COLUMN()),0)-IFERROR(INDEX(sp_gf_da_operating,0,COLUMN()),0)-IFERROR(INDEX(sp_gf_opex,0,COLUMN()),0)-IFERROR(INDEX(SP_GF_RD,0,COLUMN()),0) -> 265.7 | I29: =IFERROR(INDEX(SP_GF_Rev,0,COLUMN()),0)-IFERROR(INDEX(SP_GF_COGS,0,COLUMN()),0)-IFERROR(INDEX(SP_GF_SGA,0,COLUMN()),0)-IFERROR(INDEX(SP_GF_OI_Operating,0,COLUMN()),0)-IFERROR(INDEX(sp_gf_da_operating,0,COLUMN()),0)-IFERROR(INDEX(sp_gf_opex,0,COLUMN()),0)-IFERROR(INDEX(SP_GF_RD,0,COLUMN()),0) -> 425.4 | J29: =IFERROR(INDEX(SP_GF_Rev,0,COLUMN()),0)-IFERROR(INDEX(SP_GF_COGS,0,COLUMN()),0)-IFERROR(INDEX(SP_GF_SGA,0,COLUMN()),0)-IFERROR(INDEX(SP_GF_OI_Operating,0,COLUMN()),0)-IFERROR(INDEX(sp_gf_da_operating,0,COLUMN()),0)-IFERROR(INDEX(sp_gf_opex,0,COLUMN()),0)-IFERROR(INDEX(SP_GF_RD,0,COLUMN()),0) -> 261.4 | ... CB29: =IFERROR(INDEX(SP_GF_Rev,0,COLUMN()),0)-IFERROR(INDEX(SP_GF_COGS,0,COLUMN()),0)-IFERROR(INDEX(SP_GF_SGA,0,COLUMN()),0)-IFERROR(INDEX(SP_GF_OI_Operating,0,COLUMN()),0)-IFERROR(INDEX(sp_gf_da_operating,0,COLUMN()),0)-IFERROR(INDEX(sp_gf_opex,0,COLUMN()),0)-IFERROR(INDEX(SP_GF_RD,0,COLUMN()),0) -> 21055.988
A30: =INDEX(MO_RIS_IE_Net,0,COLUMN()) -> Net interest expense | C30: =IFERROR(INDEX(MO_RIS_IE_Net,0,COLUMN()),INDEX(mo_ris_ie,0,COLUMN())+INDEX(mo_ris_ii,0,COLUMN())) -> 8.425 | D30: =IFERROR(INDEX(MO_RIS_IE_Net,0,COLUMN()),INDEX(mo_ris_ie,0,COLUMN())+INDEX(mo_ris_ii,0,COLUMN())) -> 8.176 | E30: =IFERROR(INDEX(MO_RIS_IE_Net,0,COLUMN()),INDEX(mo_ris_ie,0,COLUMN())+INDEX(mo_ris_ii,0,COLUMN())) -> -7.419 | F30: =IFERROR(INDEX(MO_RIS_IE_Net,0,COLUMN()),INDEX(mo_ris_ie,0,COLUMN())+INDEX(mo_ris_ii,0,COLUMN())) -> 6.196 | G30: =IFERROR(INDEX(MO_RIS_IE_Net,0,COLUMN()),INDEX(mo_ris_ie,0,COLUMN())+INDEX(mo_ris_ii,0,COLUMN())) -> 24.471 | H30: =IFERROR(INDEX(MO_RIS_IE_Net,0,COLUMN()),INDEX(mo_ris_ie,0,COLUMN())+INDEX(mo_ris_ii,0,COLUMN())) -> 2.6 | I30: =IFERROR(INDEX(MO_RIS_IE_Net,0,COLUMN()),INDEX(mo_ris_ie,0,COLUMN())+INDEX(mo_ris_ii,0,COLUMN())) -> 1.4 | J30: =IFERROR(INDEX(MO_RIS_IE_Net,0,COLUMN()),INDEX(mo_ris_ie,0,COLUMN())+INDEX(mo_ris_ii,0,COLUMN())) -> 2 | ... CB30: =IFERROR(INDEX(MO_RIS_IE_Net,0,COLUMN()),INDEX(mo_ris_ie,0,COLUMN())+INDEX(mo_ris_ii,0,COLUMN())) -> 142.77408
A31: =INDEX(MO_RIS_EI,0,COLUMN()) -> Income from equity method investments | C31: =INDEX(MO_RIS_EI,0,COLUMN()) -> 0 | D31: =INDEX(MO_RIS_EI,0,COLUMN()) -> 0 | E31: =INDEX(MO_RIS_EI,0,COLUMN()) -> 0 | F31: =INDEX(MO_RIS_EI,0,COLUMN()) -> 0 | G31: =INDEX(MO_RIS_EI,0,COLUMN()) -> 0 | H31: =INDEX(MO_RIS_EI,0,COLUMN()) -> 0 | I31: =INDEX(MO_RIS_EI,0,COLUMN()) -> 0 | J31: =INDEX(MO_RIS_EI,0,COLUMN()) -> 0 | ... CB31: =INDEX(MO_RIS_EI,0,COLUMN()) -> -80
A32: =INDEX(MO_RIS_OTI,0,COLUMN()) -> One-time item | C32: =INDEX(MO_RIS_OTI,0,COLUMN()) -> 0 | D32: =INDEX(MO_RIS_OTI,0,COLUMN()) -> 0 | E32: =INDEX(MO_RIS_OTI,0,COLUMN()) -> 0 | F32: =INDEX(MO_RIS_OTI,0,COLUMN()) -> 0 | G32: =INDEX(MO_RIS_OTI,0,COLUMN()) -> 0 | H32: =INDEX(MO_RIS_OTI,0,COLUMN()) -> 0 | I32: =INDEX(MO_RIS_OTI,0,COLUMN()) -> 0 | J32: =INDEX(MO_RIS_OTI,0,COLUMN()) -> 0 | ... CB32: =INDEX(MO_RIS_OTI,0,COLUMN()) -> 0
A33: =INDEX(MO_RIS_OI,0,COLUMN()) -> Other items | C33: =INDEX(MO_RIS_OI,0,COLUMN()) -> 0 | D33: =INDEX(MO_RIS_OI,0,COLUMN()) -> 0 | E33: =INDEX(MO_RIS_OI,0,COLUMN()) -> 0 | F33: =INDEX(MO_RIS_OI,0,COLUMN()) -> 0 | G33: =INDEX(MO_RIS_OI,0,COLUMN()) -> 0 | H33: =INDEX(MO_RIS_OI,0,COLUMN()) -> 0 | I33: =INDEX(MO_RIS_OI,0,COLUMN()) -> 0 | J33: =INDEX(MO_RIS_OI,0,COLUMN()) -> 0 | ... CB33: =INDEX(MO_RIS_OI,0,COLUMN()) -> 0
A34: =INDEX(MO_RIS_EBT,0,COLUMN()) -> EBT | C34: =INDEX(SP_GF_EBIT,0,COLUMN())-INDEX(SP_GF_IE,0,COLUMN())-INDEX(SP_GF_OI,0,COLUMN())-INDEX(SP_GF_EI,0,COLUMN())-INDEX(SP_GF_OTI,0,COLUMN()) -> -171.55 | D34: =INDEX(SP_GF_EBIT,0,COLUMN())-INDEX(SP_GF_IE,0,COLUMN())-INDEX(SP_GF_OI,0,COLUMN())-INDEX(SP_GF_EI,0,COLUMN())-INDEX(SP_GF_OTI,0,COLUMN()) -> 1242.523 | E34: =INDEX(SP_GF_EBIT,0,COLUMN())-INDEX(SP_GF_IE,0,COLUMN())-INDEX(SP_GF_OI,0,COLUMN())-INDEX(SP_GF_EI,0,COLUMN())-INDEX(SP_GF_OTI,0,COLUMN()) -> 1648.635 | F34: =INDEX(SP_GF_EBIT,0,COLUMN())-INDEX(SP_GF_IE,0,COLUMN())-INDEX(SP_GF_OI,0,COLUMN())-INDEX(SP_GF_EI,0,COLUMN())-INDEX(SP_GF_OTI,0,COLUMN()) -> 1150.578 | G34: =INDEX(SP_GF_EBIT,0,COLUMN())-INDEX(SP_GF_IE,0,COLUMN())-INDEX(SP_GF_OI,0,COLUMN())-INDEX(SP_GF_EI,0,COLUMN())-INDEX(SP_GF_OTI,0,COLUMN()) -> 1023.477 | H34: =INDEX(SP_GF_EBIT,0,COLUMN())-INDEX(SP_GF_IE,0,COLUMN())-INDEX(SP_GF_OI,0,COLUMN())-INDEX(SP_GF_EI,0,COLUMN())-INDEX(SP_GF_OTI,0,COLUMN()) -> 263.1 | I34: =INDEX(SP_GF_EBIT,0,COLUMN())-INDEX(SP_GF_IE,0,COLUMN())-INDEX(SP_GF_OI,0,COLUMN())-INDEX(SP_GF_EI,0,COLUMN())-INDEX(SP_GF_OTI,0,COLUMN()) -> 424 | J34: =INDEX(SP_GF_EBIT,0,COLUMN())-INDEX(SP_GF_IE,0,COLUMN())-INDEX(SP_GF_OI,0,COLUMN())-INDEX(SP_GF_EI,0,COLUMN())-INDEX(SP_GF_OTI,0,COLUMN()) -> 259.4 | ... CB34: =INDEX(SP_GF_EBIT,0,COLUMN())-INDEX(SP_GF_IE,0,COLUMN())-INDEX(SP_GF_OI,0,COLUMN())-INDEX(SP_GF_EI,0,COLUMN())-INDEX(SP_GF_OTI,0,COLUMN()) -> 20993.214
A35: Tax | C35: =INDEX(MO_RIS_Tax_Current,0,COLUMN())+INDEX(MO_RIS_Tax_Deferred,0,COLUMN()) -> -20.625 | D35: =INDEX(MO_RIS_Tax_Current,0,COLUMN())+INDEX(MO_RIS_Tax_Deferred,0,COLUMN()) -> 220.703 | E35: =INDEX(MO_RIS_Tax_Current,0,COLUMN())+INDEX(MO_RIS_Tax_Deferred,0,COLUMN()) -> 181.675 | F35: =INDEX(MO_RIS_Tax_Current,0,COLUMN())+INDEX(MO_RIS_Tax_Deferred,0,COLUMN()) -> 4.262 | G35: =INDEX(MO_RIS_Tax_Current,0,COLUMN())+INDEX(MO_RIS_Tax_Deferred,0,COLUMN()) -> 7.987 | H35: =INDEX(MO_RIS_Tax_Current,0,COLUMN())+INDEX(MO_RIS_Tax_Deferred,0,COLUMN()) -> 14 | I35: =INDEX(MO_RIS_Tax_Current,0,COLUMN())+INDEX(MO_RIS_Tax_Deferred,0,COLUMN()) -> 25.3 | J35: =INDEX(MO_RIS_Tax_Current,0,COLUMN())+INDEX(MO_RIS_Tax_Deferred,0,COLUMN()) -> 15.4 | ... CB35: =INDEX(MO_RIS_Tax_Current,0,COLUMN())+INDEX(MO_RIS_Tax_Deferred,0,COLUMN()) -> 3358.9142
A36: =INDEX(MO_RIS_DisCont,0,COLUMN()) -> Discontinued Operations | C36: =INDEX(MO_RIS_DisCont,0,COLUMN()) -> 0 | D36: =INDEX(MO_RIS_DisCont,0,COLUMN()) -> 0 | E36: =INDEX(MO_RIS_DisCont,0,COLUMN()) -> 0 | F36: =INDEX(MO_RIS_DisCont,0,COLUMN()) -> 0 | G36: =INDEX(MO_RIS_DisCont,0,COLUMN()) -> 0 | H36: =INDEX(MO_RIS_DisCont,0,COLUMN()) -> 0 | I36: =INDEX(MO_RIS_DisCont,0,COLUMN()) -> 0 | J36: =INDEX(MO_RIS_DisCont,0,COLUMN()) -> 0 | ... CB36: =INDEX(MO_RIS_DisCont,0,COLUMN()) -> 0
A37: =INDEX(MO_RIS_NCI,0,COLUMN()) -> Net Income to NCI | C37: =INDEX(MO_RIS_NCI,0,COLUMN()) -> 0 | D37: =INDEX(MO_RIS_NCI,0,COLUMN()) -> 0 | E37: =INDEX(MO_RIS_NCI,0,COLUMN()) -> 0 | F37: =INDEX(MO_RIS_NCI,0,COLUMN()) -> 0 | G37: =INDEX(MO_RIS_NCI,0,COLUMN()) -> 0 | H37: =INDEX(MO_RIS_NCI,0,COLUMN()) -> 0 | I37: =INDEX(MO_RIS_NCI,0,COLUMN()) -> 0 | J37: =INDEX(MO_RIS_NCI,0,COLUMN()) -> 0 | ... CB37: =INDEX(MO_RIS_NCI,0,COLUMN()) -> 0
A38: =INDEX(MO_RIS_Dividend_Prefs,0,COLUMN()) -> Earnings to Preferred and Other Securities | C38: =INDEX(MO_RIS_Dividend_Prefs,0,COLUMN()) -> 0 | D38: =INDEX(MO_RIS_Dividend_Prefs,0,COLUMN()) -> 0 | E38: =INDEX(MO_RIS_Dividend_Prefs,0,COLUMN()) -> 0 | F38: =INDEX(MO_RIS_Dividend_Prefs,0,COLUMN()) -> 0 | G38: =INDEX(MO_RIS_Dividend_Prefs,0,COLUMN()) -> 0 | H38: =INDEX(MO_RIS_Dividend_Prefs,0,COLUMN()) -> 0 | I38: =INDEX(MO_RIS_Dividend_Prefs,0,COLUMN()) -> 0 | J38: =INDEX(MO_RIS_Dividend_Prefs,0,COLUMN()) -> 0 | ... CB38: =INDEX(MO_RIS_Dividend_Prefs,0,COLUMN()) -> 0
A39: =INDEX(MO_RIS_NI_GAAP_Basic,0,COLUMN()) -> Net Income to Common Shareholders | C39: =INDEX(MO_RIS_NI_GAAP_Basic,0,COLUMN()) -> -150.925 | D39: =INDEX(MO_RIS_NI_GAAP_Basic,0,COLUMN()) -> 1021.82 | E39: =INDEX(MO_RIS_NI_GAAP_Basic,0,COLUMN()) -> 1466.96 | F39: =INDEX(MO_RIS_NI_GAAP_Basic,0,COLUMN()) -> 1146.316 | G39: =INDEX(MO_RIS_NI_GAAP_Basic,0,COLUMN()) -> 1015.49 | H39: =INDEX(MO_RIS_NI_GAAP_Basic,0,COLUMN()) -> 249.1 | I39: =INDEX(MO_RIS_NI_GAAP_Basic,0,COLUMN()) -> 398.7 | J39: =INDEX(MO_RIS_NI_GAAP_Basic,0,COLUMN()) -> 244 | ... CB39: =INDEX(MO_RIS_NI_GAAP_Basic,0,COLUMN()) -> 17634.299
A40: =INDEX(MO_RIS_Adjustments_Dilution_GAAP,0,COLUMN()) -> Adjustments for Convertible Securities | C40: =INDEX(MO_RIS_Adjustments_Dilution_GAAP,0,COLUMN()) -> 0 | D40: =INDEX(MO_RIS_Adjustments_Dilution_GAAP,0,COLUMN()) -> 0 | E40: =INDEX(MO_RIS_Adjustments_Dilution_GAAP,0,COLUMN()) -> 0 | F40: =INDEX(MO_RIS_Adjustments_Dilution_GAAP,0,COLUMN()) -> 0 | G40: =INDEX(MO_RIS_Adjustments_Dilution_GAAP,0,COLUMN()) -> 0 | H40: =INDEX(MO_RIS_Adjustments_Dilution_GAAP,0,COLUMN()) -> 0 | I40: =INDEX(MO_RIS_Adjustments_Dilution_GAAP,0,COLUMN()) -> 0 | J40: =INDEX(MO_RIS_Adjustments_Dilution_GAAP,0,COLUMN()) -> 0 | ... CB40: =INDEX(MO_RIS_Adjustments_Dilution_GAAP,0,COLUMN()) -> 0
A41: =INDEX(MO_RIS_NI_GAAP_Diluted,0,COLUMN()) -> Diluted Net Income to Common Shareholders | C41: =INDEX(MO_RIS_NI_GAAP_Diluted,0,COLUMN()) -> -150.925 | D41: =INDEX(MO_RIS_NI_GAAP_Diluted,0,COLUMN()) -> 1021.82 | E41: =INDEX(MO_RIS_NI_GAAP_Diluted,0,COLUMN()) -> 1466.96 | F41: =INDEX(MO_RIS_NI_GAAP_Diluted,0,COLUMN()) -> 1146.316 | G41: =INDEX(MO_RIS_NI_GAAP_Diluted,0,COLUMN()) -> 1015.49 | H41: =INDEX(MO_RIS_NI_GAAP_Diluted,0,COLUMN()) -> 249.1 | I41: =INDEX(MO_RIS_NI_GAAP_Diluted,0,COLUMN()) -> 398.7 | J41: =INDEX(MO_RIS_NI_GAAP_Diluted,0,COLUMN()) -> 244 | ... CB41: =INDEX(MO_RIS_NI_GAAP_Diluted,0,COLUMN()) -> 17634.299
A42: =INDEX(MO_RIS_EPS_WAD,0,COLUMN()) -> Earnings Per Share - WAD | C42: =INDEX(MO_RIS_EPS_WAD,0,COLUMN()) -> -0.34886678 | D42: =INDEX(MO_RIS_EPS_WAD,0,COLUMN()) -> 2.3277461 | E42: =INDEX(MO_RIS_EPS_WAD,0,COLUMN()) -> 3.4190648 | F42: =INDEX(MO_RIS_EPS_WAD,0,COLUMN()) -> 2.6846688 | G42: =INDEX(MO_RIS_EPS_WAD,0,COLUMN()) -> 2.3428293 | H42: =INDEX(MO_RIS_EPS_WAD,0,COLUMN()) -> 0.56166855 | I42: =INDEX(MO_RIS_EPS_WAD,0,COLUMN()) -> 0.90285326 | J42: =INDEX(MO_RIS_EPS_WAD,0,COLUMN()) -> 0.55580866 | ... CB42: =INDEX(MO_RIS_EPS_WAD,0,COLUMN()) -> 45.274587
A43: =INDEX(MO_RIS_ShareCount_WAD_Adj,0,COLUMN()) -> Adjusted Shares Outstanding - WAD | C43: =INDEX(MO_RIS_ShareCount_WAD_Adj,0,COLUMN()) -> 432.615 | D43: =INDEX(MO_RIS_ShareCount_WAD_Adj,0,COLUMN()) -> 438.974 | E43: =INDEX(MO_RIS_ShareCount_WAD_Adj,0,COLUMN()) -> 429.053 | F43: =INDEX(MO_RIS_ShareCount_WAD_Adj,0,COLUMN()) -> 426.986 | G43: =INDEX(MO_RIS_ShareCount_WAD_Adj,0,COLUMN()) -> 433.446 | H43: =INDEX(MO_RIS_ShareCount_WAD_Adj,0,COLUMN()) -> 443.5 | I43: =INDEX(MO_RIS_ShareCount_WAD_Adj,0,COLUMN()) -> 441.6 | J43: =INDEX(MO_RIS_ShareCount_WAD_Adj,0,COLUMN()) -> 439 | ... CB43: =INDEX(MO_RIS_ShareCount_WAD_Adj,0,COLUMN()) -> 389.49664
A45: Non-GAAP Financials
A46: =INDEX(MO_RIS_EBITDA_Adj,0,COLUMN()) -> Adjusted EBITDA (No Adjustments) | C46: =INDEX(MO_RIS_EBITDA_Adj,0,COLUMN()) -> -8.1 | D46: =INDEX(MO_RIS_EBITDA_Adj,0,COLUMN()) -> 1414.252 | E46: =INDEX(MO_RIS_EBITDA_Adj,0,COLUMN()) -> 1818.831 | F46: =INDEX(MO_RIS_EBITDA_Adj,0,COLUMN()) -> 1362.108 | G46: =INDEX(MO_RIS_EBITDA_Adj,0,COLUMN()) -> 1329.094 | H46: =INDEX(MO_RIS_EBITDA_Adj,0,COLUMN()) -> 353.5 | I46: =INDEX(MO_RIS_EBITDA_Adj,0,COLUMN()) -> 505.9 | J46: =INDEX(MO_RIS_EBITDA_Adj,0,COLUMN()) -> 335.5 | ... CB46: =INDEX(MO_RIS_EBITDA_Adj,0,COLUMN()) -> 22123.759
A47: =INDEX(MO_RIS_EBIT_Adj,0,COLUMN()) -> Adjusted EBIT (No Adjustments) | C47: =INDEX(MO_RIS_EBIT_Adj,0,COLUMN()) -> -163.125 | D47: =INDEX(MO_RIS_EBIT_Adj,0,COLUMN()) -> 1250.699 | E47: =INDEX(MO_RIS_EBIT_Adj,0,COLUMN()) -> 1641.216 | F47: =INDEX(MO_RIS_EBIT_Adj,0,COLUMN()) -> 1156.774 | G47: =INDEX(MO_RIS_EBIT_Adj,0,COLUMN()) -> 1047.948 | H47: =INDEX(MO_RIS_EBIT_Adj,0,COLUMN()) -> 265.7 | I47: =INDEX(MO_RIS_EBIT_Adj,0,COLUMN()) -> 425.4 | J47: =INDEX(MO_RIS_EBIT_Adj,0,COLUMN()) -> 261.4 | ... CB47: =INDEX(MO_RIS_EBIT_Adj,0,COLUMN()) -> 21055.988
A48: =INDEX(MO_RIS_NI_NONGAAP_Diluted,0,COLUMN()) -> Adjusted Net Income | C48: =INDEX(MO_RIS_NI_NONGAAP_Diluted,0,COLUMN()) -> -150.925 | D48: =INDEX(MO_RIS_NI_NONGAAP_Diluted,0,COLUMN()) -> 1021.82 | E48: =INDEX(MO_RIS_NI_NONGAAP_Diluted,0,COLUMN()) -> 1466.96 | F48: =INDEX(MO_RIS_NI_NONGAAP_Diluted,0,COLUMN()) -> 1146.316 | G48: =INDEX(MO_RIS_NI_NONGAAP_Diluted,0,COLUMN()) -> 1015.49 | H48: =INDEX(MO_RIS_NI_NONGAAP_Diluted,0,COLUMN()) -> 249.1 | I48: =INDEX(MO_RIS_NI_NONGAAP_Diluted,0,COLUMN()) -> 398.7 | J48: =INDEX(MO_RIS_NI_NONGAAP_Diluted,0,COLUMN()) -> 244 | ... CB48: =INDEX(MO_RIS_NI_NONGAAP_Diluted,0,COLUMN()) -> 17634.299
A49: =INDEX(MO_RIS_EPS_WAD_Adj,0,COLUMN()) -> Adjusted Earnings Per Share - WAD (No Adjustments) | C49: =INDEX(MO_RIS_EPS_WAD_Adj,0,COLUMN()) -> -0.34886678 | D49: =INDEX(MO_RIS_EPS_WAD_Adj,0,COLUMN()) -> 2.3277461 | E49: =INDEX(MO_RIS_EPS_WAD_Adj,0,COLUMN()) -> 3.4190648 | F49: =INDEX(MO_RIS_EPS_WAD_Adj,0,COLUMN()) -> 2.6846688 | G49: =INDEX(MO_RIS_EPS_WAD_Adj,0,COLUMN()) -> 2.3428293 | H49: =INDEX(MO_RIS_EPS_WAD_Adj,0,COLUMN()) -> 0.56166855 | I49: =INDEX(MO_RIS_EPS_WAD_Adj,0,COLUMN()) -> 0.90285326 | J49: =INDEX(MO_RIS_EPS_WAD_Adj,0,COLUMN()) -> 0.55580866 | ... CB49: =INDEX(MO_RIS_EPS_WAD_Adj,0,COLUMN()) -> 45.274587
A51: Margin Analysis
A52: =INDEX(MO_MA_COGS,0,COLUMN()) -> COGS Margin, % | C52: =INDEX(SP_GF_COGS,0,COLUMN())/INDEX(SP_GF_Rev,0,COLUMN()) -> 0.7127983 | D52: =INDEX(SP_GF_COGS,0,COLUMN())/INDEX(SP_GF_Rev,0,COLUMN()) -> 0.56628285 | E52: =INDEX(SP_GF_COGS,0,COLUMN())/INDEX(SP_GF_Rev,0,COLUMN()) -> 0.56655905 | F52: =INDEX(SP_GF_COGS,0,COLUMN())/INDEX(SP_GF_Rev,0,COLUMN()) -> 0.57619493 | G52: =INDEX(SP_GF_COGS,0,COLUMN())/INDEX(SP_GF_Rev,0,COLUMN()) -> 0.58491388 | H52: =INDEX(SP_GF_COGS,0,COLUMN())/INDEX(SP_GF_Rev,0,COLUMN()) -> 0.56355174 | I52: =INDEX(SP_GF_COGS,0,COLUMN())/INDEX(SP_GF_Rev,0,COLUMN()) -> 0.5425286 | J52: =INDEX(SP_GF_COGS,0,COLUMN())/INDEX(SP_GF_Rev,0,COLUMN()) -> 0.56277416 | ... CB52: =INDEX(SP_GF_COGS,0,COLUMN())/INDEX(SP_GF_Rev,0,COLUMN()) -> 0.45574579
A53: =INDEX(MO_MA_SGA,0,COLUMN()) -> SG&A Margin, % | C53: =INDEX(SP_GF_SGA,0,COLUMN())/INDEX(SP_GF_Rev,0,COLUMN()) -> 0.096961085 | D53: =INDEX(SP_GF_SGA,0,COLUMN())/INDEX(SP_GF_Rev,0,COLUMN()) -> 0.040161378 | E53: =INDEX(SP_GF_SGA,0,COLUMN())/INDEX(SP_GF_Rev,0,COLUMN()) -> 0.038560016 | F53: =INDEX(SP_GF_SGA,0,COLUMN())/INDEX(SP_GF_Rev,0,COLUMN()) -> 0.054802491 | G53: =INDEX(SP_GF_SGA,0,COLUMN())/INDEX(SP_GF_Rev,0,COLUMN()) -> 0.05943215 | H53: =INDEX(SP_GF_SGA,0,COLUMN())/INDEX(SP_GF_Rev,0,COLUMN()) -> 0.060794844 | I53: =INDEX(SP_GF_SGA,0,COLUMN())/INDEX(SP_GF_Rev,0,COLUMN()) -> 0.048612801 | J53: =INDEX(SP_GF_SGA,0,COLUMN())/INDEX(SP_GF_Rev,0,COLUMN()) -> 0.058160641 | ... CB53: =INDEX(SP_GF_SGA,0,COLUMN())/INDEX(SP_GF_Rev,0,COLUMN()) -> 0.028797125
A54: =INDEX(MO_MA_RD,0,COLUMN()) -> R&D Margin, % | C54: =INDEX(SP_GF_RD,0,COLUMN())/INDEX(SP_GF_Rev,0,COLUMN()) -> 0.29244522 | D54: =INDEX(SP_GF_RD,0,COLUMN())/INDEX(SP_GF_Rev,0,COLUMN()) -> 0.11611207 | E54: =INDEX(SP_GF_RD,0,COLUMN())/INDEX(SP_GF_Rev,0,COLUMN()) -> 0.10445343 | F54: =INDEX(SP_GF_RD,0,COLUMN())/INDEX(SP_GF_Rev,0,COLUMN()) -> 0.12452185 | G54: =INDEX(SP_GF_RD,0,COLUMN())/INDEX(SP_GF_Rev,0,COLUMN()) -> 0.16815523 | H54: =INDEX(SP_GF_RD,0,COLUMN())/INDEX(SP_GF_Rev,0,COLUMN()) -> 0.19985678 | I54: =INDEX(SP_GF_RD,0,COLUMN())/INDEX(SP_GF_Rev,0,COLUMN()) -> 0.16238744 | J54: =INDEX(SP_GF_RD,0,COLUMN())/INDEX(SP_GF_Rev,0,COLUMN()) -> 0.19671759 | ... CB54: =INDEX(SP_GF_RD,0,COLUMN())/INDEX(SP_GF_Rev,0,COLUMN()) -> 0.1059537
A55: =INDEX(MO_MA_EBIT,0,COLUMN()) -> EBIT Margin, % | C55: =INDEX(MO_MA_EBIT,0,COLUMN()) -> -0.10220461 | D55: =INDEX(MO_MA_EBIT,0,COLUMN()) -> 0.2774437 | E55: =INDEX(MO_MA_EBIT,0,COLUMN()) -> 0.29042751 | F55: =INDEX(MO_MA_EBIT,0,COLUMN()) -> 0.24448073 | G55: =INDEX(MO_MA_EBIT,0,COLUMN()) -> 0.19978701 | H55: =INDEX(MO_MA_EBIT,0,COLUMN()) -> 0.19026137 | I55: =INDEX(MO_MA_EBIT,0,COLUMN()) -> 0.2588221 | J55: =INDEX(MO_MA_EBIT,0,COLUMN()) -> 0.1977008 | ... CB55: =INDEX(MO_MA_EBIT,0,COLUMN()) -> 0.40950338
A56: =INDEX(MO_MA_EBIT_Adj,0,COLUMN()) -> Adjusted EBIT Margin (No Adjustments), % | C56: =INDEX(MO_MA_EBIT_Adj,0,COLUMN()) -> -0.10220461 | D56: =INDEX(MO_MA_EBIT_Adj,0,COLUMN()) -> 0.2774437 | E56: =INDEX(MO_MA_EBIT_Adj,0,COLUMN()) -> 0.29042751 | F56: =INDEX(MO_MA_EBIT_Adj,0,COLUMN()) -> 0.24448073 | G56: =INDEX(MO_MA_EBIT_Adj,0,COLUMN()) -> 0.19978701 | H56: =INDEX(MO_MA_EBIT_Adj,0,COLUMN()) -> 0.19026137 | I56: =INDEX(MO_MA_EBIT_Adj,0,COLUMN()) -> 0.2588221 | J56: =INDEX(MO_MA_EBIT_Adj,0,COLUMN()) -> 0.1977008 | ... CB56: =INDEX(MO_MA_EBIT_Adj,0,COLUMN()) -> 0.40950338
A57: =INDEX(MO_MA_EBITDA,0,COLUMN()) -> EBITDA Margin, % | C57: =INDEX(MO_MA_EBITDA,0,COLUMN()) -> -0.0050749876 | D57: =INDEX(MO_MA_EBITDA,0,COLUMN()) -> 0.31372481 | E57: =INDEX(MO_MA_EBITDA,0,COLUMN()) -> 0.32185803 | F57: =INDEX(MO_MA_EBITDA,0,COLUMN()) -> 0.28787745 | G57: =INDEX(MO_MA_EBITDA,0,COLUMN()) -> 0.25338635 | H57: =INDEX(MO_MA_EBITDA,0,COLUMN()) -> 0.25313283 | I57: =INDEX(MO_MA_EBITDA,0,COLUMN()) -> 0.30779995 | J57: =INDEX(MO_MA_EBITDA,0,COLUMN()) -> 0.25374376 | ... CB57: =INDEX(MO_MA_EBITDA,0,COLUMN()) -> 0.43026972
A58: =INDEX(MO_MA_EBITDA_Adj,0,COLUMN()) -> Adjusted EBITDA Margin (No Adjustments), % | C58: =INDEX(SP_NGF_EBITDA,0,COLUMN())/INDEX(SP_GF_Rev,0,COLUMN()) -> -0.0050749876 | D58: =INDEX(SP_NGF_EBITDA,0,COLUMN())/INDEX(SP_GF_Rev,0,COLUMN()) -> 0.31372481 | E58: =INDEX(SP_NGF_EBITDA,0,COLUMN())/INDEX(SP_GF_Rev,0,COLUMN()) -> 0.32185803 | F58: =INDEX(SP_NGF_EBITDA,0,COLUMN())/INDEX(SP_GF_Rev,0,COLUMN()) -> 0.28787745 | G58: =INDEX(SP_NGF_EBITDA,0,COLUMN())/INDEX(SP_GF_Rev,0,COLUMN()) -> 0.25338635 | H58: =INDEX(SP_NGF_EBITDA,0,COLUMN())/INDEX(SP_GF_Rev,0,COLUMN()) -> 0.25313283 | I58: =INDEX(SP_NGF_EBITDA,0,COLUMN())/INDEX(SP_GF_Rev,0,COLUMN()) -> 0.30779995 | J58: =INDEX(SP_NGF_EBITDA,0,COLUMN())/INDEX(SP_GF_Rev,0,COLUMN()) -> 0.25374376 | ... CB58: =INDEX(SP_NGF_EBITDA,0,COLUMN())/INDEX(SP_GF_Rev,0,COLUMN()) -> 0.43026972
A60: Cash Flow Analysis
A61: =INDEX(MO_CFSum_CFO_BeforeWC,0,COLUMN()) -> Operating Cash Flow before WC | C61: =INDEX(MO_CFSum_CFO_BeforeWC,0,COLUMN()) -> 63.151 | D61: =INDEX(MO_CFSum_CFO_BeforeWC,0,COLUMN()) -> 1279.337 | E61: =INDEX(MO_CFSum_CFO_BeforeWC,0,COLUMN()) -> 1784.614 | F61: =INDEX(MO_CFSum_CFO_BeforeWC,0,COLUMN()) -> 1416.151 | G61: =INDEX(MO_CFSum_CFO_BeforeWC,0,COLUMN()) -> 1455.772 | H61: =INDEX(MO_CFSum_CFO_BeforeWC,0,COLUMN()) -> 353.2 | I61: =INDEX(MO_CFSum_CFO_BeforeWC,0,COLUMN()) -> 538.5 | J61: =INDEX(MO_CFSum_CFO_BeforeWC,0,COLUMN()) -> 319.5 | ... CB61: =INDEX(MO_CFSum_CFO_BeforeWC,0,COLUMN()) -> 17652.41
A62: Change in WC | C62: =Model!C545 -> 36.043 | D62: =Model!D545 -> -339.289 | E62: =Model!E545 -> 285.826 | F62: =Model!F545 -> -712.673 | G62: =Model!G545 -> -401.599 | H62: =Model!H545 -> -149.8 | I62: =Model!I545 -> -340.1 | J62: =Model!J545 -> -105.3 | ... CB62: =Model!CB545 -> 439.00612
A63: Operating Cash Flow after WC | C63: =SUM(C61:C62) -> 99.194 | D63: =SUM(D61:D62) -> 940.048 | E63: =SUM(E61:E62) -> 2070.44 | F63: =SUM(F61:F62) -> 703.478 | G63: =SUM(G61:G62) -> 1054.173 | H63: =SUM(H61:H62) -> 203.4 | I63: =SUM(I61:I62) -> 198.4 | J63: =SUM(J61:J62) -> 214.2 | ... CB63: =SUM(CB61:CB62) -> 18091.416
A64: =INDEX(MO_CFSum_Capex,0,COLUMN()) -> Capex | C64: =INDEX(MO_CFSum_Capex,0,COLUMN()) -> -104.959 | D64: =INDEX(MO_CFSum_Capex,0,COLUMN()) -> -128.728 | E64: =INDEX(MO_CFSum_Capex,0,COLUMN()) -> -300.898 | F64: =INDEX(MO_CFSum_Capex,0,COLUMN()) -> -179.536 | G64: =INDEX(MO_CFSum_Capex,0,COLUMN()) -> -214.804 | H64: =INDEX(MO_CFSum_Capex,0,COLUMN()) -> -75.5 | I64: =INDEX(MO_CFSum_Capex,0,COLUMN()) -> -73.7 | J64: =INDEX(MO_CFSum_Capex,0,COLUMN()) -> -84.2 | ... CB64: =INDEX(MO_CFSum_Capex,0,COLUMN()) -> -600
A65: Core FCF, Pre Div | C65: =SUM(C63:C64) -> -5.765 | D65: =SUM(D63:D64) -> 811.32 | E65: =SUM(E63:E64) -> 1769.542 | F65: =SUM(F63:F64) -> 523.942 | G65: =SUM(G63:G64) -> 839.369 | H65: =SUM(H63:H64) -> 127.9 | I65: =SUM(I63:I64) -> 124.7 | J65: =SUM(J63:J64) -> 130 | ... CB65: =SUM(CB63:CB64) -> 17491.416
A66: =INDEX(MO_CFSum_Dividend,0,COLUMN()) -> Dividend Paid | C66: =INDEX(MO_CFSum_Dividend,0,COLUMN()) -> -86.486 | D66: =INDEX(MO_CFSum_Dividend,0,COLUMN()) -> -86.96 | E66: =INDEX(MO_CFSum_Dividend,0,COLUMN()) -> -172.645 | F66: =INDEX(MO_CFSum_Dividend,0,COLUMN()) -> -188.892 | G66: =INDEX(MO_CFSum_Dividend,0,COLUMN()) -> -216.085 | H66: =INDEX(MO_CFSum_Dividend,0,COLUMN()) -> 0 | I66: =INDEX(MO_CFSum_Dividend,0,COLUMN()) -> -268 | J66: =INDEX(MO_CFSum_Dividend,0,COLUMN()) -> 0 | ... CB66: =INDEX(MO_CFSum_Dividend,0,COLUMN()) -> -2584.287
A67: Core FCF, Post Div | C67: =SUM(C65:C66) -> -92.251 | D67: =SUM(D65:D66) -> 724.36 | E67: =SUM(E65:E66) -> 1596.897 | F67: =SUM(F65:F66) -> 335.05 | G67: =SUM(G65:G66) -> 623.284 | H67: =SUM(H65:H66) -> 127.9 | I67: =SUM(I65:I66) -> -143.3 | J67: =SUM(J65:J66) -> 130 | ... CB67: =SUM(CB65:CB66) -> 14907.129
A68: =INDEX(MO_CFSum_Acquisition,0,COLUMN()) -> Acquisitions | C68: =INDEX(MO_CFSum_Acquisition,0,COLUMN()) -> 0 | D68: =INDEX(MO_CFSum_Acquisition,0,COLUMN()) -> 0 | E68: =INDEX(MO_CFSum_Acquisition,0,COLUMN()) -> 0 | F68: =INDEX(MO_CFSum_Acquisition,0,COLUMN()) -> -10.292 | G68: =INDEX(MO_CFSum_Acquisition,0,COLUMN()) -> -443.712 | H68: =INDEX(MO_CFSum_Acquisition,0,COLUMN()) -> 0 | I68: =INDEX(MO_CFSum_Acquisition,0,COLUMN()) -> 0 | J68: =INDEX(MO_CFSum_Acquisition,0,COLUMN()) -> 0 | ... CB68: =INDEX(MO_CFSum_Acquisition,0,COLUMN()) -> 0
A69: =INDEX(MO_CFSum_Divestiture,0,COLUMN()) -> Divestiture | C69: =INDEX(MO_CFSum_Divestiture,0,COLUMN()) -> 6.877 | D69: =INDEX(MO_CFSum_Divestiture,0,COLUMN()) -> 3.825 | E69: =INDEX(MO_CFSum_Divestiture,0,COLUMN()) -> 0 | F69: =INDEX(MO_CFSum_Divestiture,0,COLUMN()) -> 0 | G69: =INDEX(MO_CFSum_Divestiture,0,COLUMN()) -> 0 | H69: =INDEX(MO_CFSum_Divestiture,0,COLUMN()) -> 0 | I69: =INDEX(MO_CFSum_Divestiture,0,COLUMN()) -> 0 | J69: =INDEX(MO_CFSum_Divestiture,0,COLUMN()) -> 0 | ... CB69: =INDEX(MO_CFSum_Divestiture,0,COLUMN()) -> 0
A70: New Equity Issuance | C70: =INDEX(MO_CFSum_NetShares,0,COLUMN()) -> 11.073 | D70: =INDEX(MO_CFSum_NetShares,0,COLUMN()) -> 31 | E70: =INDEX(MO_CFSum_NetShares,0,COLUMN()) -> -666.368 | F70: =INDEX(MO_CFSum_NetShares,0,COLUMN()) -> 3372.293 | G70: =INDEX(MO_CFSum_NetShares,0,COLUMN()) -> -268.178 | H70: =INDEX(MO_CFSum_NetShares,0,COLUMN()) -> -139.5 | I70: =INDEX(MO_CFSum_NetShares,0,COLUMN()) -> -146.8 | J70: =INDEX(MO_CFSum_NetShares,0,COLUMN()) -> -160.5 | ... CB70: =INDEX(MO_CFSum_NetShares,0,COLUMN()) -> 0
A71: New Debt Issuance | C71: =INDEX(MO_CFSum_NetDebtIssuance,0,COLUMN()) -> -1.415 | D71: =INDEX(MO_CFSum_NetDebtIssuance,0,COLUMN()) -> -1.444 | E71: =INDEX(MO_CFSum_NetDebtIssuance,0,COLUMN()) -> -2.537 | F71: =INDEX(MO_CFSum_NetDebtIssuance,0,COLUMN()) -> -2.776 | G71: =INDEX(MO_CFSum_NetDebtIssuance,0,COLUMN()) -> 368.042 | H71: =INDEX(MO_CFSum_NetDebtIssuance,0,COLUMN()) -> -1.1 | I71: =INDEX(MO_CFSum_NetDebtIssuance,0,COLUMN()) -> -1 | J71: =INDEX(MO_CFSum_NetDebtIssuance,0,COLUMN()) -> -1.2 | ... CB71: =INDEX(MO_CFSum_NetDebtIssuance,0,COLUMN()) -> 0
A72: Other Items | C72: =Model!C571+Model!C569+Model!C567+Model!C557+Model!C553+Model!C552+Model!C551+Model!C574+Model!C556+Model!C555+Model!C554 -> 3.606 | D72: =Model!D571+Model!D569+Model!D567+Model!D557+Model!D553+Model!D552+Model!D551+Model!D574+Model!D556+Model!D555+Model!D554 -> 155.019 | E72: =Model!E571+Model!E569+Model!E567+Model!E557+Model!E553+Model!E552+Model!E551+Model!E574+Model!E556+Model!E555+Model!E554 -> -146.044 | F72: =Model!F571+Model!F569+Model!F567+Model!F557+Model!F553+Model!F552+Model!F551+Model!F574+Model!F556+Model!F555+Model!F554 -> -4658.461 | G72: =Model!G571+Model!G569+Model!G567+Model!G557+Model!G553+Model!G552+Model!G551+Model!G574+Model!G556+Model!G555+Model!G554 -> 283.662 | H72: =Model!H571+Model!H569+Model!H567+Model!H557+Model!H553+Model!H552+Model!H551+Model!H574+Model!H556+Model!H555+Model!H554 -> 80.1 | I72: =Model!I571+Model!I569+Model!I567+Model!I557+Model!I553+Model!I552+Model!I551+Model!I574+Model!I556+Model!I555+Model!I554 -> 4 | J72: =Model!J571+Model!J569+Model!J567+Model!J557+Model!J553+Model!J552+Model!J551+Model!J574+Model!J556+Model!J555+Model!J554 -> 65.5 | ... CB72: =Model!CB571+Model!CB569+Model!CB567+Model!CB557+Model!CB553+Model!CB552+Model!CB551+Model!CB574+Model!CB556+Model!CB555+Model!CB554 -> 0
A73: Change in Cash Position | C73: =SUM(C67:C72) -> -72.11 | D73: =SUM(D67:D72) -> 912.76 | E73: =SUM(E67:E72) -> 781.948 | F73: =SUM(F67:F72) -> -964.186 | G73: =SUM(G67:G72) -> 563.098 | H73: =SUM(H67:H72) -> 67.4 | I73: =SUM(I67:I72) -> -287.1 | J73: =SUM(J67:J72) -> 33.8 | ... CB73: =SUM(CB67:CB72) -> 14907.129
A75: Operating Cash Flow Per Share | C75: =INDEX(SP_CFA_CFO,0,COLUMN())/INDEX(SP_GF_ShareCount,0,COLUMN()) -> 0.22928932 | D75: =INDEX(SP_CFA_CFO,0,COLUMN())/INDEX(SP_GF_ShareCount,0,COLUMN()) -> 2.1414662 | E75: =INDEX(SP_CFA_CFO,0,COLUMN())/INDEX(SP_GF_ShareCount,0,COLUMN()) -> 4.8256043 | F75: =INDEX(SP_CFA_CFO,0,COLUMN())/INDEX(SP_GF_ShareCount,0,COLUMN()) -> 1.6475435 | G75: =INDEX(SP_CFA_CFO,0,COLUMN())/INDEX(SP_GF_ShareCount,0,COLUMN()) -> 2.4320746 | H75: =INDEX(SP_CFA_CFO,0,COLUMN())/INDEX(SP_GF_ShareCount,0,COLUMN()) -> 0.45862458 | I75: =INDEX(SP_CFA_CFO,0,COLUMN())/INDEX(SP_GF_ShareCount,0,COLUMN()) -> 0.44927536 | J75: =INDEX(SP_CFA_CFO,0,COLUMN())/INDEX(SP_GF_ShareCount,0,COLUMN()) -> 0.48792711 | ... CB75: =INDEX(SP_CFA_CFO,0,COLUMN())/INDEX(SP_GF_ShareCount,0,COLUMN()) -> 46.448195
A76: Core Free Cash Flow Per Share, Pre Div | C76: =INDEX(SP_CFA_FCF_PreDiv,0,COLUMN())/INDEX(SP_GF_ShareCount,0,COLUMN()) -> -0.013325936 | D76: =INDEX(SP_CFA_FCF_PreDiv,0,COLUMN())/INDEX(SP_GF_ShareCount,0,COLUMN()) -> 1.8482188 | E76: =INDEX(SP_CFA_FCF_PreDiv,0,COLUMN())/INDEX(SP_GF_ShareCount,0,COLUMN()) -> 4.124297 | F76: =INDEX(SP_CFA_FCF_PreDiv,0,COLUMN())/INDEX(SP_GF_ShareCount,0,COLUMN()) -> 1.2270707 | G76: =INDEX(SP_CFA_FCF_PreDiv,0,COLUMN())/INDEX(SP_GF_ShareCount,0,COLUMN()) -> 1.9365019 | H76: =INDEX(SP_CFA_FCF_PreDiv,0,COLUMN())/INDEX(SP_GF_ShareCount,0,COLUMN()) -> 0.28838782 | I76: =INDEX(SP_CFA_FCF_PreDiv,0,COLUMN())/INDEX(SP_GF_ShareCount,0,COLUMN()) -> 0.28238225 | J76: =INDEX(SP_CFA_FCF_PreDiv,0,COLUMN())/INDEX(SP_GF_ShareCount,0,COLUMN()) -> 0.29612756 | ... CB76: =INDEX(SP_CFA_FCF_PreDiv,0,COLUMN())/INDEX(SP_GF_ShareCount,0,COLUMN()) -> 44.907746
