Workbook
Name AA.AlternatePriceSourceStartPeriod: "Q1-2018"
Name AA.CIK: "813672"
Name AA.CompareQuarters.LatestMRQ: "Q3-2019"
Name AA.CSIN: "9SC16I0108"
Name AA.CurationVersion: "2023.11.1.0"
Name AA.DBMacroVersion: "1.0.13.0"
Name AA.FreeCashFlow: "TRUE"
Name AA.GuidanceAnalysisNonGaapEbitVersion: "1.0.0.0"
Name AA.GuidanceAnalysisRevenueVersion: "1.0.0.0"
Name AA.GuidanceAnalysisWadAdjustedEps: "1.0.0.0"
Name AA.HardcodeChecker.LatestMRQ: "Q3-2019"
Name AA.ModelChecks.LatestMRQ: "Q3-2021"
Name AA.ModelChecks.LatestVersionNumber: "2.38.4.0"
Name AA.ModelVersion: "Q3-2025.24"
Name AA.NonLibraryWideCurationVersion: "4"
Name AA.PartialUpdate.BsAvailable: "TRUE"
Name AA.PartialUpdate.CfsAvailable: "TRUE"
Name AA.PartialUpdate.IsAvailable: "TRUE"
Name AA.PeriodLayout: "QFY"
Name AA.PersonalMacro.VersionNumber: ""
Name AA.RowNameEnforcerVersion: "2023.11.1.0"
Name AA.SessionToUploadId: ""
Name AA.StartWorkModelVersion: "Q3-2025.23"
Name AA.StartWorkType: ""
Name AA.SubyearType: "Q"
Name AA.TemplateUpgradeAttempted: "TRUE"
Name AA.TemplateVersion: "7.5.4.0"
Name AA.UpdateType: "Regular"
Name AA.VerifyUnitsAtModelVersion: "Q1-2018.22"
Name EC_CEO_BasePay: 'Exec Comp'!$20:$20
Name EC_CEO_EquityComp_Percent: 'Exec Comp'!$26:$26
Name EC_CEO_SharesOwned: 'Exec Comp'!$67:$67
Name EC_CEO_TotalComp: 'Exec Comp'!$25:$25
Name EC_CFO_BasePay: 'Exec Comp'!$69:$69
Name EC_CFO_EquityComp_Percent: 'Exec Comp'!$75:$75
Name EC_CFO_SharesOwned: 'Exec Comp'!$105:$105
Name EC_CFO_TotalComp: 'Exec Comp'!$74:$74
Name EC_CLO_BasePay: 'Exec Comp'!$145:$145
Name EC_CLO_EquityComp_Percent: 'Exec Comp'!$151:$151
Name EC_CLO_SharesOwned: 'Exec Comp'!$156:$156
Name EC_CLO_TotalComp: 'Exec Comp'!$150:$150
Name EC_CRO_BasePay: 'Exec Comp'!$107:$107
Name EC_CRO_EquityComp_Percent: 'Exec Comp'!$113:$113
Name EC_CRO_SharesOwned: 'Exec Comp'!$143:$143
Name EC_CRO_TotalComp: 'Exec Comp'!$112:$112
Name EC_Director_Compensation_Cash: 'Exec Comp'!$178:$178
Name EC_Director_Compensation_Total: 'Exec Comp'!$201:$201
Name EC_Directors_Current: 'Exec Comp'!$159:$159
Name EC_Directors_Current_Diverse: 'Exec Comp'!$162:$162
Name EC_Directors_Current_Female: 'Exec Comp'!$161:$161
Name EC_Directors_Current_Independent: 'Exec Comp'!$160:$160
Name EC_Directors_Nominees: 'Exec Comp'!$164:$164
Name EC_Directors_Nominees_Independent: 'Exec Comp'!$165:$165
Name FP.DataSource: 'Front Page'!$H$16
Name FP.DataSourceName: 'Front Page'!$H$15
Name FP.Disclaimer: 'Front Page'!$C$22
Name FP.LastPrice: 'Front Page'!$H$20
Name FP.LastPriceDate: 'Front Page'!$F$20
Name FP.RealTimeToggle: 'Front Page'!$H$18
Name FP.UpdateDate: 'Front Page'!$H$11

Sheet Front Page
M6: Please contact this email for any model-specific questions:
M7: modelsupport@alpha-sense.com | N7: mailto:support@canalyst.com?subject=Canalyst%20Support:%20Cadence%20Design%20Systems,%20Inc.%20CDNS%20US&body=Model%20Version:%20Q1-2019.21 | O7: mailto:support@canalyst.com?subject=Canalyst%20Support:%20Cadence%20Design%20Systems,%20Inc.%20CDNS%20US&body=Model%20Version:%20Q1-2019.21
C9: Company Model: | H9: =Model!A1
C11: Updated: | H11: =OFFSET('Update Log'!$C$10,1,0,1,1)
M12: Comments on Model:
C13: For: | H13: =OFFSET('Update Log'!$E$10,1,0,1,1)
C15: Consensus Data and Real-Time Stock Price: | H15: Bloomberg
H16: =IF(FP.DataSourceName="Bloomberg",1,IF(FP.DataSourceName="Capital IQ",2,IF(FP.DataSourceName="FactSet",3,IF(FP.DataSourceName="Refinitiv",4))))
C18: Real-Time Stock Price: | H18: OFF
C20: Stock Price Override: | F20: 45961 | H20: 338.69
C22: DISCLAIMER Access to and use of this model, including the data contained herein (this "Model") is subject to Tegus, Inc.'s (a successor entity to Canalyst Financial Modeling Corporation) ("Company") Terms of Use that you accepted prior to accessing this Model, the applicable Service Agreement between the Company and you (or a corporate entity that has authorized you to access and use this Model on its behalf in accordance with the terms of such Service Agreement) or other similar agreement between you and the Company. BY CONTINUING TO ACCESS OR USE THIS MODEL, YOU EXPRESSLY AGREE TO THE TERMS AND CONDITIONS OF SUCH AGREEMENTS. The Company and certain of its licensors have exclusive proprietary rights in this Model. This Model is being provided for internal use only. Unless prior written consent by the Company and its licensors has been provided to you, you may not distribute or otherwise furnish this Model to any third party, nor use or permit anyone to use this Model for any unlawful or unauthorized purpose. IF YOU HAVE UNLAWFULLY OBTAINED, OR ARE NOT AUTHORIZED TO USE THIS MODEL, YOU ARE OBLIGATED TO PROMPTLY: (I) RETURN THIS MODEL (AND ANY DERIVATIVE WORKS ARISING FROM OR RELATING THERETO) TO THE AUTHORIZED USER OF THIS MODEL; (II) PROVIDE NOTICE TO THE COMPANY AT LEGAL@TEGUS.COM OF SUCH UNLAWFUL OR UNAUTHORIZED ACCESS AND USE; AND, (III) CERTIFY THAT YOU HAVE DESTROYED THIS MODEL (AND ANY DERIVATIVE WORKS ARISING FROM OR RELATING THERETO) AND ANY COPIES FROM YOUR SYSTEMS SO AS TO ENSURE THEY ARE INCAPABLE OF RETRIEVAL. A portion of the data contained in this Model may be powered by third party contributors and their respective licensors, or derived from data provided by such contributors, including (but not limited to): (i) QuoteMedia Inc.: A portion of the market data is powered by Quotemedia.com. All rights reserved. Data delayed 15 minutes unless otherwise indicated; (ii) S&P Global Market Intelligence LLC: Copyright (c) {{YEAR}} S&P Global Market Intelligence LLC (and its affiliates as applicable). All rights reserved. Reproduction of any information, opinions, views, data or material, including ratings ("Content") in any form is prohibited except with the prior written permission of the relevant party. Such party, its affiliates and suppliers ("Content Providers") do not guarantee the accuracy, adequacy, completeness, timeliness or availability of any Content and are not responsible for any errors or omissions (negligent or otherwise), regardless of the cause, or for the results obtained from the use of such Content. In no event shall Content Providers be liable for any damages, costs, expenses, legal fees, or losses (including lost income or lost profit and opportunity costs) in connection with any use of the Content. A reference to a particular investment or security, a rating or any observation concerning an investment that is part of the Content is not a recommendation to buy, sell or hold such investment or security, does not address the suitability of an investment or security and should not be relied on as investment advice. Credit ratings are statements of opinions and are not statements of fact; and, (iii) Refinitiv Canada Holdings Limited: A portion of the information may be provided by or derived from data provided by Refinitiv. By accessing or using this Model (including any portion of the data contained herein) you expressly represent that such access or use does not constitute a violation of any applicable law or regulation to which you or the securities are subject. This Model does not constitute investment advice by the Company or any of its licensors. Reference to a particular investment or security, credit rating or any observation concerning a security or investment in this Model is not a recommendation or solicitation to buy, sell or hold such investment or security or make any other investment decisions. For greater certainty, any forecasts or forward-looking information expressed herein are for illustrative purposes only and do not purport to express any view on what may transpire. Neither the Company nor any of its licensors have performed company-specific research on any projected information, as such, it is your responsibility to express your own views on projected results. This Model does not guarantee future performance and undue reliance should not be placed on such. You are solely responsible for evaluating the merits and risks of any investment based on your own business and financial expertise, the business and financial expertise of professional advisors with whom you have consulted, your financial situation and risk tolerance. Neither the Company, nor any of its licensors, undertake any liability with respect to your reliance on this Model. This Model is a quantitative tool with no investment views. The Company and its respective directors, officers, employees, agents, contractors, and affiliates may hold long or short positions in the security to which this Model relates, based on their personal views, and may initiate or close out any positions in such security at any time without any notice. THIS MODEL IS PROVIDED "AS IS" AND ON AN "AS AVAILABLE" BASIS ONLY, WITHOUT WARRANTIES OR CONDITIONS OF ANY KIND. NEITHER THE COMPANY NOR ANY OF ITS LICENSORS NOR THEIR RESPECTIVE AFFILIATES OR SUPPLIERS HAVE LIABILITY FOR THE ACCURACY, TIMELINESS OR COMPLETENESS OF THIS MODEL, OR FOR DELAYS, INTERRUPTIONS OR OMISSIONS HEREIN, NOR FOR ANY LOST PROFITS, INDIRECT, SPECIAL OR CONSEQUENTIAL DAMAGES. Access to data in this Model that is sourced from third party contributors is subject to termination in the event that any agreement between the Company and such third party contributors terminates for any reason. Copyright 2023 Tegus. All rights reserved.

Sheet DCF
B1: Cadence Design Systems
B2: Discounted Cash Flow Valuation Analysis
F5: Historical | G5: Projected | L5: Assumptions | Q5: Notes
L6: Risk Free Rate: | O6: 0.0425 | Q6: 10-Year US Treasury yield
B7: ($ in millions) | F7: FY2025 | G7: FY2026 | H7: FY2027 | I7: FY2028 | J7: FY2029 | L7: Market Risk Premium: | O7: 0.055 | Q7: Damodaran equity risk premium
L8: Unlevered Beta: | O8: 1.15 | Q8: EDA software industry avg
B9: Revenue Build by Segment | L9: Projected Equity to Value: | O9: 0.92 | Q9: CDNS moderate leverage
B10: Core EDA Revenue | F10: =Model!BS13 | G10: =Model!BX13 | H10: =Model!BY13 | I10: =Model!BZ13 | J10: =Model!CA13 | L10: Levered Beta: | O10: =(1+(1-O12)*(1-O9)/O9)*O8 | Q10: Hamada equation
B11: Y/Y Growth | F11: =Model!BS14 | G11: =Model!BX14 | H11: =Model!BY14 | I11: =Model!BZ14 | J11: =Model!CA14 | L11: Cost of Equity: | O11: =O6+O7*O10 | Q11: CAPM: Rf + B(Rm-Rf)
B12: System Interconnect & Analysis Revenue | F12: =Model!BS16 | G12: =Model!BX16 | H12: =Model!BY16 | I12: =Model!BZ16 | J12: =Model!CA16 | L12: Tax Rate: | O12: 0.18 | Q12: Long-term effective tax rate
B13: Y/Y Growth | F13: =Model!BS17 | G13: =Model!BX17 | H13: =Model!BY17 | I13: =Model!BZ17 | J13: =Model!CA17 | L13: Cost of Debt: | O13: 0.04 | Q13: Based on outstanding senior notes
B14: IP Revenue | F14: =Model!BS18 | G14: =Model!BX18 | H14: =Model!BY18 | I14: =Model!BZ18 | J14: =Model!CA18 | L14: WACC: | O14: =O11*O9+O13*(1-O12)*(1-O9) | Q14: Rd*(1-T)*(D/V) + Re*(E/V)
B15: Y/Y Growth | F15: =Model!BS19 | G15: =Model!BX19 | H15: =Model!BY19 | I15: =Model!BZ19 | J15: =Model!CA19 | L15: Terminal Growth Rate: | O15: 0.03 | Q15: Long-term nominal GDP growth
B16: Total Revenue | F16: =Model!BS20 | G16: =Model!BX20 | H16: =Model!BY20 | I16: =Model!BZ20 | J16: =Model!CA20 | L16: Implied TV/EBITDA: | O16: =F44/(Model!CA99+Model!CA170) | Q16: Terminal value / FY2029 EBITDA
B17: Y/Y Total Revenue Growth | G17: =G16/F16-1 | H17: =H16/G16-1 | I17: =I16/H16-1 | J17: =J16/I16-1
B19: Operating Margin Drivers
B20: Non-GAAP Gross Margin % | F20: =Model!BS47 | G20: =Model!BX47 | H20: =Model!BY47 | I20: =Model!BZ47 | J20: =Model!CA47
B21: Gross Margin Improvement (bps) | F21: =Model!BS49 | G21: =Model!BX49 | H21: =Model!BY49 | I21: =Model!BZ49 | J21: =Model!CA49
B22: Non-GAAP R&D Margin % | F22: =Model!BS61 | G22: =Model!BX61 | H22: =Model!BY61 | I22: =Model!BZ61 | J22: =Model!CA61
B23: R&D Margin Improvement (bps) | F23: =Model!BS62 | G23: =Model!BX62 | H23: =Model!BY62 | I23: =Model!BZ62 | J23: =Model!CA62
B24: Non-GAAP G&A Margin % | F24: =Model!BS74 | G24: =Model!BX74 | H24: =Model!BY74 | I24: =Model!BZ74 | J24: =Model!CA74
B25: G&A Margin Improvement (bps) | F25: =Model!BS75 | G25: =Model!BX75 | H25: =Model!BY75 | I25: =Model!BZ75 | J25: =Model!CA75
B26: Non-GAAP S&M Margin % | F26: =Model!BS87 | G26: =Model!BX87 | H26: =Model!BY87 | I26: =Model!BZ87 | J26: =Model!CA87
B27: S&M Margin Improvement (bps) | F27: =Model!BS88 | G27: =Model!BX88 | H27: =Model!BY88 | I27: =Model!BZ88 | J27: =Model!CA88
B28: Non-GAAP EBIT Margin % | F28: =Model!BS102 | G28: =Model!BX102 | H28: =Model!BY102 | I28: =Model!BZ102 | J28: =Model!CA102
B29: Non-GAAP Operating Income (EBIT) | F29: =Model!BS99 | G29: =Model!BX99 | H29: =Model!BY99 | I29: =Model!BZ99 | J29: =Model!CA99
B31: Unlevered Free Cash Flow Build
B32: Non-GAAP EBIT | G32: =G29 | H32: =H29 | I32: =I29 | J32: =J29
B33: Less: Taxes on EBIT | G33: =-G32*$O$12 | H33: =-H32*$O$12 | I33: =-I32*$O$12 | J33: =-J32*$O$12
B34: NOPAT | G34: =G32+G33 | H34: =H32+H33 | I34: =I32+I33 | J34: =J32+J33
B35: Plus: Depreciation & Amortization | G35: =Model!BX170 | H35: =Model!BY170 | I35: =Model!BZ170 | J35: =Model!CA170
B36: Less: Capital Expenditures | G36: =-Model!BX938 | H36: =-Model!BY938 | I36: =-Model!BZ938 | J36: =-Model!CA938
B37: Less: Increase in Net Working Capital | G37: =-Model!BX933 | H37: =-Model!BY933 | I37: =-Model!BZ933 | J37: =-Model!CA933
B38: Unlevered Free Cash Flow | G38: =SUM(G34:G37) | H38: =SUM(H34:H37) | I38: =SUM(I34:I37) | J38: =SUM(J34:J37)
B40: Times: Discount Factor | G40: =1/(1+$O$14)^1 | H40: =1/(1+$O$14)^2 | I40: =1/(1+$O$14)^3 | J40: =1/(1+$O$14)^4
B41: Discounted Cash Flows | G41: =G38*G40 | H41: =H38*H40 | I41: =I38*I40 | J41: =J38*J40
B43: Sum of Discounted Cash Flows | F43: =SUM(G41:J41)
B44: Terminal Value: | F44: =(J38*(1+$O$15))/($O$14-$O$15)
B45: Times: Discount Factor | F45: =J40
B46: PV of Terminal Value | F46: =F44*F45
C47: Enterprise Value | F47: =F43+F46
B49: Equity Bridge:
B50: Enterprise Value | F50: =F47
B51: Less: Total Debt | F51: =-(Model!BS964+IF(ISNUMBER(Model!BS963),Model!BS963,0))
B52: Plus: Cash & Cash Equivalents | F52: =Model!BS962
C53: Equity Value | F53: =SUM(F50:F52)
B54: Diluted Shares Outstanding (mm) | F54: =Model!BS521
C55: Implied Share Price ($/share) | F55: =F53/F54
B57: Current Stock Price ($/share) | F57: ='Front Page'!H20
B58: Upside / (Downside) | F58: =F55/F57-1
B61: Memo:
B62: Stock-Based Compensation (excluded from UFCF) | G62: =Model!BX178 | H62: =Model!BY178 | I62: =Model!BZ178 | J62: =Model!CA178
B63: UFCF Growth Rate | H63: =H38/G38-1 | I63: =I38/H38-1 | J63: =J38/I38-1

Sheet Model
A1: Cadence Design Systems, Inc.
A2: =CHOOSE(MO.DataSourceIndex,MO.Ticker.Bloomberg,MO.Ticker.CapIQ,MO.Ticker.FactSet,MO.Ticker.Thomson) | C2: =EOMONTH(C4,-12)
A3: =HP.TradeCurrency | B3: =IF(MO.RealTime="OFF",MO.LastPriceHardcoded,MO.LastPriceFormula) | C3: =C4-C2 | D3: =D4-C4 | E3: =E4-D4 | F3: =F4-E4 | G3: =G4-F4 | H3: =H4-G4 | I3: =I4-H4 | J3: =J4-I4 | K3: =K4-F4 | L3: =L4-K4 | M3: =M4-L4 | N3: =N4-M4 | O3: =O4-N4 | P3: =P4-K4 | Q3: =Q4-P4 | R3: =R4-Q4 | S3: =S4-R4 | T3: =T4-S4 | U3: =U4-P4 | V3: =V4-U4 | W3: =W4-V4 | X3: =X4-W4 | Y3: =Y4-X4 | Z3: =Z4-U4 | AA3: =AA4-Z4 | AB3: =AB4-AA4 | AC3: =AC4-AB4 | AD3: =AD4-AC4 | AE3: =AE4-Z4 | AF3: =AF4-AE4 | AG3: =AG4-AF4 | AH3: =AH4-AG4 | AI3: =AI4-AH4 | AJ3: =AJ4-AE4 | AK3: =AK4-AJ4 | AL3: =AL4-AK4 | AM3: =AM4-AL4 | AN3: =AN4-AM4 | AO3: =AO4-AJ4 | AP3: =AP4-AO4 | AQ3: =AQ4-AP4 | AR3: =AR4-AQ4 | AS3: =AS4-AR4 | AT3: =AT4-AO4 | AU3: =AU4-AT4 | AV3: =AV4-AU4 | AW3: =AW4-AV4 | AX3: =AX4-AW4 | AY3: =AY4-AT4 | AZ3: =AZ4-AY4 | BA3: =BA4-AZ4 | BB3: =BB4-BA4 | BC3: =BC4-BB4 | BD3: =BD4-AY4 | BE3: =BE4-BD4 | BF3: =BF4-BE4 | BG3: =BG4-BF4 | BH3: =BH4-BG4 | BI3: =BI4-BD4 | BJ3: =BJ4-BI4 | BK3: =BK4-BJ4 | BL3: =BL4-BK4 | BM3: =BM4-BL4 | BN3: =BN4-BI4 | BO3: =BO4-BN4 | BP3: =BP4-BO4 | BQ3: =BQ4-BP4 | BR3: =BR4-BQ4 | BS3: =BS4-BN4 | BT3: =BT4-BS4 | BU3: =BU4-BT4 | BV3: =BV4-BU4 | BW3: =BW4-BV4 | BX3: =BX4-BS4 | BY3: =BY4-BX4 | BZ3: =BZ4-BY4 | CA3: =CA4-BZ4
A4: =FP.DataSourceName | B4: =IF(AND(MO.RealTimeStockPriceToggle,MO.LastPriceFormula<>"N/A"),"ON","OFF") | C4: 40180 | D4: 40544 | E4: 40908 | F4: 41272 | G4: 41363 | H4: 41454 | I4: 41545 | J4: =K4 | K4: 41636 | L4: 41727 | M4: 41818 | N4: 41909 | O4: =P4 | P4: 42007 | Q4: 42098 | R4: 42189 | S4: 42280 | T4: =U4 | U4: 42371 | V4: 42462 | W4: 42553 | X4: 42644 | Y4: =Z4 | Z4: 42735 | AA4: 42826 | AB4: 42917 | AC4: 43008 | AD4: =AE4 | AE4: 43099 | AF4: 43190 | AG4: 43281 | AH4: 43372 | AI4: =AJ4 | AJ4: 43463 | AK4: 43554 | AL4: 43645 | AM4: 43736 | AN4: =AO4 | AO4: 43827 | AP4: 43918 | AQ4: 44009 | AR4: 44100 | AS4: =AT4 | AT4: 44198 | AU4: 44289 | AV4: 44380 | AW4: 44471 | AX4: =AY4 | AY4: 44562 | AZ4: 44653 | BA4: 44744 | BB4: 44835 | BC4: =BD4 | BD4: 44926 | BE4: 45016 | BF4: 45107 | BG4: 45199 | BH4: =BI4 | BI4: 45291 | BJ4: 45382 | BK4: 45473 | BL4: 45565 | BM4: =BN4 | BN4: 45657 | BO4: 45747 | BP4: 45838 | BQ4: 45930 | BR4: =DATE(YEAR(BQ4),12,31) | BS4: =BR4 | BT4: =+EDATE(BS4,3) | BU4: =+EDATE(BT4,3) | BV4: =+EDATE(BU4,3) | BW4: =DATE(YEAR(BV4),12,31) | BX4: =BW4 | BY4: =EOMONTH(BX4,12) | BZ4: =EOMONTH(BY4,12) | CA4: =EOMONTH(BZ4,12)
A5: =MO.ReportCurrency | C5: FY2009 | D5: =CONCATENATE("FY",RIGHT(C5,4)+1) | E5: =CONCATENATE("FY",RIGHT(D5,4)+1) | F5: =CONCATENATE("FY",RIGHT(E5,4)+1) | G5: =CONCATENATE("Q1","-",RIGHT(F5,4)+1) | H5: =CONCATENATE("Q2","-",RIGHT(G5,4)) | I5: =CONCATENATE("Q3","-",RIGHT(H5,4)) | J5: =CONCATENATE("Q4","-",RIGHT(I5,4)) | K5: =CONCATENATE("FY",RIGHT(F5,4)+1) | L5: =CONCATENATE("Q1","-",RIGHT(K5,4)+1) | M5: =CONCATENATE("Q2","-",RIGHT(L5,4)) | N5: =CONCATENATE("Q3","-",RIGHT(M5,4)) | O5: =CONCATENATE("Q4","-",RIGHT(N5,4)) | P5: =CONCATENATE("FY",RIGHT(K5,4)+1) | Q5: =CONCATENATE("Q1","-",RIGHT(P5,4)+1) | R5: =CONCATENATE("Q2","-",RIGHT(Q5,4)) | S5: =CONCATENATE("Q3","-",RIGHT(R5,4)) | T5: =CONCATENATE("Q4","-",RIGHT(S5,4)) | U5: =CONCATENATE("FY",RIGHT(P5,4)+1) | V5: =CONCATENATE("Q1","-",RIGHT(U5,4)+1) | W5: =CONCATENATE("Q2","-",RIGHT(V5,4)) | X5: =CONCATENATE("Q3","-",RIGHT(W5,4)) | Y5: =CONCATENATE("Q4","-",RIGHT(X5,4)) | Z5: =CONCATENATE("FY",RIGHT(U5,4)+1) | AA5: =CONCATENATE("Q1","-",RIGHT(Z5,4)+1) | AB5: =CONCATENATE("Q2","-",RIGHT(AA5,4)) | AC5: =CONCATENATE("Q3","-",RIGHT(AB5,4)) | AD5: =CONCATENATE("Q4","-",RIGHT(AC5,4)) | AE5: =CONCATENATE("FY",RIGHT(Z5,4)+1) | AF5: =CONCATENATE("Q1","-",RIGHT(AE5,4)+1) | AG5: =CONCATENATE("Q2","-",RIGHT(AF5,4)) | AH5: =CONCATENATE("Q3","-",RIGHT(AG5,4)) | AI5: =CONCATENATE("Q4","-",RIGHT(AH5,4)) | AJ5: =CONCATENATE("FY",RIGHT(AE5,4)+1) | AK5: =CONCATENATE("Q1","-",RIGHT(AJ5,4)+1) | AL5: =CONCATENATE("Q2","-",RIGHT(AK5,4)) | AM5: =CONCATENATE("Q3","-",RIGHT(AL5,4)) | AN5: =CONCATENATE("Q4","-",RIGHT(AM5,4)) | AO5: =CONCATENATE("FY",RIGHT(AJ5,4)+1) | AP5: =CONCATENATE("Q1","-",RIGHT(AO5,4)+1) | AQ5: =CONCATENATE("Q2","-",RIGHT(AP5,4)) | AR5: =CONCATENATE("Q3","-",RIGHT(AQ5,4)) | AS5: =CONCATENATE("Q4","-",RIGHT(AR5,4)) | AT5: =CONCATENATE("FY",RIGHT(AO5,4)+1) | AU5: =CONCATENATE("Q1","-",RIGHT(AT5,4)+1) | AV5: =CONCATENATE("Q2","-",RIGHT(AU5,4)) | AW5: =CONCATENATE("Q3","-",RIGHT(AV5,4)) | AX5: =CONCATENATE("Q4","-",RIGHT(AW5,4)) | AY5: =CONCATENATE("FY",RIGHT(AT5,4)+1) | AZ5: =CONCATENATE("Q1","-",RIGHT(AY5,4)+1) | BA5: =CONCATENATE("Q2","-",RIGHT(AZ5,4)) | BB5: =CONCATENATE("Q3","-",RIGHT(BA5,4)) | BC5: =CONCATENATE("Q4","-",RIGHT(BB5,4)) | BD5: =CONCATENATE("FY",RIGHT(AY5,4)+1) | BE5: =CONCATENATE("Q1","-",RIGHT(BD5,4)+1) | BF5: =CONCATENATE("Q2","-",RIGHT(BE5,4)) | BG5: =CONCATENATE("Q3","-",RIGHT(BF5,4)) | BH5: =CONCATENATE("Q4","-",RIGHT(BG5,4)) | BI5: =CONCATENATE("FY",RIGHT(BD5,4)+1) | BJ5: =CONCATENATE("Q1","-",RIGHT(BI5,4)+1) | BK5: =CONCATENATE("Q2","-",RIGHT(BJ5,4)) | BL5: =CONCATENATE("Q3","-",RIGHT(BK5,4)) | BM5: =CONCATENATE("Q4","-",RIGHT(BL5,4)) | BN5: =CONCATENATE("FY",RIGHT(BI5,4)+1) | BO5: =CONCATENATE("Q1","-",RIGHT(BN5,4)+1) | BP5: =CONCATENATE("Q2","-",RIGHT(BO5,4)) | BQ5: =CONCATENATE("Q3","-",RIGHT(BP5,4)) | BR5: =CONCATENATE("Q4","-",RIGHT(BQ5,4)) | BS5: =CONCATENATE("FY",RIGHT(BN5,4)+1) | BT5: =CONCATENATE("Q1","-",RIGHT(BS5,4)+1) | BU5: =CONCATENATE("Q2","-",RIGHT(BT5,4)) | BV5: =CONCATENATE("Q3","-",RIGHT(BU5,4)) | BW5: =CONCATENATE("Q4","-",RIGHT(BV5,4)) | BX5: =CONCATENATE("FY",RIGHT(BS5,4)+1) | BY5: =CONCATENATE("FY",RIGHT(BX5,4)+1) | BZ5: =CONCATENATE("FY",RIGHT(BY5,4)+1) | CA5: =CONCATENATE("FY",RIGHT(BZ5,4)+1)
A6: Revenue Build
A7: Functional Verification (including Emulation Hardware revenue), mm | C7: =C24*C454 | D7: =D24*D454 | E7: =E24*E454 | F7: =F24*F454 | G7: =G24*G454 | H7: =H24*H454 | I7: =I24*I454 | J7: =J24*J454 | ... BL7: =BL24*BL454
A8: Y/Y Functional Verification (including Emulation Hardware revenue) growth, % | D8: =D7/C7-1 | E8: =E7/D7-1 | F8: =F7/E7-1 | K8: =K7/F7-1 | L8: =L7/G7-1 | M8: =M7/H7-1 | N8: =N7/I7-1 | O8: =O7/J7-1 | P8: =P7/K7-1 | Q8: =Q7/L7-1 | R8: =R7/M7-1 | ... BL8: =BL7/BG7-1
A9: Digital IC Design and Signoff revenue, mm | C9: =C25*C454 | D9: =D25*D454 | E9: =E25*E454 | F9: =F25*F454 | G9: =G25*G454 | H9: =H25*H454 | I9: =I25*I454 | J9: =J25*J454 | ... BL9: =BL25*BL454
A10: Y/Y Digital IC Design and Signoff revenue growth, % | D10: =D9/C9-1 | E10: =E9/D9-1 | F10: =F9/E9-1 | K10: =K9/F9-1 | L10: =L9/G9-1 | M10: =M9/H9-1 | N10: =N9/I9-1 | O10: =O9/J9-1 | P10: =P9/K9-1 | Q10: =Q9/L9-1 | R10: =R9/M9-1 | ... BL10: =BL9/BG9-1
A11: Custom IC Design revenue, mm | C11: =C26*C454 | D11: =D26*D454 | E11: =E26*E454 | F11: =F26*F454 | G11: =G26*G454 | H11: =H26*H454 | I11: =I26*I454 | J11: =J26*J454 | ... BL11: =BL26*BL454
A12: Y/Y Custom IC Design revenue growth, % | D12: =D11/C11-1 | E12: =E11/D11-1 | F12: =F11/E11-1 | K12: =K11/F11-1 | L12: =L11/G11-1 | M12: =M11/H11-1 | N12: =N11/I11-1 | O12: =O11/J11-1 | P12: =P11/K11-1 | Q12: =Q11/L11-1 | R12: =R11/M11-1 | ... BL12: =BL11/BG11-1
A13: Core EDA revenue, mm | C13: =+C11+C9+C7 | D13: =+D11+D9+D7 | E13: =+E11+E9+E7 | F13: =+F11+F9+F7 | G13: =+G11+G9+G7 | H13: =+H11+H9+H7 | I13: =+I11+I9+I7 | J13: =+J11+J9+J7 | ... BL13: =+BL11+BL9+BL7 | BM13: =BM27*BM454 | BN13: =BN27*BN454 | BO13: =BO27*BO454 | BP13: =BP27*BP454 | BQ13: =BQ27*BQ454 | BR13: =BM13*(1+BR14) | BS13: =SUM(BO13,BP13,BQ13,BR13) | BT13: =BO13*(1+BT14) | BU13: =BP13*(1+BU14) | BV13: =BQ13*(1+BV14) | BW13: =BR13*(1+BW14) | BX13: =SUM(BT13,BU13,BV13,BW13) | BY13: =BX13*(1+BY14) | BZ13: =BY13*(1+BZ14) | CA13: =BZ13*(1+CA14)
A14: Y/Y Core EDA revenue growth, % | D14: =D13/C13-1 | E14: =E13/D13-1 | F14: =F13/E13-1 | K14: =K13/F13-1 | L14: =L13/G13-1 | M14: =M13/H13-1 | N14: =N13/I13-1 | O14: =O13/J13-1 | P14: =P13/K13-1 | Q14: =Q13/L13-1 | R14: =R13/M13-1 | ... BQ14: =BQ13/BL13-1 | BR14: 0.05 | BS14: =BS13/BN13-1 | BT14: 0.05 | BU14: 0.1 | BV14: 0.01 | BW14: 0.01 | BX14: =BX13/BS13-1 | BY14: 0.02 | BZ14: 0.02 | CA14: 0.02
A15: Design for Manufacturing revenue, mm | C15: =C28*C454 | D15: =D28*D454 | E15: =E28*E454 | F15: =F28*F454
A16: System Interconnect and Analysis revenue, mm | C16: =C29*C454 | D16: =D29*D454 | E16: =E29*E454 | F16: =F29*F454 | G16: =G29*G454 | H16: =H29*H454 | I16: =I29*I454 | J16: =J29*J454 | ... BQ16: =BQ29*BQ454 | BR16: =BM16*(1+BR17) | BS16: =SUM(BO16,BP16,BQ16,BR16) | BT16: =BO16*(1+BT17) | BU16: =BP16*(1+BU17) | BV16: =BQ16*(1+BV17) | BW16: =BR16*(1+BW17) | BX16: =SUM(BT16,BU16,BV16,BW16) | BY16: =BX16*(1+BY17) | BZ16: =BY16*(1+BZ17) | CA16: =BZ16*(1+CA17)
A17: Y/Y System Interconnect and Analysis revenue growth, % | D17: =D16/C16-1 | E17: =E16/D16-1 | F17: =F16/E16-1 | K17: =K16/F16-1 | L17: =L16/G16-1 | M17: =M16/H16-1 | N17: =N16/I16-1 | O17: =O16/J16-1 | P17: =P16/K16-1 | Q17: =Q16/L16-1 | R17: =R16/M16-1 | ... BQ17: =BQ16/BL16-1 | BR17: 0.05 | BS17: =BS16/BN16-1 | BT17: 0.12 | BU17: 0.12 | BV17: 0.005 | BW17: 0.005 | BX17: =BX16/BS16-1 | BY17: 0.01 | BZ17: 0.01 | CA17: 0.01
A18: IP revenue, mm | C18: =C30*C454 | D18: =D30*D454 | E18: =E30*E454 | F18: =F30*F454 | G18: =G30*G454 | H18: =H30*H454 | I18: =I30*I454 | J18: =J30*J454 | ... BQ18: =BQ30*BQ454 | BR18: =BM18*(1+BR19) | BS18: =SUM(BO18,BP18,BQ18,BR18) | BT18: =BO18*(1+BT19) | BU18: =BP18*(1+BU19) | BV18: =BQ18*(1+BV19) | BW18: =BR18*(1+BW19) | BX18: =SUM(BT18,BU18,BV18,BW18) | BY18: =BX18*(1+BY19) | BZ18: =BY18*(1+BZ19) | CA18: =BZ18*(1+CA19)
A19: Y/Y IP revenue growth, % | D19: =D18/C18-1 | E19: =E18/D18-1 | F19: =F18/E18-1 | K19: =K18/F18-1 | L19: =L18/G18-1 | M19: =M18/H18-1 | N19: =N18/I18-1 | O19: =O18/J18-1 | P19: =P18/K18-1 | Q19: =Q18/L18-1 | R19: =R18/M18-1 | ... BQ19: =BQ18/BL18-1 | BR19: 0.05 | BS19: =BS18/BN18-1 | BT19: 0.12 | BU19: 0.12 | BV19: 0.005 | BW19: 0.005 | BX19: =BX18/BS18-1 | BY19: 0.01 | BZ19: 0.01 | CA19: 0.01
A20: Total revenue, mm | C20: =+C18+C16+C15+C13 | D20: =+D18+D16+D15+D13 | E20: =+E18+E16+E15+E13 | F20: =+F18+F16+F15+F13 | G20: =+G18+G16+G15+G13 | H20: =+H18+H16+H15+H13 | I20: =+I18+I16+I15+I13 | J20: =+J18+J16+J15+J13 | ... CA20: =+CA18+CA16+CA15+CA13
A21: =A455 | BR21: =BR455 | BS21: =BS455 | BT21: =BT455 | BU21: =BU455 | BV21: =BV455 | BW21: =BW455 | BX21: =BX455 | BY21: =BY455 | ... CA21: =CA455
A22: Y/Y Total revenue growth, % | D22: =D20/C20-1 | E22: =E20/D20-1 | F22: =F20/E20-1 | K22: =K20/F20-1 | L22: =L20/G20-1 | M22: =M20/H20-1 | N22: =N20/I20-1 | O22: =O20/J20-1 | P22: =P20/K20-1 | Q22: =Q20/L20-1 | R22: =R20/M20-1 | ... BX22: =BX20/BS20-1 | BY22: =BY20/BX20-1 | BZ22: =BZ20/BY20-1 | CA22: =CA20/BZ20-1
A24: Functional Verification, including Emulation Hardware revenue mix, % | C24: 0.22 | D24: 0.24 | E24: 0.3 | F24: 0.3 | G24: 0.22 | H24: 0.22 | I24: =24%+1% | J24: 0.25 | K24: 0.23 | L24: 0.23 | M24: 0.21 | N24: 0.23 | O24: 0.21 | P24: 0.22 | Q24: 0.23 | R24: 0.21 | S24: 0.23 | T24: 0.25 | U24: 0.23 | V24: 0.26 | W24: 0.27 | X24: 0.24 | Y24: 0.25 | Z24: 0.25 | AA24: 0.23 | AB24: 0.23 | AC24: 0.21 | AD24: 0.23 | AE24: 0.22 | AF24: 0.26 | AG24: 0.23 | AH24: 0.22 | AI24: 0.25 | AJ24: 0.24 | AK24: 0.24 | AL24: 0.22 | AM24: 0.2 | AN24: 0.24 | AO24: 0.23 | AP24: 0.23 | AQ24: 0.24 | AR24: 0.23 | AS24: 0.19 | AT24: 0.22 | AU24: 0.26 | AV24: 0.25 | AW24: 0.23 | AX24: 0.21 | AY24: 0.24 | AZ24: 0.28 | BA24: 0.24 | BB24: 0.25 | BC24: 0.25 | BD24: 0.26 | BE24: 0.32 | BF24: 0.27 | BG24: 0.26 | BH24: 0.24 | BI24: 0.27 | BJ24: 0.25 | BK24: 0.25 | BL24: 0.27
A25: Digital IC Design and Signoff revenue mix, % | C25: 0.21 | D25: 0.23 | E25: 0.22 | F25: 0.23 | G25: 0.33 | H25: 0.31 | I25: 0.29 | J25: 0.29 | K25: 0.3 | L25: 0.3 | M25: 0.3 | N25: 0.29 | O25: 0.28 | P25: 0.29 | Q25: 0.28 | R25: 0.29 | S25: 0.28 | T25: 0.28 | U25: 0.28 | V25: 0.3 | W25: 0.27 | X25: 0.28 | Y25: 0.3 | Z25: 0.29 | AA25: 0.29 | AB25: 0.3 | AC25: 0.3 | AD25: 0.29 | AE25: 0.29 | AF25: 0.3 | AG25: 0.3 | AH25: 0.3 | AI25: 0.28 | AJ25: 0.29 | AK25: 0.3 | AL25: 0.31 | AM25: 0.3 | AN25: 0.29 | AO25: 0.3 | AP25: 0.29 | AQ25: 0.28 | AR25: 0.27 | AS25: 0.31 | AT25: 0.29 | AU25: 0.27 | AV25: 0.28 | AW25: 0.29 | AX25: 0.29 | AY25: 0.29 | AZ25: 0.27 | BA25: 0.27 | BB25: 0.29 | BC25: 0.28 | BD25: 0.28 | BE25: 0.25 | BF25: 0.27 | BG25: 0.28 | BH25: 0.29 | BI25: 0.27 | BJ25: 0.29 | BK25: 0.27 | BL25: 0.24
A26: Custom IC Design revenue mix, % | C26: 0.27 | D26: 0.26 | E26: 0.22 | F26: 0.23 | G26: 0.28 | H26: 0.28 | I26: 0.26 | J26: 0.26 | K26: 0.27 | L26: 0.27 | M26: 0.28 | N26: 0.27 | O26: 0.28 | P26: 0.27 | Q26: 0.27 | R26: 0.27 | S26: 0.26 | T26: 0.25 | U26: 0.26 | V26: 0.25 | W26: 0.26 | X26: 0.27 | Y26: 0.25 | Z26: 0.25 | AA26: 0.26 | AB26: 0.26 | AC26: 0.28 | AD26: 0.26 | AE26: 0.27 | AF26: 0.26 | AG26: 0.26 | AH26: 0.26 | AI26: 0.25 | AJ26: 0.26 | AK26: 0.25 | AL26: 0.26 | AM26: 0.26 | AN26: 0.25 | AO26: 0.25 | AP26: 0.25 | AQ26: 0.24 | AR26: 0.24 | AS26: 0.26 | AT26: 0.25 | AU26: 0.23 | AV26: 0.23 | AW26: 0.23 | AX26: 0.24 | AY26: 0.23 | AZ26: 0.22 | BA26: 0.23 | BB26: 0.22 | BC26: 0.22 | BD26: 0.22 | BE26: 0.2 | BF26: 0.22 | BG26: 0.22 | BH26: 0.22 | BI26: 0.22 | BJ26: 0.22 | BK26: 0.21 | BL26: 0.19
A27: Core EDA revenue mix, % | C27: =SUM(C24:C26) | D27: =SUM(D24:D26) | E27: =SUM(E24:E26) | F27: =SUM(F24:F26) | G27: =SUM(G24:G26) | H27: =SUM(H24:H26) | I27: =SUM(I24:I26) | J27: =SUM(J24:J26) | ... BL27: =SUM(BL24:BL26) | BM27: 0.68 | BN27: 0.71 | BO27: 0.71 | BP27: 0.71 | BQ27: 0.71
A28: Design for Manufacturing revenue mix, % | C28: 0.07 | D28: 0.07 | E28: 0.07 | F28: 0.06
A29: System Interconnect and Analysis revenue mix, % | C29: 0.11 | D29: 0.09 | E29: 0.09 | F29: 0.09 | G29: 0.1 | H29: 0.11 | I29: 0.1 | J29: 0.1 | K29: 0.11 | L29: 0.1 | M29: 0.11 | N29: 0.1 | O29: 0.11 | P29: 0.11 | Q29: 0.11 | R29: 0.11 | S29: 0.1 | T29: 0.1 | U29: 0.11 | V29: 0.09 | W29: 0.1 | X29: 0.1 | Y29: 0.09 | Z29: 0.1 | AA29: 0.1 | AB29: 0.1 | AC29: 0.1 | AD29: 0.1 | AE29: 0.1 | AF29: 0.09 | AG29: 0.09 | AH29: 0.09 | AI29: 0.09 | AJ29: 0.09 | AK29: 0.09 | AL29: 0.1 | AM29: 0.09 | AN29: 0.09 | AO29: 0.09 | AP29: 0.09 | AQ29: 0.1 | AR29: 0.11 | AS29: 0.11 | AT29: 0.1 | AU29: 0.1 | AV29: 0.11 | AW29: 0.11 | AX29: 0.12 | AY29: 0.11 | AZ29: 0.1 | BA29: 0.12 | BB29: 0.12 | BC29: 0.13 | BD29: 0.12 | BE29: 0.12 | BF29: 0.13 | BG29: 0.13 | BH29: 0.12 | BI29: 0.12 | BJ29: 0.12 | BK29: 0.14 | BL29: 0.16 | BM29: 0.19 | BN29: 0.16 | BO29: 0.15 | BP29: 0.16 | BQ29: 0.15 | BR29: =BR16/BR20 | BS29: =BS16/BS20 | BT29: =BT16/BT20 | BU29: =BU16/BU20 | BV29: =BV16/BV20 | BW29: =BW16/BW20 | BX29: =BX16/BX20 | BY29: =BY16/BY20 | ... CA29: =CA16/CA20
A30: IP revenue mix, % | C30: 0.12 | D30: 0.11 | E30: 0.1 | F30: 0.09 | G30: 0.07 | H30: 0.08 | I30: 0.1 | J30: 0.1 | K30: 0.09 | L30: 0.1 | M30: 0.1 | N30: 0.11 | O30: 0.12 | P30: 0.11 | Q30: 0.11 | R30: 0.12 | S30: 0.13 | T30: 0.12 | U30: 0.12 | V30: 0.1 | W30: 0.1 | X30: 0.11 | Y30: 0.11 | Z30: 0.11 | AA30: 0.12 | AB30: 0.11 | AC30: 0.11 | AD30: 0.12 | AE30: 0.12 | AF30: 0.09 | AG30: 0.12 | AH30: 0.13 | AI30: 0.13 | AJ30: 0.12 | AK30: 0.12 | AL30: 0.11 | AM30: 0.15 | AN30: 0.13 | AO30: 0.13 | AP30: 0.14 | AQ30: 0.14 | AR30: 0.15 | AS30: 0.13 | AT30: 0.14 | AU30: 0.14 | AV30: 0.13 | AW30: 0.14 | AX30: 0.14 | AY30: 0.13 | AZ30: 0.13 | BA30: 0.14 | BB30: 0.12 | BC30: 0.12 | BD30: 0.12 | BE30: 0.11 | BF30: 0.11 | BG30: 0.11 | BH30: 0.13 | BI30: 0.12 | BJ30: 0.12 | BK30: 0.13 | BL30: 0.14 | BM30: 0.13 | BN30: 0.13 | BO30: 0.14 | BP30: 0.13 | BQ30: 0.14 | BR30: =BR18/BR20 | BS30: =BS18/BS20 | BT30: =BT18/BT20 | BU30: =BU18/BU20 | BV30: =BV18/BV20 | BW30: =BW18/BW20 | BX30: =BX18/BX20 | BY30: =BY18/BY20 | ... CA30: =CA18/CA20
A31: Total revenue mix, % | C31: =SUM(C27:C30) | D31: =SUM(D27:D30) | E31: =SUM(E27:E30) | F31: =SUM(F27:F30) | G31: =SUM(G27:G30) | H31: =SUM(H27:H30) | I31: =SUM(I27:I30) | J31: =SUM(J27:J30) | ... CA31: =SUM(CA27:CA30)
A33: Operating Expense Forecasting
A34: Net revenue, mm | C34: =C454 | D34: =D454 | E34: =E454 | F34: =F454 | G34: =G454 | H34: =H454 | I34: =I454 | J34: =J454 | ... BQ34: =BQ454 | BR34: =BR20 | BS34: =SUM(BO34,BP34,BQ34,BR34) | BT34: =BT20 | BU34: =BU20 | BV34: =BV20 | BW34: =BW20 | BX34: =SUM(BT34,BU34,BV34,BW34) | BY34: =BY20 | BZ34: =BZ20 | CA34: =CA20
A35: Total cost of revenue, mm | C35: =C346 | D35: =D346 | E35: =E346 | F35: =F346 | G35: =G346 | H35: =H346 | I35: =I346 | J35: =J346 | ... BQ35: =BQ346 | BR35: =BR34-BR36 | BS35: =SUM(BO35,BP35,BQ35,BR35) | BT35: =BT34-BT36 | BU35: =BU34-BU36 | BV35: =BV34-BV36 | BW35: =BW34-BW36 | BX35: =SUM(BT35,BU35,BV35,BW35) | BY35: =BY34-BY36 | BZ35: =BZ34-BZ36 | CA35: =CA34-CA36
A36: GAAP Gross Profit, mm | C36: =C34-C35 | D36: =D34-D35 | E36: =E34-E35 | F36: =F34-F35 | G36: =G34-G35 | H36: =H34-H35 | I36: =I34-I35 | J36: =J34-J35 | ... BQ36: =BQ34-BQ35 | BR36: =BR45-BR44-BR43-BR41 | BS36: =BS34-BS35 | BT36: =BT45-BT44-BT43-BT41 | BU36: =BU45-BU44-BU43-BU41 | BV36: =BV45-BV44-BV43-BV41 | BW36: =BW45-BW44-BW43-BW41 | BX36: =BX34-BX35 | BY36: =BY45-BY44-BY43-BY41 | BZ36: =BZ45-BZ44-BZ43-BZ41 | CA36: =CA45-CA44-CA43-CA41
A37: Y/Y GAAP Gross Profit growth, % | D37: =D36/C36-1 | E37: =E36/D36-1 | F37: =F36/E36-1 | K37: =K36/F36-1 | L37: =L36/G36-1 | M37: =M36/H36-1 | N37: =N36/I36-1 | O37: =O36/J36-1 | P37: =P36/K36-1 | Q37: =Q36/L36-1 | R37: =R36/M36-1 | ... BX37: =BX36/BS36-1 | BY37: =BY36/BX36-1 | BZ37: =BZ36/BY36-1 | CA37: =CA36/BZ36-1
A38: GAAP Gross Profit margin, % | C38: =C36/C34 | D38: =D36/D34 | E38: =E36/E34 | F38: =F36/F34 | G38: =G36/G34 | H38: =H36/H34 | I38: =I36/I34 | J38: =J36/J34 | ... CA38: =CA36/CA34
A39: Y/Y GAAP Gross Profit margin improvement, bps | D39: =(D38-C38)*10000 | E39: =(E38-D38)*10000 | F39: =(F38-E38)*10000 | K39: =(K38-F38)*10000 | L39: =(L38-G38)*10000 | M39: =(M38-H38)*10000 | N39: =(N38-I38)*10000 | O39: =(O38-J38)*10000 | P39: =(P38-K38)*10000 | Q39: =(Q38-L38)*10000 | R39: =(R38-M38)*10000 | ... BX39: =(BX38-BS38)*10000 | BY39: =(BY38-BX38)*10000 | BZ39: =(BZ38-BY38)*10000 | CA39: =(CA38-BZ38)*10000
A41: SBC COGS, mm | D41: =-D459 | E41: =-E459 | F41: =-F459 | G41: =-G459 | H41: =-H459 | I41: =-I459 | J41: =-J459 | K41: =-K459 | ... BQ41: =-BQ459 | BR41: =BR42*BR34 | BS41: =SUM(BO41,BP41,BQ41,BR41) | BT41: =BT42*BT34 | BU41: =BU42*BU34 | BV41: =BV42*BV34 | BW41: =BW42*BW34 | BX41: =SUM(BT41,BU41,BV41,BW41) | BY41: =BY42*BY34 | BZ41: =BZ42*BZ34 | CA41: =CA42*CA34
A42: SBC COGS as a % of revenue, % | D42: =D41/D34 | E42: =E41/E34 | F42: =F41/F34 | G42: =G41/G34 | H42: =H41/H34 | I42: =I41/I34 | J42: =J41/J34 | K42: =K41/K34 | ... BQ42: =BQ41/BQ34 | BR42: 0.003 | BS42: =BS41/BS34 | BT42: 0.005 | BU42: 0.005 | BV42: 0.005 | BW42: 0.005 | BX42: =BX41/BX34 | BY42: 0.005 | BZ42: 0.005 | CA42: 0.005
A43: Intangible amortization COGS, mm | D43: =-D460 | E43: =-E460 | F43: =-F460 | G43: =-G460 | H43: =-H460 | I43: =-I460 | J43: =-J460 | K43: =-K460 | ... BQ43: =-BQ460 | BR43: =BR166 | BS43: =SUM(BO43,BP43,BQ43,BR43) | BT43: =BT166 | BU43: =BU166 | BV43: =BV166 | BW43: =BW166 | BX43: =SUM(BT43,BU43,BV43,BW43) | BY43: =BY166 | BZ43: =BZ166 | CA43: =CA166
A44: Other COGS Adjustments, mm | D44: =-D461 | E44: =-E461 | F44: =-F461 | G44: =-G461 | H44: =-H461 | I44: =-I461 | J44: =-J461 | K44: =-K461 | ... BQ44: =-BQ461 | BR44: 1.7 | BS44: =SUM(BO44,BP44,BQ44,BR44) | BT44: 1.7 | BU44: 1.7 | BV44: 1.7 | BW44: 1.7 | BX44: =SUM(BT44,BU44,BV44,BW44) | BY44: 6.8 | BZ44: 6.8 | CA44: 6.8
A45: Non-GAAP Gross Profit, mm | D45: =D36+D41+D43+D44 | E45: =E36+E41+E43+E44 | F45: =F36+F41+F43+F44 | G45: =G36+G41+G43+G44 | H45: =H36+H41+H43+H44 | I45: =I36+I41+I43+I44 | J45: =J36+J41+J43+J44 | K45: =K36+K41+K43+K44 | ... BQ45: =BQ36+BQ41+BQ43+BQ44 | BR45: =BR47*BR34 | BS45: =BS36+BS41+BS43+BS44 | BT45: =BT47*BT34 | BU45: =BU47*BU34 | BV45: =BV47*BV34 | BW45: =BW47*BW34 | BX45: =BX36+BX41+BX43+BX44 | BY45: =BY47*BY34 | BZ45: =BZ47*BZ34 | CA45: =CA47*CA34
A46: Y/Y Non-GAAP Gross Profit growth, % | E46: =E45/D45-1 | F46: =F45/E45-1 | K46: =K45/F45-1 | L46: =L45/G45-1 | M46: =M45/H45-1 | N46: =N45/I45-1 | O46: =O45/J45-1 | P46: =P45/K45-1 | Q46: =Q45/L45-1 | R46: =R45/M45-1 | ... BX46: =BX45/BS45-1 | BY46: =BY45/BX45-1 | BZ46: =BZ45/BY45-1 | CA46: =CA45/BZ45-1
A47: Non-GAAP Gross Profit margin, % | D47: =D45/D34 | E47: =E45/E34 | F47: =F45/F34 | G47: =G45/G34 | H47: =H45/H34 | I47: =I45/I34 | J47: =J45/J34 | K47: =K45/K34 | ... BQ47: =BQ45/BQ34 | BR47: =BM47+BR49/10000 | BS47: =BS45/BS34 | BT47: =BO47+BT49/10000 | BU47: =BP47+BU49/10000 | BV47: =BQ47+BV49/10000 | BW47: =BR47+BW49/10000 | BX47: =BX45/BX34 | BY47: =BX47+BY49/10000 | BZ47: =BY47+BZ49/10000 | CA47: =BZ47+CA49/10000
A48: Consensus Estimates - Non-GAAP Gross profit margin, % | BR48: =BR328 | BS48: =BS328 | BT48: =BT328 | BU48: =BU328 | BV48: =BV328 | BW48: =BW328 | BX48: =BX328 | BY48: =BY328 | ... CA48: =CA328
A49: Y/Y Non-GAAP Gross Profit margin improvement, bps | E49: =(E47-D47)*10000 | F49: =(F47-E47)*10000 | K49: =(K47-F47)*10000 | L49: =(L47-G47)*10000 | M49: =(M47-H47)*10000 | N49: =(N47-I47)*10000 | O49: =(O47-J47)*10000 | P49: =(P47-K47)*10000 | Q49: =(Q47-L47)*10000 | R49: =(R47-M47)*10000 | ... BQ49: =(BQ47-BL47)*10000 | BR49: -61 | BS49: =(BS47-BN47)*10000 | BT49: 150 | BU49: 50 | BV49: 10 | BW49: 10 | BX49: =(BX47-BS47)*10000 | BY49: 20 | BZ49: 20 | CA49: 20
A51: GAAP R&D, mm | C51: =C464 | D51: =D464 | E51: =E464 | F51: =F464 | G51: =G464 | H51: =H464 | I51: =I464 | J51: =J464 | ... BQ51: =BQ464 | BR51: =BR59+BR58+BR56 | BS51: =SUM(BO51,BP51,BQ51,BR51) | BT51: =BT59+BT58+BT56 | BU51: =BU59+BU58+BU56 | BV51: =BV59+BV58+BV56 | BW51: =BW59+BW58+BW56 | BX51: =SUM(BT51,BU51,BV51,BW51) | BY51: =BY59+BY58+BY56 | BZ51: =BZ59+BZ58+BZ56 | CA51: =CA59+CA58+CA56
A52: Y/Y GAAP R&D growth, % | D52: =D51/C51-1 | E52: =E51/D51-1 | F52: =F51/E51-1 | K52: =K51/F51-1 | L52: =L51/G51-1 | M52: =M51/H51-1 | N52: =N51/I51-1 | O52: =O51/J51-1 | P52: =P51/K51-1 | Q52: =Q51/L51-1 | R52: =R51/M51-1 | ... BX52: =BX51/BS51-1 | BY52: =BY51/BX51-1 | BZ52: =BZ51/BY51-1 | CA52: =CA51/BZ51-1
A53: GAAP R&D Margin, % | C53: =C51/C34 | D53: =D51/D34 | E53: =E51/E34 | F53: =F51/F34 | G53: =G51/G34 | H53: =H51/H34 | I53: =I51/I34 | J53: =J51/J34 | ... CA53: =CA51/CA34
A54: Y/Y GAAP R&D Margin improvement, bps | D54: =-(D53-C53)*10000 | E54: =-(E53-D53)*10000 | F54: =-(F53-E53)*10000 | K54: =-(K53-F53)*10000 | L54: =-(L53-G53)*10000 | M54: =-(M53-H53)*10000 | N54: =-(N53-I53)*10000 | O54: =-(O53-J53)*10000 | P54: =-(P53-K53)*10000 | Q54: =-(Q53-L53)*10000 | R54: =-(R53-M53)*10000 | ... BX54: =-(BX53-BS53)*10000 | BY54: =-(BY53-BX53)*10000 | BZ54: =-(BZ53-BY53)*10000 | CA54: =-(CA53-BZ53)*10000
A56: SBC R&D, mm | D56: =D465 | E56: =E465 | F56: =F465 | G56: =G465 | H56: =H465 | I56: =I465 | J56: =J465 | K56: =K465 | ... BQ56: =BQ465 | BR56: =BR57*BR34 | BS56: =SUM(BO56,BP56,BQ56,BR56) | BT56: =BT57*BT34 | BU56: =BU57*BU34 | BV56: =BV57*BV34 | BW56: =BW57*BW34 | BX56: =SUM(BT56,BU56,BV56,BW56) | BY56: =BY57*BY34 | BZ56: =BZ57*BZ34 | CA56: =CA57*CA34
A57: SBC R&D as & of revenue, % | D57: =D56/D34 | E57: =E56/E34 | F57: =F56/F34 | G57: =G56/G34 | H57: =H56/H34 | I57: =I56/I34 | J57: =J56/J34 | K57: =K56/K34 | ... BQ57: =BQ56/BQ34 | BR57: 0.048 | BS57: =BS56/BS34 | BT57: 0.055 | BU57: 0.055 | BV57: 0.055 | BW57: 0.055 | BX57: =BX56/BX34 | BY57: 0.055 | BZ57: 0.055 | CA57: 0.055
A58: Other adjustments R&D, mm | D58: =D466 | E58: =E466 | F58: =F466 | G58: =G466 | H58: =H466 | I58: =I466 | J58: =J466 | K58: =K466 | ... BQ58: =BQ466 | BR58: 19 | BS58: =SUM(BO58,BP58,BQ58,BR58) | BT58: 15 | BU58: 15 | BV58: 15 | BW58: 15 | BX58: =SUM(BT58,BU58,BV58,BW58) | BY58: 60 | BZ58: 60 | CA58: 60
A59: Non-GAAP R&D, mm | D59: =D51-D56-D58 | E59: =E51-E56-E58 | F59: =F51-F56-F58 | G59: =G51-G56-G58 | H59: =H51-H56-H58 | I59: =I51-I56-I58 | J59: =J51-J56-J58 | K59: =K51-K56-K58 | ... BQ59: =BQ51-BQ56-BQ58 | BR59: =BR61*BR34 | BS59: =SUM(BO59,BP59,BQ59,BR59) | BT59: =BT61*BT34 | BU59: =BU61*BU34 | BV59: =BV61*BV34 | BW59: =BW61*BW34 | BX59: =SUM(BT59,BU59,BV59,BW59) | BY59: =BY61*BY34 | BZ59: =BZ61*BZ34 | CA59: =CA61*CA34
A60: Y/Y Non-GAAP R&D growth, % | E60: =E59/D59-1 | F60: =F59/E59-1 | K60: =K59/F59-1 | L60: =L59/G59-1 | M60: =M59/H59-1 | N60: =N59/I59-1 | O60: =O59/J59-1 | P60: =P59/K59-1 | Q60: =Q59/L59-1 | R60: =R59/M59-1 | ... BX60: =BX59/BS59-1 | BY60: =BY59/BX59-1 | BZ60: =BZ59/BY59-1 | CA60: =CA59/BZ59-1
A61: Non-GAAP R&D Margin, % | D61: =D59/D34 | E61: =E59/E34 | F61: =F59/F34 | G61: =G59/G34 | H61: =H59/H34 | I61: =I59/I34 | J61: =J59/J34 | K61: =K59/K34 | ... BQ61: =BQ59/BQ34 | BR61: =BM61-BR62/10000 | BS61: =BS59/BS34 | BT61: =BO61-BT62/10000 | BU61: =BP61-BU62/10000 | BV61: =BQ61-BV62/10000 | BW61: =BR61-BW62/10000 | BX61: =BX59/BX34 | BY61: =BX61-BY62/10000 | BZ61: =BY61-BZ62/10000 | CA61: =BZ61-CA62/10000
A62: Y/Y Non-GAAP R&D Margin improvement, bps | E62: =-(E61-D61)*10000 | F62: =-(F61-E61)*10000 | K62: =-(K61-F61)*10000 | L62: =-(L61-G61)*10000 | M62: =-(M61-H61)*10000 | N62: =-(N61-I61)*10000 | O62: =-(O61-J61)*10000 | P62: =-(P61-K61)*10000 | Q62: =-(Q61-L61)*10000 | R62: =-(R61-M61)*10000 | ... BQ62: =-(BQ61-BL61)*10000 | BR62: 20 | BS62: =-(BS61-BN61)*10000 | BT62: 20 | BU62: 20 | BV62: 0 | BW62: 0 | BX62: =-(BX61-BS61)*10000 | BY62: 0 | BZ62: 0 | CA62: 0
A64: GAAP G&A, mm | C64: =C468 | D64: =D468 | E64: =E468 | F64: =F468 | G64: =G468 | H64: =H468 | I64: =I468 | J64: =J468 | ... BQ64: =BQ468 | BR64: =BR72+BR71+BR69 | BS64: =SUM(BO64,BP64,BQ64,BR64) | BT64: =BT72+BT71+BT69 | BU64: =BU72+BU71+BU69 | BV64: =BV72+BV71+BV69 | BW64: =BW72+BW71+BW69 | BX64: =SUM(BT64,BU64,BV64,BW64) | BY64: =BY72+BY71+BY69 | BZ64: =BZ72+BZ71+BZ69 | CA64: =CA72+CA71+CA69
A65: Y/Y GAAP G&A growth, % | D65: =D64/C64-1 | E65: =E64/D64-1 | F65: =F64/E64-1 | K65: =K64/F64-1 | L65: =L64/G64-1 | M65: =M64/H64-1 | N65: =N64/I64-1 | O65: =O64/J64-1 | P65: =P64/K64-1 | Q65: =Q64/L64-1 | R65: =R64/M64-1 | ... BX65: =BX64/BS64-1 | BY65: =BY64/BX64-1 | BZ65: =BZ64/BY64-1 | CA65: =CA64/BZ64-1
A66: GAAP G&A Margin, % | C66: =C64/C34 | D66: =D64/D34 | E66: =E64/E34 | F66: =F64/F34 | G66: =G64/G34 | H66: =H64/H34 | I66: =I64/I34 | J66: =J64/J34 | ... CA66: =CA64/CA34
A67: Y/Y GAAP G&A Margin improvement, bps | D67: =-(D66-C66)*10000 | E67: =-(E66-D66)*10000 | F67: =-(F66-E66)*10000 | K67: =-(K66-F66)*10000 | L67: =-(L66-G66)*10000 | M67: =-(M66-H66)*10000 | N67: =-(N66-I66)*10000 | O67: =-(O66-J66)*10000 | P67: =-(P66-K66)*10000 | Q67: =-(Q66-L66)*10000 | R67: =-(R66-M66)*10000 | ... BX67: =-(BX66-BS66)*10000 | BY67: =-(BY66-BX66)*10000 | BZ67: =-(BZ66-BY66)*10000 | CA67: =-(CA66-BZ66)*10000
A69: SBC G&A, mm | D69: =D469 | E69: =E469 | F69: =F469 | G69: =G469 | H69: =H469 | I69: =I469 | J69: =J469 | K69: =K469 | ... BQ69: =BQ469 | BR69: =BR70*BR34 | BS69: =SUM(BO69,BP69,BQ69,BR69) | BT69: =BT70*BT34 | BU69: =BU70*BU34 | BV69: =BV70*BV34 | BW69: =BW70*BW34 | BX69: =SUM(BT69,BU69,BV69,BW69) | BY69: =BY70*BY34 | BZ69: =BZ70*BZ34 | CA69: =CA70*CA34
A70: SBC G&A as & of revenue, % | D70: =D69/D34 | E70: =E69/E34 | F70: =F69/F34 | G70: =G69/G34 | H70: =H69/H34 | I70: =I69/I34 | J70: =J69/J34 | K70: =K69/K34 | ... BQ70: =BQ69/BQ34 | BR70: 0.013 | BS70: =BS69/BS34 | BT70: 0.013 | BU70: 0.013 | BV70: 0.013 | BW70: 0.013 | BX70: =BX69/BX34 | BY70: 0.013 | BZ70: 0.013 | CA70: 0.013
A71: Other adjustments G&A, mm | D71: =D470 | E71: =E470 | F71: =F470 | G71: =G470 | H71: =H470 | I71: =I470 | J71: =J470 | K71: =K470 | ... BQ71: =BQ470 | BR71: 6.2 | BS71: =SUM(BO71,BP71,BQ71,BR71) | BT71: 6.2 | BU71: 6.2 | BV71: 6.2 | BW71: 6.2 | BX71: =SUM(BT71,BU71,BV71,BW71) | BY71: 24.8 | BZ71: 24.8 | CA71: 24.8
A72: Non-GAAP G&A, mm | D72: =D64-D69-D71 | E72: =E64-E69-E71 | F72: =F64-F69-F71 | G72: =G64-G69-G71 | H72: =H64-H69-H71 | I72: =I64-I69-I71 | J72: =J64-J69-J71 | K72: =K64-K69-K71 | ... BQ72: =BQ64-BQ69-BQ71 | BR72: =BR74*BR34 | BS72: =SUM(BO72,BP72,BQ72,BR72) | BT72: =BT74*BT34 | BU72: =BU74*BU34 | BV72: =BV74*BV34 | BW72: =BW74*BW34 | BX72: =SUM(BT72,BU72,BV72,BW72) | BY72: =BY74*BY34 | BZ72: =BZ74*BZ34 | CA72: =CA74*CA34
A73: Y/Y Non-GAAP G&A growth, % | E73: =E72/D72-1 | F73: =F72/E72-1 | K73: =K72/F72-1 | L73: =L72/G72-1 | M73: =M72/H72-1 | N73: =N72/I72-1 | O73: =O72/J72-1 | P73: =P72/K72-1 | Q73: =Q72/L72-1 | R73: =R72/M72-1 | ... BX73: =BX72/BS72-1 | BY73: =BY72/BX72-1 | BZ73: =BZ72/BY72-1 | CA73: =CA72/BZ72-1
A74: Non-GAAP G&A Margin, % | D74: =D72/D34 | E74: =E72/E34 | F74: =F72/F34 | G74: =G72/G34 | H74: =H72/H34 | I74: =I72/I34 | J74: =J72/J34 | K74: =K72/K34 | ... BQ74: =BQ72/BQ34 | BR74: =BM74-BR75/10000 | BS74: =BS72/BS34 | BT74: =BO74-BT75/10000 | BU74: =BP74-BU75/10000 | BV74: =BQ74-BV75/10000 | BW74: =BR74-BW75/10000 | BX74: =BX72/BX34 | BY74: =BX74-BY75/10000 | BZ74: =BY74-BZ75/10000 | CA74: =BZ74-CA75/10000
A75: Y/Y Non-GAAP G&A Margin improvement, bps | E75: =-(E74-D74)*10000 | F75: =-(F74-E74)*10000 | K75: =-(K74-F74)*10000 | L75: =-(L74-G74)*10000 | M75: =-(M74-H74)*10000 | N75: =-(N74-I74)*10000 | O75: =-(O74-J74)*10000 | P75: =-(P74-K74)*10000 | Q75: =-(Q74-L74)*10000 | R75: =-(R74-M74)*10000 | ... BQ75: =-(BQ74-BL74)*10000 | BR75: 0 | BS75: =-(BS74-BN74)*10000 | BT75: 200 | BU75: 100 | BV75: 0 | BW75: 0 | BX75: =-(BX74-BS74)*10000 | BY75: 0 | BZ75: 0 | CA75: 0
A77: GAAP S&M, mm | C77: =C472 | D77: =D472 | E77: =E472 | F77: =F472 | G77: =G472 | H77: =H472 | I77: =I472 | J77: =J472 | ... BQ77: =BQ472 | BR77: =BR85+BR84+BR82 | BS77: =SUM(BO77,BP77,BQ77,BR77) | BT77: =BT85+BT84+BT82 | BU77: =BU85+BU84+BU82 | BV77: =BV85+BV84+BV82 | BW77: =BW85+BW84+BW82 | BX77: =SUM(BT77,BU77,BV77,BW77) | BY77: =BY85+BY84+BY82 | BZ77: =BZ85+BZ84+BZ82 | CA77: =CA85+CA84+CA82
A78: Y/Y GAAP S&M growth, % | D78: =D77/C77-1 | E78: =E77/D77-1 | F78: =F77/E77-1 | K78: =K77/F77-1 | L78: =L77/G77-1 | M78: =M77/H77-1 | N78: =N77/I77-1 | O78: =O77/J77-1 | P78: =P77/K77-1 | Q78: =Q77/L77-1 | R78: =R77/M77-1 | ... BX78: =BX77/BS77-1 | BY78: =BY77/BX77-1 | BZ78: =BZ77/BY77-1 | CA78: =CA77/BZ77-1
A79: GAAP S&M Margin, % | C79: =C77/C34 | D79: =D77/D34 | E79: =E77/E34 | F79: =F77/F34 | G79: =G77/G34 | H79: =H77/H34 | I79: =I77/I34 | J79: =J77/J34 | ... CA79: =CA77/CA34
A80: Y/Y GAAP S&M Margin improvement, bps | D80: =-(D79-C79)*10000 | E80: =-(E79-D79)*10000 | F80: =-(F79-E79)*10000 | K80: =-(K79-F79)*10000 | L80: =-(L79-G79)*10000 | M80: =-(M79-H79)*10000 | N80: =-(N79-I79)*10000 | O80: =-(O79-J79)*10000 | P80: =-(P79-K79)*10000 | Q80: =-(Q79-L79)*10000 | R80: =-(R79-M79)*10000 | ... BX80: =-(BX79-BS79)*10000 | BY80: =-(BY79-BX79)*10000 | BZ80: =-(BZ79-BY79)*10000 | CA80: =-(CA79-BZ79)*10000
A82: SBC S&M, mm | D82: =D473 | E82: =E473 | F82: =F473 | G82: =G473 | H82: =H473 | I82: =I473 | J82: =J473 | K82: =K473 | ... BQ82: =BQ473 | BR82: =BR83*BR34 | BS82: =SUM(BO82,BP82,BQ82,BR82) | BT82: =BT83*BT34 | BU82: =BU83*BU34 | BV82: =BV83*BV34 | BW82: =BW83*BW34 | BX82: =SUM(BT82,BU82,BV82,BW82) | BY82: =BY83*BY34 | BZ82: =BZ83*BZ34 | CA82: =CA83*CA34
A83: SBC S&M as & of revenue, % | D83: =D82/D34 | E83: =E82/E34 | F83: =F82/F34 | G83: =G82/G34 | H83: =H82/H34 | I83: =I82/I34 | J83: =J82/J34 | K83: =K82/K34 | ... BQ83: =BQ82/BQ34 | BR83: 0.016 | BS83: =BS82/BS34 | BT83: 0.017 | BU83: 0.017 | BV83: 0.017 | BW83: 0.017 | BX83: =BX82/BX34 | BY83: 0.017 | BZ83: 0.017 | CA83: 0.017
A84: Other adjustments S&M, mm | D84: =D474 | E84: =E474 | F84: =F474 | G84: =G474 | H84: =H474 | I84: =I474 | J84: =J474 | K84: =K474 | ... BQ84: =BQ474 | BR84: 4 | BS84: =SUM(BO84,BP84,BQ84,BR84) | BT84: 6 | BU84: 6 | BV84: 6 | BW84: 6 | BX84: =SUM(BT84,BU84,BV84,BW84) | BY84: 24 | BZ84: 24 | CA84: 24
A85: Non-GAAP S&M, mm | D85: =D77-D82-D84 | E85: =E77-E82-E84 | F85: =F77-F82-F84 | G85: =G77-G82-G84 | H85: =H77-H82-H84 | I85: =I77-I82-I84 | J85: =J77-J82-J84 | K85: =K77-K82-K84 | ... BQ85: =BQ77-BQ82-BQ84 | BR85: =BR87*BR34 | BS85: =SUM(BO85,BP85,BQ85,BR85) | BT85: =BT87*BT34 | BU85: =BU87*BU34 | BV85: =BV87*BV34 | BW85: =BW87*BW34 | BX85: =SUM(BT85,BU85,BV85,BW85) | BY85: =BY87*BY34 | BZ85: =BZ87*BZ34 | CA85: =CA87*CA34
A86: Y/Y Non-GAAP S&M growth, % | E86: =E85/D85-1 | F86: =F85/E85-1 | K86: =K85/F85-1 | L86: =L85/G85-1 | M86: =M85/H85-1 | N86: =N85/I85-1 | O86: =O85/J85-1 | P86: =P85/K85-1 | Q86: =Q85/L85-1 | R86: =R85/M85-1 | ... BX86: =BX85/BS85-1 | BY86: =BY85/BX85-1 | BZ86: =BZ85/BY85-1 | CA86: =CA85/BZ85-1
A87: Non-GAAP S&M Margin, % | D87: =D85/D34 | E87: =E85/E34 | F87: =F85/F34 | G87: =G85/G34 | H87: =H85/H34 | I87: =I85/I34 | J87: =J85/J34 | K87: =K85/K34 | ... BQ87: =BQ85/BQ34 | BR87: =BM87-BR88/10000 | BS87: =BS85/BS34 | BT87: =BO87-BT88/10000 | BU87: =BP87-BU88/10000 | BV87: =BQ87-BV88/10000 | BW87: =BR87-BW88/10000 | BX87: =BX85/BX34 | BY87: =BX87-BY88/10000 | BZ87: =BY87-BZ88/10000 | CA87: =BZ87-CA88/10000
A88: Y/Y Non-GAAP S&M Margin improvement, bps | E88: =-(E87-D87)*10000 | F88: =-(F87-E87)*10000 | K88: =-(K87-F87)*10000 | L88: =-(L87-G87)*10000 | M88: =-(M87-H87)*10000 | N88: =-(N87-I87)*10000 | O88: =-(O87-J87)*10000 | P88: =-(P87-K87)*10000 | Q88: =-(Q87-L87)*10000 | R88: =-(R87-M87)*10000 | ... BQ88: =-(BQ87-BL87)*10000 | BR88: -50 | BS88: =-(BS87-BN87)*10000 | BT88: 150 | BU88: 200 | BV88: 0 | BW88: 0 | BX88: =-(BX87-BS87)*10000 | BY88: 0 | BZ88: 0 | CA88: 0
A90: Amortization of acquired intangibles, mm | C90: =C351 | D90: =D351 | E90: =E351 | F90: =F351 | G90: =G351 | H90: =H351 | I90: =I351 | J90: =J351 | ... BQ90: =BQ351 | BR90: =BR167 | BS90: =SUM(BO90,BP90,BQ90,BR90) | BT90: =BT167 | BU90: =BU167 | BV90: =BV167 | BW90: =BW167 | BX90: =SUM(BT90,BU90,BV90,BW90) | BY90: =BY167 | BZ90: =BZ167 | CA90: =CA167
A91: Other GAAP expenses, mm | C91: =SUM(C352:C354) | D91: =SUM(D352:D354) | E91: =SUM(E352:E354) | F91: =SUM(F352:F354) | G91: =SUM(G352:G354) | H91: =SUM(H352:H354) | I91: =SUM(I352:I354) | J91: =SUM(J352:J354) | ... BQ91: =SUM(BQ352:BQ354) | BR91: -5 | BS91: =SUM(BO91,BP91,BQ91,BR91) | BT91: 5.8 | BU91: 5.8 | BV91: 5.8 | BW91: 5.8 | BX91: =SUM(BT91,BU91,BV91,BW91) | BY91: 23.2 | BZ91: 23.2 | CA91: 23.2
A93: GAAP Operating Income, mm | C93: =C36-C51-C64-C77-C90-C91 | D93: =D36-D51-D64-D77-D90-D91 | E93: =E36-E51-E64-E77-E90-E91 | F93: =F36-F51-F64-F77-F90-F91 | G93: =G36-G51-G64-G77-G90-G91 | H93: =H36-H51-H64-H77-H90-H91 | I93: =I36-I51-I64-I77-I90-I91 | J93: =J36-J51-J64-J77-J90-J91 | ... CA93: =CA36-CA51-CA64-CA77-CA90-CA91
A94: Y/Y GAAP Operating Income growth, % | D94: =D93/C93-1 | E94: =E93/D93-1 | F94: =F93/E93-1 | K94: =K93/F93-1 | L94: =L93/G93-1 | M94: =M93/H93-1 | N94: =N93/I93-1 | O94: =O93/J93-1 | P94: =P93/K93-1 | Q94: =Q93/L93-1 | R94: =R93/M93-1 | ... BX94: =BX93/BS93-1 | BY94: =BY93/BX93-1 | BZ94: =BZ93/BY93-1 | CA94: =CA93/BZ93-1
A95: GAAP Operating Income margin, % | C95: =C93/C34 | D95: =D93/D34 | E95: =E93/E34 | F95: =F93/F34 | G95: =G93/G34 | H95: =H93/H34 | I95: =I93/I34 | J95: =J93/J34 | ... CA95: =CA93/CA34
A96: Y/Y GAAP Operating Income margin improvement, bps | D96: =(D95-C95)*10000 | E96: =(E95-D95)*10000 | F96: =(F95-E95)*10000 | K96: =(K95-F95)*10000 | L96: =(L95-G95)*10000 | M96: =(M95-H95)*10000 | N96: =(N95-I95)*10000 | O96: =(O95-J95)*10000 | P96: =(P95-K95)*10000 | Q96: =(Q95-L95)*10000 | R96: =(R95-M95)*10000 | ... BX96: =(BX95-BS95)*10000 | BY96: =(BY95-BX95)*10000 | BZ96: =(BZ95-BY95)*10000 | CA96: =(CA95-BZ95)*10000
A98: Other Non-GAAP Operating Items, mm | D98: =D477 | E98: =E477 | F98: =F477 | G98: =G477 | H98: =H477 | I98: =I477 | J98: =J477 | K98: =K477 | ... BQ98: =BQ477 | BR98: 0 | BS98: =SUM(BO98,BP98,BQ98,BR98) | BT98: 0 | BU98: 0 | BV98: 0 | BW98: 0 | BX98: =SUM(BT98,BU98,BV98,BW98) | BY98: 0 | BZ98: 0 | CA98: 0
A99: Non-GAAP Operating Income, mm | D99: =D45-D59-D72-D85-D98 | E99: =E45-E59-E72-E85-E98 | F99: =F45-F59-F72-F85-F98 | G99: =G45-G59-G72-G85-G98 | H99: =H45-H59-H72-H85-H98 | I99: =I45-I59-I72-I85-I98 | J99: =J45-J59-J72-J85-J98 | K99: =K45-K59-K72-K85-K98 | ... CA99: =CA45-CA59-CA72-CA85-CA98
A100: =A479 | BR100: =BR479 | BS100: =BS479 | BT100: =BT479 | BU100: =BU479 | BV100: =BV479 | BW100: =BW479 | BX100: =BX479 | BY100: =BY479 | ... CA100: =CA479
A101: Y/Y Non-GAAP Operating Income growth, % | E101: =E99/D99-1 | F101: =F99/E99-1 | K101: =K99/F99-1 | L101: =L99/G99-1 | M101: =M99/H99-1 | N101: =N99/I99-1 | O101: =O99/J99-1 | P101: =P99/K99-1 | Q101: =Q99/L99-1 | R101: =R99/M99-1 | ... BX101: =BX99/BS99-1 | BY101: =BY99/BX99-1 | BZ101: =BZ99/BY99-1 | CA101: =CA99/BZ99-1
A102: Non-GAAP Operating Income margin, % | D102: =D99/D34 | E102: =E99/E34 | F102: =F99/F34 | G102: =G99/G34 | H102: =H99/H34 | I102: =I99/I34 | J102: =J99/J34 | K102: =K99/K34 | ... CA102: =CA99/CA34
A103: =A335 | BR103: =BR335 | BS103: =BS335 | BT103: =BT335 | BU103: =BU335 | BV103: =BV335 | BW103: =BW335 | BX103: =BX335 | BY103: =BY335 | ... CA103: =CA335
A104: Y/Y Non-GAAP Operating Income margin improvement, bps | E104: =(E102-D102)*10000 | F104: =(F102-E102)*10000 | K104: =(K102-F102)*10000 | L104: =(L102-G102)*10000 | M104: =(M102-H102)*10000 | N104: =(N102-I102)*10000 | O104: =(O102-J102)*10000 | P104: =(P102-K102)*10000 | Q104: =(Q102-L102)*10000 | R104: =(R102-M102)*10000 | ... BX104: =(BX102-BS102)*10000 | BY104: =(BY102-BX102)*10000 | BZ104: =(BZ102-BY102)*10000 | CA104: =(CA102-BZ102)*10000
A106: Key Metrics - Y/Y Cost Granularity (FS)
A107: Previous Cost of product and maintenance, mm | P107: =K343 | U107: =P343 | V107: =Q343 | W107: =R343 | X107: =S343 | Y107: =T343 | Z107: =U343 | AA107: =V343 | AB107: =W343 | ... AM107: =AH343 | AO107: =AJ343 | AP107: =AK343 | AQ107: =AL343 | AR107: =AM343 | AT107: =AO343 | AU107: =AP343 | AV107: =AQ343 | AW107: =AR343 | AY107: =AT343 | AZ107: =AU343 | BA107: =AV343 | BB107: =AW343 | BD107: =AY343 | BE107: =AZ343 | BF107: =BA343 | BG107: =BB343 | BI107: =BD343 | BJ107: =BE343 | BK107: =BF343 | BL107: =BG343 | BN107: =BI343 | BO107: =BJ343 | BP107: =BK343 | BQ107: =BL343
A108: COPM - Change in emulation and prototyping hardware costs, mm | P108: 10.2 | U108: -5.1 | V108: 2 | W108: 10.5 | X108: -2.1 | Y108: =Z108-SUM(V108,W108,X108) | Z108: 28 | AB108: -2.7 | AC108: -3.5 | AD108: =AE108-SUM(AA108,AB108,AC108) | AE108: -22.9 | AF108: -1.8 | AG108: 1.7 | AH108: 2 | AI108: =AJ108-SUM(AF108,AG108,AH108) | AJ108: 17.7 | AK108: 8.7 | AL108: 1.4 | AM108: 4.3 | AO108: 12.6 | AP108: 3.5 | AQ108: 12 | AR108: 21.7 | AT108: 34.1 | AU108: 8.5 | AV108: -1.8 | AW108: -12.8 | AY108: -12.3 | AZ108: 7.1 | BA108: 14.8 | BB108: 10.3 | BD108: 51.6 | BE108: 25.2 | BF108: 2.5 | BG108: 20.1 | BI108: 49.1 | BJ108: -26.2 | BK108: 17 | BL108: 12.8 | BN108: 80.1 | BO108: 30.1 | BP108: 36.9 | BQ108: 8.6
A109: COPM - Professional services, mm | AT109: 2.5
A110: COPM - Change in salary, benefits and other employee-related costs, mm | P110: 1.5 | Y110: =Z110-SUM(V110,W110,X110) | AA110: -1.4 | AB110: -1.5 | AC110: -0.4 | AD110: =AE110-SUM(AA110,AB110,AC110) | AO110: 3.6 | AT110: 1.8 | AW110: 1.5 | AY110: 2.6 | BD110: 4.9 | BE110: 2.6 | BF110: 1.9 | BG110: 1 | BI110: 4.4 | BN110: 4.9 | BP110: 5.1 | BQ110: 0.1
A111: COPM - Change amortization of acquired intangibles, mm | P111: 12.9 | U111: 3.6 | V111: 0.5 | W111: 0.4 | X111: 0.5 | Y111: =Z111-SUM(V111,W111,X111) | Z111: 1.9 | AA111: -0.1 | AB111: 0.4 | AC111: -0.4 | AD111: =AE111-SUM(AA111,AB111,AC111) | AE111: -0.6 | AF111: -0.3 | AG111: -0.9 | AH111: -0.7 | AI111: =AJ111-SUM(AF111,AG111,AH111) | AJ111: -2.6 | AK111: -0.4 | AL111: 1.3 | AM111: 0.4 | AO111: 1.8 | AP111: 1 | AQ111: 0.2 | AR111: =11.4-9.9 | AU111: =11.8-10.9 | AV111: =12.2-11.5 | AW111: 0.4 | AY111: 1.4 | AZ111: 0.2 | BA111: -2.1 | BB111: -2.9 | BD111: -6.3 | BF111: 0.5 | BI111: 2.5 | BJ111: 1 | BK111: 2.9 | BL111: 6.6 | BN111: 16.3 | BO111: 5.2
A112: COPM - Change in product and maintenance-related costs, mm
A113: COPM - Change in other items, mm | P113: -0.5 | U113: 0.9 | V113: -0.4 | W113: 0.4 | X113: -0.9 | Y113: =Z113-SUM(V113,W113,X113) | Z113: -2.3 | AA113: 1 | AB113: -0.4 | AC113: 0.4 | AD113: =AE113-SUM(AA113,AB113,AC113)-0.1 | AE113: -3.1 | AF113: 0.1 | AG113: 0.5 | AH113: 0.3 | AI113: =AJ113-SUM(AF113,AG113,AH113) | AJ113: 1.2 | AK113: 0.5 | AL113: 0.6 | AM113: 0.6 | AO113: -1.9 | AP113: 0.4 | AQ113: 0.1 | AR113: -0.1 | AT113: -1.7 | AU113: 0.1 | AV113: 1.2 | AW113: =AW114-SUM(AW107:AW112) | AY113: =AY114-SUM(AY107:AY112) | AZ113: 0.6 | BA113: =BA114-SUM(BA107:BA112) | BB113: =BB114-SUM(BB107:BB112) | BD113: =BD114-SUM(BD107:BD112) | BE113: =BE114-SUM(BE107:BE112) | BF113: =BF114-SUM(BF107:BF112) | BG113: =BG114-SUM(BG107:BG112) | BI113: =BI114-SUM(BI107:BI112) | BJ113: =BJ114-SUM(BJ107:BJ112) | BK113: =BK114-SUM(BK107:BK112) | BL113: =BL114-SUM(BL107:BL112) | BN113: =BN114-SUM(BN107:BN112) | BO113: =BO114-SUM(BO107:BO112) | BP113: =BP114-SUM(BP107:BP112) | BQ113: =BQ114-SUM(BQ107:BQ112)
...

Sheet Exec Comp
A1: =MO.CompanyName
A2: =MO.Ticker | C2: =Model!C2 | D2: =Model!D2 | E2: =Model!E2 | F2: =Model!F2 | G2: =Model!G2 | H2: =Model!H2 | I2: =Model!I2 | J2: =Model!J2 | ... CA2: =Model!CA2
A3: =MO.TradingCurrency | B3: =MO.LastPrice | C3: =INDEX(MO_Common_FPDays,0,MATCH(C$5,MO_Common_ColumnHeader,0)) | D3: =INDEX(MO_Common_FPDays,0,MATCH(D$5,MO_Common_ColumnHeader,0)) | E3: =INDEX(MO_Common_FPDays,0,MATCH(E$5,MO_Common_ColumnHeader,0)) | F3: =INDEX(MO_Common_FPDays,0,MATCH(F$5,MO_Common_ColumnHeader,0)) | G3: =INDEX(MO_Common_FPDays,0,MATCH(G$5,MO_Common_ColumnHeader,0)) | H3: =INDEX(MO_Common_FPDays,0,MATCH(H$5,MO_Common_ColumnHeader,0)) | I3: =INDEX(MO_Common_FPDays,0,MATCH(I$5,MO_Common_ColumnHeader,0)) | J3: =INDEX(MO_Common_FPDays,0,MATCH(J$5,MO_Common_ColumnHeader,0)) | ... CA3: =INDEX(MO_Common_FPDays,0,MATCH(CA$5,MO_Common_ColumnHeader,0))
A4: =MO.DataSourceName | B4: =MO.RealTime | C4: =INDEX(MO_Common_QEndDate,0,MATCH(C$5,MO_Common_ColumnHeader,0)) | D4: =INDEX(MO_Common_QEndDate,0,MATCH(D$5,MO_Common_ColumnHeader,0)) | E4: =INDEX(MO_Common_QEndDate,0,MATCH(E$5,MO_Common_ColumnHeader,0)) | F4: =INDEX(MO_Common_QEndDate,0,MATCH(F$5,MO_Common_ColumnHeader,0)) | G4: =INDEX(MO_Common_QEndDate,0,MATCH(G$5,MO_Common_ColumnHeader,0)) | H4: =INDEX(MO_Common_QEndDate,0,MATCH(H$5,MO_Common_ColumnHeader,0)) | I4: =INDEX(MO_Common_QEndDate,0,MATCH(I$5,MO_Common_ColumnHeader,0)) | J4: =INDEX(MO_Common_QEndDate,0,MATCH(J$5,MO_Common_ColumnHeader,0)) | ... CA4: =INDEX(MO_Common_QEndDate,0,MATCH(CA$5,MO_Common_ColumnHeader,0))
A5: =MO.ReportFX | C5: =Model!C5 | D5: =Model!D5 | E5: =Model!E5 | F5: =Model!F5 | G5: =Model!G5 | H5: =Model!H5 | I5: =Model!I5 | J5: =Model!J5 | ... CA5: =Model!CA5
A6: Executive compensation
A7: Outgoing CEO - Base Pay, 000s | AY7: 720.192
A8: Outgoing CEO - Stock Awards, 000s | AY8: 4500.004
A9: Outgoing CEO - Option Awards, 000s | AY9: 4499.646
A10: Outgoing CEO - Non-equity incentive plans, 000s | AY10: 1372.29
A11: Outgoing CEO - All other compensation, 000s | AY11: 73.884
A12: Outgoing CEO - Total Comp, 000s | AY12: =SUM(AY7:AY11)
A13: Incoming CEO - Base Pay, 000s | AY13: 604.808
A14: Incoming CEO - Stock Awards, 000s | AY14: 2499.956
A15: Incoming CEO - Option Awards, 000s | AY15: 17496.404
A16: Incoming CEO - Non-equity incentive plans, 000s | AY16: 1109.054
A17: Incoming CEO - All other compensation, 000s | AY17: 25.572
A18: Incoming CEO - Total Comp, 000s | AY18: =SUM(AY13:AY17)
A20: CEO - Base Pay, 000s | AT20: 738.942 | AY20: =SUM(AY7,AY13) | BD20: 725 | BI20: 750
A21: CEO - Stock Awards, 000s | AT21: 3750 | AY21: =SUM(AY8,AY14) | BD21: 25318.495 | BI21: 7702.791
A22: CEO - Option Awards, 000s | AT22: 3748.545 | AY22: =SUM(AY9,AY15) | BD22: 4779.658 | BI22: 7689.913
A23: CEO - Non-equity incentive plans, 000s | AT23: 1353.419 | AY23: =SUM(AY10,AY16) | BD23: 1381.859 | BI23: 1187.386
A24: CEO - All other compensation, 000s | AT24: 13.734 | AY24: =SUM(AY11,AY17) | BD24: 11.022 | BI24: 11.772
A25: CEO - Total Comp, 000s | AT25: =SUM(AT20:AT24) | AY25: =SUM(AY20:AY24) | BD25: =SUM(BD20:BD24) | BI25: =SUM(BI20:BI24)
A26: CEO - comp tied to equity, % | AT26: =SUM(AT21,AT22)/AT25 | AY26: =SUM(AY21,AY22)/AY25 | BD26: =SUM(BD21,BD22)/BD25 | BI26: =SUM(BI21,BI22)/BI25
A27: Market Cap - EoP, mm | AT27: =Model!AT982 | AU27: =Model!AU982 | AV27: =Model!AV982 | AW27: =Model!AW982 | AX27: =Model!AX982 | AY27: =Model!AY982 | AZ27: =Model!AZ982 | BA27: =Model!BA982 | ... BQ27: =Model!BQ982
A29: CEO - Options 02/09/22 # of unexercised exercisable options, 000s | AT29: 500
A30: CEO - Options 02/09/22 exercise price, $ | AT30: 17.16
A32: CEO - Options 02/08/23 # of unexercised exercisable options, 000s | AT32: 500
A33: CEO - Options 02/08/23 exercise price, $ | AT33: 19.6
A35: CEO - Options 02/21/24 # of unexercised exercisable options, 000s | AT35: 407.291
A36: CEO - Options 02/21/24 # of unexercised unexercisable options, 000s | AT36: 17.709
A37: CEO - Options 02/21/24 exercise price, $ | AT37: 30.79
A39: CEO - Options 02/06/25 # of unexercised exercisable options, 000s | AT39: 190.754 | AY39: 95.724 | BD39: 99.886 | BI39: 99.886
A40: CEO - Options 02/06/25 # of unexercised unexercisable options, 000s | AT40: 78.547 | AY40: 4.162 | BD40: 0 | BI40: 0
A41: CEO - Options 02/06/25 exercise price, $ | AT41: 39.58 | AY41: 39.58 | BD41: 39.58 | BI41: 39.58
A43: CEO - Options 02/22/26 # of unexercised exercisable options, 000s | AT43: 94.177 | AY43: 65.981 | BD43: 89.269 | BI43: 93.151
A44: CEO - Options 02/22/26 # of unexercised unexercisable options, 000s | AT44: 111.302 | AY44: 27.17 | BD44: 3.882 | BI44: 0
A45: CEO - Options 02/22/26 exercise price, $ | AT45: 56.57 | AY45: 56.57 | BD45: 56.57 | BI45: 56.57
A47: CEO - Options 02/14/27 # of unexercised exercisable options, 000s | AT47: 41.257 | AY47: 32.917 | BD47: 50.873 | BI47: 68.828
A48: CEO - Options 02/14/27 # of unexercised unexercisable options, 000s | AT48: 156.778 | AY48: 38.904 | BD48: 20.948 | BI48: 2.993
A49: CEO - Options 02/14/27 exercise price, $ | AT49: 78.76 | AY49: 78.76 | BD49: 78.76 | BI49: 78.76
A51: CEO - Options 02/25/28 # of unexercised exercisable options, 000s | AY51: 13.044 | BD51: 28.698 | BI51: 44.351
A52: CEO - Options 02/25/28 # of unexercised unexercisable options, 000s | AY52: 49.57 | BD52: 33.916 | BI52: 18.263
A53: CEO - Options 02/25/28 exercise price, $ | AY53: 138.02 | BD53: 138.02 | BI53: 138.02
A55: CEO - Options 12/15/28 # of unexercised exercisable options, 000s | BD55: 70.248 | BI55: 140.496
A56: CEO - Options 12/15/28 # of unexercised unexercisable options, 000s | AY56: 280.993 | BD56: 210.745 | BI56: 140.497
A57: CEO - Options 12/15/28 exercise price, $ | AY57: 184.27 | BD57: 184.27 | BI57: 184.27
A59: CEO - Options 03/15/29 # of unexercised exercisable options, 000s | BD59: 18.3 | BI59: 42.7
A60: CEO - Options 03/15/29 # of unexercised unexercisable options, 000s | BD60: 79.301 | BI60: 54.901
A61: CEO - Options 03/15/29 exercise price, $ | BD61: 142.5 | BI61: 142.5
A63: CEO - Options 03/15/30 # of unexercised exercisable options, 000s | BI63: 20.323
A64: CEO - Options 03/15/30 # of unexercised unexercisable options, 000s | BI64: 88.067
A65: CEO - Options 03/15/30 exercise price, $ | BI65: 202.94
A67: CEO - EoP shares beneficially owned, 000s | AT67: 3819.991 | AY67: 215.571 | BD67: 576.321 | BI67: 595.096
A69: CFO - Base Pay, 000s | AT69: 448.462 | AY69: 500 | BD69: 550 | BI69: 575
A70: CFO - Stock Awards, 000s | AT70: 1419.019 | AY70: 7310.069 | BD70: 8528.597 | BI70: 3050.188
A71: CFO - Option Awards, 000s | AT71: 730.724 | AY71: 1189.938 | BD71: 1218.8 | BI71: 1568.773
A72: CFO - Non-equity incentive plans, 000s | AT72: 688.197 | AY72: 788.207 | BD72: 845.326 | BI72: 705.606
A73: CFO - All other compensation, 000s | AT73: 10.16 | AY73: 10.572 | BD73: 11.022 | BI73: 11.772
A74: CFO - Total Comp, 000s | AT74: =SUM(AT69:AT73) | AY74: =SUM(AY69:AY73) | BD74: =SUM(BD69:BD73) | BI74: =SUM(BI69:BI73)
A75: CFO - comp tied to equity, % | AT75: =SUM(AT70,AT71)/AT74 | AY75: =SUM(AY70,AY71)/AY74 | BD75: =SUM(BD70,BD71)/BD74 | BI75: =SUM(BI70,BI71)/BI74
A77: CFO - Options 02/06/25 # of unexercised exercisable options, 000s | AT77: 29.48 | AY77: 39.884
A78: CFO - Options 02/06/25 # of unexercised unexercisable options, 000s | AT78: 12.139 | AY78: 1.735
A79: CFO - Options 02/06/25 exercise price, $ | AT79: 39.58 | AY79: 39.58
A81: CFO - Options 02/22/26 # of unexercised exercisable options, 000s | AT81: 17.077 | AY81: 26.392 | BD81: 35.707
A82: CFO - Options 02/22/26 # of unexercised unexercisable options, 000s | AT82: 20.183 | AY82: 10.868 | BD82: 1.553
A83: CFO - Options 02/22/26 exercise price, $ | AT83: 56.57 | AY83: 56.57 | BD83: 56.57
A85: CFO - Options 02/14/27 # of unexercised exercisable options, 000s | AT85: 8.042 | AY85: 17.693 | BD85: 27.344 | BI85: 4.391
A86: CFO - Options 02/14/27 # of unexercised unexercisable options, 000s | AT86: 30.562 | AY86: 20.911 | BD86: 10.868 | BI86: 1.609
A87: CFO - Options 02/14/27 exercise price, $ | AT87: 78.76 | AY87: 78.76 | BD87: 78.76 | BI87: 78.76
A89: CFO - Options 02/25/28 # of unexercised exercisable options, 000s | AY89: 6.208 | BD89: 10.733 | BI89: 16.587
A90: CFO - Options 02/25/28 # of unexercised unexercisable options, 000s | AY90: 23.597 | BD90: 12.685 | BI90: 6.831
A91: CFO - Options 02/25/28 exercise price, $ | AY91: 138.02 | BD91: 138.02 | BI91: 138.02
A93: CFO - Options 02/25/28 # of unexercised exercisable options, 000s | BD93: 2.927 | BI93: 4.524
A94: CFO - Options 02/25/28 # of unexercised unexercisable options, 000s | BD94: 3.46 | BI94: 1.863
A95: CFO - Options 02/25/28 exercise price, $ | BD95: 138.02 | BI95: 138.02
A97: CFO - Options 03/15/29 # of unexercised exercisable options, 000s | BD97: 4.666 | BI97: 10.888
A98: CFO - Options 03/15/29 # of unexercised unexercisable options, 000s | BD98: 20.222 | BI98: 14
A99: CFO - Options 03/15/29 exercise price, $ | BD99: 142.5 | BI99: 142.5
A101: CFO - Options 03/15/30 # of unexercised exercisable options, 000s | BI101: 4.146
A102: CFO - Options 03/15/30 # of unexercised unexercisable options, 000s | BI102: 17.966
A103: CFO - Options 03/15/30 exercise price, $ | BI103: 202.94
A105: CFO - EoP shares beneficially owned, 000s | AT105: 248.662 | AY105: 145.062 | BD105: 211.444 | BI105: 89.097
A107: CRO - Base Pay, 000s | AY107: 500 | BD107: 550 | BI107: 575
A108: CRO - Stock Awards, 000s | AY108: 1980.035 | BD108: 8370.707 | BI108: 2711.278
A109: CRO - Option Awards, 000s | AY109: 1019.901 | BD109: 1137.557 | BI109: 1394.457
A110: CRO - Non-equity incentive plans, 000s | AY110: 784.476 | BD110: 845.326 | BI110: 712.722
A111: CRO - All other compensation, 000s | AY111: 10.572 | BD111: 11.022 | BI111: 11.772
A112: CRO (Chief Revenue Officer) - Total Comp , 000s | AY112: =SUM(AY107:AY111) | BD112: =SUM(BD107:BD111) | BI112: =SUM(BI107:BI111)
A113: CRO - comp tied to equity, % | AY113: =SUM(AY108,AY109)/AY112 | BD113: =SUM(BD108,BD109)/BD112 | BI113: =SUM(BI108,BI109)/BI112
A115: CRO - Options 02/06/25 # of unexercised exercisable options, 000s | AY115: 4.717
A116: CRO - Options 02/06/25 # of unexercised unexercisable options, 000s | AY116: 2.359
A117: CRO - Options 02/06/25 exercise price, $ | AY117: 39.58
A119: CRO - Options 02/22/26 # of unexercised exercisable options, 000s | AY119: 4.366 | BD119: 4.367
A120: CRO - Options 02/22/26 # of unexercised unexercisable options, 000s | AY120: 12.227 | BD120: 1.747
A121: CRO - Options 02/22/26 exercise price, $ | AY121: 56.57 | BD121: 56.57
A123: CRO - Options 02/14/27 # of unexercised exercisable options, 000s | AY123: 2.992 | BD123: 3.741 | BI123: 6.733
A124: CRO - Options 02/14/27 # of unexercised unexercisable options, 000s | AY124: 19.452 | BD124: 10.474 | BI124: 1.497
A125: CRO - Options 02/14/27 exercise price, $ | AY125: 78.76 | BD125: 78.76 | BI125: 78.76
...

Sheet Guidance
B1: =MO.CompanyName
B2: Most Recent Period: | F2: =UL.MRQ
I4: Guidance | M4: Model | P4: Difference vs. Mid | S4: Update Log
B5: Type | D5: Item | E5: Item Name | F5: Fiscal Period | G5: Base Period | I5: Low | J5: High | K5: Mid | M5: Type | N5: Output | P5: Absolute | Q5: Relative | S5: Date | T5: Link
A6: 958 | B6: =IF(INDEX(MO_SNA_IsHistoricalPeriod,,MATCH(F6,MO_Common_ColumnHeader,0)),"Historical","Forward") | D6: Recurring Revenue % | F6: FY2025 | I6: 0.8 | J6: 0.8 | K6: =AVERAGE(I6:J6) | M6: =IF(INDEX(MO_SNA_IsHistoricalPeriod,,MATCH(F6,MO_Common_ColumnHeader,0)),"Actual","Estimate") | N6: =IFERROR(INDEX(INDIRECT(E6),0,MATCH(F6,MO_Common_ColumnHeader,0)),"N/A") | P6: =IF(ISNUMBER(N6),N6-K6,"N/A") | Q6: =IFERROR(IF(ISNUMBER(N6),(N6-K6)/ABS(K6),"N/A"),"N/A") | S6: 45957 | T6: CFO Commentary
A7: 957 | B7: =IF(INDEX(MO_SNA_IsHistoricalPeriod,,MATCH(F7,MO_Common_ColumnHeader,0)),"Historical","Forward") | D7: Revenue from Beginning Backlog % | F7: FY2025 | I7: 0.7 | J7: 0.7 | K7: =AVERAGE(I7:J7) | M7: =IF(INDEX(MO_SNA_IsHistoricalPeriod,,MATCH(F7,MO_Common_ColumnHeader,0)),"Actual","Estimate") | N7: =IFERROR(INDEX(INDIRECT(E7),0,MATCH(F7,MO_Common_ColumnHeader,0)),"N/A") | P7: =IF(ISNUMBER(N7),N7-K7,"N/A") | Q7: =IFERROR(IF(ISNUMBER(N7),(N7-K7)/ABS(K7),"N/A"),"N/A") | S7: 45957 | T7: CFO Commentary
A8: 956 | B8: =IF(INDEX(MO_SNA_IsHistoricalPeriod,,MATCH(F8,MO_Common_ColumnHeader,0)),"Historical","Forward") | D8: =INDEX(INDIRECT(E8),0,COLUMN(MO_Common_Column_A)) | E8: MO_RIS_REV | F8: FY2025 | I8: 5262 | J8: 5292 | K8: =AVERAGE(I8:J8) | M8: =IF(INDEX(MO_SNA_IsHistoricalPeriod,,MATCH(F8,MO_Common_ColumnHeader,0)),"Actual","Estimate") | N8: =IFERROR(INDEX(INDIRECT(E8),0,MATCH(F8,MO_Common_ColumnHeader,0)),"N/A") | P8: =IF(ISNUMBER(N8),N8-K8,"N/A") | Q8: =IFERROR(IF(ISNUMBER(N8),(N8-K8)/ABS(K8),"N/A"),"N/A") | S8: 45957 | T8: CFO Commentary
A9: 955 | B9: =IF(INDEX(MO_SNA_IsHistoricalPeriod,,MATCH(F9,MO_Common_ColumnHeader,0)),"Historical","Forward") | D9: GAAP Operating Margin | E9: MO_MA_EBIT | F9: FY2025 | I9: 0.279 | J9: 0.289 | K9: =AVERAGE(I9:J9) | M9: =IF(INDEX(MO_SNA_IsHistoricalPeriod,,MATCH(F9,MO_Common_ColumnHeader,0)),"Actual","Estimate") | N9: =IFERROR(INDEX(INDIRECT(E9),0,MATCH(F9,MO_Common_ColumnHeader,0)),"N/A") | P9: =IF(ISNUMBER(N9),N9-K9,"N/A") | Q9: =IFERROR(IF(ISNUMBER(N9),(N9-K9)/ABS(K9),"N/A"),"N/A") | S9: 45957 | T9: CFO Commentary
A10: 954 | B10: =IF(INDEX(MO_SNA_IsHistoricalPeriod,,MATCH(F10,MO_Common_ColumnHeader,0)),"Historical","Forward") | D10: =INDEX(INDIRECT(E10),0,COLUMN(MO_Common_Column_A)) | E10: MO_MA_OperatingIncome_NONGAAP | F10: FY2025 | I10: 0.439 | J10: 0.449 | K10: =AVERAGE(I10:J10) | M10: =IF(INDEX(MO_SNA_IsHistoricalPeriod,,MATCH(F10,MO_Common_ColumnHeader,0)),"Actual","Estimate") | N10: =IFERROR(INDEX(INDIRECT(E10),0,MATCH(F10,MO_Common_ColumnHeader,0)),"N/A") | P10: =IF(ISNUMBER(N10),N10-K10,"N/A") | Q10: =IFERROR(IF(ISNUMBER(N10),(N10-K10)/ABS(K10),"N/A"),"N/A") | S10: 45957 | T10: CFO Commentary
A11: 953 | B11: =IF(INDEX(MO_SNA_IsHistoricalPeriod,,MATCH(F11,MO_Common_ColumnHeader,0)),"Historical","Forward") | D11: =INDEX(INDIRECT(E11),0,COLUMN(MO_Common_Column_A)) | E11: MO_RIS_EPS_WAD | F11: FY2025 | I11: 3.8 | J11: 3.86 | K11: =AVERAGE(I11:J11) | M11: =IF(INDEX(MO_SNA_IsHistoricalPeriod,,MATCH(F11,MO_Common_ColumnHeader,0)),"Actual","Estimate") | N11: =IFERROR(INDEX(INDIRECT(E11),0,MATCH(F11,MO_Common_ColumnHeader,0)),"N/A") | P11: =IF(ISNUMBER(N11),N11-K11,"N/A") | Q11: =IFERROR(IF(ISNUMBER(N11),(N11-K11)/ABS(K11),"N/A"),"N/A") | S11: 45957 | T11: CFO Commentary
A12: 952 | B12: =IF(INDEX(MO_SNA_IsHistoricalPeriod,,MATCH(F12,MO_Common_ColumnHeader,0)),"Historical","Forward") | D12: =INDEX(INDIRECT(E12),0,COLUMN(MO_Common_Column_A)) | E12: MO_RIS_EPS_WAD_Adj | F12: FY2025 | I12: 7.02 | J12: 7.08 | K12: =AVERAGE(I12:J12) | M12: =IF(INDEX(MO_SNA_IsHistoricalPeriod,,MATCH(F12,MO_Common_ColumnHeader,0)),"Actual","Estimate") | N12: =IFERROR(INDEX(INDIRECT(E12),0,MATCH(F12,MO_Common_ColumnHeader,0)),"N/A") | P12: =IF(ISNUMBER(N12),N12-K12,"N/A") | Q12: =IFERROR(IF(ISNUMBER(N12),(N12-K12)/ABS(K12),"N/A"),"N/A") | S12: 45957 | T12: CFO Commentary
A13: 951 | B13: =IF(INDEX(MO_SNA_IsHistoricalPeriod,,MATCH(F13,MO_Common_ColumnHeader,0)),"Historical","Forward") | D13: =INDEX(INDIRECT(E13),0,COLUMN(MO_Common_Column_A)) | E13: MO_CFS_CFO | F13: FY2025 | I13: 1650 | J13: 1750 | K13: =AVERAGE(I13:J13) | M13: =IF(INDEX(MO_SNA_IsHistoricalPeriod,,MATCH(F13,MO_Common_ColumnHeader,0)),"Actual","Estimate") | N13: =IFERROR(INDEX(INDIRECT(E13),0,MATCH(F13,MO_Common_ColumnHeader,0)),"N/A") | P13: =IF(ISNUMBER(N13),N13-K13,"N/A") | Q13: =IFERROR(IF(ISNUMBER(N13),(N13-K13)/ABS(K13),"N/A"),"N/A") | S13: 45957 | T13: CFO Commentary
A14: 950 | B14: =IF(INDEX(MO_SNA_IsHistoricalPeriod,,MATCH(F14,MO_Common_ColumnHeader,0)),"Historical","Forward") | D14: GAAP Other Income & Expense | F14: FY2025 | I14: -18 | J14: -10 | K14: =AVERAGE(I14:J14) | M14: =IF(INDEX(MO_SNA_IsHistoricalPeriod,,MATCH(F14,MO_Common_ColumnHeader,0)),"Actual","Estimate") | N14: =-IFERROR(INDEX(MO_RIS_IE_Net,0,MATCH(F14,MO_Common_ColumnHeader,0)),"N/A")-IFERROR(INDEX(MO_RIS_OI,0,MATCH(F14,MO_Common_ColumnHeader,0)),"N/A") | P14: =IF(ISNUMBER(N14),N14-K14,"N/A") | Q14: =IFERROR(IF(ISNUMBER(N14),(N14-K14)/ABS(K14),"N/A"),"N/A") | S14: 45957 | T14: CFO Commentary
A15: 949 | B15: =IF(INDEX(MO_SNA_IsHistoricalPeriod,,MATCH(F15,MO_Common_ColumnHeader,0)),"Historical","Forward") | D15: Non-GAAP Other Income & Expense | F15: FY2025 | I15: -33 | J15: -25 | K15: =AVERAGE(I15:J15) | M15: =IF(INDEX(MO_SNA_IsHistoricalPeriod,,MATCH(F15,MO_Common_ColumnHeader,0)),"Actual","Estimate") | N15: =-IFERROR(INDEX(MO_RIS_IE_Net_NONGAAP,0,MATCH(F15,MO_Common_ColumnHeader,0)),"N/A")-IFERROR(INDEX(MO_RIS_OI_NONGAAP,0,MATCH(F15,MO_Common_ColumnHeader,0)),"N/A") | P15: =IF(ISNUMBER(N15),N15-K15,"N/A") | Q15: =IFERROR(IF(ISNUMBER(N15),(N15-K15)/ABS(K15),"N/A"),"N/A") | S15: 45957 | T15: CFO Commentary
A16: 948 | B16: =IF(INDEX(MO_SNA_IsHistoricalPeriod,,MATCH(F16,MO_Common_ColumnHeader,0)),"Historical","Forward") | D16: GAAP Tax Rate | E16: MO_RIS_TaxRate | F16: FY2025 | I16: 0.29 | J16: 0.29 | K16: =AVERAGE(I16:J16) | M16: =IF(INDEX(MO_SNA_IsHistoricalPeriod,,MATCH(F16,MO_Common_ColumnHeader,0)),"Actual","Estimate") | N16: =IFERROR(INDEX(INDIRECT(E16),0,MATCH(F16,MO_Common_ColumnHeader,0)),"N/A") | P16: =IF(ISNUMBER(N16),N16-K16,"N/A") | Q16: =IFERROR(IF(ISNUMBER(N16),(N16-K16)/ABS(K16),"N/A"),"N/A") | S16: 45957 | T16: CFO Commentary
A17: 947 | B17: =IF(INDEX(MO_SNA_IsHistoricalPeriod,,MATCH(F17,MO_Common_ColumnHeader,0)),"Historical","Forward") | D17: =INDEX(INDIRECT(E17),0,COLUMN(MO_Common_Column_A)) | E17: MO_RIS_TaxRate_NONGAAP | F17: FY2025 | I17: 0.165 | J17: 0.165 | K17: =AVERAGE(I17:J17) | M17: =IF(INDEX(MO_SNA_IsHistoricalPeriod,,MATCH(F17,MO_Common_ColumnHeader,0)),"Actual","Estimate") | N17: =IFERROR(INDEX(INDIRECT(E17),0,MATCH(F17,MO_Common_ColumnHeader,0)),"N/A") | P17: =IF(ISNUMBER(N17),N17-K17,"N/A") | Q17: =IFERROR(IF(ISNUMBER(N17),(N17-K17)/ABS(K17),"N/A"),"N/A") | S17: 45957 | T17: CFO Commentary
A18: 946 | B18: =IF(INDEX(MO_SNA_IsHistoricalPeriod,,MATCH(F18,MO_Common_ColumnHeader,0)),"Historical","Forward") | D18: =INDEX(INDIRECT(E18),0,COLUMN(MO_Common_Column_A)) | E18: MO_RIS_ShareCount_WAD | F18: FY2025 | I18: 273 | J18: 275 | K18: =AVERAGE(I18:J18) | M18: =IF(INDEX(MO_SNA_IsHistoricalPeriod,,MATCH(F18,MO_Common_ColumnHeader,0)),"Actual","Estimate") | N18: =IFERROR(INDEX(INDIRECT(E18),0,MATCH(F18,MO_Common_ColumnHeader,0)),"N/A") | P18: =IF(ISNUMBER(N18),N18-K18,"N/A") | Q18: =IFERROR(IF(ISNUMBER(N18),(N18-K18)/ABS(K18),"N/A"),"N/A") | S18: 45957 | T18: CFO Commentary
A19: 945 | B19: =IF(INDEX(MO_SNA_IsHistoricalPeriod,,MATCH(F19,MO_Common_ColumnHeader,0)),"Historical","Forward") | D19: DSO | F19: FY2025 | I19: 50 | J19: 50 | K19: =AVERAGE(I19:J19) | M19: =IF(INDEX(MO_SNA_IsHistoricalPeriod,,MATCH(F19,MO_Common_ColumnHeader,0)),"Actual","Estimate") | N19: =IFERROR(INDEX(INDIRECT(E19),0,MATCH(F19,MO_Common_ColumnHeader,0)),"N/A") | P19: =IF(ISNUMBER(N19),N19-K19,"N/A") | Q19: =IFERROR(IF(ISNUMBER(N19),(N19-K19)/ABS(K19),"N/A"),"N/A") | S19: 45957 | T19: CFO Commentary
A20: 944 | B20: =IF(INDEX(MO_SNA_IsHistoricalPeriod,,MATCH(F20,MO_Common_ColumnHeader,0)),"Historical","Forward") | D20: =INDEX(INDIRECT(E20),0,COLUMN(MO_Common_Column_A)) | E20: MO_CFSum_Capex | F20: FY2025 | I20: -150 | J20: -150 | K20: =AVERAGE(I20:J20) | M20: =IF(INDEX(MO_SNA_IsHistoricalPeriod,,MATCH(F20,MO_Common_ColumnHeader,0)),"Actual","Estimate") | N20: =IFERROR(INDEX(INDIRECT(E20),0,MATCH(F20,MO_Common_ColumnHeader,0)),"N/A") | P20: =IF(ISNUMBER(N20),N20-K20,"N/A") | Q20: =IFERROR(IF(ISNUMBER(N20),(N20-K20)/ABS(K20),"N/A"),"N/A") | S20: 45957 | T20: CFO Commentary
A21: 943 | B21: =IF(INDEX(MO_SNA_IsHistoricalPeriod,,MATCH(F21,MO_Common_ColumnHeader,0)),"Historical","Forward") | D21: =INDEX(INDIRECT(E21),0,COLUMN(MO_Common_Column_A)) | E21: MO_RIS_SBC | F21: FY2025 | I21: 455 | J21: 455 | K21: =AVERAGE(I21:J21) | M21: =IF(INDEX(MO_SNA_IsHistoricalPeriod,,MATCH(F21,MO_Common_ColumnHeader,0)),"Actual","Estimate") | N21: =IFERROR(INDEX(INDIRECT(E21),0,MATCH(F21,MO_Common_ColumnHeader,0)),"N/A") | P21: =IF(ISNUMBER(N21),N21-K21,"N/A") | Q21: =IFERROR(IF(ISNUMBER(N21),(N21-K21)/ABS(K21),"N/A"),"N/A") | S21: 45957 | T21: CFO Commentary
A22: 942 | B22: =IF(INDEX(MO_SNA_IsHistoricalPeriod,,MATCH(F22,MO_Common_ColumnHeader,0)),"Historical","Forward") | D22: =INDEX(INDIRECT(E22),0,COLUMN(MO_Common_Column_A)) | E22: MO_RIS_Daintangibles | F22: FY2025 | I22: 103 | J22: 103 | K22: =AVERAGE(I22:J22) | M22: =IF(INDEX(MO_SNA_IsHistoricalPeriod,,MATCH(F22,MO_Common_ColumnHeader,0)),"Actual","Estimate") | N22: =IFERROR(INDEX(INDIRECT(E22),0,MATCH(F22,MO_Common_ColumnHeader,0)),"N/A") | P22: =IF(ISNUMBER(N22),N22-K22,"N/A") | Q22: =IFERROR(IF(ISNUMBER(N22),(N22-K22)/ABS(K22),"N/A"),"N/A") | S22: 45957 | T22: CFO Commentary
A23: 941 | B23: =IF(INDEX(MO_SNA_IsHistoricalPeriod,,MATCH(F23,MO_Common_ColumnHeader,0)),"Historical","Forward") | D23: Acquisition and integration-related costs | F23: FY2025 | I23: 115 | J23: 115 | K23: =AVERAGE(I23:J23) | M23: =IF(INDEX(MO_SNA_IsHistoricalPeriod,,MATCH(F23,MO_Common_ColumnHeader,0)),"Actual","Estimate") | N23: =IFERROR(INDEX(INDIRECT(E23),0,MATCH(F23,MO_Common_ColumnHeader,0)),"N/A") | P23: =IF(ISNUMBER(N23),N23-K23,"N/A") | Q23: =IFERROR(IF(ISNUMBER(N23),(N23-K23)/ABS(K23),"N/A"),"N/A") | S23: 45957 | T23: CFO Commentary
A24: 940 | B24: =IF(INDEX(MO_SNA_IsHistoricalPeriod,,MATCH(F24,MO_Common_ColumnHeader,0)),"Historical","Forward") | D24: Restructuring and other credits | F24: FY2025 | I24: 27 | J24: 27 | K24: =AVERAGE(I24:J24) | M24: =IF(INDEX(MO_SNA_IsHistoricalPeriod,,MATCH(F24,MO_Common_ColumnHeader,0)),"Actual","Estimate") | N24: =IFERROR(INDEX(INDIRECT(E24),0,MATCH(F24,MO_Common_ColumnHeader,0)),"N/A") | P24: =IF(ISNUMBER(N24),N24-K24,"N/A") | Q24: =IFERROR(IF(ISNUMBER(N24),(N24-K24)/ABS(K24),"N/A"),"N/A") | S24: 45957 | T24: CFO Commentary
A25: 939 | B25: =IF(INDEX(MO_SNA_IsHistoricalPeriod,,MATCH(F25,MO_Common_ColumnHeader,0)),"Historical","Forward") | D25: Non-Qualified deferred compensation expenses | F25: FY2025 | I25: 12 | J25: 12 | K25: =AVERAGE(I25:J25) | M25: =IF(INDEX(MO_SNA_IsHistoricalPeriod,,MATCH(F25,MO_Common_ColumnHeader,0)),"Actual","Estimate") | N25: =IFERROR(INDEX(INDIRECT(E25),0,MATCH(F25,MO_Common_ColumnHeader,0)),"N/A") | P25: =IF(ISNUMBER(N25),N25-K25,"N/A") | Q25: =IFERROR(IF(ISNUMBER(N25),(N25-K25)/ABS(K25),"N/A"),"N/A") | S25: 45957 | T25: CFO Commentary
A26: 938 | B26: =IF(INDEX(MO_SNA_IsHistoricalPeriod,,MATCH(F26,MO_Common_ColumnHeader,0)),"Historical","Forward") | D26: Special charges | F26: FY2025 | I26: 2 | J26: 2 | K26: =AVERAGE(I26:J26) | M26: =IF(INDEX(MO_SNA_IsHistoricalPeriod,,MATCH(F26,MO_Common_ColumnHeader,0)),"Actual","Estimate") | N26: =IFERROR(INDEX(INDIRECT(E26),0,MATCH(F26,MO_Common_ColumnHeader,0)),"N/A") | P26: =IF(ISNUMBER(N26),N26-K26,"N/A") | Q26: =IFERROR(IF(ISNUMBER(N26),(N26-K26)/ABS(K26),"N/A"),"N/A") | S26: 45957 | T26: CFO Commentary
A27: 937 | B27: =IF(INDEX(MO_SNA_IsHistoricalPeriod,,MATCH(F27,MO_Common_ColumnHeader,0)),"Historical","Forward") | D27: Loss related to contingent liability | F27: FY2025 | I27: 129 | J27: 129 | K27: =AVERAGE(I27:J27) | M27: =IF(INDEX(MO_SNA_IsHistoricalPeriod,,MATCH(F27,MO_Common_ColumnHeader,0)),"Actual","Estimate") | N27: =IFERROR(INDEX(INDIRECT(E27),0,MATCH(F27,MO_Common_ColumnHeader,0)),"N/A") | P27: =IF(ISNUMBER(N27),N27-K27,"N/A") | Q27: =IFERROR(IF(ISNUMBER(N27),(N27-K27)/ABS(K27),"N/A"),"N/A") | S27: 45957 | T27: CFO Commentary
A28: 936 | B28: =IF(INDEX(MO_SNA_IsHistoricalPeriod,,MATCH(F28,MO_Common_ColumnHeader,0)),"Historical","Forward") | D28: GAAP Operating Expenses | F28: FY2025 | I28: 3778 | J28: 3778 | K28: =AVERAGE(I28:J28) | M28: =IF(INDEX(MO_SNA_IsHistoricalPeriod,,MATCH(F28,MO_Common_ColumnHeader,0)),"Actual","Estimate") | N28: =IFERROR(INDEX(MO_RIS_COGS,0,MATCH(Guidance!F28,MO_Common_ColumnHeader,0))+INDEX(MO_RIS_RD,0,MATCH(Guidance!F28,MO_Common_ColumnHeader,0))+INDEX(MO_RIS_GA,0,MATCH(Guidance!F28,MO_Common_ColumnHeader,0))+INDEX(MO_RIS_SM,0,MATCH(Guidance!F28,MO_Common_ColumnHeader,0)),"N/A") | P28: =IF(ISNUMBER(N28),N28-K28,"N/A") | Q28: =IFERROR(IF(ISNUMBER(N28),(N28-K28)/ABS(K28),"N/A"),"N/A") | S28: 45957 | T28: CFO Commentary
A29: 935 | B29: =IF(INDEX(MO_SNA_IsHistoricalPeriod,,MATCH(F29,MO_Common_ColumnHeader,0)),"Historical","Forward") | D29: Non-GAAP Operating Expenses | F29: FY2025 | I29: 2935 | J29: 2935 | K29: =AVERAGE(I29:J29) | M29: =IF(INDEX(MO_SNA_IsHistoricalPeriod,,MATCH(F29,MO_Common_ColumnHeader,0)),"Actual","Estimate") | N29: =IFERROR(INDEX(MO_RIS_REV,0,MATCH(Guidance!F29,MO_Common_ColumnHeader,0))+INDEX(MO_RIS_RD_NONGAAP,0,MATCH(Guidance!F29,MO_Common_ColumnHeader,0))+INDEX(MO_RIS_GA_NONGAAP,0,MATCH(Guidance!F29,MO_Common_ColumnHeader,0))+INDEX(MO_RIS_SM_NONGAAP,0,MATCH(Guidance!F29,MO_Common_ColumnHeader,0))-INDEX(MO_RIS_GP_NONGAAP,0,MATCH(Guidance!F29,MO_Common_ColumnHeader,0)),"N/A") | P29: =IF(ISNUMBER(N29),N29-K29,"N/A") | Q29: =IFERROR(IF(ISNUMBER(N29),(N29-K29)/ABS(K29),"N/A"),"N/A") | S29: 45957 | T29: CFO Commentary
A30: 934
A31: 933 | B31: =IF(INDEX(MO_SNA_IsHistoricalPeriod,,MATCH(F31,MO_Common_ColumnHeader,0)),"Historical","Forward") | D31: =INDEX(INDIRECT(E31),0,COLUMN(MO_Common_Column_A)) | E31: MO_RIS_REV | F31: Q4-2025 | I31: 1405 | J31: 1435 | K31: =AVERAGE(I31:J31) | M31: =IF(INDEX(MO_SNA_IsHistoricalPeriod,,MATCH(F31,MO_Common_ColumnHeader,0)),"Actual","Estimate") | N31: =IFERROR(INDEX(INDIRECT(E31),0,MATCH(F31,MO_Common_ColumnHeader,0)),"N/A") | P31: =IF(ISNUMBER(N31),N31-K31,"N/A") | Q31: =IFERROR(IF(ISNUMBER(N31),(N31-K31)/ABS(K31),"N/A"),"N/A") | S31: 45957 | T31: CFO Commentary
A32: 932 | B32: =IF(INDEX(MO_SNA_IsHistoricalPeriod,,MATCH(F32,MO_Common_ColumnHeader,0)),"Historical","Forward") | D32: GAAP Operating Margin | E32: MO_MA_EBIT | F32: Q4-2025 | I32: 0.325 | J32: 0.335 | K32: =AVERAGE(I32:J32) | M32: =IF(INDEX(MO_SNA_IsHistoricalPeriod,,MATCH(F32,MO_Common_ColumnHeader,0)),"Actual","Estimate") | N32: =IFERROR(INDEX(INDIRECT(E32),0,MATCH(F32,MO_Common_ColumnHeader,0)),"N/A") | P32: =IF(ISNUMBER(N32),N32-K32,"N/A") | Q32: =IFERROR(IF(ISNUMBER(N32),(N32-K32)/ABS(K32),"N/A"),"N/A") | S32: 45957 | T32: CFO Commentary
A33: 931 | B33: =IF(INDEX(MO_SNA_IsHistoricalPeriod,,MATCH(F33,MO_Common_ColumnHeader,0)),"Historical","Forward") | D33: =INDEX(INDIRECT(E33),0,COLUMN(MO_Common_Column_A)) | E33: MO_MA_OperatingIncome_NONGAAP | F33: Q4-2025 | I33: 0.445 | J33: 0.455 | K33: =AVERAGE(I33:J33) | M33: =IF(INDEX(MO_SNA_IsHistoricalPeriod,,MATCH(F33,MO_Common_ColumnHeader,0)),"Actual","Estimate") | N33: =IFERROR(INDEX(INDIRECT(E33),0,MATCH(F33,MO_Common_ColumnHeader,0)),"N/A") | P33: =IF(ISNUMBER(N33),N33-K33,"N/A") | Q33: =IFERROR(IF(ISNUMBER(N33),(N33-K33)/ABS(K33),"N/A"),"N/A") | S33: 45957 | T33: CFO Commentary
A34: 930 | B34: =IF(INDEX(MO_SNA_IsHistoricalPeriod,,MATCH(F34,MO_Common_ColumnHeader,0)),"Historical","Forward") | D34: =INDEX(INDIRECT(E34),0,COLUMN(MO_Common_Column_A)) | E34: MO_RIS_EPS_WAD | F34: Q4-2025 | I34: 1.17 | J34: 1.23 | K34: =AVERAGE(I34:J34) | M34: =IF(INDEX(MO_SNA_IsHistoricalPeriod,,MATCH(F34,MO_Common_ColumnHeader,0)),"Actual","Estimate") | N34: =IFERROR(INDEX(INDIRECT(E34),0,MATCH(F34,MO_Common_ColumnHeader,0)),"N/A") | P34: =IF(ISNUMBER(N34),N34-K34,"N/A") | Q34: =IFERROR(IF(ISNUMBER(N34),(N34-K34)/ABS(K34),"N/A"),"N/A") | S34: 45957 | T34: CFO Commentary
A35: 929 | B35: =IF(INDEX(MO_SNA_IsHistoricalPeriod,,MATCH(F35,MO_Common_ColumnHeader,0)),"Historical","Forward") | D35: =INDEX(INDIRECT(E35),0,COLUMN(MO_Common_Column_A)) | E35: MO_RIS_EPS_WAD_Adj | F35: Q4-2025 | I35: 1.88 | J35: 1.94 | K35: =AVERAGE(I35:J35) | M35: =IF(INDEX(MO_SNA_IsHistoricalPeriod,,MATCH(F35,MO_Common_ColumnHeader,0)),"Actual","Estimate") | N35: =IFERROR(INDEX(INDIRECT(E35),0,MATCH(F35,MO_Common_ColumnHeader,0)),"N/A") | P35: =IF(ISNUMBER(N35),N35-K35,"N/A") | Q35: =IFERROR(IF(ISNUMBER(N35),(N35-K35)/ABS(K35),"N/A"),"N/A") | S35: 45957 | T35: CFO Commentary
A36: 928 | B36: =IF(INDEX(MO_SNA_IsHistoricalPeriod,,MATCH(F36,MO_Common_ColumnHeader,0)),"Historical","Forward") | D36: =INDEX(INDIRECT(E36),0,COLUMN(MO_Common_Column_A)) | E36: MO_CFSum_NetShares | F36: Q4-2025 | I36: -200 | J36: -200 | K36: =AVERAGE(I36:J36) | M36: =IF(INDEX(MO_SNA_IsHistoricalPeriod,,MATCH(F36,MO_Common_ColumnHeader,0)),"Actual","Estimate") | N36: =IFERROR(INDEX(INDIRECT(E36),0,MATCH(F36,MO_Common_ColumnHeader,0)),"N/A") | P36: =IF(ISNUMBER(N36),N36-K36,"N/A") | Q36: =IFERROR(IF(ISNUMBER(N36),(N36-K36)/ABS(K36),"N/A"),"N/A") | S36: 45957 | T36: CFO Commentary
A37: 927
A38: 926 | B38: =IF(INDEX(MO_SNA_IsHistoricalPeriod,,MATCH(F38,MO_Common_ColumnHeader,0)),"Historical","Forward") | D38: Recurring Revenue % | F38: FY2025 | I38: 0.8 | J38: 0.8 | K38: =AVERAGE(I38:J38) | M38: =IF(INDEX(MO_SNA_IsHistoricalPeriod,,MATCH(F38,MO_Common_ColumnHeader,0)),"Actual","Estimate") | N38: =IFERROR(INDEX(INDIRECT(E38),0,MATCH(F38,MO_Common_ColumnHeader,0)),"N/A") | P38: =IF(ISNUMBER(N38),N38-K38,"N/A") | Q38: =IFERROR(IF(ISNUMBER(N38),(N38-K38)/ABS(K38),"N/A"),"N/A") | S38: 45866 | T38: CFO Commentary
A39: 925 | B39: =IF(INDEX(MO_SNA_IsHistoricalPeriod,,MATCH(F39,MO_Common_ColumnHeader,0)),"Historical","Forward") | D39: Revenue from Beginning Backlog % | F39: FY2025 | I39: 0.7 | J39: 0.7 | K39: =AVERAGE(I39:J39) | M39: =IF(INDEX(MO_SNA_IsHistoricalPeriod,,MATCH(F39,MO_Common_ColumnHeader,0)),"Actual","Estimate") | N39: =IFERROR(INDEX(INDIRECT(E39),0,MATCH(F39,MO_Common_ColumnHeader,0)),"N/A") | P39: =IF(ISNUMBER(N39),N39-K39,"N/A") | Q39: =IFERROR(IF(ISNUMBER(N39),(N39-K39)/ABS(K39),"N/A"),"N/A") | S39: 45866 | T39: CFO Commentary
A40: 924 | B40: =IF(INDEX(MO_SNA_IsHistoricalPeriod,,MATCH(F40,MO_Common_ColumnHeader,0)),"Historical","Forward") | D40: =INDEX(INDIRECT(E40),0,COLUMN(MO_Common_Column_A)) | E40: MO_RIS_REV | F40: FY2025 | I40: 5210 | J40: 5270 | K40: =AVERAGE(I40:J40) | M40: =IF(INDEX(MO_SNA_IsHistoricalPeriod,,MATCH(F40,MO_Common_ColumnHeader,0)),"Actual","Estimate") | N40: =IFERROR(INDEX(INDIRECT(E40),0,MATCH(F40,MO_Common_ColumnHeader,0)),"N/A") | P40: =IF(ISNUMBER(N40),N40-K40,"N/A") | Q40: =IFERROR(IF(ISNUMBER(N40),(N40-K40)/ABS(K40),"N/A"),"N/A") | S40: 45866 | T40: CFO Commentary
A41: 923 | B41: =IF(INDEX(MO_SNA_IsHistoricalPeriod,,MATCH(F41,MO_Common_ColumnHeader,0)),"Historical","Forward") | D41: GAAP Operating Margin | E41: MO_MA_EBIT | F41: FY2025 | I41: 0.285 | J41: 0.295 | K41: =AVERAGE(I41:J41) | M41: =IF(INDEX(MO_SNA_IsHistoricalPeriod,,MATCH(F41,MO_Common_ColumnHeader,0)),"Actual","Estimate") | N41: =IFERROR(INDEX(INDIRECT(E41),0,MATCH(F41,MO_Common_ColumnHeader,0)),"N/A") | P41: =IF(ISNUMBER(N41),N41-K41,"N/A") | Q41: =IFERROR(IF(ISNUMBER(N41),(N41-K41)/ABS(K41),"N/A"),"N/A") | S41: 45866 | T41: CFO Commentary
A42: 922 | B42: =IF(INDEX(MO_SNA_IsHistoricalPeriod,,MATCH(F42,MO_Common_ColumnHeader,0)),"Historical","Forward") | D42: =INDEX(INDIRECT(E42),0,COLUMN(MO_Common_Column_A)) | E42: MO_MA_OperatingIncome_NONGAAP | F42: FY2025 | I42: 0.435 | J42: 0.445 | K42: =AVERAGE(I42:J42) | M42: =IF(INDEX(MO_SNA_IsHistoricalPeriod,,MATCH(F42,MO_Common_ColumnHeader,0)),"Actual","Estimate") | N42: =IFERROR(INDEX(INDIRECT(E42),0,MATCH(F42,MO_Common_ColumnHeader,0)),"N/A") | P42: =IF(ISNUMBER(N42),N42-K42,"N/A") | Q42: =IFERROR(IF(ISNUMBER(N42),(N42-K42)/ABS(K42),"N/A"),"N/A") | S42: 45866 | T42: CFO Commentary
A43: 921 | B43: =IF(INDEX(MO_SNA_IsHistoricalPeriod,,MATCH(F43,MO_Common_ColumnHeader,0)),"Historical","Forward") | D43: =INDEX(INDIRECT(E43),0,COLUMN(MO_Common_Column_A)) | E43: MO_RIS_EPS_WAD | F43: FY2025 | I43: 3.97 | J43: 4.07 | K43: =AVERAGE(I43:J43) | M43: =IF(INDEX(MO_SNA_IsHistoricalPeriod,,MATCH(F43,MO_Common_ColumnHeader,0)),"Actual","Estimate") | N43: =IFERROR(INDEX(INDIRECT(E43),0,MATCH(F43,MO_Common_ColumnHeader,0)),"N/A") | P43: =IF(ISNUMBER(N43),N43-K43,"N/A") | Q43: =IFERROR(IF(ISNUMBER(N43),(N43-K43)/ABS(K43),"N/A"),"N/A") | S43: 45866 | T43: CFO Commentary
A44: 920 | B44: =IF(INDEX(MO_SNA_IsHistoricalPeriod,,MATCH(F44,MO_Common_ColumnHeader,0)),"Historical","Forward") | D44: =INDEX(INDIRECT(E44),0,COLUMN(MO_Common_Column_A)) | E44: MO_RIS_EPS_WAD_Adj | F44: FY2025 | I44: 6.85 | J44: 6.95 | K44: =AVERAGE(I44:J44) | M44: =IF(INDEX(MO_SNA_IsHistoricalPeriod,,MATCH(F44,MO_Common_ColumnHeader,0)),"Actual","Estimate") | N44: =IFERROR(INDEX(INDIRECT(E44),0,MATCH(F44,MO_Common_ColumnHeader,0)),"N/A") | P44: =IF(ISNUMBER(N44),N44-K44,"N/A") | Q44: =IFERROR(IF(ISNUMBER(N44),(N44-K44)/ABS(K44),"N/A"),"N/A") | S44: 45866 | T44: CFO Commentary
A45: 919 | B45: =IF(INDEX(MO_SNA_IsHistoricalPeriod,,MATCH(F45,MO_Common_ColumnHeader,0)),"Historical","Forward") | D45: =INDEX(INDIRECT(E45),0,COLUMN(MO_Common_Column_A)) | E45: MO_CFS_CFO | F45: FY2025 | I45: 1650 | J45: 1750 | K45: =AVERAGE(I45:J45) | M45: =IF(INDEX(MO_SNA_IsHistoricalPeriod,,MATCH(F45,MO_Common_ColumnHeader,0)),"Actual","Estimate") | N45: =IFERROR(INDEX(INDIRECT(E45),0,MATCH(F45,MO_Common_ColumnHeader,0)),"N/A") | P45: =IF(ISNUMBER(N45),N45-K45,"N/A") | Q45: =IFERROR(IF(ISNUMBER(N45),(N45-K45)/ABS(K45),"N/A"),"N/A") | S45: 45866 | T45: CFO Commentary
A46: 918 | B46: =IF(INDEX(MO_SNA_IsHistoricalPeriod,,MATCH(F46,MO_Common_ColumnHeader,0)),"Historical","Forward") | D46: GAAP Other Income & Expense | F46: FY2025 | I46: -9 | J46: 11 | K46: =AVERAGE(I46:J46) | M46: =IF(INDEX(MO_SNA_IsHistoricalPeriod,,MATCH(F46,MO_Common_ColumnHeader,0)),"Actual","Estimate") | N46: =-IFERROR(INDEX(MO_RIS_IE_Net,0,MATCH(F46,MO_Common_ColumnHeader,0)),"N/A")-IFERROR(INDEX(MO_RIS_OI,0,MATCH(F46,MO_Common_ColumnHeader,0)),"N/A") | P46: =IF(ISNUMBER(N46),N46-K46,"N/A") | Q46: =IFERROR(IF(ISNUMBER(N46),(N46-K46)/ABS(K46),"N/A"),"N/A") | S46: 45866 | T46: CFO Commentary
A47: 917 | B47: =IF(INDEX(MO_SNA_IsHistoricalPeriod,,MATCH(F47,MO_Common_ColumnHeader,0)),"Historical","Forward") | D47: Non-GAAP Other Income & Expense | F47: FY2025 | I47: -52 | J47: -32 | K47: =AVERAGE(I47:J47) | M47: =IF(INDEX(MO_SNA_IsHistoricalPeriod,,MATCH(F47,MO_Common_ColumnHeader,0)),"Actual","Estimate") | N47: =-IFERROR(INDEX(MO_RIS_IE_Net_NONGAAP,0,MATCH(F47,MO_Common_ColumnHeader,0)),"N/A")-IFERROR(INDEX(MO_RIS_OI_NONGAAP,0,MATCH(F47,MO_Common_ColumnHeader,0)),"N/A") | P47: =IF(ISNUMBER(N47),N47-K47,"N/A") | Q47: =IFERROR(IF(ISNUMBER(N47),(N47-K47)/ABS(K47),"N/A"),"N/A") | S47: 45866 | T47: CFO Commentary
A48: 916 | B48: =IF(INDEX(MO_SNA_IsHistoricalPeriod,,MATCH(F48,MO_Common_ColumnHeader,0)),"Historical","Forward") | D48: GAAP Tax Rate | E48: MO_RIS_TaxRate | F48: FY2025 | I48: 0.28 | J48: 0.28 | K48: =AVERAGE(I48:J48) | M48: =IF(INDEX(MO_SNA_IsHistoricalPeriod,,MATCH(F48,MO_Common_ColumnHeader,0)),"Actual","Estimate") | N48: =IFERROR(INDEX(INDIRECT(E48),0,MATCH(F48,MO_Common_ColumnHeader,0)),"N/A") | P48: =IF(ISNUMBER(N48),N48-K48,"N/A") | Q48: =IFERROR(IF(ISNUMBER(N48),(N48-K48)/ABS(K48),"N/A"),"N/A") | S48: 45866 | T48: CFO Commentary
A49: 915 | B49: =IF(INDEX(MO_SNA_IsHistoricalPeriod,,MATCH(F49,MO_Common_ColumnHeader,0)),"Historical","Forward") | D49: =INDEX(INDIRECT(E49),0,COLUMN(MO_Common_Column_A)) | E49: MO_RIS_TaxRate_NONGAAP | F49: FY2025 | I49: 0.165 | J49: 0.165 | K49: =AVERAGE(I49:J49) | M49: =IF(INDEX(MO_SNA_IsHistoricalPeriod,,MATCH(F49,MO_Common_ColumnHeader,0)),"Actual","Estimate") | N49: =IFERROR(INDEX(INDIRECT(E49),0,MATCH(F49,MO_Common_ColumnHeader,0)),"N/A") | P49: =IF(ISNUMBER(N49),N49-K49,"N/A") | Q49: =IFERROR(IF(ISNUMBER(N49),(N49-K49)/ABS(K49),"N/A"),"N/A") | S49: 45866 | T49: CFO Commentary
A50: 914 | B50: =IF(INDEX(MO_SNA_IsHistoricalPeriod,,MATCH(F50,MO_Common_ColumnHeader,0)),"Historical","Forward") | D50: =INDEX(INDIRECT(E50),0,COLUMN(MO_Common_Column_A)) | E50: MO_RIS_ShareCount_WAD | F50: FY2025 | I50: 273 | J50: 275 | K50: =AVERAGE(I50:J50) | M50: =IF(INDEX(MO_SNA_IsHistoricalPeriod,,MATCH(F50,MO_Common_ColumnHeader,0)),"Actual","Estimate") | N50: =IFERROR(INDEX(INDIRECT(E50),0,MATCH(F50,MO_Common_ColumnHeader,0)),"N/A") | P50: =IF(ISNUMBER(N50),N50-K50,"N/A") | Q50: =IFERROR(IF(ISNUMBER(N50),(N50-K50)/ABS(K50),"N/A"),"N/A") | S50: 45866 | T50: CFO Commentary
A51: 913 | B51: =IF(INDEX(MO_SNA_IsHistoricalPeriod,,MATCH(F51,MO_Common_ColumnHeader,0)),"Historical","Forward") | D51: DSO | F51: FY2025 | I51: 50 | J51: 50 | K51: =AVERAGE(I51:J51) | M51: =IF(INDEX(MO_SNA_IsHistoricalPeriod,,MATCH(F51,MO_Common_ColumnHeader,0)),"Actual","Estimate") | N51: =IFERROR(INDEX(INDIRECT(E51),0,MATCH(F51,MO_Common_ColumnHeader,0)),"N/A") | P51: =IF(ISNUMBER(N51),N51-K51,"N/A") | Q51: =IFERROR(IF(ISNUMBER(N51),(N51-K51)/ABS(K51),"N/A"),"N/A") | S51: 45866 | T51: CFO Commentary
A52: 912 | B52: =IF(INDEX(MO_SNA_IsHistoricalPeriod,,MATCH(F52,MO_Common_ColumnHeader,0)),"Historical","Forward") | D52: =INDEX(INDIRECT(E52),0,COLUMN(MO_Common_Column_A)) | E52: MO_CFSum_Capex | F52: FY2025 | I52: -160 | J52: -160 | K52: =AVERAGE(I52:J52) | M52: =IF(INDEX(MO_SNA_IsHistoricalPeriod,,MATCH(F52,MO_Common_ColumnHeader,0)),"Actual","Estimate") | N52: =IFERROR(INDEX(INDIRECT(E52),0,MATCH(F52,MO_Common_ColumnHeader,0)),"N/A") | P52: =IF(ISNUMBER(N52),N52-K52,"N/A") | Q52: =IFERROR(IF(ISNUMBER(N52),(N52-K52)/ABS(K52),"N/A"),"N/A") | S52: 45866 | T52: CFO Commentary
A53: 911 | B53: =IF(INDEX(MO_SNA_IsHistoricalPeriod,,MATCH(F53,MO_Common_ColumnHeader,0)),"Historical","Forward") | D53: =INDEX(INDIRECT(E53),0,COLUMN(MO_Common_Column_A)) | E53: MO_RIS_SBC | F53: FY2025 | I53: 462 | J53: 462 | K53: =AVERAGE(I53:J53) | M53: =IF(INDEX(MO_SNA_IsHistoricalPeriod,,MATCH(F53,MO_Common_ColumnHeader,0)),"Actual","Estimate") | N53: =IFERROR(INDEX(INDIRECT(E53),0,MATCH(F53,MO_Common_ColumnHeader,0)),"N/A") | P53: =IF(ISNUMBER(N53),N53-K53,"N/A") | Q53: =IFERROR(IF(ISNUMBER(N53),(N53-K53)/ABS(K53),"N/A"),"N/A") | S53: 45866 | T53: CFO Commentary
A54: 910 | B54: =IF(INDEX(MO_SNA_IsHistoricalPeriod,,MATCH(F54,MO_Common_ColumnHeader,0)),"Historical","Forward") | D54: =INDEX(INDIRECT(E54),0,COLUMN(MO_Common_Column_A)) | E54: MO_RIS_Daintangibles | F54: FY2025 | I54: 101 | J54: 101 | K54: =AVERAGE(I54:J54) | M54: =IF(INDEX(MO_SNA_IsHistoricalPeriod,,MATCH(F54,MO_Common_ColumnHeader,0)),"Actual","Estimate") | N54: =IFERROR(INDEX(INDIRECT(E54),0,MATCH(F54,MO_Common_ColumnHeader,0)),"N/A") | P54: =IF(ISNUMBER(N54),N54-K54,"N/A") | Q54: =IFERROR(IF(ISNUMBER(N54),(N54-K54)/ABS(K54),"N/A"),"N/A") | S54: 45866 | T54: CFO Commentary
A55: 909 | B55: =IF(INDEX(MO_SNA_IsHistoricalPeriod,,MATCH(F55,MO_Common_ColumnHeader,0)),"Historical","Forward") | D55: Acquisition and integration-related costs | F55: FY2025 | I55: 86 | J55: 86 | K55: =AVERAGE(I55:J55) | M55: =IF(INDEX(MO_SNA_IsHistoricalPeriod,,MATCH(F55,MO_Common_ColumnHeader,0)),"Actual","Estimate") | N55: =IFERROR(INDEX(INDIRECT(E55),0,MATCH(F55,MO_Common_ColumnHeader,0)),"N/A") | P55: =IF(ISNUMBER(N55),N55-K55,"N/A") | Q55: =IFERROR(IF(ISNUMBER(N55),(N55-K55)/ABS(K55),"N/A"),"N/A") | S55: 45866 | T55: CFO Commentary
A56: 908 | B56: =IF(INDEX(MO_SNA_IsHistoricalPeriod,,MATCH(F56,MO_Common_ColumnHeader,0)),"Historical","Forward") | D56: Restructuring and other credits | F56: FY2025 | I56: 0 | J56: 0 | K56: =AVERAGE(I56:J56) | M56: =IF(INDEX(MO_SNA_IsHistoricalPeriod,,MATCH(F56,MO_Common_ColumnHeader,0)),"Actual","Estimate") | N56: =IFERROR(INDEX(INDIRECT(E56),0,MATCH(F56,MO_Common_ColumnHeader,0)),"N/A") | P56: =IF(ISNUMBER(N56),N56-K56,"N/A") | Q56: =IFERROR(IF(ISNUMBER(N56),(N56-K56)/ABS(K56),"N/A"),"N/A") | S56: 45866 | T56: CFO Commentary
A57: 907 | B57: =IF(INDEX(MO_SNA_IsHistoricalPeriod,,MATCH(F57,MO_Common_ColumnHeader,0)),"Historical","Forward") | D57: Non-Qualified deferred compensation expenses | F57: FY2025 | I57: 6 | J57: 6 | K57: =AVERAGE(I57:J57) | M57: =IF(INDEX(MO_SNA_IsHistoricalPeriod,,MATCH(F57,MO_Common_ColumnHeader,0)),"Actual","Estimate") | N57: =IFERROR(INDEX(INDIRECT(E57),0,MATCH(F57,MO_Common_ColumnHeader,0)),"N/A") | P57: =IF(ISNUMBER(N57),N57-K57,"N/A") | Q57: =IFERROR(IF(ISNUMBER(N57),(N57-K57)/ABS(K57),"N/A"),"N/A") | S57: 45866 | T57: CFO Commentary
A58: 906 | B58: =IF(INDEX(MO_SNA_IsHistoricalPeriod,,MATCH(F58,MO_Common_ColumnHeader,0)),"Historical","Forward") | D58: Special charges | F58: FY2025 | I58: 2 | J58: 2 | K58: =AVERAGE(I58:J58) | M58: =IF(INDEX(MO_SNA_IsHistoricalPeriod,,MATCH(F58,MO_Common_ColumnHeader,0)),"Actual","Estimate") | N58: =IFERROR(INDEX(INDIRECT(E58),0,MATCH(F58,MO_Common_ColumnHeader,0)),"N/A") | P58: =IF(ISNUMBER(N58),N58-K58,"N/A") | Q58: =IFERROR(IF(ISNUMBER(N58),(N58-K58)/ABS(K58),"N/A"),"N/A") | S58: 45866 | T58: CFO Commentary
A59: 905 | B59: =IF(INDEX(MO_SNA_IsHistoricalPeriod,,MATCH(F59,MO_Common_ColumnHeader,0)),"Historical","Forward") | D59: GAAP Operating Expenses | F59: FY2025 | I59: 3720 | J59: 3720 | K59: =AVERAGE(I59:J59) | M59: =IF(INDEX(MO_SNA_IsHistoricalPeriod,,MATCH(F59,MO_Common_ColumnHeader,0)),"Actual","Estimate") | N59: =IFERROR(INDEX(MO_RIS_COGS,0,MATCH(Guidance!F59,MO_Common_ColumnHeader,0))+INDEX(MO_RIS_RD,0,MATCH(Guidance!F59,MO_Common_ColumnHeader,0))+INDEX(MO_RIS_GA,0,MATCH(Guidance!F59,MO_Common_ColumnHeader,0))+INDEX(MO_RIS_SM,0,MATCH(Guidance!F59,MO_Common_ColumnHeader,0)),"N/A") | P59: =IF(ISNUMBER(N59),N59-K59,"N/A") | Q59: =IFERROR(IF(ISNUMBER(N59),(N59-K59)/ABS(K59),"N/A"),"N/A") | S59: 45866 | T59: CFO Commentary
A60: 904 | B60: =IF(INDEX(MO_SNA_IsHistoricalPeriod,,MATCH(F60,MO_Common_ColumnHeader,0)),"Historical","Forward") | D60: Non-GAAP Operating Expenses | F60: FY2025 | I60: 2934 | J60: 2934 | K60: =AVERAGE(I60:J60) | M60: =IF(INDEX(MO_SNA_IsHistoricalPeriod,,MATCH(F60,MO_Common_ColumnHeader,0)),"Actual","Estimate") | N60: =IFERROR(INDEX(MO_RIS_REV,0,MATCH(Guidance!F60,MO_Common_ColumnHeader,0))+INDEX(MO_RIS_RD_NONGAAP,0,MATCH(Guidance!F60,MO_Common_ColumnHeader,0))+INDEX(MO_RIS_GA_NONGAAP,0,MATCH(Guidance!F60,MO_Common_ColumnHeader,0))+INDEX(MO_RIS_SM_NONGAAP,0,MATCH(Guidance!F60,MO_Common_ColumnHeader,0))-INDEX(MO_RIS_GP_NONGAAP,0,MATCH(Guidance!F60,MO_Common_ColumnHeader,0)),"N/A") | P60: =IF(ISNUMBER(N60),N60-K60,"N/A") | Q60: =IFERROR(IF(ISNUMBER(N60),(N60-K60)/ABS(K60),"N/A"),"N/A") | S60: 45866 | T60: CFO Commentary
A61: 903
A62: 902 | B62: =IF(INDEX(MO_SNA_IsHistoricalPeriod,,MATCH(F62,MO_Common_ColumnHeader,0)),"Historical","Forward") | D62: =INDEX(INDIRECT(E62),0,COLUMN(MO_Common_Column_A)) | E62: MO_RIS_REV | F62: Q3-2025 | I62: 1305 | J62: 1335 | K62: =AVERAGE(I62:J62) | M62: =IF(INDEX(MO_SNA_IsHistoricalPeriod,,MATCH(F62,MO_Common_ColumnHeader,0)),"Actual","Estimate") | N62: =IFERROR(INDEX(INDIRECT(E62),0,MATCH(F62,MO_Common_ColumnHeader,0)),"N/A") | P62: =IF(ISNUMBER(N62),N62-K62,"N/A") | Q62: =IFERROR(IF(ISNUMBER(N62),(N62-K62)/ABS(K62),"N/A"),"N/A") | S62: 45866 | T62: CFO Commentary
A63: 901 | B63: =IF(INDEX(MO_SNA_IsHistoricalPeriod,,MATCH(F63,MO_Common_ColumnHeader,0)),"Historical","Forward") | D63: GAAP Operating Margin | E63: MO_MA_EBIT | F63: Q3-2025 | I63: 0.32 | J63: 0.33 | K63: =AVERAGE(I63:J63) | M63: =IF(INDEX(MO_SNA_IsHistoricalPeriod,,MATCH(F63,MO_Common_ColumnHeader,0)),"Actual","Estimate") | N63: =IFERROR(INDEX(INDIRECT(E63),0,MATCH(F63,MO_Common_ColumnHeader,0)),"N/A") | P63: =IF(ISNUMBER(N63),N63-K63,"N/A") | Q63: =IFERROR(IF(ISNUMBER(N63),(N63-K63)/ABS(K63),"N/A"),"N/A") | S63: 45866 | T63: CFO Commentary
A64: 900 | B64: =IF(INDEX(MO_SNA_IsHistoricalPeriod,,MATCH(F64,MO_Common_ColumnHeader,0)),"Historical","Forward") | D64: =INDEX(INDIRECT(E64),0,COLUMN(MO_Common_Column_A)) | E64: MO_MA_OperatingIncome_NONGAAP | F64: Q3-2025 | I64: 0.45 | J64: 0.46 | K64: =AVERAGE(I64:J64) | M64: =IF(INDEX(MO_SNA_IsHistoricalPeriod,,MATCH(F64,MO_Common_ColumnHeader,0)),"Actual","Estimate") | N64: =IFERROR(INDEX(INDIRECT(E64),0,MATCH(F64,MO_Common_ColumnHeader,0)),"N/A") | P64: =IF(ISNUMBER(N64),N64-K64,"N/A") | Q64: =IFERROR(IF(ISNUMBER(N64),(N64-K64)/ABS(K64),"N/A"),"N/A") | S64: 45866 | T64: CFO Commentary
A65: 899 | B65: =IF(INDEX(MO_SNA_IsHistoricalPeriod,,MATCH(F65,MO_Common_ColumnHeader,0)),"Historical","Forward") | D65: =INDEX(INDIRECT(E65),0,COLUMN(MO_Common_Column_A)) | E65: MO_RIS_EPS_WAD | F65: Q3-2025 | I65: 1.14 | J65: 1.2 | K65: =AVERAGE(I65:J65) | M65: =IF(INDEX(MO_SNA_IsHistoricalPeriod,,MATCH(F65,MO_Common_ColumnHeader,0)),"Actual","Estimate") | N65: =IFERROR(INDEX(INDIRECT(E65),0,MATCH(F65,MO_Common_ColumnHeader,0)),"N/A") | P65: =IF(ISNUMBER(N65),N65-K65,"N/A") | Q65: =IFERROR(IF(ISNUMBER(N65),(N65-K65)/ABS(K65),"N/A"),"N/A") | S65: 45866 | T65: CFO Commentary
A66: 898 | B66: =IF(INDEX(MO_SNA_IsHistoricalPeriod,,MATCH(F66,MO_Common_ColumnHeader,0)),"Historical","Forward") | D66: =INDEX(INDIRECT(E66),0,COLUMN(MO_Common_Column_A)) | E66: MO_RIS_EPS_WAD_Adj | F66: Q3-2025 | I66: 1.75 | J66: 1.81 | K66: =AVERAGE(I66:J66) | M66: =IF(INDEX(MO_SNA_IsHistoricalPeriod,,MATCH(F66,MO_Common_ColumnHeader,0)),"Actual","Estimate") | N66: =IFERROR(INDEX(INDIRECT(E66),0,MATCH(F66,MO_Common_ColumnHeader,0)),"N/A") | P66: =IF(ISNUMBER(N66),N66-K66,"N/A") | Q66: =IFERROR(IF(ISNUMBER(N66),(N66-K66)/ABS(K66),"N/A"),"N/A") | S66: 45866 | T66: CFO Commentary
A67: 897 | B67: =IF(INDEX(MO_SNA_IsHistoricalPeriod,,MATCH(F67,MO_Common_ColumnHeader,0)),"Historical","Forward") | D67: =INDEX(INDIRECT(E67),0,COLUMN(MO_Common_Column_A)) | E67: MO_CFSum_NetShares | F67: Q3-2025 | I67: -200 | J67: -200 | K67: =AVERAGE(I67:J67) | M67: =IF(INDEX(MO_SNA_IsHistoricalPeriod,,MATCH(F67,MO_Common_ColumnHeader,0)),"Actual","Estimate") | N67: =IFERROR(INDEX(INDIRECT(E67),0,MATCH(F67,MO_Common_ColumnHeader,0)),"N/A") | P67: =IF(ISNUMBER(N67),N67-K67,"N/A") | Q67: =IFERROR(IF(ISNUMBER(N67),(N67-K67)/ABS(K67),"N/A"),"N/A") | S67: 45866 | T67: CFO Commentary
A68: 896
A69: 895 | B69: =IF(INDEX(MO_SNA_IsHistoricalPeriod,,MATCH(F69,MO_Common_ColumnHeader,0)),"Historical","Forward") | D69: Recurring Revenue % | F69: FY2025 | I69: 0.8 | J69: 0.8 | K69: =AVERAGE(I69:J69) | M69: =IF(INDEX(MO_SNA_IsHistoricalPeriod,,MATCH(F69,MO_Common_ColumnHeader,0)),"Actual","Estimate") | N69: =IFERROR(INDEX(INDIRECT(E69),0,MATCH(F69,MO_Common_ColumnHeader,0)),"N/A") | P69: =IF(ISNUMBER(N69),N69-K69,"N/A") | Q69: =IFERROR(IF(ISNUMBER(N69),(N69-K69)/ABS(K69),"N/A"),"N/A") | S69: 45775 | T69: CFO Commentary
A70: 894 | B70: =IF(INDEX(MO_SNA_IsHistoricalPeriod,,MATCH(F70,MO_Common_ColumnHeader,0)),"Historical","Forward") | D70: Revenue from Beginning Backlog % | F70: FY2025 | I70: 0.7 | J70: 0.7 | K70: =AVERAGE(I70:J70) | M70: =IF(INDEX(MO_SNA_IsHistoricalPeriod,,MATCH(F70,MO_Common_ColumnHeader,0)),"Actual","Estimate") | N70: =IFERROR(INDEX(INDIRECT(E70),0,MATCH(F70,MO_Common_ColumnHeader,0)),"N/A") | P70: =IF(ISNUMBER(N70),N70-K70,"N/A") | Q70: =IFERROR(IF(ISNUMBER(N70),(N70-K70)/ABS(K70),"N/A"),"N/A") | S70: 45775 | T70: CFO Commentary
A71: 893 | B71: =IF(INDEX(MO_SNA_IsHistoricalPeriod,,MATCH(F71,MO_Common_ColumnHeader,0)),"Historical","Forward") | D71: =INDEX(INDIRECT(E71),0,COLUMN(MO_Common_Column_A)) | E71: MO_RIS_REV | F71: FY2025 | I71: 5150 | J71: 5230 | K71: =AVERAGE(I71:J71) | M71: =IF(INDEX(MO_SNA_IsHistoricalPeriod,,MATCH(F71,MO_Common_ColumnHeader,0)),"Actual","Estimate") | N71: =IFERROR(INDEX(INDIRECT(E71),0,MATCH(F71,MO_Common_ColumnHeader,0)),"N/A") | P71: =IF(ISNUMBER(N71),N71-K71,"N/A") | Q71: =IFERROR(IF(ISNUMBER(N71),(N71-K71)/ABS(K71),"N/A"),"N/A") | S71: 45775 | T71: CFO Commentary
A72: 892 | B72: =IF(INDEX(MO_SNA_IsHistoricalPeriod,,MATCH(F72,MO_Common_ColumnHeader,0)),"Historical","Forward") | D72: GAAP Operating Margin | E72: MO_MA_EBIT | F72: FY2025 | I72: 0.3025 | J72: 0.3125 | K72: =AVERAGE(I72:J72) | M72: =IF(INDEX(MO_SNA_IsHistoricalPeriod,,MATCH(F72,MO_Common_ColumnHeader,0)),"Actual","Estimate") | N72: =IFERROR(INDEX(INDIRECT(E72),0,MATCH(F72,MO_Common_ColumnHeader,0)),"N/A") | P72: =IF(ISNUMBER(N72),N72-K72,"N/A") | Q72: =IFERROR(IF(ISNUMBER(N72),(N72-K72)/ABS(K72),"N/A"),"N/A") | S72: 45775 | T72: CFO Commentary
A73: 891 | B73: =IF(INDEX(MO_SNA_IsHistoricalPeriod,,MATCH(F73,MO_Common_ColumnHeader,0)),"Historical","Forward") | D73: =INDEX(INDIRECT(E73),0,COLUMN(MO_Common_Column_A)) | E73: MO_MA_OperatingIncome_NONGAAP | F73: FY2025 | I73: 0.4325 | J73: 0.4425 | K73: =AVERAGE(I73:J73) | M73: =IF(INDEX(MO_SNA_IsHistoricalPeriod,,MATCH(F73,MO_Common_ColumnHeader,0)),"Actual","Estimate") | N73: =IFERROR(INDEX(INDIRECT(E73),0,MATCH(F73,MO_Common_ColumnHeader,0)),"N/A") | P73: =IF(ISNUMBER(N73),N73-K73,"N/A") | Q73: =IFERROR(IF(ISNUMBER(N73),(N73-K73)/ABS(K73),"N/A"),"N/A") | S73: 45775 | T73: CFO Commentary
A74: 890 | B74: =IF(INDEX(MO_SNA_IsHistoricalPeriod,,MATCH(F74,MO_Common_ColumnHeader,0)),"Historical","Forward") | D74: =INDEX(INDIRECT(E74),0,COLUMN(MO_Common_Column_A)) | E74: MO_RIS_EPS_WAD | F74: FY2025 | I74: 4.21 | J74: 4.31 | K74: =AVERAGE(I74:J74) | M74: =IF(INDEX(MO_SNA_IsHistoricalPeriod,,MATCH(F74,MO_Common_ColumnHeader,0)),"Actual","Estimate") | N74: =IFERROR(INDEX(INDIRECT(E74),0,MATCH(F74,MO_Common_ColumnHeader,0)),"N/A") | P74: =IF(ISNUMBER(N74),N74-K74,"N/A") | Q74: =IFERROR(IF(ISNUMBER(N74),(N74-K74)/ABS(K74),"N/A"),"N/A") | S74: 45775 | T74: CFO Commentary
A75: 889 | B75: =IF(INDEX(MO_SNA_IsHistoricalPeriod,,MATCH(F75,MO_Common_ColumnHeader,0)),"Historical","Forward") | D75: =INDEX(INDIRECT(E75),0,COLUMN(MO_Common_Column_A)) | E75: MO_RIS_EPS_WAD_Adj | F75: FY2025 | I75: 6.73 | J75: 6.83 | K75: =AVERAGE(I75:J75) | M75: =IF(INDEX(MO_SNA_IsHistoricalPeriod,,MATCH(F75,MO_Common_ColumnHeader,0)),"Actual","Estimate") | N75: =IFERROR(INDEX(INDIRECT(E75),0,MATCH(F75,MO_Common_ColumnHeader,0)),"N/A") | P75: =IF(ISNUMBER(N75),N75-K75,"N/A") | Q75: =IFERROR(IF(ISNUMBER(N75),(N75-K75)/ABS(K75),"N/A"),"N/A") | S75: 45775 | T75: CFO Commentary
A76: 888 | B76: =IF(INDEX(MO_SNA_IsHistoricalPeriod,,MATCH(F76,MO_Common_ColumnHeader,0)),"Historical","Forward") | D76: =INDEX(INDIRECT(E76),0,COLUMN(MO_Common_Column_A)) | E76: MO_CFS_CFO | F76: FY2025 | I76: 1600 | J76: 1700 | K76: =AVERAGE(I76:J76) | M76: =IF(INDEX(MO_SNA_IsHistoricalPeriod,,MATCH(F76,MO_Common_ColumnHeader,0)),"Actual","Estimate") | N76: =IFERROR(INDEX(INDIRECT(E76),0,MATCH(F76,MO_Common_ColumnHeader,0)),"N/A") | P76: =IF(ISNUMBER(N76),N76-K76,"N/A") | Q76: =IFERROR(IF(ISNUMBER(N76),(N76-K76)/ABS(K76),"N/A"),"N/A") | S76: 45775 | T76: CFO Commentary
A77: 887 | B77: =IF(INDEX(MO_SNA_IsHistoricalPeriod,,MATCH(F77,MO_Common_ColumnHeader,0)),"Historical","Forward") | D77: GAAP Other Income & Expense | F77: FY2025 | I77: -43 | J77: -57 | K77: =AVERAGE(I77:J77) | M77: =IF(INDEX(MO_SNA_IsHistoricalPeriod,,MATCH(F77,MO_Common_ColumnHeader,0)),"Actual","Estimate") | N77: =-IFERROR(INDEX(MO_RIS_IE_Net,0,MATCH(F77,MO_Common_ColumnHeader,0)),"N/A")-IFERROR(INDEX(MO_RIS_OI,0,MATCH(F77,MO_Common_ColumnHeader,0)),"N/A") | P77: =IF(ISNUMBER(N77),N77-K77,"N/A") | Q77: =IFERROR(IF(ISNUMBER(N77),(N77-K77)/ABS(K77),"N/A"),"N/A") | S77: 45775 | T77: CFO Commentary
A78: 886 | B78: =IF(INDEX(MO_SNA_IsHistoricalPeriod,,MATCH(F78,MO_Common_ColumnHeader,0)),"Historical","Forward") | D78: Non-GAAP Other Income & Expense | F78: FY2025 | I78: -40 | J78: -54 | K78: =AVERAGE(I78:J78) | M78: =IF(INDEX(MO_SNA_IsHistoricalPeriod,,MATCH(F78,MO_Common_ColumnHeader,0)),"Actual","Estimate") | N78: =-IFERROR(INDEX(MO_RIS_IE_Net_NONGAAP,0,MATCH(F78,MO_Common_ColumnHeader,0)),"N/A")-IFERROR(INDEX(MO_RIS_OI_NONGAAP,0,MATCH(F78,MO_Common_ColumnHeader,0)),"N/A") | P78: =IF(ISNUMBER(N78),N78-K78,"N/A") | Q78: =IFERROR(IF(ISNUMBER(N78),(N78-K78)/ABS(K78),"N/A"),"N/A") | S78: 45775 | T78: CFO Commentary
A79: 885 | B79: =IF(INDEX(MO_SNA_IsHistoricalPeriod,,MATCH(F79,MO_Common_ColumnHeader,0)),"Historical","Forward") | D79: GAAP Tax Rate | E79: MO_RIS_TaxRate | F79: FY2025 | I79: 0.26 | J79: 0.26 | K79: =AVERAGE(I79:J79) | M79: =IF(INDEX(MO_SNA_IsHistoricalPeriod,,MATCH(F79,MO_Common_ColumnHeader,0)),"Actual","Estimate") | N79: =IFERROR(INDEX(INDIRECT(E79),0,MATCH(F79,MO_Common_ColumnHeader,0)),"N/A") | P79: =IF(ISNUMBER(N79),N79-K79,"N/A") | Q79: =IFERROR(IF(ISNUMBER(N79),(N79-K79)/ABS(K79),"N/A"),"N/A") | S79: 45775 | T79: CFO Commentary
A80: 884 | B80: =IF(INDEX(MO_SNA_IsHistoricalPeriod,,MATCH(F80,MO_Common_ColumnHeader,0)),"Historical","Forward") | D80: =INDEX(INDIRECT(E80),0,COLUMN(MO_Common_Column_A)) | E80: MO_RIS_TaxRate_NONGAAP | F80: FY2025 | I80: 0.165 | J80: 0.165 | K80: =AVERAGE(I80:J80) | M80: =IF(INDEX(MO_SNA_IsHistoricalPeriod,,MATCH(F80,MO_Common_ColumnHeader,0)),"Actual","Estimate") | N80: =IFERROR(INDEX(INDIRECT(E80),0,MATCH(F80,MO_Common_ColumnHeader,0)),"N/A") | P80: =IF(ISNUMBER(N80),N80-K80,"N/A") | Q80: =IFERROR(IF(ISNUMBER(N80),(N80-K80)/ABS(K80),"N/A"),"N/A") | S80: 45775 | T80: CFO Commentary
A81: 883 | B81: =IF(INDEX(MO_SNA_IsHistoricalPeriod,,MATCH(F81,MO_Common_ColumnHeader,0)),"Historical","Forward") | D81: =INDEX(INDIRECT(E81),0,COLUMN(MO_Common_Column_A)) | E81: MO_RIS_ShareCount_WAD | F81: FY2025 | I81: 273 | J81: 275 | K81: =AVERAGE(I81:J81) | M81: =IF(INDEX(MO_SNA_IsHistoricalPeriod,,MATCH(F81,MO_Common_ColumnHeader,0)),"Actual","Estimate") | N81: =IFERROR(INDEX(INDIRECT(E81),0,MATCH(F81,MO_Common_ColumnHeader,0)),"N/A") | P81: =IF(ISNUMBER(N81),N81-K81,"N/A") | Q81: =IFERROR(IF(ISNUMBER(N81),(N81-K81)/ABS(K81),"N/A"),"N/A") | S81: 45775 | T81: CFO Commentary
A82: 882 | B82: =IF(INDEX(MO_SNA_IsHistoricalPeriod,,MATCH(F82,MO_Common_ColumnHeader,0)),"Historical","Forward") | D82: DSO | F82: FY2025 | I82: 50 | J82: 50 | K82: =AVERAGE(I82:J82) | M82: =IF(INDEX(MO_SNA_IsHistoricalPeriod,,MATCH(F82,MO_Common_ColumnHeader,0)),"Actual","Estimate") | N82: =IFERROR(INDEX(INDIRECT(E82),0,MATCH(F82,MO_Common_ColumnHeader,0)),"N/A") | P82: =IF(ISNUMBER(N82),N82-K82,"N/A") | Q82: =IFERROR(IF(ISNUMBER(N82),(N82-K82)/ABS(K82),"N/A"),"N/A") | S82: 45775 | T82: CFO Commentary
A83: 881 | B83: =IF(INDEX(MO_SNA_IsHistoricalPeriod,,MATCH(F83,MO_Common_ColumnHeader,0)),"Historical","Forward") | D83: =INDEX(INDIRECT(E83),0,COLUMN(MO_Common_Column_A)) | E83: MO_CFSum_Capex | F83: FY2025 | I83: -150 | J83: -150 | K83: =AVERAGE(I83:J83) | M83: =IF(INDEX(MO_SNA_IsHistoricalPeriod,,MATCH(F83,MO_Common_ColumnHeader,0)),"Actual","Estimate") | N83: =IFERROR(INDEX(INDIRECT(E83),0,MATCH(F83,MO_Common_ColumnHeader,0)),"N/A") | P83: =IF(ISNUMBER(N83),N83-K83,"N/A") | Q83: =IFERROR(IF(ISNUMBER(N83),(N83-K83)/ABS(K83),"N/A"),"N/A") | S83: 45775 | T83: CFO Commentary
A84: 880 | B84: =IF(INDEX(MO_SNA_IsHistoricalPeriod,,MATCH(F84,MO_Common_ColumnHeader,0)),"Historical","Forward") | D84: =INDEX(INDIRECT(E84),0,COLUMN(MO_Common_Column_A)) | E84: MO_RIS_SBC | F84: FY2025 | I84: 466 | J84: 466 | K84: =AVERAGE(I84:J84) | M84: =IF(INDEX(MO_SNA_IsHistoricalPeriod,,MATCH(F84,MO_Common_ColumnHeader,0)),"Actual","Estimate") | N84: =IFERROR(INDEX(INDIRECT(E84),0,MATCH(F84,MO_Common_ColumnHeader,0)),"N/A") | P84: =IF(ISNUMBER(N84),N84-K84,"N/A") | Q84: =IFERROR(IF(ISNUMBER(N84),(N84-K84)/ABS(K84),"N/A"),"N/A") | S84: 45775 | T84: CFO Commentary
A85: 879 | B85: =IF(INDEX(MO_SNA_IsHistoricalPeriod,,MATCH(F85,MO_Common_ColumnHeader,0)),"Historical","Forward") | D85: =INDEX(INDIRECT(E85),0,COLUMN(MO_Common_Column_A)) | E85: MO_RIS_Daintangibles | F85: FY2025 | I85: 98 | J85: 98 | K85: =AVERAGE(I85:J85) | M85: =IF(INDEX(MO_SNA_IsHistoricalPeriod,,MATCH(F85,MO_Common_ColumnHeader,0)),"Actual","Estimate") | N85: =IFERROR(INDEX(INDIRECT(E85),0,MATCH(F85,MO_Common_ColumnHeader,0)),"N/A") | P85: =IF(ISNUMBER(N85),N85-K85,"N/A") | Q85: =IFERROR(IF(ISNUMBER(N85),(N85-K85)/ABS(K85),"N/A"),"N/A") | S85: 45775 | T85: CFO Commentary
A86: 878 | B86: =IF(INDEX(MO_SNA_IsHistoricalPeriod,,MATCH(F86,MO_Common_ColumnHeader,0)),"Historical","Forward") | D86: Acquisition and integration-related costs | F86: FY2025 | I86: 86 | J86: 86 | K86: =AVERAGE(I86:J86) | M86: =IF(INDEX(MO_SNA_IsHistoricalPeriod,,MATCH(F86,MO_Common_ColumnHeader,0)),"Actual","Estimate") | N86: =IFERROR(INDEX(INDIRECT(E86),0,MATCH(F86,MO_Common_ColumnHeader,0)),"N/A") | P86: =IF(ISNUMBER(N86),N86-K86,"N/A") | Q86: =IFERROR(IF(ISNUMBER(N86),(N86-K86)/ABS(K86),"N/A"),"N/A") | S86: 45775 | T86: CFO Commentary
A87: 877 | B87: =IF(INDEX(MO_SNA_IsHistoricalPeriod,,MATCH(F87,MO_Common_ColumnHeader,0)),"Historical","Forward") | D87: Restructuring and other credits | F87: FY2025 | I87: 0 | J87: 0 | K87: =AVERAGE(I87:J87) | M87: =IF(INDEX(MO_SNA_IsHistoricalPeriod,,MATCH(F87,MO_Common_ColumnHeader,0)),"Actual","Estimate") | N87: =IFERROR(INDEX(INDIRECT(E87),0,MATCH(F87,MO_Common_ColumnHeader,0)),"N/A") | P87: =IF(ISNUMBER(N87),N87-K87,"N/A") | Q87: =IFERROR(IF(ISNUMBER(N87),(N87-K87)/ABS(K87),"N/A"),"N/A") | S87: 45775 | T87: CFO Commentary
A88: 876 | B88: =IF(INDEX(MO_SNA_IsHistoricalPeriod,,MATCH(F88,MO_Common_ColumnHeader,0)),"Historical","Forward") | D88: Non-Qualified deferred compensation expenses | F88: FY2025 | I88: 2 | J88: 2 | K88: =AVERAGE(I88:J88) | M88: =IF(INDEX(MO_SNA_IsHistoricalPeriod,,MATCH(F88,MO_Common_ColumnHeader,0)),"Actual","Estimate") | N88: =IFERROR(INDEX(INDIRECT(E88),0,MATCH(F88,MO_Common_ColumnHeader,0)),"N/A") | P88: =IF(ISNUMBER(N88),N88-K88,"N/A") | Q88: =IFERROR(IF(ISNUMBER(N88),(N88-K88)/ABS(K88),"N/A"),"N/A") | S88: 45775 | T88: CFO Commentary
A89: 875 | B89: =IF(INDEX(MO_SNA_IsHistoricalPeriod,,MATCH(F89,MO_Common_ColumnHeader,0)),"Historical","Forward") | D89: Special charges | F89: FY2025 | I89: -2 | J89: -2 | K89: =AVERAGE(I89:J89) | M89: =IF(INDEX(MO_SNA_IsHistoricalPeriod,,MATCH(F89,MO_Common_ColumnHeader,0)),"Actual","Estimate") | N89: =IFERROR(INDEX(INDIRECT(E89),0,MATCH(F89,MO_Common_ColumnHeader,0)),"N/A") | P89: =IF(ISNUMBER(N89),N89-K89,"N/A") | Q89: =IFERROR(IF(ISNUMBER(N89),(N89-K89)/ABS(K89),"N/A"),"N/A") | S89: 45775 | T89: CFO Commentary
A90: 874 | B90: =IF(INDEX(MO_SNA_IsHistoricalPeriod,,MATCH(F90,MO_Common_ColumnHeader,0)),"Historical","Forward") | D90: GAAP Operating Expenses | F90: FY2025 | I90: 3569 | J90: 3569 | K90: =AVERAGE(I90:J90) | M90: =IF(INDEX(MO_SNA_IsHistoricalPeriod,,MATCH(F90,MO_Common_ColumnHeader,0)),"Actual","Estimate") | N90: =IFERROR(INDEX(MO_RIS_COGS,0,MATCH(Guidance!F90,MO_Common_ColumnHeader,0))+INDEX(MO_RIS_RD,0,MATCH(Guidance!F90,MO_Common_ColumnHeader,0))+INDEX(MO_RIS_GA,0,MATCH(Guidance!F90,MO_Common_ColumnHeader,0))+INDEX(MO_RIS_SM,0,MATCH(Guidance!F90,MO_Common_ColumnHeader,0)),"N/A") | P90: =IF(ISNUMBER(N90),N90-K90,"N/A") | Q90: =IFERROR(IF(ISNUMBER(N90),(N90-K90)/ABS(K90),"N/A"),"N/A") | S90: 45775 | T90: CFO Commentary
A91: 873 | B91: =IF(INDEX(MO_SNA_IsHistoricalPeriod,,MATCH(F91,MO_Common_ColumnHeader,0)),"Historical","Forward") | D91: Non-GAAP Operating Expenses | F91: FY2025 | I91: 2919 | J91: 2919 | K91: =AVERAGE(I91:J91) | M91: =IF(INDEX(MO_SNA_IsHistoricalPeriod,,MATCH(F91,MO_Common_ColumnHeader,0)),"Actual","Estimate") | N91: =IFERROR(INDEX(MO_RIS_REV,0,MATCH(Guidance!F91,MO_Common_ColumnHeader,0))+INDEX(MO_RIS_RD_NONGAAP,0,MATCH(Guidance!F91,MO_Common_ColumnHeader,0))+INDEX(MO_RIS_GA_NONGAAP,0,MATCH(Guidance!F91,MO_Common_ColumnHeader,0))+INDEX(MO_RIS_SM_NONGAAP,0,MATCH(Guidance!F91,MO_Common_ColumnHeader,0))-INDEX(MO_RIS_GP_NONGAAP,0,MATCH(Guidance!F91,MO_Common_ColumnHeader,0)),"N/A") | P91: =IF(ISNUMBER(N91),N91-K91,"N/A") | Q91: =IFERROR(IF(ISNUMBER(N91),(N91-K91)/ABS(K91),"N/A"),"N/A") | S91: 45775 | T91: CFO Commentary
A92: 872
A93: 871 | B93: =IF(INDEX(MO_SNA_IsHistoricalPeriod,,MATCH(F93,MO_Common_ColumnHeader,0)),"Historical","Forward") | D93: =INDEX(INDIRECT(E93),0,COLUMN(MO_Common_Column_A)) | E93: MO_RIS_REV | F93: Q2-2025 | I93: 1250 | J93: 1270 | K93: =AVERAGE(I93:J93) | M93: =IF(INDEX(MO_SNA_IsHistoricalPeriod,,MATCH(F93,MO_Common_ColumnHeader,0)),"Actual","Estimate") | N93: =IFERROR(INDEX(INDIRECT(E93),0,MATCH(F93,MO_Common_ColumnHeader,0)),"N/A") | P93: =IF(ISNUMBER(N93),N93-K93,"N/A") | Q93: =IFERROR(IF(ISNUMBER(N93),(N93-K93)/ABS(K93),"N/A"),"N/A") | S93: 45775 | T93: CFO Commentary
A94: 870 | B94: =IF(INDEX(MO_SNA_IsHistoricalPeriod,,MATCH(F94,MO_Common_ColumnHeader,0)),"Historical","Forward") | D94: GAAP Operating Margin | E94: MO_MA_EBIT | F94: Q2-2025 | I94: 0.275 | J94: 0.285 | K94: =AVERAGE(I94:J94) | M94: =IF(INDEX(MO_SNA_IsHistoricalPeriod,,MATCH(F94,MO_Common_ColumnHeader,0)),"Actual","Estimate") | N94: =IFERROR(INDEX(INDIRECT(E94),0,MATCH(F94,MO_Common_ColumnHeader,0)),"N/A") | P94: =IF(ISNUMBER(N94),N94-K94,"N/A") | Q94: =IFERROR(IF(ISNUMBER(N94),(N94-K94)/ABS(K94),"N/A"),"N/A") | S94: 45775 | T94: CFO Commentary
A95: 869 | B95: =IF(INDEX(MO_SNA_IsHistoricalPeriod,,MATCH(F95,MO_Common_ColumnHeader,0)),"Historical","Forward") | D95: =INDEX(INDIRECT(E95),0,COLUMN(MO_Common_Column_A)) | E95: MO_MA_OperatingIncome_NONGAAP | F95: Q2-2025 | I95: 0.415 | J95: 0.425 | K95: =AVERAGE(I95:J95) | M95: =IF(INDEX(MO_SNA_IsHistoricalPeriod,,MATCH(F95,MO_Common_ColumnHeader,0)),"Actual","Estimate") | N95: =IFERROR(INDEX(INDIRECT(E95),0,MATCH(F95,MO_Common_ColumnHeader,0)),"N/A") | P95: =IF(ISNUMBER(N95),N95-K95,"N/A") | Q95: =IFERROR(IF(ISNUMBER(N95),(N95-K95)/ABS(K95),"N/A"),"N/A") | S95: 45775 | T95: CFO Commentary
A96: 868 | B96: =IF(INDEX(MO_SNA_IsHistoricalPeriod,,MATCH(F96,MO_Common_ColumnHeader,0)),"Historical","Forward") | D96: =INDEX(INDIRECT(E96),0,COLUMN(MO_Common_Column_A)) | E96: MO_RIS_EPS_WAD | F96: Q2-2025 | I96: 0.89 | J96: 0.95 | K96: =AVERAGE(I96:J96) | M96: =IF(INDEX(MO_SNA_IsHistoricalPeriod,,MATCH(F96,MO_Common_ColumnHeader,0)),"Actual","Estimate") | N96: =IFERROR(INDEX(INDIRECT(E96),0,MATCH(F96,MO_Common_ColumnHeader,0)),"N/A") | P96: =IF(ISNUMBER(N96),N96-K96,"N/A") | Q96: =IFERROR(IF(ISNUMBER(N96),(N96-K96)/ABS(K96),"N/A"),"N/A") | S96: 45775 | T96: CFO Commentary
A97: 867 | B97: =IF(INDEX(MO_SNA_IsHistoricalPeriod,,MATCH(F97,MO_Common_ColumnHeader,0)),"Historical","Forward") | D97: =INDEX(INDIRECT(E97),0,COLUMN(MO_Common_Column_A)) | E97: MO_RIS_EPS_WAD_Adj | F97: Q2-2025 | I97: 1.55 | J97: 1.61 | K97: =AVERAGE(I97:J97) | M97: =IF(INDEX(MO_SNA_IsHistoricalPeriod,,MATCH(F97,MO_Common_ColumnHeader,0)),"Actual","Estimate") | N97: =IFERROR(INDEX(INDIRECT(E97),0,MATCH(F97,MO_Common_ColumnHeader,0)),"N/A") | P97: =IF(ISNUMBER(N97),N97-K97,"N/A") | Q97: =IFERROR(IF(ISNUMBER(N97),(N97-K97)/ABS(K97),"N/A"),"N/A") | S97: 45775 | T97: CFO Commentary
A98: 866 | B98: =IF(INDEX(MO_SNA_IsHistoricalPeriod,,MATCH(F98,MO_Common_ColumnHeader,0)),"Historical","Forward") | D98: =INDEX(INDIRECT(E98),0,COLUMN(MO_Common_Column_A)) | E98: MO_CFSum_NetShares | F98: Q2-2025 | I98: -175 | J98: -175 | K98: =AVERAGE(I98:J98) | M98: =IF(INDEX(MO_SNA_IsHistoricalPeriod,,MATCH(F98,MO_Common_ColumnHeader,0)),"Actual","Estimate") | N98: =IFERROR(INDEX(INDIRECT(E98),0,MATCH(F98,MO_Common_ColumnHeader,0)),"N/A") | P98: =IF(ISNUMBER(N98),N98-K98,"N/A") | Q98: =IFERROR(IF(ISNUMBER(N98),(N98-K98)/ABS(K98),"N/A"),"N/A") | S98: 45775 | T98: CFO Commentary
A99: 865
A100: 864 | B100: =IF(INDEX(MO_SNA_IsHistoricalPeriod,,MATCH(F100,MO_Common_ColumnHeader,0)),"Historical","Forward") | D100: Recurring Revenue % | F100: FY2025 | I100: 0.8 | J100: 0.8 | K100: =AVERAGE(I100:J100) | M100: =IF(INDEX(MO_SNA_IsHistoricalPeriod,,MATCH(F100,MO_Common_ColumnHeader,0)),"Actual","Estimate") | N100: =IFERROR(INDEX(INDIRECT(E100),0,MATCH(F100,MO_Common_ColumnHeader,0)),"N/A") | P100: =IF(ISNUMBER(N100),N100-K100,"N/A") | Q100: =IFERROR(IF(ISNUMBER(N100),(N100-K100)/ABS(K100),"N/A"),"N/A") | S100: 45706 | T100: CFO Commentary
A101: 863 | B101: =IF(INDEX(MO_SNA_IsHistoricalPeriod,,MATCH(F101,MO_Common_ColumnHeader,0)),"Historical","Forward") | D101: Revenue from Beginning Backlog % | F101: FY2025 | I101: 0.7 | J101: 0.7 | K101: =AVERAGE(I101:J101) | M101: =IF(INDEX(MO_SNA_IsHistoricalPeriod,,MATCH(F101,MO_Common_ColumnHeader,0)),"Actual","Estimate") | N101: =IFERROR(INDEX(INDIRECT(E101),0,MATCH(F101,MO_Common_ColumnHeader,0)),"N/A") | P101: =IF(ISNUMBER(N101),N101-K101,"N/A") | Q101: =IFERROR(IF(ISNUMBER(N101),(N101-K101)/ABS(K101),"N/A"),"N/A") | S101: 45706 | T101: CFO Commentary
...

Sheet Summary Page
A1: =MO.CompanyName | C1: =INDEX(MO_Common_QEndDate,0,COLUMN()) | D1: =INDEX(MO_Common_QEndDate,0,COLUMN()) | E1: =INDEX(MO_Common_QEndDate,0,COLUMN()) | F1: =INDEX(MO_Common_QEndDate,0,COLUMN()) | G1: =INDEX(MO_Common_QEndDate,0,COLUMN()) | H1: =INDEX(MO_Common_QEndDate,0,COLUMN()) | I1: =INDEX(MO_Common_QEndDate,0,COLUMN()) | J1: =INDEX(MO_Common_QEndDate,0,COLUMN()) | ... CA1: =INDEX(MO_Common_QEndDate,0,COLUMN())
A2: Reports | B2: =MO.ReportFX | C2: =INDEX(MO_Common_ColumnHeader,0,COLUMN()) | D2: =INDEX(MO_Common_ColumnHeader,0,COLUMN()) | E2: =INDEX(MO_Common_ColumnHeader,0,COLUMN()) | F2: =INDEX(MO_Common_ColumnHeader,0,COLUMN()) | G2: =INDEX(MO_Common_ColumnHeader,0,COLUMN()) | H2: =INDEX(MO_Common_ColumnHeader,0,COLUMN()) | I2: =INDEX(MO_Common_ColumnHeader,0,COLUMN()) | J2: =INDEX(MO_Common_ColumnHeader,0,COLUMN()) | ... CA2: =INDEX(MO_Common_ColumnHeader,0,COLUMN())
A3: Capitalization Summary
A4: ="Stock Price - "&SP.ValuationToggle | B4: EoP | C4: =IF(INDEX(MO_SNA_IsHistoricalPeriod,1,COLUMN())=FALSE,MO.LastPrice/HP.MRFX,CHOOSE(VLOOKUP(SP.ValuationToggle,tb_ValuationToggle,COLUMNS(tb_ValuationToggle),FALSE),INDEX(MO_SPT_StockHigh,1,COLUMN()),INDEX(MO_SPT_StockLow,1,COLUMN()),INDEX(MO_SPT_StockAverage,1,COLUMN()),INDEX(MO_SPT_StockEoP,1,COLUMN()))/IF(SP.ValuationToggle="EoP",IF(INDEX(MO_SPT_FXEoP,1,COLUMN())=0,1,INDEX(MO_SPT_FXEoP,1,COLUMN())),IF(INDEX(MO_SPT_FXAverage,1,COLUMN())=0,1,INDEX(MO_SPT_FXAverage,1,COLUMN())))) | D4: =IF(INDEX(MO_SNA_IsHistoricalPeriod,1,COLUMN())=FALSE,MO.LastPrice/HP.MRFX,CHOOSE(VLOOKUP(SP.ValuationToggle,tb_ValuationToggle,COLUMNS(tb_ValuationToggle),FALSE),INDEX(MO_SPT_StockHigh,1,COLUMN()),INDEX(MO_SPT_StockLow,1,COLUMN()),INDEX(MO_SPT_StockAverage,1,COLUMN()),INDEX(MO_SPT_StockEoP,1,COLUMN()))/IF(SP.ValuationToggle="EoP",IF(INDEX(MO_SPT_FXEoP,1,COLUMN())=0,1,INDEX(MO_SPT_FXEoP,1,COLUMN())),IF(INDEX(MO_SPT_FXAverage,1,COLUMN())=0,1,INDEX(MO_SPT_FXAverage,1,COLUMN())))) | E4: =IF(INDEX(MO_SNA_IsHistoricalPeriod,1,COLUMN())=FALSE,MO.LastPrice/HP.MRFX,CHOOSE(VLOOKUP(SP.ValuationToggle,tb_ValuationToggle,COLUMNS(tb_ValuationToggle),FALSE),INDEX(MO_SPT_StockHigh,1,COLUMN()),INDEX(MO_SPT_StockLow,1,COLUMN()),INDEX(MO_SPT_StockAverage,1,COLUMN()),INDEX(MO_SPT_StockEoP,1,COLUMN()))/IF(SP.ValuationToggle="EoP",IF(INDEX(MO_SPT_FXEoP,1,COLUMN())=0,1,INDEX(MO_SPT_FXEoP,1,COLUMN())),IF(INDEX(MO_SPT_FXAverage,1,COLUMN())=0,1,INDEX(MO_SPT_FXAverage,1,COLUMN())))) | F4: =IF(INDEX(MO_SNA_IsHistoricalPeriod,1,COLUMN())=FALSE,MO.LastPrice/HP.MRFX,CHOOSE(VLOOKUP(SP.ValuationToggle,tb_ValuationToggle,COLUMNS(tb_ValuationToggle),FALSE),INDEX(MO_SPT_StockHigh,1,COLUMN()),INDEX(MO_SPT_StockLow,1,COLUMN()),INDEX(MO_SPT_StockAverage,1,COLUMN()),INDEX(MO_SPT_StockEoP,1,COLUMN()))/IF(SP.ValuationToggle="EoP",IF(INDEX(MO_SPT_FXEoP,1,COLUMN())=0,1,INDEX(MO_SPT_FXEoP,1,COLUMN())),IF(INDEX(MO_SPT_FXAverage,1,COLUMN())=0,1,INDEX(MO_SPT_FXAverage,1,COLUMN())))) | G4: =IF(INDEX(MO_SNA_IsHistoricalPeriod,1,COLUMN())=FALSE,MO.LastPrice/HP.MRFX,CHOOSE(VLOOKUP(SP.ValuationToggle,tb_ValuationToggle,COLUMNS(tb_ValuationToggle),FALSE),INDEX(MO_SPT_StockHigh,1,COLUMN()),INDEX(MO_SPT_StockLow,1,COLUMN()),INDEX(MO_SPT_StockAverage,1,COLUMN()),INDEX(MO_SPT_StockEoP,1,COLUMN()))/IF(SP.ValuationToggle="EoP",IF(INDEX(MO_SPT_FXEoP,1,COLUMN())=0,1,INDEX(MO_SPT_FXEoP,1,COLUMN())),IF(INDEX(MO_SPT_FXAverage,1,COLUMN())=0,1,INDEX(MO_SPT_FXAverage,1,COLUMN())))) | H4: =IF(INDEX(MO_SNA_IsHistoricalPeriod,1,COLUMN())=FALSE,MO.LastPrice/HP.MRFX,CHOOSE(VLOOKUP(SP.ValuationToggle,tb_ValuationToggle,COLUMNS(tb_ValuationToggle),FALSE),INDEX(MO_SPT_StockHigh,1,COLUMN()),INDEX(MO_SPT_StockLow,1,COLUMN()),INDEX(MO_SPT_StockAverage,1,COLUMN()),INDEX(MO_SPT_StockEoP,1,COLUMN()))/IF(SP.ValuationToggle="EoP",IF(INDEX(MO_SPT_FXEoP,1,COLUMN())=0,1,INDEX(MO_SPT_FXEoP,1,COLUMN())),IF(INDEX(MO_SPT_FXAverage,1,COLUMN())=0,1,INDEX(MO_SPT_FXAverage,1,COLUMN())))) | I4: =IF(INDEX(MO_SNA_IsHistoricalPeriod,1,COLUMN())=FALSE,MO.LastPrice/HP.MRFX,CHOOSE(VLOOKUP(SP.ValuationToggle,tb_ValuationToggle,COLUMNS(tb_ValuationToggle),FALSE),INDEX(MO_SPT_StockHigh,1,COLUMN()),INDEX(MO_SPT_StockLow,1,COLUMN()),INDEX(MO_SPT_StockAverage,1,COLUMN()),INDEX(MO_SPT_StockEoP,1,COLUMN()))/IF(SP.ValuationToggle="EoP",IF(INDEX(MO_SPT_FXEoP,1,COLUMN())=0,1,INDEX(MO_SPT_FXEoP,1,COLUMN())),IF(INDEX(MO_SPT_FXAverage,1,COLUMN())=0,1,INDEX(MO_SPT_FXAverage,1,COLUMN())))) | J4: =IF(INDEX(MO_SNA_IsHistoricalPeriod,1,COLUMN())=FALSE,MO.LastPrice/HP.MRFX,CHOOSE(VLOOKUP(SP.ValuationToggle,tb_ValuationToggle,COLUMNS(tb_ValuationToggle),FALSE),INDEX(MO_SPT_StockHigh,1,COLUMN()),INDEX(MO_SPT_StockLow,1,COLUMN()),INDEX(MO_SPT_StockAverage,1,COLUMN()),INDEX(MO_SPT_StockEoP,1,COLUMN()))/IF(SP.ValuationToggle="EoP",IF(INDEX(MO_SPT_FXEoP,1,COLUMN())=0,1,INDEX(MO_SPT_FXEoP,1,COLUMN())),IF(INDEX(MO_SPT_FXAverage,1,COLUMN())=0,1,INDEX(MO_SPT_FXAverage,1,COLUMN())))) | ... CA4: =IF(INDEX(MO_SNA_IsHistoricalPeriod,1,COLUMN())=FALSE,MO.LastPrice/HP.MRFX,CHOOSE(VLOOKUP(SP.ValuationToggle,tb_ValuationToggle,COLUMNS(tb_ValuationToggle),FALSE),INDEX(MO_SPT_StockHigh,1,COLUMN()),INDEX(MO_SPT_StockLow,1,COLUMN()),INDEX(MO_SPT_StockAverage,1,COLUMN()),INDEX(MO_SPT_StockEoP,1,COLUMN()))/IF(SP.ValuationToggle="EoP",IF(INDEX(MO_SPT_FXEoP,1,COLUMN())=0,1,INDEX(MO_SPT_FXEoP,1,COLUMN())),IF(INDEX(MO_SPT_FXAverage,1,COLUMN())=0,1,INDEX(MO_SPT_FXAverage,1,COLUMN()))))
A5: Total diluted common stock outstanding - EoP | C5: =INDEX(MO_PDS_ShareCount_EoP,0,COLUMN())+INDEX(MO_PDS_ShareCount_Diluted_SBC_Treasury,0,COLUMN()) | D5: =INDEX(MO_PDS_ShareCount_EoP,0,COLUMN())+INDEX(MO_PDS_ShareCount_Diluted_SBC_Treasury,0,COLUMN()) | E5: =INDEX(MO_PDS_ShareCount_EoP,0,COLUMN())+INDEX(MO_PDS_ShareCount_Diluted_SBC_Treasury,0,COLUMN()) | F5: =INDEX(MO_PDS_ShareCount_EoP,0,COLUMN())+INDEX(MO_PDS_ShareCount_Diluted_SBC_Treasury,0,COLUMN()) | G5: =INDEX(MO_PDS_ShareCount_EoP,0,COLUMN())+INDEX(MO_PDS_ShareCount_Diluted_SBC_Treasury,0,COLUMN()) | H5: =INDEX(MO_PDS_ShareCount_EoP,0,COLUMN())+INDEX(MO_PDS_ShareCount_Diluted_SBC_Treasury,0,COLUMN()) | I5: =INDEX(MO_PDS_ShareCount_EoP,0,COLUMN())+INDEX(MO_PDS_ShareCount_Diluted_SBC_Treasury,0,COLUMN()) | J5: =INDEX(MO_PDS_ShareCount_EoP,0,COLUMN())+INDEX(MO_PDS_ShareCount_Diluted_SBC_Treasury,0,COLUMN()) | ... CA5: =INDEX(MO_PDS_ShareCount_EoP,0,COLUMN())+INDEX(MO_PDS_ShareCount_Diluted_SBC_Treasury,0,COLUMN())
A6: ="Market Cap - "&SP.ValuationToggle | C6: =INDEX(SP_CS_StockPrice,0,COLUMN())*INDEX(SP_CS_ShareCount_EoP_Diluted,0,COLUMN()) | D6: =INDEX(SP_CS_StockPrice,0,COLUMN())*INDEX(SP_CS_ShareCount_EoP_Diluted,0,COLUMN()) | E6: =INDEX(SP_CS_StockPrice,0,COLUMN())*INDEX(SP_CS_ShareCount_EoP_Diluted,0,COLUMN()) | F6: =INDEX(SP_CS_StockPrice,0,COLUMN())*INDEX(SP_CS_ShareCount_EoP_Diluted,0,COLUMN()) | G6: =INDEX(SP_CS_StockPrice,0,COLUMN())*INDEX(SP_CS_ShareCount_EoP_Diluted,0,COLUMN()) | H6: =INDEX(SP_CS_StockPrice,0,COLUMN())*INDEX(SP_CS_ShareCount_EoP_Diluted,0,COLUMN()) | I6: =INDEX(SP_CS_StockPrice,0,COLUMN())*INDEX(SP_CS_ShareCount_EoP_Diluted,0,COLUMN()) | J6: =INDEX(SP_CS_StockPrice,0,COLUMN())*INDEX(SP_CS_ShareCount_EoP_Diluted,0,COLUMN()) | ... CA6: =INDEX(SP_CS_StockPrice,0,COLUMN())*INDEX(SP_CS_ShareCount_EoP_Diluted,0,COLUMN())
A7: =INDEX(MO_BSS_Cash,0,COLUMN()) | C7: =INDEX(MO_BSS_Cash,0,COLUMN()) | D7: =INDEX(MO_BSS_Cash,0,COLUMN()) | E7: =INDEX(MO_BSS_Cash,0,COLUMN()) | F7: =INDEX(MO_BSS_Cash,0,COLUMN()) | G7: =INDEX(MO_BSS_Cash,0,COLUMN()) | H7: =INDEX(MO_BSS_Cash,0,COLUMN()) | I7: =INDEX(MO_BSS_Cash,0,COLUMN()) | J7: =INDEX(MO_BSS_Cash,0,COLUMN()) | ... CA7: =INDEX(MO_BSS_Cash,0,COLUMN())
A8: =INDEX(MO_BSS_Debt,0,COLUMN()) | C8: =INDEX(MO_BSS_Debt,0,COLUMN()) | D8: =INDEX(MO_BSS_Debt,0,COLUMN()) | E8: =INDEX(MO_BSS_Debt,0,COLUMN()) | F8: =INDEX(MO_BSS_Debt,0,COLUMN()) | G8: =INDEX(MO_BSS_Debt,0,COLUMN()) | H8: =INDEX(MO_BSS_Debt,0,COLUMN()) | I8: =INDEX(MO_BSS_Debt,0,COLUMN()) | J8: =INDEX(MO_BSS_Debt,0,COLUMN()) | ... CA8: =INDEX(MO_BSS_Debt,0,COLUMN())
A9: Operating Lease Liabilities | C9: =INDEX(MO_BSS_OL,0,COLUMN()) | D9: =INDEX(MO_BSS_OL,0,COLUMN()) | E9: =INDEX(MO_BSS_OL,0,COLUMN()) | F9: =INDEX(MO_BSS_OL,0,COLUMN()) | G9: =INDEX(MO_BSS_OL,0,COLUMN()) | H9: =INDEX(MO_BSS_OL,0,COLUMN()) | I9: =INDEX(MO_BSS_OL,0,COLUMN()) | J9: =INDEX(MO_BSS_OL,0,COLUMN()) | ... CA9: =INDEX(MO_BSS_OL,0,COLUMN())
A10: Other EV Components | C10: =INDEX(MO_VA_EVCalc_NCI,0,COLUMN())+INDEX(MO_VA_EVCalc_Prefs,0,COLUMN())+INDEX(MO_VA_EVCalc_Other,0,COLUMN()) | D10: =INDEX(MO_VA_EVCalc_NCI,0,COLUMN())+INDEX(MO_VA_EVCalc_Prefs,0,COLUMN())+INDEX(MO_VA_EVCalc_Other,0,COLUMN()) | E10: =INDEX(MO_VA_EVCalc_NCI,0,COLUMN())+INDEX(MO_VA_EVCalc_Prefs,0,COLUMN())+INDEX(MO_VA_EVCalc_Other,0,COLUMN()) | F10: =INDEX(MO_VA_EVCalc_NCI,0,COLUMN())+INDEX(MO_VA_EVCalc_Prefs,0,COLUMN())+INDEX(MO_VA_EVCalc_Other,0,COLUMN()) | G10: =INDEX(MO_VA_EVCalc_NCI,0,COLUMN())+INDEX(MO_VA_EVCalc_Prefs,0,COLUMN())+INDEX(MO_VA_EVCalc_Other,0,COLUMN()) | H10: =INDEX(MO_VA_EVCalc_NCI,0,COLUMN())+INDEX(MO_VA_EVCalc_Prefs,0,COLUMN())+INDEX(MO_VA_EVCalc_Other,0,COLUMN()) | I10: =INDEX(MO_VA_EVCalc_NCI,0,COLUMN())+INDEX(MO_VA_EVCalc_Prefs,0,COLUMN())+INDEX(MO_VA_EVCalc_Other,0,COLUMN()) | J10: =INDEX(MO_VA_EVCalc_NCI,0,COLUMN())+INDEX(MO_VA_EVCalc_Prefs,0,COLUMN())+INDEX(MO_VA_EVCalc_Other,0,COLUMN()) | ... CA10: =INDEX(MO_VA_EVCalc_NCI,0,COLUMN())+INDEX(MO_VA_EVCalc_Prefs,0,COLUMN())+INDEX(MO_VA_EVCalc_Other,0,COLUMN())
A11: ="Enterprise Value - "&SP.ValuationToggle | C11: =INDEX(SP_CS_MarketCap,0,COLUMN())-INDEX(SP_CS_Cash,0,COLUMN())+INDEX(SP_CS_Debt,0,COLUMN())+INDEX(SP_CS_EVCalc_Other,0,COLUMN())+INDEX(SP_CS_OL,0,COLUMN()) | D11: =INDEX(SP_CS_MarketCap,0,COLUMN())-INDEX(SP_CS_Cash,0,COLUMN())+INDEX(SP_CS_Debt,0,COLUMN())+INDEX(SP_CS_EVCalc_Other,0,COLUMN())+INDEX(SP_CS_OL,0,COLUMN()) | E11: =INDEX(SP_CS_MarketCap,0,COLUMN())-INDEX(SP_CS_Cash,0,COLUMN())+INDEX(SP_CS_Debt,0,COLUMN())+INDEX(SP_CS_EVCalc_Other,0,COLUMN())+INDEX(SP_CS_OL,0,COLUMN()) | F11: =INDEX(SP_CS_MarketCap,0,COLUMN())-INDEX(SP_CS_Cash,0,COLUMN())+INDEX(SP_CS_Debt,0,COLUMN())+INDEX(SP_CS_EVCalc_Other,0,COLUMN())+INDEX(SP_CS_OL,0,COLUMN()) | G11: =INDEX(SP_CS_MarketCap,0,COLUMN())-INDEX(SP_CS_Cash,0,COLUMN())+INDEX(SP_CS_Debt,0,COLUMN())+INDEX(SP_CS_EVCalc_Other,0,COLUMN())+INDEX(SP_CS_OL,0,COLUMN()) | H11: =INDEX(SP_CS_MarketCap,0,COLUMN())-INDEX(SP_CS_Cash,0,COLUMN())+INDEX(SP_CS_Debt,0,COLUMN())+INDEX(SP_CS_EVCalc_Other,0,COLUMN())+INDEX(SP_CS_OL,0,COLUMN()) | I11: =INDEX(SP_CS_MarketCap,0,COLUMN())-INDEX(SP_CS_Cash,0,COLUMN())+INDEX(SP_CS_Debt,0,COLUMN())+INDEX(SP_CS_EVCalc_Other,0,COLUMN())+INDEX(SP_CS_OL,0,COLUMN()) | J11: =INDEX(SP_CS_MarketCap,0,COLUMN())-INDEX(SP_CS_Cash,0,COLUMN())+INDEX(SP_CS_Debt,0,COLUMN())+INDEX(SP_CS_EVCalc_Other,0,COLUMN())+INDEX(SP_CS_OL,0,COLUMN()) | ... CA11: =INDEX(SP_CS_MarketCap,0,COLUMN())-INDEX(SP_CS_Cash,0,COLUMN())+INDEX(SP_CS_Debt,0,COLUMN())+INDEX(SP_CS_EVCalc_Other,0,COLUMN())+INDEX(SP_CS_OL,0,COLUMN())
A13: Company-Specific Operational Data
A14: =Model!A8 | D14: =Model!D8 | E14: =Model!E8 | F14: =Model!F8 | G14: =Model!G8 | H14: =Model!H8 | I14: =Model!I8 | J14: =Model!J8 | K14: =Model!K8 | ... CA14: =Model!CA8
A15: =Model!A10 | D15: =Model!D10 | E15: =Model!E10 | F15: =Model!F10 | G15: =Model!G10 | H15: =Model!H10 | I15: =Model!I10 | J15: =Model!J10 | K15: =Model!K10 | ... CA15: =Model!CA10
A16: =Model!A12 | D16: =Model!D12 | E16: =Model!E12 | F16: =Model!F12 | G16: =Model!G12 | H16: =Model!H12 | I16: =Model!I12 | J16: =Model!J12 | K16: =Model!K12 | ... CA16: =Model!CA12
A17: =Model!A14 | D17: =Model!D14 | E17: =Model!E14 | F17: =Model!F14 | G17: =Model!G14 | H17: =Model!H14 | I17: =Model!I14 | J17: =Model!J14 | K17: =Model!K14 | ... CA17: =Model!CA14
A18: =Model!A17 | D18: =Model!D17 | E18: =Model!E17 | F18: =Model!F17 | G18: =Model!G17 | H18: =Model!H17 | I18: =Model!I17 | J18: =Model!J17 | K18: =Model!K17 | ... CA18: =Model!CA17
A19: =Model!A19 | D19: =Model!D19 | E19: =Model!E19 | F19: =Model!F19 | G19: =Model!G19 | H19: =Model!H19 | I19: =Model!I19 | J19: =Model!J19 | K19: =Model!K19 | ... CA19: =Model!CA19
A20: =Model!A22 | D20: =Model!D22 | E20: =Model!E22 | F20: =Model!F22 | G20: =Model!G22 | H20: =Model!H22 | I20: =Model!I22 | J20: =Model!J22 | K20: =Model!K22 | ... CA20: =Model!CA22
A22: GAAP and Non-GAAP Financials
A23: =INDEX(MO_RIS_REV,0,COLUMN()) | C23: =INDEX(MO_RIS_REV,0,COLUMN()) | D23: =INDEX(MO_RIS_REV,0,COLUMN()) | E23: =INDEX(MO_RIS_REV,0,COLUMN()) | F23: =INDEX(MO_RIS_REV,0,COLUMN()) | G23: =INDEX(MO_RIS_REV,0,COLUMN()) | H23: =INDEX(MO_RIS_REV,0,COLUMN()) | I23: =INDEX(MO_RIS_REV,0,COLUMN()) | J23: =INDEX(MO_RIS_REV,0,COLUMN()) | ... CA23: =INDEX(MO_RIS_REV,0,COLUMN())
A24: =INDEX(MO_RIS_COGS,0,COLUMN()) | C24: =INDEX(MO_RIS_COGS,0,COLUMN()) | D24: =INDEX(MO_RIS_COGS,0,COLUMN()) | E24: =INDEX(MO_RIS_COGS,0,COLUMN()) | F24: =INDEX(MO_RIS_COGS,0,COLUMN()) | G24: =INDEX(MO_RIS_COGS,0,COLUMN()) | H24: =INDEX(MO_RIS_COGS,0,COLUMN()) | I24: =INDEX(MO_RIS_COGS,0,COLUMN()) | J24: =INDEX(MO_RIS_COGS,0,COLUMN()) | ... CA24: =INDEX(MO_RIS_COGS,0,COLUMN())
A25: =INDEX(MO_RIS_SBC_COGS,0,COLUMN()) | C25: =INDEX(MO_RIS_SBC_COGS,0,COLUMN()) | D25: =INDEX(MO_RIS_SBC_COGS,0,COLUMN()) | E25: =INDEX(MO_RIS_SBC_COGS,0,COLUMN()) | F25: =INDEX(MO_RIS_SBC_COGS,0,COLUMN()) | G25: =INDEX(MO_RIS_SBC_COGS,0,COLUMN()) | H25: =INDEX(MO_RIS_SBC_COGS,0,COLUMN()) | I25: =INDEX(MO_RIS_SBC_COGS,0,COLUMN()) | J25: =INDEX(MO_RIS_SBC_COGS,0,COLUMN()) | ... CA25: =INDEX(MO_RIS_SBC_COGS,0,COLUMN())
A26: =INDEX(MO_RIS_COGS_Adjustments_Other,0,COLUMN()) | C26: =INDEX(MO_RIS_COGS_Adjustments_Other,0,COLUMN()) | D26: =INDEX(MO_RIS_COGS_Adjustments_Other,0,COLUMN()) | E26: =INDEX(MO_RIS_COGS_Adjustments_Other,0,COLUMN()) | F26: =INDEX(MO_RIS_COGS_Adjustments_Other,0,COLUMN()) | G26: =INDEX(MO_RIS_COGS_Adjustments_Other,0,COLUMN()) | H26: =INDEX(MO_RIS_COGS_Adjustments_Other,0,COLUMN()) | I26: =INDEX(MO_RIS_COGS_Adjustments_Other,0,COLUMN()) | J26: =INDEX(MO_RIS_COGS_Adjustments_Other,0,COLUMN()) | ... CA26: =INDEX(MO_RIS_COGS_Adjustments_Other,0,COLUMN())
A27: =INDEX(MO_RIS_DAintangibles_COGS,0,COLUMN()) | C27: =INDEX(MO_RIS_DAintangibles_COGS,0,COLUMN()) | D27: =INDEX(MO_RIS_DAintangibles_COGS,0,COLUMN()) | E27: =INDEX(MO_RIS_DAintangibles_COGS,0,COLUMN()) | F27: =INDEX(MO_RIS_DAintangibles_COGS,0,COLUMN()) | G27: =INDEX(MO_RIS_DAintangibles_COGS,0,COLUMN()) | H27: =INDEX(MO_RIS_DAintangibles_COGS,0,COLUMN()) | I27: =INDEX(MO_RIS_DAintangibles_COGS,0,COLUMN()) | J27: =INDEX(MO_RIS_DAintangibles_COGS,0,COLUMN()) | ... CA27: =INDEX(MO_RIS_DAintangibles_COGS,0,COLUMN())
A28: =INDEX(MO_RIS_RD_NONGAAP,0,COLUMN()) | C28: =INDEX(MO_RIS_RD_NONGAAP,0,COLUMN()) | D28: =INDEX(MO_RIS_RD_NONGAAP,0,COLUMN()) | E28: =INDEX(MO_RIS_RD_NONGAAP,0,COLUMN()) | F28: =INDEX(MO_RIS_RD_NONGAAP,0,COLUMN()) | G28: =INDEX(MO_RIS_RD_NONGAAP,0,COLUMN()) | H28: =INDEX(MO_RIS_RD_NONGAAP,0,COLUMN()) | I28: =INDEX(MO_RIS_RD_NONGAAP,0,COLUMN()) | J28: =INDEX(MO_RIS_RD_NONGAAP,0,COLUMN()) | ... CA28: =INDEX(MO_RIS_RD_NONGAAP,0,COLUMN())
A29: =INDEX(MO_RIS_GA_NONGAAP,0,COLUMN()) | C29: =INDEX(MO_RIS_GA_NONGAAP,0,COLUMN()) | D29: =INDEX(MO_RIS_GA_NONGAAP,0,COLUMN()) | E29: =INDEX(MO_RIS_GA_NONGAAP,0,COLUMN()) | F29: =INDEX(MO_RIS_GA_NONGAAP,0,COLUMN()) | G29: =INDEX(MO_RIS_GA_NONGAAP,0,COLUMN()) | H29: =INDEX(MO_RIS_GA_NONGAAP,0,COLUMN()) | I29: =INDEX(MO_RIS_GA_NONGAAP,0,COLUMN()) | J29: =INDEX(MO_RIS_GA_NONGAAP,0,COLUMN()) | ... CA29: =INDEX(MO_RIS_GA_NONGAAP,0,COLUMN())
A30: =INDEX(MO_RIS_SM_NONGAAP,0,COLUMN()) | C30: =INDEX(MO_RIS_SM_NONGAAP,0,COLUMN()) | D30: =INDEX(MO_RIS_SM_NONGAAP,0,COLUMN()) | E30: =INDEX(MO_RIS_SM_NONGAAP,0,COLUMN()) | F30: =INDEX(MO_RIS_SM_NONGAAP,0,COLUMN()) | G30: =INDEX(MO_RIS_SM_NONGAAP,0,COLUMN()) | H30: =INDEX(MO_RIS_SM_NONGAAP,0,COLUMN()) | I30: =INDEX(MO_RIS_SM_NONGAAP,0,COLUMN()) | J30: =INDEX(MO_RIS_SM_NONGAAP,0,COLUMN()) | ... CA30: =INDEX(MO_RIS_SM_NONGAAP,0,COLUMN())
A31: =INDEX(MO_RIS_OtherOperating_NONGAAP,0,COLUMN()) | C31: =INDEX(MO_RIS_OtherOperating_NONGAAP,0,COLUMN()) | D31: =INDEX(MO_RIS_OtherOperating_NONGAAP,0,COLUMN()) | E31: =INDEX(MO_RIS_OtherOperating_NONGAAP,0,COLUMN()) | F31: =INDEX(MO_RIS_OtherOperating_NONGAAP,0,COLUMN()) | G31: =INDEX(MO_RIS_OtherOperating_NONGAAP,0,COLUMN()) | H31: =INDEX(MO_RIS_OtherOperating_NONGAAP,0,COLUMN()) | I31: =INDEX(MO_RIS_OtherOperating_NONGAAP,0,COLUMN()) | J31: =INDEX(MO_RIS_OtherOperating_NONGAAP,0,COLUMN()) | ... CA31: =INDEX(MO_RIS_OtherOperating_NONGAAP,0,COLUMN())
A32: =INDEX(MO_RIS_Reported_OperatingIncome_NONGAAP,0,COLUMN()) | C32: =INDEX(MO_RIS_Reported_OperatingIncome_NONGAAP,0,COLUMN()) | D32: =INDEX(MO_RIS_Reported_OperatingIncome_NONGAAP,0,COLUMN()) | E32: =INDEX(MO_RIS_Reported_OperatingIncome_NONGAAP,0,COLUMN()) | F32: =INDEX(MO_RIS_Reported_OperatingIncome_NONGAAP,0,COLUMN()) | G32: =INDEX(MO_RIS_Reported_OperatingIncome_NONGAAP,0,COLUMN()) | H32: =INDEX(MO_RIS_Reported_OperatingIncome_NONGAAP,0,COLUMN()) | I32: =INDEX(MO_RIS_Reported_OperatingIncome_NONGAAP,0,COLUMN()) | J32: =INDEX(MO_RIS_Reported_OperatingIncome_NONGAAP,0,COLUMN()) | ... CA32: =INDEX(MO_RIS_Reported_OperatingIncome_NONGAAP,0,COLUMN())
A33: =INDEX(MO_RIS_IE_Net_NONGAAP,0,COLUMN()) | C33: =INDEX(MO_RIS_IE_Net_NONGAAP,0,COLUMN()) | D33: =INDEX(MO_RIS_IE_Net_NONGAAP,0,COLUMN()) | E33: =INDEX(MO_RIS_IE_Net_NONGAAP,0,COLUMN()) | F33: =INDEX(MO_RIS_IE_Net_NONGAAP,0,COLUMN()) | G33: =INDEX(MO_RIS_IE_Net_NONGAAP,0,COLUMN()) | H33: =INDEX(MO_RIS_IE_Net_NONGAAP,0,COLUMN()) | I33: =INDEX(MO_RIS_IE_Net_NONGAAP,0,COLUMN()) | J33: =INDEX(MO_RIS_IE_Net_NONGAAP,0,COLUMN()) | ... CA33: =INDEX(MO_RIS_IE_Net_NONGAAP,0,COLUMN())
A34: =INDEX(MO_RIS_OI_NONGAAP,0,COLUMN()) | C34: =INDEX(MO_RIS_OI_NONGAAP,0,COLUMN()) | D34: =INDEX(MO_RIS_OI_NONGAAP,0,COLUMN()) | E34: =INDEX(MO_RIS_OI_NONGAAP,0,COLUMN()) | F34: =INDEX(MO_RIS_OI_NONGAAP,0,COLUMN()) | G34: =INDEX(MO_RIS_OI_NONGAAP,0,COLUMN()) | H34: =INDEX(MO_RIS_OI_NONGAAP,0,COLUMN()) | I34: =INDEX(MO_RIS_OI_NONGAAP,0,COLUMN()) | J34: =INDEX(MO_RIS_OI_NONGAAP,0,COLUMN()) | ... CA34: =INDEX(MO_RIS_OI_NONGAAP,0,COLUMN())
A35: =INDEX(MO_RIS_EBT_NONGAAP,0,COLUMN()) | C35: =INDEX(MO_RIS_EBT_NONGAAP,0,COLUMN()) | D35: =INDEX(MO_RIS_EBT_NONGAAP,0,COLUMN()) | E35: =INDEX(MO_RIS_EBT_NONGAAP,0,COLUMN()) | F35: =INDEX(MO_RIS_EBT_NONGAAP,0,COLUMN()) | G35: =INDEX(MO_RIS_EBT_NONGAAP,0,COLUMN()) | H35: =INDEX(MO_RIS_EBT_NONGAAP,0,COLUMN()) | I35: =INDEX(MO_RIS_EBT_NONGAAP,0,COLUMN()) | J35: =INDEX(MO_RIS_EBT_NONGAAP,0,COLUMN()) | ... CA35: =INDEX(MO_RIS_EBT_NONGAAP,0,COLUMN())
A36: =INDEX(MO_RIS_Tax_NONGAAP,0,COLUMN()) | C36: =INDEX(MO_RIS_Tax_NONGAAP,0,COLUMN()) | D36: =INDEX(MO_RIS_Tax_NONGAAP,0,COLUMN()) | E36: =INDEX(MO_RIS_Tax_NONGAAP,0,COLUMN()) | F36: =INDEX(MO_RIS_Tax_NONGAAP,0,COLUMN()) | G36: =INDEX(MO_RIS_Tax_NONGAAP,0,COLUMN()) | H36: =INDEX(MO_RIS_Tax_NONGAAP,0,COLUMN()) | I36: =INDEX(MO_RIS_Tax_NONGAAP,0,COLUMN()) | J36: =INDEX(MO_RIS_Tax_NONGAAP,0,COLUMN()) | ... CA36: =INDEX(MO_RIS_Tax_NONGAAP,0,COLUMN())
A37: =INDEX(MO_RIS_NI_NONGAAP_Diluted,0,COLUMN()) | C37: =INDEX(MO_RIS_NI_NONGAAP_Diluted,0,COLUMN()) | D37: =INDEX(MO_RIS_NI_NONGAAP_Diluted,0,COLUMN()) | E37: =INDEX(MO_RIS_NI_NONGAAP_Diluted,0,COLUMN()) | F37: =INDEX(MO_RIS_NI_NONGAAP_Diluted,0,COLUMN()) | G37: =INDEX(MO_RIS_NI_NONGAAP_Diluted,0,COLUMN()) | H37: =INDEX(MO_RIS_NI_NONGAAP_Diluted,0,COLUMN()) | I37: =INDEX(MO_RIS_NI_NONGAAP_Diluted,0,COLUMN()) | J37: =INDEX(MO_RIS_NI_NONGAAP_Diluted,0,COLUMN()) | ... CA37: =INDEX(MO_RIS_NI_NONGAAP_Diluted,0,COLUMN())
A38: GAAP Adjustments | C38: =INDEX(MO_RIS_NI_NONGAAP_Diluted,0,COLUMN())-INDEX(MO_RIS_NI_GAAP_Basic,0,COLUMN()) | D38: =INDEX(MO_RIS_NI_NONGAAP_Diluted,0,COLUMN())-INDEX(MO_RIS_NI_GAAP_Basic,0,COLUMN()) | E38: =INDEX(MO_RIS_NI_NONGAAP_Diluted,0,COLUMN())-INDEX(MO_RIS_NI_GAAP_Basic,0,COLUMN()) | F38: =INDEX(MO_RIS_NI_NONGAAP_Diluted,0,COLUMN())-INDEX(MO_RIS_NI_GAAP_Basic,0,COLUMN()) | G38: =INDEX(MO_RIS_NI_NONGAAP_Diluted,0,COLUMN())-INDEX(MO_RIS_NI_GAAP_Basic,0,COLUMN()) | H38: =INDEX(MO_RIS_NI_NONGAAP_Diluted,0,COLUMN())-INDEX(MO_RIS_NI_GAAP_Basic,0,COLUMN()) | I38: =INDEX(MO_RIS_NI_NONGAAP_Diluted,0,COLUMN())-INDEX(MO_RIS_NI_GAAP_Basic,0,COLUMN()) | J38: =INDEX(MO_RIS_NI_NONGAAP_Diluted,0,COLUMN())-INDEX(MO_RIS_NI_GAAP_Basic,0,COLUMN()) | ... CA38: =INDEX(MO_RIS_NI_NONGAAP_Diluted,0,COLUMN())-INDEX(MO_RIS_NI_GAAP_Basic,0,COLUMN())
A39: =INDEX(MO_RIS_NI_GAAP_Basic,0,COLUMN()) | C39: =INDEX(MO_RIS_NI_GAAP_Basic,0,COLUMN()) | D39: =INDEX(MO_RIS_NI_GAAP_Basic,0,COLUMN()) | E39: =INDEX(MO_RIS_NI_GAAP_Basic,0,COLUMN()) | F39: =INDEX(MO_RIS_NI_GAAP_Basic,0,COLUMN()) | G39: =INDEX(MO_RIS_NI_GAAP_Basic,0,COLUMN()) | H39: =INDEX(MO_RIS_NI_GAAP_Basic,0,COLUMN()) | I39: =INDEX(MO_RIS_NI_GAAP_Basic,0,COLUMN()) | J39: =INDEX(MO_RIS_NI_GAAP_Basic,0,COLUMN()) | ... CA39: =INDEX(MO_RIS_NI_GAAP_Basic,0,COLUMN())
A41: =INDEX(MO_RIS_EPS_WAD,0,COLUMN()) | C41: =INDEX(MO_RIS_EPS_WAD,0,COLUMN()) | D41: =INDEX(MO_RIS_EPS_WAD,0,COLUMN()) | E41: =INDEX(MO_RIS_EPS_WAD,0,COLUMN()) | F41: =INDEX(MO_RIS_EPS_WAD,0,COLUMN()) | G41: =INDEX(MO_RIS_EPS_WAD,0,COLUMN()) | H41: =INDEX(MO_RIS_EPS_WAD,0,COLUMN()) | I41: =INDEX(MO_RIS_EPS_WAD,0,COLUMN()) | J41: =INDEX(MO_RIS_EPS_WAD,0,COLUMN()) | ... CA41: =INDEX(MO_RIS_EPS_WAD,0,COLUMN())
A42: =INDEX(MO_RIS_ShareCount_WAD_Adj,0,COLUMN()) | C42: =INDEX(MO_RIS_ShareCount_WAD_Adj,0,COLUMN()) | D42: =INDEX(MO_RIS_ShareCount_WAD_Adj,0,COLUMN()) | E42: =INDEX(MO_RIS_ShareCount_WAD_Adj,0,COLUMN()) | F42: =INDEX(MO_RIS_ShareCount_WAD_Adj,0,COLUMN()) | G42: =INDEX(MO_RIS_ShareCount_WAD_Adj,0,COLUMN()) | H42: =INDEX(MO_RIS_ShareCount_WAD_Adj,0,COLUMN()) | I42: =INDEX(MO_RIS_ShareCount_WAD_Adj,0,COLUMN()) | J42: =INDEX(MO_RIS_ShareCount_WAD_Adj,0,COLUMN()) | ... CA42: =INDEX(MO_RIS_ShareCount_WAD_Adj,0,COLUMN())
A44: Non-GAAP Financials
A45: =INDEX(MO_RIS_EBITDA_Adj,0,COLUMN()) | C45: =INDEX(MO_RIS_EBITDA_Adj,0,COLUMN()) | D45: =INDEX(MO_RIS_EBITDA_Adj,0,COLUMN()) | E45: =INDEX(MO_RIS_EBITDA_Adj,0,COLUMN()) | F45: =INDEX(MO_RIS_EBITDA_Adj,0,COLUMN()) | G45: =INDEX(MO_RIS_EBITDA_Adj,0,COLUMN()) | H45: =INDEX(MO_RIS_EBITDA_Adj,0,COLUMN()) | I45: =INDEX(MO_RIS_EBITDA_Adj,0,COLUMN()) | J45: =INDEX(MO_RIS_EBITDA_Adj,0,COLUMN()) | ... CA45: =INDEX(MO_RIS_EBITDA_Adj,0,COLUMN())
A46: =INDEX(MO_RIS_NI_NONGAAP_Diluted,0,COLUMN()) | C46: =INDEX(MO_RIS_NI_NONGAAP_Diluted,0,COLUMN()) | D46: =INDEX(MO_RIS_NI_NONGAAP_Diluted,0,COLUMN()) | E46: =INDEX(MO_RIS_NI_NONGAAP_Diluted,0,COLUMN()) | F46: =INDEX(MO_RIS_NI_NONGAAP_Diluted,0,COLUMN()) | G46: =INDEX(MO_RIS_NI_NONGAAP_Diluted,0,COLUMN()) | H46: =INDEX(MO_RIS_NI_NONGAAP_Diluted,0,COLUMN()) | I46: =INDEX(MO_RIS_NI_NONGAAP_Diluted,0,COLUMN()) | J46: =INDEX(MO_RIS_NI_NONGAAP_Diluted,0,COLUMN()) | ... CA46: =INDEX(MO_RIS_NI_NONGAAP_Diluted,0,COLUMN())
A47: =INDEX(MO_RIS_EPS_WAD_Adj,0,COLUMN()) | C47: =INDEX(MO_RIS_EPS_WAD_Adj,0,COLUMN()) | D47: =INDEX(MO_RIS_EPS_WAD_Adj,0,COLUMN()) | E47: =INDEX(MO_RIS_EPS_WAD_Adj,0,COLUMN()) | F47: =INDEX(MO_RIS_EPS_WAD_Adj,0,COLUMN()) | G47: =INDEX(MO_RIS_EPS_WAD_Adj,0,COLUMN()) | H47: =INDEX(MO_RIS_EPS_WAD_Adj,0,COLUMN()) | I47: =INDEX(MO_RIS_EPS_WAD_Adj,0,COLUMN()) | J47: =INDEX(MO_RIS_EPS_WAD_Adj,0,COLUMN()) | ... CA47: =INDEX(MO_RIS_EPS_WAD_Adj,0,COLUMN())
A49: Margin Analysis
A50: =INDEX(MO_MA_COGS_NONGAAP,0,COLUMN()) | C50: =INDEX(MO_MA_COGS_NONGAAP,0,COLUMN()) | D50: =INDEX(MO_MA_COGS_NONGAAP,0,COLUMN()) | E50: =INDEX(MO_MA_COGS_NONGAAP,0,COLUMN()) | F50: =INDEX(MO_MA_COGS_NONGAAP,0,COLUMN()) | G50: =INDEX(MO_MA_COGS_NONGAAP,0,COLUMN()) | H50: =INDEX(MO_MA_COGS_NONGAAP,0,COLUMN()) | I50: =INDEX(MO_MA_COGS_NONGAAP,0,COLUMN()) | J50: =INDEX(MO_MA_COGS_NONGAAP,0,COLUMN()) | ... CA50: =INDEX(MO_MA_COGS_NONGAAP,0,COLUMN())
A51: =INDEX(MO_MA_RD_NONGAAP,0,COLUMN()) | C51: =INDEX(MO_MA_RD_NONGAAP,0,COLUMN()) | D51: =INDEX(MO_MA_RD_NONGAAP,0,COLUMN()) | E51: =INDEX(MO_MA_RD_NONGAAP,0,COLUMN()) | F51: =INDEX(MO_MA_RD_NONGAAP,0,COLUMN()) | G51: =INDEX(MO_MA_RD_NONGAAP,0,COLUMN()) | H51: =INDEX(MO_MA_RD_NONGAAP,0,COLUMN()) | I51: =INDEX(MO_MA_RD_NONGAAP,0,COLUMN()) | J51: =INDEX(MO_MA_RD_NONGAAP,0,COLUMN()) | ... CA51: =INDEX(MO_MA_RD_NONGAAP,0,COLUMN())
A52: =INDEX(MO_MA_GA_NONGAAP,0,COLUMN()) | C52: =INDEX(MO_MA_GA_NONGAAP,0,COLUMN()) | D52: =INDEX(MO_MA_GA_NONGAAP,0,COLUMN()) | E52: =INDEX(MO_MA_GA_NONGAAP,0,COLUMN()) | F52: =INDEX(MO_MA_GA_NONGAAP,0,COLUMN()) | G52: =INDEX(MO_MA_GA_NONGAAP,0,COLUMN()) | H52: =INDEX(MO_MA_GA_NONGAAP,0,COLUMN()) | I52: =INDEX(MO_MA_GA_NONGAAP,0,COLUMN()) | J52: =INDEX(MO_MA_GA_NONGAAP,0,COLUMN()) | ... CA52: =INDEX(MO_MA_GA_NONGAAP,0,COLUMN())
A53: =INDEX(MO_MA_SM_NONGAAP,0,COLUMN()) | C53: =INDEX(MO_MA_SM_NONGAAP,0,COLUMN()) | D53: =INDEX(MO_MA_SM_NONGAAP,0,COLUMN()) | E53: =INDEX(MO_MA_SM_NONGAAP,0,COLUMN()) | F53: =INDEX(MO_MA_SM_NONGAAP,0,COLUMN()) | G53: =INDEX(MO_MA_SM_NONGAAP,0,COLUMN()) | H53: =INDEX(MO_MA_SM_NONGAAP,0,COLUMN()) | I53: =INDEX(MO_MA_SM_NONGAAP,0,COLUMN()) | J53: =INDEX(MO_MA_SM_NONGAAP,0,COLUMN()) | ... CA53: =INDEX(MO_MA_SM_NONGAAP,0,COLUMN())
A54: =INDEX(MO_MA_OperatingIncome_NONGAAP,0,COLUMN()) | C54: =INDEX(MO_MA_OperatingIncome_NONGAAP,0,COLUMN()) | D54: =INDEX(MO_MA_OperatingIncome_NONGAAP,0,COLUMN()) | E54: =INDEX(MO_MA_OperatingIncome_NONGAAP,0,COLUMN()) | F54: =INDEX(MO_MA_OperatingIncome_NONGAAP,0,COLUMN()) | G54: =INDEX(MO_MA_OperatingIncome_NONGAAP,0,COLUMN()) | H54: =INDEX(MO_MA_OperatingIncome_NONGAAP,0,COLUMN()) | I54: =INDEX(MO_MA_OperatingIncome_NONGAAP,0,COLUMN()) | J54: =INDEX(MO_MA_OperatingIncome_NONGAAP,0,COLUMN()) | ... CA54: =INDEX(MO_MA_OperatingIncome_NONGAAP,0,COLUMN())
A55: =INDEX(MO_MA_OperatingIncome,0,COLUMN()) | C55: =INDEX(MO_MA_OperatingIncome,0,COLUMN()) | D55: =INDEX(MO_MA_OperatingIncome,0,COLUMN()) | E55: =INDEX(MO_MA_OperatingIncome,0,COLUMN()) | F55: =INDEX(MO_MA_OperatingIncome,0,COLUMN()) | G55: =INDEX(MO_MA_OperatingIncome,0,COLUMN()) | H55: =INDEX(MO_MA_OperatingIncome,0,COLUMN()) | I55: =INDEX(MO_MA_OperatingIncome,0,COLUMN()) | J55: =INDEX(MO_MA_OperatingIncome,0,COLUMN()) | ... CA55: =INDEX(MO_MA_OperatingIncome,0,COLUMN())
A57: Cash Flow Analysis
A58: =INDEX(MO_CFSum_CFO_BeforeWC,0,COLUMN()) | C58: =INDEX(MO_CFSum_CFO_BeforeWC,0,COLUMN()) | D58: =INDEX(MO_CFSum_CFO_BeforeWC,0,COLUMN()) | E58: =INDEX(MO_CFSum_CFO_BeforeWC,0,COLUMN()) | F58: =INDEX(MO_CFSum_CFO_BeforeWC,0,COLUMN()) | G58: =INDEX(MO_CFSum_CFO_BeforeWC,0,COLUMN()) | H58: =INDEX(MO_CFSum_CFO_BeforeWC,0,COLUMN()) | I58: =INDEX(MO_CFSum_CFO_BeforeWC,0,COLUMN()) | J58: =INDEX(MO_CFSum_CFO_BeforeWC,0,COLUMN()) | ... CA58: =INDEX(MO_CFSum_CFO_BeforeWC,0,COLUMN())
A59: Change in WC | C59: =SUM(OFFSET(INDEX(MO_CFS_CFO_BeforeWC,0,COLUMN()),1,0,ROW(INDEX(MO_CFS_CFO,0,COLUMN()))-ROW(INDEX(MO_CFS_CFO_BeforeWC,0,COLUMN()))-1,1)) | D59: =SUM(OFFSET(INDEX(MO_CFS_CFO_BeforeWC,0,COLUMN()),1,0,ROW(INDEX(MO_CFS_CFO,0,COLUMN()))-ROW(INDEX(MO_CFS_CFO_BeforeWC,0,COLUMN()))-1,1)) | E59: =SUM(OFFSET(INDEX(MO_CFS_CFO_BeforeWC,0,COLUMN()),1,0,ROW(INDEX(MO_CFS_CFO,0,COLUMN()))-ROW(INDEX(MO_CFS_CFO_BeforeWC,0,COLUMN()))-1,1)) | F59: =SUM(OFFSET(INDEX(MO_CFS_CFO_BeforeWC,0,COLUMN()),1,0,ROW(INDEX(MO_CFS_CFO,0,COLUMN()))-ROW(INDEX(MO_CFS_CFO_BeforeWC,0,COLUMN()))-1,1)) | G59: =SUM(OFFSET(INDEX(MO_CFS_CFO_BeforeWC,0,COLUMN()),1,0,ROW(INDEX(MO_CFS_CFO,0,COLUMN()))-ROW(INDEX(MO_CFS_CFO_BeforeWC,0,COLUMN()))-1,1)) | H59: =SUM(OFFSET(INDEX(MO_CFS_CFO_BeforeWC,0,COLUMN()),1,0,ROW(INDEX(MO_CFS_CFO,0,COLUMN()))-ROW(INDEX(MO_CFS_CFO_BeforeWC,0,COLUMN()))-1,1)) | I59: =SUM(OFFSET(INDEX(MO_CFS_CFO_BeforeWC,0,COLUMN()),1,0,ROW(INDEX(MO_CFS_CFO,0,COLUMN()))-ROW(INDEX(MO_CFS_CFO_BeforeWC,0,COLUMN()))-1,1)) | J59: =SUM(OFFSET(INDEX(MO_CFS_CFO_BeforeWC,0,COLUMN()),1,0,ROW(INDEX(MO_CFS_CFO,0,COLUMN()))-ROW(INDEX(MO_CFS_CFO_BeforeWC,0,COLUMN()))-1,1)) | ... CA59: =SUM(OFFSET(INDEX(MO_CFS_CFO_BeforeWC,0,COLUMN()),1,0,ROW(INDEX(MO_CFS_CFO,0,COLUMN()))-ROW(INDEX(MO_CFS_CFO_BeforeWC,0,COLUMN()))-1,1))
A60: Operating Cash Flow after WC | C60: =SUM(C58:C59) | D60: =SUM(D58:D59) | E60: =SUM(E58:E59) | F60: =SUM(F58:F59) | G60: =SUM(G58:G59) | H60: =SUM(H58:H59) | I60: =SUM(I58:I59) | J60: =SUM(J58:J59) | ... CA60: =SUM(CA58:CA59)
A61: =INDEX(MO_CFSum_Capex,0,COLUMN()) | C61: =INDEX(MO_CFSum_Capex,0,COLUMN()) | D61: =INDEX(MO_CFSum_Capex,0,COLUMN()) | E61: =INDEX(MO_CFSum_Capex,0,COLUMN()) | F61: =INDEX(MO_CFSum_Capex,0,COLUMN()) | G61: =INDEX(MO_CFSum_Capex,0,COLUMN()) | H61: =INDEX(MO_CFSum_Capex,0,COLUMN()) | I61: =INDEX(MO_CFSum_Capex,0,COLUMN()) | J61: =INDEX(MO_CFSum_Capex,0,COLUMN()) | ... CA61: =INDEX(MO_CFSum_Capex,0,COLUMN())
A62: Core FCF, Pre Div | C62: =SUM(C60:C61) | D62: =SUM(D60:D61) | E62: =SUM(E60:E61) | F62: =SUM(F60:F61) | G62: =SUM(G60:G61) | H62: =SUM(H60:H61) | I62: =SUM(I60:I61) | J62: =SUM(J60:J61) | ... CA62: =SUM(CA60:CA61)
A63: =INDEX(MO_CFSum_Dividend,0,COLUMN()) | C63: =INDEX(MO_CFSum_Dividend,0,COLUMN()) | D63: =INDEX(MO_CFSum_Dividend,0,COLUMN()) | E63: =INDEX(MO_CFSum_Dividend,0,COLUMN()) | F63: =INDEX(MO_CFSum_Dividend,0,COLUMN()) | G63: =INDEX(MO_CFSum_Dividend,0,COLUMN()) | H63: =INDEX(MO_CFSum_Dividend,0,COLUMN()) | I63: =INDEX(MO_CFSum_Dividend,0,COLUMN()) | J63: =INDEX(MO_CFSum_Dividend,0,COLUMN()) | ... CA63: =INDEX(MO_CFSum_Dividend,0,COLUMN())
A64: Core FCF, Post Div | C64: =SUM(C62:C63) | D64: =SUM(D62:D63) | E64: =SUM(E62:E63) | F64: =SUM(F62:F63) | G64: =SUM(G62:G63) | H64: =SUM(H62:H63) | I64: =SUM(I62:I63) | J64: =SUM(J62:J63) | ... CA64: =SUM(CA62:CA63)
A65: =INDEX(MO_CFSum_Acquisition,0,COLUMN()) | C65: =INDEX(MO_CFSum_Acquisition,0,COLUMN()) | D65: =INDEX(MO_CFSum_Acquisition,0,COLUMN()) | E65: =INDEX(MO_CFSum_Acquisition,0,COLUMN()) | F65: =INDEX(MO_CFSum_Acquisition,0,COLUMN()) | G65: =INDEX(MO_CFSum_Acquisition,0,COLUMN()) | H65: =INDEX(MO_CFSum_Acquisition,0,COLUMN()) | I65: =INDEX(MO_CFSum_Acquisition,0,COLUMN()) | J65: =INDEX(MO_CFSum_Acquisition,0,COLUMN()) | ... CA65: =INDEX(MO_CFSum_Acquisition,0,COLUMN())
A66: =INDEX(MO_CFSum_Divestiture,0,COLUMN()) | C66: =INDEX(MO_CFSum_Divestiture,0,COLUMN()) | D66: =INDEX(MO_CFSum_Divestiture,0,COLUMN()) | E66: =INDEX(MO_CFSum_Divestiture,0,COLUMN()) | F66: =INDEX(MO_CFSum_Divestiture,0,COLUMN()) | G66: =INDEX(MO_CFSum_Divestiture,0,COLUMN()) | H66: =INDEX(MO_CFSum_Divestiture,0,COLUMN()) | I66: =INDEX(MO_CFSum_Divestiture,0,COLUMN()) | J66: =INDEX(MO_CFSum_Divestiture,0,COLUMN()) | ... CA66: =INDEX(MO_CFSum_Divestiture,0,COLUMN())
A67: New Equity Issuance | C67: =INDEX(MO_CFSum_NetShares,0,COLUMN()) | D67: =INDEX(MO_CFSum_NetShares,0,COLUMN()) | E67: =INDEX(MO_CFSum_NetShares,0,COLUMN()) | F67: =INDEX(MO_CFSum_NetShares,0,COLUMN()) | G67: =INDEX(MO_CFSum_NetShares,0,COLUMN()) | H67: =INDEX(MO_CFSum_NetShares,0,COLUMN()) | I67: =INDEX(MO_CFSum_NetShares,0,COLUMN()) | J67: =INDEX(MO_CFSum_NetShares,0,COLUMN()) | ... CA67: =INDEX(MO_CFSum_NetShares,0,COLUMN())
A68: New Debt Issuance | C68: =INDEX(MO_CFSum_NetDebtIssuance,0,COLUMN()) | D68: =INDEX(MO_CFSum_NetDebtIssuance,0,COLUMN()) | E68: =INDEX(MO_CFSum_NetDebtIssuance,0,COLUMN()) | F68: =INDEX(MO_CFSum_NetDebtIssuance,0,COLUMN()) | G68: =INDEX(MO_CFSum_NetDebtIssuance,0,COLUMN()) | H68: =INDEX(MO_CFSum_NetDebtIssuance,0,COLUMN()) | I68: =INDEX(MO_CFSum_NetDebtIssuance,0,COLUMN()) | J68: =INDEX(MO_CFSum_NetDebtIssuance,0,COLUMN()) | ... CA68: =INDEX(MO_CFSum_NetDebtIssuance,0,COLUMN())
A69: Other Items | C69: =Model!C1138+Model!C1139+Model!C1140+Model!C1147+Model!C1113+Model!C1114+Model!C1115+Model!C1116+Model!C1117+Model!C1125+Model!C1151+Model!C1143+Model!C1142+Model!C1119+Model!C1120 | D69: =Model!D1138+Model!D1139+Model!D1140+Model!D1147+Model!D1113+Model!D1114+Model!D1115+Model!D1116+Model!D1117+Model!D1125+Model!D1151+Model!D1143+Model!D1142+Model!D1119+Model!D1120 | E69: =Model!E1138+Model!E1139+Model!E1140+Model!E1147+Model!E1113+Model!E1114+Model!E1115+Model!E1116+Model!E1117+Model!E1125+Model!E1151+Model!E1143+Model!E1142+Model!E1119+Model!E1120 | F69: =Model!F1138+Model!F1139+Model!F1140+Model!F1147+Model!F1113+Model!F1114+Model!F1115+Model!F1116+Model!F1117+Model!F1125+Model!F1151+Model!F1143+Model!F1142+Model!F1119+Model!F1120 | G69: =Model!G1138+Model!G1139+Model!G1140+Model!G1147+Model!G1113+Model!G1114+Model!G1115+Model!G1116+Model!G1117+Model!G1125+Model!G1151+Model!G1143+Model!G1142+Model!G1119+Model!G1120 | H69: =Model!H1138+Model!H1139+Model!H1140+Model!H1147+Model!H1113+Model!H1114+Model!H1115+Model!H1116+Model!H1117+Model!H1125+Model!H1151+Model!H1143+Model!H1142+Model!H1119+Model!H1120 | I69: =Model!I1138+Model!I1139+Model!I1140+Model!I1147+Model!I1113+Model!I1114+Model!I1115+Model!I1116+Model!I1117+Model!I1125+Model!I1151+Model!I1143+Model!I1142+Model!I1119+Model!I1120 | J69: =Model!J1138+Model!J1139+Model!J1140+Model!J1147+Model!J1113+Model!J1114+Model!J1115+Model!J1116+Model!J1117+Model!J1125+Model!J1151+Model!J1143+Model!J1142+Model!J1119+Model!J1120 | ... CA69: =Model!CA1138+Model!CA1139+Model!CA1140+Model!CA1147+Model!CA1113+Model!CA1114+Model!CA1115+Model!CA1116+Model!CA1117+Model!CA1125+Model!CA1151+Model!CA1143+Model!CA1142+Model!CA1119+Model!CA1120
A70: Change in Cash Position | C70: =SUM(C64:C69) | D70: =SUM(D64:D69) | E70: =SUM(E64:E69) | F70: =SUM(F64:F69) | G70: =SUM(G64:G69) | H70: =SUM(H64:H69) | I70: =SUM(I64:I69) | J70: =SUM(J64:J69) | ... CA70: =SUM(CA64:CA69)
A72: Operating Cash Flow Per Share | C72: =INDEX(SP_CFA_CFO,0,COLUMN())/INDEX(SP_GF_ShareCount,0,COLUMN()) | D72: =INDEX(SP_CFA_CFO,0,COLUMN())/INDEX(SP_GF_ShareCount,0,COLUMN()) | E72: =INDEX(SP_CFA_CFO,0,COLUMN())/INDEX(SP_GF_ShareCount,0,COLUMN()) | F72: =INDEX(SP_CFA_CFO,0,COLUMN())/INDEX(SP_GF_ShareCount,0,COLUMN()) | G72: =INDEX(SP_CFA_CFO,0,COLUMN())/INDEX(SP_GF_ShareCount,0,COLUMN()) | H72: =INDEX(SP_CFA_CFO,0,COLUMN())/INDEX(SP_GF_ShareCount,0,COLUMN()) | I72: =INDEX(SP_CFA_CFO,0,COLUMN())/INDEX(SP_GF_ShareCount,0,COLUMN()) | J72: =INDEX(SP_CFA_CFO,0,COLUMN())/INDEX(SP_GF_ShareCount,0,COLUMN()) | ... CA72: =INDEX(SP_CFA_CFO,0,COLUMN())/INDEX(SP_GF_ShareCount,0,COLUMN())
A73: Core Free Cash Flow Per Share, Pre Div | C73: =INDEX(SP_CFA_FCF_PreDiv,0,COLUMN())/INDEX(SP_GF_ShareCount,0,COLUMN()) | D73: =INDEX(SP_CFA_FCF_PreDiv,0,COLUMN())/INDEX(SP_GF_ShareCount,0,COLUMN()) | E73: =INDEX(SP_CFA_FCF_PreDiv,0,COLUMN())/INDEX(SP_GF_ShareCount,0,COLUMN()) | F73: =INDEX(SP_CFA_FCF_PreDiv,0,COLUMN())/INDEX(SP_GF_ShareCount,0,COLUMN()) | G73: =INDEX(SP_CFA_FCF_PreDiv,0,COLUMN())/INDEX(SP_GF_ShareCount,0,COLUMN()) | H73: =INDEX(SP_CFA_FCF_PreDiv,0,COLUMN())/INDEX(SP_GF_ShareCount,0,COLUMN()) | I73: =INDEX(SP_CFA_FCF_PreDiv,0,COLUMN())/INDEX(SP_GF_ShareCount,0,COLUMN()) | J73: =INDEX(SP_CFA_FCF_PreDiv,0,COLUMN())/INDEX(SP_GF_ShareCount,0,COLUMN()) | ... CA73: =INDEX(SP_CFA_FCF_PreDiv,0,COLUMN())/INDEX(SP_GF_ShareCount,0,COLUMN())
A74: Dividend Per Share | C74: =INDEX(MO_CFSum_DPS,0,COLUMN()) | D74: =INDEX(MO_CFSum_DPS,0,COLUMN()) | E74: =INDEX(MO_CFSum_DPS,0,COLUMN()) | F74: =INDEX(MO_CFSum_DPS,0,COLUMN()) | G74: =INDEX(MO_CFSum_DPS,0,COLUMN()) | H74: =INDEX(MO_CFSum_DPS,0,COLUMN()) | I74: =INDEX(MO_CFSum_DPS,0,COLUMN()) | J74: =INDEX(MO_CFSum_DPS,0,COLUMN()) | ... CA74: =INDEX(MO_CFSum_DPS,0,COLUMN())
A75: Dividend Payout Ratio vs Core FCF, Pre Div | C75: =C74/C73 | D75: =D74/D73 | E75: =E74/E73 | F75: =F74/F73 | G75: =G74/G73 | H75: =H74/H73 | I75: =I74/I73 | J75: =J74/J73 | ... CA75: =CA74/CA73
A76: Dividend Payout Ratio vs Earnings Per Share | C76: =C74/C47 | D76: =D74/D47 | E76: =E74/E47 | F76: =F74/F47 | G76: =G74/G47 | H76: =H74/H47 | I76: =I74/I47 | J76: =J74/J47 | ... CA76: =CA74/CA47
A78: Balance Sheet Ratios
A79: Net Debt / EBITDA | D79: =INDEX(MO_BSS_Debt_Net,0,COLUMN())/INDEX(SP_BSR_EBITDA_LTM,0,COLUMN()) | E79: =INDEX(MO_BSS_Debt_Net,0,COLUMN())/INDEX(SP_BSR_EBITDA_LTM,0,COLUMN()) | F79: =INDEX(MO_BSS_Debt_Net,0,COLUMN())/INDEX(SP_BSR_EBITDA_LTM,0,COLUMN()) | J79: =INDEX(MO_BSS_Debt_Net,0,COLUMN())/INDEX(SP_BSR_EBITDA_LTM,0,COLUMN()) | K79: =INDEX(MO_BSS_Debt_Net,0,COLUMN())/INDEX(SP_BSR_EBITDA_LTM,0,COLUMN()) | L79: =INDEX(MO_BSS_Debt_Net,0,COLUMN())/INDEX(SP_BSR_EBITDA_LTM,0,COLUMN()) | M79: =INDEX(MO_BSS_Debt_Net,0,COLUMN())/INDEX(SP_BSR_EBITDA_LTM,0,COLUMN()) | N79: =INDEX(MO_BSS_Debt_Net,0,COLUMN())/INDEX(SP_BSR_EBITDA_LTM,0,COLUMN()) | O79: =INDEX(MO_BSS_Debt_Net,0,COLUMN())/INDEX(SP_BSR_EBITDA_LTM,0,COLUMN()) | P79: =INDEX(MO_BSS_Debt_Net,0,COLUMN())/INDEX(SP_BSR_EBITDA_LTM,0,COLUMN()) | Q79: =INDEX(MO_BSS_Debt_Net,0,COLUMN())/INDEX(SP_BSR_EBITDA_LTM,0,COLUMN()) | ... CA79: =INDEX(MO_BSS_Debt_Net,0,COLUMN())/INDEX(SP_BSR_EBITDA_LTM,0,COLUMN())
A80: Net Debt / Cash Flow | C80: =INDEX(MO_BSS_Debt_Net,0,COLUMN())/INDEX(SP_BSR_CashFlow_LTM,0,COLUMN()) | D80: =INDEX(MO_BSS_Debt_Net,0,COLUMN())/INDEX(SP_BSR_CashFlow_LTM,0,COLUMN()) | E80: =INDEX(MO_BSS_Debt_Net,0,COLUMN())/INDEX(SP_BSR_CashFlow_LTM,0,COLUMN()) | F80: =INDEX(MO_BSS_Debt_Net,0,COLUMN())/INDEX(SP_BSR_CashFlow_LTM,0,COLUMN()) | J80: =INDEX(MO_BSS_Debt_Net,0,COLUMN())/INDEX(SP_BSR_CashFlow_LTM,0,COLUMN()) | K80: =INDEX(MO_BSS_Debt_Net,0,COLUMN())/INDEX(SP_BSR_CashFlow_LTM,0,COLUMN()) | L80: =INDEX(MO_BSS_Debt_Net,0,COLUMN())/INDEX(SP_BSR_CashFlow_LTM,0,COLUMN()) | M80: =INDEX(MO_BSS_Debt_Net,0,COLUMN())/INDEX(SP_BSR_CashFlow_LTM,0,COLUMN()) | N80: =INDEX(MO_BSS_Debt_Net,0,COLUMN())/INDEX(SP_BSR_CashFlow_LTM,0,COLUMN()) | O80: =INDEX(MO_BSS_Debt_Net,0,COLUMN())/INDEX(SP_BSR_CashFlow_LTM,0,COLUMN()) | P80: =INDEX(MO_BSS_Debt_Net,0,COLUMN())/INDEX(SP_BSR_CashFlow_LTM,0,COLUMN()) | Q80: =INDEX(MO_BSS_Debt_Net,0,COLUMN())/INDEX(SP_BSR_CashFlow_LTM,0,COLUMN()) | ... CA80: =INDEX(MO_BSS_Debt_Net,0,COLUMN())/INDEX(SP_BSR_CashFlow_LTM,0,COLUMN())
A81: Net Debt / Capital | C81: =INDEX(MO_BSS_Debt_Net,0,COLUMN())/SUM(INDEX(MO_BS_SE,0,COLUMN()),INDEX(MO_BSS_Debt,0,COLUMN()),IFERROR(INDEX(MO_BSS_OL,0,COLUMN()),0)) | D81: =INDEX(MO_BSS_Debt_Net,0,COLUMN())/SUM(INDEX(MO_BS_SE,0,COLUMN()),INDEX(MO_BSS_Debt,0,COLUMN()),IFERROR(INDEX(MO_BSS_OL,0,COLUMN()),0)) | E81: =INDEX(MO_BSS_Debt_Net,0,COLUMN())/SUM(INDEX(MO_BS_SE,0,COLUMN()),INDEX(MO_BSS_Debt,0,COLUMN()),IFERROR(INDEX(MO_BSS_OL,0,COLUMN()),0)) | F81: =INDEX(MO_BSS_Debt_Net,0,COLUMN())/SUM(INDEX(MO_BS_SE,0,COLUMN()),INDEX(MO_BSS_Debt,0,COLUMN()),IFERROR(INDEX(MO_BSS_OL,0,COLUMN()),0)) | J81: =INDEX(MO_BSS_Debt_Net,0,COLUMN())/SUM(INDEX(MO_BS_SE,0,COLUMN()),INDEX(MO_BSS_Debt,0,COLUMN()),IFERROR(INDEX(MO_BSS_OL,0,COLUMN()),0)) | K81: =INDEX(MO_BSS_Debt_Net,0,COLUMN())/SUM(INDEX(MO_BS_SE,0,COLUMN()),INDEX(MO_BSS_Debt,0,COLUMN()),IFERROR(INDEX(MO_BSS_OL,0,COLUMN()),0)) | L81: =INDEX(MO_BSS_Debt_Net,0,COLUMN())/SUM(INDEX(MO_BS_SE,0,COLUMN()),INDEX(MO_BSS_Debt,0,COLUMN()),IFERROR(INDEX(MO_BSS_OL,0,COLUMN()),0)) | M81: =INDEX(MO_BSS_Debt_Net,0,COLUMN())/SUM(INDEX(MO_BS_SE,0,COLUMN()),INDEX(MO_BSS_Debt,0,COLUMN()),IFERROR(INDEX(MO_BSS_OL,0,COLUMN()),0)) | N81: =INDEX(MO_BSS_Debt_Net,0,COLUMN())/SUM(INDEX(MO_BS_SE,0,COLUMN()),INDEX(MO_BSS_Debt,0,COLUMN()),IFERROR(INDEX(MO_BSS_OL,0,COLUMN()),0)) | O81: =INDEX(MO_BSS_Debt_Net,0,COLUMN())/SUM(INDEX(MO_BS_SE,0,COLUMN()),INDEX(MO_BSS_Debt,0,COLUMN()),IFERROR(INDEX(MO_BSS_OL,0,COLUMN()),0)) | P81: =INDEX(MO_BSS_Debt_Net,0,COLUMN())/SUM(INDEX(MO_BS_SE,0,COLUMN()),INDEX(MO_BSS_Debt,0,COLUMN()),IFERROR(INDEX(MO_BSS_OL,0,COLUMN()),0)) | Q81: =INDEX(MO_BSS_Debt_Net,0,COLUMN())/SUM(INDEX(MO_BS_SE,0,COLUMN()),INDEX(MO_BSS_Debt,0,COLUMN()),IFERROR(INDEX(MO_BSS_OL,0,COLUMN()),0)) | ... CA81: =INDEX(MO_BSS_Debt_Net,0,COLUMN())/SUM(INDEX(MO_BS_SE,0,COLUMN()),INDEX(MO_BSS_Debt,0,COLUMN()),IFERROR(INDEX(MO_BSS_OL,0,COLUMN()),0))
A82: LTM EBITDA | C82: =C45 | D82: =D45 | E82: =E45 | F82: =F45 | J82: =SUM(J45,I45,H45,G45) | K82: =K45 | L82: =SUM(L45,J45,I45,H45) | M82: =SUM(M45,L45,J45,I45) | N82: =SUM(N45,M45,L45,J45) | O82: =SUM(O45,N45,M45,L45) | P82: =P45 | Q82: =SUM(Q45,O45,N45,M45) | R82: =SUM(R45,Q45,O45,N45) | S82: =SUM(S45,R45,Q45,O45) | T82: =SUM(T45,S45,R45,Q45) | U82: =U45 | V82: =SUM(V45,T45,S45,R45) | W82: =SUM(W45,V45,T45,S45) | X82: =SUM(X45,W45,V45,T45) | Y82: =SUM(Y45,X45,W45,V45) | Z82: =Z45 | AA82: =SUM(AA45,Y45,X45,W45) | AB82: =SUM(AB45,AA45,Y45,X45) | AC82: =SUM(AC45,AB45,AA45,Y45) | AD82: =SUM(AD45,AC45,AB45,AA45) | AE82: =AE45 | AF82: =SUM(AF45,AD45,AC45,AB45) | AG82: =SUM(AG45,AF45,AD45,AC45) | AH82: =SUM(AH45,AG45,AF45,AD45) | AI82: =SUM(AI45,AH45,AG45,AF45) | AJ82: =AJ45 | AK82: =SUM(AK45,AI45,AH45,AG45) | AL82: =SUM(AL45,AK45,AI45,AH45) | AM82: =SUM(AM45,AL45,AK45,AI45) | AN82: =SUM(AN45,AM45,AL45,AK45) | AO82: =AO45 | AP82: =SUM(AP45,AN45,AM45,AL45) | AQ82: =SUM(AQ45,AP45,AN45,AM45) | AR82: =SUM(AR45,AQ45,AP45,AN45) | AS82: =SUM(AS45,AR45,AQ45,AP45) | AT82: =AT45 | AU82: =SUM(AU45,AS45,AR45,AQ45) | AV82: =SUM(AV45,AU45,AS45,AR45) | AW82: =SUM(AW45,AV45,AU45,AS45) | AX82: =SUM(AX45,AW45,AV45,AU45) | AY82: =AY45 | AZ82: =SUM(AZ45,AX45,AW45,AV45) | BA82: =SUM(BA45,AZ45,AX45,AW45) | BB82: =SUM(BB45,BA45,AZ45,AX45) | BC82: =SUM(BC45,BB45,BA45,AZ45) | BD82: =BD45 | BE82: =SUM(BE45,BC45,BB45,BA45) | BF82: =SUM(BF45,BE45,BC45,BB45) | BG82: =SUM(BG45,BF45,BE45,BC45) | BH82: =SUM(BH45,BG45,BF45,BE45) | BI82: =BI45 | BJ82: =SUM(BJ45,BH45,BG45,BF45) | BK82: =SUM(BK45,BJ45,BH45,BG45) | BL82: =SUM(BL45,BK45,BJ45,BH45) | BM82: =SUM(BM45,BL45,BK45,BJ45) | BN82: =BN45 | BO82: =SUM(BO45,BM45,BL45,BK45) | BP82: =SUM(BP45,BO45,BM45,BL45) | BQ82: =SUM(BQ45,BP45,BO45,BM45) | BR82: =SUM(BR45,BQ45,BP45,BO45) | BS82: =BS45 | BT82: =SUM(BT45,BR45,BQ45,BP45) | BU82: =SUM(BU45,BT45,BR45,BQ45) | BV82: =SUM(BV45,BU45,BT45,BR45) | BW82: =SUM(BW45,BV45,BU45,BT45) | BX82: =BX45 | BY82: =BY45 | BZ82: =BZ45 | CA82: =CA45
A83: LTM Cash Flow | C83: =C60 | D83: =D60 | E83: =E60 | F83: =F60 | J83: =SUM(J60,I60,H60,G60) | K83: =K60 | L83: =SUM(L60,J60,I60,H60) | M83: =SUM(M60,L60,J60,I60) | N83: =SUM(N60,M60,L60,J60) | O83: =SUM(O60,N60,M60,L60) | P83: =P60 | Q83: =SUM(Q60,O60,N60,M60) | R83: =SUM(R60,Q60,O60,N60) | S83: =SUM(S60,R60,Q60,O60) | T83: =SUM(T60,S60,R60,Q60) | U83: =U60 | V83: =SUM(V60,T60,S60,R60) | W83: =SUM(W60,V60,T60,S60) | X83: =SUM(X60,W60,V60,T60) | Y83: =SUM(Y60,X60,W60,V60) | Z83: =Z60 | AA83: =SUM(AA60,Y60,X60,W60) | AB83: =SUM(AB60,AA60,Y60,X60) | AC83: =SUM(AC60,AB60,AA60,Y60) | AD83: =SUM(AD60,AC60,AB60,AA60) | AE83: =AE60 | AF83: =SUM(AF60,AD60,AC60,AB60) | AG83: =SUM(AG60,AF60,AD60,AC60) | AH83: =SUM(AH60,AG60,AF60,AD60) | AI83: =SUM(AI60,AH60,AG60,AF60) | AJ83: =AJ60 | AK83: =SUM(AK60,AI60,AH60,AG60) | AL83: =SUM(AL60,AK60,AI60,AH60) | AM83: =SUM(AM60,AL60,AK60,AI60) | AN83: =SUM(AN60,AM60,AL60,AK60) | AO83: =AO60 | AP83: =SUM(AP60,AN60,AM60,AL60) | AQ83: =SUM(AQ60,AP60,AN60,AM60) | AR83: =SUM(AR60,AQ60,AP60,AN60) | AS83: =SUM(AS60,AR60,AQ60,AP60) | AT83: =AT60 | AU83: =SUM(AU60,AS60,AR60,AQ60) | AV83: =SUM(AV60,AU60,AS60,AR60) | AW83: =SUM(AW60,AV60,AU60,AS60) | AX83: =SUM(AX60,AW60,AV60,AU60) | AY83: =AY60 | AZ83: =SUM(AZ60,AX60,AW60,AV60) | BA83: =SUM(BA60,AZ60,AX60,AW60) | BB83: =SUM(BB60,BA60,AZ60,AX60) | BC83: =SUM(BC60,BB60,BA60,AZ60) | BD83: =BD60 | BE83: =SUM(BE60,BC60,BB60,BA60) | BF83: =SUM(BF60,BE60,BC60,BB60) | BG83: =SUM(BG60,BF60,BE60,BC60) | BH83: =SUM(BH60,BG60,BF60,BE60) | BI83: =BI60 | BJ83: =SUM(BJ60,BH60,BG60,BF60) | BK83: =SUM(BK60,BJ60,BH60,BG60) | BL83: =SUM(BL60,BK60,BJ60,BH60) | BM83: =SUM(BM60,BL60,BK60,BJ60) | BN83: =BN60 | BO83: =SUM(BO60,BM60,BL60,BK60) | BP83: =SUM(BP60,BO60,BM60,BL60) | BQ83: =SUM(BQ60,BP60,BO60,BM60) | BR83: =SUM(BR60,BQ60,BP60,BO60) | BS83: =BS60 | BT83: =SUM(BT60,BR60,BQ60,BP60) | BU83: =SUM(BU60,BT60,BR60,BQ60) | BV83: =SUM(BV60,BU60,BT60,BR60) | BW83: =SUM(BW60,BV60,BU60,BT60) | BX83: =BX60 | BY83: =BY60 | BZ83: =BZ60 | CA83: =CA60
A85: Profitability Ratios
A86: Net Income | C86: =INDEX(SP_NGF_NI,0,COLUMN()) | D86: =INDEX(SP_NGF_NI,0,COLUMN()) | E86: =INDEX(SP_NGF_NI,0,COLUMN()) | F86: =INDEX(SP_NGF_NI,0,COLUMN()) | G86: =INDEX(SP_NGF_NI,0,COLUMN()) | H86: =INDEX(SP_NGF_NI,0,COLUMN()) | I86: =INDEX(SP_NGF_NI,0,COLUMN()) | J86: =INDEX(SP_NGF_NI,0,COLUMN()) | ... CA86: =INDEX(SP_NGF_NI,0,COLUMN())
A87: LTM Net Income | C87: =C86 | D87: =D86 | E87: =E86 | F87: =F86 | J87: =SUM(J86,I86,H86,G86) | K87: =K86 | L87: =SUM(L86,J86,I86,H86) | M87: =SUM(M86,L86,J86,I86) | N87: =SUM(N86,M86,L86,J86) | O87: =SUM(O86,N86,M86,L86) | P87: =P86 | Q87: =SUM(Q86,O86,N86,M86) | R87: =SUM(R86,Q86,O86,N86) | S87: =SUM(S86,R86,Q86,O86) | T87: =SUM(T86,S86,R86,Q86) | U87: =U86 | V87: =SUM(V86,T86,S86,R86) | W87: =SUM(W86,V86,T86,S86) | X87: =SUM(X86,W86,V86,T86) | Y87: =SUM(Y86,X86,W86,V86) | Z87: =Z86 | AA87: =SUM(AA86,Y86,X86,W86) | AB87: =SUM(AB86,AA86,Y86,X86) | AC87: =SUM(AC86,AB86,AA86,Y86) | AD87: =SUM(AD86,AC86,AB86,AA86) | AE87: =AE86 | AF87: =SUM(AF86,AD86,AC86,AB86) | AG87: =SUM(AG86,AF86,AD86,AC86) | AH87: =SUM(AH86,AG86,AF86,AD86) | AI87: =SUM(AI86,AH86,AG86,AF86) | AJ87: =AJ86 | AK87: =SUM(AK86,AI86,AH86,AG86) | AL87: =SUM(AL86,AK86,AI86,AH86) | AM87: =SUM(AM86,AL86,AK86,AI86) | AN87: =SUM(AN86,AM86,AL86,AK86) | AO87: =AO86 | AP87: =SUM(AP86,AN86,AM86,AL86) | AQ87: =SUM(AQ86,AP86,AN86,AM86) | AR87: =SUM(AR86,AQ86,AP86,AN86) | AS87: =SUM(AS86,AR86,AQ86,AP86) | AT87: =AT86 | AU87: =SUM(AU86,AS86,AR86,AQ86) | AV87: =SUM(AV86,AU86,AS86,AR86) | AW87: =SUM(AW86,AV86,AU86,AS86) | AX87: =SUM(AX86,AW86,AV86,AU86) | AY87: =AY86 | AZ87: =SUM(AZ86,AX86,AW86,AV86) | BA87: =SUM(BA86,AZ86,AX86,AW86) | BB87: =SUM(BB86,BA86,AZ86,AX86) | BC87: =SUM(BC86,BB86,BA86,AZ86) | BD87: =BD86 | BE87: =SUM(BE86,BC86,BB86,BA86) | BF87: =SUM(BF86,BE86,BC86,BB86) | BG87: =SUM(BG86,BF86,BE86,BC86) | BH87: =SUM(BH86,BG86,BF86,BE86) | BI87: =BI86 | BJ87: =SUM(BJ86,BH86,BG86,BF86) | BK87: =SUM(BK86,BJ86,BH86,BG86) | BL87: =SUM(BL86,BK86,BJ86,BH86) | BM87: =SUM(BM86,BL86,BK86,BJ86) | BN87: =BN86 | BO87: =SUM(BO86,BM86,BL86,BK86) | BP87: =SUM(BP86,BO86,BM86,BL86) | BQ87: =SUM(BQ86,BP86,BO86,BM86) | BR87: =SUM(BR86,BQ86,BP86,BO86) | BS87: =BS86 | BT87: =SUM(BT86,BR86,BQ86,BP86) | BU87: =SUM(BU86,BT86,BR86,BQ86) | BV87: =SUM(BV86,BU86,BT86,BR86) | BW87: =SUM(BW86,BV86,BU86,BT86) | BX87: =BX86 | BY87: =BY86 | BZ87: =BZ86 | CA87: =CA86
A88: Shareholder's Equity | C88: =INDEX(MO_BS_SE,0,COLUMN()) | D88: =INDEX(MO_BS_SE,0,COLUMN()) | E88: =INDEX(MO_BS_SE,0,COLUMN()) | F88: =INDEX(MO_BS_SE,0,COLUMN()) | G88: =INDEX(MO_BS_SE,0,COLUMN()) | H88: =INDEX(MO_BS_SE,0,COLUMN()) | I88: =INDEX(MO_BS_SE,0,COLUMN()) | J88: =INDEX(MO_BS_SE,0,COLUMN()) | ... CA88: =INDEX(MO_BS_SE,0,COLUMN())
A89: Average Shareholder's Equity | C89: =C88 | D89: =AVERAGE(D88,C88) | E89: =AVERAGE(E88,D88) | F89: =AVERAGE(F88,E88) | J89: =AVERAGE(J88,I88,H88,G88) | K89: =AVERAGE(K88,F88) | L89: =AVERAGE(L88,J88,I88,H88) | M89: =AVERAGE(M88,L88,J88,I88) | N89: =AVERAGE(N88,M88,L88,J88) | O89: =AVERAGE(O88,N88,M88,L88) | P89: =AVERAGE(P88,K88) | Q89: =AVERAGE(Q88,O88,N88,M88) | R89: =AVERAGE(R88,Q88,O88,N88) | S89: =AVERAGE(S88,R88,Q88,O88) | T89: =AVERAGE(T88,S88,R88,Q88) | U89: =AVERAGE(U88,P88) | V89: =AVERAGE(V88,T88,S88,R88) | W89: =AVERAGE(W88,V88,T88,S88) | X89: =AVERAGE(X88,W88,V88,T88) | Y89: =AVERAGE(Y88,X88,W88,V88) | Z89: =AVERAGE(Z88,U88) | AA89: =AVERAGE(AA88,Y88,X88,W88) | AB89: =AVERAGE(AB88,AA88,Y88,X88) | AC89: =AVERAGE(AC88,AB88,AA88,Y88) | AD89: =AVERAGE(AD88,AC88,AB88,AA88) | AE89: =AVERAGE(AE88,Z88) | AF89: =AVERAGE(AF88,AD88,AC88,AB88) | AG89: =AVERAGE(AG88,AF88,AD88,AC88) | AH89: =AVERAGE(AH88,AG88,AF88,AD88) | AI89: =AVERAGE(AI88,AH88,AG88,AF88) | AJ89: =AVERAGE(AJ88,AE88) | AK89: =AVERAGE(AK88,AI88,AH88,AG88) | AL89: =AVERAGE(AL88,AK88,AI88,AH88) | AM89: =AVERAGE(AM88,AL88,AK88,AI88) | AN89: =AVERAGE(AN88,AM88,AL88,AK88) | AO89: =AVERAGE(AO88,AJ88) | AP89: =AVERAGE(AP88,AN88,AM88,AL88) | AQ89: =AVERAGE(AQ88,AP88,AN88,AM88) | AR89: =AVERAGE(AR88,AQ88,AP88,AN88) | AS89: =AVERAGE(AS88,AR88,AQ88,AP88) | AT89: =AVERAGE(AT88,AO88) | AU89: =AVERAGE(AU88,AS88,AR88,AQ88) | AV89: =AVERAGE(AV88,AU88,AS88,AR88) | AW89: =AVERAGE(AW88,AV88,AU88,AS88) | AX89: =AVERAGE(AX88,AW88,AV88,AU88) | AY89: =AVERAGE(AY88,AT88) | AZ89: =AVERAGE(AZ88,AX88,AW88,AV88) | BA89: =AVERAGE(BA88,AZ88,AX88,AW88) | BB89: =AVERAGE(BB88,BA88,AZ88,AX88) | BC89: =AVERAGE(BC88,BB88,BA88,AZ88) | BD89: =AVERAGE(BD88,AY88) | BE89: =AVERAGE(BE88,BC88,BB88,BA88) | BF89: =AVERAGE(BF88,BE88,BC88,BB88) | BG89: =AVERAGE(BG88,BF88,BE88,BC88) | BH89: =AVERAGE(BH88,BG88,BF88,BE88) | BI89: =AVERAGE(BI88,BD88) | BJ89: =AVERAGE(BJ88,BH88,BG88,BF88) | BK89: =AVERAGE(BK88,BJ88,BH88,BG88) | BL89: =AVERAGE(BL88,BK88,BJ88,BH88) | BM89: =AVERAGE(BM88,BL88,BK88,BJ88) | BN89: =AVERAGE(BN88,BI88) | BO89: =AVERAGE(BO88,BM88,BL88,BK88) | BP89: =AVERAGE(BP88,BO88,BM88,BL88) | BQ89: =AVERAGE(BQ88,BP88,BO88,BM88) | BR89: =AVERAGE(BR88,BQ88,BP88,BO88) | BS89: =AVERAGE(BS88,BN88) | BT89: =AVERAGE(BT88,BR88,BQ88,BP88) | BU89: =AVERAGE(BU88,BT88,BR88,BQ88) | BV89: =AVERAGE(BV88,BU88,BT88,BR88) | BW89: =AVERAGE(BW88,BV88,BU88,BT88) | BX89: =AVERAGE(BX88,BS88) | BY89: =AVERAGE(BY88,BX88) | BZ89: =AVERAGE(BZ88,BY88) | CA89: =AVERAGE(CA88,BZ88)
A90: ROE | C90: =IF(C89<0,"NMF",IF(ABS(C87/C89)>1,"NMF",C87/C89)) | D90: =IF(D89<0,"NMF",IF(ABS(D87/D89)>1,"NMF",D87/D89)) | E90: =IF(E89<0,"NMF",IF(ABS(E87/E89)>1,"NMF",E87/E89)) | F90: =IF(F89<0,"NMF",IF(ABS(F87/F89)>1,"NMF",F87/F89)) | K90: =IF(K89<0,"NMF",IF(ABS(K87/K89)>1,"NMF",K87/K89)) | L90: =IF(L89<0,"NMF",IF(ABS(L87/L89)>1,"NMF",L87/L89)) | M90: =IF(M89<0,"NMF",IF(ABS(M87/M89)>1,"NMF",M87/M89)) | N90: =IF(N89<0,"NMF",IF(ABS(N87/N89)>1,"NMF",N87/N89)) | O90: =IF(O89<0,"NMF",IF(ABS(O87/O89)>1,"NMF",O87/O89)) | P90: =IF(P89<0,"NMF",IF(ABS(P87/P89)>1,"NMF",P87/P89)) | Q90: =IF(Q89<0,"NMF",IF(ABS(Q87/Q89)>1,"NMF",Q87/Q89)) | R90: =IF(R89<0,"NMF",IF(ABS(R87/R89)>1,"NMF",R87/R89)) | ... CA90: =IF(CA89<0,"NMF",IF(ABS(CA87/CA89)>1,"NMF",CA87/CA89))
A91: NOPAT | C91: =INDEX(MO_RIS_Reported_OperatingIncome_NONGAAP,0,COLUMN())*(1-INDEX(MO_RIS_TaxRate_NONGAAP,0,COLUMN())) | D91: =INDEX(MO_RIS_Reported_OperatingIncome_NONGAAP,0,COLUMN())*(1-INDEX(MO_RIS_TaxRate_NONGAAP,0,COLUMN())) | E91: =INDEX(MO_RIS_Reported_OperatingIncome_NONGAAP,0,COLUMN())*(1-INDEX(MO_RIS_TaxRate_NONGAAP,0,COLUMN())) | F91: =INDEX(MO_RIS_Reported_OperatingIncome_NONGAAP,0,COLUMN())*(1-INDEX(MO_RIS_TaxRate_NONGAAP,0,COLUMN())) | G91: =INDEX(MO_RIS_Reported_OperatingIncome_NONGAAP,0,COLUMN())*(1-INDEX(MO_RIS_TaxRate_NONGAAP,0,COLUMN())) | H91: =INDEX(MO_RIS_Reported_OperatingIncome_NONGAAP,0,COLUMN())*(1-INDEX(MO_RIS_TaxRate_NONGAAP,0,COLUMN())) | I91: =INDEX(MO_RIS_Reported_OperatingIncome_NONGAAP,0,COLUMN())*(1-INDEX(MO_RIS_TaxRate_NONGAAP,0,COLUMN())) | J91: =INDEX(MO_RIS_Reported_OperatingIncome_NONGAAP,0,COLUMN())*(1-INDEX(MO_RIS_TaxRate_NONGAAP,0,COLUMN())) | ... CA91: =INDEX(MO_RIS_Reported_OperatingIncome_NONGAAP,0,COLUMN())*(1-INDEX(MO_RIS_TaxRate_NONGAAP,0,COLUMN()))
A92: LTM Net Operating Profit | C92: =C91 | D92: =D91 | E92: =E91 | F92: =F91 | J92: =SUM(J91,I91,H91,G91) | K92: =K91 | L92: =SUM(L91,J91,I91,H91) | M92: =SUM(M91,L91,J91,I91) | N92: =SUM(N91,M91,L91,J91) | O92: =SUM(O91,N91,M91,L91) | P92: =P91 | Q92: =SUM(Q91,O91,N91,M91) | R92: =SUM(R91,Q91,O91,N91) | S92: =SUM(S91,R91,Q91,O91) | T92: =SUM(T91,S91,R91,Q91) | U92: =U91 | V92: =SUM(V91,T91,S91,R91) | W92: =SUM(W91,V91,T91,S91) | X92: =SUM(X91,W91,V91,T91) | Y92: =SUM(Y91,X91,W91,V91) | Z92: =Z91 | AA92: =SUM(AA91,Y91,X91,W91) | AB92: =SUM(AB91,AA91,Y91,X91) | AC92: =SUM(AC91,AB91,AA91,Y91) | AD92: =SUM(AD91,AC91,AB91,AA91) | AE92: =AE91 | AF92: =SUM(AF91,AD91,AC91,AB91) | AG92: =SUM(AG91,AF91,AD91,AC91) | AH92: =SUM(AH91,AG91,AF91,AD91) | AI92: =SUM(AI91,AH91,AG91,AF91) | AJ92: =AJ91 | AK92: =SUM(AK91,AI91,AH91,AG91) | AL92: =SUM(AL91,AK91,AI91,AH91) | AM92: =SUM(AM91,AL91,AK91,AI91) | AN92: =SUM(AN91,AM91,AL91,AK91) | AO92: =AO91 | AP92: =SUM(AP91,AN91,AM91,AL91) | AQ92: =SUM(AQ91,AP91,AN91,AM91) | AR92: =SUM(AR91,AQ91,AP91,AN91) | AS92: =SUM(AS91,AR91,AQ91,AP91) | AT92: =AT91 | AU92: =SUM(AU91,AS91,AR91,AQ91) | AV92: =SUM(AV91,AU91,AS91,AR91) | AW92: =SUM(AW91,AV91,AU91,AS91) | AX92: =SUM(AX91,AW91,AV91,AU91) | AY92: =AY91 | AZ92: =SUM(AZ91,AX91,AW91,AV91) | BA92: =SUM(BA91,AZ91,AX91,AW91) | BB92: =SUM(BB91,BA91,AZ91,AX91) | BC92: =SUM(BC91,BB91,BA91,AZ91) | BD92: =BD91 | BE92: =SUM(BE91,BC91,BB91,BA91) | BF92: =SUM(BF91,BE91,BC91,BB91) | BG92: =SUM(BG91,BF91,BE91,BC91) | BH92: =SUM(BH91,BG91,BF91,BE91) | BI92: =BI91 | BJ92: =SUM(BJ91,BH91,BG91,BF91) | BK92: =SUM(BK91,BJ91,BH91,BG91) | BL92: =SUM(BL91,BK91,BJ91,BH91) | BM92: =SUM(BM91,BL91,BK91,BJ91) | BN92: =BN91 | BO92: =SUM(BO91,BM91,BL91,BK91) | BP92: =SUM(BP91,BO91,BM91,BL91) | BQ92: =SUM(BQ91,BP91,BO91,BM91) | BR92: =SUM(BR91,BQ91,BP91,BO91) | BS92: =BS91 | BT92: =SUM(BT91,BR91,BQ91,BP91) | BU92: =SUM(BU91,BT91,BR91,BQ91) | BV92: =SUM(BV91,BU91,BT91,BR91) | BW92: =SUM(BW91,BV91,BU91,BT91) | BX92: =BX91 | BY92: =BY91 | BZ92: =BZ91 | CA92: =CA91
A93: Total Assets | C93: =INDEX(MO_BS_TA,0,COLUMN()) | D93: =INDEX(MO_BS_TA,0,COLUMN()) | E93: =INDEX(MO_BS_TA,0,COLUMN()) | F93: =INDEX(MO_BS_TA,0,COLUMN()) | G93: =INDEX(MO_BS_TA,0,COLUMN()) | H93: =INDEX(MO_BS_TA,0,COLUMN()) | I93: =INDEX(MO_BS_TA,0,COLUMN()) | J93: =INDEX(MO_BS_TA,0,COLUMN()) | ... CA93: =INDEX(MO_BS_TA,0,COLUMN())
A94: Average Total Assets | C94: =C93 | D94: =AVERAGE(D93,C93) | E94: =AVERAGE(E93,D93) | F94: =AVERAGE(F93,E93) | J94: =AVERAGE(J93,I93,H93,G93) | K94: =AVERAGE(K93,F93) | L94: =AVERAGE(L93,J93,I93,H93) | M94: =AVERAGE(M93,L93,J93,I93) | N94: =AVERAGE(N93,M93,L93,J93) | O94: =AVERAGE(O93,N93,M93,L93) | P94: =AVERAGE(P93,K93) | Q94: =AVERAGE(Q93,O93,N93,M93) | R94: =AVERAGE(R93,Q93,O93,N93) | S94: =AVERAGE(S93,R93,Q93,O93) | T94: =AVERAGE(T93,S93,R93,Q93) | U94: =AVERAGE(U93,P93) | V94: =AVERAGE(V93,T93,S93,R93) | W94: =AVERAGE(W93,V93,T93,S93) | X94: =AVERAGE(X93,W93,V93,T93) | Y94: =AVERAGE(Y93,X93,W93,V93) | Z94: =AVERAGE(Z93,U93) | AA94: =AVERAGE(AA93,Y93,X93,W93) | AB94: =AVERAGE(AB93,AA93,Y93,X93) | AC94: =AVERAGE(AC93,AB93,AA93,Y93) | AD94: =AVERAGE(AD93,AC93,AB93,AA93) | AE94: =AVERAGE(AE93,Z93) | AF94: =AVERAGE(AF93,AD93,AC93,AB93) | AG94: =AVERAGE(AG93,AF93,AD93,AC93) | AH94: =AVERAGE(AH93,AG93,AF93,AD93) | AI94: =AVERAGE(AI93,AH93,AG93,AF93) | AJ94: =AVERAGE(AJ93,AE93) | AK94: =AVERAGE(AK93,AI93,AH93,AG93) | AL94: =AVERAGE(AL93,AK93,AI93,AH93) | AM94: =AVERAGE(AM93,AL93,AK93,AI93) | AN94: =AVERAGE(AN93,AM93,AL93,AK93) | AO94: =AVERAGE(AO93,AJ93) | AP94: =AVERAGE(AP93,AN93,AM93,AL93) | AQ94: =AVERAGE(AQ93,AP93,AN93,AM93) | AR94: =AVERAGE(AR93,AQ93,AP93,AN93) | AS94: =AVERAGE(AS93,AR93,AQ93,AP93) | AT94: =AVERAGE(AT93,AO93) | AU94: =AVERAGE(AU93,AS93,AR93,AQ93) | AV94: =AVERAGE(AV93,AU93,AS93,AR93) | AW94: =AVERAGE(AW93,AV93,AU93,AS93) | AX94: =AVERAGE(AX93,AW93,AV93,AU93) | AY94: =AVERAGE(AY93,AT93) | AZ94: =AVERAGE(AZ93,AX93,AW93,AV93) | BA94: =AVERAGE(BA93,AZ93,AX93,AW93) | BB94: =AVERAGE(BB93,BA93,AZ93,AX93) | BC94: =AVERAGE(BC93,BB93,BA93,AZ93) | BD94: =AVERAGE(BD93,AY93) | BE94: =AVERAGE(BE93,BC93,BB93,BA93) | BF94: =AVERAGE(BF93,BE93,BC93,BB93) | BG94: =AVERAGE(BG93,BF93,BE93,BC93) | BH94: =AVERAGE(BH93,BG93,BF93,BE93) | BI94: =AVERAGE(BI93,BD93) | BJ94: =AVERAGE(BJ93,BH93,BG93,BF93) | BK94: =AVERAGE(BK93,BJ93,BH93,BG93) | BL94: =AVERAGE(BL93,BK93,BJ93,BH93) | BM94: =AVERAGE(BM93,BL93,BK93,BJ93) | BN94: =AVERAGE(BN93,BI93) | BO94: =AVERAGE(BO93,BM93,BL93,BK93) | BP94: =AVERAGE(BP93,BO93,BM93,BL93) | BQ94: =AVERAGE(BQ93,BP93,BO93,BM93) | BR94: =AVERAGE(BR93,BQ93,BP93,BO93) | BS94: =AVERAGE(BS93,BN93) | BT94: =AVERAGE(BT93,BR93,BQ93,BP93) | BU94: =AVERAGE(BU93,BT93,BR93,BQ93) | BV94: =AVERAGE(BV93,BU93,BT93,BR93) | BW94: =AVERAGE(BW93,BV93,BU93,BT93) | BX94: =AVERAGE(BX93,BS93) | BY94: =AVERAGE(BY93,BX93) | BZ94: =AVERAGE(BZ93,BY93) | CA94: =AVERAGE(CA93,BZ93)
A95: After-tax ROA | C95: =IF(C94<0,"NMF",IF(ABS(C92/C94)>1,"NMF",C92/C94)) | D95: =IF(D94<0,"NMF",IF(ABS(D92/D94)>1,"NMF",D92/D94)) | E95: =IF(E94<0,"NMF",IF(ABS(E92/E94)>1,"NMF",E92/E94)) | F95: =IF(F94<0,"NMF",IF(ABS(F92/F94)>1,"NMF",F92/F94)) | K95: =IF(K94<0,"NMF",IF(ABS(K92/K94)>1,"NMF",K92/K94)) | L95: =IF(L94<0,"NMF",IF(ABS(L92/L94)>1,"NMF",L92/L94)) | M95: =IF(M94<0,"NMF",IF(ABS(M92/M94)>1,"NMF",M92/M94)) | N95: =IF(N94<0,"NMF",IF(ABS(N92/N94)>1,"NMF",N92/N94)) | O95: =IF(O94<0,"NMF",IF(ABS(O92/O94)>1,"NMF",O92/O94)) | P95: =IF(P94<0,"NMF",IF(ABS(P92/P94)>1,"NMF",P92/P94)) | Q95: =IF(Q94<0,"NMF",IF(ABS(Q92/Q94)>1,"NMF",Q92/Q94)) | R95: =IF(R94<0,"NMF",IF(ABS(R92/R94)>1,"NMF",R92/R94)) | ... CA95: =IF(CA94<0,"NMF",IF(ABS(CA92/CA94)>1,"NMF",CA92/CA94))
A96: Total Debt | C96: =INDEX(MO_BSS_Debt_Net,0,COLUMN())+INDEX(MO_BSS_Cash,0,COLUMN()) | D96: =INDEX(MO_BSS_Debt_Net,0,COLUMN())+INDEX(MO_BSS_Cash,0,COLUMN()) | E96: =INDEX(MO_BSS_Debt_Net,0,COLUMN())+INDEX(MO_BSS_Cash,0,COLUMN()) | F96: =INDEX(MO_BSS_Debt_Net,0,COLUMN())+INDEX(MO_BSS_Cash,0,COLUMN()) | G96: =INDEX(MO_BSS_Debt_Net,0,COLUMN())+INDEX(MO_BSS_Cash,0,COLUMN()) | H96: =INDEX(MO_BSS_Debt_Net,0,COLUMN())+INDEX(MO_BSS_Cash,0,COLUMN()) | I96: =INDEX(MO_BSS_Debt_Net,0,COLUMN())+INDEX(MO_BSS_Cash,0,COLUMN()) | J96: =INDEX(MO_BSS_Debt_Net,0,COLUMN())+INDEX(MO_BSS_Cash,0,COLUMN()) | ... CA96: =INDEX(MO_BSS_Debt_Net,0,COLUMN())+INDEX(MO_BSS_Cash,0,COLUMN())
A97: Average Book Value of Debt | C97: =C96 | D97: =AVERAGE(D96,C96) | E97: =AVERAGE(E96,D96) | F97: =AVERAGE(F96,E96) | J97: =AVERAGE(J96,I96,H96,G96) | K97: =AVERAGE(K96,F96) | L97: =AVERAGE(L96,J96,I96,H96) | M97: =AVERAGE(M96,L96,J96,I96) | N97: =AVERAGE(N96,M96,L96,J96) | O97: =AVERAGE(O96,N96,M96,L96) | P97: =AVERAGE(P96,K96) | Q97: =AVERAGE(Q96,O96,N96,M96) | R97: =AVERAGE(R96,Q96,O96,N96) | S97: =AVERAGE(S96,R96,Q96,O96) | T97: =AVERAGE(T96,S96,R96,Q96) | U97: =AVERAGE(U96,P96) | V97: =AVERAGE(V96,T96,S96,R96) | W97: =AVERAGE(W96,V96,T96,S96) | X97: =AVERAGE(X96,W96,V96,T96) | Y97: =AVERAGE(Y96,X96,W96,V96) | Z97: =AVERAGE(Z96,U96) | AA97: =AVERAGE(AA96,Y96,X96,W96) | AB97: =AVERAGE(AB96,AA96,Y96,X96) | AC97: =AVERAGE(AC96,AB96,AA96,Y96) | AD97: =AVERAGE(AD96,AC96,AB96,AA96) | AE97: =AVERAGE(AE96,Z96) | AF97: =AVERAGE(AF96,AD96,AC96,AB96) | AG97: =AVERAGE(AG96,AF96,AD96,AC96) | AH97: =AVERAGE(AH96,AG96,AF96,AD96) | AI97: =AVERAGE(AI96,AH96,AG96,AF96) | AJ97: =AVERAGE(AJ96,AE96) | AK97: =AVERAGE(AK96,AI96,AH96,AG96) | AL97: =AVERAGE(AL96,AK96,AI96,AH96) | AM97: =AVERAGE(AM96,AL96,AK96,AI96) | AN97: =AVERAGE(AN96,AM96,AL96,AK96) | AO97: =AVERAGE(AO96,AJ96) | AP97: =AVERAGE(AP96,AN96,AM96,AL96) | AQ97: =AVERAGE(AQ96,AP96,AN96,AM96) | AR97: =AVERAGE(AR96,AQ96,AP96,AN96) | AS97: =AVERAGE(AS96,AR96,AQ96,AP96) | AT97: =AVERAGE(AT96,AO96) | AU97: =AVERAGE(AU96,AS96,AR96,AQ96) | AV97: =AVERAGE(AV96,AU96,AS96,AR96) | AW97: =AVERAGE(AW96,AV96,AU96,AS96) | AX97: =AVERAGE(AX96,AW96,AV96,AU96) | AY97: =AVERAGE(AY96,AT96) | AZ97: =AVERAGE(AZ96,AX96,AW96,AV96) | BA97: =AVERAGE(BA96,AZ96,AX96,AW96) | BB97: =AVERAGE(BB96,BA96,AZ96,AX96) | BC97: =AVERAGE(BC96,BB96,BA96,AZ96) | BD97: =AVERAGE(BD96,AY96) | BE97: =AVERAGE(BE96,BC96,BB96,BA96) | BF97: =AVERAGE(BF96,BE96,BC96,BB96) | BG97: =AVERAGE(BG96,BF96,BE96,BC96) | BH97: =AVERAGE(BH96,BG96,BF96,BE96) | BI97: =AVERAGE(BI96,BD96) | BJ97: =AVERAGE(BJ96,BH96,BG96,BF96) | BK97: =AVERAGE(BK96,BJ96,BH96,BG96) | BL97: =AVERAGE(BL96,BK96,BJ96,BH96) | BM97: =AVERAGE(BM96,BL96,BK96,BJ96) | BN97: =AVERAGE(BN96,BI96) | BO97: =AVERAGE(BO96,BM96,BL96,BK96) | BP97: =AVERAGE(BP96,BO96,BM96,BL96) | BQ97: =AVERAGE(BQ96,BP96,BO96,BM96) | BR97: =AVERAGE(BR96,BQ96,BP96,BO96) | BS97: =AVERAGE(BS96,BN96) | BT97: =AVERAGE(BT96,BR96,BQ96,BP96) | BU97: =AVERAGE(BU96,BT96,BR96,BQ96) | BV97: =AVERAGE(BV96,BU96,BT96,BR96) | BW97: =AVERAGE(BW96,BV96,BU96,BT96) | BX97: =AVERAGE(BX96,BS96) | BY97: =AVERAGE(BY96,BX96) | BZ97: =AVERAGE(BZ96,BY96) | CA97: =AVERAGE(CA96,BZ96)
A98: Average Invested Capital | C98: =SUM(INDEX(SP_BSR_Debt_Avg,0,COLUMN()),INDEX(SP_BSR_SE_Avg,0,COLUMN())) | D98: =SUM(INDEX(SP_BSR_Debt_Avg,0,COLUMN()),INDEX(SP_BSR_SE_Avg,0,COLUMN())) | E98: =SUM(INDEX(SP_BSR_Debt_Avg,0,COLUMN()),INDEX(SP_BSR_SE_Avg,0,COLUMN())) | F98: =SUM(INDEX(SP_BSR_Debt_Avg,0,COLUMN()),INDEX(SP_BSR_SE_Avg,0,COLUMN())) | G98: =SUM(INDEX(SP_BSR_Debt_Avg,0,COLUMN()),INDEX(SP_BSR_SE_Avg,0,COLUMN())) | H98: =SUM(INDEX(SP_BSR_Debt_Avg,0,COLUMN()),INDEX(SP_BSR_SE_Avg,0,COLUMN())) | I98: =SUM(INDEX(SP_BSR_Debt_Avg,0,COLUMN()),INDEX(SP_BSR_SE_Avg,0,COLUMN())) | J98: =SUM(INDEX(SP_BSR_Debt_Avg,0,COLUMN()),INDEX(SP_BSR_SE_Avg,0,COLUMN())) | ... CA98: =SUM(INDEX(SP_BSR_Debt_Avg,0,COLUMN()),INDEX(SP_BSR_SE_Avg,0,COLUMN()))
A99: ROIC | C99: =IF(C98<0,"NMF",IF(ABS(C92/C98)>1,"NMF",C92/C98)) | D99: =IF(D98<0,"NMF",IF(ABS(D92/D98)>1,"NMF",D92/D98)) | E99: =IF(E98<0,"NMF",IF(ABS(E92/E98)>1,"NMF",E92/E98)) | F99: =IF(F98<0,"NMF",IF(ABS(F92/F98)>1,"NMF",F92/F98)) | J99: =IF(J98<0,"NMF",IF(ABS(J92/J98)>1,"NMF",J92/J98)) | K99: =IF(K98<0,"NMF",IF(ABS(K92/K98)>1,"NMF",K92/K98)) | L99: =IF(L98<0,"NMF",IF(ABS(L92/L98)>1,"NMF",L92/L98)) | M99: =IF(M98<0,"NMF",IF(ABS(M92/M98)>1,"NMF",M92/M98)) | N99: =IF(N98<0,"NMF",IF(ABS(N92/N98)>1,"NMF",N92/N98)) | O99: =IF(O98<0,"NMF",IF(ABS(O92/O98)>1,"NMF",O92/O98)) | P99: =IF(P98<0,"NMF",IF(ABS(P92/P98)>1,"NMF",P92/P98)) | Q99: =IF(Q98<0,"NMF",IF(ABS(Q92/Q98)>1,"NMF",Q92/Q98)) | ... CA99: =IF(CA98<0,"NMF",IF(ABS(CA92/CA98)>1,"NMF",CA92/CA98))
A100: EBIT | C100: =INDEX(MO_RIS_Reported_OperatingIncome_NONGAAP,0,COLUMN()) | D100: =INDEX(MO_RIS_Reported_OperatingIncome_NONGAAP,0,COLUMN()) | E100: =INDEX(MO_RIS_Reported_OperatingIncome_NONGAAP,0,COLUMN()) | F100: =INDEX(MO_RIS_Reported_OperatingIncome_NONGAAP,0,COLUMN()) | G100: =INDEX(MO_RIS_Reported_OperatingIncome_NONGAAP,0,COLUMN()) | H100: =INDEX(MO_RIS_Reported_OperatingIncome_NONGAAP,0,COLUMN()) | I100: =INDEX(MO_RIS_Reported_OperatingIncome_NONGAAP,0,COLUMN()) | J100: =INDEX(MO_RIS_Reported_OperatingIncome_NONGAAP,0,COLUMN()) | ... CA100: =INDEX(MO_RIS_Reported_OperatingIncome_NONGAAP,0,COLUMN())
A101: LTM EBIT | C101: =C100 | D101: =D100 | E101: =E100 | F101: =F100 | J101: =SUM(J100,I100,H100,G100) | K101: =K100 | L101: =SUM(L100,J100,I100,H100) | M101: =SUM(M100,L100,J100,I100) | N101: =SUM(N100,M100,L100,J100) | O101: =SUM(O100,N100,M100,L100) | P101: =P100 | Q101: =SUM(Q100,O100,N100,M100) | R101: =SUM(R100,Q100,O100,N100) | S101: =SUM(S100,R100,Q100,O100) | T101: =SUM(T100,S100,R100,Q100) | U101: =U100 | V101: =SUM(V100,T100,S100,R100) | W101: =SUM(W100,V100,T100,S100) | X101: =SUM(X100,W100,V100,T100) | Y101: =SUM(Y100,X100,W100,V100) | Z101: =Z100 | AA101: =SUM(AA100,Y100,X100,W100) | AB101: =SUM(AB100,AA100,Y100,X100) | AC101: =SUM(AC100,AB100,AA100,Y100) | AD101: =SUM(AD100,AC100,AB100,AA100) | AE101: =AE100 | AF101: =SUM(AF100,AD100,AC100,AB100) | AG101: =SUM(AG100,AF100,AD100,AC100) | AH101: =SUM(AH100,AG100,AF100,AD100) | AI101: =SUM(AI100,AH100,AG100,AF100) | AJ101: =AJ100 | AK101: =SUM(AK100,AI100,AH100,AG100) | AL101: =SUM(AL100,AK100,AI100,AH100) | AM101: =SUM(AM100,AL100,AK100,AI100) | AN101: =SUM(AN100,AM100,AL100,AK100) | AO101: =AO100 | AP101: =SUM(AP100,AN100,AM100,AL100) | AQ101: =SUM(AQ100,AP100,AN100,AM100) | AR101: =SUM(AR100,AQ100,AP100,AN100) | AS101: =SUM(AS100,AR100,AQ100,AP100) | AT101: =AT100 | AU101: =SUM(AU100,AS100,AR100,AQ100) | AV101: =SUM(AV100,AU100,AS100,AR100) | AW101: =SUM(AW100,AV100,AU100,AS100) | AX101: =SUM(AX100,AW100,AV100,AU100) | AY101: =AY100 | AZ101: =SUM(AZ100,AX100,AW100,AV100) | BA101: =SUM(BA100,AZ100,AX100,AW100) | BB101: =SUM(BB100,BA100,AZ100,AX100) | BC101: =SUM(BC100,BB100,BA100,AZ100) | BD101: =BD100 | BE101: =SUM(BE100,BC100,BB100,BA100) | BF101: =SUM(BF100,BE100,BC100,BB100) | BG101: =SUM(BG100,BF100,BE100,BC100) | BH101: =SUM(BH100,BG100,BF100,BE100) | BI101: =BI100 | BJ101: =SUM(BJ100,BH100,BG100,BF100) | BK101: =SUM(BK100,BJ100,BH100,BG100) | BL101: =SUM(BL100,BK100,BJ100,BH100) | BM101: =SUM(BM100,BL100,BK100,BJ100) | BN101: =BN100 | BO101: =SUM(BO100,BM100,BL100,BK100) | BP101: =SUM(BP100,BO100,BM100,BL100) | BQ101: =SUM(BQ100,BP100,BO100,BM100) | BR101: =SUM(BR100,BQ100,BP100,BO100) | BS101: =BS100 | BT101: =SUM(BT100,BR100,BQ100,BP100) | BU101: =SUM(BU100,BT100,BR100,BQ100) | BV101: =SUM(BV100,BU100,BT100,BR100) | BW101: =SUM(BW100,BV100,BU100,BT100) | BX101: =BX100 | BY101: =BY100 | BZ101: =BZ100 | CA101: =CA100
A102: Current Liabilities | C102: =INDEX(MO_BS_CL,0,COLUMN()) | D102: =INDEX(MO_BS_CL,0,COLUMN()) | E102: =INDEX(MO_BS_CL,0,COLUMN()) | F102: =INDEX(MO_BS_CL,0,COLUMN()) | G102: =INDEX(MO_BS_CL,0,COLUMN()) | H102: =INDEX(MO_BS_CL,0,COLUMN()) | I102: =INDEX(MO_BS_CL,0,COLUMN()) | J102: =INDEX(MO_BS_CL,0,COLUMN()) | ... CA102: =INDEX(MO_BS_CL,0,COLUMN())
A103: Average Current Liabilities | C103: =C102 | D103: =AVERAGE(D102,C102) | E103: =AVERAGE(E102,D102) | F103: =AVERAGE(F102,E102) | J103: =AVERAGE(J102,I102,H102,G102) | K103: =AVERAGE(K102,F102) | L103: =AVERAGE(L102,J102,I102,H102) | M103: =AVERAGE(M102,L102,J102,I102) | N103: =AVERAGE(N102,M102,L102,J102) | O103: =AVERAGE(O102,N102,M102,L102) | P103: =AVERAGE(P102,K102) | Q103: =AVERAGE(Q102,O102,N102,M102) | R103: =AVERAGE(R102,Q102,O102,N102) | S103: =AVERAGE(S102,R102,Q102,O102) | T103: =AVERAGE(T102,S102,R102,Q102) | U103: =AVERAGE(U102,P102) | V103: =AVERAGE(V102,T102,S102,R102) | W103: =AVERAGE(W102,V102,T102,S102) | X103: =AVERAGE(X102,W102,V102,T102) | Y103: =AVERAGE(Y102,X102,W102,V102) | Z103: =AVERAGE(Z102,U102) | AA103: =AVERAGE(AA102,Y102,X102,W102) | AB103: =AVERAGE(AB102,AA102,Y102,X102) | AC103: =AVERAGE(AC102,AB102,AA102,Y102) | AD103: =AVERAGE(AD102,AC102,AB102,AA102) | AE103: =AVERAGE(AE102,Z102) | AF103: =AVERAGE(AF102,AD102,AC102,AB102) | AG103: =AVERAGE(AG102,AF102,AD102,AC102) | AH103: =AVERAGE(AH102,AG102,AF102,AD102) | AI103: =AVERAGE(AI102,AH102,AG102,AF102) | AJ103: =AVERAGE(AJ102,AE102) | AK103: =AVERAGE(AK102,AI102,AH102,AG102) | AL103: =AVERAGE(AL102,AK102,AI102,AH102) | AM103: =AVERAGE(AM102,AL102,AK102,AI102) | AN103: =AVERAGE(AN102,AM102,AL102,AK102) | AO103: =AVERAGE(AO102,AJ102) | AP103: =AVERAGE(AP102,AN102,AM102,AL102) | AQ103: =AVERAGE(AQ102,AP102,AN102,AM102) | AR103: =AVERAGE(AR102,AQ102,AP102,AN102) | AS103: =AVERAGE(AS102,AR102,AQ102,AP102) | AT103: =AVERAGE(AT102,AO102) | AU103: =AVERAGE(AU102,AS102,AR102,AQ102) | AV103: =AVERAGE(AV102,AU102,AS102,AR102) | AW103: =AVERAGE(AW102,AV102,AU102,AS102) | AX103: =AVERAGE(AX102,AW102,AV102,AU102) | AY103: =AVERAGE(AY102,AT102) | AZ103: =AVERAGE(AZ102,AX102,AW102,AV102) | BA103: =AVERAGE(BA102,AZ102,AX102,AW102) | BB103: =AVERAGE(BB102,BA102,AZ102,AX102) | BC103: =AVERAGE(BC102,BB102,BA102,AZ102) | BD103: =AVERAGE(BD102,AY102) | BE103: =AVERAGE(BE102,BC102,BB102,BA102) | BF103: =AVERAGE(BF102,BE102,BC102,BB102) | BG103: =AVERAGE(BG102,BF102,BE102,BC102) | BH103: =AVERAGE(BH102,BG102,BF102,BE102) | BI103: =AVERAGE(BI102,BD102) | BJ103: =AVERAGE(BJ102,BH102,BG102,BF102) | BK103: =AVERAGE(BK102,BJ102,BH102,BG102) | BL103: =AVERAGE(BL102,BK102,BJ102,BH102) | BM103: =AVERAGE(BM102,BL102,BK102,BJ102) | BN103: =AVERAGE(BN102,BI102) | BO103: =AVERAGE(BO102,BM102,BL102,BK102) | BP103: =AVERAGE(BP102,BO102,BM102,BL102) | BQ103: =AVERAGE(BQ102,BP102,BO102,BM102) | BR103: =AVERAGE(BR102,BQ102,BP102,BO102) | BS103: =AVERAGE(BS102,BN102) | BT103: =AVERAGE(BT102,BR102,BQ102,BP102) | BU103: =AVERAGE(BU102,BT102,BR102,BQ102) | BV103: =AVERAGE(BV102,BU102,BT102,BR102) | BW103: =AVERAGE(BW102,BV102,BU102,BT102) | BX103: =AVERAGE(BX102,BS102) | BY103: =AVERAGE(BY102,BX102) | BZ103: =AVERAGE(BZ102,BY102) | CA103: =AVERAGE(CA102,BZ102)
A104: Average Capital Employed | C104: =INDEX(SP_BSR_TA_Avg,0,COLUMN())-INDEX(SP_BSR_CL_Avg,0,COLUMN()) | D104: =INDEX(SP_BSR_TA_Avg,0,COLUMN())-INDEX(SP_BSR_CL_Avg,0,COLUMN()) | E104: =INDEX(SP_BSR_TA_Avg,0,COLUMN())-INDEX(SP_BSR_CL_Avg,0,COLUMN()) | F104: =INDEX(SP_BSR_TA_Avg,0,COLUMN())-INDEX(SP_BSR_CL_Avg,0,COLUMN()) | G104: =INDEX(SP_BSR_TA_Avg,0,COLUMN())-INDEX(SP_BSR_CL_Avg,0,COLUMN()) | H104: =INDEX(SP_BSR_TA_Avg,0,COLUMN())-INDEX(SP_BSR_CL_Avg,0,COLUMN()) | I104: =INDEX(SP_BSR_TA_Avg,0,COLUMN())-INDEX(SP_BSR_CL_Avg,0,COLUMN()) | J104: =INDEX(SP_BSR_TA_Avg,0,COLUMN())-INDEX(SP_BSR_CL_Avg,0,COLUMN()) | ... CA104: =INDEX(SP_BSR_TA_Avg,0,COLUMN())-INDEX(SP_BSR_CL_Avg,0,COLUMN())
A105: ROCE | C105: =IF(C104<0,"NMF",IF(ABS(C101/C104)>1,"NMF",C101/C104)) | D105: =IF(D104<0,"NMF",IF(ABS(D101/D104)>1,"NMF",D101/D104)) | E105: =IF(E104<0,"NMF",IF(ABS(E101/E104)>1,"NMF",E101/E104)) | F105: =IF(F104<0,"NMF",IF(ABS(F101/F104)>1,"NMF",F101/F104)) | J105: =IF(J104<0,"NMF",IF(ABS(J101/J104)>1,"NMF",J101/J104)) | K105: =IF(K104<0,"NMF",IF(ABS(K101/K104)>1,"NMF",K101/K104)) | L105: =IF(L104<0,"NMF",IF(ABS(L101/L104)>1,"NMF",L101/L104)) | M105: =IF(M104<0,"NMF",IF(ABS(M101/M104)>1,"NMF",M101/M104)) | N105: =IF(N104<0,"NMF",IF(ABS(N101/N104)>1,"NMF",N101/N104)) | O105: =IF(O104<0,"NMF",IF(ABS(O101/O104)>1,"NMF",O101/O104)) | P105: =IF(P104<0,"NMF",IF(ABS(P101/P104)>1,"NMF",P101/P104)) | Q105: =IF(Q104<0,"NMF",IF(ABS(Q101/Q104)>1,"NMF",Q101/Q104)) | ... CA105: =IF(CA104<0,"NMF",IF(ABS(CA101/CA104)>1,"NMF",CA101/CA104))
A107: Per-Share Growth Metrics
A108: Revenue Per Share Growth | D108: =IF(OR(INDEX(SP_GF_Rev,0,COLUMN())<=0,C23<=0),"NMF",IF(ABS((INDEX(SP_GF_Rev,0,COLUMN())/INDEX(SP_GF_ShareCount,0,COLUMN()))/(C23/C42)-1)>10,"NMF",(INDEX(SP_GF_Rev,0,COLUMN())/INDEX(SP_GF_ShareCount,0,COLUMN()))/(C23/C42)-1)) | E108: =IF(OR(INDEX(SP_GF_Rev,0,COLUMN())<=0,D23<=0),"NMF",IF(ABS((INDEX(SP_GF_Rev,0,COLUMN())/INDEX(SP_GF_ShareCount,0,COLUMN()))/(D23/D42)-1)>10,"NMF",(INDEX(SP_GF_Rev,0,COLUMN())/INDEX(SP_GF_ShareCount,0,COLUMN()))/(D23/D42)-1)) | F108: =IF(OR(INDEX(SP_GF_Rev,0,COLUMN())<=0,E23<=0),"NMF",IF(ABS((INDEX(SP_GF_Rev,0,COLUMN())/INDEX(SP_GF_ShareCount,0,COLUMN()))/(E23/E42)-1)>10,"NMF",(INDEX(SP_GF_Rev,0,COLUMN())/INDEX(SP_GF_ShareCount,0,COLUMN()))/(E23/E42)-1)) | K108: =IF(OR(INDEX(SP_GF_Rev,0,COLUMN())<=0,F23<=0),"NMF",IF(ABS((INDEX(SP_GF_Rev,0,COLUMN())/INDEX(SP_GF_ShareCount,0,COLUMN()))/(F23/F42)-1)>10,"NMF",(INDEX(SP_GF_Rev,0,COLUMN())/INDEX(SP_GF_ShareCount,0,COLUMN()))/(F23/F42)-1)) | L108: =IF(OR(INDEX(SP_GF_Rev,0,COLUMN())<=0,G23<=0),"NMF",IF(ABS((INDEX(SP_GF_Rev,0,COLUMN())/INDEX(SP_GF_ShareCount,0,COLUMN()))/(G23/G42)-1)>10,"NMF",(INDEX(SP_GF_Rev,0,COLUMN())/INDEX(SP_GF_ShareCount,0,COLUMN()))/(G23/G42)-1)) | M108: =IF(OR(INDEX(SP_GF_Rev,0,COLUMN())<=0,H23<=0),"NMF",IF(ABS((INDEX(SP_GF_Rev,0,COLUMN())/INDEX(SP_GF_ShareCount,0,COLUMN()))/(H23/H42)-1)>10,"NMF",(INDEX(SP_GF_Rev,0,COLUMN())/INDEX(SP_GF_ShareCount,0,COLUMN()))/(H23/H42)-1)) | N108: =IF(OR(INDEX(SP_GF_Rev,0,COLUMN())<=0,I23<=0),"NMF",IF(ABS((INDEX(SP_GF_Rev,0,COLUMN())/INDEX(SP_GF_ShareCount,0,COLUMN()))/(I23/I42)-1)>10,"NMF",(INDEX(SP_GF_Rev,0,COLUMN())/INDEX(SP_GF_ShareCount,0,COLUMN()))/(I23/I42)-1)) | O108: =IF(OR(INDEX(SP_GF_Rev,0,COLUMN())<=0,J23<=0),"NMF",IF(ABS((INDEX(SP_GF_Rev,0,COLUMN())/INDEX(SP_GF_ShareCount,0,COLUMN()))/(J23/J42)-1)>10,"NMF",(INDEX(SP_GF_Rev,0,COLUMN())/INDEX(SP_GF_ShareCount,0,COLUMN()))/(J23/J42)-1)) | P108: =IF(OR(INDEX(SP_GF_Rev,0,COLUMN())<=0,K23<=0),"NMF",IF(ABS((INDEX(SP_GF_Rev,0,COLUMN())/INDEX(SP_GF_ShareCount,0,COLUMN()))/(K23/K42)-1)>10,"NMF",(INDEX(SP_GF_Rev,0,COLUMN())/INDEX(SP_GF_ShareCount,0,COLUMN()))/(K23/K42)-1)) | Q108: =IF(OR(INDEX(SP_GF_Rev,0,COLUMN())<=0,L23<=0),"NMF",IF(ABS((INDEX(SP_GF_Rev,0,COLUMN())/INDEX(SP_GF_ShareCount,0,COLUMN()))/(L23/L42)-1)>10,"NMF",(INDEX(SP_GF_Rev,0,COLUMN())/INDEX(SP_GF_ShareCount,0,COLUMN()))/(L23/L42)-1)) | R108: =IF(OR(INDEX(SP_GF_Rev,0,COLUMN())<=0,M23<=0),"NMF",IF(ABS((INDEX(SP_GF_Rev,0,COLUMN())/INDEX(SP_GF_ShareCount,0,COLUMN()))/(M23/M42)-1)>10,"NMF",(INDEX(SP_GF_Rev,0,COLUMN())/INDEX(SP_GF_ShareCount,0,COLUMN()))/(M23/M42)-1)) | ... BX108: =IF(OR(INDEX(SP_GF_Rev,0,COLUMN())<=0,BS23<=0),"NMF",IF(ABS((INDEX(SP_GF_Rev,0,COLUMN())/INDEX(SP_GF_ShareCount,0,COLUMN()))/(BS23/BS42)-1)>10,"NMF",(INDEX(SP_GF_Rev,0,COLUMN())/INDEX(SP_GF_ShareCount,0,COLUMN()))/(BS23/BS42)-1)) | BY108: =IF(OR(INDEX(SP_GF_Rev,0,COLUMN())<=0,BX23<=0),"NMF",IF(ABS((INDEX(SP_GF_Rev,0,COLUMN())/INDEX(SP_GF_ShareCount,0,COLUMN()))/(BX23/BX42)-1)>10,"NMF",(INDEX(SP_GF_Rev,0,COLUMN())/INDEX(SP_GF_ShareCount,0,COLUMN()))/(BX23/BX42)-1)) | BZ108: =IF(OR(INDEX(SP_GF_Rev,0,COLUMN())<=0,BY23<=0),"NMF",IF(ABS((INDEX(SP_GF_Rev,0,COLUMN())/INDEX(SP_GF_ShareCount,0,COLUMN()))/(BY23/BY42)-1)>10,"NMF",(INDEX(SP_GF_Rev,0,COLUMN())/INDEX(SP_GF_ShareCount,0,COLUMN()))/(BY23/BY42)-1)) | CA108: =IF(OR(INDEX(SP_GF_Rev,0,COLUMN())<=0,BZ23<=0),"NMF",IF(ABS((INDEX(SP_GF_Rev,0,COLUMN())/INDEX(SP_GF_ShareCount,0,COLUMN()))/(BZ23/BZ42)-1)>10,"NMF",(INDEX(SP_GF_Rev,0,COLUMN())/INDEX(SP_GF_ShareCount,0,COLUMN()))/(BZ23/BZ42)-1))
A109: Adj. EBITDA Per Share Growth | D109: =IF(OR(INDEX(SP_NGF_EBITDA,0,COLUMN())<=0,C45<=0),"NMF",IF(ABS((INDEX(SP_NGF_EBITDA,0,COLUMN())/INDEX(SP_GF_ShareCount,0,COLUMN()))/(C45/C42)-1)>10,"NMF",(INDEX(SP_NGF_EBITDA,0,COLUMN())/INDEX(SP_GF_ShareCount,0,COLUMN()))/(C45/C42)-1)) | E109: =IF(OR(INDEX(SP_NGF_EBITDA,0,COLUMN())<=0,D45<=0),"NMF",IF(ABS((INDEX(SP_NGF_EBITDA,0,COLUMN())/INDEX(SP_GF_ShareCount,0,COLUMN()))/(D45/D42)-1)>10,"NMF",(INDEX(SP_NGF_EBITDA,0,COLUMN())/INDEX(SP_GF_ShareCount,0,COLUMN()))/(D45/D42)-1)) | F109: =IF(OR(INDEX(SP_NGF_EBITDA,0,COLUMN())<=0,E45<=0),"NMF",IF(ABS((INDEX(SP_NGF_EBITDA,0,COLUMN())/INDEX(SP_GF_ShareCount,0,COLUMN()))/(E45/E42)-1)>10,"NMF",(INDEX(SP_NGF_EBITDA,0,COLUMN())/INDEX(SP_GF_ShareCount,0,COLUMN()))/(E45/E42)-1)) | K109: =IF(OR(INDEX(SP_NGF_EBITDA,0,COLUMN())<=0,F45<=0),"NMF",IF(ABS((INDEX(SP_NGF_EBITDA,0,COLUMN())/INDEX(SP_GF_ShareCount,0,COLUMN()))/(F45/F42)-1)>10,"NMF",(INDEX(SP_NGF_EBITDA,0,COLUMN())/INDEX(SP_GF_ShareCount,0,COLUMN()))/(F45/F42)-1)) | L109: =IF(OR(INDEX(SP_NGF_EBITDA,0,COLUMN())<=0,G45<=0),"NMF",IF(ABS((INDEX(SP_NGF_EBITDA,0,COLUMN())/INDEX(SP_GF_ShareCount,0,COLUMN()))/(G45/G42)-1)>10,"NMF",(INDEX(SP_NGF_EBITDA,0,COLUMN())/INDEX(SP_GF_ShareCount,0,COLUMN()))/(G45/G42)-1)) | M109: =IF(OR(INDEX(SP_NGF_EBITDA,0,COLUMN())<=0,H45<=0),"NMF",IF(ABS((INDEX(SP_NGF_EBITDA,0,COLUMN())/INDEX(SP_GF_ShareCount,0,COLUMN()))/(H45/H42)-1)>10,"NMF",(INDEX(SP_NGF_EBITDA,0,COLUMN())/INDEX(SP_GF_ShareCount,0,COLUMN()))/(H45/H42)-1)) | N109: =IF(OR(INDEX(SP_NGF_EBITDA,0,COLUMN())<=0,I45<=0),"NMF",IF(ABS((INDEX(SP_NGF_EBITDA,0,COLUMN())/INDEX(SP_GF_ShareCount,0,COLUMN()))/(I45/I42)-1)>10,"NMF",(INDEX(SP_NGF_EBITDA,0,COLUMN())/INDEX(SP_GF_ShareCount,0,COLUMN()))/(I45/I42)-1)) | O109: =IF(OR(INDEX(SP_NGF_EBITDA,0,COLUMN())<=0,J45<=0),"NMF",IF(ABS((INDEX(SP_NGF_EBITDA,0,COLUMN())/INDEX(SP_GF_ShareCount,0,COLUMN()))/(J45/J42)-1)>10,"NMF",(INDEX(SP_NGF_EBITDA,0,COLUMN())/INDEX(SP_GF_ShareCount,0,COLUMN()))/(J45/J42)-1)) | P109: =IF(OR(INDEX(SP_NGF_EBITDA,0,COLUMN())<=0,K45<=0),"NMF",IF(ABS((INDEX(SP_NGF_EBITDA,0,COLUMN())/INDEX(SP_GF_ShareCount,0,COLUMN()))/(K45/K42)-1)>10,"NMF",(INDEX(SP_NGF_EBITDA,0,COLUMN())/INDEX(SP_GF_ShareCount,0,COLUMN()))/(K45/K42)-1)) | Q109: =IF(OR(INDEX(SP_NGF_EBITDA,0,COLUMN())<=0,L45<=0),"NMF",IF(ABS((INDEX(SP_NGF_EBITDA,0,COLUMN())/INDEX(SP_GF_ShareCount,0,COLUMN()))/(L45/L42)-1)>10,"NMF",(INDEX(SP_NGF_EBITDA,0,COLUMN())/INDEX(SP_GF_ShareCount,0,COLUMN()))/(L45/L42)-1)) | R109: =IF(OR(INDEX(SP_NGF_EBITDA,0,COLUMN())<=0,M45<=0),"NMF",IF(ABS((INDEX(SP_NGF_EBITDA,0,COLUMN())/INDEX(SP_GF_ShareCount,0,COLUMN()))/(M45/M42)-1)>10,"NMF",(INDEX(SP_NGF_EBITDA,0,COLUMN())/INDEX(SP_GF_ShareCount,0,COLUMN()))/(M45/M42)-1)) | ... BX109: =IF(OR(INDEX(SP_NGF_EBITDA,0,COLUMN())<=0,BS45<=0),"NMF",IF(ABS((INDEX(SP_NGF_EBITDA,0,COLUMN())/INDEX(SP_GF_ShareCount,0,COLUMN()))/(BS45/BS42)-1)>10,"NMF",(INDEX(SP_NGF_EBITDA,0,COLUMN())/INDEX(SP_GF_ShareCount,0,COLUMN()))/(BS45/BS42)-1)) | BY109: =IF(OR(INDEX(SP_NGF_EBITDA,0,COLUMN())<=0,BX45<=0),"NMF",IF(ABS((INDEX(SP_NGF_EBITDA,0,COLUMN())/INDEX(SP_GF_ShareCount,0,COLUMN()))/(BX45/BX42)-1)>10,"NMF",(INDEX(SP_NGF_EBITDA,0,COLUMN())/INDEX(SP_GF_ShareCount,0,COLUMN()))/(BX45/BX42)-1)) | BZ109: =IF(OR(INDEX(SP_NGF_EBITDA,0,COLUMN())<=0,BY45<=0),"NMF",IF(ABS((INDEX(SP_NGF_EBITDA,0,COLUMN())/INDEX(SP_GF_ShareCount,0,COLUMN()))/(BY45/BY42)-1)>10,"NMF",(INDEX(SP_NGF_EBITDA,0,COLUMN())/INDEX(SP_GF_ShareCount,0,COLUMN()))/(BY45/BY42)-1)) | CA109: =IF(OR(INDEX(SP_NGF_EBITDA,0,COLUMN())<=0,BZ45<=0),"NMF",IF(ABS((INDEX(SP_NGF_EBITDA,0,COLUMN())/INDEX(SP_GF_ShareCount,0,COLUMN()))/(BZ45/BZ42)-1)>10,"NMF",(INDEX(SP_NGF_EBITDA,0,COLUMN())/INDEX(SP_GF_ShareCount,0,COLUMN()))/(BZ45/BZ42)-1))
A110: Adj. Earnings Per Share Growth | D110: =IF(OR(INDEX(SP_NGF_NI,0,COLUMN())<=0,C46<=0),"NMF",IF(ABS((INDEX(SP_NGF_NI,0,COLUMN())/INDEX(SP_GF_ShareCount,0,COLUMN()))/(C46/C42)-1)>10,"NMF",(INDEX(SP_NGF_NI,0,COLUMN())/INDEX(SP_GF_ShareCount,0,COLUMN()))/(C46/C42)-1)) | E110: =IF(OR(INDEX(SP_NGF_NI,0,COLUMN())<=0,D46<=0),"NMF",IF(ABS((INDEX(SP_NGF_NI,0,COLUMN())/INDEX(SP_GF_ShareCount,0,COLUMN()))/(D46/D42)-1)>10,"NMF",(INDEX(SP_NGF_NI,0,COLUMN())/INDEX(SP_GF_ShareCount,0,COLUMN()))/(D46/D42)-1)) | F110: =IF(OR(INDEX(SP_NGF_NI,0,COLUMN())<=0,E46<=0),"NMF",IF(ABS((INDEX(SP_NGF_NI,0,COLUMN())/INDEX(SP_GF_ShareCount,0,COLUMN()))/(E46/E42)-1)>10,"NMF",(INDEX(SP_NGF_NI,0,COLUMN())/INDEX(SP_GF_ShareCount,0,COLUMN()))/(E46/E42)-1)) | K110: =IF(OR(INDEX(SP_NGF_NI,0,COLUMN())<=0,F46<=0),"NMF",IF(ABS((INDEX(SP_NGF_NI,0,COLUMN())/INDEX(SP_GF_ShareCount,0,COLUMN()))/(F46/F42)-1)>10,"NMF",(INDEX(SP_NGF_NI,0,COLUMN())/INDEX(SP_GF_ShareCount,0,COLUMN()))/(F46/F42)-1)) | L110: =IF(OR(INDEX(SP_NGF_NI,0,COLUMN())<=0,G46<=0),"NMF",IF(ABS((INDEX(SP_NGF_NI,0,COLUMN())/INDEX(SP_GF_ShareCount,0,COLUMN()))/(G46/G42)-1)>10,"NMF",(INDEX(SP_NGF_NI,0,COLUMN())/INDEX(SP_GF_ShareCount,0,COLUMN()))/(G46/G42)-1)) | M110: =IF(OR(INDEX(SP_NGF_NI,0,COLUMN())<=0,H46<=0),"NMF",IF(ABS((INDEX(SP_NGF_NI,0,COLUMN())/INDEX(SP_GF_ShareCount,0,COLUMN()))/(H46/H42)-1)>10,"NMF",(INDEX(SP_NGF_NI,0,COLUMN())/INDEX(SP_GF_ShareCount,0,COLUMN()))/(H46/H42)-1)) | N110: =IF(OR(INDEX(SP_NGF_NI,0,COLUMN())<=0,I46<=0),"NMF",IF(ABS((INDEX(SP_NGF_NI,0,COLUMN())/INDEX(SP_GF_ShareCount,0,COLUMN()))/(I46/I42)-1)>10,"NMF",(INDEX(SP_NGF_NI,0,COLUMN())/INDEX(SP_GF_ShareCount,0,COLUMN()))/(I46/I42)-1)) | O110: =IF(OR(INDEX(SP_NGF_NI,0,COLUMN())<=0,J46<=0),"NMF",IF(ABS((INDEX(SP_NGF_NI,0,COLUMN())/INDEX(SP_GF_ShareCount,0,COLUMN()))/(J46/J42)-1)>10,"NMF",(INDEX(SP_NGF_NI,0,COLUMN())/INDEX(SP_GF_ShareCount,0,COLUMN()))/(J46/J42)-1)) | P110: =IF(OR(INDEX(SP_NGF_NI,0,COLUMN())<=0,K46<=0),"NMF",IF(ABS((INDEX(SP_NGF_NI,0,COLUMN())/INDEX(SP_GF_ShareCount,0,COLUMN()))/(K46/K42)-1)>10,"NMF",(INDEX(SP_NGF_NI,0,COLUMN())/INDEX(SP_GF_ShareCount,0,COLUMN()))/(K46/K42)-1)) | Q110: =IF(OR(INDEX(SP_NGF_NI,0,COLUMN())<=0,L46<=0),"NMF",IF(ABS((INDEX(SP_NGF_NI,0,COLUMN())/INDEX(SP_GF_ShareCount,0,COLUMN()))/(L46/L42)-1)>10,"NMF",(INDEX(SP_NGF_NI,0,COLUMN())/INDEX(SP_GF_ShareCount,0,COLUMN()))/(L46/L42)-1)) | R110: =IF(OR(INDEX(SP_NGF_NI,0,COLUMN())<=0,M46<=0),"NMF",IF(ABS((INDEX(SP_NGF_NI,0,COLUMN())/INDEX(SP_GF_ShareCount,0,COLUMN()))/(M46/M42)-1)>10,"NMF",(INDEX(SP_NGF_NI,0,COLUMN())/INDEX(SP_GF_ShareCount,0,COLUMN()))/(M46/M42)-1)) | ... BX110: =IF(OR(INDEX(SP_NGF_NI,0,COLUMN())<=0,BS46<=0),"NMF",IF(ABS((INDEX(SP_NGF_NI,0,COLUMN())/INDEX(SP_GF_ShareCount,0,COLUMN()))/(BS46/BS42)-1)>10,"NMF",(INDEX(SP_NGF_NI,0,COLUMN())/INDEX(SP_GF_ShareCount,0,COLUMN()))/(BS46/BS42)-1)) | BY110: =IF(OR(INDEX(SP_NGF_NI,0,COLUMN())<=0,BX46<=0),"NMF",IF(ABS((INDEX(SP_NGF_NI,0,COLUMN())/INDEX(SP_GF_ShareCount,0,COLUMN()))/(BX46/BX42)-1)>10,"NMF",(INDEX(SP_NGF_NI,0,COLUMN())/INDEX(SP_GF_ShareCount,0,COLUMN()))/(BX46/BX42)-1)) | BZ110: =IF(OR(INDEX(SP_NGF_NI,0,COLUMN())<=0,BY46<=0),"NMF",IF(ABS((INDEX(SP_NGF_NI,0,COLUMN())/INDEX(SP_GF_ShareCount,0,COLUMN()))/(BY46/BY42)-1)>10,"NMF",(INDEX(SP_NGF_NI,0,COLUMN())/INDEX(SP_GF_ShareCount,0,COLUMN()))/(BY46/BY42)-1)) | CA110: =IF(OR(INDEX(SP_NGF_NI,0,COLUMN())<=0,BZ46<=0),"NMF",IF(ABS((INDEX(SP_NGF_NI,0,COLUMN())/INDEX(SP_GF_ShareCount,0,COLUMN()))/(BZ46/BZ42)-1)>10,"NMF",(INDEX(SP_NGF_NI,0,COLUMN())/INDEX(SP_GF_ShareCount,0,COLUMN()))/(BZ46/BZ42)-1))
...

Sheet Update Log
E7: =MO.MRFPColumnNumber | F7: =MO.MRFP | H7: =AA.CSIN
H8: =+AA.ModelVersion
C10: Update Date | D10: Updated By (Initials) | E10: Update Type | F10: Most Recent Period | G10: Special Comments | H10: Link to Press Release / News Item
C11: 45959 | D11: AN | E11: Quarterly (Earnings Report) | F11: Q3-2025 | H11: Earnings Press Release
C12: 45957 | D12: TP | E12: Initial (Press Release) | F12: Q3-2025 | H12: Earnings Press Release
C13: 45868 | D13: AN | E13: Quarterly (Earnings Report) | F13: Q2-2025 | H13: Earnings Press Release
C14: 45866 | D14: AN | E14: Initial (Press Release) | F14: Q2-2025 | H14: Earnings Press Release
C15: 45777 | D15: AR | E15: Quarterly (Earnings Report) | F15: Q1-2025 | H15: Earnings Press Release
C16: 45775 | D16: BL | E16: Initial (Press Release) | F16: Q1-2025 | H16: Earnings Press Release
C17: 45709 | D17: WW | E17: Annual (Earnings Report) | F17: FY2024 | H17: Earnings Press Release
C18: 45706 | D18: CZ | E18: Initial (Press Release) | F18: FY2024 | H18: Earnings Press Release
C19: 45595 | D19: KS | E19: Quarterly (Earnings Report) | F19: Q3-2024 | H19: Earnings Press Release
C20: 45593 | D20: ALT | E20: Initial (Press Release) | F20: Q3-2024 | H20: Earnings Press Release
C21: 45497 | D21: AA | E21: Quarterly (Earnings Report) | F21: Q2-2024 | H21: Earnings Press Release
C22: 45495 | D22: HS | E22: Initial (Press Release) | F22: Q2-2024 | H22: Earnings Press Release
... C45: 43873 | D45: LZ | E45: Initial (Press Release) | F45: FY2019 | H45: Earnings Press Release
C46: 43801 | D46: AW | E46: Model Improvement | F46: Q3-2019 | G46: Y/Y Cost Granularity
C47: 43759 | D47: AW AP | E47: Quarterly (Earnings Report) | F47: Q3-2019 | H47: Earnings Press Release
C48: 43668 | D48: HS | E48: Quarterly (Earnings Report) | F48: Q2-2019 | H48: Earnings Press Release
C49: 43668 | D49: LZ | E49: Initial (Press Release) | F49: Q2-2019 | H49: Earnings Press Release
