Workbook
Name AA.AlternatePriceSourceStartPeriod: "Q1-2019"
Name AA.CIK: "1045810"
Name AA.ColorizerVersion: "2.0.4.0"
Name AA.CompareQuarters.LatestMRQ: "Q2-2025"
Name AA.CSIN: "A7FLSL0150"
Name AA.CurationVersion: "2023.11.1.0"
Name AA.DBMacroVersion: "1.0.13.0"
Name AA.FreeCashFlow: "TRUE"
Name AA.GuidanceAnalysisNonGaapGrossProfitVersion: "1.0.0.0"
Name AA.GuidanceAnalysisRevenueVersion: "1.0.0.0"
Name AA.HardcodeChecker.LatestMRQ: "Q3-2020"
Name AA.ModelChecks.LatestMRQ: "Q3-2022"
Name AA.ModelChecks.LatestVersionNumber: "2.38.25.0"
Name AA.ModelColorScheme: "Classic"
Name AA.ModelVersion: "Q3-2026.20"
Name AA.NonLibraryWideCurationVersion: "4"
Name AA.PartialUpdate.BsAvailable: "TRUE"
Name AA.PartialUpdate.CfsAvailable: "TRUE"
Name AA.PartialUpdate.IsAvailable: "TRUE"
Name AA.PeriodLayout: "QFY"
Name AA.PersonalMacro.VersionNumber: ""
Name AA.RowNameEnforcerVersion: "2023.11.1.0"
Name AA.SessionToUploadId: ""
Name AA.StartWorkModelVersion: "Q2-2026.22"
Name AA.StartWorkType: ""
Name AA.SubyearType: "Q"
Name AA.TemplateUpgradeAttempted: "TRUE"
Name AA.TemplateVersion: "7.5.4.0"
Name AA.UpdateType: "Regular"
Name AA.VerifyUnitsAtModelVersion: "Q2-2019.21"
Name EC_CEO_BasePay: 'Exec Comp'!$7:$7
Name EC_CEO_EquityComp_Percent: 'Exec Comp'!$12:$12
Name EC_CEO_SharesOwned: 'Exec Comp'!$38:$38
Name EC_CEO_TotalComp: 'Exec Comp'!$11:$11
Name EC_CFO_BasePay: 'Exec Comp'!$40:$40
Name EC_CFO_EquityComp_Percent: 'Exec Comp'!$45:$45
Name EC_CFO_SharesOwned: 'Exec Comp'!$49:$49
Name EC_CFO_TotalComp: 'Exec Comp'!$44:$44
Name EC_Director_Compensation_Cash: 'Exec Comp'!$74:$74
Name EC_Director_Compensation_Total: 'Exec Comp'!$103:$103
Name EC_Directors_Current: 'Exec Comp'!$52:$52
Name EC_Directors_Current_Diverse: 'Exec Comp'!$55:$55
Name EC_Directors_Current_Female: 'Exec Comp'!$54:$54
Name EC_Directors_Current_Independent: 'Exec Comp'!$53:$53
Name EC_Directors_Nominees: 'Exec Comp'!$57:$57
Name EC_Directors_Nominees_Independent: 'Exec Comp'!$58:$58
Name EC_OperatingIncome_Target_NONGAAP: 'Exec Comp'!$118:$118
Name EC_Revenue_Target: 'Exec Comp'!$113:$113
Name FP_Comment: 'Front Page'!$M$13:$P$20
Name FP_StockPriceOverride: 'Front Page'!$C$20:$H$20
Name FP.DataSource: 'Front Page'!$H$16
Name FP.DataSourceName: 'Front Page'!$H$15
Name FP.Disclaimer: 'Front Page'!$C$22
Name FP.LastPrice: 'Front Page'!$H$20
Name FP.LastPriceDate: 'Front Page'!$F$20
Name FP.RealTimeToggle: 'Front Page'!$H$18
Name FP.UpdateDate: 'Front Page'!$H$11
Name FP.UpdateEvent: 'Front Page'!$H$13
Name GD_Difference_Mid_Absolute: Guidance!$P:$P
Name GD_Difference_Mid_Relative: Guidance!$Q:$Q

Sheet Front Page
M6: Please contact this email for any model-specific questions:
M7: modelsupport@alpha-sense.com | N7: mailto:support@canalyst.com?subject=Canalyst%20Support:%20NVIDIA%20Corporation%20NVDA%20US&body=Model%20Version:%20Q1-2020.20 | O7: mailto:support@canalyst.com?subject=Canalyst%20Support:%20NVIDIA%20Corporation%20NVDA%20US&body=Model%20Version:%20Q1-2020.20
C9: Company Model: | H9: =Model!A1
C11: Updated: | H11: =OFFSET('Update Log'!$C$10,1,0,1,1)
M12: Comments on Model:
C13: For: | H13: =OFFSET('Update Log'!$E$10,1,0,1,1) | M13: On August 26, 2024, the Board of Directors approved an additional $50.0 billion in share repurchase authorization, without expiration. 'On, May 21, 2021, The company announced a 4-for-1 stock split. The model was adjusted for the split on July 20, 2021' 'Starting with the first quarter of fiscal 2021, the company's reportable segments have changed to “Graphics” and “Compute & Networking.” During the third quarter, NVIDIA announced a definitive agreement to acquire Arm Limited from SoftBank Capital Limited and SVF Holdco (UK) Limited in a transaction valued at $40 billion. The transaction -- which is expected to be immediately accretive to NVIDIA’s non-GAAP gross margin and non-GAAP earnings per share -- is expected to close in the first quarter of calendar 2022.
C15: Consensus Data and Real-Time Stock Price: | H15: Bloomberg
H16: =IF(FP.DataSourceName="Bloomberg",1,IF(FP.DataSourceName="Capital IQ",2,IF(FP.DataSourceName="FactSet",3,IF(FP.DataSourceName="Refinitiv",4))))
C18: Real-Time Stock Price: | H18: OFF
C20: Stock Price Override: | F20: 45979 | H20: 181.36
C22: DISCLAIMER Access to and use of this model, including the data contained herein (this "Model") is subject to Tegus, Inc.'s (a successor entity to Canalyst Financial Modeling Corporation) ("Company") Terms of Use that you accepted prior to accessing this Model, the applicable Service Agreement between the Company and you (or a corporate entity that has authorized you to access and use this Model on its behalf in accordance with the terms of such Service Agreement) or other similar agreement between you and the Company. BY CONTINUING TO ACCESS OR USE THIS MODEL, YOU EXPRESSLY AGREE TO THE TERMS AND CONDITIONS OF SUCH AGREEMENTS. The Company and certain of its licensors have exclusive proprietary rights in this Model. This Model is being provided for internal use only. Unless prior written consent by the Company and its licensors has been provided to you, you may not distribute or otherwise furnish this Model to any third party, nor use or permit anyone to use this Model for any unlawful or unauthorized purpose. IF YOU HAVE UNLAWFULLY OBTAINED, OR ARE NOT AUTHORIZED TO USE THIS MODEL, YOU ARE OBLIGATED TO PROMPTLY: (I) RETURN THIS MODEL (AND ANY DERIVATIVE WORKS ARISING FROM OR RELATING THERETO) TO THE AUTHORIZED USER OF THIS MODEL; (II) PROVIDE NOTICE TO THE COMPANY AT LEGAL@TEGUS.COM OF SUCH UNLAWFUL OR UNAUTHORIZED ACCESS AND USE; AND, (III) CERTIFY THAT YOU HAVE DESTROYED THIS MODEL (AND ANY DERIVATIVE WORKS ARISING FROM OR RELATING THERETO) AND ANY COPIES FROM YOUR SYSTEMS SO AS TO ENSURE THEY ARE INCAPABLE OF RETRIEVAL. A portion of the data contained in this Model may be powered by third party contributors and their respective licensors, or derived from data provided by such contributors, including (but not limited to): (i) QuoteMedia Inc.: A portion of the market data is powered by Quotemedia.com. All rights reserved. Data delayed 15 minutes unless otherwise indicated; (ii) S&P Global Market Intelligence LLC: Copyright (c) {{YEAR}} S&P Global Market Intelligence LLC (and its affiliates as applicable). All rights reserved. Reproduction of any information, opinions, views, data or material, including ratings ("Content") in any form is prohibited except with the prior written permission of the relevant party. Such party, its affiliates and suppliers ("Content Providers") do not guarantee the accuracy, adequacy, completeness, timeliness or availability of any Content and are not responsible for any errors or omissions (negligent or otherwise), regardless of the cause, or for the results obtained from the use of such Content. In no event shall Content Providers be liable for any damages, costs, expenses, legal fees, or losses (including lost income or lost profit and opportunity costs) in connection with any use of the Content. A reference to a particular investment or security, a rating or any observation concerning an investment that is part of the Content is not a recommendation to buy, sell or hold such investment or security, does not address the suitability of an investment or security and should not be relied on as investment advice. Credit ratings are statements of opinions and are not statements of fact; and, (iii) Refinitiv Canada Holdings Limited: A portion of the information may be provided by or derived from data provided by Refinitiv. By accessing or using this Model (including any portion of the data contained herein) you expressly represent that such access or use does not constitute a violation of any applicable law or regulation to which you or the securities are subject. This Model does not constitute investment advice by the Company or any of its licensors. Reference to a particular investment or security, credit rating or any observation concerning a security or investment in this Model is not a recommendation or solicitation to buy, sell or hold such investment or security or make any other investment decisions. For greater certainty, any forecasts or forward-looking information expressed herein are for illustrative purposes only and do not purport to express any view on what may transpire. Neither the Company nor any of its licensors have performed company-specific research on any projected information, as such, it is your responsibility to express your own views on projected results. This Model does not guarantee future performance and undue reliance should not be placed on such. You are solely responsible for evaluating the merits and risks of any investment based on your own business and financial expertise, the business and financial expertise of professional advisors with whom you have consulted, your financial situation and risk tolerance. Neither the Company, nor any of its licensors, undertake any liability with respect to your reliance on this Model. This Model is a quantitative tool with no investment views. The Company and its respective directors, officers, employees, agents, contractors, and affiliates may hold long or short positions in the security to which this Model relates, based on their personal views, and may initiate or close out any positions in such security at any time without any notice. THIS MODEL IS PROVIDED "AS IS" AND ON AN "AS AVAILABLE" BASIS ONLY, WITHOUT WARRANTIES OR CONDITIONS OF ANY KIND. NEITHER THE COMPANY NOR ANY OF ITS LICENSORS NOR THEIR RESPECTIVE AFFILIATES OR SUPPLIERS HAVE LIABILITY FOR THE ACCURACY, TIMELINESS OR COMPLETENESS OF THIS MODEL, OR FOR DELAYS, INTERRUPTIONS OR OMISSIONS HEREIN, NOR FOR ANY LOST PROFITS, INDIRECT, SPECIAL OR CONSEQUENTIAL DAMAGES. Access to data in this Model that is sourced from third party contributors is subject to termination in the event that any agreement between the Company and such third party contributors terminates for any reason. Copyright 2023 Tegus. All rights reserved.

Sheet Multiples
A1: NVIDIA — MULTIPLES-BASED VALUATION
A3: Period | F3: TTM | G3: NTM | H3: FY2027 | I3: FY2028 | J3: FY2029
A5: FINANCIAL METRICS
A6: Revenue ($M) | F6: =Model!BS34 | G6: =Model!BX34 | H6: =Model!CC34 | I6: =Model!CD34 | J6: =Model!CE34
A7: Operating Income / EBIT ($M) | F7: =Model!BS386 | G7: =Model!BX386 | H7: =Model!CC386 | I7: =Model!CD386 | J7: =Model!CE386
A8: EBITDA ($M) | F8: =Model!BS392 | G8: =Model!BX392 | H8: =Model!CC392 | I8: =Model!CD392 | J8: =Model!CE392
A9: Shares Outstanding (M) | F9: =Model!BS429 | G9: =Model!BS429 | H9: =Model!BS429 | I9: =Model!BS429 | J9: =Model!BS429
A10: Current Stock Price ($) | F10: =Model!'Front Page'!H20 | G10: =Model!'Front Page'!H20 | H10: =Model!'Front Page'!H20 | I10: =Model!'Front Page'!H20 | J10: =Model!'Front Page'!H20
A11: Market Cap ($M) | F11: =F9*F10 | G11: =G9*G10 | H11: =H9*H10 | I11: =I9*I10 | J11: =J9*J10
A13: P/E VALUATION
A14: Consensus P/E Multiple | F14: 45 | G14: 24 | H14: 22 | I14: 20 | J14: 19
A15: Earnings for P/E ($M) | F15: =F7 | G15: =G7 | H15: =H7 | I15: =I7 | J15: =J7
A16: Implied Market Cap via P/E ($M) | F16: =F14*F15 | G16: =G14*G15 | H16: =H14*H15 | I16: =I14*I15 | J16: =J14*J15
A17: Implied Price via P/E ($) | F17: =F16/F9 | G17: =G16/G9 | H17: =H16/H9 | I17: =I16/I9 | J17: =J16/J9
A18: Upside vs Current (P/E) | F18: =F17/F10-1 | G18: =G17/G10-1 | H18: =H17/H10-1 | I18: =I17/I10-1 | J18: =J17/J10-1
A20: EV/EBITDA VALUATION
A21: Consensus EV/EBITDA Multiple | F21: 35 | G21: 18 | H21: 16 | I21: 15 | J21: 14
A22: EBITDA ($M) | F22: =F8 | G22: =G8 | H22: =H8 | I22: =I8 | J22: =J8
A23: Implied TEV via EV/EBITDA ($M) | F23: =F21*F22 | G23: =G21*G22 | H23: =H21*H22 | I23: =I21*I22 | J23: =J21*J22
A24: Less: Net Debt ($M) | F24: 5000 | G24: 5000 | H24: 5000 | I24: 5000 | J24: 5000
A25: Implied Equity Value ($M) | F25: =F23-F24 | G25: =G23-G24 | H25: =H23-H24 | I25: =I23-I24 | J25: =J23-J24
A26: Implied Price via EV/EBITDA ($) | F26: =F25/F9 | G26: =G25/G9 | H26: =H25/H9 | I26: =I25/I9 | J26: =J25/J9
A27: Upside vs Current (EV/EBITDA) | F27: =F26/F10-1 | G27: =G26/G10-1 | H27: =H26/H10-1 | I27: =I26/I10-1 | J27: =J26/J10-1
A29: VALUATION SUMMARY
A30: Current Price | F30: =F10 | G30: =G10 | H30: =H10 | I30: =I10 | J30: =J10
A31: P/E Implied (NTM) | G31: =G17
A32: EV/EBITDA Implied (NTM) | G32: =G26
A33: Average Implied Price | G33: =(G17+G26)/2
A34: Upside (Avg vs Current) | G34: =G33/G30-1

Sheet DCF
B1: NVIDIA Corporation
B2: Discounted Cash Flow Valuation Analysis
F5: Historical | G5: Projected | M5: Assumptions | R5: Notes
M6: Risk Free Rate: | P6: 0.0425 | R6: 10-Year US Treasury yield
B7: ($ in millions) | F7: FY2025 | G7: FY2026 | H7: FY2027 | I7: FY2028 | J7: FY2029 | K7: FY2030 | M7: Market Risk Premium: | P7: 0.055 | R7: Damodaran equity risk premium
M8: Unlevered Beta: | P8: 1.65 | R8: Semiconductor industry avg
B9: Revenue Build by Segment | M9: Projected Equity to Value: | P9: 0.998 | R9: NVDA ~100% equity-financed
B10: Datacenter Revenue | F10: =Model!BS22 | G10: =Model!BX22 | H10: =Model!CC22 | I10: =Model!CD22 | J10: =Model!CE22 | K10: =Model!CF22 | M10: Levered Beta: | P10: =(1+(1-P12)*(1-P9)/P9)*P8 | R10: Hamada equation
B11: Y/Y Growth | F11: =Model!BS24 | G11: =Model!BX24 | H11: =Model!CC24 | I11: =Model!CD24 | J11: =Model!CE24 | K11: =Model!CF24 | M11: Cost of Equity: | P11: =P6+P7*P10 | R11: CAPM: Rf + B(Rm-Rf)
B12: Gaming Revenue | F12: =Model!BS7 | G12: =Model!BX7 | H12: =Model!CC7 | I12: =Model!CD7 | J12: =Model!CE7 | K12: =Model!CF7 | M12: Tax Rate: | P12: 0.15 | R12: Long-term effective tax rate
B13: Y/Y Growth | F13: =Model!BS9 | G13: =Model!BX9 | H13: =Model!CC9 | I13: =Model!CD9 | J13: =Model!CE9 | K13: =Model!CF9 | M13: Cost of Debt: | P13: 0.035 | R13: Based on outstanding senior notes
B14: Automotive Revenue | F14: =Model!BS26 | G14: =Model!BX26 | H14: =Model!CC26 | I14: =Model!CD26 | J14: =Model!CE26 | K14: =Model!CF26 | M14: WACC: | P14: =P11*P9+P13*(1-P12)*(1-P9) | R14: Rd*(1-T)*(D/V) + Re*(E/V)
B15: Y/Y Growth | F15: =Model!BS28 | G15: =Model!BX28 | H15: =Model!CC28 | I15: =Model!CD28 | J15: =Model!CE28 | K15: =Model!CF28 | M15: Terminal Growth Rate: | P15: 0.03 | R15: Long-term nominal GDP growth
B16: Professional Visualization Revenue | F16: =Model!BS11 | G16: =Model!BX11 | H16: =Model!CC11 | I16: =Model!CD11 | J16: =Model!CE11 | K16: =Model!CF11 | M16: Implied TV/EBITDA: | P16: =F46/Model!CF392 | R16: Terminal value / FY2030 EBITDA
B17: Y/Y Growth | F17: =Model!BS13 | G17: =Model!BX13 | H17: =Model!CC13 | I17: =Model!CD13 | J17: =Model!CE13 | K17: =Model!CF13
B18: OEM & IP Revenue | F18: =Model!BS30 | G18: =Model!BX30 | H18: =Model!CC30 | I18: =Model!CD30 | J18: =Model!CE30 | K18: =Model!CF30
B19: Y/Y Growth | F19: =Model!BS32 | G19: =Model!BX32 | H19: =Model!CC32 | I19: =Model!CD32 | J19: =Model!CE32 | K19: =Model!CF32
B20: Total Revenue | F20: =Model!BS34 | G20: =Model!BX34 | H20: =Model!CC34 | I20: =Model!CD34 | J20: =Model!CE34 | K20: =Model!CF34
B21: Y/Y Total Revenue Growth | G21: =G20/F20-1 | H21: =H20/G20-1 | I21: =I20/H20-1 | J21: =J20/I20-1 | K21: =K20/J20-1
B23: Operating Margin Drivers
B24: Non-GAAP Gross Margin % | F24: =Model!BS59 | G24: =Model!BX59 | H24: =Model!CC59 | I24: =Model!CD59 | J24: =Model!CE59 | K24: =Model!CF59
B25: Gross Margin Improvement (bps) | F25: =Model!BS62 | G25: =Model!BX62 | H25: =Model!CC62 | I25: =Model!CD62 | J25: =Model!CE62 | K25: =Model!CF62
B26: Non-GAAP R&D Margin % | F26: =Model!BS76 | G26: =Model!BX76 | H26: =Model!CC76 | I26: =Model!CD76 | J26: =Model!CE76 | K26: =Model!CF76
B27: R&D Margin Improvement (bps) | F27: =Model!BS77 | G27: =Model!BX77 | H27: =Model!CC77 | I27: =Model!CD77 | J27: =Model!CE77 | K27: =Model!CF77
B28: Non-GAAP SG&A Margin % | F28: =Model!BS91 | G28: =Model!BX91 | H28: =Model!CC91 | I28: =Model!CD91 | J28: =Model!CE91 | K28: =Model!CF91
B29: SG&A Margin Improvement (bps) | F29: =Model!BS92 | G29: =Model!BX92 | H29: =Model!CC92 | I29: =Model!CD92 | J29: =Model!CE92 | K29: =Model!CF92
B30: Non-GAAP EBIT Margin % | F30: =Model!BS109 | G30: =Model!BX109 | H30: =Model!CC109 | I30: =Model!CD109 | J30: =Model!CE109 | K30: =Model!CF109
B31: Non-GAAP Operating Income (EBIT) | F31: =Model!BS386 | G31: =Model!BX386 | H31: =Model!CC386 | I31: =Model!CD386 | J31: =Model!CE386 | K31: =Model!CF386
B33: Unlevered Free Cash Flow Build
B34: Non-GAAP EBIT | G34: =G31 | H34: =H31 | I34: =I31 | J34: =J31 | K34: =K31
B35: Less: Taxes on EBIT | G35: =-G34*$P$12 | H35: =-H34*$P$12 | I35: =-I34*$P$12 | J35: =-J34*$P$12 | K35: =-K34*$P$12
B36: NOPAT | G36: =G34+G35 | H36: =H34+H35 | I36: =I34+I35 | J36: =J34+J35 | K36: =K34+K35
B37: Plus: Depreciation & Amortization | G37: =Model!BX933 | H37: =Model!CC933 | I37: =Model!CD933 | J37: =Model!CE933 | K37: =Model!CF933
B38: Less: Capital Expenditures | G38: =-Model!BX934 | H38: =-Model!CC934 | I38: =-Model!CD934 | J38: =-Model!CE934 | K38: =-Model!CF934
B39: Less: Increase in Net Working Capital | G39: =-G72 | H39: =-H72 | I39: =-I72 | J39: =-J72 | K39: =-K72
B40: Unlevered Free Cash Flow | G40: =SUM(G36:G39) | H40: =SUM(H36:H39) | I40: =SUM(I36:I39) | J40: =SUM(J36:J39) | K40: =SUM(K36:K39)
B42: Times: Discount Factor | G42: =1/(1+$P$14)^1 | H42: =1/(1+$P$14)^2 | I42: =1/(1+$P$14)^3 | J42: =1/(1+$P$14)^4 | K42: =1/(1+$P$14)^5
B43: Discounted Cash Flows | G43: =G40*G42 | H43: =H40*H42 | I43: =I40*I42 | J43: =J40*J42 | K43: =K40*K42
B45: Sum of Discounted Cash Flows | F45: =SUM(G43:K43)
B46: Terminal Value: | F46: =(K40*(1+$P$15))/($P$14-$P$15)
B47: Times: Discount Factor | F47: =K42
B48: PV of Terminal Value | F48: =F46*F47
C49: Enterprise Value | F49: =F45+F48
B51: Equity Bridge:
B52: Enterprise Value | F52: =F49
B53: Less: Total Debt | F53: =-(Model!BS992+IF(ISNUMBER(Model!BS988),Model!BS988,0))
B54: Plus: Cash & Cash Equivalents | F54: =Model!BS952
B55: Plus: Marketable Securities | F55: =Model!BS953
C56: Equity Value | F56: =SUM(F52:F55)
B57: Diluted Shares Outstanding (mm) | F57: =Model!BS429
C58: Implied Share Price ($/share) | F58: =F56/F57
B60: Current Stock Price ($/share) | F60: ='Front Page'!H20
B61: Upside / (Downside) | F61: =F58/F60-1
B64: Net Working Capital Calculation:
F65: FY2025 | G65: FY2026 | H65: FY2027 | I65: FY2028 | J65: FY2029 | K65: FY2030
B66: Accounts Receivable | F66: =Model!BS954 | G66: =Model!BX954 | H66: =Model!CC954 | I66: =Model!CD954 | J66: =Model!CE954 | K66: =Model!CF954
B67: Inventories | F67: =Model!BS958 | G67: =Model!BX958 | H67: =Model!CC958 | I67: =Model!CD958 | J67: =Model!CE958 | K67: =Model!CF958
B68: Less: Accounts Payable | F68: =-Model!BS985 | G68: =-Model!BX985 | H68: =-Model!CC985 | I68: =-Model!CD985 | J68: =-Model!CE985 | K68: =-Model!CF985
B69: Less: Accrued & Other Current Liabilities | F69: =-Model!BS987 | G69: =-Model!BX987 | H69: =-Model!CC987 | I69: =-Model!CD987 | J69: =-Model!CE987 | K69: =-Model!CF987
B70: Net Working Capital | F70: =SUM(F66:F69) | G70: =SUM(G66:G69) | H70: =SUM(H66:H69) | I70: =SUM(I66:I69) | J70: =SUM(J66:J69) | K70: =SUM(K66:K69)
B72: Change in Net Working Capital | G72: =G70-F70 | H72: =H70-G70 | I72: =I70-H70 | J72: =J70-I70 | K72: =K70-J70
B75: Memo:
B76: Stock-Based Compensation (excluded from UFCF) | G76: =Model!BX408 | H76: =Model!CC408 | I76: =Model!CD408 | J76: =Model!CE408 | K76: =Model!CF408
B77: Non-GAAP EBITDA | F77: =Model!BS392 | G77: =Model!BX392 | H77: =Model!CC392 | I77: =Model!CD392 | J77: =Model!CE392 | K77: =Model!CF392
B78: UFCF Growth Rate | H78: =H40/G40-1 | I78: =I40/H40-1 | J78: =J40/I40-1 | K78: =K40/J40-1

Sheet Model
A1: NVIDIA Corporation
A2: =CHOOSE(MO.DataSourceIndex,MO.Ticker.Bloomberg,MO.Ticker.CapIQ,MO.Ticker.FactSet,MO.Ticker.Thomson) | C2: =EOMONTH(C4,-12) | AA2: Restated | AB2: Restated | AC2: Restated | AD2: Restated | AE2: Restated
A3: =HP.TradeCurrency | B3: =IF(MO.RealTime="OFF",MO.LastPriceHardcoded,MO.LastPriceFormula) | C3: =C4-C2 | D3: =D4-C4 | E3: =E4-D4 | F3: =F4-E4 | G3: =G4-F4 | H3: =H4-G4 | I3: =I4-H4 | J3: =J4-I4 | K3: =K4-F4 | L3: =L4-K4 | M3: =M4-L4 | N3: =N4-M4 | O3: =O4-N4 | P3: =P4-K4 | Q3: =Q4-P4 | R3: =R4-Q4 | S3: =S4-R4 | T3: =T4-S4 | U3: =U4-P4 | V3: =V4-U4 | W3: =W4-V4 | X3: =X4-W4 | Y3: =Y4-X4 | Z3: =Z4-U4 | AA3: =AA4-Z4 | AB3: =AB4-AA4 | AC3: =AC4-AB4 | AD3: =AD4-AC4 | AE3: =AE4-Z4 | AF3: =AF4-AE4 | AG3: =AG4-AF4 | AH3: =AH4-AG4 | AI3: =AI4-AH4 | AJ3: =AJ4-AE4 | AK3: =AK4-AJ4 | AL3: =AL4-AK4 | AM3: =AM4-AL4 | AN3: =AN4-AM4 | AO3: =AO4-AJ4 | AP3: =AP4-AO4 | AQ3: =AQ4-AP4 | AR3: =AR4-AQ4 | AS3: =AS4-AR4 | AT3: =AT4-AO4 | AU3: =AU4-AT4 | AV3: =AV4-AU4 | AW3: =AW4-AV4 | AX3: =AX4-AW4 | AY3: =AY4-AT4 | AZ3: =AZ4-AY4 | BA3: =BA4-AZ4 | BB3: =BB4-BA4 | BC3: =BC4-BB4 | BD3: =BD4-AY4 | BE3: =BE4-BD4 | BF3: =BF4-BE4 | BG3: =BG4-BF4 | BH3: =BH4-BG4 | BI3: =BI4-BD4 | BJ3: =BJ4-BI4 | BK3: =BK4-BJ4 | BL3: =BL4-BK4 | BM3: =BM4-BL4 | BN3: =BN4-BI4 | BO3: =BO4-BN4 | BP3: =BP4-BO4 | BQ3: =BQ4-BP4 | BR3: =BR4-BQ4 | BS3: =BS4-BN4 | BT3: =BT4-BS4 | BU3: =BU4-BT4 | BV3: =BV4-BU4 | BW3: =BW4-BV4 | BX3: =BX4-BS4 | BY3: =BY4-BX4 | BZ3: =BZ4-BY4 | CA3: =CA4-BZ4 | CB3: =CB4-CA4 | CC3: =CC4-BX4 | CD3: =CD4-CC4 | CE3: =CE4-CD4 | CF3: =CF4-CE4
A4: =FP.DataSourceName | B4: =IF(AND(MO.RealTimeStockPriceToggle,MO.LastPriceFormula<>"N/A"),"ON","OFF") | C4: 39838 | D4: 40209 | E4: 40573 | F4: 40937 | G4: 41028 | H4: 41119 | I4: 41210 | J4: =K4 | K4: 41301 | L4: 41392 | M4: 41483 | N4: 41574 | O4: =P4 | P4: 41665 | Q4: 41756 | R4: 41847 | S4: 41938 | T4: =U4 | U4: 42029 | V4: 42120 | W4: 42211 | X4: 42302 | Y4: =Z4 | Z4: 42400 | AA4: 42491 | AB4: 42582 | AC4: 42673 | AD4: =AE4 | AE4: 42764 | AF4: 42855 | AG4: 42946 | AH4: 43037 | AI4: =AJ4 | AJ4: 43128 | AK4: 43219 | AL4: 43310 | AM4: 43401 | AN4: =AO4 | AO4: 43492 | AP4: 43583 | AQ4: 43674 | AR4: 43765 | AS4: =AT4 | AT4: 43856 | AU4: 43947 | AV4: 44038 | AW4: 44129 | AX4: =AY4 | AY4: 44227 | AZ4: 44318 | BA4: 44409 | BB4: 44500 | BC4: =BD4 | BD4: 44591 | BE4: 44682 | BF4: 44773 | BG4: 44864 | BH4: =BI4 | BI4: 44955 | BJ4: 45046 | BK4: 45137 | BL4: 45228 | BM4: =BN4 | BN4: 45319 | BO4: 45410 | BP4: 45501 | BQ4: 45592 | BR4: =BS4 | BS4: 45683 | BT4: 45774 | BU4: 45865 | BV4: 45956 | BW4: =DATE(YEAR(BV4)+1,1,31) | BX4: =BW4 | BY4: =+EDATE(BX4,3) | BZ4: =+EDATE(BY4,3) | CA4: =+EDATE(BZ4,3) | CB4: =DATE(YEAR(CA4)+1,1,31) | CC4: =CB4 | CD4: =EOMONTH(CC4,12) | CE4: =EOMONTH(CD4,12) | CF4: =EOMONTH(CE4,12)
A5: =MO.ReportCurrency | C5: FY2009 | D5: =CONCATENATE("FY",RIGHT(C5,4)+1) | E5: =CONCATENATE("FY",RIGHT(D5,4)+1) | F5: =CONCATENATE("FY",RIGHT(E5,4)+1) | G5: =CONCATENATE("Q1","-",RIGHT(F5,4)+1) | H5: =CONCATENATE("Q2","-",RIGHT(G5,4)) | I5: =CONCATENATE("Q3","-",RIGHT(H5,4)) | J5: =CONCATENATE("Q4","-",RIGHT(I5,4)) | K5: =CONCATENATE("FY",RIGHT(F5,4)+1) | L5: =CONCATENATE("Q1","-",RIGHT(K5,4)+1) | M5: =CONCATENATE("Q2","-",RIGHT(L5,4)) | N5: =CONCATENATE("Q3","-",RIGHT(M5,4)) | O5: =CONCATENATE("Q4","-",RIGHT(N5,4)) | P5: =CONCATENATE("FY",RIGHT(K5,4)+1) | Q5: =CONCATENATE("Q1","-",RIGHT(P5,4)+1) | R5: =CONCATENATE("Q2","-",RIGHT(Q5,4)) | S5: =CONCATENATE("Q3","-",RIGHT(R5,4)) | T5: =CONCATENATE("Q4","-",RIGHT(S5,4)) | U5: =CONCATENATE("FY",RIGHT(P5,4)+1) | V5: =CONCATENATE("Q1","-",RIGHT(U5,4)+1) | W5: =CONCATENATE("Q2","-",RIGHT(V5,4)) | X5: =CONCATENATE("Q3","-",RIGHT(W5,4)) | Y5: =CONCATENATE("Q4","-",RIGHT(X5,4)) | Z5: =CONCATENATE("FY",RIGHT(U5,4)+1) | AA5: =CONCATENATE("Q1","-",RIGHT(Z5,4)+1) | AB5: =CONCATENATE("Q2","-",RIGHT(AA5,4)) | AC5: =CONCATENATE("Q3","-",RIGHT(AB5,4)) | AD5: =CONCATENATE("Q4","-",RIGHT(AC5,4)) | AE5: =CONCATENATE("FY",RIGHT(Z5,4)+1) | AF5: =CONCATENATE("Q1","-",RIGHT(AE5,4)+1) | AG5: =CONCATENATE("Q2","-",RIGHT(AF5,4)) | AH5: =CONCATENATE("Q3","-",RIGHT(AG5,4)) | AI5: =CONCATENATE("Q4","-",RIGHT(AH5,4)) | AJ5: =CONCATENATE("FY",RIGHT(AE5,4)+1) | AK5: =CONCATENATE("Q1","-",RIGHT(AJ5,4)+1) | AL5: =CONCATENATE("Q2","-",RIGHT(AK5,4)) | AM5: =CONCATENATE("Q3","-",RIGHT(AL5,4)) | AN5: =CONCATENATE("Q4","-",RIGHT(AM5,4)) | AO5: =CONCATENATE("FY",RIGHT(AJ5,4)+1) | AP5: =CONCATENATE("Q1","-",RIGHT(AO5,4)+1) | AQ5: =CONCATENATE("Q2","-",RIGHT(AP5,4)) | AR5: =CONCATENATE("Q3","-",RIGHT(AQ5,4)) | AS5: =CONCATENATE("Q4","-",RIGHT(AR5,4)) | AT5: =CONCATENATE("FY",RIGHT(AO5,4)+1) | AU5: =CONCATENATE("Q1","-",RIGHT(AT5,4)+1) | AV5: =CONCATENATE("Q2","-",RIGHT(AU5,4)) | AW5: =CONCATENATE("Q3","-",RIGHT(AV5,4)) | AX5: =CONCATENATE("Q4","-",RIGHT(AW5,4)) | AY5: =CONCATENATE("FY",RIGHT(AT5,4)+1) | AZ5: =CONCATENATE("Q1","-",RIGHT(AY5,4)+1) | BA5: =CONCATENATE("Q2","-",RIGHT(AZ5,4)) | BB5: =CONCATENATE("Q3","-",RIGHT(BA5,4)) | BC5: =CONCATENATE("Q4","-",RIGHT(BB5,4)) | BD5: =CONCATENATE("FY",RIGHT(AY5,4)+1) | BE5: =CONCATENATE("Q1","-",RIGHT(BD5,4)+1) | BF5: =CONCATENATE("Q2","-",RIGHT(BE5,4)) | BG5: =CONCATENATE("Q3","-",RIGHT(BF5,4)) | BH5: =CONCATENATE("Q4","-",RIGHT(BG5,4)) | BI5: =CONCATENATE("FY",RIGHT(BD5,4)+1) | BJ5: =CONCATENATE("Q1","-",RIGHT(BI5,4)+1) | BK5: =CONCATENATE("Q2","-",RIGHT(BJ5,4)) | BL5: =CONCATENATE("Q3","-",RIGHT(BK5,4)) | BM5: =CONCATENATE("Q4","-",RIGHT(BL5,4)) | BN5: =CONCATENATE("FY",RIGHT(BI5,4)+1) | BO5: =CONCATENATE("Q1","-",RIGHT(BN5,4)+1) | BP5: =CONCATENATE("Q2","-",RIGHT(BO5,4)) | BQ5: =CONCATENATE("Q3","-",RIGHT(BP5,4)) | BR5: =CONCATENATE("Q4","-",RIGHT(BQ5,4)) | BS5: =CONCATENATE("FY",RIGHT(BN5,4)+1) | BT5: =CONCATENATE("Q1","-",RIGHT(BS5,4)+1) | BU5: =CONCATENATE("Q2","-",RIGHT(BT5,4)) | BV5: =CONCATENATE("Q3","-",RIGHT(BU5,4)) | BW5: =CONCATENATE("Q4","-",RIGHT(BV5,4)) | BX5: =CONCATENATE("FY",RIGHT(BS5,4)+1) | BY5: =CONCATENATE("Q1","-",RIGHT(BX5,4)+1) | BZ5: =CONCATENATE("Q2","-",RIGHT(BY5,4)) | CA5: =CONCATENATE("Q3","-",RIGHT(BZ5,4)) | CB5: =CONCATENATE("Q4","-",RIGHT(CA5,4)) | CC5: =CONCATENATE("FY",RIGHT(BX5,4)+1) | CD5: =CONCATENATE("FY",RIGHT(CC5,4)+1) | CE5: =CONCATENATE("FY",RIGHT(CD5,4)+1) | CF5: =CONCATENATE("FY",RIGHT(CE5,4)+1)
A6: Revenue Build (FS/PR)
A7: Gaming Revenue, mm | P7: 1511 | Q7: 468 | R7: 417 | S7: 527 | T7: =U7-SUM(Q7,R7,S7) | U7: 2058 | V7: 587 | W7: 660 | X7: 761 | Y7: =Z7-SUM(V7,W7,X7) | Z7: 2818 | AA7: 687 | AB7: 781 | AC7: 1244 | AD7: =AE7-SUM(AA7,AB7,AC7) | AE7: 4060 | AF7: 1027 | AG7: 1186 | AH7: 1561 | AI7: =AJ7-SUM(AF7,AG7,AH7) | AJ7: 5513 | AK7: 1723 | AL7: 1805 | AM7: 1764 | AN7: 954 | AO7: =SUM(AK7,AL7,AM7,AN7) | AP7: 1055 | AQ7: 1313 | AR7: 1659 | AS7: 1491 | AT7: =SUM(AP7,AQ7,AR7,AS7) | AU7: 1339 | AV7: 1654 | AW7: 2271 | AX7: 2495 | AY7: =SUM(AU7,AV7,AW7,AX7) | AZ7: 2760 | BA7: 3061 | BB7: 3221 | BC7: 3420 | BD7: =SUM(AZ7,BA7,BB7,BC7) | BE7: 3620 | BF7: 2042 | BG7: 1574 | BH7: 1831 | BI7: =SUM(BE7,BF7,BG7,BH7) | BJ7: 2240 | BK7: 2486 | BL7: 2856 | BM7: 2865 | BN7: =SUM(BJ7,BK7,BL7,BM7) | BO7: 2647 | BP7: 2880 | BQ7: 3279 | BR7: 2544 | BS7: =SUM(BO7,BP7,BQ7,BR7) | BT7: 3763 | BU7: 4287 | BV7: 4265 | BW7: =+BR7*(1+BW9) | BX7: =SUM(BT7,BU7,BV7,BW7) | BY7: =+BT7*(1+BY9) | BZ7: =+BU7*(1+BZ9) | CA7: =+BV7*(1+CA9) | CB7: =+BW7*(1+CB9) | CC7: =SUM(BY7,BZ7,CA7,CB7) | CD7: =+CC7*(1+CD9) | CE7: =+CD7*(1+CE9) | CF7: =+CE7*(1+CF9)
A8: Q/Q Gaming Revenue growth, % | R8: =R7/Q7-1 | S8: =S7/R7-1 | T8: =T7/S7-1 | V8: =V7/T7-1 | W8: =W7/V7-1 | X8: =X7/W7-1 | Y8: =Y7/X7-1 | AA8: =AA7/Y7-1 | AB8: =AB7/AA7-1 | AC8: =AC7/AB7-1 | AD8: =AD7/AC7-1 | AF8: =AF7/AD7-1 | AG8: =AG7/AF7-1 | AH8: =AH7/AG7-1 | AI8: =AI7/AH7-1 | AK8: =AK7/AI7-1 | AL8: =AL7/AK7-1 | AM8: =AM7/AL7-1 | AN8: =AN7/AM7-1 | AP8: =AP7/AN7-1 | AQ8: =AQ7/AP7-1 | AR8: =AR7/AQ7-1 | AS8: =AS7/AR7-1 | AU8: =AU7/AS7-1 | AV8: =AV7/AU7-1 | AW8: =AW7/AV7-1 | AX8: =AX7/AW7-1 | AZ8: =AZ7/AX7-1 | BA8: =BA7/AZ7-1 | BB8: =BB7/BA7-1 | BC8: =BC7/BB7-1 | BE8: =BE7/BC7-1 | BF8: =BF7/BE7-1 | BG8: =BG7/BF7-1 | BH8: =BH7/BG7-1 | BJ8: =BJ7/BH7-1 | BK8: =BK7/BJ7-1 | BL8: =BL7/BK7-1 | BM8: =BM7/BL7-1 | BO8: =BO7/BM7-1 | BP8: =BP7/BO7-1 | BQ8: =BQ7/BP7-1 | BR8: =BR7/BQ7-1 | BT8: =BT7/BR7-1 | BU8: =BU7/BT7-1 | BV8: =BV7/BU7-1 | BW8: =BW7/BV7-1 | BY8: =BY7/BW7-1 | BZ8: =BZ7/BY7-1 | CA8: =CA7/BZ7-1 | CB8: =CB7/CA7-1
A9: Y/Y Gaming Revenue Growth, % | U9: =+U7/P7-1 | V9: =+V7/Q7-1 | W9: =+W7/R7-1 | X9: =+X7/S7-1 | Y9: =+Y7/T7-1 | Z9: =+Z7/U7-1 | AA9: =+AA7/V7-1 | AB9: =+AB7/W7-1 | ... BV9: =+BV7/BQ7-1 | BW9: 0.5 | BX9: =+BX7/BS7-1 | BY9: 0.5 | BZ9: 0.3 | CA9: 0.25 | CB9: 0.2 | CC9: =+CC7/BX7-1 | CD9: 0.1 | CE9: 0.1 | CF9: 0.1
A11: Professional Visualization Revenue, mm | P11: 789 | Q11: 191 | R11: 208 | S11: 206 | T11: =U11-SUM(Q11,R11,S11) | U11: 795 | V11: 181 | W11: 176 | X11: 190 | Y11: =Z11-SUM(V11,W11,X11) | Z11: 750 | AA11: 189 | AB11: 214 | AC11: 207 | AD11: =AE11-SUM(AA11,AB11,AC11) | AE11: 835 | AF11: 205 | AG11: 235 | AH11: 239 | AI11: =AJ11-SUM(AF11,AG11,AH11) | AJ11: 934 | AK11: 251 | AL11: 281 | AM11: 305 | AN11: 293 | AO11: =SUM(AK11,AL11,AM11,AN11) | AP11: 266 | AQ11: 291 | AR11: 324 | AS11: 331 | AT11: =SUM(AP11,AQ11,AR11,AS11) | AU11: 307 | AV11: 203 | AW11: 236 | AX11: 307 | AY11: =SUM(AU11,AV11,AW11,AX11) | AZ11: 372 | BA11: 519 | BB11: 577 | BC11: 643 | BD11: =SUM(AZ11,BA11,BB11,BC11) | BE11: 622 | BF11: 496 | BG11: 200 | BH11: 226 | BI11: =SUM(BE11,BF11,BG11,BH11) | BJ11: 295 | BK11: 379 | BL11: 416 | BM11: 463 | BN11: =SUM(BJ11,BK11,BL11,BM11) | BO11: 427 | BP11: 454 | BQ11: 486 | BR11: 511 | BS11: =SUM(BO11,BP11,BQ11,BR11) | BT11: 509 | BU11: 601 | BV11: 760 | BW11: =+BR11*(1+BW13) | BX11: =SUM(BT11,BU11,BV11,BW11) | BY11: =+BT11*(1+BY13) | BZ11: =+BU11*(1+BZ13) | CA11: =+BV11*(1+CA13) | CB11: =+BW11*(1+CB13) | CC11: =SUM(BY11,BZ11,CA11,CB11) | CD11: =+CC11*(1+CD13) | CE11: =+CD11*(1+CE13) | CF11: =+CE11*(1+CF13)
A12: Q/Q Professional Visualization Revenue growth, % | R12: =R11/Q11-1 | S12: =S11/R11-1 | T12: =T11/S11-1 | V12: =V11/T11-1 | W12: =W11/V11-1 | X12: =X11/W11-1 | Y12: =Y11/X11-1 | AA12: =AA11/Y11-1 | AB12: =AB11/AA11-1 | AC12: =AC11/AB11-1 | AD12: =AD11/AC11-1 | AF12: =AF11/AD11-1 | AG12: =AG11/AF11-1 | AH12: =AH11/AG11-1 | AI12: =AI11/AH11-1 | AK12: =AK11/AI11-1 | AL12: =AL11/AK11-1 | AM12: =AM11/AL11-1 | AN12: =AN11/AM11-1 | AP12: =AP11/AN11-1 | AQ12: =AQ11/AP11-1 | AR12: =AR11/AQ11-1 | AS12: =AS11/AR11-1 | AU12: =AU11/AS11-1 | AV12: =AV11/AU11-1 | AW12: =AW11/AV11-1 | AX12: =AX11/AW11-1 | AZ12: =AZ11/AX11-1 | BA12: =BA11/AZ11-1 | BB12: =BB11/BA11-1 | BC12: =BC11/BB11-1 | BE12: =BE11/BC11-1 | BF12: =BF11/BE11-1 | BG12: =BG11/BF11-1 | BH12: =BH11/BG11-1 | BJ12: =BJ11/BH11-1 | BK12: =BK11/BJ11-1 | BL12: =BL11/BK11-1 | BM12: =BM11/BL11-1 | BO12: =BO11/BM11-1 | BP12: =BP11/BO11-1 | BQ12: =BQ11/BP11-1 | BR12: =BR11/BQ11-1 | BT12: =BT11/BR11-1 | BU12: =BU11/BT11-1 | BV12: =BV11/BU11-1 | BW12: =BW11/BV11-1 | BY12: =BY11/BW11-1 | BZ12: =BZ11/BY11-1 | CA12: =CA11/BZ11-1 | CB12: =CB11/CA11-1
A13: Y/Y Professional Visualization Revenue Growth, % | U13: =+U11/P11-1 | V13: =+V11/Q11-1 | W13: =+W11/R11-1 | X13: =+X11/S11-1 | Y13: =+Y11/T11-1 | Z13: =+Z11/U11-1 | AA13: =+AA11/V11-1 | AB13: =+AB11/W11-1 | ... BV13: =+BV11/BQ11-1 | BW13: 0.3 | BX13: =+BX11/BS11-1 | BY13: 0.05 | BZ13: 0.05 | CA13: 0.05 | CB13: 0.05 | CC13: =+CC11/BX11-1 | CD13: 0.1 | CE13: 0.1 | CF13: 0.1
A15: Compute revenue, mm | BJ15: 3357 | BK15: 8612 | BL15: 11908 | BM15: 15073 | BN15: 38950 | BO15: 19392 | BP15: 22604 | BQ15: 27644 | BR15: =BS15-SUM(BO15,BP15,BQ15) | BS15: 102196 | BT15: 34155 | BU15: 33844 | BV15: 43028
A16: Q/Q Compute Revenue growth, % | BK16: =BK15/BJ15-1 | BL16: =BL15/BK15-1 | BM16: =BM15/BL15-1 | BO16: =BO15/BM15-1 | BP16: =BP15/BO15-1 | BQ16: =BQ15/BP15-1 | BR16: =BR15/BQ15-1 | BT16: =BT15/BR15-1 | BU16: =BU15/BT15-1 | BV16: =BV15/BU15-1
A17: Y/Y Compute Revenue Growth, % | BO17: =+BO15/BJ15-1 | BP17: =+BP15/BK15-1 | BQ17: =+BQ15/BL15-1 | BR17: =+BR15/BM15-1 | BS17: =+BS15/BN15-1 | BT17: =+BT15/BO15-1 | BU17: =+BU15/BP15-1 | BV17: =+BV15/BQ15-1
A19: Networking revenue, mm | BJ19: 927 | BK19: 1711 | BL19: 2606 | BM19: 3331 | BN19: 8575 | BO19: 3171 | BP19: 3668 | BQ19: 3127 | BR19: =BS19-SUM(BO19,BP19,BQ19) | BS19: 12990 | BT19: 4957 | BU19: 7252 | BV19: 8187
A20: Q/Q Networking Revenue growth, % | BK20: =BK19/BJ19-1 | BL20: =BL19/BK19-1 | BM20: =BM19/BL19-1 | BO20: =BO19/BM19-1 | BP20: =BP19/BO19-1 | BQ20: =BQ19/BP19-1 | BR20: =BR19/BQ19-1 | BT20: =BT19/BR19-1 | BU20: =BU19/BT19-1 | BV20: =BV19/BU19-1
A21: Y/Y Networking Revenue Growth, % | BO21: =+BO19/BJ19-1 | BP21: =+BP19/BK19-1 | BQ21: =+BQ19/BL19-1 | BR21: =+BR19/BM19-1 | BS21: =+BS19/BN19-1 | BT21: =+BT19/BO19-1 | BU21: =+BU19/BP19-1 | BV21: =+BV19/BQ19-1
A22: Datacenter Revenue, mm | P22: 199 | Q22: 57 | R22: 83 | S22: 89 | T22: =U22-SUM(Q22,R22,S22) | U22: 317 | V22: 88 | W22: 72 | X22: 82 | Y22: =Z22-SUM(V22,W22,X22) | Z22: 339 | AA22: 143 | AB22: 151 | AC22: 240 | AD22: =AE22-SUM(AA22,AB22,AC22) | AE22: 830 | AF22: 409 | AG22: 416 | AH22: 501 | AI22: =AJ22-SUM(AF22,AG22,AH22) | AJ22: 1932 | AK22: 701 | AL22: 760 | AM22: 792 | AN22: 679 | AO22: =SUM(AK22,AL22,AM22,AN22) | AP22: 634 | AQ22: 655 | AR22: 726 | AS22: 968 | AT22: =SUM(AP22,AQ22,AR22,AS22) | AU22: 1141 | AV22: 1752 | AW22: 1900 | AX22: 1903 | AY22: =SUM(AU22,AV22,AW22,AX22) | AZ22: 2048 | BA22: 2366 | BB22: 2936 | BC22: 3263 | BD22: =SUM(AZ22,BA22,BB22,BC22) | BE22: 3750 | BF22: 3806 | BG22: 3833 | BH22: 3616 | BI22: =SUM(BE22,BF22,BG22,BH22) | BJ22: 4284 | BK22: 10323 | BL22: 14514 | BM22: 18404 | BN22: =SUM(BJ22,BK22,BL22,BM22) | BO22: 22563 | BP22: 26272 | BQ22: 30771 | BR22: 35580 | BS22: =SUM(BO22,BP22,BQ22,BR22) | BT22: 39112 | BU22: 41096 | BV22: 51215 | BW22: =+BR22*(1+BW24) | BX22: =SUM(BT22,BU22,BV22,BW22) | BY22: =+BT22*(1+BY24) | BZ22: =+BU22*(1+BZ24) | CA22: =+BV22*(1+CA24) | CB22: =+BW22*(1+CB24) | CC22: =SUM(BY22,BZ22,CA22,CB22) | CD22: =+CC22*(1+CD24) | CE22: =+CD22*(1+CE24) | CF22: =+CE22*(1+CF24)
A23: Q/Q Datacenter Revenue growth, % | R23: =R22/Q22-1 | S23: =S22/R22-1 | T23: =T22/S22-1 | V23: =V22/T22-1 | W23: =W22/V22-1 | X23: =X22/W22-1 | Y23: =Y22/X22-1 | AA23: =AA22/Y22-1 | AB23: =AB22/AA22-1 | AC23: =AC22/AB22-1 | AD23: =AD22/AC22-1 | AF23: =AF22/AD22-1 | AG23: =AG22/AF22-1 | AH23: =AH22/AG22-1 | AI23: =AI22/AH22-1 | AK23: =AK22/AI22-1 | AL23: =AL22/AK22-1 | AM23: =AM22/AL22-1 | AN23: =AN22/AM22-1 | AP23: =AP22/AN22-1 | AQ23: =AQ22/AP22-1 | AR23: =AR22/AQ22-1 | AS23: =AS22/AR22-1 | AU23: =AU22/AS22-1 | AV23: =AV22/AU22-1 | AW23: =AW22/AV22-1 | AX23: =AX22/AW22-1 | AZ23: =AZ22/AX22-1 | BA23: =BA22/AZ22-1 | BB23: =BB22/BA22-1 | BC23: =BC22/BB22-1 | BE23: =BE22/BC22-1 | BF23: =BF22/BE22-1 | BG23: =BG22/BF22-1 | BH23: =BH22/BG22-1 | BJ23: =BJ22/BH22-1 | BK23: =BK22/BJ22-1 | BL23: =BL22/BK22-1 | BM23: =BM22/BL22-1 | BO23: =BO22/BM22-1 | BP23: =BP22/BO22-1 | BQ23: =BQ22/BP22-1 | BR23: =BR22/BQ22-1 | BT23: =BT22/BR22-1 | BU23: =BU22/BT22-1 | BV23: =BV22/BU22-1 | BW23: =BW22/BV22-1 | BY23: =BY22/BW22-1 | BZ23: =BZ22/BY22-1 | CA23: =CA22/BZ22-1 | CB23: =CB22/CA22-1
A24: Y/Y Datacenter Revenue Growth, % | U24: =+U22/P22-1 | V24: =+V22/Q22-1 | W24: =+W22/R22-1 | X24: =+X22/S22-1 | Y24: =+Y22/T22-1 | Z24: =+Z22/U22-1 | AA24: =+AA22/V22-1 | AB24: =+AB22/W22-1 | ... BV24: =+BV22/BQ22-1 | BW24: 0.67 | BX24: =+BX22/BS22-1 | BY24: 0.5 | BZ24: 0.5 | CA24: 0.35 | CB24: 0.3 | CC24: =+CC22/BX22-1 | CD24: 0.25 | CE24: 0.2 | CF24: 0.18
A26: Automotive Revenue, mm | P26: 99 | Q26: 35 | R26: 40 | S26: 52 | T26: =U26-SUM(Q26,R26,S26) | U26: 183 | V26: 77 | W26: 71 | X26: 79 | Y26: =Z26-SUM(V26,W26,X26) | Z26: 320 | AA26: 113 | AB26: 119 | AC26: 127 | AD26: =AE26-SUM(AA26,AB26,AC26) | AE26: 487 | AF26: 140 | AG26: 142 | AH26: 144 | AI26: =AJ26-SUM(AF26,AG26,AH26) | AJ26: 558 | AK26: 145 | AL26: 161 | AM26: 172 | AN26: 163 | AO26: =SUM(AK26,AL26,AM26,AN26) | AP26: 166 | AQ26: 209 | AR26: 162 | AS26: 163 | AT26: =SUM(AP26,AQ26,AR26,AS26) | AU26: 155 | AV26: 111 | AW26: 125 | AX26: 145 | AY26: =SUM(AU26,AV26,AW26,AX26) | AZ26: 154 | BA26: 152 | BB26: 135 | BC26: 125 | BD26: =SUM(AZ26,BA26,BB26,BC26) | BE26: 138 | BF26: 220 | BG26: 251 | BH26: 294 | BI26: =SUM(BE26,BF26,BG26,BH26) | BJ26: 296 | BK26: 253 | BL26: 261 | BM26: 281 | BN26: =SUM(BJ26,BK26,BL26,BM26) | BO26: 329 | BP26: 346 | BQ26: 449 | BR26: 570 | BS26: =SUM(BO26,BP26,BQ26,BR26) | BT26: 567 | BU26: 586 | BV26: 592 | BW26: =+BR26*(1+BW28) | BX26: =SUM(BT26,BU26,BV26,BW26) | BY26: =+BT26*(1+BY28) | BZ26: =+BU26*(1+BZ28) | CA26: =+BV26*(1+CA28) | CB26: =+BW26*(1+CB28) | CC26: =SUM(BY26,BZ26,CA26,CB26) | CD26: =+CC26*(1+CD28) | CE26: =+CD26*(1+CE28) | CF26: =+CE26*(1+CF28)
A27: Q/Q Automotive Revenue growth, % | R27: =R26/Q26-1 | S27: =S26/R26-1 | T27: =T26/S26-1 | V27: =V26/T26-1 | W27: =W26/V26-1 | X27: =X26/W26-1 | Y27: =Y26/X26-1 | AA27: =AA26/Y26-1 | AB27: =AB26/AA26-1 | AC27: =AC26/AB26-1 | AD27: =AD26/AC26-1 | AF27: =AF26/AD26-1 | AG27: =AG26/AF26-1 | AH27: =AH26/AG26-1 | AI27: =AI26/AH26-1 | AK27: =AK26/AI26-1 | AL27: =AL26/AK26-1 | AM27: =AM26/AL26-1 | AN27: =AN26/AM26-1 | AP27: =AP26/AN26-1 | AQ27: =AQ26/AP26-1 | AR27: =AR26/AQ26-1 | AS27: =AS26/AR26-1 | AU27: =AU26/AS26-1 | AV27: =AV26/AU26-1 | AW27: =AW26/AV26-1 | AX27: =AX26/AW26-1 | AZ27: =AZ26/AX26-1 | BA27: =BA26/AZ26-1 | BB27: =BB26/BA26-1 | BC27: =BC26/BB26-1 | BE27: =BE26/BC26-1 | BF27: =BF26/BE26-1 | BG27: =BG26/BF26-1 | BH27: =BH26/BG26-1 | BJ27: =BJ26/BH26-1 | BK27: =BK26/BJ26-1 | BL27: =BL26/BK26-1 | BM27: =BM26/BL26-1 | BO27: =BO26/BM26-1 | BP27: =BP26/BO26-1 | BQ27: =BQ26/BP26-1 | BR27: =BR26/BQ26-1 | BT27: =BT26/BR26-1 | BU27: =BU26/BT26-1 | BV27: =BV26/BU26-1 | BW27: =BW26/BV26-1 | BY27: =BY26/BW26-1 | BZ27: =BZ26/BY26-1 | CA27: =CA26/BZ26-1 | CB27: =CB26/CA26-1
A28: Y/Y Automotive Revenue Growth, % | U28: =+U26/P26-1 | V28: =+V26/Q26-1 | W28: =+W26/R26-1 | X28: =+X26/S26-1 | Y28: =+Y26/T26-1 | Z28: =+Z26/U26-1 | AA28: =+AA26/V26-1 | AB28: =+AB26/W26-1 | ... BV28: =+BV26/BQ26-1 | BW28: 0.1 | BX28: =+BX26/BS26-1 | BY28: 0.3 | BZ28: 0.2 | CA28: 0.2 | CB28: 0.2 | CC28: =+CC26/BX26-1 | CD28: 0.1 | CE28: 0.1 | CF28: 0.1
A30: OEM & IP Revenue, mm | P30: 1532 | Q30: 352 | R30: 355 | S30: 351 | T30: =U30-SUM(Q30,R30,S30) | U30: 1329 | V30: 218 | W30: 174 | X30: 193 | Y30: =Z30-SUM(V30,W30,X30) | Z30: 783 | AA30: 173 | AB30: 163 | AC30: 186 | AD30: =AE30-SUM(AA30,AB30,AC30) | AE30: 698 | AF30: 156 | AG30: 251 | AH30: 191 | AI30: =AJ30-SUM(AF30,AG30,AH30) | AJ30: 777 | AK30: 387 | AL30: 116 | AM30: 148 | AN30: 116 | AO30: =SUM(AK30,AL30,AM30,AN30) | AP30: 99 | AQ30: 111 | AR30: 143 | AS30: 152 | AT30: =SUM(AP30,AQ30,AR30,AS30) | AU30: 138 | AV30: 146 | AW30: 194 | AX30: 153 | AY30: =SUM(AU30,AV30,AW30,AX30) | AZ30: 327 | BA30: 409 | BB30: 234 | BC30: 192 | BD30: =SUM(AZ30,BA30,BB30,BC30) | BE30: 158 | BF30: 140 | BG30: 73 | BH30: 84 | BI30: =SUM(BE30,BF30,BG30,BH30) | BJ30: 77 | BK30: 66 | BL30: 73 | BM30: 90 | BN30: =SUM(BJ30,BK30,BL30,BM30) | BO30: 78 | BP30: 88 | BQ30: 97 | BR30: 126 | BS30: =SUM(BO30,BP30,BQ30,BR30) | BT30: 111 | BU30: 173 | BV30: 174 | BW30: =+BR30*(1+BW32) | BX30: =SUM(BT30,BU30,BV30,BW30) | BY30: =+BT30*(1+BY32) | BZ30: =+BU30*(1+BZ32) | CA30: =+BV30*(1+CA32) | CB30: =+BW30*(1+CB32) | CC30: =SUM(BY30,BZ30,CA30,CB30) | CD30: =+CC30*(1+CD32) | CE30: =+CD30*(1+CE32) | CF30: =+CE30*(1+CF32)
A31: Q/Q OEM & IP Revenue growth, % | R31: =R30/Q30-1 | S31: =S30/R30-1 | T31: =T30/S30-1 | V31: =V30/T30-1 | W31: =W30/V30-1 | X31: =X30/W30-1 | Y31: =Y30/X30-1 | AA31: =AA30/Y30-1 | AB31: =AB30/AA30-1 | AC31: =AC30/AB30-1 | AD31: =AD30/AC30-1 | AF31: =AF30/AD30-1 | AG31: =AG30/AF30-1 | AH31: =AH30/AG30-1 | AI31: =AI30/AH30-1 | AK31: =AK30/AI30-1 | AL31: =AL30/AK30-1 | AM31: =AM30/AL30-1 | AN31: =AN30/AM30-1 | AP31: =AP30/AN30-1 | AQ31: =AQ30/AP30-1 | AR31: =AR30/AQ30-1 | AS31: =AS30/AR30-1 | AU31: =AU30/AS30-1 | AV31: =AV30/AU30-1 | AW31: =AW30/AV30-1 | AX31: =AX30/AW30-1 | AZ31: =AZ30/AX30-1 | BA31: =BA30/AZ30-1 | BB31: =BB30/BA30-1 | BC31: =BC30/BB30-1 | BE31: =BE30/BC30-1 | BF31: =BF30/BE30-1 | BG31: =BG30/BF30-1 | BH31: =BH30/BG30-1 | BJ31: =BJ30/BH30-1 | BK31: =BK30/BJ30-1 | BL31: =BL30/BK30-1 | BM31: =BM30/BL30-1 | BO31: =BO30/BM30-1 | BP31: =BP30/BO30-1 | BQ31: =BQ30/BP30-1 | BR31: =BR30/BQ30-1 | BT31: =BT30/BR30-1 | BU31: =BU30/BT30-1 | BV31: =BV30/BU30-1 | BW31: =BW30/BV30-1 | BY31: =BY30/BW30-1 | BZ31: =BZ30/BY30-1 | CA31: =CA30/BZ30-1 | CB31: =CB30/CA30-1
A32: Y/Y OEM & IP Revenue Growth, % | U32: =+U30/P30-1 | V32: =+V30/Q30-1 | W32: =+W30/R30-1 | X32: =+X30/S30-1 | Y32: =+Y30/T30-1 | Z32: =+Z30/U30-1 | AA32: =+AA30/V30-1 | AB32: =+AB30/W30-1 | ... BV32: =+BV30/BQ30-1 | BW32: 0.5 | BX32: =+BX30/BS30-1 | BY32: 0.1 | BZ32: 0.1 | CA32: 0.1 | CB32: 0.1 | CC32: =+CC30/BX30-1 | CD32: 0.1 | CE32: 0.1 | CF32: 0.1
A34: Total Revenue, mm | C34: =C292 | D34: =D292 | E34: =E292 | F34: =F292 | G34: =G292 | H34: =H292 | I34: =I292 | J34: =J292 | ... O34: =O292 | P34: =P7+P11+P22+P26+P30 | Q34: =Q7+Q11+Q22+Q26+Q30 | R34: =R7+R11+R22+R26+R30 | S34: =S7+S11+S22+S26+S30 | T34: =T7+T11+T22+T26+T30 | U34: =U7+U11+U22+U26+U30 | V34: =V7+V11+V22+V26+V30 | W34: =W7+W11+W22+W26+W30 | ... CF34: =CF7+CF11+CF22+CF26+CF30
A35: =CONCATENATE("Consensus Estimates - ",IFERROR(LEFT(A34,FIND("(",A34)-1),A34)) | BW35: =BW363 | BX35: =BX363 | BY35: =BY363 | BZ35: =BZ363 | CA35: =CA363 | CB35: =CB363 | CC35: =CC363 | CD35: =CD363 | ... CF35: =CF363
A36: Guidance - Total Revenue, mm | BW36: =BW572 | BX36: =BX572 | BY36: =BY572 | BZ36: =BZ572 | CA36: =CA572 | CB36: =CB572 | CC36: =CC572 | CD36: =CD572 | ... CF36: =CF572
A37: Q/Q Total Revenue growth, % | H37: =H34/G34-1 | I37: =I34/H34-1 | J37: =J34/I34-1 | L37: =L34/J34-1 | M37: =M34/L34-1 | N37: =N34/M34-1 | O37: =O34/N34-1 | Q37: =Q34/O34-1 | R37: =R34/Q34-1 | S37: =S34/R34-1 | T37: =T34/S34-1 | V37: =V34/T34-1 | W37: =W34/V34-1 | X37: =X34/W34-1 | Y37: =Y34/X34-1 | AA37: =AA34/Y34-1 | AB37: =AB34/AA34-1 | AC37: =AC34/AB34-1 | AD37: =AD34/AC34-1 | AF37: =AF34/AD34-1 | AG37: =AG34/AF34-1 | AH37: =AH34/AG34-1 | AI37: =AI34/AH34-1 | AK37: =AK34/AI34-1 | AL37: =AL34/AK34-1 | AM37: =AM34/AL34-1 | AN37: =AN34/AM34-1 | AP37: =AP34/AN34-1 | AQ37: =AQ34/AP34-1 | AR37: =AR34/AQ34-1 | AS37: =AS34/AR34-1 | AU37: =AU34/AS34-1 | AV37: =AV34/AU34-1 | AW37: =AW34/AV34-1 | AX37: =AX34/AW34-1 | AZ37: =AZ34/AX34-1 | BA37: =BA34/AZ34-1 | BB37: =BB34/BA34-1 | BC37: =BC34/BB34-1 | BE37: =BE34/BC34-1 | BF37: =BF34/BE34-1 | BG37: =BG34/BF34-1 | BH37: =BH34/BG34-1 | BJ37: =BJ34/BH34-1 | BK37: =BK34/BJ34-1 | BL37: =BL34/BK34-1 | BM37: =BM34/BL34-1 | BO37: =BO34/BM34-1 | BP37: =BP34/BO34-1 | BQ37: =BQ34/BP34-1 | BR37: =BR34/BQ34-1 | BT37: =BT34/BR34-1 | BU37: =BU34/BT34-1 | BV37: =BV34/BU34-1 | BW37: =BW34/BV34-1 | BY37: =BY34/BW34-1 | BZ37: =BZ34/BY34-1 | CA37: =CA34/BZ34-1 | CB37: =CB34/CA34-1
A38: Y/Y Total Revenue Growth, % | D38: =D34/C34-1 | E38: =E34/D34-1 | F38: =F34/E34-1 | K38: =K34/F34-1 | L38: =L34/G34-1 | M38: =M34/H34-1 | N38: =N34/I34-1 | O38: =O34/J34-1 | P38: =P34/K34-1 | Q38: =Q34/L34-1 | R38: =R34/M34-1 | ... CC38: =CC34/BX34-1 | CD38: =CD34/CC34-1 | CE38: =CE34/CD34-1 | CF38: =CF34/CE34-1
A40: Blackwell Revenue, mm | BR40: 11000
A41: CMP Revenue, mm | AF41: 289 | AK41: 0 | AY41: 0 | AZ41: 155 | BA41: 266 | BB41: 105 | BC41: =BD41-SUM(AZ41,BA41,BB41) | BD41: 550 | BE41: 0 | BF41: 0 | BG41: 0 | BH41: =BI41-SUM(BE41,BF41,BG41) | BI41: 0 | BM41: =BN41-SUM(BJ41,BK41,BL41) | BR41: =BS41-SUM(BO41,BP41,BQ41)
A43: Operating Expense Forecasting
A44: Revenue, mm | C44: =C292 | D44: =D292 | E44: =E292 | F44: =F292 | G44: =G292 | H44: =H292 | I44: =I292 | J44: =J292 | ... O44: =O292 | P44: =P34 | Q44: =Q34 | R44: =R34 | S44: =S34 | T44: =T34 | U44: =U34 | V44: =V34 | W44: =W34 | ... CF44: =CF34
A45: Cost of revenue, mm | C45: =C293 | D45: =D293 | E45: =E293 | F45: =F293 | G45: =G293 | H45: =H293 | I45: =I293 | J45: =J293 | ... BV45: =BV293 | BW45: =BW44-BW46 | BX45: =BX44-BX46 | BY45: =BY44-BY46 | BZ45: =BZ44-BZ46 | CA45: =CA44-CA46 | CB45: =CB44-CB46 | CC45: =CC44-CC46 | CD45: =CD44-CD46 | ... CF45: =CF44-CF46
A46: GAAP Gross Profit, mm | C46: =C44-C45 | D46: =D44-D45 | E46: =E44-E45 | F46: =F44-F45 | G46: =G44-G45 | H46: =H44-H45 | I46: =I44-I45 | J46: =J44-J45 | ... BV46: =BV44-BV45 | BW46: =BW57-BW55-BW53-BW51 | BX46: =SUM(BT46,BU46,BV46,BW46) | BY46: =BY57-BY55-BY53-BY51 | BZ46: =BZ57-BZ55-BZ53-BZ51 | CA46: =CA57-CA55-CA53-CA51 | CB46: =CB57-CB55-CB53-CB51 | CC46: =SUM(BY46,BZ46,CA46,CB46) | CD46: =CD57-CD55-CD53-CD51 | CE46: =CE57-CE55-CE53-CE51 | CF46: =CF57-CF55-CF53-CF51
A47: Y/Y growth in Gross Profit, % | D47: =D46/C46-1 | E47: =E46/D46-1 | F47: =F46/E46-1 | K47: =K46/F46-1 | L47: =L46/G46-1 | M47: =M46/H46-1 | N47: =N46/I46-1 | O47: =O46/J46-1 | P47: =P46/K46-1 | Q47: =Q46/L46-1 | R47: =R46/M46-1 | ... CC47: =CC46/BX46-1 | CD47: =CD46/CC46-1 | CE47: =CE46/CD46-1 | CF47: =CF46/CE46-1
A48: GAAP Gross Margin, % | C48: =C46/C44 | D48: =D46/D44 | E48: =E46/E44 | F48: =F46/F44 | G48: =G46/G44 | H48: =H46/H44 | I48: =I46/I44 | J48: =J46/J44 | ... CF48: =CF46/CF44
A49: Y/Y improvement in GAAP Gross Margin, bps | D49: =(D48-C48)*10000 | E49: =(E48-D48)*10000 | F49: =(F48-E48)*10000 | K49: =(K48-F48)*10000 | L49: =(L48-G48)*10000 | M49: =(M48-H48)*10000 | N49: =(N48-I48)*10000 | O49: =(O48-J48)*10000 | P49: =(P48-K48)*10000 | Q49: =(Q48-L48)*10000 | R49: =(R48-M48)*10000 | ... CC49: =(CC48-BX48)*10000 | CD49: =(CD48-CC48)*10000 | CE49: =(CE48-CD48)*10000 | CF49: =(CF48-CE48)*10000
A51: SBC COGS, mm | C51: =-C367 | D51: =-D367 | E51: =-E367 | F51: =-F367 | G51: =-G367 | H51: =-H367 | I51: =-I367 | J51: =-J367 | ... BV51: =-BV367 | BW51: =BW44*BW52 | BX51: =SUM(BT51,BU51,BV51,BW51) | BY51: =BY44*BY52 | BZ51: =BZ44*BZ52 | CA51: =CA44*CA52 | CB51: =CB44*CB52 | CC51: =SUM(BY51,BZ51,CA51,CB51) | CD51: =CD44*CD52 | CE51: =CE44*CE52 | CF51: =CF44*CF52
A52: SBC COGS as % of revenue, % | C52: =C51/C44 | D52: =D51/D44 | E52: =E51/E44 | F52: =F51/F44 | G52: =G51/G44 | H52: =H51/H44 | I52: =I51/I44 | J52: =J51/J44 | ... BV52: =BV51/BV44 | BW52: 0.001 | BX52: =BX51/BX44 | BY52: 0.001 | BZ52: 0.001 | CA52: 0.001 | CB52: 0.001 | CC52: =CC51/CC44 | CD52: 0.001 | CE52: 0.001 | CF52: 0.001
A53: Acquisition-related costs COGS, mm | C53: =-C368 | D53: =-D368 | E53: =-E368 | F53: =-F368 | G53: =-G368 | H53: =-H368 | I53: =-I368 | J53: =-J368 | ... BV53: =-BV368 | BW53: =BW44*BW54 | BX53: =SUM(BT53,BU53,BV53,BW53) | BY53: =BY44*BY54 | BZ53: =BZ44*BZ54 | CA53: =CA44*CA54 | CB53: =CB44*CB54 | CC53: =SUM(BY53,BZ53,CA53,CB53) | CD53: =CD44*CD54 | CE53: =CE44*CE54 | CF53: =CF44*CF54
A54: Acquisition-related costs COGS as % of revenue, % | C54: =C53/C44 | D54: =D53/D44 | E54: =E53/E44 | F54: =F53/F44 | G54: =G53/G44 | H54: =H53/H44 | I54: =I53/I44 | J54: =J53/J44 | ... BV54: =BV53/BV44 | BW54: 0.001 | BX54: =BX53/BX44 | BY54: 0.001 | BZ54: 0.001 | CA54: 0.001 | CB54: 0.001 | CC54: =CC53/CC44 | CD54: 0.002 | CE54: 0.002 | CF54: 0.002
A55: Other COGS Adjustments, mm | C55: =-C369 | D55: =-D369 | E55: =-E369 | F55: =-F369 | G55: =-G369 | H55: =-H369 | I55: =-I369 | J55: =-J369 | ... BV55: =-BV369 | BW55: 0 | BX55: =SUM(BT55,BU55,BV55,BW55) | BY55: 0 | BZ55: 0 | CA55: 0 | CB55: 0 | CC55: =SUM(BY55,BZ55,CA55,CB55) | CD55: 0 | CE55: 0 | CF55: 0
A56: Non-GAAP COGS, mm | C56: =C45-C51-C53-C55 | D56: =D45-D51-D53-D55 | E56: =E45-E51-E53-E55 | F56: =F45-F51-F53-F55 | G56: =G45-G51-G53-G55 | H56: =H45-H51-H53-H55 | I56: =I45-I51-I53-I55 | J56: =J45-J51-J53-J55 | ... BV56: =BV45-BV51-BV53-BV55 | BW56: =BW44-BW57 | BX56: =SUM(BT56,BU56,BV56,BW56) | BY56: =BY44-BY57 | BZ56: =BZ44-BZ57 | CA56: =CA44-CA57 | CB56: =CB44-CB57 | CC56: =SUM(BY56,BZ56,CA56,CB56) | CD56: =CD44-CD57 | CE56: =CE44-CE57 | CF56: =CF44-CF57
A57: Non-GAAP Gross Profit, mm | C57: =C44-C56 | D57: =D44-D56 | E57: =E44-E56 | F57: =F44-F56 | G57: =G44-G56 | H57: =H44-H56 | I57: =I44-I56 | J57: =J44-J56 | ... BV57: =BV44-BV56 | BW57: =BW44*BW59 | BX57: =SUM(BT57,BU57,BV57,BW57) | BY57: =BY44*BY59 | BZ57: =BZ44*BZ59 | CA57: =CA44*CA59 | CB57: =CB44*CB59 | CC57: =SUM(BY57,BZ57,CA57,CB57) | CD57: =CD44*CD59 | CE57: =CE44*CE59 | CF57: =CF44*CF59
A58: Y/Y Non-GAAP gross profit growth, % | D58: =D57/C57-1 | E58: =E57/D57-1 | F58: =F57/E57-1 | K58: =K57/F57-1 | L58: =L57/G57-1 | M58: =M57/H57-1 | N58: =N57/I57-1 | O58: =O57/J57-1 | P58: =P57/K57-1 | Q58: =Q57/L57-1 | R58: =R57/M57-1 | ... CC58: =CC57/BX57-1 | CD58: =CD57/CC57-1 | CE58: =CE57/CD57-1 | CF58: =CF57/CE57-1
A59: Non-GAAP Gross Margin, % | C59: =C57/C44 | D59: =D57/D44 | E59: =E57/E44 | F59: =F57/F44 | G59: =G57/G44 | H59: =H57/H44 | I59: =I57/I44 | J59: =J57/J44 | ... BV59: =BV57/BV44 | BW59: =BR59+BW62/10000 | BX59: =BX57/BX44 | BY59: =BT59+BY62/10000 | BZ59: =BU59+BZ62/10000 | CA59: =BV59+CA62/10000 | CB59: =BW59+CB62/10000 | CC59: =CC57/CC44 | CD59: =CC59+CD62/10000 | CE59: =CD59+CE62/10000 | CF59: =CE59+CF62/10000
A60: Consensus Estimates - Non-GAAP Gross Margin, % | BW60: =BW279 | BX60: =BX279 | BY60: =BY279 | BZ60: =BZ279 | CA60: =CA279 | CB60: =CB279 | CC60: =CC279 | CD60: =CD279 | ... CF60: =CF279
A61: Guidance - Non-GAAP Gross Margin, % | BW61: =BW642 | BX61: =BX642 | BY61: =BY642 | BZ61: =BZ642 | CA61: =CA642 | CB61: =CB642 | CC61: =CC642 | CD61: =CD642 | ... CF61: =CF642
A62: Y/Y Improvement in non-GAAP gross margin, bps | D62: =(D59-C59)*10000 | E62: =(E59-D59)*10000 | F62: =(F59-E59)*10000 | K62: =(K59-F59)*10000 | L62: =(L59-G59)*10000 | M62: =(M59-H59)*10000 | N62: =(N59-I59)*10000 | O62: =(O59-J59)*10000 | P62: =(P59-K59)*10000 | Q62: =(Q59-L59)*10000 | R62: =(R59-M59)*10000 | ... BV62: =(BV59-BQ59)*10000 | BW62: 150 | BX62: =(BX59-BS59)*10000 | BY62: 1500 | BZ62: 200 | CA62: 100 | CB62: 100 | CC62: =(CC59-BX59)*10000 | CD62: 0 | CE62: 0 | CF62: 0
A64: GAAP R&D Expense, mm | C64: =C373 | D64: =D373 | E64: =E373 | F64: =F373 | G64: =G373 | H64: =H373 | I64: =I373 | J64: =J373 | ... BV64: =BV373 | BW64: =BW74+BW71+BW69+BW73 | BX64: =SUM(BT64,BU64,BV64,BW64) | BY64: =BY74+BY71+BY69+BY73 | BZ64: =BZ74+BZ71+BZ69+BZ73 | CA64: =CA74+CA71+CA69+CA73 | CB64: =CB74+CB71+CB69+CB73 | CC64: =SUM(BY64,BZ64,CA64,CB64) | CD64: =CD74+CD71+CD69+CD73 | CE64: =CE74+CE71+CE69+CE73 | CF64: =CF74+CF71+CF69+CF73
A65: Y/Y growth in GAAP R&D, % | D65: =D64/C64-1 | E65: =E64/D64-1 | F65: =F64/E64-1 | K65: =K64/F64-1 | L65: =L64/G64-1 | M65: =M64/H64-1 | N65: =N64/I64-1 | O65: =O64/J64-1 | P65: =P64/K64-1 | Q65: =Q64/L64-1 | R65: =R64/M64-1 | ... CC65: =CC64/BX64-1 | CD65: =CD64/CC64-1 | CE65: =CE64/CD64-1 | CF65: =CF64/CE64-1
A66: GAAP R&D Margin, % | C66: =C64/C44 | D66: =D64/D44 | E66: =E64/E44 | F66: =F64/F44 | G66: =G64/G44 | H66: =H64/H44 | I66: =I64/I44 | J66: =J64/J44 | ... CF66: =CF64/CF44
A67: Y/Y Improvement in GAAP R&D Margin, bps | D67: =-(D66-C66)*10000 | E67: =-(E66-D66)*10000 | F67: =-(F66-E66)*10000 | K67: =-(K66-F66)*10000 | L67: =-(L66-G66)*10000 | M67: =-(M66-H66)*10000 | N67: =-(N66-I66)*10000 | O67: =-(O66-J66)*10000 | P67: =-(P66-K66)*10000 | Q67: =-(Q66-L66)*10000 | R67: =-(R66-M66)*10000 | ... CC67: =-(CC66-BX66)*10000 | CD67: =-(CD66-CC66)*10000 | CE67: =-(CE66-CD66)*10000 | CF67: =-(CF66-CE66)*10000
A69: SBC R&D, mm | C69: =C374 | D69: =D374 | E69: =E374 | F69: =F374 | G69: =G374 | H69: =H374 | I69: =I374 | J69: =J374 | ... BV69: =BV374 | BW69: =BW44*BW70 | BX69: =SUM(BT69,BU69,BV69,BW69) | BY69: =BY44*BY70 | BZ69: =BZ44*BZ70 | CA69: =CA44*CA70 | CB69: =CB44*CB70 | CC69: =SUM(BY69,BZ69,CA69,CB69) | CD69: =CD44*CD70 | CE69: =CE44*CE70 | CF69: =CF44*CF70
A70: SBC R&D as % of revenue, % | C70: =C69/C44 | D70: =D69/D44 | E70: =E69/E44 | F70: =F69/F44 | G70: =G69/G44 | H70: =H69/H44 | I70: =I69/I44 | J70: =J69/J44 | ... BV70: =BV69/BV44 | BW70: 0.021 | BX70: =BX69/BX44 | BY70: 0.021 | BZ70: 0.021 | CA70: 0.021 | CB70: 0.021 | CC70: =CC69/CC44 | CD70: 0.021 | CE70: 0.021 | CF70: 0.021
A71: Acquisition-related costs R&D, mm | C71: =C375 | D71: =D375 | E71: =E375 | F71: =F375 | G71: =G375 | H71: =H375 | I71: =I375 | J71: =J375 | ... BV71: =BV375 | BW71: =BW44*BW72 | BX71: =SUM(BT71,BU71,BV71,BW71) | BY71: =BY44*BY72 | BZ71: =BZ44*BZ72 | CA71: =CA44*CA72 | CB71: =CB44*CB72 | CC71: =SUM(BY71,BZ71,CA71,CB71) | CD71: =CD44*CD72 | CE71: =CE44*CE72 | CF71: =CF44*CF72
A72: Acquisition-related costs R&D as % of revenue, % | C72: =C71/C44 | D72: =D71/D44 | E72: =E71/E44 | F72: =F71/F44 | G72: =G71/G44 | H72: =H71/H44 | I72: =I71/I44 | J72: =J71/J44 | ... BV72: =BV71/BV44 | BW72: 0.001 | BX72: =BX71/BX44 | BY72: 0.001 | BZ72: 0.001 | CA72: 0.001 | CB72: 0.001 | CC72: =CC71/CC44 | CD72: 0.001 | CE72: 0.001 | CF72: 0.001
A73: Other R&D, mm | C73: =C376 | D73: =D376 | E73: =E376 | F73: =F376 | G73: =G376 | H73: =H376 | I73: =I376 | J73: =J376 | ... BV73: =BV376 | BW73: 0 | BX73: =SUM(BT73,BU73,BV73,BW73) | BY73: 0 | BZ73: 0 | CA73: 0 | CB73: 0 | CC73: =SUM(BY73,BZ73,CA73,CB73) | CD73: 0 | CE73: 0 | CF73: 0
A74: Non-GAAP R&D Expense, mm | C74: =C64-C69-C71-C73 | D74: =D64-D69-D71-D73 | E74: =E64-E69-E71-E73 | F74: =F64-F69-F71-F73 | G74: =G64-G69-G71-G73 | H74: =H64-H69-H71-H73 | I74: =I64-I69-I71-I73 | J74: =J64-J69-J71-J73 | ... BV74: =BV64-BV69-BV71-BV73 | BW74: =BW44*BW76 | BX74: =SUM(BT74,BU74,BV74,BW74) | BY74: =BY44*BY76 | BZ74: =BZ44*BZ76 | CA74: =CA44*CA76 | CB74: =CB44*CB76 | CC74: =SUM(BY74,BZ74,CA74,CB74) | CD74: =CD44*CD76 | CE74: =CE44*CE76 | CF74: =CF44*CF76
A75: Y/Y Growth in non-GAAP R&D Expense, % | D75: =D74/C74-1 | E75: =E74/D74-1 | F75: =F74/E74-1 | K75: =K74/F74-1 | L75: =L74/G74-1 | M75: =M74/H74-1 | N75: =N74/I74-1 | O75: =O74/J74-1 | P75: =P74/K74-1 | Q75: =Q74/L74-1 | R75: =R74/M74-1 | ... CC75: =CC74/BX74-1 | CD75: =CD74/CC74-1 | CE75: =CE74/CD74-1 | CF75: =CF74/CE74-1
A76: Non-GAAP R&D Margin, % | C76: =C74/C44 | D76: =D74/D44 | E76: =E74/E44 | F76: =F74/F44 | G76: =G74/G44 | H76: =H74/H44 | I76: =I74/I44 | J76: =J74/J44 | ... BV76: =BV74/BV44 | BW76: =BR76-BW77/10000 | BX76: =BX74/BX44 | BY76: =BT76-BY77/10000 | BZ76: =BU76-BZ77/10000 | CA76: =BV76-CA77/10000 | CB76: =BW76-CB77/10000 | CC76: =CC74/CC44 | CD76: =CC76-CD77/10000 | CE76: =CD76-CE77/10000 | CF76: =CE76-CF77/10000
A77: Y/Y Improvement in Non-GAAP R&D Margin, bps | D77: =-(D76-C76)*10000 | E77: =-(E76-D76)*10000 | F77: =-(F76-E76)*10000 | K77: =-(K76-F76)*10000 | L77: =-(L76-G76)*10000 | M77: =-(M76-H76)*10000 | N77: =-(N76-I76)*10000 | O77: =-(O76-J76)*10000 | P77: =-(P76-K76)*10000 | Q77: =-(Q76-L76)*10000 | R77: =-(R76-M76)*10000 | ... BV77: =-(BV76-BQ76)*10000 | BW77: 60 | BX77: =-(BX76-BS76)*10000 | BY77: 0 | BZ77: 0 | CA77: 0 | CB77: 0 | CC77: =-(CC76-BX76)*10000 | CD77: 0 | CE77: 0 | CF77: 0
A79: GAAP SG&A Expense, mm | C79: =C378 | D79: =D378 | E79: =E378 | F79: =F378 | G79: =G378 | H79: =H378 | I79: =I378 | J79: =J378 | ... BV79: =BV378 | BW79: =BW89+BW86+BW84+BW88 | BX79: =SUM(BT79,BU79,BV79,BW79) | BY79: =BY89+BY86+BY84+BY88 | BZ79: =BZ89+BZ86+BZ84+BZ88 | CA79: =CA89+CA86+CA84+CA88 | CB79: =CB89+CB86+CB84+CB88 | CC79: =SUM(BY79,BZ79,CA79,CB79) | CD79: =CD89+CD86+CD84+CD88 | CE79: =CE89+CE86+CE84+CE88 | CF79: =CF89+CF86+CF84+CF88
A80: Y/Y growth in GAAP SG&A, % | D80: =D79/C79-1 | E80: =E79/D79-1 | F80: =F79/E79-1 | K80: =K79/F79-1 | L80: =L79/G79-1 | M80: =M79/H79-1 | N80: =N79/I79-1 | O80: =O79/J79-1 | P80: =P79/K79-1 | Q80: =Q79/L79-1 | R80: =R79/M79-1 | ... CC80: =CC79/BX79-1 | CD80: =CD79/CC79-1 | CE80: =CE79/CD79-1 | CF80: =CF79/CE79-1
A81: GAAP SG&A Margin, % | C81: =C79/C44 | D81: =D79/D44 | E81: =E79/E44 | F81: =F79/F44 | G81: =G79/G44 | H81: =H79/H44 | I81: =I79/I44 | J81: =J79/J44 | ... CF81: =CF79/CF44
A82: Y/Y Improvement in GAAP SG&A Margin, bps | D82: =-(D81-C81)*10000 | E82: =-(E81-D81)*10000 | F82: =-(F81-E81)*10000 | K82: =-(K81-F81)*10000 | L82: =-(L81-G81)*10000 | M82: =-(M81-H81)*10000 | N82: =-(N81-I81)*10000 | O82: =-(O81-J81)*10000 | P82: =-(P81-K81)*10000 | Q82: =-(Q81-L81)*10000 | R82: =-(R81-M81)*10000 | ... CC82: =-(CC81-BX81)*10000 | CD82: =-(CD81-CC81)*10000 | CE82: =-(CE81-CD81)*10000 | CF82: =-(CF81-CE81)*10000
A84: SBC SG&A, mm | C84: =C379 | D84: =D379 | E84: =E379 | F84: =F379 | G84: =G379 | H84: =H379 | I84: =I379 | J84: =J379 | ... BV84: =BV379 | BW84: =BW44*BW85 | BX84: =SUM(BT84,BU84,BV84,BW84) | BY84: =BY44*BY85 | BZ84: =BZ44*BZ85 | CA84: =CA44*CA85 | CB84: =CB44*CB85 | CC84: =SUM(BY84,BZ84,CA84,CB84) | CD84: =CD44*CD85 | CE84: =CE44*CE85 | CF84: =CF44*CF85
A85: SBC SG&A as % of revenue, % | C85: =C84/C44 | D85: =D84/D44 | E85: =E84/E44 | F85: =F84/F44 | G85: =G84/G44 | H85: =H84/H44 | I85: =I84/I44 | J85: =J84/J44 | ... BV85: =BV84/BV44 | BW85: 0.007 | BX85: =BX84/BX44 | BY85: 0.007 | BZ85: 0.007 | CA85: 0.007 | CB85: 0.007 | CC85: =CC84/CC44 | CD85: 0.007 | CE85: 0.007 | CF85: 0.007
A86: Acquisition-related costs SG&A, mm | C86: =C380 | D86: =D380 | E86: =E380 | F86: =F380 | G86: =G380 | H86: =H380 | I86: =I380 | J86: =J380 | ... BV86: =BV380 | BW86: =BW44*BW87 | BX86: =SUM(BT86,BU86,BV86,BW86) | BY86: =BY44*BY87 | BZ86: =BZ44*BZ87 | CA86: =CA44*CA87 | CB86: =CB44*CB87 | CC86: =SUM(BY86,BZ86,CA86,CB86) | CD86: =CD44*CD87 | CE86: =CE44*CE87 | CF86: =CF44*CF87
A87: Acquisition-related costs SG&A as % of revenue, % | C87: =C86/C44 | D87: =D86/D44 | E87: =E86/E44 | F87: =F86/F44 | G87: =G86/G44 | H87: =H86/H44 | I87: =I86/I44 | J87: =J86/J44 | ... BV87: =BV86/BV44 | BW87: 0.0002 | BX87: =BX86/BX44 | BY87: 0.0002 | BZ87: 0.0002 | CA87: 0.0002 | CB87: 0.0002 | CC87: =CC86/CC44 | CD87: 0.0002 | CE87: 0.0002 | CF87: 0.0002
A88: Other SG&A, mm | C88: =C381 | D88: =D381 | E88: =E381 | F88: =F381 | G88: =G381 | H88: =H381 | I88: =I381 | J88: =J381 | ... BV88: =BV381 | BW88: 0 | BX88: =SUM(BT88,BU88,BV88,BW88) | BY88: 0 | BZ88: 0 | CA88: 0 | CB88: 0 | CC88: =SUM(BY88,BZ88,CA88,CB88) | CD88: 0 | CE88: 0 | CF88: 0
A89: Non-GAAP SG&A Expense, mm | C89: =C79-C84-C86-C88 | D89: =D79-D84-D86-D88 | E89: =E79-E84-E86-E88 | F89: =F79-F84-F86-F88 | G89: =G79-G84-G86-G88 | H89: =H79-H84-H86-H88 | I89: =I79-I84-I86-I88 | J89: =J79-J84-J86-J88 | ... BV89: =BV79-BV84-BV86-BV88 | BW89: =BW91*BW44 | BX89: =SUM(BT89,BU89,BV89,BW89) | BY89: =BY91*BY44 | BZ89: =BZ91*BZ44 | CA89: =CA91*CA44 | CB89: =CB91*CB44 | CC89: =SUM(BY89,BZ89,CA89,CB89) | CD89: =CD91*CD44 | CE89: =CE91*CE44 | CF89: =CF91*CF44
A90: Y/Y Growth in non-GAAP SG&A Expense, % | D90: =D89/C89-1 | E90: =E89/D89-1 | F90: =F89/E89-1 | K90: =K89/F89-1 | L90: =L89/G89-1 | M90: =M89/H89-1 | N90: =N89/I89-1 | O90: =O89/J89-1 | P90: =P89/K89-1 | Q90: =Q89/L89-1 | R90: =R89/M89-1 | ... CC90: =CC89/BX89-1 | CD90: =CD89/CC89-1 | CE90: =CE89/CD89-1 | CF90: =CF89/CE89-1
A91: Non-GAAP SG&A Margin, % | C91: =C89/C44 | D91: =D89/D44 | E91: =E89/E44 | F91: =F89/F44 | G91: =G89/G44 | H91: =H89/H44 | I91: =I89/I44 | J91: =J89/J44 | ... BV91: =BV89/BV44 | BW91: =BR91-BW92/10000 | BX91: =BX89/BX44 | BY91: =BT91-BY92/10000 | BZ91: =BU91-BZ92/10000 | CA91: =BV91-CA92/10000 | CB91: =BW91-CB92/10000 | CC91: =CC89/CC44 | CD91: =CC91-CD92/10000 | CE91: =CD91-CE92/10000 | CF91: =CE91-CF92/10000
A92: Y/Y Improvement in Non-GAAP SG&A Margin, bps | D92: =-(D91-C91)*10000 | E92: =-(E91-D91)*10000 | F92: =-(F91-E91)*10000 | K92: =-(K91-F91)*10000 | L92: =-(L91-G91)*10000 | M92: =-(M91-H91)*10000 | N92: =-(N91-I91)*10000 | O92: =-(O91-J91)*10000 | P92: =-(P91-K91)*10000 | Q92: =-(Q91-L91)*10000 | R92: =-(R91-M91)*10000 | ... BV92: =-(BV91-BQ91)*10000 | BW92: 30 | BX92: =-(BX91-BS91)*10000 | BY92: 0 | BZ92: 0 | CA92: 0 | CB92: 0 | CC92: =-(CC91-BX91)*10000 | CD92: 5 | CE92: 5 | CF92: 5
A94: GAAP OPEX Expense, mm | C94: =SUM(C297:C299) | D94: =SUM(D297:D299) | E94: =SUM(E297:E299) | F94: =SUM(F297:F299) | G94: =SUM(G297:G299) | H94: =SUM(H297:H299) | I94: =SUM(I297:I299) | J94: =SUM(J297:J299) | ... BV94: =SUM(BV297:BV299) | BW94: =BW100+BW99 | BX94: =SUM(BT94,BU94,BV94,BW94) | BY94: =BY100+BY99 | BZ94: =BZ100+BZ99 | CA94: =CA100+CA99 | CB94: =CB100+CB99 | CC94: =SUM(BY94,BZ94,CA94,CB94) | CD94: =CD100+CD99 | CE94: =CE100+CE99 | CF94: =CF100+CF99
A95: Y/Y growth in GAAP OPEX, % | D95: =IFERROR(D94/C94-1,"N/A") | E95: =IFERROR(E94/D94-1,"N/A") | F95: =IFERROR(F94/E94-1,"N/A") | K95: =IFERROR(K94/F94-1,"N/A") | L95: =IFERROR(L94/G94-1,"N/A") | M95: =IFERROR(M94/H94-1,"N/A") | N95: =IFERROR(N94/I94-1,"N/A") | O95: =IFERROR(O94/J94-1,"N/A") | P95: =IFERROR(P94/K94-1,"N/A") | Q95: =IFERROR(Q94/L94-1,"N/A") | R95: =IFERROR(R94/M94-1,"N/A") | ... CC95: =IFERROR(CC94/BX94-1,"N/A") | CD95: =IFERROR(CD94/CC94-1,"N/A") | CE95: =IFERROR(CE94/CD94-1,"N/A") | CF95: =IFERROR(CF94/CE94-1,"N/A")
A96: GAAP OPEX Margin, % | C96: =C94/C44 | D96: =D94/D44 | E96: =E94/E44 | F96: =F94/F44 | G96: =G94/G44 | H96: =H94/H44 | I96: =I94/I44 | J96: =J94/J44 | ... CF96: =CF94/CF44
A97: Y/Y Improvement in GAAP OPEX Margin, bps | D97: =-(D96-C96)*10000 | E97: =-(E96-D96)*10000 | F97: =-(F96-E96)*10000 | K97: =-(K96-F96)*10000 | L97: =-(L96-G96)*10000 | M97: =-(M96-H96)*10000 | N97: =-(N96-I96)*10000 | O97: =-(O96-J96)*10000 | P97: =-(P96-K96)*10000 | Q97: =-(Q96-L96)*10000 | R97: =-(R96-M96)*10000 | ... CC97: =-(CC96-BX96)*10000 | CD97: =-(CD96-CC96)*10000 | CE97: =-(CE96-CD96)*10000 | CF97: =-(CF96-CE96)*10000
A99: Other OPEX Adjustments, mm | C99: =C384 | D99: =D384 | E99: =E384 | F99: =F384 | G99: =G384 | H99: =H384 | I99: =I384 | J99: =J384 | ... BV99: =BV384 | BW99: 0 | BX99: =SUM(BT99,BU99,BV99,BW99) | BY99: 0 | BZ99: 0 | CA99: 0 | CB99: 0 | CC99: =SUM(BY99,BZ99,CA99,CB99) | CD99: 0 | CE99: 0 | CF99: 0
A100: Non-GAAP OPEX Expense, mm | C100: =C94-C99 | D100: =D94-D99 | E100: =E94-E99 | F100: =F94-F99 | G100: =G94-G99 | H100: =H94-H99 | I100: =I94-I99 | J100: =J94-J99 | ... BV100: =BV94-BV99 | BW100: 0 | BX100: =BX94-BX99 | BY100: 0 | BZ100: 0 | CA100: 0 | CB100: 0 | CC100: =CC94-CC99 | CD100: 0 | CE100: 0 | CF100: 0
A101: Y/Y Growth in non-GAAP OPEX Expense, % | D101: =IFERROR(D100/C100-1,"N/A") | E101: =IFERROR(E100/D100-1,"N/A") | F101: =IFERROR(F100/E100-1,"N/A") | K101: =IFERROR(K100/F100-1,"N/A") | L101: =IFERROR(L100/G100-1,"N/A") | M101: =IFERROR(M100/H100-1,"N/A") | N101: =IFERROR(N100/I100-1,"N/A") | O101: =IFERROR(O100/J100-1,"N/A") | P101: =IFERROR(P100/K100-1,"N/A") | Q101: =IFERROR(Q100/L100-1,"N/A") | R101: =IFERROR(R100/M100-1,"N/A") | ... CC101: =IFERROR(CC100/BX100-1,"N/A") | CD101: =IFERROR(CD100/CC100-1,"N/A") | CE101: =IFERROR(CE100/CD100-1,"N/A") | CF101: =IFERROR(CF100/CE100-1,"N/A")
A102: Non-GAAP OPEX Margin, % | C102: =C100/C44 | D102: =D100/D44 | E102: =E100/E44 | F102: =F100/F44 | G102: =G100/G44 | H102: =H100/H44 | I102: =I100/I44 | J102: =J100/J44 | ... CF102: =CF100/CF44
A103: Y/Y Improvement in Non-GAAP OPEX Margin, bps | D103: =-(D102-C102)*10000 | E103: =-(E102-D102)*10000 | F103: =-(F102-E102)*10000 | K103: =-(K102-F102)*10000 | L103: =-(L102-G102)*10000 | M103: =-(M102-H102)*10000 | N103: =-(N102-I102)*10000 | O103: =-(O102-J102)*10000 | P103: =-(P102-K102)*10000 | Q103: =-(Q102-L102)*10000 | R103: =-(R102-M102)*10000 | ... CC103: =-(CC102-BX102)*10000 | CD103: =-(CD102-CC102)*10000 | CE103: =-(CE102-CD102)*10000 | CF103: =-(CF102-CE102)*10000
A105: Other Non-GAAP Operating Items, mm | C105: =C387 | D105: =D387 | E105: =E387 | F105: =F387 | G105: =G387 | H105: =H387 | I105: =I387 | J105: =J387 | ... BV105: =BV387 | BW105: 0 | BX105: =SUM(BT105,BU105,BV105,BW105) | BY105: 0 | BZ105: 0 | CA105: 0 | CB105: 0 | CC105: =SUM(BY105,BZ105,CA105,CB105) | CD105: 0 | CE105: 0 | CF105: 0
A106: Non-GAAP Operating Income, mm | C106: =C57-C74-C89-C100-C105 | D106: =D57-D74-D89-D100-D105 | E106: =E57-E74-E89-E100-E105 | F106: =F57-F74-F89-F100-F105 | G106: =G57-G74-G89-G100-G105 | H106: =H57-H74-H89-H100-H105 | I106: =I57-I74-I89-I100-I105 | J106: =J57-J74-J89-J100-J105 | ... CF106: =CF57-CF74-CF89-CF100-CF105
A107: =CONCATENATE("Consensus Estimates - ",IFERROR(LEFT(A106,FIND("(",A106)-1),A106)) | BW107: =BW389 | BX107: =BX389 | BY107: =BY389 | BZ107: =BZ389 | CA107: =CA389 | CB107: =CB389 | CC107: =CC389 | CD107: =CD389 | ... CF107: =CF389
A108: Y/Y Growth in Non-GAAP Operating Income, % | D108: =D106/C106-1 | E108: =E106/D106-1 | F108: =F106/E106-1 | K108: =K106/F106-1 | L108: =L106/G106-1 | M108: =M106/H106-1 | N108: =N106/I106-1 | O108: =O106/J106-1 | P108: =P106/K106-1 | Q108: =Q106/L106-1 | R108: =R106/M106-1 | ... CC108: =CC106/BX106-1 | CD108: =CD106/CC106-1 | CE108: =CE106/CD106-1 | CF108: =CF106/CE106-1
A109: Non-GAAP Operating Income margin, % | C109: =C106/C44 | D109: =D106/D44 | E109: =E106/E44 | F109: =F106/F44 | G109: =G106/G44 | H109: =H106/H44 | I109: =I106/I44 | J109: =J106/J44 | ... CF109: =CF106/CF44
A110: Consensus Estimates - Non-GAAP Operating Income Margin, % | BW110: =BW287 | BX110: =BX287 | BY110: =BY287 | BZ110: =BZ287 | CA110: =CA287 | CB110: =CB287 | CC110: =CC287 | CD110: =CD287 | ... CF110: =CF287
A111: Y/Y Improvement in Non-GAAP Operating Income margin, bps | D111: =(D109-C109)*10000 | E111: =(E109-D109)*10000 | F111: =(F109-E109)*10000 | K111: =(K109-F109)*10000 | L111: =(L109-G109)*10000 | M111: =(M109-H109)*10000 | N111: =(N109-I109)*10000 | O111: =(O109-J109)*10000 | P111: =(P109-K109)*10000 | Q111: =(Q109-L109)*10000 | R111: =(R109-M109)*10000 | ... CC111: =(CC109-BX109)*10000 | CD111: =(CD109-CC109)*10000 | CE111: =(CE109-CD109)*10000 | CF111: =(CF109-CE109)*10000
A113: Total Non-GAAP Operating Expenses, mm | C113: =+C100+C89+C74 | D113: =+D100+D89+D74 | E113: =+E100+E89+E74 | F113: =+F100+F89+F74 | G113: =+G100+G89+G74 | H113: =+H100+H89+H74 | I113: =+I100+I89+I74 | J113: =+J100+J89+J74 | ... CF113: =+CF100+CF89+CF74
A114: =CONCATENATE("Guidance - ",IFERROR(LEFT(A113,FIND("(",A113)-1),A113)) | AH114: =+AH522 | AI114: =+AI522 | AJ114: =+AJ522 | AK114: =+AK522 | AL114: =+AL522 | AM114: =+AM522 | AN114: =+AN522 | AO114: =+AO522 | ... CF114: =+CF522
A116: SBC, D&A, Acquisition-related Costs Breakdown (FS)
A117: Depreciation, mm | C117: =C119-C118 | D117: =D119-D118 | E117: =E119-E118 | F117: =F119-F118 | G117: =G119-G118 | H117: =H119-H118 | I117: =I119-I118 | J117: =J119-J118 | ... Y117: =Y119-Y118 | Z117: 124 | AA117: =AA119-AA118 | AB117: =AB119-AB118 | AC117: =AC119-AC118 | AD117: =AD119-AD118 | AE117: =AE119-AE118 | AF117: =AF119-AF118 | AG117: =AG119-AG118 | AH117: =AH119-AH118 | AI117: =AI119-AI118 | AJ117: 144 | AK117: =AK119-AK118 | AL117: =AL119-AL118 | AM117: =AM119-AM118 | AN117: =AN119-AN118 | AO117: 233 | AP117: =AP119-AP118 | AQ117: =AQ119-AQ118 | AR117: =AR119-AR118 | AS117: =AS119-AS118 | AT117: =AT119-AT118 | AU117: =AU119-AU118 | AV117: =AV119-AV118 | AW117: =AW119-AW118 | AX117: =AX119-AX118 | AY117: 486 | AZ117: =AZ119-AZ118 | BA117: =BA119-BA118 | BB117: =BB119-BB118 | BC117: =BD117-SUM(AZ117,BA117,BB117) | BD117: 611 | BE117: =BE119-BE118 | BF117: =BF119-BF118 | BG117: =BG119-BG118 | BH117: =BI117-SUM(BE117,BF117,BG117) | BI117: 844 | BJ117: =BJ119-BJ118 | BK117: =BK119-BK118 | BL117: =BL119-BL118 | BM117: =BN117-SUM(BJ117,BK117,BL117) | BN117: 894 | BO117: =BO119-BO118 | BP117: =BP119-BP118 | BQ117: =BQ119-BQ118 | BR117: =BS117-SUM(BO117,BP117,BQ117) | BS117: =BS119-BS118 | BT117: =BT119-BT118 | BU117: =BU119-BU118 | BV117: =BV119-BV118 | BW117: =BW391 | BX117: =SUM(BT117,BU117,BV117,BW117) | BY117: =BY391 | BZ117: =BZ391 | CA117: =CA391 | CB117: =CB391 | CC117: =SUM(BY117,BZ117,CA117,CB117) | CD117: =CD391 | CE117: =CE391 | CF117: =CF391
A118: Amortization, mm | C118: 32.6 | D118: 31.9 | E118: 30 | F118: 59 | G118: 16.6 | H118: 17.2 | I118: 17.3 | J118: =K118-SUM(G118,H118,I118) | K118: 68.4 | L118: 17.4 | M118: 18.6 | N118: 19.6 | O118: =P118-SUM(L118,M118,N118) | P118: 72.7 | Q118: 19 | R118: 19 | S118: 19 | T118: =U118-SUM(Q118,R118,S118) | U118: 77 | V118: 19 | W118: 19 | X118: 18 | Y118: =Z118-SUM(V118,W118,X118) | Z118: 73 | AA118: 17 | AB118: 18 | AC118: 18 | AD118: =AE118-SUM(AA118,AB118,AC118) | AE118: 68 | AF118: 15 | AG118: 14 | AH118: 13 | AI118: =AJ118-SUM(AF118,AG118,AH118) | AJ118: 55 | AK118: 11 | AL118: 6 | AM118: 7 | AN118: =AO118-SUM(AK118,AL118,AM118) | AO118: 29 | AP118: 7 | AQ118: 6 | AR118: 6 | AS118: =AT118-SUM(AP118,AQ118,AR118) | AT118: 25 | AU118: 7 | AV118: 284 | AW118: 174 | AX118: =AY118-SUM(AU118,AV118,AW118) | AY118: 612 | AZ118: 137 | BA118: 138 | BB118: 143 | BC118: =BD118-SUM(AZ118,BA118,BB118) | BD118: 563 | BE118: 155 | BF118: 182 | BG118: 181 | BH118: =BI118-SUM(BE118,BF118,BG118) | BI118: 699 | BJ118: 181 | BK118: 146 | BL118: 144 | BM118: =BN118-SUM(BJ118,BK118,BL118) | BN118: 614 | BO118: 143 | BP118: 146 | BQ118: 149 | BR118: =BS118-SUM(BO118,BP118,BQ118) | BS118: 593 | BT118: 159 | BU118: 86 | BV118: 96 | BW118: =-BW923 | BX118: =SUM(BT118,BU118,BV118,BW118) | BY118: =-BY923 | BZ118: =-BZ923 | CA118: =-CA923 | CB118: =-CB923 | CC118: =SUM(BY118,BZ118,CA118,CB118) | CD118: =-CD923 | CE118: =-CE923 | CF118: =-CF923
...

Sheet Exec Comp
A1: =MO.CompanyName
A2: =MO.Ticker | C2: =Model!C2 | D2: =Model!D2 | E2: =Model!E2 | F2: =Model!F2 | G2: =Model!G2 | H2: =Model!H2 | I2: =Model!I2 | J2: =Model!J2 | ... CF2: =Model!CF2
A3: =MO.TradingCurrency | B3: =MO.LastPrice | C3: =INDEX(MO_Common_FPDays,0,MATCH(C$5,MO_Common_ColumnHeader,0)) | D3: =INDEX(MO_Common_FPDays,0,MATCH(D$5,MO_Common_ColumnHeader,0)) | E3: =INDEX(MO_Common_FPDays,0,MATCH(E$5,MO_Common_ColumnHeader,0)) | F3: =INDEX(MO_Common_FPDays,0,MATCH(F$5,MO_Common_ColumnHeader,0)) | G3: =INDEX(MO_Common_FPDays,0,MATCH(G$5,MO_Common_ColumnHeader,0)) | H3: =INDEX(MO_Common_FPDays,0,MATCH(H$5,MO_Common_ColumnHeader,0)) | I3: =INDEX(MO_Common_FPDays,0,MATCH(I$5,MO_Common_ColumnHeader,0)) | J3: =INDEX(MO_Common_FPDays,0,MATCH(J$5,MO_Common_ColumnHeader,0)) | ... CF3: =INDEX(MO_Common_FPDays,0,MATCH(CF$5,MO_Common_ColumnHeader,0))
A4: =MO.DataSourceName | B4: =MO.RealTime | C4: =INDEX(MO_Common_QEndDate,0,MATCH(C$5,MO_Common_ColumnHeader,0)) | D4: =INDEX(MO_Common_QEndDate,0,MATCH(D$5,MO_Common_ColumnHeader,0)) | E4: =INDEX(MO_Common_QEndDate,0,MATCH(E$5,MO_Common_ColumnHeader,0)) | F4: =INDEX(MO_Common_QEndDate,0,MATCH(F$5,MO_Common_ColumnHeader,0)) | G4: =INDEX(MO_Common_QEndDate,0,MATCH(G$5,MO_Common_ColumnHeader,0)) | H4: =INDEX(MO_Common_QEndDate,0,MATCH(H$5,MO_Common_ColumnHeader,0)) | I4: =INDEX(MO_Common_QEndDate,0,MATCH(I$5,MO_Common_ColumnHeader,0)) | J4: =INDEX(MO_Common_QEndDate,0,MATCH(J$5,MO_Common_ColumnHeader,0)) | ... CF4: =INDEX(MO_Common_QEndDate,0,MATCH(CF$5,MO_Common_ColumnHeader,0))
A5: =MO.ReportFX | C5: =Model!C5 | D5: =Model!D5 | E5: =Model!E5 | F5: =Model!F5 | G5: =Model!G5 | H5: =Model!H5 | I5: =Model!I5 | J5: =Model!J5 | ... CF5: =Model!CF5
A6: Executive Compensation
A7: CEO - Base Pay, 000s | AT7: 996.514 | AY7: 1017.355 | BD7: 996.216 | BI7: 996.832 | BN7: 996.514
A8: CEO - Stock Awards, 000s | AT8: 9676.92 | AY8: 15279.78 | BD8: 18660.407 | BI8: 19666.382 | BN8: 26676.415
A9: CEO - Non-equity incentive plans, 000s | AT9: 805.444 | AY9: 3000 | BD9: 4000 | BI9: 0 | BN9: 4000
A10: CEO - All other compensation, 000s | AT10: 13.402 | AY10: 19.266 | BD10: 81.038 | BI10: 693.71 | BN10: 2494.973
A11: CEO - Total Comp, 000s | AT11: =SUM(AT7:AT10) | AY11: =SUM(AY7:AY10) | BD11: =SUM(BD7:BD10) | BI11: =SUM(BI7:BI10) | BN11: =SUM(BN7:BN10)
A12: CEO - comp tied to equity, % | AT12: =SUM(AT8)/AT11 | AY12: =SUM(AY8)/AY11 | BD12: =SUM(BD8)/BD11 | BI12: =SUM(BI8)/BI11 | BN12: =SUM(BN8)/BN11
A13: Market Cap - EoP, mm | AT13: =Model!AT746 | AU13: =Model!AU746 | AV13: =Model!AV746 | AW13: =Model!AW746 | AX13: =Model!AX746 | AY13: =Model!AY746 | AZ13: =Model!AZ746 | BA13: =Model!BA746 | ... BV13: =Model!BV746
A15: CEO - Options 09/14/2020 # of unexercised exercisable options, 000s | AT15: 250
A16: CEO - Options 09/14/2020 exercise price, $ | AT16: 10.56
A18: CEO - Options 03/17/2021 # of unexercised exercisable options, 000s | AT18: 250 | AY18: 50
A19: CEO - Options 03/17/2021 exercise price, $ | AT19: 17.62 | AY19: 17.62
A21: CEO - Options 09/20/2021 # of unexercised exercisable options, 000s | AT21: 250 | AY21: 250
A22: CEO - Options 09/20/2021 exercise price, $ | AT22: 14.465 | AY22: 14.465
A24: CEO - Options 03/20/2022 # of unexercised exercisable options, 000s | AT24: 300 | AY24: 300 | BD24: 292.34
A25: CEO - Options 03/20/2022 exercise price, $ | AT25: 14.46 | AY25: 14.46 | BD25: 3.615
A27: CEO - Options 09/18/2022 # of unexercised exercisable options, 000s | AT27: 300 | AY27: 300 | BD27: 1200
A28: CEO - Options 09/18/2022 exercise price, $ | AT28: 13.71 | AY28: 13.71 | BD28: 3.4275
A30: CEO - Options 03/19/2023 # of unexercised exercisable options, 000s | AT30: 237.5 | AY30: 237.5 | BD30: 950
A31: CEO - Options 03/19/2023 exercise price, $ | AT31: 12.62 | AY31: 12.62 | BD31: 3.155
A33: CEO - Options 09/17/2023 # of unexercised excercisable options, 000s | AT33: 237.5 | AY33: 237.5 | BD33: 950 | BI33: 475
A34: CEO - Options 09/17/2023 exercise price, $ | AT34: 16 | AY34: 16 | BD34: 4 | BI34: 4
A36: CEO - EoP shares owned, 000s | AT36: =(21462.889*(10))*(4) | AY36: =(21375.455*(10))*(4) | BD36: =84421.722*(10) | BI36: =86403.193*(10) | BN36: =93463.791*(10)
A37: CEO - EoP Shares Issuable Within 60 days, 000s | AT37: =(1825*(10))*(4) | AY37: =(1325*(10))*(4) | BD37: =3100*(10) | BI37: =475*(10)
A38: CEO - EoP shares beneficially owned, 000s | AT38: =SUM(AT36:AT37) | AY38: =SUM(AY36:AY37) | BD38: =SUM(BD36:BD37) | BI38: =SUM(BI36:BI37) | BN38: =SUM(BN36:BN37)
A40: CFO - Base Pay, 000s | AT40: 896.863 | AY40: 915.62 | BD40: 896.595 | BI40: 897.149 | BN40: 896.863
A41: CFO - Stock Awards, 000s | AT41: 3307.188 | AY41: 6595.691 | BD41: 8269.02 | BI41: 10004.677 | BN41: 11756.027
A42: CFO - Non-equity incentive plans, 000s | AT42: 219.667 | AY42: 600 | BD42: 600 | BI42: 0 | BN42: 600
A43: CFO - All other compensation, 000s | AT43: 9.122 | AY43: 9.731 | BD43: 10.312 | BI43: 15.402 | BN43: 13.902
A44: CFO - Total Comp, 000s | AT44: =SUM(AT40:AT43) | AY44: =SUM(AY40:AY43) | BD44: =SUM(BD40:BD43) | BI44: =SUM(BI40:BI43) | BN44: =SUM(BN40:BN43)
A45: CFO - comp tied to equity, % | AT45: =SUM(AT41)/AT44 | AY45: =SUM(AY41)/AY44 | BD45: =SUM(BD41)/BD44 | BI45: =SUM(BI41)/BI44 | BN45: =SUM(BN41)/BN44
A47: CFO - EoP shares owned, 000s | AT47: 81.792 | AY47: 98.873 | BD47: 447.471 | BI47: 478.297 | BN47: 515.421
A48: CFO - EoP Shares Issuable Within 60 days, 000s
A49: CFO - EoP shares beneficially owned, 000s | AT49: =SUM(AT47:AT47) | AY49: =SUM(AY47:AY47) | BD49: =SUM(BD47:BD47) | BI49: =SUM(BI47:BI47) | BN49: =SUM(BN47:BN48)
A51: Board Diversity
A52: Total # of current directors | AT52: 11 | AY52: 13 | BD52: 13 | BI52: 13 | BN52: 14
A53: Total # of independent current directors | AT53: 10 | AY53: 12 | BD53: 12 | BI53: 12 | BN53: 13
A54: Total # of female current directors | AY54: 3 | BD54: 3 | BI54: 3 | BN54: 4
A55: Total # of racially/ethnically diverse current directors | AY55: 3 | BD55: 3 | BI55: 3 | BN55: 3
A57: Total # of director nominees | AT57: 11 | AY57: 13 | BD57: 13 | BI57: 13 | BN57: 12
A58: Total # of independent director nominees | AT58: 10 | AY58: 12 | BD58: 12 | BI58: 12 | BN58: 11
A60: Director Compensation
A61: Director 1 cash comp, 000s | AT61: 75 | AY61: 75 | BD61: 82.5 | BI61: 85 | BN61: 85
A62: Director 2 cash comp, 000s | AT62: 75 | AY62: 75 | BD62: 82.5 | BI62: 85 | BN62: 85
A63: Director 3 cash comp, 000s | AT63: 75 | AY63: 48.03 | BD63: 82.5 | BI63: 85 | BN63: 85
A64: Director 4 cash comp, 000s | AT64: 75 | AY64: 75 | BD64: 82.5 | BI64: 85 | BN64: 85
A65: Director 5 cash comp, 000s | AT65: 75 | AY65: 37.5 | BD65: 82.5 | BI65: 85 | BN65: 85
A66: Director 6 cash comp, 000s | AT66: 75 | AY66: 75 | BD66: 82.5 | BI66: 85 | BN66: 85
A67: Director 7 cash comp, 000s | AT67: 75 | AY67: 75 | BD67: 82.5 | BI67: 85 | BN67: 56
A68: Director 8 cash comp, 000s | AT68: 67.14 | AY68: 75 | BD68: 82.5 | BI68: 85 | BN68: 85
A69: Director 9 cash comp, 000s | AT69: 75 | AY69: 75 | BD69: 82.5 | BI69: 85 | BN69: 85
A70: Director 10 cash comp, 000s | AT70: 75 | AY70: 75 | BD70: 82.5 | BI70: 85 | BN70: 85
A71: Director 11 cash comp, 000s | AT71: 75 | AY71: 75 | BD71: 82.5 | BI71: 85 | BN71: 85
A72: Director 12 cash comp, 000s | AY72: 23.55 | BD72: 82.5 | BI72: 85 | BN72: 85
A73: Director 13 cash comp, 000s | AY73: 75 | BN73: 85
A74: Total director cash comp, 000s | AT74: =SUM(AT61:AT73) | AY74: =SUM(AY61:AY73) | BD74: =SUM(BD61:BD73) | BI74: =SUM(BI61:BI73) | BN74: =SUM(BN61:BN73)
A75: Director 1 stock award comp, 000s | AT75: 184.536 | AY75: 266.338 | BD75: 301.381 | BI75: 268.978 | BN75: 274.268
A76: Director 2 stock award comp, 000s | AT76: 184.536 | AY76: 266.338 | BD76: 301.381 | BI76: 268.978 | BN76: 274.268
A77: Director 3 stock award comp, 000s | AT77: 184.536 | AY77: 558.145 | BD77: 301.381 | BI77: 268.978 | BN77: 274.268
A78: Director 4 stock award comp, 000s | AT78: 184.536 | AY78: 266.338 | BD78: 301.381 | BI78: 268.978 | BN78: 274.268
A79: Director 5 stock award comp, 000s | AT79: 184.536 | AY79: 0 | BD79: 301.381 | BI79: 268.978 | BN79: 274.268
A80: Director 6 stock award comp, 000s | AT80: 184.536 | AY80: 266.338 | BD80: 301.381 | BI80: 268.978 | BN80: 274.268
A81: Director 7 stock award comp, 000s | AT81: 184.536 | AY81: 266.338 | BD81: 301.381 | BI81: 268.978 | BN81: 525.372
A82: Director 8 stock award comp, 000s | AT82: 480.776 | AY82: 266.338 | BD82: 301.381 | BI82: 268.978 | BN82: 274.268
A83: Director 9 stock award comp, 000s | AT83: 184.536 | AY83: 266.338 | BD83: 301.381 | BI83: 268.978 | BN83: 274.268
A84: Director 10 stock award comp, 000s | AT84: 184.536 | AY84: 266.338 | BD84: 301.381 | BI84: 268.978 | BN84: 274.268
A85: Director 11 stock award comp, 000s | AT85: 184.536 | AY85: 266.338 | BD85: 301.381 | BI85: 268.978 | BN85: 274.268
A86: Director 12 stock award comp, 000s | AY86: 440.668 | BD86: 301.381 | BI86: 268.978 | BN86: 274.268
A87: Director 13 stock award comp, 000s | AY87: 266.338 | BN87: 274.268
A88: Total director stock award comp, 000s | AT88: =SUM(AT75:AT87) | AY88: =SUM(AY75:AY87) | BD88: =SUM(BD75:BD87) | BI88: =SUM(BI75:BI87) | BN88: =SUM(BN75:BN87)
A89: Director 1 all other comp, 000s
A90: Director 2 all other comp, 000s
A91: Director 3 all other comp, 000s
A92: Director 4 all other comp, 000s
A93: Director 5 all other comp, 000s
A94: Director 6 all other comp, 000s
A95: Director 7 all other comp, 000s
A96: Director 8 all other comp, 000s
A97: Director 9 all other comp, 000s
A98: Director 10 all other comp, 000s
A99: Director 11 all other comp, 000s
A100: Director 12 all other comp, 000s
A101: Director 13 all other comp, 000s
A102: Total director all other comp, 000s | AT102: =SUM(AT89:AT101) | AY102: =SUM(AY89:AY101) | BD102: =SUM(BD89:BD101) | BI102: =SUM(BI89:BI101) | BN102: =SUM(BN89:BN101)
A103: Total director compensation, 000s | AT103: =AT74+AT88+AT102 | AY103: =AY74+AY88+AY102 | BD103: =BD74+BD88+BD102 | BI103: =BI74+BI88+BI102 | BN103: =BN74+BN88+BN102
A104: Market Cap - EoP, mm | AT104: =AT13 | AU104: =AU13 | AV104: =AV13 | AW104: =AW13 | AX104: =AX13 | AY104: =AY13 | AZ104: =AZ13 | BA104: =BA13 | ... BV104: =BV13
A106: Other Alignment Data Points
A107: CEO - Stock Ownership Guidelines times base salary, x | AT107: 6 | AY107: 6 | BD107: 6 | BI107: 6 | BN107: 6
A108: NEO reporting to CEO - Stock Ownership Guidelines base salary, x | AT108: 1 | AY108: 1 | BD108: 1 | BI108: 1 | BN108: 1
A109: Directors - Stock Owneshership Guidelines base salary, x | AT109: 6 | AY109: 6 | BD109: 6 | BI109: 6 | BN109: 6
A111: Company Financial Goals
A112: Revenue (Base Operating Plan) goal, bn | AT112: 11.4 | AY112: 12.7 | BD112: 20.5 | BI112: 33.5 | BN112: 26
A113: Revenue (Base Operating Plan) goal, mm | AT113: =AT112*1000 | AY113: =AY112*1000 | BD113: =BD112*1000 | BI113: =BI112*1000 | BN113: 26000
A114: Revenue actual, bn | AT114: 10.92 | AY114: 15 | BD114: 26.9 | BI114: 27 | BN114: 60.9
A115: Revenue variable cash plan payout, % | AT115: 0.732 | AY115: 2 | BD115: 2 | BI115: 0 | BN115: 2
...

Sheet Guidance
B1: =MO.CompanyName
B2: Most Recent Period: | F2: =UL.MRQ
I4: Guidance | M4: Model | P4: Difference vs. Mid | S4: Update Log
B5: Type | D5: Item | E5: Item Name | F5: Fiscal Period | G5: Base Period | I5: Low | J5: High | K5: Mid | M5: Type | N5: Output | P5: Absolute | Q5: Relative | S5: Date | T5: Link
A6: 388 | B6: =IF(INDEX(MO_SNA_IsHistoricalPeriod,,MATCH(F6,MO_Common_ColumnHeader,0)),"Historical","Forward") | D6: =INDEX(INDIRECT(E6),0,COLUMN(MO_Common_Column_A)) | E6: MO_RIS_REV | F6: Q4-2026 | I6: =65000*0.98 | J6: =65000*1.02 | K6: =AVERAGE(I6:J6) | M6: =IF(INDEX(MO_SNA_IsHistoricalPeriod,,MATCH(F6,MO_Common_ColumnHeader,0)),"Actual","Estimate") | N6: =IFERROR(INDEX(INDIRECT(E6),0,MATCH(F6,MO_Common_ColumnHeader,0)),"N/A") | P6: =IF(ISNUMBER(N6),N6-K6,"N/A") | Q6: =IFERROR(IF(ISNUMBER(N6),(N6-K6)/ABS(K6),"N/A"),"N/A") | S6: 45980 | T6: CFO Commentary
A7: 387 | B7: =IF(INDEX(MO_SNA_IsHistoricalPeriod,,MATCH(F7,MO_Common_ColumnHeader,0)),"Historical","Forward") | D7: =INDEX(INDIRECT(E7),0,COLUMN(MO_Common_Column_A)) | E7: MO_MA_GM | F7: Q4-2026 | I7: =74.8%-0.5% | J7: =74.8%+0.5% | K7: =AVERAGE(I7:J7) | M7: =IF(INDEX(MO_SNA_IsHistoricalPeriod,,MATCH(F7,MO_Common_ColumnHeader,0)),"Actual","Estimate") | N7: =IFERROR(INDEX(INDIRECT(E7),0,MATCH(F7,MO_Common_ColumnHeader,0)),"N/A") | P7: =IF(ISNUMBER(N7),N7-K7,"N/A") | Q7: =IFERROR(IF(ISNUMBER(N7),(N7-K7)/ABS(K7),"N/A"),"N/A") | S7: 45980 | T7: CFO Commentary
A8: 386 | B8: =IF(INDEX(MO_SNA_IsHistoricalPeriod,,MATCH(F8,MO_Common_ColumnHeader,0)),"Historical","Forward") | D8: =INDEX(INDIRECT(E8),0,COLUMN(MO_Common_Column_A)) | E8: MO_MA_GM_NONGAAP | F8: Q4-2026 | I8: =75%-0.5% | J8: =75%+0.5% | K8: =AVERAGE(I8:J8) | M8: =IF(INDEX(MO_SNA_IsHistoricalPeriod,,MATCH(F8,MO_Common_ColumnHeader,0)),"Actual","Estimate") | N8: =IFERROR(INDEX(INDIRECT(E8),0,MATCH(F8,MO_Common_ColumnHeader,0)),"N/A") | P8: =IF(ISNUMBER(N8),N8-K8,"N/A") | Q8: =IFERROR(IF(ISNUMBER(N8),(N8-K8)/ABS(K8),"N/A"),"N/A") | S8: 45980 | T8: CFO Commentary
A9: 385 | B9: =IF(INDEX(MO_SNA_IsHistoricalPeriod,,MATCH(F9,MO_Common_ColumnHeader,0)),"Historical","Forward") | D9: GAAP Operating Expenses | F9: Q4-2026 | I9: 6700 | J9: 6700 | K9: =AVERAGE(I9:J9) | M9: =IF(INDEX(MO_SNA_IsHistoricalPeriod,,MATCH(F9,MO_Common_ColumnHeader,0)),"Actual","Estimate") | N9: =INDEX(MO_RIS_RD,0,MATCH(F9,MO_Common_ColumnHeader,0))+INDEX(MO_RIS_SGA,0,MATCH(F9,MO_Common_ColumnHeader,0)) | P9: =IF(ISNUMBER(N9),N9-K9,"N/A") | Q9: =IFERROR(IF(ISNUMBER(N9),(N9-K9)/ABS(K9),"N/A"),"N/A") | S9: 45980 | T9: CFO Commentary
A10: 384 | B10: =IF(INDEX(MO_SNA_IsHistoricalPeriod,,MATCH(F10,MO_Common_ColumnHeader,0)),"Historical","Forward") | D10: =INDEX(INDIRECT(E10),0,COLUMN(MO_Common_Column_A)) | E10: MO_OS_OPEX | F10: Q4-2026 | I10: 5000 | J10: 5000 | K10: =AVERAGE(I10:J10) | M10: =IF(INDEX(MO_SNA_IsHistoricalPeriod,,MATCH(F10,MO_Common_ColumnHeader,0)),"Actual","Estimate") | N10: =IFERROR(INDEX(INDIRECT(E10),0,MATCH(F10,MO_Common_ColumnHeader,0)),"N/A") | P10: =IF(ISNUMBER(N10),N10-K10,"N/A") | Q10: =IFERROR(IF(ISNUMBER(N10),(N10-K10)/ABS(K10),"N/A"),"N/A") | S10: 45980 | T10: CFO Commentary
A11: 383 | B11: =IF(INDEX(MO_SNA_IsHistoricalPeriod,,MATCH(F11,MO_Common_ColumnHeader,0)),"Historical","Forward") | D11: GAAP Other Income | F11: Q4-2026 | I11: -500 | J11: -500 | K11: =AVERAGE(I11:J11) | M11: =IF(INDEX(MO_SNA_IsHistoricalPeriod,,MATCH(F11,MO_Common_ColumnHeader,0)),"Actual","Estimate") | N11: =IFERROR(INDEX(INDIRECT(E11),0,MATCH(F11,MO_Common_ColumnHeader,0)),"N/A") | P11: =IF(ISNUMBER(N11),N11-K11,"N/A") | Q11: =IFERROR(IF(ISNUMBER(N11),(N11-K11)/ABS(K11),"N/A"),"N/A") | S11: 45980 | T11: CFO Commentary
A12: 382 | B12: =IF(INDEX(MO_SNA_IsHistoricalPeriod,,MATCH(F12,MO_Common_ColumnHeader,0)),"Historical","Forward") | D12: Non-GAAP Other Income | F12: Q4-2026 | I12: -500 | J12: -500 | K12: =AVERAGE(I12:J12) | M12: =IF(INDEX(MO_SNA_IsHistoricalPeriod,,MATCH(F12,MO_Common_ColumnHeader,0)),"Actual","Estimate") | N12: =INDEX(MO_RIS_IE_Net_NONGAAP,0,MATCH(F12,MO_Common_ColumnHeader,0))+INDEX(MO_RIS_OI_NONGAAP,0,MATCH(F12,MO_Common_ColumnHeader,0)) | P12: =IF(ISNUMBER(N12),N12-K12,"N/A") | Q12: =IFERROR(IF(ISNUMBER(N12),(N12-K12)/ABS(K12),"N/A"),"N/A") | S12: 45980 | T12: CFO Commentary
A13: 381 | B13: =IF(INDEX(MO_SNA_IsHistoricalPeriod,,MATCH(F13,MO_Common_ColumnHeader,0)),"Historical","Forward") | D13: GAAP Tax Rate | E13: MO_RIS_TaxRate | F13: Q4-2026 | I13: 0.16 | J13: 0.18 | K13: =AVERAGE(I13:J13) | M13: =IF(INDEX(MO_SNA_IsHistoricalPeriod,,MATCH(F13,MO_Common_ColumnHeader,0)),"Actual","Estimate") | N13: =IFERROR(INDEX(INDIRECT(E13),0,MATCH(F13,MO_Common_ColumnHeader,0)),"N/A") | P13: =IF(ISNUMBER(N13),N13-K13,"N/A") | Q13: =IFERROR(IF(ISNUMBER(N13),(N13-K13)/ABS(K13),"N/A"),"N/A") | S13: 45980 | T13: CFO Commentary
A14: 380 | B14: =IF(INDEX(MO_SNA_IsHistoricalPeriod,,MATCH(F14,MO_Common_ColumnHeader,0)),"Historical","Forward") | D14: =INDEX(INDIRECT(E14),0,COLUMN(MO_Common_Column_A)) | E14: MO_RIS_TaxRate_NONGAAP | F14: Q4-2026 | I14: 0.16 | J14: 0.18 | K14: =AVERAGE(I14:J14) | M14: =IF(INDEX(MO_SNA_IsHistoricalPeriod,,MATCH(F14,MO_Common_ColumnHeader,0)),"Actual","Estimate") | N14: =IFERROR(INDEX(INDIRECT(E14),0,MATCH(F14,MO_Common_ColumnHeader,0)),"N/A") | P14: =IF(ISNUMBER(N14),N14-K14,"N/A") | Q14: =IFERROR(IF(ISNUMBER(N14),(N14-K14)/ABS(K14),"N/A"),"N/A") | S14: 45980 | T14: CFO Commentary
A15: 379
A16: 378 | B16: =IF(INDEX(MO_SNA_IsHistoricalPeriod,,MATCH(F16,MO_Common_ColumnHeader,0)),"Historical","Forward") | D16: =INDEX(INDIRECT(E16),0,COLUMN(MO_Common_Column_A)) | E16: MO_RIS_REV | F16: Q3-2026 | I16: =54000*0.98 | J16: =54000*1.02 | K16: =AVERAGE(I16:J16) | M16: =IF(INDEX(MO_SNA_IsHistoricalPeriod,,MATCH(F16,MO_Common_ColumnHeader,0)),"Actual","Estimate") | N16: =IFERROR(INDEX(INDIRECT(E16),0,MATCH(F16,MO_Common_ColumnHeader,0)),"N/A") | P16: =IF(ISNUMBER(N16),N16-K16,"N/A") | Q16: =IFERROR(IF(ISNUMBER(N16),(N16-K16)/ABS(K16),"N/A"),"N/A") | S16: 45896 | T16: CFO Commentary
A17: 377 | B17: =IF(INDEX(MO_SNA_IsHistoricalPeriod,,MATCH(F17,MO_Common_ColumnHeader,0)),"Historical","Forward") | D17: =INDEX(INDIRECT(E17),0,COLUMN(MO_Common_Column_A)) | E17: MO_MA_GM | F17: Q3-2026 | I17: =73.3%-0.5% | J17: =73.3%+0.5% | K17: =AVERAGE(I17:J17) | M17: =IF(INDEX(MO_SNA_IsHistoricalPeriod,,MATCH(F17,MO_Common_ColumnHeader,0)),"Actual","Estimate") | N17: =IFERROR(INDEX(INDIRECT(E17),0,MATCH(F17,MO_Common_ColumnHeader,0)),"N/A") | P17: =IF(ISNUMBER(N17),N17-K17,"N/A") | Q17: =IFERROR(IF(ISNUMBER(N17),(N17-K17)/ABS(K17),"N/A"),"N/A") | S17: 45896 | T17: CFO Commentary
A18: 376 | B18: =IF(INDEX(MO_SNA_IsHistoricalPeriod,,MATCH(F18,MO_Common_ColumnHeader,0)),"Historical","Forward") | D18: =INDEX(INDIRECT(E18),0,COLUMN(MO_Common_Column_A)) | E18: MO_MA_GM_NONGAAP | F18: Q3-2026 | I18: =73.5%-0.5% | J18: =73.5%+0.5% | K18: =AVERAGE(I18:J18) | M18: =IF(INDEX(MO_SNA_IsHistoricalPeriod,,MATCH(F18,MO_Common_ColumnHeader,0)),"Actual","Estimate") | N18: =IFERROR(INDEX(INDIRECT(E18),0,MATCH(F18,MO_Common_ColumnHeader,0)),"N/A") | P18: =IF(ISNUMBER(N18),N18-K18,"N/A") | Q18: =IFERROR(IF(ISNUMBER(N18),(N18-K18)/ABS(K18),"N/A"),"N/A") | S18: 45896 | T18: CFO Commentary
A19: 375 | B19: =IF(INDEX(MO_SNA_IsHistoricalPeriod,,MATCH(F19,MO_Common_ColumnHeader,0)),"Historical","Forward") | D19: GAAP Operating Expenses | F19: Q3-2026 | I19: 5900 | J19: 5900 | K19: =AVERAGE(I19:J19) | M19: =IF(INDEX(MO_SNA_IsHistoricalPeriod,,MATCH(F19,MO_Common_ColumnHeader,0)),"Actual","Estimate") | N19: =INDEX(MO_RIS_RD,0,MATCH(F19,MO_Common_ColumnHeader,0))+INDEX(MO_RIS_SGA,0,MATCH(F19,MO_Common_ColumnHeader,0)) | P19: =IF(ISNUMBER(N19),N19-K19,"N/A") | Q19: =IFERROR(IF(ISNUMBER(N19),(N19-K19)/ABS(K19),"N/A"),"N/A") | S19: 45896 | T19: CFO Commentary
A20: 374 | B20: =IF(INDEX(MO_SNA_IsHistoricalPeriod,,MATCH(F20,MO_Common_ColumnHeader,0)),"Historical","Forward") | D20: =INDEX(INDIRECT(E20),0,COLUMN(MO_Common_Column_A)) | E20: MO_OS_OPEX | F20: Q3-2026 | I20: 4200 | J20: 4200 | K20: =AVERAGE(I20:J20) | M20: =IF(INDEX(MO_SNA_IsHistoricalPeriod,,MATCH(F20,MO_Common_ColumnHeader,0)),"Actual","Estimate") | N20: =IFERROR(INDEX(INDIRECT(E20),0,MATCH(F20,MO_Common_ColumnHeader,0)),"N/A") | P20: =IF(ISNUMBER(N20),N20-K20,"N/A") | Q20: =IFERROR(IF(ISNUMBER(N20),(N20-K20)/ABS(K20),"N/A"),"N/A") | S20: 45896 | T20: CFO Commentary
A21: 373 | B21: =IF(INDEX(MO_SNA_IsHistoricalPeriod,,MATCH(F21,MO_Common_ColumnHeader,0)),"Historical","Forward") | D21: GAAP Other Income | F21: Q3-2026 | I21: -500 | J21: -500 | K21: =AVERAGE(I21:J21) | M21: =IF(INDEX(MO_SNA_IsHistoricalPeriod,,MATCH(F21,MO_Common_ColumnHeader,0)),"Actual","Estimate") | N21: =IFERROR(INDEX(INDIRECT(E21),0,MATCH(F21,MO_Common_ColumnHeader,0)),"N/A") | P21: =IF(ISNUMBER(N21),N21-K21,"N/A") | Q21: =IFERROR(IF(ISNUMBER(N21),(N21-K21)/ABS(K21),"N/A"),"N/A") | S21: 45896 | T21: CFO Commentary
A22: 372 | B22: =IF(INDEX(MO_SNA_IsHistoricalPeriod,,MATCH(F22,MO_Common_ColumnHeader,0)),"Historical","Forward") | D22: Non-GAAP Other Income | F22: Q3-2026 | I22: -500 | J22: -500 | K22: =AVERAGE(I22:J22) | M22: =IF(INDEX(MO_SNA_IsHistoricalPeriod,,MATCH(F22,MO_Common_ColumnHeader,0)),"Actual","Estimate") | N22: =INDEX(MO_RIS_IE_Net_NONGAAP,0,MATCH(F22,MO_Common_ColumnHeader,0))+INDEX(MO_RIS_OI_NONGAAP,0,MATCH(F22,MO_Common_ColumnHeader,0)) | P22: =IF(ISNUMBER(N22),N22-K22,"N/A") | Q22: =IFERROR(IF(ISNUMBER(N22),(N22-K22)/ABS(K22),"N/A"),"N/A") | S22: 45896 | T22: CFO Commentary
A23: 371 | B23: =IF(INDEX(MO_SNA_IsHistoricalPeriod,,MATCH(F23,MO_Common_ColumnHeader,0)),"Historical","Forward") | D23: GAAP Tax Rate | E23: MO_RIS_TaxRate | F23: Q3-2026 | I23: 0.155 | J23: 0.175 | K23: =AVERAGE(I23:J23) | M23: =IF(INDEX(MO_SNA_IsHistoricalPeriod,,MATCH(F23,MO_Common_ColumnHeader,0)),"Actual","Estimate") | N23: =IFERROR(INDEX(INDIRECT(E23),0,MATCH(F23,MO_Common_ColumnHeader,0)),"N/A") | P23: =IF(ISNUMBER(N23),N23-K23,"N/A") | Q23: =IFERROR(IF(ISNUMBER(N23),(N23-K23)/ABS(K23),"N/A"),"N/A") | S23: 45896 | T23: CFO Commentary
A24: 370 | B24: =IF(INDEX(MO_SNA_IsHistoricalPeriod,,MATCH(F24,MO_Common_ColumnHeader,0)),"Historical","Forward") | D24: =INDEX(INDIRECT(E24),0,COLUMN(MO_Common_Column_A)) | E24: MO_RIS_TaxRate_NONGAAP | F24: Q3-2026 | I24: 0.155 | J24: 0.175 | K24: =AVERAGE(I24:J24) | M24: =IF(INDEX(MO_SNA_IsHistoricalPeriod,,MATCH(F24,MO_Common_ColumnHeader,0)),"Actual","Estimate") | N24: =IFERROR(INDEX(INDIRECT(E24),0,MATCH(F24,MO_Common_ColumnHeader,0)),"N/A") | P24: =IF(ISNUMBER(N24),N24-K24,"N/A") | Q24: =IFERROR(IF(ISNUMBER(N24),(N24-K24)/ABS(K24),"N/A"),"N/A") | S24: 45896 | T24: CFO Commentary
A25: 369
A26: 368 | B26: =IF(INDEX(MO_SNA_IsHistoricalPeriod,,MATCH(F26,MO_Common_ColumnHeader,0)),"Historical","Forward") | D26: =INDEX(INDIRECT(E26),0,COLUMN(MO_Common_Column_A)) | E26: MO_RIS_REV | F26: Q2-2026 | I26: =45000*0.98 | J26: =45000*1.02 | K26: =AVERAGE(I26:J26) | M26: =IF(INDEX(MO_SNA_IsHistoricalPeriod,,MATCH(F26,MO_Common_ColumnHeader,0)),"Actual","Estimate") | N26: =IFERROR(INDEX(INDIRECT(E26),0,MATCH(F26,MO_Common_ColumnHeader,0)),"N/A") | P26: =IF(ISNUMBER(N26),N26-K26,"N/A") | Q26: =IFERROR(IF(ISNUMBER(N26),(N26-K26)/ABS(K26),"N/A"),"N/A") | S26: 45805 | T26: CFO Commentary
A27: 367 | B27: =IF(INDEX(MO_SNA_IsHistoricalPeriod,,MATCH(F27,MO_Common_ColumnHeader,0)),"Historical","Forward") | D27: =INDEX(INDIRECT(E27),0,COLUMN(MO_Common_Column_A)) | E27: MO_MA_GM | F27: Q2-2026 | I27: 0.713 | J27: 0.723 | K27: =AVERAGE(I27:J27) | M27: =IF(INDEX(MO_SNA_IsHistoricalPeriod,,MATCH(F27,MO_Common_ColumnHeader,0)),"Actual","Estimate") | N27: =IFERROR(INDEX(INDIRECT(E27),0,MATCH(F27,MO_Common_ColumnHeader,0)),"N/A") | P27: =IF(ISNUMBER(N27),N27-K27,"N/A") | Q27: =IFERROR(IF(ISNUMBER(N27),(N27-K27)/ABS(K27),"N/A"),"N/A") | S27: 45805 | T27: CFO Commentary
A28: 366 | B28: =IF(INDEX(MO_SNA_IsHistoricalPeriod,,MATCH(F28,MO_Common_ColumnHeader,0)),"Historical","Forward") | D28: =INDEX(INDIRECT(E28),0,COLUMN(MO_Common_Column_A)) | E28: MO_MA_GM_NONGAAP | F28: Q2-2026 | I28: 0.715 | J28: 0.725 | K28: =AVERAGE(I28:J28) | M28: =IF(INDEX(MO_SNA_IsHistoricalPeriod,,MATCH(F28,MO_Common_ColumnHeader,0)),"Actual","Estimate") | N28: =IFERROR(INDEX(INDIRECT(E28),0,MATCH(F28,MO_Common_ColumnHeader,0)),"N/A") | P28: =IF(ISNUMBER(N28),N28-K28,"N/A") | Q28: =IFERROR(IF(ISNUMBER(N28),(N28-K28)/ABS(K28),"N/A"),"N/A") | S28: 45805 | T28: CFO Commentary
A29: 365 | B29: =IF(INDEX(MO_SNA_IsHistoricalPeriod,,MATCH(F29,MO_Common_ColumnHeader,0)),"Historical","Forward") | D29: GAAP Operating Expenses | F29: Q2-2026 | I29: 5700 | J29: 5700 | K29: =AVERAGE(I29:J29) | M29: =IF(INDEX(MO_SNA_IsHistoricalPeriod,,MATCH(F29,MO_Common_ColumnHeader,0)),"Actual","Estimate") | N29: =INDEX(MO_RIS_RD,0,MATCH(F29,MO_Common_ColumnHeader,0))+INDEX(MO_RIS_SGA,0,MATCH(F29,MO_Common_ColumnHeader,0)) | P29: =IF(ISNUMBER(N29),N29-K29,"N/A") | Q29: =IFERROR(IF(ISNUMBER(N29),(N29-K29)/ABS(K29),"N/A"),"N/A") | S29: 45805 | T29: CFO Commentary
A30: 364 | B30: =IF(INDEX(MO_SNA_IsHistoricalPeriod,,MATCH(F30,MO_Common_ColumnHeader,0)),"Historical","Forward") | D30: =INDEX(INDIRECT(E30),0,COLUMN(MO_Common_Column_A)) | E30: MO_OS_OPEX | F30: Q2-2026 | I30: 4000 | J30: 4000 | K30: =AVERAGE(I30:J30) | M30: =IF(INDEX(MO_SNA_IsHistoricalPeriod,,MATCH(F30,MO_Common_ColumnHeader,0)),"Actual","Estimate") | N30: =IFERROR(INDEX(INDIRECT(E30),0,MATCH(F30,MO_Common_ColumnHeader,0)),"N/A") | P30: =IF(ISNUMBER(N30),N30-K30,"N/A") | Q30: =IFERROR(IF(ISNUMBER(N30),(N30-K30)/ABS(K30),"N/A"),"N/A") | S30: 45805 | T30: CFO Commentary
A31: 363 | B31: =IF(INDEX(MO_SNA_IsHistoricalPeriod,,MATCH(F31,MO_Common_ColumnHeader,0)),"Historical","Forward") | D31: GAAP Other Income | F31: Q2-2026 | I31: -450 | J31: -450 | K31: =AVERAGE(I31:J31) | M31: =IF(INDEX(MO_SNA_IsHistoricalPeriod,,MATCH(F31,MO_Common_ColumnHeader,0)),"Actual","Estimate") | N31: =IFERROR(INDEX(INDIRECT(E31),0,MATCH(F31,MO_Common_ColumnHeader,0)),"N/A") | P31: =IF(ISNUMBER(N31),N31-K31,"N/A") | Q31: =IFERROR(IF(ISNUMBER(N31),(N31-K31)/ABS(K31),"N/A"),"N/A") | S31: 45805 | T31: CFO Commentary
A32: 362 | B32: =IF(INDEX(MO_SNA_IsHistoricalPeriod,,MATCH(F32,MO_Common_ColumnHeader,0)),"Historical","Forward") | D32: Non-GAAP Other Income | F32: Q2-2026 | I32: -450 | J32: -450 | K32: =AVERAGE(I32:J32) | M32: =IF(INDEX(MO_SNA_IsHistoricalPeriod,,MATCH(F32,MO_Common_ColumnHeader,0)),"Actual","Estimate") | N32: =INDEX(MO_RIS_IE_Net_NONGAAP,0,MATCH(F32,MO_Common_ColumnHeader,0))+INDEX(MO_RIS_OI_NONGAAP,0,MATCH(F32,MO_Common_ColumnHeader,0)) | P32: =IF(ISNUMBER(N32),N32-K32,"N/A") | Q32: =IFERROR(IF(ISNUMBER(N32),(N32-K32)/ABS(K32),"N/A"),"N/A") | S32: 45805 | T32: CFO Commentary
A33: 361 | B33: =IF(INDEX(MO_SNA_IsHistoricalPeriod,,MATCH(F33,MO_Common_ColumnHeader,0)),"Historical","Forward") | D33: GAAP Tax Rate | E33: MO_RIS_TaxRate | F33: Q2-2026 | I33: 0.155 | J33: 0.175 | K33: =AVERAGE(I33:J33) | M33: =IF(INDEX(MO_SNA_IsHistoricalPeriod,,MATCH(F33,MO_Common_ColumnHeader,0)),"Actual","Estimate") | N33: =IFERROR(INDEX(INDIRECT(E33),0,MATCH(F33,MO_Common_ColumnHeader,0)),"N/A") | P33: =IF(ISNUMBER(N33),N33-K33,"N/A") | Q33: =IFERROR(IF(ISNUMBER(N33),(N33-K33)/ABS(K33),"N/A"),"N/A") | S33: 45805 | T33: CFO Commentary
A34: 360 | B34: =IF(INDEX(MO_SNA_IsHistoricalPeriod,,MATCH(F34,MO_Common_ColumnHeader,0)),"Historical","Forward") | D34: =INDEX(INDIRECT(E34),0,COLUMN(MO_Common_Column_A)) | E34: MO_RIS_TaxRate_NONGAAP | F34: Q2-2026 | I34: 0.155 | J34: 0.175 | K34: =AVERAGE(I34:J34) | M34: =IF(INDEX(MO_SNA_IsHistoricalPeriod,,MATCH(F34,MO_Common_ColumnHeader,0)),"Actual","Estimate") | N34: =IFERROR(INDEX(INDIRECT(E34),0,MATCH(F34,MO_Common_ColumnHeader,0)),"N/A") | P34: =IF(ISNUMBER(N34),N34-K34,"N/A") | Q34: =IFERROR(IF(ISNUMBER(N34),(N34-K34)/ABS(K34),"N/A"),"N/A") | S34: 45805 | T34: CFO Commentary
A35: 359
A36: 358 | B36: =IF(INDEX(MO_SNA_IsHistoricalPeriod,,MATCH(F36,MO_Common_ColumnHeader,0)),"Historical","Forward") | D36: =INDEX(INDIRECT(E36),0,COLUMN(MO_Common_Column_A)) | E36: MO_RIS_REV | F36: Q1-2026 | I36: =43000*0.98 | J36: =43000*1.02 | K36: =AVERAGE(I36:J36) | M36: =IF(INDEX(MO_SNA_IsHistoricalPeriod,,MATCH(F36,MO_Common_ColumnHeader,0)),"Actual","Estimate") | N36: =IFERROR(INDEX(INDIRECT(E36),0,MATCH(F36,MO_Common_ColumnHeader,0)),"N/A") | P36: =IF(ISNUMBER(N36),N36-K36,"N/A") | Q36: =IFERROR(IF(ISNUMBER(N36),(N36-K36)/ABS(K36),"N/A"),"N/A") | S36: 45714 | T36: CFO Commentary
A37: 357 | B37: =IF(INDEX(MO_SNA_IsHistoricalPeriod,,MATCH(F37,MO_Common_ColumnHeader,0)),"Historical","Forward") | D37: =INDEX(INDIRECT(E37),0,COLUMN(MO_Common_Column_A)) | E37: MO_MA_GM | F37: Q1-2026 | I37: =70.6%-0.5% | J37: =70.6%+0.5% | K37: =AVERAGE(I37:J37) | M37: =IF(INDEX(MO_SNA_IsHistoricalPeriod,,MATCH(F37,MO_Common_ColumnHeader,0)),"Actual","Estimate") | N37: =IFERROR(INDEX(INDIRECT(E37),0,MATCH(F37,MO_Common_ColumnHeader,0)),"N/A") | P37: =IF(ISNUMBER(N37),N37-K37,"N/A") | Q37: =IFERROR(IF(ISNUMBER(N37),(N37-K37)/ABS(K37),"N/A"),"N/A") | S37: 45714 | T37: CFO Commentary
A38: 356 | B38: =IF(INDEX(MO_SNA_IsHistoricalPeriod,,MATCH(F38,MO_Common_ColumnHeader,0)),"Historical","Forward") | D38: =INDEX(INDIRECT(E38),0,COLUMN(MO_Common_Column_A)) | E38: MO_MA_GM_NONGAAP | F38: Q1-2026 | I38: =71%-0.5% | J38: =71%+0.5% | K38: =AVERAGE(I38:J38) | M38: =IF(INDEX(MO_SNA_IsHistoricalPeriod,,MATCH(F38,MO_Common_ColumnHeader,0)),"Actual","Estimate") | N38: =IFERROR(INDEX(INDIRECT(E38),0,MATCH(F38,MO_Common_ColumnHeader,0)),"N/A") | P38: =IF(ISNUMBER(N38),N38-K38,"N/A") | Q38: =IFERROR(IF(ISNUMBER(N38),(N38-K38)/ABS(K38),"N/A"),"N/A") | S38: 45714 | T38: CFO Commentary
A39: 355 | B39: =IF(INDEX(MO_SNA_IsHistoricalPeriod,,MATCH(F39,MO_Common_ColumnHeader,0)),"Historical","Forward") | D39: GAAP Operating Expenses | F39: Q1-2026 | I39: 5200 | J39: 5200 | K39: =AVERAGE(I39:J39) | M39: =IF(INDEX(MO_SNA_IsHistoricalPeriod,,MATCH(F39,MO_Common_ColumnHeader,0)),"Actual","Estimate") | N39: =INDEX(MO_RIS_RD,0,MATCH(F39,MO_Common_ColumnHeader,0))+INDEX(MO_RIS_SGA,0,MATCH(F39,MO_Common_ColumnHeader,0)) | P39: =IF(ISNUMBER(N39),N39-K39,"N/A") | Q39: =IFERROR(IF(ISNUMBER(N39),(N39-K39)/ABS(K39),"N/A"),"N/A") | S39: 45714 | T39: CFO Commentary
A40: 354 | B40: =IF(INDEX(MO_SNA_IsHistoricalPeriod,,MATCH(F40,MO_Common_ColumnHeader,0)),"Historical","Forward") | D40: =INDEX(INDIRECT(E40),0,COLUMN(MO_Common_Column_A)) | E40: MO_OS_OPEX | F40: Q1-2026 | I40: 3600 | J40: 3600 | K40: =AVERAGE(I40:J40) | M40: =IF(INDEX(MO_SNA_IsHistoricalPeriod,,MATCH(F40,MO_Common_ColumnHeader,0)),"Actual","Estimate") | N40: =IFERROR(INDEX(INDIRECT(E40),0,MATCH(F40,MO_Common_ColumnHeader,0)),"N/A") | P40: =IF(ISNUMBER(N40),N40-K40,"N/A") | Q40: =IFERROR(IF(ISNUMBER(N40),(N40-K40)/ABS(K40),"N/A"),"N/A") | S40: 45714 | T40: CFO Commentary
A41: 353 | B41: =IF(INDEX(MO_SNA_IsHistoricalPeriod,,MATCH(F41,MO_Common_ColumnHeader,0)),"Historical","Forward") | D41: GAAP Other Income | F41: Q1-2026 | I41: -400 | J41: -400 | K41: =AVERAGE(I41:J41) | M41: =IF(INDEX(MO_SNA_IsHistoricalPeriod,,MATCH(F41,MO_Common_ColumnHeader,0)),"Actual","Estimate") | N41: =IFERROR(INDEX(INDIRECT(E41),0,MATCH(F41,MO_Common_ColumnHeader,0)),"N/A") | P41: =IF(ISNUMBER(N41),N41-K41,"N/A") | Q41: =IFERROR(IF(ISNUMBER(N41),(N41-K41)/ABS(K41),"N/A"),"N/A") | S41: 45714 | T41: CFO Commentary
A42: 352 | B42: =IF(INDEX(MO_SNA_IsHistoricalPeriod,,MATCH(F42,MO_Common_ColumnHeader,0)),"Historical","Forward") | D42: Non-GAAP Other Income | F42: Q1-2026 | I42: -400 | J42: -400 | K42: =AVERAGE(I42:J42) | M42: =IF(INDEX(MO_SNA_IsHistoricalPeriod,,MATCH(F42,MO_Common_ColumnHeader,0)),"Actual","Estimate") | N42: =INDEX(MO_RIS_IE_Net_NONGAAP,0,MATCH(F42,MO_Common_ColumnHeader,0))+INDEX(MO_RIS_OI_NONGAAP,0,MATCH(F42,MO_Common_ColumnHeader,0)) | P42: =IF(ISNUMBER(N42),N42-K42,"N/A") | Q42: =IFERROR(IF(ISNUMBER(N42),(N42-K42)/ABS(K42),"N/A"),"N/A") | S42: 45714 | T42: CFO Commentary
A43: 351 | B43: =IF(INDEX(MO_SNA_IsHistoricalPeriod,,MATCH(F43,MO_Common_ColumnHeader,0)),"Historical","Forward") | D43: GAAP Tax Rate | E43: MO_RIS_TaxRate | F43: Q1-2026 | I43: 0.16 | J43: 0.18 | K43: =AVERAGE(I43:J43) | M43: =IF(INDEX(MO_SNA_IsHistoricalPeriod,,MATCH(F43,MO_Common_ColumnHeader,0)),"Actual","Estimate") | N43: =IFERROR(INDEX(INDIRECT(E43),0,MATCH(F43,MO_Common_ColumnHeader,0)),"N/A") | P43: =IF(ISNUMBER(N43),N43-K43,"N/A") | Q43: =IFERROR(IF(ISNUMBER(N43),(N43-K43)/ABS(K43),"N/A"),"N/A") | S43: 45714 | T43: CFO Commentary
A44: 350 | B44: =IF(INDEX(MO_SNA_IsHistoricalPeriod,,MATCH(F44,MO_Common_ColumnHeader,0)),"Historical","Forward") | D44: =INDEX(INDIRECT(E44),0,COLUMN(MO_Common_Column_A)) | E44: MO_RIS_TaxRate_NONGAAP | F44: Q1-2026 | I44: 0.16 | J44: 0.18 | K44: =AVERAGE(I44:J44) | M44: =IF(INDEX(MO_SNA_IsHistoricalPeriod,,MATCH(F44,MO_Common_ColumnHeader,0)),"Actual","Estimate") | N44: =IFERROR(INDEX(INDIRECT(E44),0,MATCH(F44,MO_Common_ColumnHeader,0)),"N/A") | P44: =IF(ISNUMBER(N44),N44-K44,"N/A") | Q44: =IFERROR(IF(ISNUMBER(N44),(N44-K44)/ABS(K44),"N/A"),"N/A") | S44: 45714 | T44: CFO Commentary
A45: 349
A46: 348 | B46: =IF(INDEX(MO_SNA_IsHistoricalPeriod,,MATCH(F46,MO_Common_ColumnHeader,0)),"Historical","Forward") | D46: =INDEX(INDIRECT(E46),0,COLUMN(MO_Common_Column_A)) | E46: MO_RIS_REV | F46: Q4-2025 | I46: =37500*(1-2%) | J46: =37500*(1+2%) | K46: =AVERAGE(I46:J46) | M46: =IF(INDEX(MO_SNA_IsHistoricalPeriod,,MATCH(F46,MO_Common_ColumnHeader,0)),"Actual","Estimate") | N46: =IFERROR(INDEX(INDIRECT(E46),0,MATCH(F46,MO_Common_ColumnHeader,0)),"N/A") | P46: =IF(ISNUMBER(N46),N46-K46,"N/A") | Q46: =IFERROR(IF(ISNUMBER(N46),(N46-K46)/ABS(K46),"N/A"),"N/A") | S46: 45616 | T46: CFO Commentary
A47: 347 | B47: =IF(INDEX(MO_SNA_IsHistoricalPeriod,,MATCH(F47,MO_Common_ColumnHeader,0)),"Historical","Forward") | D47: =INDEX(INDIRECT(E47),0,COLUMN(MO_Common_Column_A)) | E47: MO_MA_GM | F47: Q4-2025 | I47: 0.725 | J47: 0.735 | K47: =AVERAGE(I47:J47) | M47: =IF(INDEX(MO_SNA_IsHistoricalPeriod,,MATCH(F47,MO_Common_ColumnHeader,0)),"Actual","Estimate") | N47: =IFERROR(INDEX(INDIRECT(E47),0,MATCH(F47,MO_Common_ColumnHeader,0)),"N/A") | P47: =IF(ISNUMBER(N47),N47-K47,"N/A") | Q47: =IFERROR(IF(ISNUMBER(N47),(N47-K47)/ABS(K47),"N/A"),"N/A") | S47: 45616 | T47: CFO Commentary
A48: 346 | B48: =IF(INDEX(MO_SNA_IsHistoricalPeriod,,MATCH(F48,MO_Common_ColumnHeader,0)),"Historical","Forward") | D48: =INDEX(INDIRECT(E48),0,COLUMN(MO_Common_Column_A)) | E48: MO_MA_GM_NONGAAP | F48: Q4-2025 | I48: 0.73 | J48: 0.74 | K48: =AVERAGE(I48:J48) | M48: =IF(INDEX(MO_SNA_IsHistoricalPeriod,,MATCH(F48,MO_Common_ColumnHeader,0)),"Actual","Estimate") | N48: =IFERROR(INDEX(INDIRECT(E48),0,MATCH(F48,MO_Common_ColumnHeader,0)),"N/A") | P48: =IF(ISNUMBER(N48),N48-K48,"N/A") | Q48: =IFERROR(IF(ISNUMBER(N48),(N48-K48)/ABS(K48),"N/A"),"N/A") | S48: 45616 | T48: CFO Commentary
A49: 345 | B49: =IF(INDEX(MO_SNA_IsHistoricalPeriod,,MATCH(F49,MO_Common_ColumnHeader,0)),"Historical","Forward") | D49: GAAP Operating Expenses | F49: Q4-2025 | I49: 4750 | J49: 4750 | K49: =AVERAGE(I49:J49) | M49: =IF(INDEX(MO_SNA_IsHistoricalPeriod,,MATCH(F49,MO_Common_ColumnHeader,0)),"Actual","Estimate") | N49: =INDEX(MO_RIS_RD,0,MATCH(F49,MO_Common_ColumnHeader,0))+INDEX(MO_RIS_SGA,0,MATCH(F49,MO_Common_ColumnHeader,0)) | P49: =IF(ISNUMBER(N49),N49-K49,"N/A") | Q49: =IFERROR(IF(ISNUMBER(N49),(N49-K49)/ABS(K49),"N/A"),"N/A") | S49: 45616 | T49: CFO Commentary
A50: 344 | B50: =IF(INDEX(MO_SNA_IsHistoricalPeriod,,MATCH(F50,MO_Common_ColumnHeader,0)),"Historical","Forward") | D50: =INDEX(INDIRECT(E50),0,COLUMN(MO_Common_Column_A)) | E50: MO_OS_OPEX | F50: Q4-2025 | I50: 3400 | J50: 3400 | K50: =AVERAGE(I50:J50) | M50: =IF(INDEX(MO_SNA_IsHistoricalPeriod,,MATCH(F50,MO_Common_ColumnHeader,0)),"Actual","Estimate") | N50: =IFERROR(INDEX(INDIRECT(E50),0,MATCH(F50,MO_Common_ColumnHeader,0)),"N/A") | P50: =IF(ISNUMBER(N50),N50-K50,"N/A") | Q50: =IFERROR(IF(ISNUMBER(N50),(N50-K50)/ABS(K50),"N/A"),"N/A") | S50: 45616 | T50: CFO Commentary
A51: 343 | B51: =IF(INDEX(MO_SNA_IsHistoricalPeriod,,MATCH(F51,MO_Common_ColumnHeader,0)),"Historical","Forward") | D51: GAAP Other Income | F51: Q4-2025 | I51: -400 | J51: -400 | K51: =AVERAGE(I51:J51) | M51: =IF(INDEX(MO_SNA_IsHistoricalPeriod,,MATCH(F51,MO_Common_ColumnHeader,0)),"Actual","Estimate") | N51: =IFERROR(INDEX(INDIRECT(E51),0,MATCH(F51,MO_Common_ColumnHeader,0)),"N/A") | P51: =IF(ISNUMBER(N51),N51-K51,"N/A") | Q51: =IFERROR(IF(ISNUMBER(N51),(N51-K51)/ABS(K51),"N/A"),"N/A") | S51: 45616 | T51: CFO Commentary
A52: 342 | B52: =IF(INDEX(MO_SNA_IsHistoricalPeriod,,MATCH(F52,MO_Common_ColumnHeader,0)),"Historical","Forward") | D52: Non-GAAP Other Income | F52: Q4-2025 | I52: -400 | J52: -400 | K52: =AVERAGE(I52:J52) | M52: =IF(INDEX(MO_SNA_IsHistoricalPeriod,,MATCH(F52,MO_Common_ColumnHeader,0)),"Actual","Estimate") | N52: =INDEX(MO_RIS_IE_Net_NONGAAP,0,MATCH(F52,MO_Common_ColumnHeader,0))+INDEX(MO_RIS_OI_NONGAAP,0,MATCH(F52,MO_Common_ColumnHeader,0)) | P52: =IF(ISNUMBER(N52),N52-K52,"N/A") | Q52: =IFERROR(IF(ISNUMBER(N52),(N52-K52)/ABS(K52),"N/A"),"N/A") | S52: 45616 | T52: CFO Commentary
A53: 341 | B53: =IF(INDEX(MO_SNA_IsHistoricalPeriod,,MATCH(F53,MO_Common_ColumnHeader,0)),"Historical","Forward") | D53: GAAP Tax Rate | E53: MO_RIS_TaxRate | F53: Q4-2025 | I53: 0.155 | J53: 0.175 | K53: =AVERAGE(I53:J53) | M53: =IF(INDEX(MO_SNA_IsHistoricalPeriod,,MATCH(F53,MO_Common_ColumnHeader,0)),"Actual","Estimate") | N53: =IFERROR(INDEX(INDIRECT(E53),0,MATCH(F53,MO_Common_ColumnHeader,0)),"N/A") | P53: =IF(ISNUMBER(N53),N53-K53,"N/A") | Q53: =IFERROR(IF(ISNUMBER(N53),(N53-K53)/ABS(K53),"N/A"),"N/A") | S53: 45616 | T53: CFO Commentary
A54: 340 | B54: =IF(INDEX(MO_SNA_IsHistoricalPeriod,,MATCH(F54,MO_Common_ColumnHeader,0)),"Historical","Forward") | D54: =INDEX(INDIRECT(E54),0,COLUMN(MO_Common_Column_A)) | E54: MO_RIS_TaxRate_NONGAAP | F54: Q4-2025 | I54: 0.155 | J54: 0.175 | K54: =AVERAGE(I54:J54) | M54: =IF(INDEX(MO_SNA_IsHistoricalPeriod,,MATCH(F54,MO_Common_ColumnHeader,0)),"Actual","Estimate") | N54: =IFERROR(INDEX(INDIRECT(E54),0,MATCH(F54,MO_Common_ColumnHeader,0)),"N/A") | P54: =IF(ISNUMBER(N54),N54-K54,"N/A") | Q54: =IFERROR(IF(ISNUMBER(N54),(N54-K54)/ABS(K54),"N/A"),"N/A") | S54: 45616 | T54: CFO Commentary
A55: 339 | T55: https://investor.nvidia.com/files/doc_financials/2024/Q4FY24/Q4FY24-CFO-Commentary.pdf
A56: 338 | B56: =IF(INDEX(MO_SNA_IsHistoricalPeriod,,MATCH(F56,MO_Common_ColumnHeader,0)),"Historical","Forward") | D56: =INDEX(INDIRECT(E56),0,COLUMN(MO_Common_Column_A)) | E56: MO_MA_GM | F56: FY2025 | I56: 0.74 | J56: 0.76 | K56: =AVERAGE(I56:J56) | M56: =IF(INDEX(MO_SNA_IsHistoricalPeriod,,MATCH(F56,MO_Common_ColumnHeader,0)),"Actual","Estimate") | N56: =IFERROR(INDEX(INDIRECT(E56),0,MATCH(F56,MO_Common_ColumnHeader,0)),"N/A") | P56: =IF(ISNUMBER(N56),N56-K56,"N/A") | Q56: =IFERROR(IF(ISNUMBER(N56),(N56-K56)/ABS(K56),"N/A"),"N/A") | S56: 45532 | T56: CFO Commentary
A57: 337 | B57: =IF(INDEX(MO_SNA_IsHistoricalPeriod,,MATCH(F57,MO_Common_ColumnHeader,0)),"Historical","Forward") | D57: =INDEX(INDIRECT(E57),0,COLUMN(MO_Common_Column_A)) | E57: MO_MA_GM_NONGAAP | F57: FY2025 | I57: 0.74 | J57: 0.76 | K57: =AVERAGE(I57:J57) | M57: =IF(INDEX(MO_SNA_IsHistoricalPeriod,,MATCH(F57,MO_Common_ColumnHeader,0)),"Actual","Estimate") | N57: =IFERROR(INDEX(INDIRECT(E57),0,MATCH(F57,MO_Common_ColumnHeader,0)),"N/A") | P57: =IF(ISNUMBER(N57),N57-K57,"N/A") | Q57: =IFERROR(IF(ISNUMBER(N57),(N57-K57)/ABS(K57),"N/A"),"N/A") | S57: 45532 | T57: CFO Commentary
A58: 336 | B58: =IF(INDEX(MO_SNA_IsHistoricalPeriod,,MATCH(F58,MO_Common_ColumnHeader,0)),"Historical","Forward") | D58: GAAP Operating Expenses | F58: FY2025 | G58: FY2024 | I58: 0.44 | J58: 0.49 | K58: =AVERAGE(I58:J58) | M58: =IF(INDEX(MO_SNA_IsHistoricalPeriod,,MATCH(F58,MO_Common_ColumnHeader,0)),"Actual","Estimate") | N58: =(INDEX(MO_RIS_RD,0,MATCH(F58,MO_Common_ColumnHeader,0))+INDEX(MO_RIS_SGA,0,MATCH(F58,MO_Common_ColumnHeader,0)))/(INDEX(MO_RIS_RD,0,MATCH(G58,MO_Common_ColumnHeader,0))+INDEX(MO_RIS_SGA,0,MATCH(G58,MO_Common_ColumnHeader,0)))-1 | P58: =IF(ISNUMBER(N58),N58-K58,"N/A") | Q58: =IFERROR(IF(ISNUMBER(N58),(N58-K58)/ABS(K58),"N/A"),"N/A") | S58: 45532 | T58: CFO Commentary
A59: 335 | B59: =IF(INDEX(MO_SNA_IsHistoricalPeriod,,MATCH(F59,MO_Common_ColumnHeader,0)),"Historical","Forward") | D59: =INDEX(INDIRECT(E59),0,COLUMN(MO_Common_Column_A)) | E59: MO_OS_OPEX | F59: FY2025 | G59: FY2024 | I59: 0.44 | J59: 0.49 | K59: =AVERAGE(I59:J59) | M59: =IF(INDEX(MO_SNA_IsHistoricalPeriod,,MATCH(F59,MO_Common_ColumnHeader,0)),"Actual","Estimate") | N59: =(INDEX(MO_RIS_RD,0,MATCH(F59,MO_Common_ColumnHeader,0))+INDEX(MO_RIS_SGA,0,MATCH(F59,MO_Common_ColumnHeader,0)))/(INDEX(MO_RIS_RD,0,MATCH(G59,MO_Common_ColumnHeader,0))+INDEX(MO_RIS_SGA,0,MATCH(G59,MO_Common_ColumnHeader,0)))-1 | P59: =IF(ISNUMBER(N59),N59-K59,"N/A") | Q59: =IFERROR(IF(ISNUMBER(N59),(N59-K59)/ABS(K59),"N/A"),"N/A") | S59: 45532 | T59: CFO Commentary
A60: 334
A61: 333 | B61: =IF(INDEX(MO_SNA_IsHistoricalPeriod,,MATCH(F61,MO_Common_ColumnHeader,0)),"Historical","Forward") | D61: =INDEX(INDIRECT(E61),0,COLUMN(MO_Common_Column_A)) | E61: MO_RIS_REV | F61: Q3-2025 | I61: 31850 | J61: 33150 | K61: =AVERAGE(I61:J61) | M61: =IF(INDEX(MO_SNA_IsHistoricalPeriod,,MATCH(F61,MO_Common_ColumnHeader,0)),"Actual","Estimate") | N61: =IFERROR(INDEX(INDIRECT(E61),0,MATCH(F61,MO_Common_ColumnHeader,0)),"N/A") | P61: =IF(ISNUMBER(N61),N61-K61,"N/A") | Q61: =IFERROR(IF(ISNUMBER(N61),(N61-K61)/ABS(K61),"N/A"),"N/A") | S61: 45532 | T61: CFO Commentary
A62: 332 | B62: =IF(INDEX(MO_SNA_IsHistoricalPeriod,,MATCH(F62,MO_Common_ColumnHeader,0)),"Historical","Forward") | D62: =INDEX(INDIRECT(E62),0,COLUMN(MO_Common_Column_A)) | E62: MO_MA_GM | F62: Q3-2025 | I62: 0.739 | J62: 0.749 | K62: =AVERAGE(I62:J62) | M62: =IF(INDEX(MO_SNA_IsHistoricalPeriod,,MATCH(F62,MO_Common_ColumnHeader,0)),"Actual","Estimate") | N62: =IFERROR(INDEX(INDIRECT(E62),0,MATCH(F62,MO_Common_ColumnHeader,0)),"N/A") | P62: =IF(ISNUMBER(N62),N62-K62,"N/A") | Q62: =IFERROR(IF(ISNUMBER(N62),(N62-K62)/ABS(K62),"N/A"),"N/A") | S62: 45532 | T62: CFO Commentary
A63: 331 | B63: =IF(INDEX(MO_SNA_IsHistoricalPeriod,,MATCH(F63,MO_Common_ColumnHeader,0)),"Historical","Forward") | D63: =INDEX(INDIRECT(E63),0,COLUMN(MO_Common_Column_A)) | E63: MO_MA_GM_NONGAAP | F63: Q3-2025 | I63: 0.745 | J63: 0.755 | K63: =AVERAGE(I63:J63) | M63: =IF(INDEX(MO_SNA_IsHistoricalPeriod,,MATCH(F63,MO_Common_ColumnHeader,0)),"Actual","Estimate") | N63: =IFERROR(INDEX(INDIRECT(E63),0,MATCH(F63,MO_Common_ColumnHeader,0)),"N/A") | P63: =IF(ISNUMBER(N63),N63-K63,"N/A") | Q63: =IFERROR(IF(ISNUMBER(N63),(N63-K63)/ABS(K63),"N/A"),"N/A") | S63: 45532 | T63: CFO Commentary
A64: 330 | B64: =IF(INDEX(MO_SNA_IsHistoricalPeriod,,MATCH(F64,MO_Common_ColumnHeader,0)),"Historical","Forward") | D64: GAAP Operating Expenses | F64: Q3-2025 | I64: 4300 | J64: 4300 | K64: =AVERAGE(I64:J64) | M64: =IF(INDEX(MO_SNA_IsHistoricalPeriod,,MATCH(F64,MO_Common_ColumnHeader,0)),"Actual","Estimate") | N64: =INDEX(MO_RIS_RD,0,MATCH(F64,MO_Common_ColumnHeader,0))+INDEX(MO_RIS_SGA,0,MATCH(F64,MO_Common_ColumnHeader,0)) | P64: =IF(ISNUMBER(N64),N64-K64,"N/A") | Q64: =IFERROR(IF(ISNUMBER(N64),(N64-K64)/ABS(K64),"N/A"),"N/A") | S64: 45532 | T64: CFO Commentary
A65: 329 | B65: =IF(INDEX(MO_SNA_IsHistoricalPeriod,,MATCH(F65,MO_Common_ColumnHeader,0)),"Historical","Forward") | D65: =INDEX(INDIRECT(E65),0,COLUMN(MO_Common_Column_A)) | E65: MO_OS_OPEX | F65: Q3-2025 | I65: 3000 | J65: 3000 | K65: =AVERAGE(I65:J65) | M65: =IF(INDEX(MO_SNA_IsHistoricalPeriod,,MATCH(F65,MO_Common_ColumnHeader,0)),"Actual","Estimate") | N65: =IFERROR(INDEX(INDIRECT(E65),0,MATCH(F65,MO_Common_ColumnHeader,0)),"N/A") | P65: =IF(ISNUMBER(N65),N65-K65,"N/A") | Q65: =IFERROR(IF(ISNUMBER(N65),(N65-K65)/ABS(K65),"N/A"),"N/A") | S65: 45532 | T65: CFO Commentary
A66: 328 | B66: =IF(INDEX(MO_SNA_IsHistoricalPeriod,,MATCH(F66,MO_Common_ColumnHeader,0)),"Historical","Forward") | D66: GAAP Other Income | F66: Q3-2025 | I66: -350 | J66: -350 | K66: =AVERAGE(I66:J66) | M66: =IF(INDEX(MO_SNA_IsHistoricalPeriod,,MATCH(F66,MO_Common_ColumnHeader,0)),"Actual","Estimate") | N66: =IFERROR(INDEX(INDIRECT(E66),0,MATCH(F66,MO_Common_ColumnHeader,0)),"N/A") | P66: =IF(ISNUMBER(N66),N66-K66,"N/A") | Q66: =IFERROR(IF(ISNUMBER(N66),(N66-K66)/ABS(K66),"N/A"),"N/A") | S66: 45532 | T66: CFO Commentary
A67: 327 | B67: =IF(INDEX(MO_SNA_IsHistoricalPeriod,,MATCH(F67,MO_Common_ColumnHeader,0)),"Historical","Forward") | D67: Non-GAAP Other Income | F67: Q3-2025 | I67: -350 | J67: -350 | K67: =AVERAGE(I67:J67) | M67: =IF(INDEX(MO_SNA_IsHistoricalPeriod,,MATCH(F67,MO_Common_ColumnHeader,0)),"Actual","Estimate") | N67: =INDEX(MO_RIS_IE_Net_NONGAAP,0,MATCH(F67,MO_Common_ColumnHeader,0))+INDEX(MO_RIS_OI_NONGAAP,0,MATCH(F67,MO_Common_ColumnHeader,0)) | P67: =IF(ISNUMBER(N67),N67-K67,"N/A") | Q67: =IFERROR(IF(ISNUMBER(N67),(N67-K67)/ABS(K67),"N/A"),"N/A") | S67: 45532 | T67: CFO Commentary
A68: 326 | B68: =IF(INDEX(MO_SNA_IsHistoricalPeriod,,MATCH(F68,MO_Common_ColumnHeader,0)),"Historical","Forward") | D68: GAAP Tax Rate | E68: MO_RIS_TaxRate | F68: Q3-2025 | I68: 0.16 | J68: 0.18 | K68: =AVERAGE(I68:J68) | M68: =IF(INDEX(MO_SNA_IsHistoricalPeriod,,MATCH(F68,MO_Common_ColumnHeader,0)),"Actual","Estimate") | N68: =IFERROR(INDEX(INDIRECT(E68),0,MATCH(F68,MO_Common_ColumnHeader,0)),"N/A") | P68: =IF(ISNUMBER(N68),N68-K68,"N/A") | Q68: =IFERROR(IF(ISNUMBER(N68),(N68-K68)/ABS(K68),"N/A"),"N/A") | S68: 45532 | T68: CFO Commentary
A69: 325 | B69: =IF(INDEX(MO_SNA_IsHistoricalPeriod,,MATCH(F69,MO_Common_ColumnHeader,0)),"Historical","Forward") | D69: =INDEX(INDIRECT(E69),0,COLUMN(MO_Common_Column_A)) | E69: MO_RIS_TaxRate_NONGAAP | F69: Q3-2025 | I69: 0.16 | J69: 0.18 | K69: =AVERAGE(I69:J69) | M69: =IF(INDEX(MO_SNA_IsHistoricalPeriod,,MATCH(F69,MO_Common_ColumnHeader,0)),"Actual","Estimate") | N69: =IFERROR(INDEX(INDIRECT(E69),0,MATCH(F69,MO_Common_ColumnHeader,0)),"N/A") | P69: =IF(ISNUMBER(N69),N69-K69,"N/A") | Q69: =IFERROR(IF(ISNUMBER(N69),(N69-K69)/ABS(K69),"N/A"),"N/A") | S69: 45532 | T69: CFO Commentary
A70: 324 | T70: https://investor.nvidia.com/files/doc_financials/2024/Q4FY24/Q4FY24-CFO-Commentary.pdf
A71: 323 | B71: =IF(INDEX(MO_SNA_IsHistoricalPeriod,,MATCH(F71,MO_Common_ColumnHeader,0)),"Historical","Forward") | D71: =INDEX(INDIRECT(E71),0,COLUMN(MO_Common_Column_A)) | E71: MO_MA_GM | F71: FY2025 | I71: 0.74 | J71: 0.76 | K71: =AVERAGE(I71:J71) | M71: =IF(INDEX(MO_SNA_IsHistoricalPeriod,,MATCH(F71,MO_Common_ColumnHeader,0)),"Actual","Estimate") | N71: =IFERROR(INDEX(INDIRECT(E71),0,MATCH(F71,MO_Common_ColumnHeader,0)),"N/A") | P71: =IF(ISNUMBER(N71),N71-K71,"N/A") | Q71: =IFERROR(IF(ISNUMBER(N71),(N71-K71)/ABS(K71),"N/A"),"N/A") | S71: 45434 | T71: CFO Commentary
A72: 322 | B72: =IF(INDEX(MO_SNA_IsHistoricalPeriod,,MATCH(F72,MO_Common_ColumnHeader,0)),"Historical","Forward") | D72: =INDEX(INDIRECT(E72),0,COLUMN(MO_Common_Column_A)) | E72: MO_MA_GM_NONGAAP | F72: FY2025 | I72: 0.74 | J72: 0.76 | K72: =AVERAGE(I72:J72) | M72: =IF(INDEX(MO_SNA_IsHistoricalPeriod,,MATCH(F72,MO_Common_ColumnHeader,0)),"Actual","Estimate") | N72: =IFERROR(INDEX(INDIRECT(E72),0,MATCH(F72,MO_Common_ColumnHeader,0)),"N/A") | P72: =IF(ISNUMBER(N72),N72-K72,"N/A") | Q72: =IFERROR(IF(ISNUMBER(N72),(N72-K72)/ABS(K72),"N/A"),"N/A") | S72: 45434 | T72: CFO Commentary
A73: 321 | B73: =IF(INDEX(MO_SNA_IsHistoricalPeriod,,MATCH(F73,MO_Common_ColumnHeader,0)),"Historical","Forward") | D73: GAAP Operating Expenses | F73: FY2025 | G73: FY2024 | I73: 0.41 | J73: 0.43 | K73: =AVERAGE(I73:J73) | M73: =IF(INDEX(MO_SNA_IsHistoricalPeriod,,MATCH(F73,MO_Common_ColumnHeader,0)),"Actual","Estimate") | N73: =(INDEX(MO_RIS_RD,0,MATCH(F73,MO_Common_ColumnHeader,0))+INDEX(MO_RIS_SGA,0,MATCH(F73,MO_Common_ColumnHeader,0)))/(INDEX(MO_RIS_RD,0,MATCH(G73,MO_Common_ColumnHeader,0))+INDEX(MO_RIS_SGA,0,MATCH(G73,MO_Common_ColumnHeader,0)))-1 | P73: =IF(ISNUMBER(N73),N73-K73,"N/A") | Q73: =IFERROR(IF(ISNUMBER(N73),(N73-K73)/ABS(K73),"N/A"),"N/A") | S73: 45434 | T73: CFO Commentary
A74: 320 | B74: =IF(INDEX(MO_SNA_IsHistoricalPeriod,,MATCH(F74,MO_Common_ColumnHeader,0)),"Historical","Forward") | D74: =INDEX(INDIRECT(E74),0,COLUMN(MO_Common_Column_A)) | E74: MO_OS_OPEX | F74: FY2025 | G74: FY2024 | I74: 0.41 | J74: 0.43 | K74: =AVERAGE(I74:J74) | M74: =IF(INDEX(MO_SNA_IsHistoricalPeriod,,MATCH(F74,MO_Common_ColumnHeader,0)),"Actual","Estimate") | N74: =(INDEX(MO_RIS_RD,0,MATCH(F74,MO_Common_ColumnHeader,0))+INDEX(MO_RIS_SGA,0,MATCH(F74,MO_Common_ColumnHeader,0)))/(INDEX(MO_RIS_RD,0,MATCH(G74,MO_Common_ColumnHeader,0))+INDEX(MO_RIS_SGA,0,MATCH(G74,MO_Common_ColumnHeader,0)))-1 | P74: =IF(ISNUMBER(N74),N74-K74,"N/A") | Q74: =IFERROR(IF(ISNUMBER(N74),(N74-K74)/ABS(K74),"N/A"),"N/A") | S74: 45434 | T74: CFO Commentary
A75: 319
A76: 318 | B76: =IF(INDEX(MO_SNA_IsHistoricalPeriod,,MATCH(F76,MO_Common_ColumnHeader,0)),"Historical","Forward") | D76: =INDEX(INDIRECT(E76),0,COLUMN(MO_Common_Column_A)) | E76: MO_RIS_REV | F76: Q2-2025 | I76: =28000*0.98 | J76: =28000*1.02 | K76: =AVERAGE(I76:J76) | M76: =IF(INDEX(MO_SNA_IsHistoricalPeriod,,MATCH(F76,MO_Common_ColumnHeader,0)),"Actual","Estimate") | N76: =IFERROR(INDEX(INDIRECT(E76),0,MATCH(F76,MO_Common_ColumnHeader,0)),"N/A") | P76: =IF(ISNUMBER(N76),N76-K76,"N/A") | Q76: =IFERROR(IF(ISNUMBER(N76),(N76-K76)/ABS(K76),"N/A"),"N/A") | S76: 45434 | T76: CFO Commentary
A77: 317 | B77: =IF(INDEX(MO_SNA_IsHistoricalPeriod,,MATCH(F77,MO_Common_ColumnHeader,0)),"Historical","Forward") | D77: =INDEX(INDIRECT(E77),0,COLUMN(MO_Common_Column_A)) | E77: MO_MA_GM | F77: Q2-2025 | I77: 0.743 | J77: 0.753 | K77: =AVERAGE(I77:J77) | M77: =IF(INDEX(MO_SNA_IsHistoricalPeriod,,MATCH(F77,MO_Common_ColumnHeader,0)),"Actual","Estimate") | N77: =IFERROR(INDEX(INDIRECT(E77),0,MATCH(F77,MO_Common_ColumnHeader,0)),"N/A") | P77: =IF(ISNUMBER(N77),N77-K77,"N/A") | Q77: =IFERROR(IF(ISNUMBER(N77),(N77-K77)/ABS(K77),"N/A"),"N/A") | S77: 45434 | T77: CFO Commentary
A78: 316 | B78: =IF(INDEX(MO_SNA_IsHistoricalPeriod,,MATCH(F78,MO_Common_ColumnHeader,0)),"Historical","Forward") | D78: =INDEX(INDIRECT(E78),0,COLUMN(MO_Common_Column_A)) | E78: MO_MA_GM_NONGAAP | F78: Q2-2025 | I78: 0.75 | J78: 0.76 | K78: =AVERAGE(I78:J78) | M78: =IF(INDEX(MO_SNA_IsHistoricalPeriod,,MATCH(F78,MO_Common_ColumnHeader,0)),"Actual","Estimate") | N78: =IFERROR(INDEX(INDIRECT(E78),0,MATCH(F78,MO_Common_ColumnHeader,0)),"N/A") | P78: =IF(ISNUMBER(N78),N78-K78,"N/A") | Q78: =IFERROR(IF(ISNUMBER(N78),(N78-K78)/ABS(K78),"N/A"),"N/A") | S78: 45434 | T78: CFO Commentary
A79: 315 | B79: =IF(INDEX(MO_SNA_IsHistoricalPeriod,,MATCH(F79,MO_Common_ColumnHeader,0)),"Historical","Forward") | D79: GAAP Operating Expenses | F79: Q2-2025 | I79: 4000 | J79: 4000 | K79: =AVERAGE(I79:J79) | M79: =IF(INDEX(MO_SNA_IsHistoricalPeriod,,MATCH(F79,MO_Common_ColumnHeader,0)),"Actual","Estimate") | N79: =INDEX(MO_RIS_RD,0,MATCH(F79,MO_Common_ColumnHeader,0))+INDEX(MO_RIS_SGA,0,MATCH(F79,MO_Common_ColumnHeader,0)) | P79: =IF(ISNUMBER(N79),N79-K79,"N/A") | Q79: =IFERROR(IF(ISNUMBER(N79),(N79-K79)/ABS(K79),"N/A"),"N/A") | S79: 45434 | T79: CFO Commentary
A80: 314 | B80: =IF(INDEX(MO_SNA_IsHistoricalPeriod,,MATCH(F80,MO_Common_ColumnHeader,0)),"Historical","Forward") | D80: =INDEX(INDIRECT(E80),0,COLUMN(MO_Common_Column_A)) | E80: MO_OS_OPEX | F80: Q2-2025 | I80: 2800 | J80: 2800 | K80: =AVERAGE(I80:J80) | M80: =IF(INDEX(MO_SNA_IsHistoricalPeriod,,MATCH(F80,MO_Common_ColumnHeader,0)),"Actual","Estimate") | N80: =IFERROR(INDEX(INDIRECT(E80),0,MATCH(F80,MO_Common_ColumnHeader,0)),"N/A") | P80: =IF(ISNUMBER(N80),N80-K80,"N/A") | Q80: =IFERROR(IF(ISNUMBER(N80),(N80-K80)/ABS(K80),"N/A"),"N/A") | S80: 45434 | T80: CFO Commentary
A81: 313 | B81: =IF(INDEX(MO_SNA_IsHistoricalPeriod,,MATCH(F81,MO_Common_ColumnHeader,0)),"Historical","Forward") | D81: GAAP Other Income | F81: Q2-2025 | I81: -300 | J81: -300 | K81: =AVERAGE(I81:J81) | M81: =IF(INDEX(MO_SNA_IsHistoricalPeriod,,MATCH(F81,MO_Common_ColumnHeader,0)),"Actual","Estimate") | N81: =IFERROR(INDEX(INDIRECT(E81),0,MATCH(F81,MO_Common_ColumnHeader,0)),"N/A") | P81: =IF(ISNUMBER(N81),N81-K81,"N/A") | Q81: =IFERROR(IF(ISNUMBER(N81),(N81-K81)/ABS(K81),"N/A"),"N/A") | S81: 45434 | T81: CFO Commentary
A82: 312 | B82: =IF(INDEX(MO_SNA_IsHistoricalPeriod,,MATCH(F82,MO_Common_ColumnHeader,0)),"Historical","Forward") | D82: Non-GAAP Other Income | F82: Q2-2025 | I82: -300 | J82: -300 | K82: =AVERAGE(I82:J82) | M82: =IF(INDEX(MO_SNA_IsHistoricalPeriod,,MATCH(F82,MO_Common_ColumnHeader,0)),"Actual","Estimate") | N82: =INDEX(MO_RIS_IE_Net_NONGAAP,0,MATCH(F82,MO_Common_ColumnHeader,0))+INDEX(MO_RIS_OI_NONGAAP,0,MATCH(F82,MO_Common_ColumnHeader,0)) | P82: =IF(ISNUMBER(N82),N82-K82,"N/A") | Q82: =IFERROR(IF(ISNUMBER(N82),(N82-K82)/ABS(K82),"N/A"),"N/A") | S82: 45434 | T82: CFO Commentary
A83: 311 | B83: =IF(INDEX(MO_SNA_IsHistoricalPeriod,,MATCH(F83,MO_Common_ColumnHeader,0)),"Historical","Forward") | D83: GAAP Tax Rate | E83: MO_RIS_TaxRate | F83: Q2-2025 | I83: 0.16 | J83: 0.18 | K83: =AVERAGE(I83:J83) | M83: =IF(INDEX(MO_SNA_IsHistoricalPeriod,,MATCH(F83,MO_Common_ColumnHeader,0)),"Actual","Estimate") | N83: =IFERROR(INDEX(INDIRECT(E83),0,MATCH(F83,MO_Common_ColumnHeader,0)),"N/A") | P83: =IF(ISNUMBER(N83),N83-K83,"N/A") | Q83: =IFERROR(IF(ISNUMBER(N83),(N83-K83)/ABS(K83),"N/A"),"N/A") | S83: 45434 | T83: CFO Commentary
A84: 310 | B84: =IF(INDEX(MO_SNA_IsHistoricalPeriod,,MATCH(F84,MO_Common_ColumnHeader,0)),"Historical","Forward") | D84: =INDEX(INDIRECT(E84),0,COLUMN(MO_Common_Column_A)) | E84: MO_RIS_TaxRate_NONGAAP | F84: Q2-2025 | I84: 0.16 | J84: 0.18 | K84: =AVERAGE(I84:J84) | M84: =IF(INDEX(MO_SNA_IsHistoricalPeriod,,MATCH(F84,MO_Common_ColumnHeader,0)),"Actual","Estimate") | N84: =IFERROR(INDEX(INDIRECT(E84),0,MATCH(F84,MO_Common_ColumnHeader,0)),"N/A") | P84: =IF(ISNUMBER(N84),N84-K84,"N/A") | Q84: =IFERROR(IF(ISNUMBER(N84),(N84-K84)/ABS(K84),"N/A"),"N/A") | S84: 45434 | T84: CFO Commentary
A85: 309
A86: 308 | B86: =IF(INDEX(MO_SNA_IsHistoricalPeriod,,MATCH(F86,MO_Common_ColumnHeader,0)),"Historical","Forward") | D86: =INDEX(INDIRECT(E86),0,COLUMN(MO_Common_Column_A)) | E86: MO_RIS_REV | F86: Q1-2025 | I86: 23520 | J86: 24480 | K86: =AVERAGE(I86:J86) | M86: =IF(INDEX(MO_SNA_IsHistoricalPeriod,,MATCH(F86,MO_Common_ColumnHeader,0)),"Actual","Estimate") | N86: =IFERROR(INDEX(INDIRECT(E86),0,MATCH(F86,MO_Common_ColumnHeader,0)),"N/A") | P86: =IF(ISNUMBER(N86),N86-K86,"N/A") | Q86: =IFERROR(IF(ISNUMBER(N86),(N86-K86)/ABS(K86),"N/A"),"N/A") | S86: 45343 | T86: CFO Commentary
A87: 307 | B87: =IF(INDEX(MO_SNA_IsHistoricalPeriod,,MATCH(F87,MO_Common_ColumnHeader,0)),"Historical","Forward") | D87: =INDEX(INDIRECT(E87),0,COLUMN(MO_Common_Column_A)) | E87: MO_MA_GM | F87: Q1-2025 | I87: 0.758 | J87: 0.768 | K87: =AVERAGE(I87:J87) | M87: =IF(INDEX(MO_SNA_IsHistoricalPeriod,,MATCH(F87,MO_Common_ColumnHeader,0)),"Actual","Estimate") | N87: =IFERROR(INDEX(INDIRECT(E87),0,MATCH(F87,MO_Common_ColumnHeader,0)),"N/A") | P87: =IF(ISNUMBER(N87),N87-K87,"N/A") | Q87: =IFERROR(IF(ISNUMBER(N87),(N87-K87)/ABS(K87),"N/A"),"N/A") | S87: 45343 | T87: CFO Commentary
A88: 306 | B88: =IF(INDEX(MO_SNA_IsHistoricalPeriod,,MATCH(F88,MO_Common_ColumnHeader,0)),"Historical","Forward") | D88: =INDEX(INDIRECT(E88),0,COLUMN(MO_Common_Column_A)) | E88: MO_MA_GM_NONGAAP | F88: Q1-2025 | I88: 0.765 | J88: 0.775 | K88: =AVERAGE(I88:J88) | M88: =IF(INDEX(MO_SNA_IsHistoricalPeriod,,MATCH(F88,MO_Common_ColumnHeader,0)),"Actual","Estimate") | N88: =IFERROR(INDEX(INDIRECT(E88),0,MATCH(F88,MO_Common_ColumnHeader,0)),"N/A") | P88: =IF(ISNUMBER(N88),N88-K88,"N/A") | Q88: =IFERROR(IF(ISNUMBER(N88),(N88-K88)/ABS(K88),"N/A"),"N/A") | S88: 45343 | T88: CFO Commentary
A89: 305 | B89: =IF(INDEX(MO_SNA_IsHistoricalPeriod,,MATCH(F89,MO_Common_ColumnHeader,0)),"Historical","Forward") | D89: GAAP Operating Expenses | F89: Q1-2025 | I89: 3500 | J89: 3500 | K89: =AVERAGE(I89:J89) | M89: =IF(INDEX(MO_SNA_IsHistoricalPeriod,,MATCH(F89,MO_Common_ColumnHeader,0)),"Actual","Estimate") | N89: =INDEX(MO_RIS_RD,0,MATCH(F89,MO_Common_ColumnHeader,0))+INDEX(MO_RIS_SGA,0,MATCH(F89,MO_Common_ColumnHeader,0)) | P89: =IF(ISNUMBER(N89),N89-K89,"N/A") | Q89: =IFERROR(IF(ISNUMBER(N89),(N89-K89)/ABS(K89),"N/A"),"N/A") | S89: 45343 | T89: CFO Commentary
A90: 304 | B90: =IF(INDEX(MO_SNA_IsHistoricalPeriod,,MATCH(F90,MO_Common_ColumnHeader,0)),"Historical","Forward") | D90: =INDEX(INDIRECT(E90),0,COLUMN(MO_Common_Column_A)) | E90: MO_OS_OPEX | F90: Q1-2025 | I90: 2500 | J90: 2500 | K90: =AVERAGE(I90:J90) | M90: =IF(INDEX(MO_SNA_IsHistoricalPeriod,,MATCH(F90,MO_Common_ColumnHeader,0)),"Actual","Estimate") | N90: =IFERROR(INDEX(INDIRECT(E90),0,MATCH(F90,MO_Common_ColumnHeader,0)),"N/A") | P90: =IF(ISNUMBER(N90),N90-K90,"N/A") | Q90: =IFERROR(IF(ISNUMBER(N90),(N90-K90)/ABS(K90),"N/A"),"N/A") | S90: 45343 | T90: CFO Commentary
A91: 303 | B91: =IF(INDEX(MO_SNA_IsHistoricalPeriod,,MATCH(F91,MO_Common_ColumnHeader,0)),"Historical","Forward") | D91: GAAP Other Income | F91: Q1-2025 | I91: -250 | J91: -250 | K91: =AVERAGE(I91:J91) | M91: =IF(INDEX(MO_SNA_IsHistoricalPeriod,,MATCH(F91,MO_Common_ColumnHeader,0)),"Actual","Estimate") | N91: =IFERROR(INDEX(INDIRECT(E91),0,MATCH(F91,MO_Common_ColumnHeader,0)),"N/A") | P91: =IF(ISNUMBER(N91),N91-K91,"N/A") | Q91: =IFERROR(IF(ISNUMBER(N91),(N91-K91)/ABS(K91),"N/A"),"N/A") | S91: 45343 | T91: CFO Commentary
A92: 302 | B92: =IF(INDEX(MO_SNA_IsHistoricalPeriod,,MATCH(F92,MO_Common_ColumnHeader,0)),"Historical","Forward") | D92: Non-GAAP Other Income | F92: Q1-2025 | I92: -250 | J92: -250 | K92: =AVERAGE(I92:J92) | M92: =IF(INDEX(MO_SNA_IsHistoricalPeriod,,MATCH(F92,MO_Common_ColumnHeader,0)),"Actual","Estimate") | N92: =INDEX(MO_RIS_IE_Net_NONGAAP,0,MATCH(F92,MO_Common_ColumnHeader,0))+INDEX(MO_RIS_OI_NONGAAP,0,MATCH(F92,MO_Common_ColumnHeader,0)) | P92: =IF(ISNUMBER(N92),N92-K92,"N/A") | Q92: =IFERROR(IF(ISNUMBER(N92),(N92-K92)/ABS(K92),"N/A"),"N/A") | S92: 45343 | T92: CFO Commentary
A93: 301 | B93: =IF(INDEX(MO_SNA_IsHistoricalPeriod,,MATCH(F93,MO_Common_ColumnHeader,0)),"Historical","Forward") | D93: GAAP Tax Rate | E93: MO_RIS_TaxRate | F93: Q1-2025 | I93: 0.16 | J93: 0.18 | K93: =AVERAGE(I93:J93) | M93: =IF(INDEX(MO_SNA_IsHistoricalPeriod,,MATCH(F93,MO_Common_ColumnHeader,0)),"Actual","Estimate") | N93: =IFERROR(INDEX(INDIRECT(E93),0,MATCH(F93,MO_Common_ColumnHeader,0)),"N/A") | P93: =IF(ISNUMBER(N93),N93-K93,"N/A") | Q93: =IFERROR(IF(ISNUMBER(N93),(N93-K93)/ABS(K93),"N/A"),"N/A") | S93: 45343 | T93: CFO Commentary
A94: 300 | B94: =IF(INDEX(MO_SNA_IsHistoricalPeriod,,MATCH(F94,MO_Common_ColumnHeader,0)),"Historical","Forward") | D94: =INDEX(INDIRECT(E94),0,COLUMN(MO_Common_Column_A)) | E94: MO_RIS_TaxRate_NONGAAP | F94: Q1-2025 | I94: 0.16 | J94: 0.18 | K94: =AVERAGE(I94:J94) | M94: =IF(INDEX(MO_SNA_IsHistoricalPeriod,,MATCH(F94,MO_Common_ColumnHeader,0)),"Actual","Estimate") | N94: =IFERROR(INDEX(INDIRECT(E94),0,MATCH(F94,MO_Common_ColumnHeader,0)),"N/A") | P94: =IF(ISNUMBER(N94),N94-K94,"N/A") | Q94: =IFERROR(IF(ISNUMBER(N94),(N94-K94)/ABS(K94),"N/A"),"N/A") | S94: 45343 | T94: CFO Commentary
A95: 299
A96: 298 | B96: =IF(INDEX(MO_SNA_IsHistoricalPeriod,,MATCH(F96,MO_Common_ColumnHeader,0)),"Historical","Forward") | D96: =INDEX(INDIRECT(E96),0,COLUMN(MO_Common_Column_A)) | E96: MO_RIS_REV | F96: Q4-2024 | I96: =20000*0.98 | J96: =20000*1.02 | K96: =AVERAGE(I96:J96) | M96: =IF(INDEX(MO_SNA_IsHistoricalPeriod,,MATCH(F96,MO_Common_ColumnHeader,0)),"Actual","Estimate") | N96: =IFERROR(INDEX(INDIRECT(E96),0,MATCH(F96,MO_Common_ColumnHeader,0)),"N/A") | P96: =IF(ISNUMBER(N96),N96-K96,"N/A") | Q96: =IFERROR(IF(ISNUMBER(N96),(N96-K96)/ABS(K96),"N/A"),"N/A") | S96: 45251 | T96: CFO Commentary
A97: 297 | B97: =IF(INDEX(MO_SNA_IsHistoricalPeriod,,MATCH(F97,MO_Common_ColumnHeader,0)),"Historical","Forward") | D97: =INDEX(INDIRECT(E97),0,COLUMN(MO_Common_Column_A)) | E97: MO_MA_GM | F97: Q4-2024 | I97: =74.5%-0.5% | J97: =74.5%+0.5% | K97: =AVERAGE(I97:J97) | M97: =IF(INDEX(MO_SNA_IsHistoricalPeriod,,MATCH(F97,MO_Common_ColumnHeader,0)),"Actual","Estimate") | N97: =IFERROR(INDEX(INDIRECT(E97),0,MATCH(F97,MO_Common_ColumnHeader,0)),"N/A") | P97: =IF(ISNUMBER(N97),N97-K97,"N/A") | Q97: =IFERROR(IF(ISNUMBER(N97),(N97-K97)/ABS(K97),"N/A"),"N/A") | S97: 45251 | T97: CFO Commentary
A98: 296 | B98: =IF(INDEX(MO_SNA_IsHistoricalPeriod,,MATCH(F98,MO_Common_ColumnHeader,0)),"Historical","Forward") | D98: =INDEX(INDIRECT(E98),0,COLUMN(MO_Common_Column_A)) | E98: MO_MA_GM_NONGAAP | F98: Q4-2024 | I98: =75.5%-0.5% | J98: =75.5%+0.5% | K98: =AVERAGE(I98:J98) | M98: =IF(INDEX(MO_SNA_IsHistoricalPeriod,,MATCH(F98,MO_Common_ColumnHeader,0)),"Actual","Estimate") | N98: =IFERROR(INDEX(INDIRECT(E98),0,MATCH(F98,MO_Common_ColumnHeader,0)),"N/A") | P98: =IF(ISNUMBER(N98),N98-K98,"N/A") | Q98: =IFERROR(IF(ISNUMBER(N98),(N98-K98)/ABS(K98),"N/A"),"N/A") | S98: 45251 | T98: CFO Commentary
A99: 295 | B99: =IF(INDEX(MO_SNA_IsHistoricalPeriod,,MATCH(F99,MO_Common_ColumnHeader,0)),"Historical","Forward") | D99: GAAP Operating Expenses | F99: Q4-2024 | I99: 3170 | J99: 3170 | K99: =AVERAGE(I99:J99) | M99: =IF(INDEX(MO_SNA_IsHistoricalPeriod,,MATCH(F99,MO_Common_ColumnHeader,0)),"Actual","Estimate") | N99: =INDEX(MO_RIS_RD,0,MATCH(F99,MO_Common_ColumnHeader,0))+INDEX(MO_RIS_SGA,0,MATCH(F99,MO_Common_ColumnHeader,0)) | P99: =IF(ISNUMBER(N99),N99-K99,"N/A") | Q99: =IFERROR(IF(ISNUMBER(N99),(N99-K99)/ABS(K99),"N/A"),"N/A") | S99: 45251 | T99: CFO Commentary
A100: 294 | B100: =IF(INDEX(MO_SNA_IsHistoricalPeriod,,MATCH(F100,MO_Common_ColumnHeader,0)),"Historical","Forward") | D100: =INDEX(INDIRECT(E100),0,COLUMN(MO_Common_Column_A)) | E100: MO_OS_OPEX | F100: Q4-2024 | I100: 2200 | J100: 2200 | K100: =AVERAGE(I100:J100) | M100: =IF(INDEX(MO_SNA_IsHistoricalPeriod,,MATCH(F100,MO_Common_ColumnHeader,0)),"Actual","Estimate") | N100: =IFERROR(INDEX(INDIRECT(E100),0,MATCH(F100,MO_Common_ColumnHeader,0)),"N/A") | P100: =IF(ISNUMBER(N100),N100-K100,"N/A") | Q100: =IFERROR(IF(ISNUMBER(N100),(N100-K100)/ABS(K100),"N/A"),"N/A") | S100: 45251 | T100: CFO Commentary
A101: 293 | B101: =IF(INDEX(MO_SNA_IsHistoricalPeriod,,MATCH(F101,MO_Common_ColumnHeader,0)),"Historical","Forward") | D101: GAAP Other Income | F101: Q4-2024 | I101: -200 | J101: -200 | K101: =AVERAGE(I101:J101) | M101: =IF(INDEX(MO_SNA_IsHistoricalPeriod,,MATCH(F101,MO_Common_ColumnHeader,0)),"Actual","Estimate") | N101: =IFERROR(INDEX(INDIRECT(E101),0,MATCH(F101,MO_Common_ColumnHeader,0)),"N/A") | P101: =IF(ISNUMBER(N101),N101-K101,"N/A") | Q101: =IFERROR(IF(ISNUMBER(N101),(N101-K101)/ABS(K101),"N/A"),"N/A") | S101: 45251 | T101: CFO Commentary
...

Sheet Summary Page
A1: =MO.CompanyName | C1: =INDEX(MO_Common_QEndDate,0,COLUMN()) | D1: =INDEX(MO_Common_QEndDate,0,COLUMN()) | E1: =INDEX(MO_Common_QEndDate,0,COLUMN()) | F1: =INDEX(MO_Common_QEndDate,0,COLUMN()) | G1: =INDEX(MO_Common_QEndDate,0,COLUMN()) | H1: =INDEX(MO_Common_QEndDate,0,COLUMN()) | I1: =INDEX(MO_Common_QEndDate,0,COLUMN()) | J1: =INDEX(MO_Common_QEndDate,0,COLUMN()) | ... CF1: =INDEX(MO_Common_QEndDate,0,COLUMN())
A2: Reports | B2: =MO.ReportFX | C2: =INDEX(MO_Common_ColumnHeader,0,COLUMN()) | D2: =INDEX(MO_Common_ColumnHeader,0,COLUMN()) | E2: =INDEX(MO_Common_ColumnHeader,0,COLUMN()) | F2: =INDEX(MO_Common_ColumnHeader,0,COLUMN()) | G2: =INDEX(MO_Common_ColumnHeader,0,COLUMN()) | H2: =INDEX(MO_Common_ColumnHeader,0,COLUMN()) | I2: =INDEX(MO_Common_ColumnHeader,0,COLUMN()) | J2: =INDEX(MO_Common_ColumnHeader,0,COLUMN()) | ... CF2: =INDEX(MO_Common_ColumnHeader,0,COLUMN())
A3: Capitalization Summary
A4: ="Stock Price - "&SP.ValuationToggle | B4: EoP | C4: =IF(INDEX(MO_SNA_IsHistoricalPeriod,1,COLUMN())=FALSE,MO.LastPrice/HP.MRFX,CHOOSE(VLOOKUP(SP.ValuationToggle,tb_ValuationToggle,COLUMNS(tb_ValuationToggle),FALSE),INDEX(MO_SPT_StockHigh,1,COLUMN()),INDEX(MO_SPT_StockLow,1,COLUMN()),INDEX(MO_SPT_StockAverage,1,COLUMN()),INDEX(MO_SPT_StockEoP,1,COLUMN()))/IF(SP.ValuationToggle="EoP",IF(INDEX(MO_SPT_FXEoP,1,COLUMN())=0,1,INDEX(MO_SPT_FXEoP,1,COLUMN())),IF(INDEX(MO_SPT_FXAverage,1,COLUMN())=0,1,INDEX(MO_SPT_FXAverage,1,COLUMN())))) | D4: =IF(INDEX(MO_SNA_IsHistoricalPeriod,1,COLUMN())=FALSE,MO.LastPrice/HP.MRFX,CHOOSE(VLOOKUP(SP.ValuationToggle,tb_ValuationToggle,COLUMNS(tb_ValuationToggle),FALSE),INDEX(MO_SPT_StockHigh,1,COLUMN()),INDEX(MO_SPT_StockLow,1,COLUMN()),INDEX(MO_SPT_StockAverage,1,COLUMN()),INDEX(MO_SPT_StockEoP,1,COLUMN()))/IF(SP.ValuationToggle="EoP",IF(INDEX(MO_SPT_FXEoP,1,COLUMN())=0,1,INDEX(MO_SPT_FXEoP,1,COLUMN())),IF(INDEX(MO_SPT_FXAverage,1,COLUMN())=0,1,INDEX(MO_SPT_FXAverage,1,COLUMN())))) | E4: =IF(INDEX(MO_SNA_IsHistoricalPeriod,1,COLUMN())=FALSE,MO.LastPrice/HP.MRFX,CHOOSE(VLOOKUP(SP.ValuationToggle,tb_ValuationToggle,COLUMNS(tb_ValuationToggle),FALSE),INDEX(MO_SPT_StockHigh,1,COLUMN()),INDEX(MO_SPT_StockLow,1,COLUMN()),INDEX(MO_SPT_StockAverage,1,COLUMN()),INDEX(MO_SPT_StockEoP,1,COLUMN()))/IF(SP.ValuationToggle="EoP",IF(INDEX(MO_SPT_FXEoP,1,COLUMN())=0,1,INDEX(MO_SPT_FXEoP,1,COLUMN())),IF(INDEX(MO_SPT_FXAverage,1,COLUMN())=0,1,INDEX(MO_SPT_FXAverage,1,COLUMN())))) | F4: =IF(INDEX(MO_SNA_IsHistoricalPeriod,1,COLUMN())=FALSE,MO.LastPrice/HP.MRFX,CHOOSE(VLOOKUP(SP.ValuationToggle,tb_ValuationToggle,COLUMNS(tb_ValuationToggle),FALSE),INDEX(MO_SPT_StockHigh,1,COLUMN()),INDEX(MO_SPT_StockLow,1,COLUMN()),INDEX(MO_SPT_StockAverage,1,COLUMN()),INDEX(MO_SPT_StockEoP,1,COLUMN()))/IF(SP.ValuationToggle="EoP",IF(INDEX(MO_SPT_FXEoP,1,COLUMN())=0,1,INDEX(MO_SPT_FXEoP,1,COLUMN())),IF(INDEX(MO_SPT_FXAverage,1,COLUMN())=0,1,INDEX(MO_SPT_FXAverage,1,COLUMN())))) | G4: =IF(INDEX(MO_SNA_IsHistoricalPeriod,1,COLUMN())=FALSE,MO.LastPrice/HP.MRFX,CHOOSE(VLOOKUP(SP.ValuationToggle,tb_ValuationToggle,COLUMNS(tb_ValuationToggle),FALSE),INDEX(MO_SPT_StockHigh,1,COLUMN()),INDEX(MO_SPT_StockLow,1,COLUMN()),INDEX(MO_SPT_StockAverage,1,COLUMN()),INDEX(MO_SPT_StockEoP,1,COLUMN()))/IF(SP.ValuationToggle="EoP",IF(INDEX(MO_SPT_FXEoP,1,COLUMN())=0,1,INDEX(MO_SPT_FXEoP,1,COLUMN())),IF(INDEX(MO_SPT_FXAverage,1,COLUMN())=0,1,INDEX(MO_SPT_FXAverage,1,COLUMN())))) | H4: =IF(INDEX(MO_SNA_IsHistoricalPeriod,1,COLUMN())=FALSE,MO.LastPrice/HP.MRFX,CHOOSE(VLOOKUP(SP.ValuationToggle,tb_ValuationToggle,COLUMNS(tb_ValuationToggle),FALSE),INDEX(MO_SPT_StockHigh,1,COLUMN()),INDEX(MO_SPT_StockLow,1,COLUMN()),INDEX(MO_SPT_StockAverage,1,COLUMN()),INDEX(MO_SPT_StockEoP,1,COLUMN()))/IF(SP.ValuationToggle="EoP",IF(INDEX(MO_SPT_FXEoP,1,COLUMN())=0,1,INDEX(MO_SPT_FXEoP,1,COLUMN())),IF(INDEX(MO_SPT_FXAverage,1,COLUMN())=0,1,INDEX(MO_SPT_FXAverage,1,COLUMN())))) | I4: =IF(INDEX(MO_SNA_IsHistoricalPeriod,1,COLUMN())=FALSE,MO.LastPrice/HP.MRFX,CHOOSE(VLOOKUP(SP.ValuationToggle,tb_ValuationToggle,COLUMNS(tb_ValuationToggle),FALSE),INDEX(MO_SPT_StockHigh,1,COLUMN()),INDEX(MO_SPT_StockLow,1,COLUMN()),INDEX(MO_SPT_StockAverage,1,COLUMN()),INDEX(MO_SPT_StockEoP,1,COLUMN()))/IF(SP.ValuationToggle="EoP",IF(INDEX(MO_SPT_FXEoP,1,COLUMN())=0,1,INDEX(MO_SPT_FXEoP,1,COLUMN())),IF(INDEX(MO_SPT_FXAverage,1,COLUMN())=0,1,INDEX(MO_SPT_FXAverage,1,COLUMN())))) | J4: =IF(INDEX(MO_SNA_IsHistoricalPeriod,1,COLUMN())=FALSE,MO.LastPrice/HP.MRFX,CHOOSE(VLOOKUP(SP.ValuationToggle,tb_ValuationToggle,COLUMNS(tb_ValuationToggle),FALSE),INDEX(MO_SPT_StockHigh,1,COLUMN()),INDEX(MO_SPT_StockLow,1,COLUMN()),INDEX(MO_SPT_StockAverage,1,COLUMN()),INDEX(MO_SPT_StockEoP,1,COLUMN()))/IF(SP.ValuationToggle="EoP",IF(INDEX(MO_SPT_FXEoP,1,COLUMN())=0,1,INDEX(MO_SPT_FXEoP,1,COLUMN())),IF(INDEX(MO_SPT_FXAverage,1,COLUMN())=0,1,INDEX(MO_SPT_FXAverage,1,COLUMN())))) | ... CF4: =IF(INDEX(MO_SNA_IsHistoricalPeriod,1,COLUMN())=FALSE,MO.LastPrice/HP.MRFX,CHOOSE(VLOOKUP(SP.ValuationToggle,tb_ValuationToggle,COLUMNS(tb_ValuationToggle),FALSE),INDEX(MO_SPT_StockHigh,1,COLUMN()),INDEX(MO_SPT_StockLow,1,COLUMN()),INDEX(MO_SPT_StockAverage,1,COLUMN()),INDEX(MO_SPT_StockEoP,1,COLUMN()))/IF(SP.ValuationToggle="EoP",IF(INDEX(MO_SPT_FXEoP,1,COLUMN())=0,1,INDEX(MO_SPT_FXEoP,1,COLUMN())),IF(INDEX(MO_SPT_FXAverage,1,COLUMN())=0,1,INDEX(MO_SPT_FXAverage,1,COLUMN()))))
A5: =INDEX(MO_SCA_ShareCount_EoP_Diluted,0,COLUMN()) | C5: =INDEX(MO_SCA_ShareCount_EoP_Diluted,0,COLUMN()) | D5: =INDEX(MO_SCA_ShareCount_EoP_Diluted,0,COLUMN()) | E5: =INDEX(MO_SCA_ShareCount_EoP_Diluted,0,COLUMN()) | F5: =INDEX(MO_SCA_ShareCount_EoP_Diluted,0,COLUMN()) | G5: =INDEX(MO_SCA_ShareCount_EoP_Diluted,0,COLUMN()) | H5: =INDEX(MO_SCA_ShareCount_EoP_Diluted,0,COLUMN()) | I5: =INDEX(MO_SCA_ShareCount_EoP_Diluted,0,COLUMN()) | J5: =INDEX(MO_SCA_ShareCount_EoP_Diluted,0,COLUMN()) | ... CF5: =INDEX(MO_SCA_ShareCount_EoP_Diluted,0,COLUMN())
A6: ="Market Cap - "&SP.ValuationToggle | C6: =INDEX(SP_CS_StockPrice,0,COLUMN())*INDEX(SP_CS_ShareCount_EoP_Diluted,0,COLUMN()) | D6: =INDEX(SP_CS_StockPrice,0,COLUMN())*INDEX(SP_CS_ShareCount_EoP_Diluted,0,COLUMN()) | E6: =INDEX(SP_CS_StockPrice,0,COLUMN())*INDEX(SP_CS_ShareCount_EoP_Diluted,0,COLUMN()) | F6: =INDEX(SP_CS_StockPrice,0,COLUMN())*INDEX(SP_CS_ShareCount_EoP_Diluted,0,COLUMN()) | G6: =INDEX(SP_CS_StockPrice,0,COLUMN())*INDEX(SP_CS_ShareCount_EoP_Diluted,0,COLUMN()) | H6: =INDEX(SP_CS_StockPrice,0,COLUMN())*INDEX(SP_CS_ShareCount_EoP_Diluted,0,COLUMN()) | I6: =INDEX(SP_CS_StockPrice,0,COLUMN())*INDEX(SP_CS_ShareCount_EoP_Diluted,0,COLUMN()) | J6: =INDEX(SP_CS_StockPrice,0,COLUMN())*INDEX(SP_CS_ShareCount_EoP_Diluted,0,COLUMN()) | ... CF6: =INDEX(SP_CS_StockPrice,0,COLUMN())*INDEX(SP_CS_ShareCount_EoP_Diluted,0,COLUMN())
A7: =INDEX(MO_BSS_Cash,0,COLUMN()) | C7: =INDEX(MO_BSS_Cash,0,COLUMN()) | D7: =INDEX(MO_BSS_Cash,0,COLUMN()) | E7: =INDEX(MO_BSS_Cash,0,COLUMN()) | F7: =INDEX(MO_BSS_Cash,0,COLUMN()) | G7: =INDEX(MO_BSS_Cash,0,COLUMN()) | H7: =INDEX(MO_BSS_Cash,0,COLUMN()) | I7: =INDEX(MO_BSS_Cash,0,COLUMN()) | J7: =INDEX(MO_BSS_Cash,0,COLUMN()) | ... CF7: =INDEX(MO_BSS_Cash,0,COLUMN())
A8: =INDEX(MO_BSS_Debt,0,COLUMN()) | C8: =INDEX(MO_BSS_Debt,0,COLUMN()) | D8: =INDEX(MO_BSS_Debt,0,COLUMN()) | E8: =INDEX(MO_BSS_Debt,0,COLUMN()) | F8: =INDEX(MO_BSS_Debt,0,COLUMN()) | G8: =INDEX(MO_BSS_Debt,0,COLUMN()) | H8: =INDEX(MO_BSS_Debt,0,COLUMN()) | I8: =INDEX(MO_BSS_Debt,0,COLUMN()) | J8: =INDEX(MO_BSS_Debt,0,COLUMN()) | ... CF8: =INDEX(MO_BSS_Debt,0,COLUMN())
A9: Operating Lease Liabilities | C9: =INDEX(MO_BSS_OL,0,COLUMN()) | D9: =INDEX(MO_BSS_OL,0,COLUMN()) | E9: =INDEX(MO_BSS_OL,0,COLUMN()) | F9: =INDEX(MO_BSS_OL,0,COLUMN()) | G9: =INDEX(MO_BSS_OL,0,COLUMN()) | H9: =INDEX(MO_BSS_OL,0,COLUMN()) | I9: =INDEX(MO_BSS_OL,0,COLUMN()) | J9: =INDEX(MO_BSS_OL,0,COLUMN()) | ... CF9: =INDEX(MO_BSS_OL,0,COLUMN())
A10: Other EV Components | C10: =INDEX(MO_VA_EVCalc_NCI,0,COLUMN())+INDEX(MO_VA_EVCalc_Prefs,0,COLUMN())+INDEX(MO_VA_EVCalc_Other,0,COLUMN()) | D10: =INDEX(MO_VA_EVCalc_NCI,0,COLUMN())+INDEX(MO_VA_EVCalc_Prefs,0,COLUMN())+INDEX(MO_VA_EVCalc_Other,0,COLUMN()) | E10: =INDEX(MO_VA_EVCalc_NCI,0,COLUMN())+INDEX(MO_VA_EVCalc_Prefs,0,COLUMN())+INDEX(MO_VA_EVCalc_Other,0,COLUMN()) | F10: =INDEX(MO_VA_EVCalc_NCI,0,COLUMN())+INDEX(MO_VA_EVCalc_Prefs,0,COLUMN())+INDEX(MO_VA_EVCalc_Other,0,COLUMN()) | G10: =INDEX(MO_VA_EVCalc_NCI,0,COLUMN())+INDEX(MO_VA_EVCalc_Prefs,0,COLUMN())+INDEX(MO_VA_EVCalc_Other,0,COLUMN()) | H10: =INDEX(MO_VA_EVCalc_NCI,0,COLUMN())+INDEX(MO_VA_EVCalc_Prefs,0,COLUMN())+INDEX(MO_VA_EVCalc_Other,0,COLUMN()) | I10: =INDEX(MO_VA_EVCalc_NCI,0,COLUMN())+INDEX(MO_VA_EVCalc_Prefs,0,COLUMN())+INDEX(MO_VA_EVCalc_Other,0,COLUMN()) | J10: =INDEX(MO_VA_EVCalc_NCI,0,COLUMN())+INDEX(MO_VA_EVCalc_Prefs,0,COLUMN())+INDEX(MO_VA_EVCalc_Other,0,COLUMN()) | ... CF10: =INDEX(MO_VA_EVCalc_NCI,0,COLUMN())+INDEX(MO_VA_EVCalc_Prefs,0,COLUMN())+INDEX(MO_VA_EVCalc_Other,0,COLUMN())
A11: ="Enterprise Value - "&SP.ValuationToggle | C11: =INDEX(SP_CS_MarketCap,0,COLUMN())-INDEX(SP_CS_Cash,0,COLUMN())+INDEX(SP_CS_Debt,0,COLUMN())+INDEX(SP_CS_OL,0,COLUMN())+INDEX(SP_CS_EVCalc_Other,0,COLUMN()) | D11: =INDEX(SP_CS_MarketCap,0,COLUMN())-INDEX(SP_CS_Cash,0,COLUMN())+INDEX(SP_CS_Debt,0,COLUMN())+INDEX(SP_CS_OL,0,COLUMN())+INDEX(SP_CS_EVCalc_Other,0,COLUMN()) | E11: =INDEX(SP_CS_MarketCap,0,COLUMN())-INDEX(SP_CS_Cash,0,COLUMN())+INDEX(SP_CS_Debt,0,COLUMN())+INDEX(SP_CS_OL,0,COLUMN())+INDEX(SP_CS_EVCalc_Other,0,COLUMN()) | F11: =INDEX(SP_CS_MarketCap,0,COLUMN())-INDEX(SP_CS_Cash,0,COLUMN())+INDEX(SP_CS_Debt,0,COLUMN())+INDEX(SP_CS_OL,0,COLUMN())+INDEX(SP_CS_EVCalc_Other,0,COLUMN()) | G11: =INDEX(SP_CS_MarketCap,0,COLUMN())-INDEX(SP_CS_Cash,0,COLUMN())+INDEX(SP_CS_Debt,0,COLUMN())+INDEX(SP_CS_OL,0,COLUMN())+INDEX(SP_CS_EVCalc_Other,0,COLUMN()) | H11: =INDEX(SP_CS_MarketCap,0,COLUMN())-INDEX(SP_CS_Cash,0,COLUMN())+INDEX(SP_CS_Debt,0,COLUMN())+INDEX(SP_CS_OL,0,COLUMN())+INDEX(SP_CS_EVCalc_Other,0,COLUMN()) | I11: =INDEX(SP_CS_MarketCap,0,COLUMN())-INDEX(SP_CS_Cash,0,COLUMN())+INDEX(SP_CS_Debt,0,COLUMN())+INDEX(SP_CS_OL,0,COLUMN())+INDEX(SP_CS_EVCalc_Other,0,COLUMN()) | J11: =INDEX(SP_CS_MarketCap,0,COLUMN())-INDEX(SP_CS_Cash,0,COLUMN())+INDEX(SP_CS_Debt,0,COLUMN())+INDEX(SP_CS_OL,0,COLUMN())+INDEX(SP_CS_EVCalc_Other,0,COLUMN()) | ... CF11: =INDEX(SP_CS_MarketCap,0,COLUMN())-INDEX(SP_CS_Cash,0,COLUMN())+INDEX(SP_CS_Debt,0,COLUMN())+INDEX(SP_CS_OL,0,COLUMN())+INDEX(SP_CS_EVCalc_Other,0,COLUMN())
A13: Company-Specific Operational Data
A14: =+Model!A9 | U14: =+Model!U9 | V14: =+Model!V9 | W14: =+Model!W9 | X14: =+Model!X9 | Y14: =+Model!Y9 | Z14: =+Model!Z9 | AA14: =+Model!AA9 | AB14: =+Model!AB9 | ... CF14: =+Model!CF9
A15: =+Model!A13 | U15: =+Model!U13 | V15: =+Model!V13 | W15: =+Model!W13 | X15: =+Model!X13 | Y15: =+Model!Y13 | Z15: =+Model!Z13 | AA15: =+Model!AA13 | AB15: =+Model!AB13 | ... CF15: =+Model!CF13
A16: =+Model!A24 | U16: =+Model!U24 | V16: =+Model!V24 | W16: =+Model!W24 | X16: =+Model!X24 | Y16: =+Model!Y24 | Z16: =+Model!Z24 | AA16: =+Model!AA24 | AB16: =+Model!AB24 | ... CF16: =+Model!CF24
A17: =+Model!A28 | U17: =+Model!U28 | V17: =+Model!V28 | W17: =+Model!W28 | X17: =+Model!X28 | Y17: =+Model!Y28 | Z17: =+Model!Z28 | AA17: =+Model!AA28 | AB17: =+Model!AB28 | ... CF17: =+Model!CF28
A18: =+Model!A32 | U18: =+Model!U32 | V18: =+Model!V32 | W18: =+Model!W32 | X18: =+Model!X32 | Y18: =+Model!Y32 | Z18: =+Model!Z32 | AA18: =+Model!AA32 | AB18: =+Model!AB32 | ... CF18: =+Model!CF32
A19: =+Model!A38 | D19: =+Model!D38 | E19: =+Model!E38 | F19: =+Model!F38 | K19: =+Model!K38 | L19: =+Model!L38 | M19: =+Model!M38 | N19: =+Model!N38 | O19: =+Model!O38 | P19: =+Model!P38 | Q19: =+Model!Q38 | R19: =+Model!R38 | ... CF19: =+Model!CF38
A21: =+Model!A7 | P21: =+Model!P7 | Q21: =+Model!Q7 | R21: =+Model!R7 | S21: =+Model!S7 | T21: =+Model!T7 | U21: =+Model!U7 | V21: =+Model!V7 | W21: =+Model!W7 | ... CF21: =+Model!CF7
A22: =+Model!A11 | P22: =+Model!P11 | Q22: =+Model!Q11 | R22: =+Model!R11 | S22: =+Model!S11 | T22: =+Model!T11 | U22: =+Model!U11 | V22: =+Model!V11 | W22: =+Model!W11 | ... CF22: =+Model!CF11
A23: =+Model!A22 | P23: =+Model!P22 | Q23: =+Model!Q22 | R23: =+Model!R22 | S23: =+Model!S22 | T23: =+Model!T22 | U23: =+Model!U22 | V23: =+Model!V22 | W23: =+Model!W22 | ... CF23: =+Model!CF22
A24: =+Model!A26 | P24: =+Model!P26 | Q24: =+Model!Q26 | R24: =+Model!R26 | S24: =+Model!S26 | T24: =+Model!T26 | U24: =+Model!U26 | V24: =+Model!V26 | W24: =+Model!W26 | ... CF24: =+Model!CF26
A25: =+Model!A30 | P25: =+Model!P30 | Q25: =+Model!Q30 | R25: =+Model!R30 | S25: =+Model!S30 | T25: =+Model!T30 | U25: =+Model!U30 | V25: =+Model!V30 | W25: =+Model!W30 | ... CF25: =+Model!CF30
A26: =+Model!A34 | P26: =+Model!P34 | Q26: =+Model!Q34 | R26: =+Model!R34 | S26: =+Model!S34 | T26: =+Model!T34 | U26: =+Model!U34 | V26: =+Model!V34 | W26: =+Model!W34 | ... CF26: =+Model!CF34
A28: GAAP and Non-GAAP Financials
A29: =INDEX(MO_RIS_REV,0,COLUMN()) | C29: =INDEX(MO_RIS_REV,0,COLUMN()) | D29: =INDEX(MO_RIS_REV,0,COLUMN()) | E29: =INDEX(MO_RIS_REV,0,COLUMN()) | F29: =INDEX(MO_RIS_REV,0,COLUMN()) | G29: =INDEX(MO_RIS_REV,0,COLUMN()) | H29: =INDEX(MO_RIS_REV,0,COLUMN()) | I29: =INDEX(MO_RIS_REV,0,COLUMN()) | J29: =INDEX(MO_RIS_REV,0,COLUMN()) | ... CF29: =INDEX(MO_RIS_REV,0,COLUMN())
A30: =INDEX(MO_RIS_COGS,0,COLUMN()) | C30: =INDEX(MO_RIS_COGS,0,COLUMN()) | D30: =INDEX(MO_RIS_COGS,0,COLUMN()) | E30: =INDEX(MO_RIS_COGS,0,COLUMN()) | F30: =INDEX(MO_RIS_COGS,0,COLUMN()) | G30: =INDEX(MO_RIS_COGS,0,COLUMN()) | H30: =INDEX(MO_RIS_COGS,0,COLUMN()) | I30: =INDEX(MO_RIS_COGS,0,COLUMN()) | J30: =INDEX(MO_RIS_COGS,0,COLUMN()) | ... CF30: =INDEX(MO_RIS_COGS,0,COLUMN())
A31: =INDEX(MO_RIS_SBC_COGS,0,COLUMN()) | C31: =INDEX(MO_RIS_SBC_COGS,0,COLUMN()) | D31: =INDEX(MO_RIS_SBC_COGS,0,COLUMN()) | E31: =INDEX(MO_RIS_SBC_COGS,0,COLUMN()) | F31: =INDEX(MO_RIS_SBC_COGS,0,COLUMN()) | G31: =INDEX(MO_RIS_SBC_COGS,0,COLUMN()) | H31: =INDEX(MO_RIS_SBC_COGS,0,COLUMN()) | I31: =INDEX(MO_RIS_SBC_COGS,0,COLUMN()) | J31: =INDEX(MO_RIS_SBC_COGS,0,COLUMN()) | ... CF31: =INDEX(MO_RIS_SBC_COGS,0,COLUMN())
A32: =INDEX(z_A7FLSL0150_MO_RIS_AcquisitionrelatedcostsCOGS,0,COLUMN()) | C32: =INDEX(z_A7FLSL0150_MO_RIS_AcquisitionrelatedcostsCOGS,0,COLUMN()) | D32: =INDEX(z_A7FLSL0150_MO_RIS_AcquisitionrelatedcostsCOGS,0,COLUMN()) | E32: =INDEX(z_A7FLSL0150_MO_RIS_AcquisitionrelatedcostsCOGS,0,COLUMN()) | F32: =INDEX(z_A7FLSL0150_MO_RIS_AcquisitionrelatedcostsCOGS,0,COLUMN()) | G32: =INDEX(z_A7FLSL0150_MO_RIS_AcquisitionrelatedcostsCOGS,0,COLUMN()) | H32: =INDEX(z_A7FLSL0150_MO_RIS_AcquisitionrelatedcostsCOGS,0,COLUMN()) | I32: =INDEX(z_A7FLSL0150_MO_RIS_AcquisitionrelatedcostsCOGS,0,COLUMN()) | J32: =INDEX(z_A7FLSL0150_MO_RIS_AcquisitionrelatedcostsCOGS,0,COLUMN()) | ... CF32: =INDEX(z_A7FLSL0150_MO_RIS_AcquisitionrelatedcostsCOGS,0,COLUMN())
A33: =INDEX(MO_RIS_COGS_Adjustments,0,COLUMN()) | C33: =INDEX(MO_RIS_COGS_Adjustments,0,COLUMN()) | D33: =INDEX(MO_RIS_COGS_Adjustments,0,COLUMN()) | E33: =INDEX(MO_RIS_COGS_Adjustments,0,COLUMN()) | F33: =INDEX(MO_RIS_COGS_Adjustments,0,COLUMN()) | G33: =INDEX(MO_RIS_COGS_Adjustments,0,COLUMN()) | H33: =INDEX(MO_RIS_COGS_Adjustments,0,COLUMN()) | I33: =INDEX(MO_RIS_COGS_Adjustments,0,COLUMN()) | J33: =INDEX(MO_RIS_COGS_Adjustments,0,COLUMN()) | ... CF33: =INDEX(MO_RIS_COGS_Adjustments,0,COLUMN())
A34: =INDEX(MO_RIS_RD_NONGAAP,0,COLUMN()) | C34: =INDEX(MO_RIS_RD_NONGAAP,0,COLUMN()) | D34: =INDEX(MO_RIS_RD_NONGAAP,0,COLUMN()) | E34: =INDEX(MO_RIS_RD_NONGAAP,0,COLUMN()) | F34: =INDEX(MO_RIS_RD_NONGAAP,0,COLUMN()) | G34: =INDEX(MO_RIS_RD_NONGAAP,0,COLUMN()) | H34: =INDEX(MO_RIS_RD_NONGAAP,0,COLUMN()) | I34: =INDEX(MO_RIS_RD_NONGAAP,0,COLUMN()) | J34: =INDEX(MO_RIS_RD_NONGAAP,0,COLUMN()) | ... CF34: =INDEX(MO_RIS_RD_NONGAAP,0,COLUMN())
A35: =INDEX(MO_RIS_SGA_NONGAAP,0,COLUMN()) | C35: =INDEX(MO_RIS_SGA_NONGAAP,0,COLUMN()) | D35: =INDEX(MO_RIS_SGA_NONGAAP,0,COLUMN()) | E35: =INDEX(MO_RIS_SGA_NONGAAP,0,COLUMN()) | F35: =INDEX(MO_RIS_SGA_NONGAAP,0,COLUMN()) | G35: =INDEX(MO_RIS_SGA_NONGAAP,0,COLUMN()) | H35: =INDEX(MO_RIS_SGA_NONGAAP,0,COLUMN()) | I35: =INDEX(MO_RIS_SGA_NONGAAP,0,COLUMN()) | J35: =INDEX(MO_RIS_SGA_NONGAAP,0,COLUMN()) | ... CF35: =INDEX(MO_RIS_SGA_NONGAAP,0,COLUMN())
A36: =INDEX(MO_RIS_OPEX_NONGAAP,0,COLUMN()) | C36: =INDEX(MO_RIS_OPEX_NONGAAP,0,COLUMN()) | D36: =INDEX(MO_RIS_OPEX_NONGAAP,0,COLUMN()) | E36: =INDEX(MO_RIS_OPEX_NONGAAP,0,COLUMN()) | F36: =INDEX(MO_RIS_OPEX_NONGAAP,0,COLUMN()) | G36: =INDEX(MO_RIS_OPEX_NONGAAP,0,COLUMN()) | H36: =INDEX(MO_RIS_OPEX_NONGAAP,0,COLUMN()) | I36: =INDEX(MO_RIS_OPEX_NONGAAP,0,COLUMN()) | J36: =INDEX(MO_RIS_OPEX_NONGAAP,0,COLUMN()) | ... CF36: =INDEX(MO_RIS_OPEX_NONGAAP,0,COLUMN())
A37: =INDEX(MO_RIS_OtherOperating_NONGAAP,0,COLUMN()) | C37: =INDEX(MO_RIS_OtherOperating_NONGAAP,0,COLUMN()) | D37: =INDEX(MO_RIS_OtherOperating_NONGAAP,0,COLUMN()) | E37: =INDEX(MO_RIS_OtherOperating_NONGAAP,0,COLUMN()) | F37: =INDEX(MO_RIS_OtherOperating_NONGAAP,0,COLUMN()) | G37: =INDEX(MO_RIS_OtherOperating_NONGAAP,0,COLUMN()) | H37: =INDEX(MO_RIS_OtherOperating_NONGAAP,0,COLUMN()) | I37: =INDEX(MO_RIS_OtherOperating_NONGAAP,0,COLUMN()) | J37: =INDEX(MO_RIS_OtherOperating_NONGAAP,0,COLUMN()) | ... CF37: =INDEX(MO_RIS_OtherOperating_NONGAAP,0,COLUMN())
A38: =INDEX(MO_RIS_Reported_OperatingIncome_NONGAAP,0,COLUMN()) | C38: =INDEX(MO_RIS_Reported_OperatingIncome_NONGAAP,0,COLUMN()) | D38: =INDEX(MO_RIS_Reported_OperatingIncome_NONGAAP,0,COLUMN()) | E38: =INDEX(MO_RIS_Reported_OperatingIncome_NONGAAP,0,COLUMN()) | F38: =INDEX(MO_RIS_Reported_OperatingIncome_NONGAAP,0,COLUMN()) | G38: =INDEX(MO_RIS_Reported_OperatingIncome_NONGAAP,0,COLUMN()) | H38: =INDEX(MO_RIS_Reported_OperatingIncome_NONGAAP,0,COLUMN()) | I38: =INDEX(MO_RIS_Reported_OperatingIncome_NONGAAP,0,COLUMN()) | J38: =INDEX(MO_RIS_Reported_OperatingIncome_NONGAAP,0,COLUMN()) | ... CF38: =INDEX(MO_RIS_Reported_OperatingIncome_NONGAAP,0,COLUMN())
A39: =INDEX(MO_RIS_IE_Net_NONGAAP,0,COLUMN()) | C39: =INDEX(MO_RIS_IE_Net_NONGAAP,0,COLUMN()) | D39: =INDEX(MO_RIS_IE_Net_NONGAAP,0,COLUMN()) | E39: =INDEX(MO_RIS_IE_Net_NONGAAP,0,COLUMN()) | F39: =INDEX(MO_RIS_IE_Net_NONGAAP,0,COLUMN()) | G39: =INDEX(MO_RIS_IE_Net_NONGAAP,0,COLUMN()) | H39: =INDEX(MO_RIS_IE_Net_NONGAAP,0,COLUMN()) | I39: =INDEX(MO_RIS_IE_Net_NONGAAP,0,COLUMN()) | J39: =INDEX(MO_RIS_IE_Net_NONGAAP,0,COLUMN()) | ... CF39: =INDEX(MO_RIS_IE_Net_NONGAAP,0,COLUMN())
A40: =INDEX(MO_RIS_OI_NONGAAP,0,COLUMN()) | C40: =INDEX(MO_RIS_OI_NONGAAP,0,COLUMN()) | D40: =INDEX(MO_RIS_OI_NONGAAP,0,COLUMN()) | E40: =INDEX(MO_RIS_OI_NONGAAP,0,COLUMN()) | F40: =INDEX(MO_RIS_OI_NONGAAP,0,COLUMN()) | G40: =INDEX(MO_RIS_OI_NONGAAP,0,COLUMN()) | H40: =INDEX(MO_RIS_OI_NONGAAP,0,COLUMN()) | I40: =INDEX(MO_RIS_OI_NONGAAP,0,COLUMN()) | J40: =INDEX(MO_RIS_OI_NONGAAP,0,COLUMN()) | ... CF40: =INDEX(MO_RIS_OI_NONGAAP,0,COLUMN())
A41: =INDEX(MO_MA_RIS_EBIT_NONGAAP,0,COLUMN()) | C41: =INDEX(MO_MA_RIS_EBIT_NONGAAP,0,COLUMN()) | D41: =INDEX(MO_MA_RIS_EBIT_NONGAAP,0,COLUMN()) | E41: =INDEX(MO_MA_RIS_EBIT_NONGAAP,0,COLUMN()) | F41: =INDEX(MO_MA_RIS_EBIT_NONGAAP,0,COLUMN()) | G41: =INDEX(MO_MA_RIS_EBIT_NONGAAP,0,COLUMN()) | H41: =INDEX(MO_MA_RIS_EBIT_NONGAAP,0,COLUMN()) | I41: =INDEX(MO_MA_RIS_EBIT_NONGAAP,0,COLUMN()) | J41: =INDEX(MO_MA_RIS_EBIT_NONGAAP,0,COLUMN()) | ... CF41: =INDEX(MO_MA_RIS_EBIT_NONGAAP,0,COLUMN())
A42: =INDEX(MO_RIS_Tax_NONGAAP,0,COLUMN()) | C42: =INDEX(MO_RIS_Tax_NONGAAP,0,COLUMN()) | D42: =INDEX(MO_RIS_Tax_NONGAAP,0,COLUMN()) | E42: =INDEX(MO_RIS_Tax_NONGAAP,0,COLUMN()) | F42: =INDEX(MO_RIS_Tax_NONGAAP,0,COLUMN()) | G42: =INDEX(MO_RIS_Tax_NONGAAP,0,COLUMN()) | H42: =INDEX(MO_RIS_Tax_NONGAAP,0,COLUMN()) | I42: =INDEX(MO_RIS_Tax_NONGAAP,0,COLUMN()) | J42: =INDEX(MO_RIS_Tax_NONGAAP,0,COLUMN()) | ... CF42: =INDEX(MO_RIS_Tax_NONGAAP,0,COLUMN())
A43: =INDEX(MO_RIS_NI_NONGAAP_Diluted,0,COLUMN()) | C43: =INDEX(MO_RIS_NI_NONGAAP_Diluted,0,COLUMN()) | D43: =INDEX(MO_RIS_NI_NONGAAP_Diluted,0,COLUMN()) | E43: =INDEX(MO_RIS_NI_NONGAAP_Diluted,0,COLUMN()) | F43: =INDEX(MO_RIS_NI_NONGAAP_Diluted,0,COLUMN()) | G43: =INDEX(MO_RIS_NI_NONGAAP_Diluted,0,COLUMN()) | H43: =INDEX(MO_RIS_NI_NONGAAP_Diluted,0,COLUMN()) | I43: =INDEX(MO_RIS_NI_NONGAAP_Diluted,0,COLUMN()) | J43: =INDEX(MO_RIS_NI_NONGAAP_Diluted,0,COLUMN()) | ... CF43: =INDEX(MO_RIS_NI_NONGAAP_Diluted,0,COLUMN())
A44: GAAP Adjustments | C44: =+Model!C408+Model!C409+Model!C410+Model!C411+Model!C412+Model!C413 | D44: =+Model!D408+Model!D409+Model!D410+Model!D411+Model!D412+Model!D413 | E44: =+Model!E408+Model!E409+Model!E410+Model!E411+Model!E412+Model!E413 | F44: =+Model!F408+Model!F409+Model!F410+Model!F411+Model!F412+Model!F413 | G44: =+Model!G408+Model!G409+Model!G410+Model!G411+Model!G412+Model!G413 | H44: =+Model!H408+Model!H409+Model!H410+Model!H411+Model!H412+Model!H413 | I44: =+Model!I408+Model!I409+Model!I410+Model!I411+Model!I412+Model!I413 | J44: =+Model!J408+Model!J409+Model!J410+Model!J411+Model!J412+Model!J413 | ... CF44: =+Model!CF408+Model!CF409+Model!CF410+Model!CF411+Model!CF412+Model!CF413
A45: =INDEX(MO_RIS_NI_GAAP_Diluted,0,COLUMN()) | C45: =INDEX(MO_RIS_NI_GAAP_Diluted,0,COLUMN()) | D45: =INDEX(MO_RIS_NI_GAAP_Diluted,0,COLUMN()) | E45: =INDEX(MO_RIS_NI_GAAP_Diluted,0,COLUMN()) | F45: =INDEX(MO_RIS_NI_GAAP_Diluted,0,COLUMN()) | G45: =INDEX(MO_RIS_NI_GAAP_Diluted,0,COLUMN()) | H45: =INDEX(MO_RIS_NI_GAAP_Diluted,0,COLUMN()) | I45: =INDEX(MO_RIS_NI_GAAP_Diluted,0,COLUMN()) | J45: =INDEX(MO_RIS_NI_GAAP_Diluted,0,COLUMN()) | ... CF45: =INDEX(MO_RIS_NI_GAAP_Diluted,0,COLUMN())
A47: =INDEX(MO_RIS_EPS_WAD,0,COLUMN()) | C47: =INDEX(MO_RIS_EPS_WAD,0,COLUMN()) | D47: =INDEX(MO_RIS_EPS_WAD,0,COLUMN()) | E47: =INDEX(MO_RIS_EPS_WAD,0,COLUMN()) | F47: =INDEX(MO_RIS_EPS_WAD,0,COLUMN()) | G47: =INDEX(MO_RIS_EPS_WAD,0,COLUMN()) | H47: =INDEX(MO_RIS_EPS_WAD,0,COLUMN()) | I47: =INDEX(MO_RIS_EPS_WAD,0,COLUMN()) | J47: =INDEX(MO_RIS_EPS_WAD,0,COLUMN()) | ... CF47: =INDEX(MO_RIS_EPS_WAD,0,COLUMN())
A48: =INDEX(MO_RIS_ShareCount_WAD_Adj,0,COLUMN()) | C48: =INDEX(MO_RIS_ShareCount_WAD_Adj,0,COLUMN()) | D48: =INDEX(MO_RIS_ShareCount_WAD_Adj,0,COLUMN()) | E48: =INDEX(MO_RIS_ShareCount_WAD_Adj,0,COLUMN()) | F48: =INDEX(MO_RIS_ShareCount_WAD_Adj,0,COLUMN()) | G48: =INDEX(MO_RIS_ShareCount_WAD_Adj,0,COLUMN()) | H48: =INDEX(MO_RIS_ShareCount_WAD_Adj,0,COLUMN()) | I48: =INDEX(MO_RIS_ShareCount_WAD_Adj,0,COLUMN()) | J48: =INDEX(MO_RIS_ShareCount_WAD_Adj,0,COLUMN()) | ... CF48: =INDEX(MO_RIS_ShareCount_WAD_Adj,0,COLUMN())
A50: Non-GAAP Financials
A51: =INDEX(MO_RIS_EBITDA_Adj,0,COLUMN()) | C51: =INDEX(MO_RIS_EBITDA_Adj,0,COLUMN()) | D51: =INDEX(MO_RIS_EBITDA_Adj,0,COLUMN()) | E51: =INDEX(MO_RIS_EBITDA_Adj,0,COLUMN()) | F51: =INDEX(MO_RIS_EBITDA_Adj,0,COLUMN()) | G51: =INDEX(MO_RIS_EBITDA_Adj,0,COLUMN()) | H51: =INDEX(MO_RIS_EBITDA_Adj,0,COLUMN()) | I51: =INDEX(MO_RIS_EBITDA_Adj,0,COLUMN()) | J51: =INDEX(MO_RIS_EBITDA_Adj,0,COLUMN()) | ... CF51: =INDEX(MO_RIS_EBITDA_Adj,0,COLUMN())
A52: =INDEX(MO_RIS_NI_NONGAAP_Diluted,0,COLUMN()) | C52: =INDEX(MO_RIS_NI_NONGAAP_Diluted,0,COLUMN()) | D52: =INDEX(MO_RIS_NI_NONGAAP_Diluted,0,COLUMN()) | E52: =INDEX(MO_RIS_NI_NONGAAP_Diluted,0,COLUMN()) | F52: =INDEX(MO_RIS_NI_NONGAAP_Diluted,0,COLUMN()) | G52: =INDEX(MO_RIS_NI_NONGAAP_Diluted,0,COLUMN()) | H52: =INDEX(MO_RIS_NI_NONGAAP_Diluted,0,COLUMN()) | I52: =INDEX(MO_RIS_NI_NONGAAP_Diluted,0,COLUMN()) | J52: =INDEX(MO_RIS_NI_NONGAAP_Diluted,0,COLUMN()) | ... CF52: =INDEX(MO_RIS_NI_NONGAAP_Diluted,0,COLUMN())
A53: =+Model!A425 | C53: =+Model!C425 | D53: =+Model!D425 | E53: =+Model!E425 | F53: =+Model!F425 | G53: =+Model!G425 | H53: =+Model!H425 | I53: =+Model!I425 | J53: =+Model!J425 | ... CF53: =+Model!CF425
A55: Margin Analysis
A56: =INDEX(MO_MA_COGS_NONGAAP,0,COLUMN()) | C56: =INDEX(MO_MA_COGS_NONGAAP,0,COLUMN()) | D56: =INDEX(MO_MA_COGS_NONGAAP,0,COLUMN()) | E56: =INDEX(MO_MA_COGS_NONGAAP,0,COLUMN()) | F56: =INDEX(MO_MA_COGS_NONGAAP,0,COLUMN()) | G56: =INDEX(MO_MA_COGS_NONGAAP,0,COLUMN()) | H56: =INDEX(MO_MA_COGS_NONGAAP,0,COLUMN()) | I56: =INDEX(MO_MA_COGS_NONGAAP,0,COLUMN()) | J56: =INDEX(MO_MA_COGS_NONGAAP,0,COLUMN()) | ... CF56: =INDEX(MO_MA_COGS_NONGAAP,0,COLUMN())
A57: =INDEX(MO_MA_RD_NONGAAP,0,COLUMN()) | C57: =INDEX(MO_MA_RD_NONGAAP,0,COLUMN()) | D57: =INDEX(MO_MA_RD_NONGAAP,0,COLUMN()) | E57: =INDEX(MO_MA_RD_NONGAAP,0,COLUMN()) | F57: =INDEX(MO_MA_RD_NONGAAP,0,COLUMN()) | G57: =INDEX(MO_MA_RD_NONGAAP,0,COLUMN()) | H57: =INDEX(MO_MA_RD_NONGAAP,0,COLUMN()) | I57: =INDEX(MO_MA_RD_NONGAAP,0,COLUMN()) | J57: =INDEX(MO_MA_RD_NONGAAP,0,COLUMN()) | ... CF57: =INDEX(MO_MA_RD_NONGAAP,0,COLUMN())
A58: =INDEX(MO_MA_SGA_NONGAAP,0,COLUMN()) | C58: =INDEX(MO_MA_SGA_NONGAAP,0,COLUMN()) | D58: =INDEX(MO_MA_SGA_NONGAAP,0,COLUMN()) | E58: =INDEX(MO_MA_SGA_NONGAAP,0,COLUMN()) | F58: =INDEX(MO_MA_SGA_NONGAAP,0,COLUMN()) | G58: =INDEX(MO_MA_SGA_NONGAAP,0,COLUMN()) | H58: =INDEX(MO_MA_SGA_NONGAAP,0,COLUMN()) | I58: =INDEX(MO_MA_SGA_NONGAAP,0,COLUMN()) | J58: =INDEX(MO_MA_SGA_NONGAAP,0,COLUMN()) | ... CF58: =INDEX(MO_MA_SGA_NONGAAP,0,COLUMN())
A59: =INDEX(MO_MA_OPEX_NONGAAP,0,COLUMN()) | C59: =INDEX(MO_MA_OPEX_NONGAAP,0,COLUMN()) | D59: =INDEX(MO_MA_OPEX_NONGAAP,0,COLUMN()) | E59: =INDEX(MO_MA_OPEX_NONGAAP,0,COLUMN()) | F59: =INDEX(MO_MA_OPEX_NONGAAP,0,COLUMN()) | G59: =INDEX(MO_MA_OPEX_NONGAAP,0,COLUMN()) | H59: =INDEX(MO_MA_OPEX_NONGAAP,0,COLUMN()) | I59: =INDEX(MO_MA_OPEX_NONGAAP,0,COLUMN()) | J59: =INDEX(MO_MA_OPEX_NONGAAP,0,COLUMN()) | ... CF59: =INDEX(MO_MA_OPEX_NONGAAP,0,COLUMN())
A60: =INDEX(MO_MA_OperatingIncome_NONGAAP,0,COLUMN()) | C60: =INDEX(MO_MA_OperatingIncome_NONGAAP,0,COLUMN()) | D60: =INDEX(MO_MA_OperatingIncome_NONGAAP,0,COLUMN()) | E60: =INDEX(MO_MA_OperatingIncome_NONGAAP,0,COLUMN()) | F60: =INDEX(MO_MA_OperatingIncome_NONGAAP,0,COLUMN()) | G60: =INDEX(MO_MA_OperatingIncome_NONGAAP,0,COLUMN()) | H60: =INDEX(MO_MA_OperatingIncome_NONGAAP,0,COLUMN()) | I60: =INDEX(MO_MA_OperatingIncome_NONGAAP,0,COLUMN()) | J60: =INDEX(MO_MA_OperatingIncome_NONGAAP,0,COLUMN()) | ... CF60: =INDEX(MO_MA_OperatingIncome_NONGAAP,0,COLUMN())
A61: =INDEX(MO_MA_OperatingIncome,0,COLUMN()) | C61: =INDEX(MO_MA_OperatingIncome,0,COLUMN()) | D61: =INDEX(MO_MA_OperatingIncome,0,COLUMN()) | E61: =INDEX(MO_MA_OperatingIncome,0,COLUMN()) | F61: =INDEX(MO_MA_OperatingIncome,0,COLUMN()) | G61: =INDEX(MO_MA_OperatingIncome,0,COLUMN()) | H61: =INDEX(MO_MA_OperatingIncome,0,COLUMN()) | I61: =INDEX(MO_MA_OperatingIncome,0,COLUMN()) | J61: =INDEX(MO_MA_OperatingIncome,0,COLUMN()) | ... CF61: =INDEX(MO_MA_OperatingIncome,0,COLUMN())
A63: Cash Flow Analysis
A64: =INDEX(MO_CFSum_CFO_BeforeWC,0,COLUMN()) | C64: =INDEX(MO_CFSum_CFO_BeforeWC,0,COLUMN()) | D64: =INDEX(MO_CFSum_CFO_BeforeWC,0,COLUMN()) | E64: =INDEX(MO_CFSum_CFO_BeforeWC,0,COLUMN()) | F64: =INDEX(MO_CFSum_CFO_BeforeWC,0,COLUMN()) | G64: =INDEX(MO_CFSum_CFO_BeforeWC,0,COLUMN()) | H64: =INDEX(MO_CFSum_CFO_BeforeWC,0,COLUMN()) | I64: =INDEX(MO_CFSum_CFO_BeforeWC,0,COLUMN()) | J64: =INDEX(MO_CFSum_CFO_BeforeWC,0,COLUMN()) | ... CF64: =INDEX(MO_CFSum_CFO_BeforeWC,0,COLUMN())
A65: Change in WC | C65: =SUM(OFFSET(INDEX(MO_CFS_CFO_BeforeWC,0,COLUMN()),1,0,ROW(INDEX(MO_CFS_CFO,0,COLUMN()))-ROW(INDEX(MO_CFS_CFO_BeforeWC,0,COLUMN()))-1,1)) | D65: =SUM(OFFSET(INDEX(MO_CFS_CFO_BeforeWC,0,COLUMN()),1,0,ROW(INDEX(MO_CFS_CFO,0,COLUMN()))-ROW(INDEX(MO_CFS_CFO_BeforeWC,0,COLUMN()))-1,1)) | E65: =SUM(OFFSET(INDEX(MO_CFS_CFO_BeforeWC,0,COLUMN()),1,0,ROW(INDEX(MO_CFS_CFO,0,COLUMN()))-ROW(INDEX(MO_CFS_CFO_BeforeWC,0,COLUMN()))-1,1)) | F65: =SUM(OFFSET(INDEX(MO_CFS_CFO_BeforeWC,0,COLUMN()),1,0,ROW(INDEX(MO_CFS_CFO,0,COLUMN()))-ROW(INDEX(MO_CFS_CFO_BeforeWC,0,COLUMN()))-1,1)) | G65: =SUM(OFFSET(INDEX(MO_CFS_CFO_BeforeWC,0,COLUMN()),1,0,ROW(INDEX(MO_CFS_CFO,0,COLUMN()))-ROW(INDEX(MO_CFS_CFO_BeforeWC,0,COLUMN()))-1,1)) | H65: =SUM(OFFSET(INDEX(MO_CFS_CFO_BeforeWC,0,COLUMN()),1,0,ROW(INDEX(MO_CFS_CFO,0,COLUMN()))-ROW(INDEX(MO_CFS_CFO_BeforeWC,0,COLUMN()))-1,1)) | I65: =SUM(OFFSET(INDEX(MO_CFS_CFO_BeforeWC,0,COLUMN()),1,0,ROW(INDEX(MO_CFS_CFO,0,COLUMN()))-ROW(INDEX(MO_CFS_CFO_BeforeWC,0,COLUMN()))-1,1)) | J65: =SUM(OFFSET(INDEX(MO_CFS_CFO_BeforeWC,0,COLUMN()),1,0,ROW(INDEX(MO_CFS_CFO,0,COLUMN()))-ROW(INDEX(MO_CFS_CFO_BeforeWC,0,COLUMN()))-1,1)) | ... CF65: =SUM(OFFSET(INDEX(MO_CFS_CFO_BeforeWC,0,COLUMN()),1,0,ROW(INDEX(MO_CFS_CFO,0,COLUMN()))-ROW(INDEX(MO_CFS_CFO_BeforeWC,0,COLUMN()))-1,1))
A66: Operating Cash Flow after WC | C66: =SUM(C64:C65) | D66: =SUM(D64:D65) | E66: =SUM(E64:E65) | F66: =SUM(F64:F65) | G66: =SUM(G64:G65) | H66: =SUM(H64:H65) | I66: =SUM(I64:I65) | J66: =SUM(J64:J65) | ... CF66: =SUM(CF64:CF65)
A67: =INDEX(MO_CFSum_Capex,0,COLUMN()) | C67: =INDEX(MO_CFSum_Capex,0,COLUMN()) | D67: =INDEX(MO_CFSum_Capex,0,COLUMN()) | E67: =INDEX(MO_CFSum_Capex,0,COLUMN()) | F67: =INDEX(MO_CFSum_Capex,0,COLUMN()) | G67: =INDEX(MO_CFSum_Capex,0,COLUMN()) | H67: =INDEX(MO_CFSum_Capex,0,COLUMN()) | I67: =INDEX(MO_CFSum_Capex,0,COLUMN()) | J67: =INDEX(MO_CFSum_Capex,0,COLUMN()) | ... CF67: =INDEX(MO_CFSum_Capex,0,COLUMN())
A68: Core FCF, Pre Div | C68: =SUM(C66:C67) | D68: =SUM(D66:D67) | E68: =SUM(E66:E67) | F68: =SUM(F66:F67) | G68: =SUM(G66:G67) | H68: =SUM(H66:H67) | I68: =SUM(I66:I67) | J68: =SUM(J66:J67) | ... CF68: =SUM(CF66:CF67)
A69: =INDEX(MO_CFSum_Dividend,0,COLUMN()) | C69: =INDEX(MO_CFSum_Dividend,0,COLUMN()) | D69: =INDEX(MO_CFSum_Dividend,0,COLUMN()) | E69: =INDEX(MO_CFSum_Dividend,0,COLUMN()) | F69: =INDEX(MO_CFSum_Dividend,0,COLUMN()) | G69: =INDEX(MO_CFSum_Dividend,0,COLUMN()) | H69: =INDEX(MO_CFSum_Dividend,0,COLUMN()) | I69: =INDEX(MO_CFSum_Dividend,0,COLUMN()) | J69: =INDEX(MO_CFSum_Dividend,0,COLUMN()) | ... CF69: =INDEX(MO_CFSum_Dividend,0,COLUMN())
A70: Core FCF, Post Div | C70: =SUM(C68:C69) | D70: =SUM(D68:D69) | E70: =SUM(E68:E69) | F70: =SUM(F68:F69) | G70: =SUM(G68:G69) | H70: =SUM(H68:H69) | I70: =SUM(I68:I69) | J70: =SUM(J68:J69) | ... CF70: =SUM(CF68:CF69)
A71: =INDEX(MO_CFSum_Acquisition,0,COLUMN()) | C71: =INDEX(MO_CFSum_Acquisition,0,COLUMN()) | D71: =INDEX(MO_CFSum_Acquisition,0,COLUMN()) | E71: =INDEX(MO_CFSum_Acquisition,0,COLUMN()) | F71: =INDEX(MO_CFSum_Acquisition,0,COLUMN()) | G71: =INDEX(MO_CFSum_Acquisition,0,COLUMN()) | H71: =INDEX(MO_CFSum_Acquisition,0,COLUMN()) | I71: =INDEX(MO_CFSum_Acquisition,0,COLUMN()) | J71: =INDEX(MO_CFSum_Acquisition,0,COLUMN()) | ... CF71: =INDEX(MO_CFSum_Acquisition,0,COLUMN())
A72: =INDEX(MO_CFSum_Divestiture,0,COLUMN()) | C72: =INDEX(MO_CFSum_Divestiture,0,COLUMN()) | D72: =INDEX(MO_CFSum_Divestiture,0,COLUMN()) | E72: =INDEX(MO_CFSum_Divestiture,0,COLUMN()) | F72: =INDEX(MO_CFSum_Divestiture,0,COLUMN()) | G72: =INDEX(MO_CFSum_Divestiture,0,COLUMN()) | H72: =INDEX(MO_CFSum_Divestiture,0,COLUMN()) | I72: =INDEX(MO_CFSum_Divestiture,0,COLUMN()) | J72: =INDEX(MO_CFSum_Divestiture,0,COLUMN()) | ... CF72: =INDEX(MO_CFSum_Divestiture,0,COLUMN())
A73: New Equity Issuance | C73: =INDEX(MO_CFSum_NetShares,0,COLUMN()) | D73: =INDEX(MO_CFSum_NetShares,0,COLUMN()) | E73: =INDEX(MO_CFSum_NetShares,0,COLUMN()) | F73: =INDEX(MO_CFSum_NetShares,0,COLUMN()) | G73: =INDEX(MO_CFSum_NetShares,0,COLUMN()) | H73: =INDEX(MO_CFSum_NetShares,0,COLUMN()) | I73: =INDEX(MO_CFSum_NetShares,0,COLUMN()) | J73: =INDEX(MO_CFSum_NetShares,0,COLUMN()) | ... CF73: =INDEX(MO_CFSum_NetShares,0,COLUMN())
A74: New Debt Issuance | C74: =INDEX(MO_CFSum_NetDebtIssuance,0,COLUMN()) | D74: =INDEX(MO_CFSum_NetDebtIssuance,0,COLUMN()) | E74: =INDEX(MO_CFSum_NetDebtIssuance,0,COLUMN()) | F74: =INDEX(MO_CFSum_NetDebtIssuance,0,COLUMN()) | G74: =INDEX(MO_CFSum_NetDebtIssuance,0,COLUMN()) | H74: =INDEX(MO_CFSum_NetDebtIssuance,0,COLUMN()) | I74: =INDEX(MO_CFSum_NetDebtIssuance,0,COLUMN()) | J74: =INDEX(MO_CFSum_NetDebtIssuance,0,COLUMN()) | ... CF74: =INDEX(MO_CFSum_NetDebtIssuance,0,COLUMN())
A75: Other Items | C75: =+Model!C881+Model!C901+Model!C904+Model!C880+Model!C872+Model!C873+Model!C874+Model!C879+Model!C900+Model!C803 | D75: =+Model!D881+Model!D901+Model!D904+Model!D880+Model!D872+Model!D873+Model!D874+Model!D879+Model!D900+Model!D803 | E75: =+Model!E881+Model!E901+Model!E904+Model!E880+Model!E872+Model!E873+Model!E874+Model!E879+Model!E900+Model!E803 | F75: =+Model!F881+Model!F901+Model!F904+Model!F880+Model!F872+Model!F873+Model!F874+Model!F879+Model!F900+Model!F803 | G75: =+Model!G881+Model!G901+Model!G904+Model!G880+Model!G872+Model!G873+Model!G874+Model!G879+Model!G900+Model!G803 | H75: =+Model!H881+Model!H901+Model!H904+Model!H880+Model!H872+Model!H873+Model!H874+Model!H879+Model!H900+Model!H803 | I75: =+Model!I881+Model!I901+Model!I904+Model!I880+Model!I872+Model!I873+Model!I874+Model!I879+Model!I900+Model!I803 | J75: =+Model!J881+Model!J901+Model!J904+Model!J880+Model!J872+Model!J873+Model!J874+Model!J879+Model!J900+Model!J803 | ... CF75: =+Model!CF881+Model!CF901+Model!CF904+Model!CF880+Model!CF872+Model!CF873+Model!CF874+Model!CF879+Model!CF900+Model!CF803
A76: Change in Cash Position | C76: =SUM(C70:C75) | D76: =SUM(D70:D75) | E76: =SUM(E70:E75) | F76: =SUM(F70:F75) | G76: =SUM(G70:G75) | H76: =SUM(H70:H75) | I76: =SUM(I70:I75) | J76: =SUM(J70:J75) | ... CF76: =SUM(CF70:CF75)
A78: Operating Cash Flow Per Share | C78: =INDEX(SP_CFA_CFO,0,COLUMN())/INDEX(SP_CS_ShareCount,0,COLUMN()) | D78: =INDEX(SP_CFA_CFO,0,COLUMN())/INDEX(SP_CS_ShareCount,0,COLUMN()) | E78: =INDEX(SP_CFA_CFO,0,COLUMN())/INDEX(SP_CS_ShareCount,0,COLUMN()) | F78: =INDEX(SP_CFA_CFO,0,COLUMN())/INDEX(SP_CS_ShareCount,0,COLUMN()) | G78: =INDEX(SP_CFA_CFO,0,COLUMN())/INDEX(SP_CS_ShareCount,0,COLUMN()) | H78: =INDEX(SP_CFA_CFO,0,COLUMN())/INDEX(SP_CS_ShareCount,0,COLUMN()) | I78: =INDEX(SP_CFA_CFO,0,COLUMN())/INDEX(SP_CS_ShareCount,0,COLUMN()) | J78: =INDEX(SP_CFA_CFO,0,COLUMN())/INDEX(SP_CS_ShareCount,0,COLUMN()) | ... CF78: =INDEX(SP_CFA_CFO,0,COLUMN())/INDEX(SP_CS_ShareCount,0,COLUMN())
A79: Core Free Cash Flow Per Share, Pre Div | C79: =INDEX(SP_CFA_FCF_PreDiv,0,COLUMN())/INDEX(SP_CS_ShareCount,0,COLUMN()) | D79: =INDEX(SP_CFA_FCF_PreDiv,0,COLUMN())/INDEX(SP_CS_ShareCount,0,COLUMN()) | E79: =INDEX(SP_CFA_FCF_PreDiv,0,COLUMN())/INDEX(SP_CS_ShareCount,0,COLUMN()) | F79: =INDEX(SP_CFA_FCF_PreDiv,0,COLUMN())/INDEX(SP_CS_ShareCount,0,COLUMN()) | G79: =INDEX(SP_CFA_FCF_PreDiv,0,COLUMN())/INDEX(SP_CS_ShareCount,0,COLUMN()) | H79: =INDEX(SP_CFA_FCF_PreDiv,0,COLUMN())/INDEX(SP_CS_ShareCount,0,COLUMN()) | I79: =INDEX(SP_CFA_FCF_PreDiv,0,COLUMN())/INDEX(SP_CS_ShareCount,0,COLUMN()) | J79: =INDEX(SP_CFA_FCF_PreDiv,0,COLUMN())/INDEX(SP_CS_ShareCount,0,COLUMN()) | ... CF79: =INDEX(SP_CFA_FCF_PreDiv,0,COLUMN())/INDEX(SP_CS_ShareCount,0,COLUMN())
A80: Dividend Per Share | C80: =INDEX(MO_CFSum_DPS,0,COLUMN()) | D80: =INDEX(MO_CFSum_DPS,0,COLUMN()) | E80: =INDEX(MO_CFSum_DPS,0,COLUMN()) | F80: =INDEX(MO_CFSum_DPS,0,COLUMN()) | G80: =INDEX(MO_CFSum_DPS,0,COLUMN()) | H80: =INDEX(MO_CFSum_DPS,0,COLUMN()) | I80: =INDEX(MO_CFSum_DPS,0,COLUMN()) | J80: =INDEX(MO_CFSum_DPS,0,COLUMN()) | ... CF80: =INDEX(MO_CFSum_DPS,0,COLUMN())
A81: Dividend Payout Ratio vs Core FCF, Pre Div | C81: =C80/C79 | D81: =D80/D79 | E81: =E80/E79 | F81: =F80/F79 | G81: =G80/G79 | H81: =H80/H79 | I81: =I80/I79 | J81: =J80/J79 | ... CF81: =CF80/CF79
A82: Dividend Payout Ratio vs Earnings Per Share | C82: =C80/C53 | D82: =D80/D53 | E82: =E80/E53 | F82: =F80/F53 | G82: =G80/G53 | H82: =H80/H53 | I82: =I80/I53 | J82: =J80/J53 | ... CF82: =CF80/CF53
A84: Balance Sheet Ratios
A85: Net Debt / EBITDA | D85: =INDEX(MO_BSS_Debt_Net,0,COLUMN())/INDEX(SP_BSR_EBITDA_LTM,0,COLUMN()) | E85: =INDEX(MO_BSS_Debt_Net,0,COLUMN())/INDEX(SP_BSR_EBITDA_LTM,0,COLUMN()) | F85: =INDEX(MO_BSS_Debt_Net,0,COLUMN())/INDEX(SP_BSR_EBITDA_LTM,0,COLUMN()) | J85: =INDEX(MO_BSS_Debt_Net,0,COLUMN())/INDEX(SP_BSR_EBITDA_LTM,0,COLUMN()) | K85: =INDEX(MO_BSS_Debt_Net,0,COLUMN())/INDEX(SP_BSR_EBITDA_LTM,0,COLUMN()) | L85: =INDEX(MO_BSS_Debt_Net,0,COLUMN())/INDEX(SP_BSR_EBITDA_LTM,0,COLUMN()) | M85: =INDEX(MO_BSS_Debt_Net,0,COLUMN())/INDEX(SP_BSR_EBITDA_LTM,0,COLUMN()) | N85: =INDEX(MO_BSS_Debt_Net,0,COLUMN())/INDEX(SP_BSR_EBITDA_LTM,0,COLUMN()) | O85: =INDEX(MO_BSS_Debt_Net,0,COLUMN())/INDEX(SP_BSR_EBITDA_LTM,0,COLUMN()) | P85: =INDEX(MO_BSS_Debt_Net,0,COLUMN())/INDEX(SP_BSR_EBITDA_LTM,0,COLUMN()) | Q85: =INDEX(MO_BSS_Debt_Net,0,COLUMN())/INDEX(SP_BSR_EBITDA_LTM,0,COLUMN()) | ... CF85: =INDEX(MO_BSS_Debt_Net,0,COLUMN())/INDEX(SP_BSR_EBITDA_LTM,0,COLUMN())
A86: Net Debt / Cash Flow | C86: =INDEX(MO_BSS_Debt_Net,0,COLUMN())/INDEX(SP_BSR_CashFlow_LTM,0,COLUMN()) | D86: =INDEX(MO_BSS_Debt_Net,0,COLUMN())/INDEX(SP_BSR_CashFlow_LTM,0,COLUMN()) | E86: =INDEX(MO_BSS_Debt_Net,0,COLUMN())/INDEX(SP_BSR_CashFlow_LTM,0,COLUMN()) | F86: =INDEX(MO_BSS_Debt_Net,0,COLUMN())/INDEX(SP_BSR_CashFlow_LTM,0,COLUMN()) | J86: =INDEX(MO_BSS_Debt_Net,0,COLUMN())/INDEX(SP_BSR_CashFlow_LTM,0,COLUMN()) | K86: =INDEX(MO_BSS_Debt_Net,0,COLUMN())/INDEX(SP_BSR_CashFlow_LTM,0,COLUMN()) | L86: =INDEX(MO_BSS_Debt_Net,0,COLUMN())/INDEX(SP_BSR_CashFlow_LTM,0,COLUMN()) | M86: =INDEX(MO_BSS_Debt_Net,0,COLUMN())/INDEX(SP_BSR_CashFlow_LTM,0,COLUMN()) | N86: =INDEX(MO_BSS_Debt_Net,0,COLUMN())/INDEX(SP_BSR_CashFlow_LTM,0,COLUMN()) | O86: =INDEX(MO_BSS_Debt_Net,0,COLUMN())/INDEX(SP_BSR_CashFlow_LTM,0,COLUMN()) | P86: =INDEX(MO_BSS_Debt_Net,0,COLUMN())/INDEX(SP_BSR_CashFlow_LTM,0,COLUMN()) | Q86: =INDEX(MO_BSS_Debt_Net,0,COLUMN())/INDEX(SP_BSR_CashFlow_LTM,0,COLUMN()) | ... CF86: =INDEX(MO_BSS_Debt_Net,0,COLUMN())/INDEX(SP_BSR_CashFlow_LTM,0,COLUMN())
A87: Net Debt / Capital | C87: =INDEX(MO_BSS_Debt_Net,0,COLUMN())/SUM(INDEX(MO_BS_SE,0,COLUMN()),INDEX(MO_BSS_Debt,0,COLUMN()),IFERROR(INDEX(MO_BSS_OL,0,COLUMN()),0)) | D87: =INDEX(MO_BSS_Debt_Net,0,COLUMN())/SUM(INDEX(MO_BS_SE,0,COLUMN()),INDEX(MO_BSS_Debt,0,COLUMN()),IFERROR(INDEX(MO_BSS_OL,0,COLUMN()),0)) | E87: =INDEX(MO_BSS_Debt_Net,0,COLUMN())/SUM(INDEX(MO_BS_SE,0,COLUMN()),INDEX(MO_BSS_Debt,0,COLUMN()),IFERROR(INDEX(MO_BSS_OL,0,COLUMN()),0)) | F87: =INDEX(MO_BSS_Debt_Net,0,COLUMN())/SUM(INDEX(MO_BS_SE,0,COLUMN()),INDEX(MO_BSS_Debt,0,COLUMN()),IFERROR(INDEX(MO_BSS_OL,0,COLUMN()),0)) | J87: =INDEX(MO_BSS_Debt_Net,0,COLUMN())/SUM(INDEX(MO_BS_SE,0,COLUMN()),INDEX(MO_BSS_Debt,0,COLUMN()),IFERROR(INDEX(MO_BSS_OL,0,COLUMN()),0)) | K87: =INDEX(MO_BSS_Debt_Net,0,COLUMN())/SUM(INDEX(MO_BS_SE,0,COLUMN()),INDEX(MO_BSS_Debt,0,COLUMN()),IFERROR(INDEX(MO_BSS_OL,0,COLUMN()),0)) | L87: =INDEX(MO_BSS_Debt_Net,0,COLUMN())/SUM(INDEX(MO_BS_SE,0,COLUMN()),INDEX(MO_BSS_Debt,0,COLUMN()),IFERROR(INDEX(MO_BSS_OL,0,COLUMN()),0)) | M87: =INDEX(MO_BSS_Debt_Net,0,COLUMN())/SUM(INDEX(MO_BS_SE,0,COLUMN()),INDEX(MO_BSS_Debt,0,COLUMN()),IFERROR(INDEX(MO_BSS_OL,0,COLUMN()),0)) | N87: =INDEX(MO_BSS_Debt_Net,0,COLUMN())/SUM(INDEX(MO_BS_SE,0,COLUMN()),INDEX(MO_BSS_Debt,0,COLUMN()),IFERROR(INDEX(MO_BSS_OL,0,COLUMN()),0)) | O87: =INDEX(MO_BSS_Debt_Net,0,COLUMN())/SUM(INDEX(MO_BS_SE,0,COLUMN()),INDEX(MO_BSS_Debt,0,COLUMN()),IFERROR(INDEX(MO_BSS_OL,0,COLUMN()),0)) | P87: =INDEX(MO_BSS_Debt_Net,0,COLUMN())/SUM(INDEX(MO_BS_SE,0,COLUMN()),INDEX(MO_BSS_Debt,0,COLUMN()),IFERROR(INDEX(MO_BSS_OL,0,COLUMN()),0)) | Q87: =INDEX(MO_BSS_Debt_Net,0,COLUMN())/SUM(INDEX(MO_BS_SE,0,COLUMN()),INDEX(MO_BSS_Debt,0,COLUMN()),IFERROR(INDEX(MO_BSS_OL,0,COLUMN()),0)) | ... CF87: =INDEX(MO_BSS_Debt_Net,0,COLUMN())/SUM(INDEX(MO_BS_SE,0,COLUMN()),INDEX(MO_BSS_Debt,0,COLUMN()),IFERROR(INDEX(MO_BSS_OL,0,COLUMN()),0))
A88: LTM EBITDA | C88: =C51 | D88: =D51 | E88: =E51 | F88: =F51 | J88: =SUM(J51,I51,H51,G51) | K88: =K51 | L88: =SUM(L51,J51,I51,H51) | M88: =SUM(M51,L51,J51,I51) | N88: =SUM(N51,M51,L51,J51) | O88: =SUM(O51,N51,M51,L51) | P88: =P51 | Q88: =SUM(Q51,O51,N51,M51) | R88: =SUM(R51,Q51,O51,N51) | S88: =SUM(S51,R51,Q51,O51) | T88: =SUM(T51,S51,R51,Q51) | U88: =U51 | V88: =SUM(V51,T51,S51,R51) | W88: =SUM(W51,V51,T51,S51) | X88: =SUM(X51,W51,V51,T51) | Y88: =SUM(Y51,X51,W51,V51) | Z88: =Z51 | AA88: =SUM(AA51,Y51,X51,W51) | AB88: =SUM(AB51,AA51,Y51,X51) | AC88: =SUM(AC51,AB51,AA51,Y51) | AD88: =SUM(AD51,AC51,AB51,AA51) | AE88: =AE51 | AF88: =SUM(AF51,AD51,AC51,AB51) | AG88: =SUM(AG51,AF51,AD51,AC51) | AH88: =SUM(AH51,AG51,AF51,AD51) | AI88: =SUM(AI51,AH51,AG51,AF51) | AJ88: =AJ51 | AK88: =SUM(AK51,AI51,AH51,AG51) | AL88: =SUM(AL51,AK51,AI51,AH51) | AM88: =SUM(AM51,AL51,AK51,AI51) | AN88: =SUM(AN51,AM51,AL51,AK51) | AO88: =AO51 | AP88: =SUM(AP51,AN51,AM51,AL51) | AQ88: =SUM(AQ51,AP51,AN51,AM51) | AR88: =SUM(AR51,AQ51,AP51,AN51) | AS88: =SUM(AS51,AR51,AQ51,AP51) | AT88: =AT51 | AU88: =SUM(AU51,AS51,AR51,AQ51) | AV88: =SUM(AV51,AU51,AS51,AR51) | AW88: =SUM(AW51,AV51,AU51,AS51) | AX88: =SUM(AX51,AW51,AV51,AU51) | AY88: =AY51 | AZ88: =SUM(AZ51,AX51,AW51,AV51) | BA88: =SUM(BA51,AZ51,AX51,AW51) | BB88: =SUM(BB51,BA51,AZ51,AX51) | BC88: =SUM(BC51,BB51,BA51,AZ51) | BD88: =BD51 | BE88: =SUM(BE51,BC51,BB51,BA51) | BF88: =SUM(BF51,BE51,BC51,BB51) | BG88: =SUM(BG51,BF51,BE51,BC51) | BH88: =SUM(BH51,BG51,BF51,BE51) | BI88: =BI51 | BJ88: =SUM(BJ51,BH51,BG51,BF51) | BK88: =SUM(BK51,BJ51,BH51,BG51) | BL88: =SUM(BL51,BK51,BJ51,BH51) | BM88: =SUM(BM51,BL51,BK51,BJ51) | BN88: =BN51 | BO88: =SUM(BO51,BM51,BL51,BK51) | BP88: =SUM(BP51,BO51,BM51,BL51) | BQ88: =SUM(BQ51,BP51,BO51,BM51) | BR88: =SUM(BR51,BQ51,BP51,BO51) | BS88: =BS51 | BT88: =SUM(BT51,BR51,BQ51,BP51) | BU88: =SUM(BU51,BT51,BR51,BQ51) | BV88: =SUM(BV51,BU51,BT51,BR51) | BW88: =SUM(BW51,BV51,BU51,BT51) | BX88: =BX51 | BY88: =SUM(BY51,BW51,BV51,BU51) | BZ88: =SUM(BZ51,BY51,BW51,BV51) | CA88: =SUM(CA51,BZ51,BY51,BW51) | CB88: =SUM(CB51,CA51,BZ51,BY51) | CC88: =CC51 | CD88: =CD51 | CE88: =CE51 | CF88: =CF51
A89: LTM Cash Flow | C89: =C66 | D89: =D66 | E89: =E66 | F89: =F66 | J89: =SUM(J66,I66,H66,G66) | K89: =K66 | L89: =SUM(L66,J66,I66,H66) | M89: =SUM(M66,L66,J66,I66) | N89: =SUM(N66,M66,L66,J66) | O89: =SUM(O66,N66,M66,L66) | P89: =P66 | Q89: =SUM(Q66,O66,N66,M66) | R89: =SUM(R66,Q66,O66,N66) | S89: =SUM(S66,R66,Q66,O66) | T89: =SUM(T66,S66,R66,Q66) | U89: =U66 | V89: =SUM(V66,T66,S66,R66) | W89: =SUM(W66,V66,T66,S66) | X89: =SUM(X66,W66,V66,T66) | Y89: =SUM(Y66,X66,W66,V66) | Z89: =Z66 | AA89: =SUM(AA66,Y66,X66,W66) | AB89: =SUM(AB66,AA66,Y66,X66) | AC89: =SUM(AC66,AB66,AA66,Y66) | AD89: =SUM(AD66,AC66,AB66,AA66) | AE89: =AE66 | AF89: =SUM(AF66,AD66,AC66,AB66) | AG89: =SUM(AG66,AF66,AD66,AC66) | AH89: =SUM(AH66,AG66,AF66,AD66) | AI89: =SUM(AI66,AH66,AG66,AF66) | AJ89: =AJ66 | AK89: =SUM(AK66,AI66,AH66,AG66) | AL89: =SUM(AL66,AK66,AI66,AH66) | AM89: =SUM(AM66,AL66,AK66,AI66) | AN89: =SUM(AN66,AM66,AL66,AK66) | AO89: =AO66 | AP89: =SUM(AP66,AN66,AM66,AL66) | AQ89: =SUM(AQ66,AP66,AN66,AM66) | AR89: =SUM(AR66,AQ66,AP66,AN66) | AS89: =SUM(AS66,AR66,AQ66,AP66) | AT89: =AT66 | AU89: =SUM(AU66,AS66,AR66,AQ66) | AV89: =SUM(AV66,AU66,AS66,AR66) | AW89: =SUM(AW66,AV66,AU66,AS66) | AX89: =SUM(AX66,AW66,AV66,AU66) | AY89: =AY66 | AZ89: =SUM(AZ66,AX66,AW66,AV66) | BA89: =SUM(BA66,AZ66,AX66,AW66) | BB89: =SUM(BB66,BA66,AZ66,AX66) | BC89: =SUM(BC66,BB66,BA66,AZ66) | BD89: =BD66 | BE89: =SUM(BE66,BC66,BB66,BA66) | BF89: =SUM(BF66,BE66,BC66,BB66) | BG89: =SUM(BG66,BF66,BE66,BC66) | BH89: =SUM(BH66,BG66,BF66,BE66) | BI89: =BI66 | BJ89: =SUM(BJ66,BH66,BG66,BF66) | BK89: =SUM(BK66,BJ66,BH66,BG66) | BL89: =SUM(BL66,BK66,BJ66,BH66) | BM89: =SUM(BM66,BL66,BK66,BJ66) | BN89: =BN66 | BO89: =SUM(BO66,BM66,BL66,BK66) | BP89: =SUM(BP66,BO66,BM66,BL66) | BQ89: =SUM(BQ66,BP66,BO66,BM66) | BR89: =SUM(BR66,BQ66,BP66,BO66) | BS89: =BS66 | BT89: =SUM(BT66,BR66,BQ66,BP66) | BU89: =SUM(BU66,BT66,BR66,BQ66) | BV89: =SUM(BV66,BU66,BT66,BR66) | BW89: =SUM(BW66,BV66,BU66,BT66) | BX89: =BX66 | BY89: =SUM(BY66,BW66,BV66,BU66) | BZ89: =SUM(BZ66,BY66,BW66,BV66) | CA89: =SUM(CA66,BZ66,BY66,BW66) | CB89: =SUM(CB66,CA66,BZ66,BY66) | CC89: =CC66 | CD89: =CD66 | CE89: =CE66 | CF89: =CF66
A91: Profitability Ratios
A92: Net Income | C92: =INDEX(SP_NGF_NI,0,COLUMN()) | D92: =INDEX(SP_NGF_NI,0,COLUMN()) | E92: =INDEX(SP_NGF_NI,0,COLUMN()) | F92: =INDEX(SP_NGF_NI,0,COLUMN()) | G92: =INDEX(SP_NGF_NI,0,COLUMN()) | H92: =INDEX(SP_NGF_NI,0,COLUMN()) | I92: =INDEX(SP_NGF_NI,0,COLUMN()) | J92: =INDEX(SP_NGF_NI,0,COLUMN()) | ... CF92: =INDEX(SP_NGF_NI,0,COLUMN())
A93: LTM Net Income | C93: =C92 | D93: =D92 | E93: =E92 | F93: =F92 | J93: =SUM(J92,I92,H92,G92) | K93: =K92 | L93: =SUM(L92,J92,I92,H92) | M93: =SUM(M92,L92,J92,I92) | N93: =SUM(N92,M92,L92,J92) | O93: =SUM(O92,N92,M92,L92) | P93: =P92 | Q93: =SUM(Q92,O92,N92,M92) | R93: =SUM(R92,Q92,O92,N92) | S93: =SUM(S92,R92,Q92,O92) | T93: =SUM(T92,S92,R92,Q92) | U93: =U92 | V93: =SUM(V92,T92,S92,R92) | W93: =SUM(W92,V92,T92,S92) | X93: =SUM(X92,W92,V92,T92) | Y93: =SUM(Y92,X92,W92,V92) | Z93: =Z92 | AA93: =SUM(AA92,Y92,X92,W92) | AB93: =SUM(AB92,AA92,Y92,X92) | AC93: =SUM(AC92,AB92,AA92,Y92) | AD93: =SUM(AD92,AC92,AB92,AA92) | AE93: =AE92 | AF93: =SUM(AF92,AD92,AC92,AB92) | AG93: =SUM(AG92,AF92,AD92,AC92) | AH93: =SUM(AH92,AG92,AF92,AD92) | AI93: =SUM(AI92,AH92,AG92,AF92) | AJ93: =AJ92 | AK93: =SUM(AK92,AI92,AH92,AG92) | AL93: =SUM(AL92,AK92,AI92,AH92) | AM93: =SUM(AM92,AL92,AK92,AI92) | AN93: =SUM(AN92,AM92,AL92,AK92) | AO93: =AO92 | AP93: =SUM(AP92,AN92,AM92,AL92) | AQ93: =SUM(AQ92,AP92,AN92,AM92) | AR93: =SUM(AR92,AQ92,AP92,AN92) | AS93: =SUM(AS92,AR92,AQ92,AP92) | AT93: =AT92 | AU93: =SUM(AU92,AS92,AR92,AQ92) | AV93: =SUM(AV92,AU92,AS92,AR92) | AW93: =SUM(AW92,AV92,AU92,AS92) | AX93: =SUM(AX92,AW92,AV92,AU92) | AY93: =AY92 | AZ93: =SUM(AZ92,AX92,AW92,AV92) | BA93: =SUM(BA92,AZ92,AX92,AW92) | BB93: =SUM(BB92,BA92,AZ92,AX92) | BC93: =SUM(BC92,BB92,BA92,AZ92) | BD93: =BD92 | BE93: =SUM(BE92,BC92,BB92,BA92) | BF93: =SUM(BF92,BE92,BC92,BB92) | BG93: =SUM(BG92,BF92,BE92,BC92) | BH93: =SUM(BH92,BG92,BF92,BE92) | BI93: =BI92 | BJ93: =SUM(BJ92,BH92,BG92,BF92) | BK93: =SUM(BK92,BJ92,BH92,BG92) | BL93: =SUM(BL92,BK92,BJ92,BH92) | BM93: =SUM(BM92,BL92,BK92,BJ92) | BN93: =BN92 | BO93: =SUM(BO92,BM92,BL92,BK92) | BP93: =SUM(BP92,BO92,BM92,BL92) | BQ93: =SUM(BQ92,BP92,BO92,BM92) | BR93: =SUM(BR92,BQ92,BP92,BO92) | BS93: =BS92 | BT93: =SUM(BT92,BR92,BQ92,BP92) | BU93: =SUM(BU92,BT92,BR92,BQ92) | BV93: =SUM(BV92,BU92,BT92,BR92) | BW93: =SUM(BW92,BV92,BU92,BT92) | BX93: =BX92 | BY93: =SUM(BY92,BW92,BV92,BU92) | BZ93: =SUM(BZ92,BY92,BW92,BV92) | CA93: =SUM(CA92,BZ92,BY92,BW92) | CB93: =SUM(CB92,CA92,BZ92,BY92) | CC93: =CC92 | CD93: =CD92 | CE93: =CE92 | CF93: =CF92
A94: Shareholder's Equity | C94: =INDEX(MO_BS_SE,0,COLUMN()) | D94: =INDEX(MO_BS_SE,0,COLUMN()) | E94: =INDEX(MO_BS_SE,0,COLUMN()) | F94: =INDEX(MO_BS_SE,0,COLUMN()) | G94: =INDEX(MO_BS_SE,0,COLUMN()) | H94: =INDEX(MO_BS_SE,0,COLUMN()) | I94: =INDEX(MO_BS_SE,0,COLUMN()) | J94: =INDEX(MO_BS_SE,0,COLUMN()) | ... CF94: =INDEX(MO_BS_SE,0,COLUMN())
A95: Average Shareholder's Equity | C95: =C94 | D95: =AVERAGE(D94,C94) | E95: =AVERAGE(E94,D94) | F95: =AVERAGE(F94,E94) | J95: =AVERAGE(J94,I94,H94,G94) | K95: =AVERAGE(K94,F94) | L95: =AVERAGE(L94,J94,I94,H94) | M95: =AVERAGE(M94,L94,J94,I94) | N95: =AVERAGE(N94,M94,L94,J94) | O95: =AVERAGE(O94,N94,M94,L94) | P95: =AVERAGE(P94,K94) | Q95: =AVERAGE(Q94,O94,N94,M94) | R95: =AVERAGE(R94,Q94,O94,N94) | S95: =AVERAGE(S94,R94,Q94,O94) | T95: =AVERAGE(T94,S94,R94,Q94) | U95: =AVERAGE(U94,P94) | V95: =AVERAGE(V94,T94,S94,R94) | W95: =AVERAGE(W94,V94,T94,S94) | X95: =AVERAGE(X94,W94,V94,T94) | Y95: =AVERAGE(Y94,X94,W94,V94) | Z95: =AVERAGE(Z94,U94) | AA95: =AVERAGE(AA94,Y94,X94,W94) | AB95: =AVERAGE(AB94,AA94,Y94,X94) | AC95: =AVERAGE(AC94,AB94,AA94,Y94) | AD95: =AVERAGE(AD94,AC94,AB94,AA94) | AE95: =AVERAGE(AE94,Z94) | AF95: =AVERAGE(AF94,AD94,AC94,AB94) | AG95: =AVERAGE(AG94,AF94,AD94,AC94) | AH95: =AVERAGE(AH94,AG94,AF94,AD94) | AI95: =AVERAGE(AI94,AH94,AG94,AF94) | AJ95: =AVERAGE(AJ94,AE94) | AK95: =AVERAGE(AK94,AI94,AH94,AG94) | AL95: =AVERAGE(AL94,AK94,AI94,AH94) | AM95: =AVERAGE(AM94,AL94,AK94,AI94) | AN95: =AVERAGE(AN94,AM94,AL94,AK94) | AO95: =AVERAGE(AO94,AJ94) | AP95: =AVERAGE(AP94,AN94,AM94,AL94) | AQ95: =AVERAGE(AQ94,AP94,AN94,AM94) | AR95: =AVERAGE(AR94,AQ94,AP94,AN94) | AS95: =AVERAGE(AS94,AR94,AQ94,AP94) | AT95: =AVERAGE(AT94,AO94) | AU95: =AVERAGE(AU94,AS94,AR94,AQ94) | AV95: =AVERAGE(AV94,AU94,AS94,AR94) | AW95: =AVERAGE(AW94,AV94,AU94,AS94) | AX95: =AVERAGE(AX94,AW94,AV94,AU94) | AY95: =AVERAGE(AY94,AT94) | AZ95: =AVERAGE(AZ94,AX94,AW94,AV94) | BA95: =AVERAGE(BA94,AZ94,AX94,AW94) | BB95: =AVERAGE(BB94,BA94,AZ94,AX94) | BC95: =AVERAGE(BC94,BB94,BA94,AZ94) | BD95: =AVERAGE(BD94,AY94) | BE95: =AVERAGE(BE94,BC94,BB94,BA94) | BF95: =AVERAGE(BF94,BE94,BC94,BB94) | BG95: =AVERAGE(BG94,BF94,BE94,BC94) | BH95: =AVERAGE(BH94,BG94,BF94,BE94) | BI95: =AVERAGE(BI94,BD94) | BJ95: =AVERAGE(BJ94,BH94,BG94,BF94) | BK95: =AVERAGE(BK94,BJ94,BH94,BG94) | BL95: =AVERAGE(BL94,BK94,BJ94,BH94) | BM95: =AVERAGE(BM94,BL94,BK94,BJ94) | BN95: =AVERAGE(BN94,BI94) | BO95: =AVERAGE(BO94,BM94,BL94,BK94) | BP95: =AVERAGE(BP94,BO94,BM94,BL94) | BQ95: =AVERAGE(BQ94,BP94,BO94,BM94) | BR95: =AVERAGE(BR94,BQ94,BP94,BO94) | BS95: =AVERAGE(BS94,BN94) | BT95: =AVERAGE(BT94,BR94,BQ94,BP94) | BU95: =AVERAGE(BU94,BT94,BR94,BQ94) | BV95: =AVERAGE(BV94,BU94,BT94,BR94) | BW95: =AVERAGE(BW94,BV94,BU94,BT94) | BX95: =AVERAGE(BX94,BS94) | BY95: =AVERAGE(BY94,BW94,BV94,BU94) | BZ95: =AVERAGE(BZ94,BY94,BW94,BV94) | CA95: =AVERAGE(CA94,BZ94,BY94,BW94) | CB95: =AVERAGE(CB94,CA94,BZ94,BY94) | CC95: =AVERAGE(CC94,BX94) | CD95: =AVERAGE(CD94,CC94) | CE95: =AVERAGE(CE94,CD94) | CF95: =AVERAGE(CF94,CE94)
A96: ROE | C96: =IF(C95<0,"NMF",IF(ABS(C93/C95)>1,"NMF",C93/C95)) | D96: =IF(D95<0,"NMF",IF(ABS(D93/D95)>1,"NMF",D93/D95)) | E96: =IF(E95<0,"NMF",IF(ABS(E93/E95)>1,"NMF",E93/E95)) | F96: =IF(F95<0,"NMF",IF(ABS(F93/F95)>1,"NMF",F93/F95)) | K96: =IF(K95<0,"NMF",IF(ABS(K93/K95)>1,"NMF",K93/K95)) | L96: =IF(L95<0,"NMF",IF(ABS(L93/L95)>1,"NMF",L93/L95)) | M96: =IF(M95<0,"NMF",IF(ABS(M93/M95)>1,"NMF",M93/M95)) | N96: =IF(N95<0,"NMF",IF(ABS(N93/N95)>1,"NMF",N93/N95)) | O96: =IF(O95<0,"NMF",IF(ABS(O93/O95)>1,"NMF",O93/O95)) | P96: =IF(P95<0,"NMF",IF(ABS(P93/P95)>1,"NMF",P93/P95)) | Q96: =IF(Q95<0,"NMF",IF(ABS(Q93/Q95)>1,"NMF",Q93/Q95)) | R96: =IF(R95<0,"NMF",IF(ABS(R93/R95)>1,"NMF",R93/R95)) | ... CF96: =IF(CF95<0,"NMF",IF(ABS(CF93/CF95)>1,"NMF",CF93/CF95))
A97: Net Operating Profit | C97: =+C38 | D97: =+D38 | E97: =+E38 | F97: =+F38 | G97: =+G38 | H97: =+H38 | I97: =+I38 | J97: =+J38 | ... CF97: =+CF38
A98: LTM Net Operating Profit | C98: =C97 | D98: =D97 | E98: =E97 | F98: =F97 | J98: =SUM(J97,I97,H97,G97) | K98: =K97 | L98: =SUM(L97,J97,I97,H97) | M98: =SUM(M97,L97,J97,I97) | N98: =SUM(N97,M97,L97,J97) | O98: =SUM(O97,N97,M97,L97) | P98: =P97 | Q98: =SUM(Q97,O97,N97,M97) | R98: =SUM(R97,Q97,O97,N97) | S98: =SUM(S97,R97,Q97,O97) | T98: =SUM(T97,S97,R97,Q97) | U98: =U97 | V98: =SUM(V97,T97,S97,R97) | W98: =SUM(W97,V97,T97,S97) | X98: =SUM(X97,W97,V97,T97) | Y98: =SUM(Y97,X97,W97,V97) | Z98: =Z97 | AA98: =SUM(AA97,Y97,X97,W97) | AB98: =SUM(AB97,AA97,Y97,X97) | AC98: =SUM(AC97,AB97,AA97,Y97) | AD98: =SUM(AD97,AC97,AB97,AA97) | AE98: =AE97 | AF98: =SUM(AF97,AD97,AC97,AB97) | AG98: =SUM(AG97,AF97,AD97,AC97) | AH98: =SUM(AH97,AG97,AF97,AD97) | AI98: =SUM(AI97,AH97,AG97,AF97) | AJ98: =AJ97 | AK98: =SUM(AK97,AI97,AH97,AG97) | AL98: =SUM(AL97,AK97,AI97,AH97) | AM98: =SUM(AM97,AL97,AK97,AI97) | AN98: =SUM(AN97,AM97,AL97,AK97) | AO98: =AO97 | AP98: =SUM(AP97,AN97,AM97,AL97) | AQ98: =SUM(AQ97,AP97,AN97,AM97) | AR98: =SUM(AR97,AQ97,AP97,AN97) | AS98: =SUM(AS97,AR97,AQ97,AP97) | AT98: =AT97 | AU98: =SUM(AU97,AS97,AR97,AQ97) | AV98: =SUM(AV97,AU97,AS97,AR97) | AW98: =SUM(AW97,AV97,AU97,AS97) | AX98: =SUM(AX97,AW97,AV97,AU97) | AY98: =AY97 | AZ98: =SUM(AZ97,AX97,AW97,AV97) | BA98: =SUM(BA97,AZ97,AX97,AW97) | BB98: =SUM(BB97,BA97,AZ97,AX97) | BC98: =SUM(BC97,BB97,BA97,AZ97) | BD98: =BD97 | BE98: =SUM(BE97,BC97,BB97,BA97) | BF98: =SUM(BF97,BE97,BC97,BB97) | BG98: =SUM(BG97,BF97,BE97,BC97) | BH98: =SUM(BH97,BG97,BF97,BE97) | BI98: =BI97 | BJ98: =SUM(BJ97,BH97,BG97,BF97) | BK98: =SUM(BK97,BJ97,BH97,BG97) | BL98: =SUM(BL97,BK97,BJ97,BH97) | BM98: =SUM(BM97,BL97,BK97,BJ97) | BN98: =BN97 | BO98: =SUM(BO97,BM97,BL97,BK97) | BP98: =SUM(BP97,BO97,BM97,BL97) | BQ98: =SUM(BQ97,BP97,BO97,BM97) | BR98: =SUM(BR97,BQ97,BP97,BO97) | BS98: =BS97 | BT98: =SUM(BT97,BR97,BQ97,BP97) | BU98: =SUM(BU97,BT97,BR97,BQ97) | BV98: =SUM(BV97,BU97,BT97,BR97) | BW98: =SUM(BW97,BV97,BU97,BT97) | BX98: =BX97 | BY98: =SUM(BY97,BW97,BV97,BU97) | BZ98: =SUM(BZ97,BY97,BW97,BV97) | CA98: =SUM(CA97,BZ97,BY97,BW97) | CB98: =SUM(CB97,CA97,BZ97,BY97) | CC98: =CC97 | CD98: =CD97 | CE98: =CE97 | CF98: =CF97
A99: Total Assets | C99: =INDEX(MO_BS_TA,0,COLUMN()) | D99: =INDEX(MO_BS_TA,0,COLUMN()) | E99: =INDEX(MO_BS_TA,0,COLUMN()) | F99: =INDEX(MO_BS_TA,0,COLUMN()) | G99: =INDEX(MO_BS_TA,0,COLUMN()) | H99: =INDEX(MO_BS_TA,0,COLUMN()) | I99: =INDEX(MO_BS_TA,0,COLUMN()) | J99: =INDEX(MO_BS_TA,0,COLUMN()) | ... CF99: =INDEX(MO_BS_TA,0,COLUMN())
A100: Average Total Assets | C100: =C99 | D100: =AVERAGE(D99,C99) | E100: =AVERAGE(E99,D99) | F100: =AVERAGE(F99,E99) | J100: =AVERAGE(J99,I99,H99,G99) | K100: =AVERAGE(K99,F99) | L100: =AVERAGE(L99,J99,I99,H99) | M100: =AVERAGE(M99,L99,J99,I99) | N100: =AVERAGE(N99,M99,L99,J99) | O100: =AVERAGE(O99,N99,M99,L99) | P100: =AVERAGE(P99,K99) | Q100: =AVERAGE(Q99,O99,N99,M99) | R100: =AVERAGE(R99,Q99,O99,N99) | S100: =AVERAGE(S99,R99,Q99,O99) | T100: =AVERAGE(T99,S99,R99,Q99) | U100: =AVERAGE(U99,P99) | V100: =AVERAGE(V99,T99,S99,R99) | W100: =AVERAGE(W99,V99,T99,S99) | X100: =AVERAGE(X99,W99,V99,T99) | Y100: =AVERAGE(Y99,X99,W99,V99) | Z100: =AVERAGE(Z99,U99) | AA100: =AVERAGE(AA99,Y99,X99,W99) | AB100: =AVERAGE(AB99,AA99,Y99,X99) | AC100: =AVERAGE(AC99,AB99,AA99,Y99) | AD100: =AVERAGE(AD99,AC99,AB99,AA99) | AE100: =AVERAGE(AE99,Z99) | AF100: =AVERAGE(AF99,AD99,AC99,AB99) | AG100: =AVERAGE(AG99,AF99,AD99,AC99) | AH100: =AVERAGE(AH99,AG99,AF99,AD99) | AI100: =AVERAGE(AI99,AH99,AG99,AF99) | AJ100: =AVERAGE(AJ99,AE99) | AK100: =AVERAGE(AK99,AI99,AH99,AG99) | AL100: =AVERAGE(AL99,AK99,AI99,AH99) | AM100: =AVERAGE(AM99,AL99,AK99,AI99) | AN100: =AVERAGE(AN99,AM99,AL99,AK99) | AO100: =AVERAGE(AO99,AJ99) | AP100: =AVERAGE(AP99,AN99,AM99,AL99) | AQ100: =AVERAGE(AQ99,AP99,AN99,AM99) | AR100: =AVERAGE(AR99,AQ99,AP99,AN99) | AS100: =AVERAGE(AS99,AR99,AQ99,AP99) | AT100: =AVERAGE(AT99,AO99) | AU100: =AVERAGE(AU99,AS99,AR99,AQ99) | AV100: =AVERAGE(AV99,AU99,AS99,AR99) | AW100: =AVERAGE(AW99,AV99,AU99,AS99) | AX100: =AVERAGE(AX99,AW99,AV99,AU99) | AY100: =AVERAGE(AY99,AT99) | AZ100: =AVERAGE(AZ99,AX99,AW99,AV99) | BA100: =AVERAGE(BA99,AZ99,AX99,AW99) | BB100: =AVERAGE(BB99,BA99,AZ99,AX99) | BC100: =AVERAGE(BC99,BB99,BA99,AZ99) | BD100: =AVERAGE(BD99,AY99) | BE100: =AVERAGE(BE99,BC99,BB99,BA99) | BF100: =AVERAGE(BF99,BE99,BC99,BB99) | BG100: =AVERAGE(BG99,BF99,BE99,BC99) | BH100: =AVERAGE(BH99,BG99,BF99,BE99) | BI100: =AVERAGE(BI99,BD99) | BJ100: =AVERAGE(BJ99,BH99,BG99,BF99) | BK100: =AVERAGE(BK99,BJ99,BH99,BG99) | BL100: =AVERAGE(BL99,BK99,BJ99,BH99) | BM100: =AVERAGE(BM99,BL99,BK99,BJ99) | BN100: =AVERAGE(BN99,BI99) | BO100: =AVERAGE(BO99,BM99,BL99,BK99) | BP100: =AVERAGE(BP99,BO99,BM99,BL99) | BQ100: =AVERAGE(BQ99,BP99,BO99,BM99) | BR100: =AVERAGE(BR99,BQ99,BP99,BO99) | BS100: =AVERAGE(BS99,BN99) | BT100: =AVERAGE(BT99,BR99,BQ99,BP99) | BU100: =AVERAGE(BU99,BT99,BR99,BQ99) | BV100: =AVERAGE(BV99,BU99,BT99,BR99) | BW100: =AVERAGE(BW99,BV99,BU99,BT99) | BX100: =AVERAGE(BX99,BS99) | BY100: =AVERAGE(BY99,BW99,BV99,BU99) | BZ100: =AVERAGE(BZ99,BY99,BW99,BV99) | CA100: =AVERAGE(CA99,BZ99,BY99,BW99) | CB100: =AVERAGE(CB99,CA99,BZ99,BY99) | CC100: =AVERAGE(CC99,BX99) | CD100: =AVERAGE(CD99,CC99) | CE100: =AVERAGE(CE99,CD99) | CF100: =AVERAGE(CF99,CE99)
A101: ROA | C101: =IF(C100<0,"NMF",IF(ABS(C98/C100)>1,"NMF",C98/C100)) | D101: =IF(D100<0,"NMF",IF(ABS(D98/D100)>1,"NMF",D98/D100)) | E101: =IF(E100<0,"NMF",IF(ABS(E98/E100)>1,"NMF",E98/E100)) | F101: =IF(F100<0,"NMF",IF(ABS(F98/F100)>1,"NMF",F98/F100)) | K101: =IF(K100<0,"NMF",IF(ABS(K98/K100)>1,"NMF",K98/K100)) | L101: =IF(L100<0,"NMF",IF(ABS(L98/L100)>1,"NMF",L98/L100)) | M101: =IF(M100<0,"NMF",IF(ABS(M98/M100)>1,"NMF",M98/M100)) | N101: =IF(N100<0,"NMF",IF(ABS(N98/N100)>1,"NMF",N98/N100)) | O101: =IF(O100<0,"NMF",IF(ABS(O98/O100)>1,"NMF",O98/O100)) | P101: =IF(P100<0,"NMF",IF(ABS(P98/P100)>1,"NMF",P98/P100)) | Q101: =IF(Q100<0,"NMF",IF(ABS(Q98/Q100)>1,"NMF",Q98/Q100)) | R101: =IF(R100<0,"NMF",IF(ABS(R98/R100)>1,"NMF",R98/R100)) | ... CF101: =IF(CF100<0,"NMF",IF(ABS(CF98/CF100)>1,"NMF",CF98/CF100))
A102: Total Debt | C102: =INDEX(MO_BSS_Debt_Net,0,COLUMN())+INDEX(MO_BSS_Cash,0,COLUMN()) | D102: =INDEX(MO_BSS_Debt_Net,0,COLUMN())+INDEX(MO_BSS_Cash,0,COLUMN()) | E102: =INDEX(MO_BSS_Debt_Net,0,COLUMN())+INDEX(MO_BSS_Cash,0,COLUMN()) | F102: =INDEX(MO_BSS_Debt_Net,0,COLUMN())+INDEX(MO_BSS_Cash,0,COLUMN()) | G102: =INDEX(MO_BSS_Debt_Net,0,COLUMN())+INDEX(MO_BSS_Cash,0,COLUMN()) | H102: =INDEX(MO_BSS_Debt_Net,0,COLUMN())+INDEX(MO_BSS_Cash,0,COLUMN()) | I102: =INDEX(MO_BSS_Debt_Net,0,COLUMN())+INDEX(MO_BSS_Cash,0,COLUMN()) | J102: =INDEX(MO_BSS_Debt_Net,0,COLUMN())+INDEX(MO_BSS_Cash,0,COLUMN()) | ... CF102: =INDEX(MO_BSS_Debt_Net,0,COLUMN())+INDEX(MO_BSS_Cash,0,COLUMN())
A103: Average Book Value of Debt | C103: =C102 | D103: =AVERAGE(D102,C102) | E103: =AVERAGE(E102,D102) | F103: =AVERAGE(F102,E102) | J103: =AVERAGE(J102,I102,H102,G102) | K103: =AVERAGE(K102,F102) | L103: =AVERAGE(L102,J102,I102,H102) | M103: =AVERAGE(M102,L102,J102,I102) | N103: =AVERAGE(N102,M102,L102,J102) | O103: =AVERAGE(O102,N102,M102,L102) | P103: =AVERAGE(P102,K102) | Q103: =AVERAGE(Q102,O102,N102,M102) | R103: =AVERAGE(R102,Q102,O102,N102) | S103: =AVERAGE(S102,R102,Q102,O102) | T103: =AVERAGE(T102,S102,R102,Q102) | U103: =AVERAGE(U102,P102) | V103: =AVERAGE(V102,T102,S102,R102) | W103: =AVERAGE(W102,V102,T102,S102) | X103: =AVERAGE(X102,W102,V102,T102) | Y103: =AVERAGE(Y102,X102,W102,V102) | Z103: =AVERAGE(Z102,U102) | AA103: =AVERAGE(AA102,Y102,X102,W102) | AB103: =AVERAGE(AB102,AA102,Y102,X102) | AC103: =AVERAGE(AC102,AB102,AA102,Y102) | AD103: =AVERAGE(AD102,AC102,AB102,AA102) | AE103: =AVERAGE(AE102,Z102) | AF103: =AVERAGE(AF102,AD102,AC102,AB102) | AG103: =AVERAGE(AG102,AF102,AD102,AC102) | AH103: =AVERAGE(AH102,AG102,AF102,AD102) | AI103: =AVERAGE(AI102,AH102,AG102,AF102) | AJ103: =AVERAGE(AJ102,AE102) | AK103: =AVERAGE(AK102,AI102,AH102,AG102) | AL103: =AVERAGE(AL102,AK102,AI102,AH102) | AM103: =AVERAGE(AM102,AL102,AK102,AI102) | AN103: =AVERAGE(AN102,AM102,AL102,AK102) | AO103: =AVERAGE(AO102,AJ102) | AP103: =AVERAGE(AP102,AN102,AM102,AL102) | AQ103: =AVERAGE(AQ102,AP102,AN102,AM102) | AR103: =AVERAGE(AR102,AQ102,AP102,AN102) | AS103: =AVERAGE(AS102,AR102,AQ102,AP102) | AT103: =AVERAGE(AT102,AO102) | AU103: =AVERAGE(AU102,AS102,AR102,AQ102) | AV103: =AVERAGE(AV102,AU102,AS102,AR102) | AW103: =AVERAGE(AW102,AV102,AU102,AS102) | AX103: =AVERAGE(AX102,AW102,AV102,AU102) | AY103: =AVERAGE(AY102,AT102) | AZ103: =AVERAGE(AZ102,AX102,AW102,AV102) | BA103: =AVERAGE(BA102,AZ102,AX102,AW102) | BB103: =AVERAGE(BB102,BA102,AZ102,AX102) | BC103: =AVERAGE(BC102,BB102,BA102,AZ102) | BD103: =AVERAGE(BD102,AY102) | BE103: =AVERAGE(BE102,BC102,BB102,BA102) | BF103: =AVERAGE(BF102,BE102,BC102,BB102) | BG103: =AVERAGE(BG102,BF102,BE102,BC102) | BH103: =AVERAGE(BH102,BG102,BF102,BE102) | BI103: =AVERAGE(BI102,BD102) | BJ103: =AVERAGE(BJ102,BH102,BG102,BF102) | BK103: =AVERAGE(BK102,BJ102,BH102,BG102) | BL103: =AVERAGE(BL102,BK102,BJ102,BH102) | BM103: =AVERAGE(BM102,BL102,BK102,BJ102) | BN103: =AVERAGE(BN102,BI102) | BO103: =AVERAGE(BO102,BM102,BL102,BK102) | BP103: =AVERAGE(BP102,BO102,BM102,BL102) | BQ103: =AVERAGE(BQ102,BP102,BO102,BM102) | BR103: =AVERAGE(BR102,BQ102,BP102,BO102) | BS103: =AVERAGE(BS102,BN102) | BT103: =AVERAGE(BT102,BR102,BQ102,BP102) | BU103: =AVERAGE(BU102,BT102,BR102,BQ102) | BV103: =AVERAGE(BV102,BU102,BT102,BR102) | BW103: =AVERAGE(BW102,BV102,BU102,BT102) | BX103: =AVERAGE(BX102,BS102) | BY103: =AVERAGE(BY102,BW102,BV102,BU102) | BZ103: =AVERAGE(BZ102,BY102,BW102,BV102) | CA103: =AVERAGE(CA102,BZ102,BY102,BW102) | CB103: =AVERAGE(CB102,CA102,BZ102,BY102) | CC103: =AVERAGE(CC102,BX102) | CD103: =AVERAGE(CD102,CC102) | CE103: =AVERAGE(CE102,CD102) | CF103: =AVERAGE(CF102,CE102)
A104: Average Invested Capital | C104: =SUM(INDEX(SP_BSR_Debt_Avg,0,COLUMN()),INDEX(SP_BSR_SE_Avg,0,COLUMN())) | D104: =SUM(INDEX(SP_BSR_Debt_Avg,0,COLUMN()),INDEX(SP_BSR_SE_Avg,0,COLUMN())) | E104: =SUM(INDEX(SP_BSR_Debt_Avg,0,COLUMN()),INDEX(SP_BSR_SE_Avg,0,COLUMN())) | F104: =SUM(INDEX(SP_BSR_Debt_Avg,0,COLUMN()),INDEX(SP_BSR_SE_Avg,0,COLUMN())) | G104: =SUM(INDEX(SP_BSR_Debt_Avg,0,COLUMN()),INDEX(SP_BSR_SE_Avg,0,COLUMN())) | H104: =SUM(INDEX(SP_BSR_Debt_Avg,0,COLUMN()),INDEX(SP_BSR_SE_Avg,0,COLUMN())) | I104: =SUM(INDEX(SP_BSR_Debt_Avg,0,COLUMN()),INDEX(SP_BSR_SE_Avg,0,COLUMN())) | J104: =SUM(INDEX(SP_BSR_Debt_Avg,0,COLUMN()),INDEX(SP_BSR_SE_Avg,0,COLUMN())) | ... CF104: =SUM(INDEX(SP_BSR_Debt_Avg,0,COLUMN()),INDEX(SP_BSR_SE_Avg,0,COLUMN()))
A105: ROIC | C105: =IF(C104<0,"NMF",IF(ABS(C98/C104)>1,"NMF",C98/C104)) | D105: =IF(D104<0,"NMF",IF(ABS(D98/D104)>1,"NMF",D98/D104)) | E105: =IF(E104<0,"NMF",IF(ABS(E98/E104)>1,"NMF",E98/E104)) | F105: =IF(F104<0,"NMF",IF(ABS(F98/F104)>1,"NMF",F98/F104)) | J105: =IF(J104<0,"NMF",IF(ABS(J98/J104)>1,"NMF",J98/J104)) | K105: =IF(K104<0,"NMF",IF(ABS(K98/K104)>1,"NMF",K98/K104)) | L105: =IF(L104<0,"NMF",IF(ABS(L98/L104)>1,"NMF",L98/L104)) | M105: =IF(M104<0,"NMF",IF(ABS(M98/M104)>1,"NMF",M98/M104)) | N105: =IF(N104<0,"NMF",IF(ABS(N98/N104)>1,"NMF",N98/N104)) | O105: =IF(O104<0,"NMF",IF(ABS(O98/O104)>1,"NMF",O98/O104)) | P105: =IF(P104<0,"NMF",IF(ABS(P98/P104)>1,"NMF",P98/P104)) | Q105: =IF(Q104<0,"NMF",IF(ABS(Q98/Q104)>1,"NMF",Q98/Q104)) | ... CF105: =IF(CF104<0,"NMF",IF(ABS(CF98/CF104)>1,"NMF",CF98/CF104))
A106: EBIT | C106: =+C41 | D106: =+D41 | E106: =+E41 | F106: =+F41 | G106: =+G41 | H106: =+H41 | I106: =+I41 | J106: =+J41 | ... CF106: =+CF41
A107: LTM EBIT | C107: =C106 | D107: =D106 | E107: =E106 | F107: =F106 | J107: =SUM(J106,I106,H106,G106) | K107: =K106 | L107: =SUM(L106,J106,I106,H106) | M107: =SUM(M106,L106,J106,I106) | N107: =SUM(N106,M106,L106,J106) | O107: =SUM(O106,N106,M106,L106) | P107: =P106 | Q107: =SUM(Q106,O106,N106,M106) | R107: =SUM(R106,Q106,O106,N106) | S107: =SUM(S106,R106,Q106,O106) | T107: =SUM(T106,S106,R106,Q106) | U107: =U106 | V107: =SUM(V106,T106,S106,R106) | W107: =SUM(W106,V106,T106,S106) | X107: =SUM(X106,W106,V106,T106) | Y107: =SUM(Y106,X106,W106,V106) | Z107: =Z106 | AA107: =SUM(AA106,Y106,X106,W106) | AB107: =SUM(AB106,AA106,Y106,X106) | AC107: =SUM(AC106,AB106,AA106,Y106) | AD107: =SUM(AD106,AC106,AB106,AA106) | AE107: =AE106 | AF107: =SUM(AF106,AD106,AC106,AB106) | AG107: =SUM(AG106,AF106,AD106,AC106) | AH107: =SUM(AH106,AG106,AF106,AD106) | AI107: =SUM(AI106,AH106,AG106,AF106) | AJ107: =AJ106 | AK107: =SUM(AK106,AI106,AH106,AG106) | AL107: =SUM(AL106,AK106,AI106,AH106) | AM107: =SUM(AM106,AL106,AK106,AI106) | AN107: =SUM(AN106,AM106,AL106,AK106) | AO107: =AO106 | AP107: =SUM(AP106,AN106,AM106,AL106) | AQ107: =SUM(AQ106,AP106,AN106,AM106) | AR107: =SUM(AR106,AQ106,AP106,AN106) | AS107: =SUM(AS106,AR106,AQ106,AP106) | AT107: =AT106 | AU107: =SUM(AU106,AS106,AR106,AQ106) | AV107: =SUM(AV106,AU106,AS106,AR106) | AW107: =SUM(AW106,AV106,AU106,AS106) | AX107: =SUM(AX106,AW106,AV106,AU106) | AY107: =AY106 | AZ107: =SUM(AZ106,AX106,AW106,AV106) | BA107: =SUM(BA106,AZ106,AX106,AW106) | BB107: =SUM(BB106,BA106,AZ106,AX106) | BC107: =SUM(BC106,BB106,BA106,AZ106) | BD107: =BD106 | BE107: =SUM(BE106,BC106,BB106,BA106) | BF107: =SUM(BF106,BE106,BC106,BB106) | BG107: =SUM(BG106,BF106,BE106,BC106) | BH107: =SUM(BH106,BG106,BF106,BE106) | BI107: =BI106 | BJ107: =SUM(BJ106,BH106,BG106,BF106) | BK107: =SUM(BK106,BJ106,BH106,BG106) | BL107: =SUM(BL106,BK106,BJ106,BH106) | BM107: =SUM(BM106,BL106,BK106,BJ106) | BN107: =BN106 | BO107: =SUM(BO106,BM106,BL106,BK106) | BP107: =SUM(BP106,BO106,BM106,BL106) | BQ107: =SUM(BQ106,BP106,BO106,BM106) | BR107: =SUM(BR106,BQ106,BP106,BO106) | BS107: =BS106 | BT107: =SUM(BT106,BR106,BQ106,BP106) | BU107: =SUM(BU106,BT106,BR106,BQ106) | BV107: =SUM(BV106,BU106,BT106,BR106) | BW107: =SUM(BW106,BV106,BU106,BT106) | BX107: =BX106 | BY107: =SUM(BY106,BW106,BV106,BU106) | BZ107: =SUM(BZ106,BY106,BW106,BV106) | CA107: =SUM(CA106,BZ106,BY106,BW106) | CB107: =SUM(CB106,CA106,BZ106,BY106) | CC107: =CC106 | CD107: =CD106 | CE107: =CE106 | CF107: =CF106
A108: Current Liabilities | C108: =INDEX(MO_BS_CL,0,COLUMN()) | D108: =INDEX(MO_BS_CL,0,COLUMN()) | E108: =INDEX(MO_BS_CL,0,COLUMN()) | F108: =INDEX(MO_BS_CL,0,COLUMN()) | G108: =INDEX(MO_BS_CL,0,COLUMN()) | H108: =INDEX(MO_BS_CL,0,COLUMN()) | I108: =INDEX(MO_BS_CL,0,COLUMN()) | J108: =INDEX(MO_BS_CL,0,COLUMN()) | ... CF108: =INDEX(MO_BS_CL,0,COLUMN())
A109: Average Current Liabilities | C109: =C108 | D109: =AVERAGE(D108,C108) | E109: =AVERAGE(E108,D108) | F109: =AVERAGE(F108,E108) | J109: =AVERAGE(J108,I108,H108,G108) | K109: =AVERAGE(K108,F108) | L109: =AVERAGE(L108,J108,I108,H108) | M109: =AVERAGE(M108,L108,J108,I108) | N109: =AVERAGE(N108,M108,L108,J108) | O109: =AVERAGE(O108,N108,M108,L108) | P109: =AVERAGE(P108,K108) | Q109: =AVERAGE(Q108,O108,N108,M108) | R109: =AVERAGE(R108,Q108,O108,N108) | S109: =AVERAGE(S108,R108,Q108,O108) | T109: =AVERAGE(T108,S108,R108,Q108) | U109: =AVERAGE(U108,P108) | V109: =AVERAGE(V108,T108,S108,R108) | W109: =AVERAGE(W108,V108,T108,S108) | X109: =AVERAGE(X108,W108,V108,T108) | Y109: =AVERAGE(Y108,X108,W108,V108) | Z109: =AVERAGE(Z108,U108) | AA109: =AVERAGE(AA108,Y108,X108,W108) | AB109: =AVERAGE(AB108,AA108,Y108,X108) | AC109: =AVERAGE(AC108,AB108,AA108,Y108) | AD109: =AVERAGE(AD108,AC108,AB108,AA108) | AE109: =AVERAGE(AE108,Z108) | AF109: =AVERAGE(AF108,AD108,AC108,AB108) | AG109: =AVERAGE(AG108,AF108,AD108,AC108) | AH109: =AVERAGE(AH108,AG108,AF108,AD108) | AI109: =AVERAGE(AI108,AH108,AG108,AF108) | AJ109: =AVERAGE(AJ108,AE108) | AK109: =AVERAGE(AK108,AI108,AH108,AG108) | AL109: =AVERAGE(AL108,AK108,AI108,AH108) | AM109: =AVERAGE(AM108,AL108,AK108,AI108) | AN109: =AVERAGE(AN108,AM108,AL108,AK108) | AO109: =AVERAGE(AO108,AJ108) | AP109: =AVERAGE(AP108,AN108,AM108,AL108) | AQ109: =AVERAGE(AQ108,AP108,AN108,AM108) | AR109: =AVERAGE(AR108,AQ108,AP108,AN108) | AS109: =AVERAGE(AS108,AR108,AQ108,AP108) | AT109: =AVERAGE(AT108,AO108) | AU109: =AVERAGE(AU108,AS108,AR108,AQ108) | AV109: =AVERAGE(AV108,AU108,AS108,AR108) | AW109: =AVERAGE(AW108,AV108,AU108,AS108) | AX109: =AVERAGE(AX108,AW108,AV108,AU108) | AY109: =AVERAGE(AY108,AT108) | AZ109: =AVERAGE(AZ108,AX108,AW108,AV108) | BA109: =AVERAGE(BA108,AZ108,AX108,AW108) | BB109: =AVERAGE(BB108,BA108,AZ108,AX108) | BC109: =AVERAGE(BC108,BB108,BA108,AZ108) | BD109: =AVERAGE(BD108,AY108) | BE109: =AVERAGE(BE108,BC108,BB108,BA108) | BF109: =AVERAGE(BF108,BE108,BC108,BB108) | BG109: =AVERAGE(BG108,BF108,BE108,BC108) | BH109: =AVERAGE(BH108,BG108,BF108,BE108) | BI109: =AVERAGE(BI108,BD108) | BJ109: =AVERAGE(BJ108,BH108,BG108,BF108) | BK109: =AVERAGE(BK108,BJ108,BH108,BG108) | BL109: =AVERAGE(BL108,BK108,BJ108,BH108) | BM109: =AVERAGE(BM108,BL108,BK108,BJ108) | BN109: =AVERAGE(BN108,BI108) | BO109: =AVERAGE(BO108,BM108,BL108,BK108) | BP109: =AVERAGE(BP108,BO108,BM108,BL108) | BQ109: =AVERAGE(BQ108,BP108,BO108,BM108) | BR109: =AVERAGE(BR108,BQ108,BP108,BO108) | BS109: =AVERAGE(BS108,BN108) | BT109: =AVERAGE(BT108,BR108,BQ108,BP108) | BU109: =AVERAGE(BU108,BT108,BR108,BQ108) | BV109: =AVERAGE(BV108,BU108,BT108,BR108) | BW109: =AVERAGE(BW108,BV108,BU108,BT108) | BX109: =AVERAGE(BX108,BS108) | BY109: =AVERAGE(BY108,BW108,BV108,BU108) | BZ109: =AVERAGE(BZ108,BY108,BW108,BV108) | CA109: =AVERAGE(CA108,BZ108,BY108,BW108) | CB109: =AVERAGE(CB108,CA108,BZ108,BY108) | CC109: =AVERAGE(CC108,BX108) | CD109: =AVERAGE(CD108,CC108) | CE109: =AVERAGE(CE108,CD108) | CF109: =AVERAGE(CF108,CE108)
A110: Average Capital Employed | C110: =INDEX(SP_BSR_TA_Avg,0,COLUMN())-INDEX(SP_BSR_CL_Avg,0,COLUMN()) | D110: =INDEX(SP_BSR_TA_Avg,0,COLUMN())-INDEX(SP_BSR_CL_Avg,0,COLUMN()) | E110: =INDEX(SP_BSR_TA_Avg,0,COLUMN())-INDEX(SP_BSR_CL_Avg,0,COLUMN()) | F110: =INDEX(SP_BSR_TA_Avg,0,COLUMN())-INDEX(SP_BSR_CL_Avg,0,COLUMN()) | G110: =INDEX(SP_BSR_TA_Avg,0,COLUMN())-INDEX(SP_BSR_CL_Avg,0,COLUMN()) | H110: =INDEX(SP_BSR_TA_Avg,0,COLUMN())-INDEX(SP_BSR_CL_Avg,0,COLUMN()) | I110: =INDEX(SP_BSR_TA_Avg,0,COLUMN())-INDEX(SP_BSR_CL_Avg,0,COLUMN()) | J110: =INDEX(SP_BSR_TA_Avg,0,COLUMN())-INDEX(SP_BSR_CL_Avg,0,COLUMN()) | ... CF110: =INDEX(SP_BSR_TA_Avg,0,COLUMN())-INDEX(SP_BSR_CL_Avg,0,COLUMN())
...

Sheet MLNX
A1: Mellanox Technologies, Ltd.
A2: =CHOOSE(MO.DataSourceIndex,MO.Ticker.Bloomberg,MO.Ticker.CapIQ,MO.Ticker.FactSet,MO.Ticker.Thomson) | C2: =EOMONTH(C4,-12)
A3: =HP.TradeCurrency | B3: =IF(MO.RealTime="OFF",MO.LastPriceHardcoded,MO.LastPriceFormula) | C3: =C4-C2 | D3: =D4-C4 | E3: =E4-D4 | F3: =F4-E4 | G3: =G4-F4 | H3: =H4-G4 | I3: =I4-H4 | J3: =J4-I4 | K3: =K4-F4 | L3: =L4-K4 | M3: =M4-L4 | N3: =N4-M4 | O3: =O4-N4 | P3: =P4-K4 | Q3: =Q4-P4 | R3: =R4-Q4 | S3: =S4-R4 | T3: =T4-S4 | U3: =U4-P4 | V3: =V4-U4 | W3: =W4-V4 | X3: =X4-W4 | Y3: =Y4-X4 | Z3: =Z4-U4 | AA3: =AA4-Z4 | AB3: =AB4-AA4 | AC3: =AC4-AB4 | AD3: =AD4-AC4 | AE3: =AE4-Z4 | AF3: =AF4-AE4 | AG3: =AG4-AF4 | AH3: =AH4-AG4 | AI3: =AI4-AH4 | AJ3: =AJ4-AE4 | AK3: =AK4-AJ4 | AL3: =AL4-AK4 | AM3: =AM4-AL4 | AN3: =AN4-AM4 | AO3: =AO4-AJ4 | AP3: =AP4-AO4 | AQ3: =AQ4-AP4 | AR3: =AR4-AQ4 | AS3: =AS4-AR4 | AT3: =AT4-AO4 | AU3: =AU4-AT4 | AV3: =AV4-AU4 | AW3: =AW4-AV4
A4: =FP.DataSourceName | B4: =IF(AND(MO.RealTimeStockPriceToggle,MO.LastPriceFormula<>"N/A"),"ON","OFF") | C4: 40178 | D4: =EOMONTH(C4,12) | E4: =EOMONTH(D4,12) | F4: =EOMONTH(E4,12) | G4: =EOMONTH(F4,3) | H4: =EOMONTH(G4,3) | I4: =EOMONTH(H4,3) | J4: =EOMONTH(I4,3) | K4: =J4 | L4: =EOMONTH(K4,3) | M4: =EOMONTH(L4,3) | N4: =EOMONTH(M4,3) | O4: =EOMONTH(N4,3) | P4: =O4 | Q4: =EOMONTH(P4,3) | R4: =EOMONTH(Q4,3) | S4: =EOMONTH(R4,3) | T4: =EOMONTH(S4,3) | U4: =T4 | V4: =EOMONTH(U4,3) | W4: =EOMONTH(V4,3) | X4: =EOMONTH(W4,3) | Y4: =EOMONTH(X4,3) | Z4: =Y4 | AA4: =EOMONTH(Z4,3) | AB4: =EOMONTH(AA4,3) | AC4: =EOMONTH(AB4,3) | AD4: =EOMONTH(AC4,3) | AE4: =AD4 | AF4: =EOMONTH(AE4,3) | AG4: =EOMONTH(AF4,3) | AH4: =EOMONTH(AG4,3) | AI4: =EOMONTH(AH4,3) | AJ4: =AI4 | AK4: =EOMONTH(AJ4,3) | AL4: =EOMONTH(AK4,3) | AM4: =EOMONTH(AL4,3) | AN4: =EOMONTH(AM4,3) | AO4: =AN4 | AP4: =EOMONTH(AO4,3) | AQ4: =EOMONTH(AP4,3) | AR4: =EOMONTH(AQ4,3) | AS4: =EOMONTH(AR4,3) | AT4: =AS4 | AU4: =EOMONTH(AT4,12) | AV4: =EOMONTH(AU4,12) | AW4: =EOMONTH(AV4,12)
