Workbook
Name AA.AlternatePriceSourceStartPeriod: "Q1-2018"
Name AA.CIK: "1046179"
Name AA.CompareQuarters.LatestMRQ: "Q3-2024"
Name AA.CSIN: "M2B13B0184"
Name AA.CurationVersion: "2023.11.1.0"
Name AA.DBMacroVersion: "1.0.13.0"
Name AA.FreeCashFlow: "TRUE"
Name AA.HardcodeChecker.LatestMRQ: "Q3-2019"
Name AA.ModelChecks.LatestMRQ: "Q3-2021"
Name AA.ModelChecks.LatestVersionNumber: "2.38.27.0"
Name AA.ModelVersion: "FY2025.24"
Name AA.NonLibraryWideCurationVersion: "4"
Name AA.PartialUpdate.BsAvailable: "TRUE"
Name AA.PartialUpdate.CfsAvailable: "TRUE"
Name AA.PartialUpdate.IsAvailable: "TRUE"
Name AA.PeriodLayout: "QFY"
Name AA.PersonalMacro.VersionNumber: "1.5.1.5"
Name AA.RowNameEnforcerVersion: "2023.11.1.0"
Name AA.SessionToUploadId: ""
Name AA.StartWorkModelVersion: "FY2025.22"
Name AA.StartWorkType: ""
Name AA.SubyearType: "Q"
Name AA.TemplateUpgradeAttempted: "TRUE"
Name AA.TemplateVersion: "7.5.4.0"
Name AA.UpdateType: "Partial"
Name FP.DataSource: 'Front Page'!$H$16
Name FP.DataSourceName: 'Front Page'!$H$15
Name FP.Disclaimer: 'Front Page'!$C$22
Name FP.LastPrice: 'Front Page'!$H$20
Name FP.LastPriceDate: 'Front Page'!$F$20
Name FP.RealTimeToggle: 'Front Page'!$H$18
Name FP.UpdateDate: 'Front Page'!$H$11
Name FP.UpdateEvent: 'Front Page'!$H$13
Name FP_Comment: 'Front Page'!$M$13:$P$20
Name FP_StockPriceOverride: 'Front Page'!$C$20:$H$20
Name GD.CompanyName: Guidance!$B$1
Name GD.MRQ: Guidance!$F$2
Name GD_Difference_Mid_Absolute: Guidance!$P:$P
Name GD_Difference_Mid_Relative: Guidance!$Q:$Q
Name GD_Guidance_High: Guidance!$J:$J
Name GD_Guidance_Low: Guidance!$I:$I
Name GD_Guidance_Mid: Guidance!$K:$K
Name GD_Header_Column: Guidance!$5:$5
Name GD_Header_Section: Guidance!$4:$4
Name GD_Index: Guidance!$A:$A
Name GD_Item: Guidance!$D:$D
Name GD_Item_BasePeriod: Guidance!$G:$G
Name GD_Item_FiscalPeriod: Guidance!$F:$F
Name GD_Item_Name: Guidance!$E:$E
Name GD_Model_Output: Guidance!$N:$N
Name GD_Model_Type: Guidance!$M:$M
Name GD_Type: Guidance!$B:$B
Name GD_Update_Date: Guidance!$S:$S
Name GD_Update_Link: Guidance!$T:$T
Name HP.MRFX: Model!$B$1096
Name HP.ReportCurrency: Model!$B$1095
Name HP.Ticker: Model!$A$2
Name HP.TradeCurrency: Model!$B$1093
Name HP.TradeCurrency.HardCoded: Model!$B$1094
Name MO.ApplyTradeCurrencyScaling: Model!$B$1092

Sheet Front Page
M6: Please contact this email for any model-specific questions:
M7: modelsupport@alpha-sense.com | N7: mailto:support@canalyst.com?subject=Canalyst%20Support:%20Taiwan%20Semiconductor%20Manufacturing%20Company%20Ltd.%20TSM%20US&body=Model%20Version:%20Q2-2019.21 | O7: mailto:support@canalyst.com?subject=Canalyst%20Support:%20Taiwan%20Semiconductor%20Manufacturing%20Company%20Ltd.%20TSM%20US&body=Model%20Version:%20Q2-2019.21
C9: Company Model: | H9: =Model!A1
C11: Updated: | H11: =OFFSET('Update Log'!$C$10,1,0,1,1)
M12: Comments on Model:
C13: For: | H13: =OFFSET('Update Log'!$E$10,1,0,1,1) | M13: 1 ADR represents 5 shares. Partially updated with PR, to be fully updated with 20F
C15: Consensus Data and Real-Time Stock Price: | H15: Bloomberg
H16: =IF(FP.DataSourceName="Bloomberg",1,IF(FP.DataSourceName="Capital IQ",2,IF(FP.DataSourceName="FactSet",3,IF(FP.DataSourceName="Refinitiv",4))))
C18: Real-Time Stock Price: | H18: OFF
C20: Stock Price Override: | F20: 46051 | H20: 339.55
C22: DISCLAIMER Access to and use of this model, including the data contained herein (this "Model") is subject to Tegus, Inc.'s (a successor entity to Canalyst Financial Modeling Corporation) ("Company") Terms of Use that you accepted prior to accessing this Model, the applicable Service Agreement between the Company and you (or a corporate entity that has authorized you to access and use this Model on its behalf in accordance with the terms of such Service Agreement) or other similar agreement between you and the Company. BY CONTINUING TO ACCESS OR USE THIS MODEL, YOU EXPRESSLY AGREE TO THE TERMS AND CONDITIONS OF SUCH AGREEMENTS. The Company and certain of its licensors have exclusive proprietary rights in this Model. This Model is being provided for internal use only. Unless prior written consent by the Company and its licensors has been provided to you, you may not distribute or otherwise furnish this Model to any third party, nor use or permit anyone to use this Model for any unlawful or unauthorized purpose. IF YOU HAVE UNLAWFULLY OBTAINED, OR ARE NOT AUTHORIZED TO USE THIS MODEL, YOU ARE OBLIGATED TO PROMPTLY: (I) RETURN THIS MODEL (AND ANY DERIVATIVE WORKS ARISING FROM OR RELATING THERETO) TO THE AUTHORIZED USER OF THIS MODEL; (II) PROVIDE NOTICE TO THE COMPANY AT LEGAL@TEGUS.COM OF SUCH UNLAWFUL OR UNAUTHORIZED ACCESS AND USE; AND, (III) CERTIFY THAT YOU HAVE DESTROYED THIS MODEL (AND ANY DERIVATIVE WORKS ARISING FROM OR RELATING THERETO) AND ANY COPIES FROM YOUR SYSTEMS SO AS TO ENSURE THEY ARE INCAPABLE OF RETRIEVAL. A portion of the data contained in this Model may be powered by third party contributors and their respective licensors, or derived from data provided by such contributors, including (but not limited to): (i) QuoteMedia Inc.: A portion of the market data is powered by Quotemedia.com. All rights reserved. Data delayed 15 minutes unless otherwise indicated; (ii) S&P Global Market Intelligence LLC: Copyright (c) {{YEAR}} S&P Global Market Intelligence LLC (and its affiliates as applicable). All rights reserved. Reproduction of any information, opinions, views, data or material, including ratings ("Content") in any form is prohibited except with the prior written permission of the relevant party. Such party, its affiliates and suppliers ("Content Providers") do not guarantee the accuracy, adequacy, completeness, timeliness or availability of any Content and are not responsible for any errors or omissions (negligent or otherwise), regardless of the cause, or for the results obtained from the use of such Content. In no event shall Content Providers be liable for any damages, costs, expenses, legal fees, or losses (including lost income or lost profit and opportunity costs) in connection with any use of the Content. A reference to a particular investment or security, a rating or any observation concerning an investment that is part of the Content is not a recommendation to buy, sell or hold such investment or security, does not address the suitability of an investment or security and should not be relied on as investment advice. Credit ratings are statements of opinions and are not statements of fact; and, (iii) Refinitiv Canada Holdings Limited: A portion of the information may be provided by or derived from data provided by Refinitiv. By accessing or using this Model (including any portion of the data contained herein) you expressly represent that such access or use does not constitute a violation of any applicable law or regulation to which you or the securities are subject. This Model does not constitute investment advice by the Company or any of its licensors. Reference to a particular investment or security, credit rating or any observation concerning a security or investment in this Model is not a recommendation or solicitation to buy, sell or hold such investment or security or make any other investment decisions. For greater certainty, any forecasts or forward-looking information expressed herein are for illustrative purposes only and do not purport to express any view on what may transpire. Neither the Company nor any of its licensors have performed company-specific research on any projected information, as such, it is your responsibility to express your own views on projected results. This Model does not guarantee future performance and undue reliance should not be placed on such. You are solely responsible for evaluating the merits and risks of any investment based on your own business and financial expertise, the business and financial expertise of professional advisors with whom you have consulted, your financial situation and risk tolerance. Neither the Company, nor any of its licensors, undertake any liability with respect to your reliance on this Model. This Model is a quantitative tool with no investment views. The Company and its respective directors, officers, employees, agents, contractors, and affiliates may hold long or short positions in the security to which this Model relates, based on their personal views, and may initiate or close out any positions in such security at any time without any notice. THIS MODEL IS PROVIDED "AS IS" AND ON AN "AS AVAILABLE" BASIS ONLY, WITHOUT WARRANTIES OR CONDITIONS OF ANY KIND. NEITHER THE COMPANY NOR ANY OF ITS LICENSORS NOR THEIR RESPECTIVE AFFILIATES OR SUPPLIERS HAVE LIABILITY FOR THE ACCURACY, TIMELINESS OR COMPLETENESS OF THIS MODEL, OR FOR DELAYS, INTERRUPTIONS OR OMISSIONS HEREIN, NOR FOR ANY LOST PROFITS, INDIRECT, SPECIAL OR CONSEQUENTIAL DAMAGES. Access to data in this Model that is sourced from third party contributors is subject to termination in the event that any agreement between the Company and such third party contributors terminates for any reason. Copyright 2023 Tegus. All rights reserved.

Sheet DCF
A1: TSMC DCF Valuation Analysis
A4: Period | F4: FY2025 | G4: FY2026 | H4: FY2027 | I4: FY2028 | J4: FY2029
A6: REVENUE BUILD
A7: Smartphone Revenue | F7: =Model!L7 | G7: =Model!Q7 | H7: =Model!V7 | I7: =Model!AA7 | J7: =Model!AF7
A8: HPC Revenue | F8: =Model!L10 | G8: =Model!Q10 | H8: =Model!V10 | I8: =Model!AA10 | J8: =Model!AF10
A9: IoT Revenue | F9: =Model!L13 | G9: =Model!Q13 | H9: =Model!V13 | I9: =Model!AA13 | J9: =Model!AF13
A10: Automotive Revenue | F10: =Model!L16 | G10: =Model!Q16 | H10: =Model!V16 | I10: =Model!AA16 | J10: =Model!AF16
A11: Digital Consumer Revenue | F11: =Model!L19 | G11: =Model!Q19 | H11: =Model!V19 | I11: =Model!AA19 | J11: =Model!AF19
A12: Other Revenue | F12: =Model!L22 | G12: =Model!Q22 | H12: =Model!V22 | I12: =Model!AA22 | J12: =Model!AF22
A13: Total Revenue | F13: =SUM(F7:F12) | G13: =SUM(G7:G12) | H13: =SUM(H7:H12) | I13: =SUM(I7:I12) | J13: =SUM(J7:J12)
A14: Y/Y Growth % | G14: =G13/F13 - 1 | H14: =H13/G13 - 1 | I14: =I13/H13 - 1 | J14: =J13/I13 - 1
A16: OPERATING MARGINS
A17: Gross Margin % | F17: =Model!L38 | G17: =Model!Q38 | H17: =Model!V38 | I17: =Model!AA38 | J17: =Model!AF38
A18: Operating Margin % | F18: =Model!L59 / Model!L25 | G18: =Model!Q59 / Model!Q25 | H18: =Model!V59 / Model!V25 | I18: =Model!AA59 / Model!AA25 | J18: =Model!AF59 / Model!AF25
A27: UFCF BUILD
A28: Revenue | F28: =F13 | G28: =G13 | H28: =H13 | I28: =I13 | J28: =J13
A29: Gross Margin % | F29: =F17 | G29: =G17 | H29: =H17 | I29: =I17 | J29: =J17
A30: Gross Profit | F30: =F28 * F29 | G30: =G28 * G29 | H30: =H28 * H29 | I30: =I28 * I29 | J30: =J28 * J29
A31: Operating Margin % | F31: =F18 | G31: =G18 | H31: =H18 | I31: =I18 | J31: =J18
A32: EBIT | F32: =F28 * F31 | G32: =G28 * G31 | H32: =H28 * H31 | I32: =I28 * I31 | J32: =J28 * J31
A33: Tax Rate % | F33: 0.15 | G33: 0.15 | H33: 0.15 | I33: 0.15 | J33: 0.15
A34: NOPAT (EBIT × (1-tax)) | F34: =F32 * (1 - F33) | G34: =G32 * (1 - G33) | H34: =H32 * (1 - H33) | I34: =I32 * (1 - I33) | J34: =J32 * (1 - J33)
A35: D&A | F35: =Model!L72 + Model!L76 | G35: =Model!Q72 + Model!Q76 | H35: =Model!V72 + Model!V76 | I35: =Model!AA72 + Model!AA76 | J35: =Model!AF72 + Model!AF76
A36: CapEx | F36: =Model!L86 * 1000 | G36: =Model!Q86 * 1000 | H36: =Model!V86 * 1000 | I36: =Model!AA86 * 1000 | J36: =Model!AF86 * 1000
A37: Change in Working Capital | F37: =F28 * 0.10 | G37: =G28 * 0.10 | H37: =H28 * 0.10 | I37: =I28 * 0.10 | J37: =J28 * 0.10
A38: Unlevered FCF | F38: =F34 + F35 - F36 - F37 | G38: =G34 + G35 - G36 - G37 | H38: =H34 + H35 - H36 - H37 | I38: =I34 + I35 - I36 - I37 | J38: =J34 + J35 - J36 - J37
A40: DISCOUNTING
A41: WACC % | F41: 0.09 | G41: 0.09 | H41: 0.09 | I41: 0.09 | J41: 0.09
A42: Discount Factor | F42: =1 / (1 + F41)^1 | G42: =1 / (1 + G41)^2 | H42: =1 / (1 + H41)^3 | I42: =1 / (1 + I41)^4 | J42: =1 / (1 + J41)^5
A43: PV of UFCF | F43: =F38 * F42 | G43: =G38 * G42 | H43: =H38 * H42 | I43: =I38 * I42 | J43: =J38 * J42
A45: TERMINAL VALUE
A46: Terminal Growth % | F46: 0.025
A47: Terminal Value | F47: =F38 * (1 + F46) / (F41 - F46)
A48: PV of TV | F48: =F47 * F42
A50: VALUATION
A51: Sum PV UFCF | F51: =SUM(F43:J43)
A52: PV Terminal Value | F52: =F48
A53: Enterprise Value | F53: =F51 + F52
A54: Less: Net Debt | F54: =Model!L84 - Model!L80
A55: Equity Value | F55: =F53 - F54
A56: Shares Outstanding (mm) | F56: =Model!L500
A57: Implied Price | F57: =F55 / F56
A58: Current Price | F58: ='Front Page'!H20
A59: Upside % | F59: =F57 / F58 - 1

Sheet Model
A1: Taiwan Semiconductor Manufacturing Company Ltd.
A2: =CHOOSE(MO.DataSourceIndex,MO.Ticker.Bloomberg,MO.Ticker.CapIQ,MO.Ticker.FactSet,MO.Ticker.Thomson) | C2: =EOMONTH(C4,-12) | BN2: Partial | BO2: Partial
A3: =HP.TradeCurrency | B3: =IF(MO.RealTime="OFF",MO.LastPriceHardcoded,MO.LastPriceFormula) | C3: =C4-C2 | D3: =D4-C4 | E3: =E4-D4 | F3: =F4-E4 | G3: =G4-F4 | H3: =H4-G4 | I3: =I4-H4 | J3: =J4-I4 | K3: =K4-J4 | L3: =L4-G4 | M3: =M4-L4 | N3: =N4-M4 | O3: =O4-N4 | P3: =P4-O4 | Q3: =Q4-L4 | R3: =R4-Q4 | S3: =S4-R4 | T3: =T4-S4 | U3: =U4-T4 | V3: =V4-Q4 | W3: =W4-V4 | X3: =X4-W4 | Y3: =Y4-X4 | Z3: =Z4-Y4 | AA3: =AA4-V4 | AB3: =AB4-AA4 | AC3: =AC4-AB4 | AD3: =AD4-AC4 | AE3: =AE4-AD4 | AF3: =AF4-AA4 | AG3: =AG4-AF4 | AH3: =AH4-AG4 | AI3: =AI4-AH4 | AJ3: =AJ4-AI4 | AK3: =AK4-AF4 | AL3: =AL4-AK4 | AM3: =AM4-AL4 | AN3: =AN4-AM4 | AO3: =AO4-AN4 | AP3: =AP4-AK4 | AQ3: =AQ4-AP4 | AR3: =AR4-AQ4 | AS3: =AS4-AR4 | AT3: =AT4-AS4 | AU3: =AU4-AP4 | AV3: =AV4-AU4 | AW3: =AW4-AV4 | AX3: =AX4-AW4 | AY3: =AY4-AX4 | AZ3: =AZ4-AU4 | BA3: =BA4-AZ4 | BB3: =BB4-BA4 | BC3: =BC4-BB4 | BD3: =BD4-BC4 | BE3: =BE4-AZ4 | BF3: =BF4-BE4 | BG3: =BG4-BF4 | BH3: =BH4-BG4 | BI3: =BI4-BH4 | BJ3: =BJ4-BE4 | BK3: =BK4-BJ4 | BL3: =BL4-BK4 | BM3: =BM4-BL4 | BN3: =BN4-BM4 | BO3: =BO4-BJ4 | BP3: =BP4-BO4 | BQ3: =BQ4-BP4 | BR3: =BR4-BQ4 | BS3: =BS4-BR4 | BT3: =BT4-BO4 | BU3: =BU4-BT4 | BV3: =BV4-BU4 | BW3: =BW4-BV4 | BX3: =BX4-BW4 | BY3: =BY4-BT4 | BZ3: =BZ4-BY4 | CA3: =CA4-BZ4 | CB3: =CB4-CA4
A4: =FP.DataSourceName | B4: =IF(AND(MO.RealTimeStockPriceToggle,MO.LastPriceFormula<>"N/A"),"ON","OFF") | C4: 40178 | D4: =EOMONTH(C4,12) | E4: =EOMONTH(D4,12) | F4: =EOMONTH(E4,12) | G4: =EOMONTH(F4,12) | H4: =EOMONTH(G4,3) | I4: =EOMONTH(H4,3) | J4: =EOMONTH(I4,3) | K4: =EOMONTH(J4,3) | L4: =K4 | M4: =EOMONTH(L4,3) | N4: =EOMONTH(M4,3) | O4: =EOMONTH(N4,3) | P4: =EOMONTH(O4,3) | Q4: =P4 | R4: =EOMONTH(Q4,3) | S4: =EOMONTH(R4,3) | T4: =EOMONTH(S4,3) | U4: =EOMONTH(T4,3) | V4: =U4 | W4: =EOMONTH(V4,3) | X4: =EOMONTH(W4,3) | Y4: =EOMONTH(X4,3) | Z4: =EOMONTH(Y4,3) | AA4: =Z4 | AB4: =EOMONTH(AA4,3) | AC4: =EOMONTH(AB4,3) | AD4: =EOMONTH(AC4,3) | AE4: =EOMONTH(AD4,3) | AF4: =AE4 | AG4: =EOMONTH(AF4,3) | AH4: =EOMONTH(AG4,3) | AI4: =EOMONTH(AH4,3) | AJ4: =EOMONTH(AI4,3) | AK4: =AJ4 | AL4: =EOMONTH(AK4,3) | AM4: =EOMONTH(AL4,3) | AN4: =EOMONTH(AM4,3) | AO4: =EOMONTH(AN4,3) | AP4: =AO4 | AQ4: =EOMONTH(AP4,3) | AR4: =EOMONTH(AQ4,3) | AS4: =EOMONTH(AR4,3) | AT4: =EOMONTH(AS4,3) | AU4: =AT4 | AV4: =EOMONTH(AU4,3) | AW4: =EOMONTH(AV4,3) | AX4: =EOMONTH(AW4,3) | AY4: =EOMONTH(AX4,3) | AZ4: =AY4 | BA4: =EOMONTH(AZ4,3) | BB4: =EOMONTH(BA4,3) | BC4: =EOMONTH(BB4,3) | BD4: =EOMONTH(BC4,3) | BE4: =BD4 | BF4: =EOMONTH(BE4,3) | BG4: =EOMONTH(BF4,3) | BH4: =EOMONTH(BG4,3) | BI4: =EOMONTH(BH4,3) | BJ4: =BI4 | BK4: =EOMONTH(BJ4,3) | BL4: =EOMONTH(BK4,3) | BM4: =EOMONTH(BL4,3) | BN4: =EOMONTH(BM4,3) | BO4: =BN4 | BP4: =EOMONTH(BO4,3) | BQ4: =EOMONTH(BP4,3) | BR4: =EOMONTH(BQ4,3) | BS4: =EOMONTH(BR4,3) | BT4: =BS4 | BU4: =EOMONTH(BT4,3) | BV4: =EOMONTH(BU4,3) | BW4: =EOMONTH(BV4,3) | BX4: =EOMONTH(BW4,3) | BY4: =BX4 | BZ4: =EOMONTH(BY4,12) | CA4: =EOMONTH(BZ4,12) | CB4: =EOMONTH(CA4,12)
A5: =MO.ReportCurrency | C5: FY2009 | D5: =CONCATENATE("FY",RIGHT(C5,4)+1) | E5: =CONCATENATE("FY",RIGHT(D5,4)+1) | F5: =CONCATENATE("FY",RIGHT(E5,4)+1) | G5: =CONCATENATE("FY",RIGHT(F5,4)+1) | H5: =CONCATENATE("Q1","-",RIGHT(G5,4)+1) | I5: =CONCATENATE("Q2","-",RIGHT(H5,4)) | J5: =CONCATENATE("Q3","-",RIGHT(I5,4)) | K5: =CONCATENATE("Q4","-",RIGHT(J5,4)) | L5: =CONCATENATE("FY",RIGHT(G5,4)+1) | M5: =CONCATENATE("Q1","-",RIGHT(L5,4)+1) | N5: =CONCATENATE("Q2","-",RIGHT(M5,4)) | O5: =CONCATENATE("Q3","-",RIGHT(N5,4)) | P5: =CONCATENATE("Q4","-",RIGHT(O5,4)) | Q5: =CONCATENATE("FY",RIGHT(L5,4)+1) | R5: =CONCATENATE("Q1","-",RIGHT(Q5,4)+1) | S5: =CONCATENATE("Q2","-",RIGHT(R5,4)) | T5: =CONCATENATE("Q3","-",RIGHT(S5,4)) | U5: =CONCATENATE("Q4","-",RIGHT(T5,4)) | V5: =CONCATENATE("FY",RIGHT(Q5,4)+1) | W5: =CONCATENATE("Q1","-",RIGHT(V5,4)+1) | X5: =CONCATENATE("Q2","-",RIGHT(W5,4)) | Y5: =CONCATENATE("Q3","-",RIGHT(X5,4)) | Z5: =CONCATENATE("Q4","-",RIGHT(Y5,4)) | AA5: =CONCATENATE("FY",RIGHT(V5,4)+1) | AB5: =CONCATENATE("Q1","-",RIGHT(AA5,4)+1) | AC5: =CONCATENATE("Q2","-",RIGHT(AB5,4)) | AD5: =CONCATENATE("Q3","-",RIGHT(AC5,4)) | AE5: =CONCATENATE("Q4","-",RIGHT(AD5,4)) | AF5: =CONCATENATE("FY",RIGHT(AA5,4)+1) | AG5: =CONCATENATE("Q1","-",RIGHT(AF5,4)+1) | AH5: =CONCATENATE("Q2","-",RIGHT(AG5,4)) | AI5: =CONCATENATE("Q3","-",RIGHT(AH5,4)) | AJ5: =CONCATENATE("Q4","-",RIGHT(AI5,4)) | AK5: =CONCATENATE("FY",RIGHT(AF5,4)+1) | AL5: =CONCATENATE("Q1","-",RIGHT(AK5,4)+1) | AM5: =CONCATENATE("Q2","-",RIGHT(AL5,4)) | AN5: =CONCATENATE("Q3","-",RIGHT(AM5,4)) | AO5: =CONCATENATE("Q4","-",RIGHT(AN5,4)) | AP5: =CONCATENATE("FY",RIGHT(AK5,4)+1) | AQ5: =CONCATENATE("Q1","-",RIGHT(AP5,4)+1) | AR5: =CONCATENATE("Q2","-",RIGHT(AQ5,4)) | AS5: =CONCATENATE("Q3","-",RIGHT(AR5,4)) | AT5: =CONCATENATE("Q4","-",RIGHT(AS5,4)) | AU5: =CONCATENATE("FY",RIGHT(AP5,4)+1) | AV5: =CONCATENATE("Q1","-",RIGHT(AU5,4)+1) | AW5: =CONCATENATE("Q2","-",RIGHT(AV5,4)) | AX5: =CONCATENATE("Q3","-",RIGHT(AW5,4)) | AY5: =CONCATENATE("Q4","-",RIGHT(AX5,4)) | AZ5: =CONCATENATE("FY",RIGHT(AU5,4)+1) | BA5: =CONCATENATE("Q1","-",RIGHT(AZ5,4)+1) | BB5: =CONCATENATE("Q2","-",RIGHT(BA5,4)) | BC5: =CONCATENATE("Q3","-",RIGHT(BB5,4)) | BD5: =CONCATENATE("Q4","-",RIGHT(BC5,4)) | BE5: =CONCATENATE("FY",RIGHT(AZ5,4)+1) | BF5: =CONCATENATE("Q1","-",RIGHT(BE5,4)+1) | BG5: =CONCATENATE("Q2","-",RIGHT(BF5,4)) | BH5: =CONCATENATE("Q3","-",RIGHT(BG5,4)) | BI5: =CONCATENATE("Q4","-",RIGHT(BH5,4)) | BJ5: =CONCATENATE("FY",RIGHT(BE5,4)+1) | BK5: =CONCATENATE("Q1","-",RIGHT(BJ5,4)+1) | BL5: =CONCATENATE("Q2","-",RIGHT(BK5,4)) | BM5: =CONCATENATE("Q3","-",RIGHT(BL5,4)) | BN5: =CONCATENATE("Q4","-",RIGHT(BM5,4)) | BO5: =CONCATENATE("FY",RIGHT(BJ5,4)+1) | BP5: =CONCATENATE("Q1","-",RIGHT(BO5,4)+1) | BQ5: =CONCATENATE("Q2","-",RIGHT(BP5,4)) | BR5: =CONCATENATE("Q3","-",RIGHT(BQ5,4)) | BS5: =CONCATENATE("Q4","-",RIGHT(BR5,4)) | BT5: =CONCATENATE("FY",RIGHT(BO5,4)+1) | BU5: =CONCATENATE("Q1","-",RIGHT(BT5,4)+1) | BV5: =CONCATENATE("Q2","-",RIGHT(BU5,4)) | BW5: =CONCATENATE("Q3","-",RIGHT(BV5,4)) | BX5: =CONCATENATE("Q4","-",RIGHT(BW5,4)) | BY5: =CONCATENATE("FY",RIGHT(BT5,4)+1) | BZ5: =CONCATENATE("FY",RIGHT(BY5,4)+1) | CA5: =CONCATENATE("FY",RIGHT(BZ5,4)+1) | CB5: =CONCATENATE("FY",RIGHT(CA5,4)+1)
A6: Revenue Build
A7: Smartphone revenue , mm | AB7: 113267.91 | AC7: 82753.245 | AD7: 117666.46 | AE7: =AF7-SUM(AB7,AC7,AD7) | AF7: 466452.28 | AG7: 103210.27 | AH7: 108860.87 | AI7: 144301.2 | AJ7: =AK7-SUM(AG7,AH7,AI7) | AK7: 523612.86 | AL7: 151931.28 | AM7: 145843.88 | AN7: 163491.24 | AO7: =AP7-SUM(AL7,AM7,AN7) | AP7: 645303.61 | AQ7: 163207.8 | AR7: 157744.89 | AS7: 180649.83 | AT7: =AU7-SUM(AQ7,AR7,AS7) | AU7: 695091.19 | AV7: 195999.89 | AW7: 201555.76 | AX7: 251069.57 | AY7: =AZ7-SUM(AV7,AW7,AX7) | AZ7: 888879.25 | BA7: 174372.27 | BB7: 159366.87 | BC7: 212001.18 | BD7: =BE7-SUM(BA7,BB7,BC7) | BE7: 814914.29 | BF7: 225032.14 | BG7: 222543.37 | BH7: 257495.61 | BI7: =BJ7-SUM(BF7,BG7,BH7) | BJ7: 1005130.5 | BK7: 233611.39 | BL7: 249959.55 | BM7: 296745.65 | BN7: =BN25*0.32 | BO7: =SUM(BK7,BL7,BM7,BN7) | BP7: =BK7*(1+BP9) | BQ7: =BL7*(1+BQ9) | BR7: =BM7*(1+BR9) | BS7: =BN7*(1+BS9) | BT7: =SUM(BP7,BQ7,BR7,BS7) | BU7: =BP7*(1+BU9) | BV7: =BQ7*(1+BV9) | BW7: =BR7*(1+BW9) | BX7: =BS7*(1+BX9) | BY7: =SUM(BU7,BV7,BW7,BX7) | BZ7: =BY7*(1+BZ9) | CA7: =BZ7*(1+CA9) | CB7: =CA7*(1+CB9)
A8: Q/Q Smartphone revenue growth, % | AC8: =AC7/AB7-1 | AD8: =AD7/AC7-1 | AE8: =AE7/AD7-1 | AG8: =AG7/AE7-1 | AH8: =AH7/AG7-1 | AI8: =AI7/AH7-1 | AJ8: =AJ7/AI7-1 | AL8: =AL7/AJ7-1 | AM8: =AM7/AL7-1 | AN8: =AN7/AM7-1 | AO8: =AO7/AN7-1 | AQ8: =AQ7/AO7-1 | AR8: =AR7/AQ7-1 | AS8: =AS7/AR7-1 | AT8: =AT7/AS7-1 | AV8: =AV7/AT7-1 | AW8: =AW7/AV7-1 | AX8: =AX7/AW7-1 | AY8: =AY7/AX7-1 | BA8: =BA7/AY7-1 | BB8: =BB7/BA7-1 | BC8: =BC7/BB7-1 | BD8: =BD7/BC7-1 | BF8: =BF7/BD7-1 | BG8: =BG7/BF7-1 | BH8: =BH7/BG7-1 | BI8: =BI7/BH7-1 | BK8: =BK7/BI7-1 | BL8: =BL7/BK7-1 | BM8: =BM7/BL7-1 | BN8: =BN7/BM7-1 | BP8: =BP7/BN7-1 | BQ8: =BQ7/BP7-1 | BR8: =BR7/BQ7-1 | BS8: =BS7/BR7-1 | BU8: =BU7/BS7-1 | BV8: =BV7/BU7-1 | BW8: =BW7/BV7-1 | BX8: =BX7/BW7-1
A9: Y/Y Smartphone revenue growth, % | AG9: =AG7/AB7-1 | AH9: =AH7/AC7-1 | AI9: =AI7/AD7-1 | AJ9: =AJ7/AE7-1 | AK9: =AK7/AF7-1 | AL9: =AL7/AG7-1 | AM9: =AM7/AH7-1 | AN9: =AN7/AI7-1 | ... BO9: =BO7/BJ7-1 | BP9: 0.15 | BQ9: 0.05 | BR9: 0.191 | BS9: 0.2 | BT9: =BT7/BO7-1 | BU9: 0.1 | BV9: 0.05 | BW9: 0.191 | BX9: 0.2 | BY9: =BY7/BT7-1 | BZ9: 0.2 | CA9: 0.1 | CB9: 0.1
A10: High performance computing revenue , mm | AB10: 78988.359 | AC10: 93089.339 | AD10: 84945.146 | AE10: =AF10-SUM(AB10,AC10,AD10) | AF10: 341910.2 | AG10: 62824.973 | AH10: 77376.963 | AI10: 85300.705 | AJ10: =AK10-SUM(AG10,AH10,AI10) | AK10: 315822.31 | AL10: 92993.61 | AM10: 104115.54 | AN10: 130404.09 | AO10: =AP10-SUM(AL10,AM10,AN10) | AP10: 439809.98 | AQ10: 127843.39 | AR10: 143391.01 | AS10: 155629.73 | AT10: =AU10-SUM(AQ10,AR10,AS10) | AU10: 587780.14 | AV10: 202245.16 | AW10: 228940.67 | AX10: 238237.29 | AY10: =AZ10-SUM(AV10,AW10,AX10) | AZ10: 932383.73 | BA10: 225532.03 | BB10: 214359.34 | BC10: 227816.59 | BD10: =BE10-SUM(BA10,BB10,BC10) | BE10: 934768.62 | BF10: 274772.97 | BG10: 351392.53 | BH10: 389309.41 | BI10: =BJ10-SUM(BF10,BG10,BH10) | BJ10: 1476890.6 | BK10: 493223.15 | BL10: 561155.35 | BM10: 558592.35 | BN10: =BN25*0.55 | BO10: =SUM(BK10,BL10,BM10,BN10) | BP10: =BK10*(1+BP12) | BQ10: =BL10*(1+BQ12) | BR10: =BM10*(1+BR12) | BS10: =BN10*(1+BS12) | BT10: =SUM(BP10,BQ10,BR10,BS10) | BU10: =BP10*(1+BU12) | BV10: =BQ10*(1+BV12) | BW10: =BR10*(1+BW12) | BX10: =BS10*(1+BX12) | BY10: =SUM(BU10,BV10,BW10,BX10) | BZ10: =BY10*(1+BZ12) | CA10: =BZ10*(1+CA12) | CB10: =CA10*(1+CB12)
A11: Q/Q High performance computing revenue growth, % | AC11: =AC10/AB10-1 | AD11: =AD10/AC10-1 | AE11: =AE10/AD10-1 | AG11: =AG10/AE10-1 | AH11: =AH10/AG10-1 | AI11: =AI10/AH10-1 | AJ11: =AJ10/AI10-1 | AL11: =AL10/AJ10-1 | AM11: =AM10/AL10-1 | AN11: =AN10/AM10-1 | AO11: =AO10/AN10-1 | AQ11: =AQ10/AO10-1 | AR11: =AR10/AQ10-1 | AS11: =AS10/AR10-1 | AT11: =AT10/AS10-1 | AV11: =AV10/AT10-1 | AW11: =AW10/AV10-1 | AX11: =AX10/AW10-1 | AY11: =AY10/AX10-1 | BA11: =BA10/AY10-1 | BB11: =BB10/BA10-1 | BC11: =BC10/BB10-1 | BD11: =BD10/BC10-1 | BF11: =BF10/BD10-1 | BG11: =BG10/BF10-1 | BH11: =BH10/BG10-1 | BI11: =BI10/BH10-1 | BK11: =BK10/BI10-1 | BL11: =BL10/BK10-1 | BM11: =BM10/BL10-1 | BN11: =BN10/BM10-1 | BP11: =BP10/BN10-1 | BQ11: =BQ10/BP10-1 | BR11: =BR10/BQ10-1 | BS11: =BS10/BR10-1 | BU11: =BU10/BS10-1 | BV11: =BV10/BU10-1 | BW11: =BW10/BV10-1 | BX11: =BX10/BW10-1
A12: Y/Y High performance computing revenue growth, % | AG12: =AG10/AB10-1 | AH12: =AH10/AC10-1 | AI12: =AI10/AD10-1 | AJ12: =AJ10/AE10-1 | AK12: =AK10/AF10-1 | AL12: =AL10/AG10-1 | AM12: =AM10/AH10-1 | AN12: =AN10/AI10-1 | ... BO12: =BO10/BJ10-1 | BP12: 0.4 | BQ12: 0.05 | BR12: 0.23 | BS12: 0.26 | BT12: =BT10/BO10-1 | BU12: 0.1 | BV12: 0.05 | BW12: 0.23 | BX12: 0.26 | BY12: =BY10/BT10-1 | BZ12: 0.05 | CA12: 0.12 | CB12: 0.12
A13: Internet of things revenue , mm | AB13: 15379.027 | AC13: 15747.791 | AD13: 17015.261 | AE13: =AF13-SUM(AB13,AC13,AD13) | AF13: 65091.314 | AG13: 16717.625 | AH13: 19150.847 | AI13: 25790.65 | AJ13: =AK13-SUM(AG13,AH13,AI13) | AK13: 86342.707 | AL13: 26595.813 | AM13: 25265.823 | AN13: 31201.283 | AO13: =AP13-SUM(AL13,AM13,AN13) | AP13: 110355.19 | AQ13: 30122.731 | AR13: 29391.787 | AS13: 36282.241 | AT13: =AU13-SUM(AQ13,AR13,AS13) | AU13: 133005.98 | AV13: 39045.775 | AW13: 44648.551 | AX13: 59410.567 | AY13: =AZ13-SUM(AV13,AW13,AX13) | AZ13: 196114.99 | BA13: 42720.43 | BB13: 38168.913 | BC13: 47409.811 | BD13: =BE13-SUM(BA13,BB13,BC13) | BE13: 161916.54 | BF13: 35320.95 | BG13: 37346.267 | BH13: 50255.327 | BI13: =BJ13-SUM(BF13,BG13,BH13) | BJ13: 165516.21 | BK13: 38723.19 | BL13: 44298.398 | BM13: 53250.285 | BN13: =BN25*0.05 | BO13: =SUM(BK13,BL13,BM13,BN13) | BP13: =BK13*(1+BP15) | BQ13: =BL13*(1+BQ15) | BR13: =BM13*(1+BR15) | BS13: =BN13*(1+BS15) | BT13: =SUM(BP13,BQ13,BR13,BS13) | BU13: =BP13*(1+BU15) | BV13: =BQ13*(1+BV15) | BW13: =BR13*(1+BW15) | BX13: =BS13*(1+BX15) | BY13: =SUM(BU13,BV13,BW13,BX13) | BZ13: =BY13*(1+BZ15) | CA13: =BZ13*(1+CA15) | CB13: =CA13*(1+CB15)
A14: Q/Q Internet of things revenue growth, % | AC14: =AC13/AB13-1 | AD14: =AD13/AC13-1 | AE14: =AE13/AD13-1 | AG14: =AG13/AE13-1 | AH14: =AH13/AG13-1 | AI14: =AI13/AH13-1 | AJ14: =AJ13/AI13-1 | AL14: =AL13/AJ13-1 | AM14: =AM13/AL13-1 | AN14: =AN13/AM13-1 | AO14: =AO13/AN13-1 | AQ14: =AQ13/AO13-1 | AR14: =AR13/AQ13-1 | AS14: =AS13/AR13-1 | AT14: =AT13/AS13-1 | AV14: =AV13/AT13-1 | AW14: =AW13/AV13-1 | AX14: =AX13/AW13-1 | AY14: =AY13/AX13-1 | BA14: =BA13/AY13-1 | BB14: =BB13/BA13-1 | BC14: =BC13/BB13-1 | BD14: =BD13/BC13-1 | BF14: =BF13/BD13-1 | BG14: =BG13/BF13-1 | BH14: =BH13/BG13-1 | BI14: =BI13/BH13-1 | BK14: =BK13/BI13-1 | BL14: =BL13/BK13-1 | BM14: =BM13/BL13-1 | BN14: =BN13/BM13-1 | BP14: =BP13/BN13-1 | BQ14: =BQ13/BP13-1 | BR14: =BR13/BQ13-1 | BS14: =BS13/BR13-1 | BU14: =BU13/BS13-1 | BV14: =BV13/BU13-1 | BW14: =BW13/BV13-1 | BX14: =BX13/BW13-1
A15: Y/Y Internet of things revenue growth, % | AG15: =AG13/AB13-1 | AH15: =AH13/AC13-1 | AI15: =AI13/AD13-1 | AJ15: =AJ13/AE13-1 | AK15: =AK13/AF13-1 | AL15: =AL13/AG13-1 | AM15: =AM13/AH13-1 | AN15: =AN13/AI13-1 | ... BO15: =BO13/BJ13-1 | BP15: 0.25 | BQ15: 0.3 | BR15: 0.3 | BS15: 0.35 | BT15: =BT13/BO13-1 | BU15: 0.15 | BV15: 0.3 | BW15: 0.3 | BX15: 0.35 | BY15: =BY13/BT13-1 | BZ15: 0.05 | CA15: 0.1 | CB15: 0.1
A16: Automotive revenue , mm | AB16: 12907.788 | AC16: 13285.974 | AD16: 13288.092 | AE16: =AF16-SUM(AB16,AC16,AD16) | AF16: 51709.787 | AG16: 10626.515 | AH16: 10960.006 | AI16: 13143.575 | AJ16: =AK16-SUM(AG16,AH16,AI16) | AK16: 47914.518 | AL16: 13061.727 | AM16: 11392.379 | AN16: 8791.105 | AO16: =AP16-SUM(AL16,AM16,AN16) | AP16: 44367.562 | AQ16: 14605.54 | AR16: 16395.914 | AS16: 17186.114 | AT16: =AU16-SUM(AQ16,AR16,AS16) | AU16: 67076.353 | AV16: 23731.218 | AW16: 27041.397 | AX16: 31203.686 | AY16: =AZ16-SUM(AV16,AW16,AX16) | AZ16: 116380.99 | BA16: 36022.65 | BB16: 37275.507 | BC16: 28338.188 | BD16: =BE16-SUM(BA16,BB16,BC16) | BE16: 133654.28 | BF16: 32136.633 | BG16: 33747.863 | BH16: 35671.522 | BI16: =BJ16-SUM(BF16,BG16,BH16) | BJ16: 139323.1 | BK16: 43028.245 | BL16: 43029.218 | BM16: 50586.157 | BN16: =BN25*0.05 | BO16: =SUM(BK16,BL16,BM16,BN16) | BP16: =BK16*(1+BP18) | BQ16: =BL16*(1+BQ18) | BR16: =BM16*(1+BR18) | BS16: =BN16*(1+BS18) | BT16: =SUM(BP16,BQ16,BR16,BS16) | BU16: =BP16*(1+BU18) | BV16: =BQ16*(1+BV18) | BW16: =BR16*(1+BW18) | BX16: =BS16*(1+BX18) | BY16: =SUM(BU16,BV16,BW16,BX16) | BZ16: =BY16*(1+BZ18) | CA16: =BZ16*(1+CA18) | CB16: =CA16*(1+CB18)
A17: Q/Q Automotive revenue growth, % | AC17: =AC16/AB16-1 | AD17: =AD16/AC16-1 | AE17: =AE16/AD16-1 | AG17: =AG16/AE16-1 | AH17: =AH16/AG16-1 | AI17: =AI16/AH16-1 | AJ17: =AJ16/AI16-1 | AL17: =AL16/AJ16-1 | AM17: =AM16/AL16-1 | AN17: =AN16/AM16-1 | AO17: =AO16/AN16-1 | AQ17: =AQ16/AO16-1 | AR17: =AR16/AQ16-1 | AS17: =AS16/AR16-1 | AT17: =AT16/AS16-1 | AV17: =AV16/AT16-1 | AW17: =AW16/AV16-1 | AX17: =AX16/AW16-1 | AY17: =AY16/AX16-1 | BA17: =BA16/AY16-1 | BB17: =BB16/BA16-1 | BC17: =BC16/BB16-1 | BD17: =BD16/BC16-1 | BF17: =BF16/BD16-1 | BG17: =BG16/BF16-1 | BH17: =BH16/BG16-1 | BI17: =BI16/BH16-1 | BK17: =BK16/BI16-1 | BL17: =BL16/BK16-1 | BM17: =BM16/BL16-1 | BN17: =BN16/BM16-1 | BP17: =BP16/BN16-1 | BQ17: =BQ16/BP16-1 | BR17: =BR16/BQ16-1 | BS17: =BS16/BR16-1 | BU17: =BU16/BS16-1 | BV17: =BV16/BU16-1 | BW17: =BW16/BV16-1 | BX17: =BX16/BW16-1
A18: Y/Y Automotive revenue growth, % | AG18: =AG16/AB16-1 | AH18: =AH16/AC16-1 | AI18: =AI16/AD16-1 | AJ18: =AJ16/AE16-1 | AK18: =AK16/AF16-1 | AL18: =AL16/AG16-1 | AM18: =AM16/AH16-1 | AN18: =AN16/AI16-1 | ... BO18: =BO16/BJ16-1 | BP18: 0.4 | BQ18: 0.3 | BR18: 0.3 | BS18: 0.3 | BT18: =BT16/BO16-1 | BU18: 0.15 | BV18: 0.3 | BW18: 0.3 | BX18: 0.3 | BY18: =BY16/BT16-1 | BZ18: 0.05 | CA18: 0.1 | CB18: 0.1
A19: Digital consumer electronics revenue , mm | AB19: 15723.792 | AC19: 15511.894 | AD19: 14829.678 | AE19: =AF19-SUM(AB19,AC19,AD19) | AF19: 58470.179 | AG19: 14627.749 | AH19: 14183.705 | AI19: 14078.762 | AJ19: =AK19-SUM(AG19,AH19,AI19) | AK19: 53733.395 | AL19: 15577.838 | AM19: 14213.141 | AN19: 10820.057 | AO19: =AP19-SUM(AL19,AM19,AN19) | AP19: 54555.665 | AQ19: 15414.085 | AR19: 13540.616 | AS19: 13204.541 | AT19: =AU19-SUM(AQ19,AR19,AS19) | AU19: 55577.223 | AV19: 14478.836 | AW19: 15245.696 | AX19: 14900.562 | AY19: =AZ19-SUM(AV19,AW19,AX19) | AZ19: 56158.772 | BA19: 10929.154 | BB19: 13657.809 | BC19: 13570.337 | BD19: =BE19-SUM(BA19,BB19,BC19) | BE19: 46999.803 | BF19: 11737.785 | BG19: 14119.376 | BH19: 11404.721 | BI19: =BJ19-SUM(BF19,BG19,BH19) | BJ19: 47960.415 | BK19: 11552.466 | BL19: 14997.583 | BM19: 12023.942 | BN19: =BN25*0.01 | BO19: =SUM(BK19,BL19,BM19,BN19) | BP19: =BK19*(1+BP21) | BQ19: =BL19*(1+BQ21) | BR19: =BM19*(1+BR21) | BS19: =BN19*(1+BS21) | BT19: =SUM(BP19,BQ19,BR19,BS19) | BU19: =BP19*(1+BU21) | BV19: =BQ19*(1+BV21) | BW19: =BR19*(1+BW21) | BX19: =BS19*(1+BX21) | BY19: =SUM(BU19,BV19,BW19,BX19) | BZ19: =BY19*(1+BZ21) | CA19: =BZ19*(1+CA21) | CB19: =CA19*(1+CB21)
A20: Q/Q Digital consumer electronics revenue growth, % | AC20: =AC19/AB19-1 | AD20: =AD19/AC19-1 | AE20: =AE19/AD19-1 | AG20: =AG19/AE19-1 | AH20: =AH19/AG19-1 | AI20: =AI19/AH19-1 | AJ20: =AJ19/AI19-1 | AL20: =AL19/AJ19-1 | AM20: =AM19/AL19-1 | AN20: =AN19/AM19-1 | AO20: =AO19/AN19-1 | AQ20: =AQ19/AO19-1 | AR20: =AR19/AQ19-1 | AS20: =AS19/AR19-1 | AT20: =AT19/AS19-1 | AV20: =AV19/AT19-1 | AW20: =AW19/AV19-1 | AX20: =AX19/AW19-1 | AY20: =AY19/AX19-1 | BA20: =BA19/AY19-1 | BB20: =BB19/BA19-1 | BC20: =BC19/BB19-1 | BD20: =BD19/BC19-1 | BF20: =BF19/BD19-1 | BG20: =BG19/BF19-1 | BH20: =BH19/BG19-1 | BI20: =BI19/BH19-1 | BK20: =BK19/BI19-1 | BL20: =BL19/BK19-1 | BM20: =BM19/BL19-1 | BN20: =BN19/BM19-1 | BP20: =BP19/BN19-1 | BQ20: =BQ19/BP19-1 | BR20: =BR19/BQ19-1 | BS20: =BS19/BR19-1 | BU20: =BU19/BS19-1 | BV20: =BV19/BU19-1 | BW20: =BW19/BV19-1 | BX20: =BX19/BW19-1
A21: Y/Y Digital consumer electronics revenue growth, % | AG21: =AG19/AB19-1 | AH21: =AH19/AC19-1 | AI21: =AI19/AD19-1 | AJ21: =AJ19/AE19-1 | AK21: =AK19/AF19-1 | AL21: =AL19/AG19-1 | AM21: =AM19/AH19-1 | AN21: =AN19/AI19-1 | ... BO21: =BO19/BJ19-1 | BP21: 0.25 | BQ21: 0.2 | BR21: 0.2 | BS21: 0.2 | BT21: =BT19/BO19-1 | BU21: 0.2 | BV21: 0.2 | BW21: 0.2 | BX21: 0.2 | BY21: =BY19/BT19-1 | BZ21: 0.05 | CA21: 0.1 | CB21: 0.1
A22: Other revenue , mm | AB22: 11811.79 | AC22: 12888.568 | AD22: 12603.243 | AE22: =AF22-SUM(AB22,AC22,AD22) | AF22: 47839.802 | AG22: 10697.338 | AH22: 10466.088 | AI22: 10430.547 | AJ22: =AK22-SUM(AG22,AH22,AI22) | AK22: 42559.654 | AL22: 10436.918 | AM22: 9867.604 | AN22: 11718.428 | AO22: =AP22-SUM(AL22,AM22,AN22) | AP22: 44862.799 | AQ22: 11216.69 | AR22: 11680.896 | AS22: 11717.914 | AT22: =AU22-SUM(AQ22,AR22,AS22) | AU22: 48884.147 | AV22: 15574.988 | AW22: 16708.735 | AX22: 18321.07 | AY22: =AZ22-SUM(AV22,AW22,AX22) | AZ22: 73973.567 | BA22: 19056.43 | BB22: 18012.813 | BC22: 17596.658 | BD22: =BE22-SUM(BA22,BB22,BC22) | BE22: 69482.307 | BF22: 13643.72 | BG22: 14360.771 | BH22: 15555.553 | BI22: =BJ22-SUM(BF22,BG22,BH22) | BJ22: 59486.924 | BK22: 19115.229 | BL22: 20351.771 | BM22: 18719.934 | BN22: =BN25*0.02 | BO22: =SUM(BK22,BL22,BM22,BN22) | BP22: =BK22*(1+BP24) | BQ22: =BL22*(1+BQ24) | BR22: =BM22*(1+BR24) | BS22: =BN22*(1+BS24) | BT22: =SUM(BP22,BQ22,BR22,BS22) | BU22: =BP22*(1+BU24) | BV22: =BQ22*(1+BV24) | BW22: =BR22*(1+BW24) | BX22: =BS22*(1+BX24) | BY22: =SUM(BU22,BV22,BW22,BX22) | BZ22: =BY22*(1+BZ24) | CA22: =BZ22*(1+CA24) | CB22: =CA22*(1+CB24)
A23: Q/Q Other revenue growth, % | AC23: =AC22/AB22-1 | AD23: =AD22/AC22-1 | AE23: =AE22/AD22-1 | AG23: =AG22/AE22-1 | AH23: =AH22/AG22-1 | AI23: =AI22/AH22-1 | AJ23: =AJ22/AI22-1 | AL23: =AL22/AJ22-1 | AM23: =AM22/AL22-1 | AN23: =AN22/AM22-1 | AO23: =AO22/AN22-1 | AQ23: =AQ22/AO22-1 | AR23: =AR22/AQ22-1 | AS23: =AS22/AR22-1 | AT23: =AT22/AS22-1 | AV23: =AV22/AT22-1 | AW23: =AW22/AV22-1 | AX23: =AX22/AW22-1 | AY23: =AY22/AX22-1 | BA23: =BA22/AY22-1 | BB23: =BB22/BA22-1 | BC23: =BC22/BB22-1 | BD23: =BD22/BC22-1 | BF23: =BF22/BD22-1 | BG23: =BG22/BF22-1 | BH23: =BH22/BG22-1 | BI23: =BI22/BH22-1 | BK23: =BK22/BI22-1 | BL23: =BL22/BK22-1 | BM23: =BM22/BL22-1 | BN23: =BN22/BM22-1 | BP23: =BP22/BN22-1 | BQ23: =BQ22/BP22-1 | BR23: =BR22/BQ22-1 | BS23: =BS22/BR22-1 | BU23: =BU22/BS22-1 | BV23: =BV22/BU22-1 | BW23: =BW22/BV22-1 | BX23: =BX22/BW22-1
A24: Y/Y Other revenue growth, % | AG24: =AG22/AB22-1 | AH24: =AH22/AC22-1 | AI24: =AI22/AD22-1 | AJ24: =AJ22/AE22-1 | AK24: =AK22/AF22-1 | AL24: =AL22/AG22-1 | AM24: =AM22/AH22-1 | AN24: =AN22/AI22-1 | ... BO24: =BO22/BJ22-1 | BP24: 0.3 | BQ24: 0.1 | BR24: 0.1 | BS24: 0.1 | BT24: =BT22/BO22-1 | BU24: 0.1 | BV24: 0.1 | BW24: 0.1 | BX24: 0.1 | BY24: =BY22/BT22-1 | BZ24: 0.05 | CA24: 0.05 | CB24: 0.05
A25: Total Revenue, mm | AB25: =AB7+AB10+AB13+AB16+AB19+AB22 | AC25: =AC7+AC10+AC13+AC16+AC19+AC22 | AD25: =AD7+AD10+AD13+AD16+AD19+AD22 | AE25: =AE7+AE10+AE13+AE16+AE19+AE22 | AF25: =AF7+AF10+AF13+AF16+AF19+AF22 | AG25: =AG7+AG10+AG13+AG16+AG19+AG22 | AH25: =AH7+AH10+AH13+AH16+AH19+AH22 | AI25: =AI7+AI10+AI13+AI16+AI19+AI22 | ... BL25: =BL7+BL10+BL13+BL16+BL19+BL22 | BM25: =BM369 | BN25: =BN322 | BO25: =BO322 | BP25: =BP7+BP10+BP13+BP16+BP19+BP22 | BQ25: =BQ7+BQ10+BQ13+BQ16+BQ19+BQ22 | BR25: =BR7+BR10+BR13+BR16+BR19+BR22 | BS25: =BS7+BS10+BS13+BS16+BS19+BS22 | BT25: =BT7+BT10+BT13+BT16+BT19+BT22 | BU25: =BU7+BU10+BU13+BU16+BU19+BU22 | BV25: =BV7+BV10+BV13+BV16+BV19+BV22 | BW25: =BW7+BW10+BW13+BW16+BW19+BW22 | ... CB25: =CB7+CB10+CB13+CB16+CB19+CB22
A26: =A370 | BP26: =BP370 | BQ26: =BQ370 | BR26: =BR370 | BS26: =BS370 | BT26: =BT370 | BU26: =BU370 | BV26: =BV370 | BW26: =BW370 | ... CB26: =CB370
A27: Q/Q Total revenue growth, % | AC27: =AC25/AB25-1 | AD27: =AD25/AC25-1 | AE27: =AE25/AD25-1 | AG27: =AG25/AE25-1 | AH27: =AH25/AG25-1 | AI27: =AI25/AH25-1 | AJ27: =AJ25/AI25-1 | AL27: =AL25/AJ25-1 | AM27: =AM25/AL25-1 | AN27: =AN25/AM25-1 | AO27: =AO25/AN25-1 | AQ27: =AQ25/AO25-1 | AR27: =AR25/AQ25-1 | AS27: =AS25/AR25-1 | AT27: =AT25/AS25-1 | AV27: =AV25/AT25-1 | AW27: =AW25/AV25-1 | AX27: =AX25/AW25-1 | AY27: =AY25/AX25-1 | BA27: =BA25/AY25-1 | BB27: =BB25/BA25-1 | BC27: =BC25/BB25-1 | BD27: =BD25/BC25-1 | BF27: =BF25/BD25-1 | BG27: =BG25/BF25-1 | BH27: =BH25/BG25-1 | BI27: =BI25/BH25-1 | BK27: =BK25/BI25-1 | BL27: =BL25/BK25-1 | BM27: =BM25/BL25-1 | BN27: =BN25/BM25-1 | BP27: =BP25/BN25-1 | BQ27: =BQ25/BP25-1 | BR27: =BR25/BQ25-1 | BS27: =BS25/BR25-1 | BU27: =BU25/BS25-1 | BV27: =BV25/BU25-1 | BW27: =BW25/BV25-1 | BX27: =BX25/BW25-1
A28: Y/Y Total Revenue Growth, % | C28: =C$369/333158-1 | D28: =D369/C369-1 | E28: =E369/D369-1 | F28: =F369/E369-1 | G28: =G369/F369-1 | H28: =H$369/132755-1 | I28: =I$369/155886-1 | J28: =J$369/162577-1 | K28: =K$369/145806-1 | L28: =L369/G369-1 | M28: =M369/H369-1 | N28: =N369/I369-1 | O28: =O369/J369-1 | P28: =P369/K369-1 | Q28: =Q369/L369-1 | R28: =R369/M369-1 | S28: =S369/N369-1 | ... BY28: =BY369/BT369-1 | BZ28: =BZ369/BY369-1 | CA28: =CA369/BZ369-1 | CB28: =CB369/CA369-1
A30: Consolidated revenue in USD (Calculated), mm USD | C30: =C322/C257 | D30: =D322/D257 | E30: =E322/E257 | F30: =F322/F257 | G30: =G322/G257 | H30: =H322/H257 | I30: =I322/I257 | J30: =J322/J257 | K30: =K322/K257 | L30: =SUM(H30,I30,J30,K30) | M30: =M322/M257 | N30: =N322/N257 | O30: =O322/O257 | P30: =P322/P257 | Q30: =SUM(M30,N30,O30,P30) | R30: =R322/R257 | S30: =S322/S257 | T30: =T322/T257 | U30: =U322/U257 | V30: =SUM(R30,S30,T30,U30) | W30: =W322/W257 | X30: =X322/X257 | Y30: =Y322/Y257 | Z30: =Z322/Z257 | AA30: =SUM(W30,X30,Y30,Z30) | AB30: =AB322/AB257 | AC30: =AC322/AC257 | AD30: =AD322/AD257 | AE30: =AE322/AE257 | AF30: =SUM(AB30,AC30,AD30,AE30) | AG30: =AG322/AG257 | AH30: =AH322/AH257 | AI30: =AI322/AI257 | AJ30: =AJ322/AJ257 | AK30: =SUM(AG30,AH30,AI30,AJ30) | AL30: =AL322/AL257 | AM30: =AM322/AM257 | AN30: =AN322/AN257 | AO30: =AO322/AO257 | AP30: =SUM(AL30,AM30,AN30,AO30) | AQ30: =AQ322/AQ257 | AR30: =AR322/AR257 | AS30: =AS322/AS257 | AT30: =AT322/AT257 | AU30: =SUM(AQ30,AR30,AS30,AT30) | AV30: =AV322/AV257 | AW30: =AW322/AW257 | AX30: =AX322/AX257 | AY30: =AY322/AY257 | AZ30: =SUM(AV30,AW30,AX30,AY30) | BA30: =BA322/BA257 | BB30: =BB322/BB257 | BC30: =BC322/BC257 | BD30: =BD322/BD257 | BE30: =SUM(BA30,BB30,BC30,BD30) | BF30: =BF322/BF257 | BG30: =BG322/BG257 | BH30: =BH322/BH257 | BI30: =BI322/BI257 | BJ30: =SUM(BF30,BG30,BH30,BI30) | BK30: =BK322/BK257 | BL30: =BL322/BL257 | BM30: =BM322/BM257 | BN30: =BN322/BN257 | BO30: =SUM(BK30,BL30,BM30,BN30)
A31: Consolidated revenue in USD (Reported), mm USD | C31: 8998 | D31: 13322 | E31: 14543 | F31: 17116 | G31: 20111 | H31: 4900 | I31: 6076 | J31: 6968 | K31: 7228 | L31: 25173 | M31: 7041 | N31: 6661 | O31: 6665 | P31: 6238 | Q31: 26606 | R31: 6141 | S31: 6843 | T31: 8197 | U31: 8253 | V31: =SUM(R31,S31,T31,U31) | W31: 7507 | X31: 7061 | Y31: 8324 | Z31: 9213 | AA31: =SUM(W31,X31,Y31,Z31) | AB31: 8459 | AC31: 7853 | AD31: 8486 | AE31: 9398 | AF31: =SUM(AB31,AC31,AD31,AE31) | AG31: 7096 | AH31: 7746 | AI31: 9396 | AJ31: 10394 | AK31: =SUM(AG31,AH31,AI31,AJ31) | AL31: 10306 | AM31: 10385 | AN31: 12138 | AO31: 12676 | AP31: =SUM(AL31,AM31,AN31,AO31) | AQ31: 12919 | AR31: 13289 | AS31: 14878 | AT31: 15736 | AU31: =SUM(AQ31,AR31,AS31,AT31) | AV31: 17567 | AW31: 18158 | AX31: 20225 | AY31: 19931 | AZ31: =SUM(AV31,AW31,AX31,AY31) | BA31: 16719 | BB31: 15677 | BC31: 17278 | BD31: 19624 | BE31: =SUM(BA31,BB31,BC31,BD31) | BF31: 18873 | BG31: 20822 | BH31: 23504 | BI31: 26884 | BJ31: =SUM(BF31,BG31,BH31,BI31) | BK31: 25526 | BL31: 30070 | BM31: 33097 | BN31: 33731 | BO31: =SUM(BK31,BL31,BM31,BN31)
A33: Operating Expense Forecasting
A34: Revenue, mm | C34: =C369 | D34: =D369 | E34: =E369 | F34: =F369 | G34: =G369 | H34: =H369 | I34: =I369 | J34: =J369 | ... BO34: =BO369 | BP34: =BP25 | BQ34: =BQ25 | BR34: =BR25 | BS34: =BS25 | BT34: =BT25 | BU34: =BU25 | BV34: =BV25 | BW34: =BW25 | ... CB34: =CB25
A35: COGS, mm | C35: =C34-C36 | D35: =D34-D36 | E35: =E34-E36 | F35: =F34-F36 | G35: =G34-G36 | H35: =H34-H36 | I35: =I34-I36 | J35: =J34-J36 | ... CB35: =CB34-CB36
A36: Gross Profit, mm | C36: =C373 | D36: =D373 | E36: =E373 | F36: =F373 | G36: =G373 | H36: =H373 | I36: =I373 | J36: =J373 | ... BO36: =BO373 | BP36: =BP34*BP38 | BQ36: =BQ34*BQ38 | BR36: =BR34*BR38 | BS36: =BS34*BS38 | BT36: =BS36+BR36+BQ36+BP36 | BU36: =BU34*BU38 | BV36: =BV34*BV38 | BW36: =BW34*BW38 | BX36: =BX34*BX38 | BY36: =BX36+BW36+BV36+BU36 | BZ36: =BZ34*BZ38 | CA36: =CA34*CA38 | CB36: =CB34*CB38
A37: Y/Y growth in Gross profit, % | D37: =D36/C36-1 | E37: =E36/D36-1 | F37: =F36/E36-1 | G37: =G36/F36-1 | L37: =L36/G36-1 | M37: =M36/H36-1 | N37: =N36/I36-1 | O37: =O36/J36-1 | P37: =P36/K36-1 | Q37: =Q36/L36-1 | R37: =R36/M36-1 | S37: =S36/N36-1 | ... BY37: =BY36/BT36-1 | BZ37: =BZ36/BY36-1 | CA37: =CA36/BZ36-1 | CB37: =CB36/CA36-1
A38: Gross Margin, % | C38: =C36/C34 | D38: =D36/D34 | E38: =E36/E34 | F38: =F36/F34 | G38: =G36/G34 | H38: =H36/H34 | I38: =I36/I34 | J38: =J36/J34 | ... BO38: =BO36/BO34 | BP38: =BK38+BP40/10000 | BQ38: =BL38+BQ40/10000 | BR38: =BM38+BR40/10000 | BS38: =BN38+BS40/10000 | BT38: =BT36/BT34 | BU38: =BP38+BU40/10000 | BV38: =BQ38+BV40/10000 | BW38: =BR38+BW40/10000 | BX38: =BS38+BX40/10000 | BY38: =BY36/BY34 | BZ38: =BY38+BZ40/10000 | CA38: =BZ38+CA40/10000 | CB38: =CA38+CB40/10000
A39: Consensus Estimates - Gross Margin, % | BP39: =BP304 | BQ39: =BQ304 | BR39: =BR304 | BS39: =BS304 | BT39: =BT304 | BU39: =BU304 | BV39: =BV304 | BW39: =BW304 | ... CB39: =CB304
A40: Y/Y improvement in Gross Margin, bps | D40: =(D38-C38)*10000 | E40: =(E38-D38)*10000 | F40: =(F38-E38)*10000 | G40: =(G38-F38)*10000 | L40: =(L38-G38)*10000 | M40: =(M38-H38)*10000 | N40: =(N38-I38)*10000 | O40: =(O38-J38)*10000 | P40: =(P38-K38)*10000 | Q40: =(Q38-L38)*10000 | R40: =(R38-M38)*10000 | S40: =(S38-N38)*10000 | ... BO40: =(BO38-BJ38)*10000 | BP40: 520 | BQ40: 0 | BR40: 0 | BS40: 0 | BT40: =(BT38-BO38)*10000 | BU40: 0 | BV40: 0 | BW40: 0 | BX40: 0 | BY40: =(BY38-BT38)*10000 | BZ40: 0 | CA40: 0 | CB40: 0
A42: R&D Expense, mm | C42: =C375 | D42: =D375 | E42: =E375 | F42: =F375 | G42: =G375 | H42: =H375 | I42: =I375 | J42: =J375 | ... BO42: =BO375 | BP42: =BP34*BP44 | BQ42: =BQ34*BQ44 | BR42: =BR34*BR44 | BS42: =BS34*BS44 | BT42: =BS42+BR42+BQ42+BP42 | BU42: =BU34*BU44 | BV42: =BV34*BV44 | BW42: =BW34*BW44 | BX42: =BX34*BX44 | BY42: =BX42+BW42+BV42+BU42 | BZ42: =BZ34*BZ44 | CA42: =CA34*CA44 | CB42: =CB34*CB44
A43: Y/Y growth in R&D expense, % | D43: =D42/C42-1 | E43: =E42/D42-1 | F43: =F42/E42-1 | G43: =G42/F42-1 | H43: =H42/C42-1 | I43: =I42/D42-1 | J43: =J42/E42-1 | K43: =K42/F42-1 | L43: =L42/G42-1 | M43: =M42/H42-1 | N43: =N42/I42-1 | O43: =O42/J42-1 | ... BY43: =BY42/BT42-1 | BZ43: =BZ42/BY42-1 | CA43: =CA42/BZ42-1 | CB43: =CB42/CA42-1
A44: R&D Margin, % | C44: =C42/C34 | D44: =D42/D34 | E44: =E42/E34 | F44: =F42/F34 | G44: =G42/G34 | H44: =H42/H34 | I44: =I42/I34 | J44: =J42/J34 | ... BO44: =BO42/BO34 | BP44: =BK44-BP45/10000 | BQ44: =BL44-BQ45/10000 | BR44: =BM44-BR45/10000 | BS44: =BN44-BS45/10000 | BT44: =BT42/BT34 | BU44: =BP44-BU45/10000 | BV44: =BQ44-BV45/10000 | BW44: =BR44-BW45/10000 | BX44: =BS44-BX45/10000 | BY44: =BY42/BY34 | BZ44: =BY44-BZ45/10000 | CA44: =BZ44-CA45/10000 | CB44: =CA44-CB45/10000
A45: Y/Y improvement in R&D Margin, bps | D45: =-(D44-C44)*10000 | E45: =-(E44-D44)*10000 | F45: =-(F44-E44)*10000 | G45: =-(G44-F44)*10000 | H45: =-(H44-C44)*10000 | I45: =-(I44-D44)*10000 | J45: =-(J44-E44)*10000 | K45: =-(K44-F44)*10000 | L45: =-(L44-G44)*10000 | M45: =-(M44-H44)*10000 | N45: =-(N44-I44)*10000 | O45: =-(O44-J44)*10000 | ... BO45: =-(BO44-BJ44)*10000 | BP45: 80 | BQ45: 0 | BR45: 0 | BS45: 0 | BT45: =-(BT44-BO44)*10000 | BU45: 0 | BV45: 0 | BW45: 0 | BX45: 0 | BY45: =-(BY44-BT44)*10000 | BZ45: 0 | CA45: 0 | CB45: 0
A47: G&A Expense, mm | C47: =C376 | D47: =D376 | E47: =E376 | F47: =F376 | G47: =G376 | H47: =H376 | I47: =I376 | J47: =J376 | ... BO47: =BO376 | BP47: =BP34*BP49 | BQ47: =BQ34*BQ49 | BR47: =BR34*BR49 | BS47: =BS34*BS49 | BT47: =BS47+BR47+BQ47+BP47 | BU47: =BU34*BU49 | BV47: =BV34*BV49 | BW47: =BW34*BW49 | BX47: =BX34*BX49 | BY47: =BX47+BW47+BV47+BU47 | BZ47: =BZ34*BZ49 | CA47: =CA34*CA49 | CB47: =CB34*CB49
A48: Y/Y growth in G&A expense, % | D48: =D47/C47-1 | E48: =E47/D47-1 | F48: =F47/E47-1 | G48: =G47/F47-1 | H48: =H47/C47-1 | I48: =I47/D47-1 | J48: =J47/E47-1 | K48: =K47/F47-1 | L48: =L47/G47-1 | M48: =M47/H47-1 | N48: =N47/I47-1 | O48: =O47/J47-1 | ... BY48: =BY47/BT47-1 | BZ48: =BZ47/BY47-1 | CA48: =CA47/BZ47-1 | CB48: =CB47/CA47-1
A49: G&A Margin, % | C49: =C47/C34 | D49: =D47/D34 | E49: =E47/E34 | F49: =F47/F34 | G49: =G47/G34 | H49: =H47/H34 | I49: =I47/I34 | J49: =J47/J34 | ... BO49: =BO47/BO34 | BP49: =BK49-BP50/10000 | BQ49: =BL49-BQ50/10000 | BR49: =BM49-BR50/10000 | BS49: =BN49-BS50/10000 | BT49: =BT47/BT34 | BU49: =BP49-BU50/10000 | BV49: =BQ49-BV50/10000 | BW49: =BR49-BW50/10000 | BX49: =BS49-BX50/10000 | BY49: =BY47/BY34 | BZ49: =BY49-BZ50/10000 | CA49: =BZ49-CA50/10000 | CB49: =CA49-CB50/10000
A50: Y/Y improvement in G&A Margin, bps | D50: =-(D49-C49)*10000 | E50: =-(E49-D49)*10000 | F50: =-(F49-E49)*10000 | G50: =-(G49-F49)*10000 | H50: =-(H49-C49)*10000 | I50: =-(I49-D49)*10000 | J50: =-(J49-E49)*10000 | K50: =-(K49-F49)*10000 | L50: =-(L49-G49)*10000 | M50: =-(M49-H49)*10000 | N50: =-(N49-I49)*10000 | O50: =-(O49-J49)*10000 | ... BO50: =-(BO49-BJ49)*10000 | BP50: 0 | BQ50: 0 | BR50: 0 | BS50: 0 | BT50: =-(BT49-BO49)*10000 | BU50: 0 | BV50: 0 | BW50: 0 | BX50: 0 | BY50: =-(BY49-BT49)*10000 | BZ50: 0 | CA50: 0 | CB50: 0
A52: S&M Expense, mm | C52: =C377 | D52: =D377 | E52: =E377 | F52: =F377 | G52: =G377 | H52: =H377 | I52: =I377 | J52: =J377 | ... BO52: =BO377 | BP52: =BP34*BP54 | BQ52: =BQ34*BQ54 | BR52: =BR34*BR54 | BS52: =BS34*BS54 | BT52: =BS52+BR52+BQ52+BP52 | BU52: =BU34*BU54 | BV52: =BV34*BV54 | BW52: =BW34*BW54 | BX52: =BX34*BX54 | BY52: =BX52+BW52+BV52+BU52 | BZ52: =BZ34*BZ54 | CA52: =CA34*CA54 | CB52: =CB34*CB54
A53: Y/Y growth in S&M expense, % | D53: =D52/C52-1 | E53: =E52/D52-1 | F53: =F52/E52-1 | G53: =G52/F52-1 | H53: =H52/C52-1 | I53: =I52/D52-1 | J53: =J52/E52-1 | K53: =K52/F52-1 | L53: =L52/G52-1 | M53: =M52/H52-1 | N53: =N52/I52-1 | O53: =O52/J52-1 | ... BY53: =BY52/BT52-1 | BZ53: =BZ52/BY52-1 | CA53: =CA52/BZ52-1 | CB53: =CB52/CA52-1
A54: S&M Margin, % | C54: =C52/C34 | D54: =D52/D34 | E54: =E52/E34 | F54: =F52/F34 | G54: =G52/G34 | H54: =H52/H34 | I54: =I52/I34 | J54: =J52/J34 | ... BO54: =BO52/BO34 | BP54: =BK54-BP55/10000 | BQ54: =BL54-BQ55/10000 | BR54: =BM54-BR55/10000 | BS54: =BN54-BS55/10000 | BT54: =BT52/BT34 | BU54: =BP54-BU55/10000 | BV54: =BQ54-BV55/10000 | BW54: =BR54-BW55/10000 | BX54: =BS54-BX55/10000 | BY54: =BY52/BY34 | BZ54: =BY54-BZ55/10000 | CA54: =BZ54-CA55/10000 | CB54: =CA54-CB55/10000
A55: Y/Y improvement in S&M Margin, bps | D55: =-(D54-C54)*10000 | E55: =-(E54-D54)*10000 | F55: =-(F54-E54)*10000 | G55: =-(G54-F54)*10000 | H55: =-(H54-C54)*10000 | I55: =-(I54-D54)*10000 | J55: =-(J54-E54)*10000 | K55: =-(K54-F54)*10000 | L55: =-(L54-G54)*10000 | M55: =-(M54-H54)*10000 | N55: =-(N54-I54)*10000 | O55: =-(O54-J54)*10000 | ... BO55: =-(BO54-BJ54)*10000 | BP55: 0 | BQ55: 0 | BR55: 0 | BS55: 0 | BT55: =-(BT54-BO54)*10000 | BU55: 0 | BV55: 0 | BW55: 0 | BX55: 0 | BY55: =-(BY54-BT54)*10000 | BZ55: 0 | CA55: 0 | CB55: 0
A57: Other Expense, mm | C57: =C379 | D57: =D379 | E57: =E379 | F57: =F379 | G57: =G379 | H57: =H379 | I57: =I379 | J57: =J379 | ... BO57: =BO379 | BP57: 0 | BQ57: 0 | BR57: 0 | BS57: 0 | BT57: =BS57+BR57+BQ57+BP57 | BU57: 0 | BV57: 0 | BW57: 0 | BX57: 0 | BY57: =BX57+BW57+BV57+BU57 | BZ57: 0 | CA57: 0 | CB57: 0
A59: EBIT, mm | C59: =C36-C42-C47-C52-C57 | D59: =D36-D42-D47-D52-D57 | E59: =E36-E42-E47-E52-E57 | F59: =F36-F42-F47-F52-F57 | G59: =G36-G42-G47-G52-G57 | H59: =H36-H42-H47-H52-H57 | I59: =I36-I42-I47-I52-I57 | J59: =J36-J42-J47-J52-J57 | ... CB59: =CB36-CB42-CB47-CB52-CB57
A60: Y/Y growth in EBIT, % | D60: =D59/C59-1 | E60: =E59/D59-1 | F60: =F59/E59-1 | G60: =G59/F59-1 | L60: =L59/G59-1 | M60: =M59/H59-1 | N60: =N59/I59-1 | O60: =O59/J59-1 | P60: =P59/K59-1 | Q60: =Q59/L59-1 | R60: =R59/M59-1 | S60: =S59/N59-1 | ... BY60: =BY59/BT59-1 | BZ60: =BZ59/BY59-1 | CA60: =CA59/BZ59-1 | CB60: =CB59/CA59-1
A61: EBIT Margin, % | C61: =C59/C34 | D61: =D59/D34 | E61: =E59/E34 | F61: =F59/F34 | G61: =G59/G34 | H61: =H59/H34 | I61: =I59/I34 | J61: =J59/J34 | ... CB61: =CB59/CB34
A62: Y/Y improvement in EBIT Margin, bps | D62: =(D61-C61)*10000 | E62: =(E61-D61)*10000 | F62: =(F61-E61)*10000 | G62: =(G61-F61)*10000 | L62: =(L61-G61)*10000 | M62: =(M61-H61)*10000 | N62: =(N61-I61)*10000 | O62: =(O61-J61)*10000 | P62: =(P61-K61)*10000 | Q62: =(Q61-L61)*10000 | R62: =(R61-M61)*10000 | S62: =(S61-N61)*10000 | ... BY62: =(BY61-BT61)*10000 | BZ62: =(BZ61-BY61)*10000 | CA62: =(CA61-BZ61)*10000 | CB62: =(CB61-CA61)*10000
A64: D&A Breakdown (FS)
A65: Depreciation - Cost of revenue, mm | C65: 74482.133 | D65: 80123.895 | E65: 98065.992 | F65: 118313.58 | G65: 141002.26 | H65: 37457.425 | I65: 41804.816 | J65: 52193.345 | K65: =L65-SUM(H65,I65,J65) | L65: 183750.95 | M65: 51041.714 | N65: 50147.268 | O65: 51504.491 | P65: =Q65-SUM(M65,N65,O65) | Q65: 204126.24 | R65: 50829.281 | S65: 50255.557 | T65: 51260.197 | U65: =V65-SUM(R65,S65,T65) | V65: 203476.85 | W65: 54492.962 | X65: 52169.204 | Y65: 65040.285 | Z65: =AA65-SUM(W65,X65,Y65) | AA65: 235985.19 | AB65: 64798.902 | AC65: 64558.463 | AD65: 66715.027 | AE65: =AF65-SUM(AB65,AC65,AD65) | AF65: 264804.74 | AG65: 69934.176 | AH65: 67257.072 | AI65: 59338.43 | AJ65: =AK65-SUM(AG65,AH65,AI65) | AK65: 256530.96 | AL65: 60839.984 | AM65: 62604.362 | AN65: 86576.054 | AO65: =AP65-SUM(AL65,AM65,AN65) | AP65: 299311.41 | AQ65: 92234.075 | AR65: 94713.022 | AS65: 97830.855 | AT65: =AU65-SUM(AQ65,AR65,AS65) | AU65: 386103.92 | AV65: 101657.69 | AW65: 103802.52 | AX65: 95904.327 | AY65: =AZ65-SUM(AV65,AW65,AX65) | AZ65: 399638.76 | BA65: 100833.82 | BB65: 114113.02 | BC65: 137203.83 | BD65: =BE65-SUM(BA65,BB65,BC65) | BE65: 492827.38 | BF65: 148662.64 | BG65: 153957.49 | BH65: 156176.64 | BI65: =BJ65-SUM(BF65,BG65,BH65) | BJ65: 616390.41 | BK65: 161648.24 | BL65: 175806.06 | BM65: 150797.51 | BN65: =BN68-BN67-BN66 | BO65: =SUM(BK65,BL65,BM65,BN65)
A66: Depreciation - Operating Expense, mm | C66: 4180.237 | D66: 5427.488 | E66: 7261.159 | F66: 10848.277 | G66: 12952.464 | H66: 3522.295 | I66: 3541.464 | J66: 3381.809 | K66: =L66-SUM(H66,I66,J66) | L66: 13869.354 | M66: 3658.291 | N66: 3685.08 | O66: 3828.916 | P66: =Q66-SUM(M66,N66,O66) | Q66: 15152.174 | R66: 4115.03 | S66: 4140.384 | T66: 4046.009 | U66: =V66-SUM(R66,S66,T66) | V66: 16583.067 | W66: 4634.177 | X66: 4790.33 | Y66: 4974.403 | Z66: =AA66-SUM(W66,X66,Y66) | AA66: 19746.263 | AB66: 5652.531 | AC66: 5786.785 | AD66: 5784.173 | AE66: =AF66-SUM(AB66,AC66,AD66) | AF66: 23292.299 | AG66: 6252.169 | AH66: 6441.494 | AI66: 6033.031 | AJ66: =AK66-SUM(AG66,AH66,AI66) | AK66: 24856.701 | AL66: 6237.895 | AM66: 6371.65 | AN66: 6245.834 | AO66: =AP66-SUM(AL66,AM66,AN66) | AP66: 25191.358 | AQ66: 6666.175 | AR66: 6949.727 | AS66: 7057.572 | AT66: =AU66-SUM(AQ66,AR66,AS66) | AU66: 27936.211 | AV66: 7276.382 | AW66: 7236.218 | AX66: 7239.604 | AY66: =AZ66-SUM(AV66,AW66,AX66) | AZ66: 28850.463 | BA66: 7247.386 | BB66: 7529.817 | BC66: 7722.319 | BD66: =BE66-SUM(BA66,BB66,BC66) | BE66: 30097.805 | BF66: 8026.174 | BG66: 8963.535 | BH66: 9730.876 | BI66: =BJ66-SUM(BF66,BG66,BH66) | BJ66: 37190.415 | BK66: 11351.218 | BL66: 10190.757 | BM66: 9874.777 | BN66: 9500 | BO66: =SUM(BK66,BL66,BM66,BN66)
A67: Depreciation - Other operating expense, mm | C67: 22.003 | D67: 22.004 | E67: 16.8 | F67: 6.656 | G67: 25.12 | H67: 6.222 | I67: 6.221 | J67: 6.222 | K67: =L67-SUM(H67,I67,J67) | L67: 24.887 | M67: 6.222 | N67: 6.221 | O67: 6.222 | P67: =Q67-SUM(M67,N67,O67) | Q67: 24.952 | R67: 6.418 | S67: 6.222 | T67: 6.221 | U67: =V67-SUM(R67,S67,T67) | V67: 25.083 | W67: 6.222 | X67: 6.221 | Y67: 18.14 | Z67: =AA67-SUM(W67,X67,Y67) | AA67: 64.51 | AB67: 10.853 | AC67: 6.222 | AD67: 5.994 | AE67: =AF67-SUM(AB67,AC67,AD67) | AF67: 27.857 | AG67: 6.123 | AH67: 6.014 | AI67: 6.015 | AJ67: =AK67-SUM(AG67,AH67,AI67) | AK67: 24.167 | AL67: 5.862 | AM67: 5.556 | AN67: 3.049 | AO67: =AP67-SUM(AL67,AM67,AN67) | AP67: 35.68 | AQ67: 72.617 | AR67: 61.437 | AS67: 13.317 | AT67: =AU67-SUM(AQ67,AR67,AS67) | AU67: 147.566 | AV67: 0.195 | AW67: 1.995 | AX67: 3.288 | AY67: =AZ67-SUM(AV67,AW67,AX67) | AZ67: 8.961 | BA67: 2.168 | BB67: 1.121 | BC67: 0.68 | BD67: =BE67-SUM(BA67,BB67,BC67) | BE67: 7.487 | BF67: 8.288 | BG67: 8.288 | BH67: 7.624 | BI67: =BJ67-SUM(BF67,BG67,BH67) | BJ67: 29.663 | BK67: 5.464 | BL67: 10.452 | BM67: 20.227 | BN67: 10 | BO67: =SUM(BK67,BL67,BM67,BN67)
A68: Total Depreciation, mm | C68: =SUM(C65:C67) | D68: =SUM(D65:D67) | E68: =SUM(E65:E67) | F68: =SUM(F65:F67) | G68: =SUM(G65:G67) | H68: =SUM(H65:H67) | I68: =SUM(I65:I67) | J68: =SUM(J65:J67) | ... BL68: =SUM(BL65:BL67) | BM68: =BM72 | BN68: =BN677 | BO68: =BO677
A70: Depreciation of right-of-use assets, mm | AG70: 665.867 | AH70: 646.692 | AI70: 649.69 | AJ70: =AK70-AI70-AH70-AG70 | AK70: 2622.7 | AL70: 725.766 | AM70: 752.326 | AN70: 658.266 | AO70: =AP70-AN70-AM70-AL70 | AP70: 2681.6 | AQ70: 604.043 | AR70: 617.015 | AS70: 653.803 | AT70: =AU70-AS70-AR70-AQ70 | AU70: 2556.2 | AV70: 692.721 | AW70: 717.963 | AX70: 824.788 | AY70: =AZ70-AX70-AW70-AV70 | AZ70: 3073.005 | BA70: 859.085 | BB70: 854.817 | BC70: 881.047 | BD70: =BE70-BC70-BB70-BA70 | BE70: 3458.968 | BF70: 974.183 | BG70: 876.513 | BH70: 888.29 | BI70: =BJ70-SUM(BF70,BG70,BH70) | BJ70: 3679.507 | BK70: 973.411 | BL70: 1022.165 | BM70: 1113.125 | BN70: 1000 | BO70: =SUM(BK70,BL70,BM70,BN70) | BP70: 800 | BQ70: 800 | BR70: 800 | BS70: 800 | BT70: =BS70+BR70+BQ70+BP70 | BU70: 800 | BV70: 800 | BW70: 800 | BX70: 800 | BY70: =BX70+BW70+BV70+BU70 | BZ70: 3200 | CA70: 3200 | CB70: 3200
A71: Depreciation of PP&E (calculated), mm | AG71: =AG72-AG70 | AH71: =AH72-AH70 | AI71: =AI72-AI70 | AJ71: =AJ72-AJ70 | AK71: =AK72-AK70 | AL71: =AL72-AL70 | AM71: =AM72-AM70 | AN71: =AN72-AN70 | ... BO71: =BO72-BO70 | BP71: =-BP836 | BQ71: =-BQ836 | BR71: =-BR836 | BS71: =-BS836 | BT71: =BS71+BR71+BQ71+BP71 | BU71: =-BU836 | BV71: =-BV836 | BW71: =-BW836 | BX71: =-BX836 | BY71: =BX71+BW71+BV71+BU71 | BZ71: =-BZ836 | CA71: =-CA836 | CB71: =-CB836
A72: Total depreciation, mm | AG72: =AG677 | AH72: =AH677 | AI72: =AI677 | AJ72: =AJ677 | AK72: =AK677 | AL72: =AL677 | AM72: =AM677 | AN72: =AN677 | ... BO72: =BO677 | BP72: =SUM(BP70:BP71) | BQ72: =SUM(BQ70:BQ71) | BR72: =SUM(BR70:BR71) | BS72: =SUM(BS70:BS71) | BT72: =SUM(BT70:BT71) | BU72: =SUM(BU70:BU71) | BV72: =SUM(BV70:BV71) | BW72: =SUM(BW70:BW71) | ... CB72: =SUM(CB70:CB71)
A74: Amortization of intangibles - Cost of revenue, mm | C74: 1259.949 | D74: 1309.257 | E74: 1463.405 | F74: 1344.819 | G74: 1154.698 | H74: 333.467 | I74: 320.331 | J74: 346.78 | K74: =L74-SUM(H74,I74,J74) | L74: 1356.858 | M74: 407.75 | N74: 404.092 | O74: 412.698 | P74: =Q74-SUM(M74,N74,O74) | Q74: 1642.051 | R74: 489.677 | S74: 491.251 | T74: 518.837 | U74: =V74-SUM(R74,S74,T74) | V74: 2028.492 | W74: 527.908 | X74: 514.854 | Y74: 542.083 | Z74: =AA74-SUM(W74,X74,Y74) | AA74: 2135.521 | AB74: 484.597 | AC74: 493.629 | AD74: 492.247 | AE74: =AF74-SUM(AB74,AC74,AD74) | AF74: 2073.48 | AG74: 713.093 | AH74: 729.526 | AI74: 786.959 | AJ74: =AK74-SUM(AG74,AH74,AI74) | AK74: 3069.901 | AL74: 895.398 | AM74: 1279.576 | AN74: 1337.967 | AO74: =AP74-SUM(AL74,AM74,AN74) | AP74: 4837.728 | AQ74: 1286.904 | AR74: 1394.961 | AS74: 1468.312 | AT74: =AU74-SUM(AQ74,AR74,AS74) | AU74: 5574.246 | AV74: 1502.075 | AW74: 1509.549 | AX74: 1536.479 | AY74: =AZ74-SUM(AV74,AW74,AX74) | AZ74: 6086.246 | BA74: 1567.43 | BB74: 1619.384 | BC74: 1672.325 | BD74: =BE74-SUM(BA74,BB74,BC74) | BE74: 6538.107 | BF74: 1628.675 | BG74: 1538.4 | BH74: 1584.94 | BI74: =BJ74-SUM(BF74,BG74,BH74) | BJ74: 6342.31 | BK74: 1410.729 | BL74: 1321.247 | BM74: 1316.056 | BN74: =BN76-BN75 | BO74: =SUM(BK74,BL74,BM74,BN74)
A75: Amortization of intangibles - Operating expense, mm | C75: 870.426 | D75: 927.459 | E75: 874.165 | F75: 835.956 | G75: 1047.324 | H75: 302.968 | I75: 306.282 | J75: 304.411 | K75: =L75-SUM(H75,I75,J75) | L75: 1249.491 | M75: 364.019 | N75: 380.446 | O75: 396.315 | P75: =Q75-SUM(M75,N75,O75) | Q75: 1560.149 | R75: 406.655 | S75: 381.574 | T75: 437.53 | U75: =V75-SUM(R75,S75,T75) | V75: 1714.914 | W75: 510.916 | X75: 511.781 | Y75: 589.751 | Z75: =AA75-SUM(W75,X75,Y75) | AA75: 2211.215 | AB75: 550.994 | AC75: 563.585 | AD75: 612.376 | AE75: =AF75-SUM(AB75,AC75,AD75) | AF75: 2347.925 | AG75: 642.243 | AH75: 614.244 | AI75: 591.867 | AJ75: =AK75-SUM(AG75,AH75,AI75) | AK75: 2402.508 | AL75: 575.338 | AM75: 614.108 | AN75: 570.172 | AO75: =AP75-SUM(AL75,AM75,AN75) | AP75: 2348.52 | AQ75: 640.547 | AR75: 686.011 | AS75: 656.707 | AT75: =AU75-SUM(AQ75,AR75,AS75) | AU75: 2632.923 | AV75: 665.723 | AW75: 674.363 | AX75: 661.968 | AY75: =AZ75-SUM(AV75,AW75,AX75) | AZ75: 2669.848 | BA75: 671.835 | BB75: 676.343 | BC75: 681.007 | BD75: =BE75-SUM(BA75,BB75,BC75) | BE75: 2720.143 | BF75: 697.386 | BG75: 698.884 | BH75: 728.482 | BI75: =BJ75-SUM(BF75,BG75,BH75) | BJ75: 2843.839 | BK75: 723.423 | BL75: 729.398 | BM75: 778.702 | BN75: 750 | BO75: =SUM(BK75,BL75,BM75,BN75)
A76: Total Amortization of intangibles, mm | C76: =SUM(C74:C75) | D76: =SUM(D74:D75) | E76: =SUM(E74:E75) | F76: =SUM(F74:F75) | G76: =SUM(G74:G75) | H76: =SUM(H74:H75) | I76: =SUM(I74:I75) | J76: =SUM(J74:J75) | ... BL76: =SUM(BL74:BL75) | BM76: =BM678 | BN76: =BN678 | BO76: =BO678 | BP76: =-BP842 | BQ76: =-BQ842 | BR76: =-BR842 | BS76: =-BS842 | BT76: =-BT842 | BU76: =-BU842 | BV76: =-BV842 | BW76: =-BW842 | ... CB76: =-CB842
A78: Supplemental Information
A79: Key Metrics - USD Metrics (FS/SI)
A80: Net revenue, mm US$ | C80: =C31 | D80: =D31 | E80: =E31 | F80: =F31 | G80: =G31 | H80: =H31 | I80: =I31 | J80: =J31 | ... BO80: =BO31
A82: Net income(loss) attributable to shareholders of the parent, mm US$ | C82: 2714 | D82: 5132 | E82: 4570 | F82: 5618 | G82: 6338 | H82: 1583 | I82: 1982 | J82: 2544 | K82: 2599 | L82: =SUM(H82,I82,J82,K82) | M82: 2505 | N82: 2575 | O82: 2363 | P82: 2232 | Q82: =SUM(M82,N82,O82,P82) | R82: 1955 | S82: 2237 | T82: 3045 | U82: 3154 | V82: =SUM(R82,S82,T82,U82) | W82: 2812 | X82: 2188 | Y82: 2969 | Z82: 3295 | AA82: =SUM(W82,X82,Y82,Z82) | AB82: 3062 | AC82: 2434 | AD82: 2903 | AE82: 3243 | AF82: =SUM(AB82,AC82,AD82,AE82) | AG82: 1992 | AH82: 2146 | AI82: 3241 | AJ82: 3802 | AK82: =SUM(AG82,AH82,AI82,AJ82) | AL82: 3882 | AM82: 4038 | AN82: 4676 | AO82: 5006 | AP82: =SUM(AL82,AM82,AN82,AO82) | AQ82: 4980 | AR82: 4798 | AS82: 5606 | AT82: 5970 | AU82: =SUM(AQ82,AR82,AS82,AT82) | AV82: 7252 | AW82: 8057 | AX82: 9265 | AY82: 9428 | AZ82: =SUM(AV82,AW82,AX82,AY82) | BA82: 6804 | BB82: 5927 | BC82: 6668 | BD82: 7489 | BE82: =SUM(BA82,BB82,BC82,BD82) | BF82: 7181 | BG82: 7662 | BH82: 10063 | BI82: 11599 | BJ82: =SUM(BF82,BG82,BH82,BI82) | BK82: 10997 | BL82: 12825 | BM82: 15122 | BN82: 16307 | BO82: =SUM(BK82,BL82,BM82,BN82)
A83: Earnings Per Share - WAD, US$ | C83: =C$82/C422 | D83: =D$82/D422 | E83: =E$82/E422 | F83: =F$82/F422 | G83: =G$82/G422 | H83: =H$82/H422 | I83: =I$82/I422 | J83: =J$82/J422 | ... BO83: =BO$82/BO422
A84: Earnings Per ADR - WAD, US$ | C84: =C$82/C426 | D84: =D$82/D426 | E84: =E$82/E426 | F84: =F$82/F426 | G84: =G$82/G426 | H84: =H$82/H426 | I84: =I$82/I426 | J84: =J$82/J426 | ... BO84: =BO$82/BO426
A86: Capex, bn US$ | C86: 2.671 | D86: 5.936 | E86: 7.286 | F86: 8.322 | G86: 9.688 | H86: 3.799 | I86: 2.438 | J86: 1.605 | K86: 1.68 | L86: =SUM(H86,I86,J86,K86) | M86: 1.55 | N86: 1.742 | O86: 2.214 | P86: 2.617 | Q86: =SUM(M86,N86,O86,P86) | R86: 1.15 | S86: 2.26 | T86: 3.25 | U86: 3.53 | V86: =SUM(R86,S86,T86,U86) | W86: 3.29 | X86: 3.47 | Y86: 2.05 | Z86: 2.05 | AA86: =SUM(W86,X86,Y86,Z86) | AB86: 2.45 | AC86: 2.01 | AD86: 2.28 | AE86: 3.72 | AF86: =SUM(AB86,AC86,AD86,AE86) | AG86: 2.46 | AH86: 3.75 | AI86: 3.14 | AJ86: 5.55 | AK86: =SUM(AG86,AH86,AI86,AJ86) | AL86: 6.39 | AM86: 4.24 | AN86: 3.42 | AO86: 3.19 | AP86: =SUM(AL86,AM86,AN86,AO86) | AQ86: 8.84 | AR86: 5.97 | AS86: 6.77 | AT86: 8.46 | AU86: =SUM(AQ86,AR86,AS86,AT86) | AV86: 9.38 | AW86: 7.34 | AX86: 8.75 | AY86: 10.82 | AZ86: =SUM(AV86,AW86,AX86,AY86) | BA86: 9.94 | BB86: 8.17 | BC86: 7.1 | BD86: 5.24 | BE86: =SUM(BA86,BB86,BC86,BD86) | BF86: 5.77 | BG86: 6.36 | BH86: 6.4 | BI86: 11.23 | BJ86: 29.76 | BK86: 10.06 | BL86: 9.63 | BM86: 9.7 | BN86: 11.51 | BO86: 40.9
A88: Key Metrics - Revenue Breakdown by Process Node (FS/IR/SI)
A89: 3-nanometer revenue contribution, % | BB89: =BB105/BB$119 | BC89: =BC105/BC$119 | BD89: =BD105/BD$119 | BE89: =BE105/BE$119 | BF89: =BF105/BF$119 | BG89: =BG105/BG$119 | BH89: =BH105/BH$119 | BI89: =BI105/BI$119 | ... BM89: =BM105/BM$119 | BN89: 0.28 | BO89: =BO105/BO$119
A90: 5-nanometer revenue contribution, % | AN90: =AN106/AN$119 | AO90: =AO106/AO$119 | AP90: =AP106/AP$119 | AQ90: =AQ106/AQ$119 | AR90: =AR106/AR$119 | AS90: =AS106/AS$119 | AT90: =AT106/AT$119 | AU90: =AU106/AU$119 | ... BM90: =BM106/BM$119 | BN90: 0.35 | BO90: =BO106/BO$119
A91: 7-nanometer revenue contribution, % | H91: - | I91: - | J91: - | K91: - | M91: - | N91: - | O91: - | P91: - | R91: - | S91: - | T91: - | U91: - | W91: - | X91: - | Y91: - | Z91: - | AB91: =AB107/AB$119 | AC91: =AC107/AC$119 | AD91: =AD107/AD$119 | AE91: =AE107/AE$119 | AF91: =AF107/AF$119 | AG91: =AG107/AG$119 | AH91: =AH107/AH$119 | AI91: =AI107/AI$119 | ... BM91: =BM107/BM$119 | BN91: 0.14 | BO91: =BO107/BO$119
A92: 10-nanometer revenue contribution, % | H92: - | I92: - | J92: - | K92: - | M92: - | N92: - | O92: - | P92: - | R92: - | S92: - | T92: - | U92: - | W92: - | X92: 0.01 | Y92: 0.1 | Z92: 0.25 | AA92: 0.1 | AB92: =AB108/AB$119 | AC92: =AC108/AC$119 | AD92: =AD108/AD$119 | AE92: =AE108/AE$119 | AF92: =AF108/AF$119 | AG92: =AG108/AG$119 | AH92: =AH108/AH$119 | AI92: =AI108/AI$119 | ... BM92: =BM108/BM$119 | BN92: 0 | BO92: =BO108/BO$119
A93: 16-nanometer revenue contribution, % | AQ93: =AQ109/AQ$119 | AR93: =AR109/AR$119 | AS93: =AS109/AS$119 | AT93: =AT109/AT$119 | AU93: =AU109/AU$119 | AV93: =AV109/AV$119 | AW93: =AW109/AW$119 | AX93: =AX109/AX$119 | ... BM93: =BM109/BM$119 | BN93: 0.058 | BO93: =BO109/BO$119
A94: 20-nanometer revenue contribution, % | AQ94: =AQ110/AQ$119 | AR94: =AR110/AR$119 | AS94: =AS110/AS$119 | AT94: =AT110/AT$119 | AU94: =AU110/AU$119 | AV94: =AV110/AV$119 | AW94: =AW110/AW$119 | AX94: =AX110/AX$119 | ... BM94: =BM110/BM$119 | BN94: 0.002 | BO94: =BO110/BO$119
A95: 16/20-nanometer revenue contribution, % | H95: - | I95: - | J95: 0.09 | K95: 0.21 | L95: 0.09 | M95: 0.16 | N95: 0.2 | O95: 0.21 | P95: 0.24 | Q95: 0.2 | R95: 0.23 | S95: 0.23 | T95: 0.31 | U95: 0.33 | V95: 0.28 | W95: 0.31 | X95: 0.26 | Y95: 0.24 | Z95: 0.2 | AA95: 0.25 | AB95: =AB109/AB$119 | AC95: =AC109/AC$119 | AD95: =AD109/AD$119 | AE95: =AE109/AE$119 | AF95: =AF109/AF$119 | AG95: =AG109/AG$119 | AH95: =AH109/AH$119 | AI95: =AI109/AI$119 | ... AP95: =AP109/AP$119 | AQ95: =AQ111/AQ$119 | AR95: =AR111/AR$119 | AS95: =AS111/AS$119 | AT95: =AT111/AT$119 | AU95: =AU111/AU$119 | AV95: =AV111/AV$119 | AW95: =AW111/AW$119 | AX95: =AX111/AX$119 | ... BO95: =BO111/BO$119
A96: 28-nanometer revenue contribution, % | E96: 0.01 | F96: 0.12 | G96: 0.3 | H96: 0.34 | I96: 0.37 | J96: 0.34 | K96: 0.3 | L96: 0.33 | M96: 0.3 | N96: 0.27 | O96: 0.27 | P96: 0.25 | Q96: 0.28 | R96: 0.3 | S96: 0.28 | T96: 0.24 | U96: 0.24 | V96: 0.26 | W96: 0.25 | X96: 0.27 | Y96: 0.23 | Z96: 0.18 | AA96: 0.23 | AB96: =AB112/AB$119 | AC96: =AC112/AC$119 | AD96: =AD112/AD$119 | AE96: =AE112/AE$119 | AF96: =AF112/AF$119 | AG96: =AG112/AG$119 | AH96: =AH112/AH$119 | AI96: =AI112/AI$119 | ... BM96: =BM112/BM$119 | BN96: 0.06 | BO96: =BO112/BO$119
A97: 40/45-nanometer revenue contribution, % | C97: 0.04 | D97: 0.17 | E97: 0.26 | F97: 0.27 | G97: 0.2 | H97: 0.21 | I97: 0.19 | J97: 0.17 | K97: 0.13 | L97: 0.16 | M97: 0.15 | N97: 0.14 | O97: 0.14 | P97: 0.14 | Q97: 0.14 | R97: 0.14 | S97: 0.15 | T97: 0.13 | U97: 0.12 | V97: 0.14 | W97: 0.13 | X97: 0.13 | Y97: 0.12 | Z97: 0.1 | AA97: 0.12 | AB97: =AB113/AB$119 | AC97: =AC113/AC$119 | AD97: =AD113/AD$119 | AE97: =AE113/AE$119 | AF97: =AF113/AF$119 | AG97: =AG113/AG$119 | AH97: =AH113/AH$119 | AI97: =AI113/AI$119 | ... BM97: =BM113/BM$119 | BN97: 0.03 | BO97: =BO113/BO$119
A98: 65-nanometer revenue contribution, % | C98: 0.29 | D98: 0.29 | E98: 0.29 | F98: 0.23 | G98: 0.16 | H98: 0.16 | I98: 0.15 | J98: 0.13 | K98: 0.11 | L98: 0.14 | M98: 0.12 | N98: 0.11 | O98: 0.11 | P98: 0.11 | Q98: 0.12 | R98: 0.1 | S98: 0.12 | T98: 0.11 | U98: 0.11 | V98: 0.11 | W98: 0.11 | X98: 0.1 | Y98: 0.1 | Z98: 0.09 | AA98: 0.1 | AB98: =AB114/AB$119 | AC98: =AC114/AC$119 | AD98: =AD114/AD$119 | AE98: =AE114/AE$119 | AF98: =AF114/AF$119 | AG98: =AG114/AG$119 | AH98: =AH114/AH$119 | AI98: =AI114/AI$119 | ... BM98: =BM114/BM$119 | BN98: 0.04 | BO98: =BO114/BO$119
A99: 90-nanometer revenue contribution, % | C99: 0.2 | D99: 0.14 | E99: 0.09 | F99: 0.09 | G99: 0.08 | H99: 0.07 | I99: 0.07 | J99: 0.06 | K99: 0.06 | L99: 0.07 | M99: 0.07 | N99: 0.07 | O99: 0.08 | P99: 0.07 | Q99: 0.07 | R99: 0.06 | S99: 0.05 | T99: 0.05 | U99: 0.05 | V99: 0.05 | W99: 0.04 | X99: 0.05 | Y99: 0.05 | Z99: 0.04 | AA99: 0.04 | AB99: =AB115/AB$119 | AC99: =AC115/AC$119 | AD99: =AD115/AD$119 | AE99: =AE115/AE$119 | AF99: =AF115/AF$119 | AG99: =AG115/AG$119 | AH99: =AH115/AH$119 | AI99: =AI115/AI$119 | ... BM99: =BM115/BM$119 | BN99: 0.01 | BO99: =BO115/BO$119
A100: 0.11/0.13 micron revenue contribution, % | C100: 0.14 | D100: 0.12 | E100: 0.08 | F100: 0.06 | G100: 0.04 | H100: 0.03 | I100: 0.03 | J100: 0.03 | K100: 0.02 | L100: 0.03 | M100: 0.02 | N100: 0.03 | O100: 0.02 | P100: 0.03 | Q100: 0.02 | R100: 0.02 | S100: 0.02 | T100: 0.03 | U100: 0.02 | V100: 0.02 | W100: 0.02 | X100: 0.03 | Y100: 0.03 | Z100: 0.02 | AA100: 0.03 | AB100: =AB116/AB$119 | AC100: =AC116/AC$119 | AD100: =AD116/AD$119 | AE100: =AE116/AE$119 | AF100: =AF116/AF$119 | AG100: =AG116/AG$119 | AH100: =AH116/AH$119 | AI100: =AI116/AI$119 | ... BM100: =BM116/BM$119 | BN100: 0.01 | BO100: =BO116/BO$119
A101: 0.15/0.18 micron revenue contribution, % | C101: 0.21 | D101: 0.17 | E101: 0.18 | F101: 0.15 | G101: 0.16 | H101: 0.14 | I101: 0.14 | J101: 0.13 | K101: 0.12 | L101: 0.13 | M101: 0.13 | N101: 0.13 | O101: 0.12 | P101: 0.11 | Q101: 0.12 | R101: 0.11 | S101: 0.11 | T101: 0.09 | U101: 0.1 | V101: 0.1 | W101: 0.11 | X101: 0.11 | Y101: 0.1 | Z101: 0.09 | AA101: 0.1 | AB101: =AB117/AB$119 | AC101: =AC117/AC$119 | AD101: =AD117/AD$119 | AE101: =AE117/AE$119 | AF101: =AF117/AF$119 | AG101: =AG117/AG$119 | AH101: =AH117/AH$119 | AI101: =AI117/AI$119 | ... BM101: =BM117/BM$119 | BN101: 0.02 | BO101: =BO117/BO$119
A102: 0.25 micron and above revenue contribution, % | C102: 0.12 | D102: 0.11 | E102: 0.09 | F102: 0.08 | G102: 0.06 | H102: 0.05 | I102: 0.05 | J102: 0.05 | K102: 0.05 | L102: 0.05 | M102: 0.05 | N102: 0.05 | O102: 0.05 | P102: 0.05 | Q102: 0.05 | R102: 0.04 | S102: 0.04 | T102: 0.04 | U102: 0.03 | V102: 0.04 | W102: 0.03 | X102: 0.04 | Y102: 0.03 | Z102: 0.03 | AA102: 0.03 | AB102: =AB118/AB$119 | AC102: =AC118/AC$119 | AD102: =AD118/AD$119 | AE102: =AE118/AE$119 | AF102: =AF118/AF$119 | AG102: =AG118/AG$119 | AH102: =AH118/AH$119 | AI102: =AI118/AI$119 | ... BM102: =BM118/BM$119 | BN102: 0 | BO102: =BO118/BO$119
A103: Total wafer revenue, % | C103: =SUM(C90:C92)+SUM(C95:C102) | D103: =SUM(D90:D92)+SUM(D95:D102) | E103: =SUM(E90:E92)+SUM(E95:E102) | F103: =SUM(F90:F92)+SUM(F95:F102) | G103: =SUM(G90:G92)+SUM(G95:G102) | H103: =SUM(H90:H92)+SUM(H95:H102) | I103: =SUM(I90:I92)+SUM(I95:I102) | J103: =SUM(J90:J92)+SUM(J95:J102) | ... AP103: =SUM(AP90:AP92)+SUM(AP95:AP102) | AQ103: =SUM(AQ89:AQ92)+SUM(AQ95:AQ102) | AR103: =SUM(AR89:AR92)+SUM(AR95:AR102) | AS103: =SUM(AS89:AS92)+SUM(AS95:AS102) | AT103: =SUM(AT89:AT92)+SUM(AT95:AT102) | AU103: =SUM(AU89:AU92)+SUM(AU95:AU102) | AV103: =SUM(AV89:AV92)+SUM(AV95:AV102) | AW103: =SUM(AW89:AW92)+SUM(AW95:AW102) | AX103: =SUM(AX89:AX92)+SUM(AX95:AX102) | ... BO103: =SUM(BO89:BO92)+SUM(BO95:BO102)
A105: 3-nanometer revenue, mm | BB105: 483.71 | BC105: 28994.752 | BD105: =BE105-SUM(BA105,BB105,BC105) | BE105: 108045.27 | BF105: 45448.96 | BG105: 90111.26 | BH105: 129922.71 | BI105: =BJ105-SUM(BF105,BG105,BH105) | BJ105: 459530.17 | BK105: 160180.19 | BL105: 187252.11 | BM105: 198608.33 | BN105: =BN$119*BN89 | BO105: =SUM(BK105,BL105,BM105,BN105)
A106: 5-nanometer revenue, mm | AN106: 25829.998 | AO106: =AP106-SUM(AL106,AM106,AN106) | AP106: 90934.485 | AQ106: 45613.201 | AR106: 61189.745 | AS106: 66930.524 | AT106: =AU106-SUM(AQ106,AR106,AS106) | AU106: 262327.36 | AV106: 86291.79 | AW106: 100729.72 | AX106: 148812.93 | AY106: =AZ106-SUM(AV106,AW106,AX106) | AZ106: 508689.88 | BA106: 139295.48 | BB106: 127824.56 | BC106: 173185.79 | BD106: =BE106-SUM(BA106,BB106,BC106) | BE106: 629300.39 | BF106: 190695.75 | BG106: 209567.53 | BH106: 205265.44 | BI106: =BJ106-SUM(BF106,BG106,BH106) | BJ106: 861318.86 | BK106: 254408.26 | BL106: 289669.22 | BM106: 323170.79 | BN106: =BN$119*BN90 | BO106: =SUM(BK106,BL106,BM106,BN106)
A107: 7-nanometer revenue, mm | C107: =C91*C$119 | D107: =D91*D$119 | E107: =E91*E$119 | F107: =F91*F$119 | G107: =G91*G$119 | L107: =L91*L$119 | Q107: =Q91*Q$119 | AA107: =AA91*AA$119 | AC107: 913.283 | AD107: 25336.977 | AE107: =AF107-SUM(AB107,AC107,AD107) | AF107: 81680.746 | AG107: 42208.718 | AH107: 43852.62 | AI107: 68541.892 | AJ107: =AK107-SUM(AG107,AH107,AI107) | AK107: 249548.14 | AL107: 95707.564 | AM107: 100229.08 | AN107: 109428.96 | AO107: =AP107-SUM(AL107,AM107,AN107) | AP107: 394836.96 | AQ107: 111021.38 | AR107: 101327.25 | AS107: 122606.05 | AT107: =AU107-SUM(AQ107,AR107,AS107) | AU107: 440383.1 | AV107: 132325.11 | AW107: 142919.24 | AX107: 142152.18 | AY107: =AZ107-SUM(AV107,AW107,AX107) | AZ107: 535153.76 | BA107: 88841.656 | BB107: 97189.205 | BC107: 78277.122 | BD107: =BE107-SUM(BA107,BB107,BC107) | BE107: 357247.36 | BF107: =100388.853+0.734 | BG107: 101106.64 | BH107: 110118.63 | BI107: =BJ107-SUM(BF107,BG107,BH107) | BJ107: 416790.3 | BK107: 108196.55 | BL107: 109051.36 | BM107: 117257.6 | BN107: =BN$119*BN91 | BO107: =SUM(BK107,BL107,BM107,BN107)
A108: 10-nanometer revenue, mm | C108: =C92*C$119 | D108: =D92*D$119 | E108: =E92*E$119 | F108: =F92*F$119 | G108: =G92*G$119 | L108: =L92*L$119 | Q108: =Q92*Q$119 | V108: =V92*V$119 | AA108: =AA92*AA$119 | AB108: 40853.554 | AC108: 26873.324 | AD108: 13476.325 | AE108: =AF108-SUM(AB108,AC108,AD108) | AF108: 96989.486 | AG108: 6981.206 | AH108: 6957.387 | AI108: 5077.177 | AJ108: =AK108-SUM(AG108,AH108,AI108) | AK108: 23266.355 | AL108: 1279.497 | AM108: 724.04 | AN108: 766.811 | AO108: =AP108-SUM(AL108,AM108,AN108) | AP108: 3403.151 | AQ108: 457.038 | AR108: 171.448 | AS108: 14.701 | AT108: =AU108-SUM(AQ108,AR108,AS108) | AU108: 659.989 | AV108: 3.145 | AW108: 10.212 | AX108: 4.48 | AY108: =AZ108-SUM(AV108,AW108,AX108) | AZ108: 24.871 | BA108: 11.515 | BB108: 5.386 | BC108: 3.5 | BD108: =BE108-SUM(BA108,BB108,BC108) | BE108: 23.332 | BN108: =BN$119*BN92 | BO108: =SUM(BK108,BL108,BM108,BN108)
A109: 16-nanometer revenue, mm | C109: =C95*C$119 | D109: =D95*D$119 | E109: =E95*E$119 | F109: =F95*F$119 | G109: =G95*G$119 | L109: =L95*L$119 | Q109: =Q95*Q$119 | V109: =V95*V$119 | AA109: =AA95*AA$119 | AB109: 47322.891 | AC109: 53330.347 | AD109: 58294.618 | AE109: =AF109-SUM(AB109,AC109,AD109) | AF109: 210989.03 | AG109: =30049.7+2763.835 | AH109: =48069.217+2740.789 | AI109: =54833.514+2030.871 | AJ109: =AK109-SUM(AG109,AH109,AI109) | AK109: =186700.858+9535.831 | AL109: =51419.279+1852.768 | AM109: =48709.06+2243.613 | AN109: =55726.975+2415.743 | AO109: =AP109-SUM(AL109,AM109,AN109) | AP109: =197959.003+8450.865 | AQ109: 45307.582 | AR109: 45342.157 | AS109: 48812.969 | AT109: =AU109-SUM(AQ109,AR109,AS109) | AU109: 191058.94 | AV109: 60867.539 | AW109: 64478.129 | AX109: 66299.632 | AY109: =AZ109-SUM(AV109,AW109,AX109) | AZ109: 258544.27 | BA109: 57616.256 | BB109: 44651.154 | BC109: 44470.242 | BD109: =BE109-SUM(BA109,BB109,BC109) | BE109: 191306.07 | BF109: 48472.211 | BG109: 52681.064 | BH109: 50836.959 | BI109: =BJ109-SUM(BF109,BG109,BH109) | BJ109: 202383.72 | BK109: 47336.847 | BL109: 56317.381 | BM109: 57307.151 | BN109: =BN$119*BN93 | BO109: =SUM(BK109,BL109,BM109,BN109)
A110: 20-nanometer revenue, mm | AQ110: 1201.403 | AR110: 1329.397 | AS110: 1203.472 | AT110: =AU110-SUM(AQ110,AR110,AS110) | AU110: 5668.752 | AV110: 2154.465 | AW110: 2129.924 | AX110: 2124.614 | AY110: =AZ110-SUM(AV110,AW110,AX110) | AZ110: 8853.291 | BA110: 3121.459 | BB110: 2800.296 | BC110: 2788.643 | BD110: =BE110-SUM(BA110,BB110,BC110) | BE110: 10359.042 | BF110: 1399.295 | BG110: 1077.092 | BH110: 671.1 | BI110: =BJ110-SUM(BF110,BG110,BH110) | BJ110: 4077.241 | BK110: 1182.574 | BL110: 633.072 | BM110: 1293.465 | BN110: =BN$119*BN94 | BO110: =SUM(BK110,BL110,BM110,BN110)
A111: 16/20 nanometer revenue, mm | AQ111: =SUM(AQ109:AQ110) | AR111: =SUM(AR109:AR110) | AS111: =SUM(AS109:AS110) | AT111: =SUM(AT109:AT110) | AU111: =SUM(AU109:AU110) | AV111: =SUM(AV109:AV110) | AW111: =SUM(AW109:AW110) | AX111: =SUM(AX109:AX110) | ... BO111: =SUM(BO109:BO110)
A112: 28-nanometer revenue, mm | C112: =C96*C$119 | D112: =D96*D$119 | E112: =E96*E$119 | F112: =F96*F$119 | G112: =G96*G$119 | L112: =L96*L$119 | Q112: =Q96*Q$119 | V112: =V96*V$119 | AA112: =AA96*AA$119 | AB112: 44156.689 | AC112: 47910.378 | AD112: 43739.621 | AE112: =AF112-SUM(AB112,AC112,AD112) | AF112: 178440.4 | AG112: 37142.36 | AH112: 37527.722 | AI112: 39855.841 | AJ112: =AK112-SUM(AG112,AH112,AI112) | AK112: 149578.72 | AL112: 37999.954 | AM112: 38479.201 | AN112: 37682.521 | AO112: =AP112-SUM(AL112,AM112,AN112) | AP112: 149367.73 | AQ112: 36664.175 | AR112: 37518.815 | AS112: 37739.348 | AT112: =AU112-SUM(AQ112,AR112,AS112) | AU112: 153066.56 | AV112: 47447.095 | AW112: 49533.008 | AX112: 52861.617 | AY112: =AZ112-SUM(AV112,AW112,AX112) | AZ112: 206611.95 | BA112: 52057.042 | BB112: 47590.123 | BC112: 47211.672 | BD112: =BE112-SUM(BA112,BB112,BC112) | BE112: 186924.92 | BF112: 43019.318 | BG112: 50557.516 | BH112: 47499.161 | BI112: =BJ112-SUM(BF112,BG112,BH112) | BJ112: 188155.01 | BK112: 52743.689 | BL112: 54583.088 | BM112: 59227.14 | BN112: =BN$119*BN96 | BO112: =SUM(BK112,BL112,BM112,BN112)
A113: 40/45-nanometer revenue, mm | C113: =C97*C$119 | D113: =D97*D$119 | E113: =E97*E$119 | F113: =F97*F$119 | G113: =G97*G$119 | L113: =L97*L$119 | Q113: =Q97*Q$119 | V113: =V97*V$119 | AA113: =AA97*AA$119 | AB113: 25240.238 | AC113: 24329.416 | AD113: 27035.128 | AE113: =AF113-SUM(AB113,AC113,AD113) | AF113: 101801.02 | AG113: 23286.88 | AH113: 22769.629 | AI113: 24624.309 | AJ113: =AK113-SUM(AG113,AH113,AI113) | AK113: 93366.285 | AL113: 26094.254 | AM113: 26050.83 | AN113: 26360.109 | AO113: =AP113-SUM(AL113,AM113,AN113) | AP113: 103176.54 | AQ113: 23190.957 | AR113: 23604.843 | AS113: 27233.876 | AT113: =AU113-SUM(AQ113,AR113,AS113) | AU113: 103413.64 | AV113: 34029.97 | AW113: 36441.273 | AX113: 37855.129 | AY113: =AZ113-SUM(AV113,AW113,AX113) | AZ113: 145546.24 | BA113: 32631.097 | BB113: 29537.533 | BC113: 29417.131 | BD113: =BE113-SUM(BA113,BB113,BC113) | BE113: 114667.36 | BF113: 27114.454 | BG113: 27586.077 | BH113: 29856.699 | BI113: =BJ113-SUM(BF113,BG113,BH113) | BJ113: 108468.21 | BK113: 20331.363 | BL113: 25199.803 | BM113: 26220.755 | BN113: =BN$119*BN97 | BO113: =SUM(BK113,BL113,BM113,BN113)
A114: 65-nanometer revenue, mm | C114: =C98*C$119 | D114: =D98*D$119 | E114: =E98*E$119 | F114: =F98*F$119 | G114: =G98*G$119 | L114: =L98*L$119 | Q114: =Q98*Q$119 | V114: =V98*V$119 | AA114: =AA98*AA$119 | AB114: 20445.219 | AC114: 18284.124 | AD114: 17833.438 | AE114: =AF114-SUM(AB114,AC114,AD114) | AF114: 76122.259 | AG114: 15828.535 | AH114: 16444.732 | AI114: 18785.556 | AJ114: =AK114-SUM(AG114,AH114,AI114) | AK114: 69250.008 | AL114: 15984.202 | AM114: 15576.755 | AN114: 15184.482 | AO114: =AP114-SUM(AL114,AM114,AN114) | AP114: 61226.671 | AQ114: 15623.227 | AR114: 16335.174 | AS114: 16189.697 | AT114: =AU114-SUM(AQ114,AR114,AS114) | AU114: 66467.903 | AV114: 21186.906 | AW114: 22537.887 | AX114: 25338.814 | AY114: =AZ114-SUM(AV114,AW114,AX114) | AZ114: 93288.614 | BA114: 27430.079 | BB114: 27994.41 | BC114: 26323.837 | BD114: =BE114-SUM(BA114,BB114,BC114) | BE114: 107425.4 | BF114: 21277.009 | BG114: 20728.246 | BH114: 24121.011 | BI114: =BJ114-SUM(BF114,BG114,BH114) | BJ114: 93120.068 | BK114: 26550.958 | BL114: 27827.833 | BM114: 32568.409 | BN114: =BN$119*BN98 | BO114: =SUM(BK114,BL114,BM114,BN114)
A115: 90-nanometer revenue, mm | C115: =C99*C$119 | D115: =D99*D$119 | E115: =E99*E$119 | F115: =F99*F$119 | G115: =G99*G$119 | L115: =L99*L$119 | Q115: =Q99*Q$119 | V115: =V99*V$119 | AA115: =AA99*AA$119 | AB115: 10038.144 | AC115: 10692.169 | AD115: 8633.488 | AE115: =AF115-SUM(AB115,AC115,AD115) | AF115: 36652.061 | AG115: 6300.002 | AH115: 5692.407 | AI115: 6346.472 | AJ115: =AK115-SUM(AG115,AH115,AI115) | AK115: 25624.251 | AL115: 7671.469 | AM115: 7628.781 | AN115: 7670.558 | AO115: =AP115-SUM(AL115,AM115,AN115) | AP115: 29380.358 | AQ115: 8724.44 | AR115: 9031.28 | AS115: 6998.277 | AT115: =AU115-SUM(AQ115,AR115,AS115) | AU115: 32260.288 | AV115: 9264.496 | AW115: 10513.833 | AX115: 11311.235 | AY115: =AZ115-SUM(AV115,AW115,AX115) | AZ115: 40184.169 | BA115: 8150.951 | BB115: 7394.845 | BC115: 5044.479 | BD115: =BE115-SUM(BA115,BB115,BC115) | BE115: 25642.01 | BF115: 5514.291 | BG115: 5591.099 | BH115: 5217.346 | BI115: =BJ115-SUM(BF115,BG115,BH115) | BJ115: 21509.306 | BK115: 5137.987 | BL115: 4980.173 | BM115: 5554.045 | BN115: =BN$119*BN99 | BO115: =SUM(BK115,BL115,BM115,BN115)
...

Sheet Guidance
B1: =MO.CompanyName
B2: Most Recent Period: | F2: =UL.MRQ
I4: Guidance | M4: Model | P4: Difference vs. Mid | S4: Update Log
B5: Type | D5: Item | E5: Item Name | F5: Fiscal Period | G5: Base Period | I5: Low | J5: High | K5: Mid | M5: Type | N5: Output | P5: Absolute | Q5: Relative | S5: Date | T5: Link
A6: 250 | B6: =IF(INDEX(MO_SNA_IsHistoricalPeriod,,MATCH(F6,MO_Common_ColumnHeader,0)),"Historical","Forward") | D6: =INDEX(INDIRECT(E6),0,COLUMN(MO_Common_Column_A)) | E6: MO_CFSum_Capex | F6: FY2026 | I6: -56000 | J6: -52000 | K6: =AVERAGE(I6:J6) | M6: =IF(INDEX(MO_SNA_IsHistoricalPeriod,,MATCH(F6,MO_Common_ColumnHeader,0)),"Actual","Estimate") | N6: =IFERROR(INDEX(INDIRECT(E6),0,MATCH(F6,MO_Common_ColumnHeader,0)),"N/A")*INDEX(MO_VA_FX_Average,0,MATCH(F6,MO_Common_ColumnHeader,0)) | P6: =IF(ISNUMBER(N6),N6-K6,"N/A") | Q6: =IFERROR(IF(ISNUMBER(N6),(N6-K6)/ABS(K6),"N/A"),"N/A") | S6: 46037 | T6: Transcript
A7: 249
A8: 248 | B8: =IF(INDEX(MO_SNA_IsHistoricalPeriod,,MATCH(F8,MO_Common_ColumnHeader,0)),"Historical","Forward") | D8: =INDEX(INDIRECT(E8),0,COLUMN(MO_Common_Column_A)) | E8: MO_RIS_REV | F8: Q1-2026 | I8: 34600 | J8: 35800 | K8: =AVERAGE(I8:J8) | M8: =IF(INDEX(MO_SNA_IsHistoricalPeriod,,MATCH(F8,MO_Common_ColumnHeader,0)),"Actual","Estimate") | N8: =IFERROR(INDEX(INDIRECT(E8),0,MATCH(F8,MO_Common_ColumnHeader,0)),"N/A")/INDEX(z_M2B13B0184_MO_OS_Weightedaverageforeignexchangedratereported,0,MATCH(F8,MO_Common_ColumnHeader,0)) | P8: =IF(ISNUMBER(N8),N8-K8,"N/A") | Q8: =IFERROR(IF(ISNUMBER(N8),(N8-K8)/ABS(K8),"N/A"),"N/A") | S8: 46037 | T8: Investor Presentation
A9: 247 | B9: =IF(INDEX(MO_SNA_IsHistoricalPeriod,,MATCH(F9,MO_Common_ColumnHeader,0)),"Historical","Forward") | D9: =INDEX(INDIRECT(E9),0,COLUMN(MO_Common_Column_A)) | E9: z_M2B13B0184_MO_OS_Weightedaverageforeignexchangedratereported | F9: Q1-2026 | I9: 31.6 | J9: 31.6 | K9: =AVERAGE(I9:J9) | M9: =IF(INDEX(MO_SNA_IsHistoricalPeriod,,MATCH(F9,MO_Common_ColumnHeader,0)),"Actual","Estimate") | N9: =IFERROR(INDEX(INDIRECT(E9),0,MATCH(F9,MO_Common_ColumnHeader,0)),"N/A") | P9: =IF(ISNUMBER(N9),N9-K9,"N/A") | Q9: =IFERROR(IF(ISNUMBER(N9),(N9-K9)/ABS(K9),"N/A"),"N/A") | S9: 46037 | T9: Investor Presentation
A10: 246 | B10: =IF(INDEX(MO_SNA_IsHistoricalPeriod,,MATCH(F10,MO_Common_ColumnHeader,0)),"Historical","Forward") | D10: =INDEX(INDIRECT(E10),0,COLUMN(MO_Common_Column_A)) | E10: MO_MA_GM | F10: Q1-2026 | I10: 0.63 | J10: 0.65 | K10: =AVERAGE(I10:J10) | M10: =IF(INDEX(MO_SNA_IsHistoricalPeriod,,MATCH(F10,MO_Common_ColumnHeader,0)),"Actual","Estimate") | N10: =IFERROR(INDEX(INDIRECT(E10),0,MATCH(F10,MO_Common_ColumnHeader,0)),"N/A") | P10: =IF(ISNUMBER(N10),N10-K10,"N/A") | Q10: =IFERROR(IF(ISNUMBER(N10),(N10-K10)/ABS(K10),"N/A"),"N/A") | S10: 46037 | T10: Investor Presentation
A11: 245 | B11: =IF(INDEX(MO_SNA_IsHistoricalPeriod,,MATCH(F11,MO_Common_ColumnHeader,0)),"Historical","Forward") | D11: Operating Profit Margin | F11: Q1-2026 | I11: 0.54 | J11: 0.56 | K11: =AVERAGE(I11:J11) | M11: =IF(INDEX(MO_SNA_IsHistoricalPeriod,,MATCH(F11,MO_Common_ColumnHeader,0)),"Actual","Estimate") | N11: =INDEX(MO_RIS_EBIT,0,MATCH(F11,MO_Common_ColumnHeader,0))/INDEX(MO_RIS_REV,0,MATCH(F11,MO_Common_ColumnHeader,0)) | P11: =IF(ISNUMBER(N11),N11-K11,"N/A") | Q11: =IFERROR(IF(ISNUMBER(N11),(N11-K11)/ABS(K11),"N/A"),"N/A") | S11: 46037 | T11: Investor Presentation
A12: 244
A13: 243 | B13: =IF(INDEX(MO_SNA_IsHistoricalPeriod,,MATCH(F13,MO_Common_ColumnHeader,0)),"Historical","Forward") | D13: =INDEX(INDIRECT(E13),0,COLUMN(MO_Common_Column_A)) | E13: MO_CFSum_Capex | F13: FY2025 | I13: -42000 | J13: -40000 | K13: =AVERAGE(I13:J13) | M13: =IF(INDEX(MO_SNA_IsHistoricalPeriod,,MATCH(F13,MO_Common_ColumnHeader,0)),"Actual","Estimate") | N13: =IFERROR(INDEX(INDIRECT(E13),0,MATCH(F13,MO_Common_ColumnHeader,0)),"N/A")*INDEX(MO_VA_FX_Average,0,MATCH(F13,MO_Common_ColumnHeader,0)) | P13: =IF(ISNUMBER(N13),N13-K13,"N/A") | Q13: =IFERROR(IF(ISNUMBER(N13),(N13-K13)/ABS(K13),"N/A"),"N/A") | S13: 45946 | T13: Transcript
A14: 242
A15: 241 | B15: =IF(INDEX(MO_SNA_IsHistoricalPeriod,,MATCH(F15,MO_Common_ColumnHeader,0)),"Historical","Forward") | D15: =INDEX(INDIRECT(E15),0,COLUMN(MO_Common_Column_A)) | E15: MO_RIS_REV | F15: Q4-2025 | I15: 32200 | J15: 33400 | K15: =AVERAGE(I15:J15) | M15: =IF(INDEX(MO_SNA_IsHistoricalPeriod,,MATCH(F15,MO_Common_ColumnHeader,0)),"Actual","Estimate") | N15: =IFERROR(INDEX(INDIRECT(E15),0,MATCH(F15,MO_Common_ColumnHeader,0)),"N/A")/INDEX(z_M2B13B0184_MO_OS_Weightedaverageforeignexchangedratereported,0,MATCH(F15,MO_Common_ColumnHeader,0)) | P15: =IF(ISNUMBER(N15),N15-K15,"N/A") | Q15: =IFERROR(IF(ISNUMBER(N15),(N15-K15)/ABS(K15),"N/A"),"N/A") | S15: 45946 | T15: Investor Presentation
A16: 240 | B16: =IF(INDEX(MO_SNA_IsHistoricalPeriod,,MATCH(F16,MO_Common_ColumnHeader,0)),"Historical","Forward") | D16: =INDEX(INDIRECT(E16),0,COLUMN(MO_Common_Column_A)) | E16: z_M2B13B0184_MO_OS_Weightedaverageforeignexchangedratereported | F16: Q4-2025 | I16: 30.6 | J16: 30.6 | K16: =AVERAGE(I16:J16) | M16: =IF(INDEX(MO_SNA_IsHistoricalPeriod,,MATCH(F16,MO_Common_ColumnHeader,0)),"Actual","Estimate") | N16: =IFERROR(INDEX(INDIRECT(E16),0,MATCH(F16,MO_Common_ColumnHeader,0)),"N/A") | P16: =IF(ISNUMBER(N16),N16-K16,"N/A") | Q16: =IFERROR(IF(ISNUMBER(N16),(N16-K16)/ABS(K16),"N/A"),"N/A") | S16: 45946 | T16: Investor Presentation
A17: 239 | B17: =IF(INDEX(MO_SNA_IsHistoricalPeriod,,MATCH(F17,MO_Common_ColumnHeader,0)),"Historical","Forward") | D17: =INDEX(INDIRECT(E17),0,COLUMN(MO_Common_Column_A)) | E17: MO_MA_GM | F17: Q4-2025 | I17: 0.59 | J17: 0.61 | K17: =AVERAGE(I17:J17) | M17: =IF(INDEX(MO_SNA_IsHistoricalPeriod,,MATCH(F17,MO_Common_ColumnHeader,0)),"Actual","Estimate") | N17: =IFERROR(INDEX(INDIRECT(E17),0,MATCH(F17,MO_Common_ColumnHeader,0)),"N/A") | P17: =IF(ISNUMBER(N17),N17-K17,"N/A") | Q17: =IFERROR(IF(ISNUMBER(N17),(N17-K17)/ABS(K17),"N/A"),"N/A") | S17: 45946 | T17: Investor Presentation
A18: 238 | B18: =IF(INDEX(MO_SNA_IsHistoricalPeriod,,MATCH(F18,MO_Common_ColumnHeader,0)),"Historical","Forward") | D18: Operating Profit Margin | F18: Q4-2025 | I18: 0.49 | J18: 0.51 | K18: =AVERAGE(I18:J18) | M18: =IF(INDEX(MO_SNA_IsHistoricalPeriod,,MATCH(F18,MO_Common_ColumnHeader,0)),"Actual","Estimate") | N18: =INDEX(MO_RIS_EBIT,0,MATCH(F18,MO_Common_ColumnHeader,0))/INDEX(MO_RIS_REV,0,MATCH(F18,MO_Common_ColumnHeader,0)) | P18: =IF(ISNUMBER(N18),N18-K18,"N/A") | Q18: =IFERROR(IF(ISNUMBER(N18),(N18-K18)/ABS(K18),"N/A"),"N/A") | S18: 45946 | T18: Investor Presentation
A19: 237
A20: 236 | B20: =IF(INDEX(MO_SNA_IsHistoricalPeriod,,MATCH(F20,MO_Common_ColumnHeader,0)),"Historical","Forward") | D20: Revenue growth in USD | E20: MO_RIS_REV | F20: FY2025 | G20: FY2024 | I20: 0.3 | J20: 0.3 | K20: =AVERAGE(I20:J20) | M20: =IF(INDEX(MO_SNA_IsHistoricalPeriod,,MATCH(F20,MO_Common_ColumnHeader,0)),"Actual","Estimate") | N20: =IFERROR(INDEX(INDIRECT(E20),0,MATCH(F20,MO_Common_ColumnHeader,0)),"N/A")/INDEX(z_M2B13B0184_MO_OS_Weightedaverageforeignexchangedratereported,0,MATCH(F20,MO_Common_ColumnHeader,0))/(IFERROR(INDEX(INDIRECT(E20),0,MATCH(G20,MO_Common_ColumnHeader,0)),"N/A")/INDEX(z_M2B13B0184_MO_OS_Weightedaverageforeignexchangedratereported,0,MATCH(G20,MO_Common_ColumnHeader,0)))-1 | P20: =IF(ISNUMBER(N20),N20-K20,"N/A") | Q20: =IFERROR(IF(ISNUMBER(N20),(N20-K20)/ABS(K20),"N/A"),"N/A") | S20: 45855 | T20: Investor Presentation
A21: 235 | B21: =IF(INDEX(MO_SNA_IsHistoricalPeriod,,MATCH(F21,MO_Common_ColumnHeader,0)),"Historical","Forward") | D21: =INDEX(INDIRECT(E21),0,COLUMN(MO_Common_Column_A)) | E21: MO_CFSum_Capex | F21: FY2025 | I21: -42000 | J21: -38000 | K21: =AVERAGE(I21:J21) | M21: =IF(INDEX(MO_SNA_IsHistoricalPeriod,,MATCH(F21,MO_Common_ColumnHeader,0)),"Actual","Estimate") | N21: =IFERROR(INDEX(INDIRECT(E21),0,MATCH(F21,MO_Common_ColumnHeader,0)),"N/A")*INDEX(MO_VA_FX_Average,0,MATCH(F21,MO_Common_ColumnHeader,0)) | P21: =IF(ISNUMBER(N21),N21-K21,"N/A") | Q21: =IFERROR(IF(ISNUMBER(N21),(N21-K21)/ABS(K21),"N/A"),"N/A") | S21: 45855 | T21: Transcript
A22: 234
A23: 233 | B23: =IF(INDEX(MO_SNA_IsHistoricalPeriod,,MATCH(F23,MO_Common_ColumnHeader,0)),"Historical","Forward") | D23: =INDEX(INDIRECT(E23),0,COLUMN(MO_Common_Column_A)) | E23: MO_RIS_REV | F23: Q3-2025 | I23: 31800 | J23: 33000 | K23: =AVERAGE(I23:J23) | M23: =IF(INDEX(MO_SNA_IsHistoricalPeriod,,MATCH(F23,MO_Common_ColumnHeader,0)),"Actual","Estimate") | N23: =IFERROR(INDEX(INDIRECT(E23),0,MATCH(F23,MO_Common_ColumnHeader,0)),"N/A")/INDEX(z_M2B13B0184_MO_OS_Weightedaverageforeignexchangedratereported,0,MATCH(F23,MO_Common_ColumnHeader,0)) | P23: =IF(ISNUMBER(N23),N23-K23,"N/A") | Q23: =IFERROR(IF(ISNUMBER(N23),(N23-K23)/ABS(K23),"N/A"),"N/A") | S23: 45855 | T23: Investor Presentation
A24: 232 | B24: =IF(INDEX(MO_SNA_IsHistoricalPeriod,,MATCH(F24,MO_Common_ColumnHeader,0)),"Historical","Forward") | D24: =INDEX(INDIRECT(E24),0,COLUMN(MO_Common_Column_A)) | E24: z_M2B13B0184_MO_OS_Weightedaverageforeignexchangedratereported | F24: Q3-2025 | I24: 29 | J24: 29 | K24: =AVERAGE(I24:J24) | M24: =IF(INDEX(MO_SNA_IsHistoricalPeriod,,MATCH(F24,MO_Common_ColumnHeader,0)),"Actual","Estimate") | N24: =IFERROR(INDEX(INDIRECT(E24),0,MATCH(F24,MO_Common_ColumnHeader,0)),"N/A") | P24: =IF(ISNUMBER(N24),N24-K24,"N/A") | Q24: =IFERROR(IF(ISNUMBER(N24),(N24-K24)/ABS(K24),"N/A"),"N/A") | S24: 45855 | T24: Investor Presentation
A25: 231 | B25: =IF(INDEX(MO_SNA_IsHistoricalPeriod,,MATCH(F25,MO_Common_ColumnHeader,0)),"Historical","Forward") | D25: =INDEX(INDIRECT(E25),0,COLUMN(MO_Common_Column_A)) | E25: MO_MA_GM | F25: Q3-2025 | I25: 0.555 | J25: 0.575 | K25: =AVERAGE(I25:J25) | M25: =IF(INDEX(MO_SNA_IsHistoricalPeriod,,MATCH(F25,MO_Common_ColumnHeader,0)),"Actual","Estimate") | N25: =IFERROR(INDEX(INDIRECT(E25),0,MATCH(F25,MO_Common_ColumnHeader,0)),"N/A") | P25: =IF(ISNUMBER(N25),N25-K25,"N/A") | Q25: =IFERROR(IF(ISNUMBER(N25),(N25-K25)/ABS(K25),"N/A"),"N/A") | S25: 45855 | T25: Investor Presentation
A26: 230 | B26: =IF(INDEX(MO_SNA_IsHistoricalPeriod,,MATCH(F26,MO_Common_ColumnHeader,0)),"Historical","Forward") | D26: Operating Profit Margin | F26: Q3-2025 | I26: 0.455 | J26: 0.475 | K26: =AVERAGE(I26:J26) | M26: =IF(INDEX(MO_SNA_IsHistoricalPeriod,,MATCH(F26,MO_Common_ColumnHeader,0)),"Actual","Estimate") | N26: =INDEX(MO_RIS_EBIT,0,MATCH(F26,MO_Common_ColumnHeader,0))/INDEX(MO_RIS_REV,0,MATCH(F26,MO_Common_ColumnHeader,0)) | P26: =IF(ISNUMBER(N26),N26-K26,"N/A") | Q26: =IFERROR(IF(ISNUMBER(N26),(N26-K26)/ABS(K26),"N/A"),"N/A") | S26: 45855 | T26: Investor Presentation
A27: 229
A28: 228 | B28: =IF(INDEX(MO_SNA_IsHistoricalPeriod,,MATCH(F28,MO_Common_ColumnHeader,0)),"Historical","Forward") | D28: Revenue growth in USD | E28: MO_RIS_REV | F28: FY2025 | G28: FY2024 | I28: 0.24 | J28: 0.26 | K28: =AVERAGE(I28:J28) | M28: =IF(INDEX(MO_SNA_IsHistoricalPeriod,,MATCH(F28,MO_Common_ColumnHeader,0)),"Actual","Estimate") | N28: =IFERROR(INDEX(INDIRECT(E28),0,MATCH(F28,MO_Common_ColumnHeader,0)),"N/A")/INDEX(z_M2B13B0184_MO_OS_Weightedaverageforeignexchangedratereported,0,MATCH(F28,MO_Common_ColumnHeader,0))/(IFERROR(INDEX(INDIRECT(E28),0,MATCH(G28,MO_Common_ColumnHeader,0)),"N/A")/INDEX(z_M2B13B0184_MO_OS_Weightedaverageforeignexchangedratereported,0,MATCH(G28,MO_Common_ColumnHeader,0)))-1 | P28: =IF(ISNUMBER(N28),N28-K28,"N/A") | Q28: =IFERROR(IF(ISNUMBER(N28),(N28-K28)/ABS(K28),"N/A"),"N/A") | S28: 45764 | T28: Investor Presentation
A29: 227 | B29: =IF(INDEX(MO_SNA_IsHistoricalPeriod,,MATCH(F29,MO_Common_ColumnHeader,0)),"Historical","Forward") | D29: =INDEX(INDIRECT(E29),0,COLUMN(MO_Common_Column_A)) | E29: MO_CFSum_Capex | F29: FY2025 | I29: -42000 | J29: -38000 | K29: =AVERAGE(I29:J29) | M29: =IF(INDEX(MO_SNA_IsHistoricalPeriod,,MATCH(F29,MO_Common_ColumnHeader,0)),"Actual","Estimate") | N29: =IFERROR(INDEX(INDIRECT(E29),0,MATCH(F29,MO_Common_ColumnHeader,0)),"N/A")*INDEX(MO_VA_FX_Average,0,MATCH(F29,MO_Common_ColumnHeader,0)) | P29: =IF(ISNUMBER(N29),N29-K29,"N/A") | Q29: =IFERROR(IF(ISNUMBER(N29),(N29-K29)/ABS(K29),"N/A"),"N/A") | S29: 45764 | T29: Transcript
A30: 226 | B30: =IF(INDEX(MO_SNA_IsHistoricalPeriod,,MATCH(F30,MO_Common_ColumnHeader,0)),"Historical","Forward") | D30: =INDEX(INDIRECT(E30),0,COLUMN(MO_Common_Column_A)) | E30: MO_RIS_TaxRate_Current | F30: FY2025 | I30: 0.16 | J30: 0.17 | K30: =AVERAGE(I30:J30) | M30: =IF(INDEX(MO_SNA_IsHistoricalPeriod,,MATCH(F30,MO_Common_ColumnHeader,0)),"Actual","Estimate") | N30: =IFERROR(INDEX(INDIRECT(E30),0,MATCH(F30,MO_Common_ColumnHeader,0)),"N/A") | P30: =IF(ISNUMBER(N30),N30-K30,"N/A") | Q30: =IFERROR(IF(ISNUMBER(N30),(N30-K30)/ABS(K30),"N/A"),"N/A") | S30: 45764 | T30: Transcript
A31: 225
A32: 224 | B32: =IF(INDEX(MO_SNA_IsHistoricalPeriod,,MATCH(F32,MO_Common_ColumnHeader,0)),"Historical","Forward") | D32: =INDEX(INDIRECT(E32),0,COLUMN(MO_Common_Column_A)) | E32: MO_RIS_REV | F32: Q2-2025 | I32: 28400 | J32: 29200 | K32: =AVERAGE(I32:J32) | M32: =IF(INDEX(MO_SNA_IsHistoricalPeriod,,MATCH(F32,MO_Common_ColumnHeader,0)),"Actual","Estimate") | N32: =IFERROR(INDEX(INDIRECT(E32),0,MATCH(F32,MO_Common_ColumnHeader,0)),"N/A")/INDEX(z_M2B13B0184_MO_OS_Weightedaverageforeignexchangedratereported,0,MATCH(F32,MO_Common_ColumnHeader,0)) | P32: =IF(ISNUMBER(N32),N32-K32,"N/A") | Q32: =IFERROR(IF(ISNUMBER(N32),(N32-K32)/ABS(K32),"N/A"),"N/A") | S32: 45764 | T32: Investor Presentation
A33: 223 | B33: =IF(INDEX(MO_SNA_IsHistoricalPeriod,,MATCH(F33,MO_Common_ColumnHeader,0)),"Historical","Forward") | D33: =INDEX(INDIRECT(E33),0,COLUMN(MO_Common_Column_A)) | E33: z_M2B13B0184_MO_OS_Weightedaverageforeignexchangedratereported | F33: Q2-2025 | I33: 32.5 | J33: 32.5 | K33: =AVERAGE(I33:J33) | M33: =IF(INDEX(MO_SNA_IsHistoricalPeriod,,MATCH(F33,MO_Common_ColumnHeader,0)),"Actual","Estimate") | N33: =IFERROR(INDEX(INDIRECT(E33),0,MATCH(F33,MO_Common_ColumnHeader,0)),"N/A") | P33: =IF(ISNUMBER(N33),N33-K33,"N/A") | Q33: =IFERROR(IF(ISNUMBER(N33),(N33-K33)/ABS(K33),"N/A"),"N/A") | S33: 45764 | T33: Investor Presentation
A34: 222 | B34: =IF(INDEX(MO_SNA_IsHistoricalPeriod,,MATCH(F34,MO_Common_ColumnHeader,0)),"Historical","Forward") | D34: =INDEX(INDIRECT(E34),0,COLUMN(MO_Common_Column_A)) | E34: MO_MA_GM | F34: Q2-2025 | I34: 0.57 | J34: 0.59 | K34: =AVERAGE(I34:J34) | M34: =IF(INDEX(MO_SNA_IsHistoricalPeriod,,MATCH(F34,MO_Common_ColumnHeader,0)),"Actual","Estimate") | N34: =IFERROR(INDEX(INDIRECT(E34),0,MATCH(F34,MO_Common_ColumnHeader,0)),"N/A") | P34: =IF(ISNUMBER(N34),N34-K34,"N/A") | Q34: =IFERROR(IF(ISNUMBER(N34),(N34-K34)/ABS(K34),"N/A"),"N/A") | S34: 45764 | T34: Investor Presentation
A35: 221 | B35: =IF(INDEX(MO_SNA_IsHistoricalPeriod,,MATCH(F35,MO_Common_ColumnHeader,0)),"Historical","Forward") | D35: Operating Profit Margin | F35: Q2-2025 | I35: 0.47 | J35: 0.49 | K35: =AVERAGE(I35:J35) | M35: =IF(INDEX(MO_SNA_IsHistoricalPeriod,,MATCH(F35,MO_Common_ColumnHeader,0)),"Actual","Estimate") | N35: =INDEX(MO_RIS_EBIT,0,MATCH(F35,MO_Common_ColumnHeader,0))/INDEX(MO_RIS_REV,0,MATCH(F35,MO_Common_ColumnHeader,0)) | P35: =IF(ISNUMBER(N35),N35-K35,"N/A") | Q35: =IFERROR(IF(ISNUMBER(N35),(N35-K35)/ABS(K35),"N/A"),"N/A") | S35: 45764 | T35: Investor Presentation
A36: 220 | B36: =IF(INDEX(MO_SNA_IsHistoricalPeriod,,MATCH(F36,MO_Common_ColumnHeader,0)),"Historical","Forward") | D36: =INDEX(INDIRECT(E36),0,COLUMN(MO_Common_Column_A)) | E36: MO_RIS_TaxRate_Current | F36: Q2-2025 | I36: 0.2 | J36: 0.2 | K36: =AVERAGE(I36:J36) | M36: =IF(INDEX(MO_SNA_IsHistoricalPeriod,,MATCH(F36,MO_Common_ColumnHeader,0)),"Actual","Estimate") | N36: =IFERROR(INDEX(INDIRECT(E36),0,MATCH(F36,MO_Common_ColumnHeader,0)),"N/A") | P36: =IF(ISNUMBER(N36),N36-K36,"N/A") | Q36: =IFERROR(IF(ISNUMBER(N36),(N36-K36)/ABS(K36),"N/A"),"N/A") | S36: 45764 | T36: Transcript
A37: 219
A38: 218 | B38: =IF(INDEX(MO_SNA_IsHistoricalPeriod,,MATCH(F38,MO_Common_ColumnHeader,0)),"Historical","Forward") | D38: =INDEX(INDIRECT(E38),0,COLUMN(MO_Common_Column_A)) | E38: MO_CFSum_Capex | F38: FY2025 | I38: -42000 | J38: -38000 | K38: =AVERAGE(I38:J38) | M38: =IF(INDEX(MO_SNA_IsHistoricalPeriod,,MATCH(F38,MO_Common_ColumnHeader,0)),"Actual","Estimate") | N38: =IFERROR(INDEX(INDIRECT(E38),0,MATCH(F38,MO_Common_ColumnHeader,0)),"N/A")*INDEX(MO_VA_FX_Average,0,MATCH(F38,MO_Common_ColumnHeader,0)) | P38: =IF(ISNUMBER(N38),N38-K38,"N/A") | Q38: =IFERROR(IF(ISNUMBER(N38),(N38-K38)/ABS(K38),"N/A"),"N/A") | S38: 45673 | T38: Transcript
A39: 217 | B39: =IF(INDEX(MO_SNA_IsHistoricalPeriod,,MATCH(F39,MO_Common_ColumnHeader,0)),"Historical","Forward") | D39: =INDEX(INDIRECT(E39),0,COLUMN(MO_Common_Column_A)) | E39: MO_RIS_TaxRate_Current | F39: FY2025 | I39: 0.16 | J39: 0.17 | K39: =AVERAGE(I39:J39) | M39: =IF(INDEX(MO_SNA_IsHistoricalPeriod,,MATCH(F39,MO_Common_ColumnHeader,0)),"Actual","Estimate") | N39: =IFERROR(INDEX(INDIRECT(E39),0,MATCH(F39,MO_Common_ColumnHeader,0)),"N/A") | P39: =IF(ISNUMBER(N39),N39-K39,"N/A") | Q39: =IFERROR(IF(ISNUMBER(N39),(N39-K39)/ABS(K39),"N/A"),"N/A") | S39: 45673 | T39: Transcript
A40: 216
A41: 215 | B41: =IF(INDEX(MO_SNA_IsHistoricalPeriod,,MATCH(F41,MO_Common_ColumnHeader,0)),"Historical","Forward") | D41: =INDEX(INDIRECT(E41),0,COLUMN(MO_Common_Column_A)) | E41: MO_RIS_REV | F41: Q1-2025 | I41: 25000 | J41: 25800 | K41: =AVERAGE(I41:J41) | M41: =IF(INDEX(MO_SNA_IsHistoricalPeriod,,MATCH(F41,MO_Common_ColumnHeader,0)),"Actual","Estimate") | N41: =IFERROR(INDEX(INDIRECT(E41),0,MATCH(F41,MO_Common_ColumnHeader,0)),"N/A")/INDEX(z_M2B13B0184_MO_OS_Weightedaverageforeignexchangedratereported,0,MATCH(F41,MO_Common_ColumnHeader,0)) | P41: =IF(ISNUMBER(N41),N41-K41,"N/A") | Q41: =IFERROR(IF(ISNUMBER(N41),(N41-K41)/ABS(K41),"N/A"),"N/A") | S41: 45673 | T41: Investor Presentation
A42: 214 | B42: =IF(INDEX(MO_SNA_IsHistoricalPeriod,,MATCH(F42,MO_Common_ColumnHeader,0)),"Historical","Forward") | D42: =INDEX(INDIRECT(E42),0,COLUMN(MO_Common_Column_A)) | E42: z_M2B13B0184_MO_OS_Weightedaverageforeignexchangedratereported | F42: Q1-2025 | I42: 32.8 | J42: 32.8 | K42: =AVERAGE(I42:J42) | M42: =IF(INDEX(MO_SNA_IsHistoricalPeriod,,MATCH(F42,MO_Common_ColumnHeader,0)),"Actual","Estimate") | N42: =IFERROR(INDEX(INDIRECT(E42),0,MATCH(F42,MO_Common_ColumnHeader,0)),"N/A") | P42: =IF(ISNUMBER(N42),N42-K42,"N/A") | Q42: =IFERROR(IF(ISNUMBER(N42),(N42-K42)/ABS(K42),"N/A"),"N/A") | S42: 45673 | T42: Investor Presentation
A43: 213 | B43: =IF(INDEX(MO_SNA_IsHistoricalPeriod,,MATCH(F43,MO_Common_ColumnHeader,0)),"Historical","Forward") | D43: =INDEX(INDIRECT(E43),0,COLUMN(MO_Common_Column_A)) | E43: MO_MA_GM | F43: Q1-2025 | I43: 0.57 | J43: 0.59 | K43: =AVERAGE(I43:J43) | M43: =IF(INDEX(MO_SNA_IsHistoricalPeriod,,MATCH(F43,MO_Common_ColumnHeader,0)),"Actual","Estimate") | N43: =IFERROR(INDEX(INDIRECT(E43),0,MATCH(F43,MO_Common_ColumnHeader,0)),"N/A") | P43: =IF(ISNUMBER(N43),N43-K43,"N/A") | Q43: =IFERROR(IF(ISNUMBER(N43),(N43-K43)/ABS(K43),"N/A"),"N/A") | S43: 45673 | T43: Investor Presentation
A44: 212 | B44: =IF(INDEX(MO_SNA_IsHistoricalPeriod,,MATCH(F44,MO_Common_ColumnHeader,0)),"Historical","Forward") | D44: Operating Profit Margin | F44: Q1-2025 | I44: 0.465 | J44: 0.485 | K44: =AVERAGE(I44:J44) | M44: =IF(INDEX(MO_SNA_IsHistoricalPeriod,,MATCH(F44,MO_Common_ColumnHeader,0)),"Actual","Estimate") | N44: =INDEX(MO_RIS_EBIT,0,MATCH(F44,MO_Common_ColumnHeader,0))/INDEX(MO_RIS_REV,0,MATCH(F44,MO_Common_ColumnHeader,0)) | P44: =IF(ISNUMBER(N44),N44-K44,"N/A") | Q44: =IFERROR(IF(ISNUMBER(N44),(N44-K44)/ABS(K44),"N/A"),"N/A") | S44: 45673 | T44: Investor Presentation
A45: 211
A46: 210 | B46: =IF(INDEX(MO_SNA_IsHistoricalPeriod,,MATCH(F46,MO_Common_ColumnHeader,0)),"Historical","Forward") | D46: =INDEX(INDIRECT(E46),0,COLUMN(MO_Common_Column_A)) | E46: MO_CFSum_Capex | F46: FY2024 | I46: -30000 | J46: -30000 | K46: =AVERAGE(I46:J46) | M46: =IF(INDEX(MO_SNA_IsHistoricalPeriod,,MATCH(F46,MO_Common_ColumnHeader,0)),"Actual","Estimate") | N46: =IFERROR(INDEX(INDIRECT(E46),0,MATCH(F46,MO_Common_ColumnHeader,0)),"N/A")*INDEX(MO_VA_FX_Average,0,MATCH(F46,MO_Common_ColumnHeader,0)) | P46: =IF(ISNUMBER(N46),N46-K46,"N/A") | Q46: =IFERROR(IF(ISNUMBER(N46),(N46-K46)/ABS(K46),"N/A"),"N/A") | S46: 45582 | T46: Transcript
A47: 209
A48: 208 | B48: =IF(INDEX(MO_SNA_IsHistoricalPeriod,,MATCH(F48,MO_Common_ColumnHeader,0)),"Historical","Forward") | D48: =INDEX(INDIRECT(E48),0,COLUMN(MO_Common_Column_A)) | E48: MO_RIS_REV | F48: Q4-2024 | I48: 26100 | J48: 26900 | K48: =AVERAGE(I48:J48) | M48: =IF(INDEX(MO_SNA_IsHistoricalPeriod,,MATCH(F48,MO_Common_ColumnHeader,0)),"Actual","Estimate") | N48: =IFERROR(INDEX(INDIRECT(E48),0,MATCH(F48,MO_Common_ColumnHeader,0)),"N/A")/INDEX(z_M2B13B0184_MO_OS_Weightedaverageforeignexchangedratereported,0,MATCH(F48,MO_Common_ColumnHeader,0)) | P48: =IF(ISNUMBER(N48),N48-K48,"N/A") | Q48: =IFERROR(IF(ISNUMBER(N48),(N48-K48)/ABS(K48),"N/A"),"N/A") | S48: 45582 | T48: Investor Presentation
A49: 207 | B49: =IF(INDEX(MO_SNA_IsHistoricalPeriod,,MATCH(F49,MO_Common_ColumnHeader,0)),"Historical","Forward") | D49: =INDEX(INDIRECT(E49),0,COLUMN(MO_Common_Column_A)) | E49: z_M2B13B0184_MO_OS_Weightedaverageforeignexchangedratereported | F49: Q4-2024 | I49: 32 | J49: 32 | K49: =AVERAGE(I49:J49) | M49: =IF(INDEX(MO_SNA_IsHistoricalPeriod,,MATCH(F49,MO_Common_ColumnHeader,0)),"Actual","Estimate") | N49: =IFERROR(INDEX(INDIRECT(E49),0,MATCH(F49,MO_Common_ColumnHeader,0)),"N/A") | P49: =IF(ISNUMBER(N49),N49-K49,"N/A") | Q49: =IFERROR(IF(ISNUMBER(N49),(N49-K49)/ABS(K49),"N/A"),"N/A") | S49: 45582 | T49: Investor Presentation
A50: 206 | B50: =IF(INDEX(MO_SNA_IsHistoricalPeriod,,MATCH(F50,MO_Common_ColumnHeader,0)),"Historical","Forward") | D50: =INDEX(INDIRECT(E50),0,COLUMN(MO_Common_Column_A)) | E50: MO_MA_GM | F50: Q4-2024 | I50: 0.57 | J50: 0.59 | K50: =AVERAGE(I50:J50) | M50: =IF(INDEX(MO_SNA_IsHistoricalPeriod,,MATCH(F50,MO_Common_ColumnHeader,0)),"Actual","Estimate") | N50: =IFERROR(INDEX(INDIRECT(E50),0,MATCH(F50,MO_Common_ColumnHeader,0)),"N/A") | P50: =IF(ISNUMBER(N50),N50-K50,"N/A") | Q50: =IFERROR(IF(ISNUMBER(N50),(N50-K50)/ABS(K50),"N/A"),"N/A") | S50: 45582 | T50: Investor Presentation
A51: 205 | B51: =IF(INDEX(MO_SNA_IsHistoricalPeriod,,MATCH(F51,MO_Common_ColumnHeader,0)),"Historical","Forward") | D51: Operating Profit Margin | F51: Q4-2024 | I51: 0.465 | J51: 0.485 | K51: =AVERAGE(I51:J51) | M51: =IF(INDEX(MO_SNA_IsHistoricalPeriod,,MATCH(F51,MO_Common_ColumnHeader,0)),"Actual","Estimate") | N51: =INDEX(MO_RIS_EBIT,0,MATCH(F51,MO_Common_ColumnHeader,0))/INDEX(MO_RIS_REV,0,MATCH(F51,MO_Common_ColumnHeader,0)) | P51: =IF(ISNUMBER(N51),N51-K51,"N/A") | Q51: =IFERROR(IF(ISNUMBER(N51),(N51-K51)/ABS(K51),"N/A"),"N/A") | S51: 45582 | T51: Investor Presentation
A52: 204
A53: 203 | B53: =IF(INDEX(MO_SNA_IsHistoricalPeriod,,MATCH(F53,MO_Common_ColumnHeader,0)),"Historical","Forward") | D53: =INDEX(INDIRECT(E53),0,COLUMN(MO_Common_Column_A)) | E53: MO_CFSum_Capex | F53: FY2024 | I53: -32000 | J53: -30000 | K53: =AVERAGE(I53:J53) | M53: =IF(INDEX(MO_SNA_IsHistoricalPeriod,,MATCH(F53,MO_Common_ColumnHeader,0)),"Actual","Estimate") | N53: =IFERROR(INDEX(INDIRECT(E53),0,MATCH(F53,MO_Common_ColumnHeader,0)),"N/A")*INDEX(MO_VA_FX_Average,0,MATCH(F53,MO_Common_ColumnHeader,0)) | P53: =IF(ISNUMBER(N53),N53-K53,"N/A") | Q53: =IFERROR(IF(ISNUMBER(N53),(N53-K53)/ABS(K53),"N/A"),"N/A") | S53: 45491 | T53: Transcript
A54: 202
A55: 201 | B55: =IF(INDEX(MO_SNA_IsHistoricalPeriod,,MATCH(F55,MO_Common_ColumnHeader,0)),"Historical","Forward") | D55: =INDEX(INDIRECT(E55),0,COLUMN(MO_Common_Column_A)) | E55: MO_RIS_REV | F55: Q3-2024 | I55: 22400 | J55: 23200 | K55: =AVERAGE(I55:J55) | M55: =IF(INDEX(MO_SNA_IsHistoricalPeriod,,MATCH(F55,MO_Common_ColumnHeader,0)),"Actual","Estimate") | N55: =IFERROR(INDEX(INDIRECT(E55),0,MATCH(F55,MO_Common_ColumnHeader,0)),"N/A")/INDEX(z_M2B13B0184_MO_OS_Weightedaverageforeignexchangedratereported,0,MATCH(F55,MO_Common_ColumnHeader,0)) | P55: =IF(ISNUMBER(N55),N55-K55,"N/A") | Q55: =IFERROR(IF(ISNUMBER(N55),(N55-K55)/ABS(K55),"N/A"),"N/A") | S55: 45491 | T55: Investor Presentation
A56: 200 | B56: =IF(INDEX(MO_SNA_IsHistoricalPeriod,,MATCH(F56,MO_Common_ColumnHeader,0)),"Historical","Forward") | D56: =INDEX(INDIRECT(E56),0,COLUMN(MO_Common_Column_A)) | E56: z_M2B13B0184_MO_OS_Weightedaverageforeignexchangedratereported | F56: Q3-2024 | I56: 32.5 | J56: 32.5 | K56: =AVERAGE(I56:J56) | M56: =IF(INDEX(MO_SNA_IsHistoricalPeriod,,MATCH(F56,MO_Common_ColumnHeader,0)),"Actual","Estimate") | N56: =IFERROR(INDEX(INDIRECT(E56),0,MATCH(F56,MO_Common_ColumnHeader,0)),"N/A") | P56: =IF(ISNUMBER(N56),N56-K56,"N/A") | Q56: =IFERROR(IF(ISNUMBER(N56),(N56-K56)/ABS(K56),"N/A"),"N/A") | S56: 45491 | T56: Investor Presentation
A57: 199 | B57: =IF(INDEX(MO_SNA_IsHistoricalPeriod,,MATCH(F57,MO_Common_ColumnHeader,0)),"Historical","Forward") | D57: =INDEX(INDIRECT(E57),0,COLUMN(MO_Common_Column_A)) | E57: MO_MA_GM | F57: Q3-2024 | I57: 0.535 | J57: 0.555 | K57: =AVERAGE(I57:J57) | M57: =IF(INDEX(MO_SNA_IsHistoricalPeriod,,MATCH(F57,MO_Common_ColumnHeader,0)),"Actual","Estimate") | N57: =IFERROR(INDEX(INDIRECT(E57),0,MATCH(F57,MO_Common_ColumnHeader,0)),"N/A") | P57: =IF(ISNUMBER(N57),N57-K57,"N/A") | Q57: =IFERROR(IF(ISNUMBER(N57),(N57-K57)/ABS(K57),"N/A"),"N/A") | S57: 45491 | T57: Investor Presentation
A58: 198 | B58: =IF(INDEX(MO_SNA_IsHistoricalPeriod,,MATCH(F58,MO_Common_ColumnHeader,0)),"Historical","Forward") | D58: Operating Profit Margin | F58: Q3-2024 | I58: 0.425 | J58: 0.445 | K58: =AVERAGE(I58:J58) | M58: =IF(INDEX(MO_SNA_IsHistoricalPeriod,,MATCH(F58,MO_Common_ColumnHeader,0)),"Actual","Estimate") | N58: =INDEX(MO_RIS_EBIT,0,MATCH(F58,MO_Common_ColumnHeader,0))/INDEX(MO_RIS_REV,0,MATCH(F58,MO_Common_ColumnHeader,0)) | P58: =IF(ISNUMBER(N58),N58-K58,"N/A") | Q58: =IFERROR(IF(ISNUMBER(N58),(N58-K58)/ABS(K58),"N/A"),"N/A") | S58: 45491 | T58: Investor Presentation
A59: 197
A60: 196 | B60: =IF(INDEX(MO_SNA_IsHistoricalPeriod,,MATCH(F60,MO_Common_ColumnHeader,0)),"Historical","Forward") | D60: =INDEX(INDIRECT(E60),0,COLUMN(MO_Common_Column_A)) | E60: MO_CFSum_Capex | F60: FY2024 | I60: -32000 | J60: -28000 | K60: =AVERAGE(I60:J60) | M60: =IF(INDEX(MO_SNA_IsHistoricalPeriod,,MATCH(F60,MO_Common_ColumnHeader,0)),"Actual","Estimate") | N60: =IFERROR(INDEX(INDIRECT(E60),0,MATCH(F60,MO_Common_ColumnHeader,0)),"N/A")*INDEX(MO_VA_FX_Average,0,MATCH(F60,MO_Common_ColumnHeader,0)) | P60: =IF(ISNUMBER(N60),N60-K60,"N/A") | Q60: =IFERROR(IF(ISNUMBER(N60),(N60-K60)/ABS(K60),"N/A"),"N/A") | S60: 45400 | T60: Transcript
A61: 195 | B61: =IF(INDEX(MO_SNA_IsHistoricalPeriod,,MATCH(F61,MO_Common_ColumnHeader,0)),"Historical","Forward") | D61: =INDEX(INDIRECT(E61),0,COLUMN(MO_Common_Column_A)) | E61: MO_RIS_TaxRate_Current | F61: FY2024 | I61: 0.15 | J61: 0.16 | K61: =AVERAGE(I61:J61) | M61: =IF(INDEX(MO_SNA_IsHistoricalPeriod,,MATCH(F61,MO_Common_ColumnHeader,0)),"Actual","Estimate") | N61: =IFERROR(INDEX(INDIRECT(E61),0,MATCH(F61,MO_Common_ColumnHeader,0)),"N/A") | P61: =IF(ISNUMBER(N61),N61-K61,"N/A") | Q61: =IFERROR(IF(ISNUMBER(N61),(N61-K61)/ABS(K61),"N/A"),"N/A") | S61: 45400 | T61: Transcript
A62: 194
A63: 193 | B63: =IF(INDEX(MO_SNA_IsHistoricalPeriod,,MATCH(F63,MO_Common_ColumnHeader,0)),"Historical","Forward") | D63: =INDEX(INDIRECT(E63),0,COLUMN(MO_Common_Column_A)) | E63: MO_RIS_REV | F63: Q2-2024 | I63: 19600 | J63: 20400 | K63: =AVERAGE(I63:J63) | M63: =IF(INDEX(MO_SNA_IsHistoricalPeriod,,MATCH(F63,MO_Common_ColumnHeader,0)),"Actual","Estimate") | N63: =IFERROR(INDEX(INDIRECT(E63),0,MATCH(F63,MO_Common_ColumnHeader,0)),"N/A")/INDEX(z_M2B13B0184_MO_OS_Weightedaverageforeignexchangedratereported,0,MATCH(F63,MO_Common_ColumnHeader,0)) | P63: =IF(ISNUMBER(N63),N63-K63,"N/A") | Q63: =IFERROR(IF(ISNUMBER(N63),(N63-K63)/ABS(K63),"N/A"),"N/A") | S63: 45400 | T63: Investor Presentation
A64: 192 | B64: =IF(INDEX(MO_SNA_IsHistoricalPeriod,,MATCH(F64,MO_Common_ColumnHeader,0)),"Historical","Forward") | D64: =INDEX(INDIRECT(E64),0,COLUMN(MO_Common_Column_A)) | E64: z_M2B13B0184_MO_OS_Weightedaverageforeignexchangedratereported | F64: Q2-2024 | I64: 32.3 | J64: 32.3 | K64: =AVERAGE(I64:J64) | M64: =IF(INDEX(MO_SNA_IsHistoricalPeriod,,MATCH(F64,MO_Common_ColumnHeader,0)),"Actual","Estimate") | N64: =IFERROR(INDEX(INDIRECT(E64),0,MATCH(F64,MO_Common_ColumnHeader,0)),"N/A") | P64: =IF(ISNUMBER(N64),N64-K64,"N/A") | Q64: =IFERROR(IF(ISNUMBER(N64),(N64-K64)/ABS(K64),"N/A"),"N/A") | S64: 45400 | T64: Investor Presentation
A65: 191 | B65: =IF(INDEX(MO_SNA_IsHistoricalPeriod,,MATCH(F65,MO_Common_ColumnHeader,0)),"Historical","Forward") | D65: =INDEX(INDIRECT(E65),0,COLUMN(MO_Common_Column_A)) | E65: MO_MA_GM | F65: Q2-2024 | I65: 0.51 | J65: 0.53 | K65: =AVERAGE(I65:J65) | M65: =IF(INDEX(MO_SNA_IsHistoricalPeriod,,MATCH(F65,MO_Common_ColumnHeader,0)),"Actual","Estimate") | N65: =IFERROR(INDEX(INDIRECT(E65),0,MATCH(F65,MO_Common_ColumnHeader,0)),"N/A") | P65: =IF(ISNUMBER(N65),N65-K65,"N/A") | Q65: =IFERROR(IF(ISNUMBER(N65),(N65-K65)/ABS(K65),"N/A"),"N/A") | S65: 45400 | T65: Investor Presentation
A66: 190 | B66: =IF(INDEX(MO_SNA_IsHistoricalPeriod,,MATCH(F66,MO_Common_ColumnHeader,0)),"Historical","Forward") | D66: Operating Profit Margin | F66: Q2-2024 | I66: 0.4 | J66: 0.42 | K66: =AVERAGE(I66:J66) | M66: =IF(INDEX(MO_SNA_IsHistoricalPeriod,,MATCH(F66,MO_Common_ColumnHeader,0)),"Actual","Estimate") | N66: =INDEX(MO_RIS_EBIT,0,MATCH(F66,MO_Common_ColumnHeader,0))/INDEX(MO_RIS_REV,0,MATCH(F66,MO_Common_ColumnHeader,0)) | P66: =IF(ISNUMBER(N66),N66-K66,"N/A") | Q66: =IFERROR(IF(ISNUMBER(N66),(N66-K66)/ABS(K66),"N/A"),"N/A") | S66: 45400 | T66: Investor Presentation
A67: 189 | B67: =IF(INDEX(MO_SNA_IsHistoricalPeriod,,MATCH(F67,MO_Common_ColumnHeader,0)),"Historical","Forward") | D67: =INDEX(INDIRECT(E67),0,COLUMN(MO_Common_Column_A)) | E67: MO_RIS_TaxRate_Current | F67: Q2-2024 | I67: 0.19 | J67: 0.19 | K67: =AVERAGE(I67:J67) | M67: =IF(INDEX(MO_SNA_IsHistoricalPeriod,,MATCH(F67,MO_Common_ColumnHeader,0)),"Actual","Estimate") | N67: =IFERROR(INDEX(INDIRECT(E67),0,MATCH(F67,MO_Common_ColumnHeader,0)),"N/A") | P67: =IF(ISNUMBER(N67),N67-K67,"N/A") | Q67: =IFERROR(IF(ISNUMBER(N67),(N67-K67)/ABS(K67),"N/A"),"N/A") | S67: 45400 | T67: Transcript
A68: 188
A69: 187 | B69: =IF(INDEX(MO_SNA_IsHistoricalPeriod,,MATCH(F69,MO_Common_ColumnHeader,0)),"Historical","Forward") | D69: =INDEX(INDIRECT(E69),0,COLUMN(MO_Common_Column_A)) | E69: MO_CFSum_Capex | F69: FY2024 | I69: -32000 | J69: -28000 | K69: =AVERAGE(I69:J69) | M69: =IF(INDEX(MO_SNA_IsHistoricalPeriod,,MATCH(F69,MO_Common_ColumnHeader,0)),"Actual","Estimate") | N69: =IFERROR(INDEX(INDIRECT(E69),0,MATCH(F69,MO_Common_ColumnHeader,0)),"N/A")*INDEX(MO_VA_FX_Average,0,MATCH(F69,MO_Common_ColumnHeader,0)) | P69: =IF(ISNUMBER(N69),N69-K69,"N/A") | Q69: =IFERROR(IF(ISNUMBER(N69),(N69-K69)/ABS(K69),"N/A"),"N/A") | S69: 45309 | T69: Transcript
A70: 186
A71: 185 | B71: =IF(INDEX(MO_SNA_IsHistoricalPeriod,,MATCH(F71,MO_Common_ColumnHeader,0)),"Historical","Forward") | D71: =INDEX(INDIRECT(E71),0,COLUMN(MO_Common_Column_A)) | E71: MO_RIS_REV | F71: Q1-2024 | I71: 18000 | J71: 18800 | K71: =AVERAGE(I71:J71) | M71: =IF(INDEX(MO_SNA_IsHistoricalPeriod,,MATCH(F71,MO_Common_ColumnHeader,0)),"Actual","Estimate") | N71: =IFERROR(INDEX(INDIRECT(E71),0,MATCH(F71,MO_Common_ColumnHeader,0)),"N/A")/31.1 | P71: =IF(ISNUMBER(N71),N71-K71,"N/A") | Q71: =IFERROR(IF(ISNUMBER(N71),(N71-K71)/ABS(K71),"N/A"),"N/A") | S71: 45309 | T71: Investor Presentation
A72: 184 | B72: =IF(INDEX(MO_SNA_IsHistoricalPeriod,,MATCH(F72,MO_Common_ColumnHeader,0)),"Historical","Forward") | D72: =INDEX(INDIRECT(E72),0,COLUMN(MO_Common_Column_A)) | E72: z_M2B13B0184_MO_OS_Weightedaverageforeignexchangedratereported | F72: Q1-2024 | I72: 31.1 | J72: 31.1 | K72: =AVERAGE(I72:J72) | M72: =IF(INDEX(MO_SNA_IsHistoricalPeriod,,MATCH(F72,MO_Common_ColumnHeader,0)),"Actual","Estimate") | N72: =IF(B72="Historical",INDEX(INDIRECT(E72),0,MATCH(F72,MO_Common_ColumnHeader,0)),"N/A") | P72: =IF(ISNUMBER(N72),N72-K72,"N/A") | Q72: =IFERROR(IF(ISNUMBER(N72),(N72-K72)/ABS(K72),"N/A"),"N/A") | S72: 45309 | T72: Investor Presentation
A73: 183 | B73: =IF(INDEX(MO_SNA_IsHistoricalPeriod,,MATCH(F73,MO_Common_ColumnHeader,0)),"Historical","Forward") | D73: =INDEX(INDIRECT(E73),0,COLUMN(MO_Common_Column_A)) | E73: MO_MA_GM | F73: Q1-2024 | I73: 0.52 | J73: 0.54 | K73: =AVERAGE(I73:J73) | M73: =IF(INDEX(MO_SNA_IsHistoricalPeriod,,MATCH(F73,MO_Common_ColumnHeader,0)),"Actual","Estimate") | N73: =IFERROR(INDEX(INDIRECT(E73),0,MATCH(F73,MO_Common_ColumnHeader,0)),"N/A") | P73: =IF(ISNUMBER(N73),N73-K73,"N/A") | Q73: =IFERROR(IF(ISNUMBER(N73),(N73-K73)/ABS(K73),"N/A"),"N/A") | S73: 45309 | T73: Investor Presentation
A74: 182 | B74: =IF(INDEX(MO_SNA_IsHistoricalPeriod,,MATCH(F74,MO_Common_ColumnHeader,0)),"Historical","Forward") | D74: Operating Profit Margin | F74: Q1-2024 | I74: 0.4 | J74: 0.42 | K74: =AVERAGE(I74:J74) | M74: =IF(INDEX(MO_SNA_IsHistoricalPeriod,,MATCH(F74,MO_Common_ColumnHeader,0)),"Actual","Estimate") | N74: =INDEX(MO_RIS_EBIT,0,MATCH(F74,MO_Common_ColumnHeader,0))/INDEX(MO_RIS_REV,0,MATCH(F74,MO_Common_ColumnHeader,0)) | P74: =IF(ISNUMBER(N74),N74-K74,"N/A") | Q74: =IFERROR(IF(ISNUMBER(N74),(N74-K74)/ABS(K74),"N/A"),"N/A") | S74: 45309 | T74: Investor Presentation
A75: 181
A76: 180 | B76: =IF(INDEX(MO_SNA_IsHistoricalPeriod,,MATCH(F76,MO_Common_ColumnHeader,0)),"Historical","Forward") | D76: =INDEX(INDIRECT(E76),0,COLUMN(MO_Common_Column_A)) | E76: MO_CFSum_Capex | F76: FY2023 | I76: -32000 | J76: -32000 | K76: =AVERAGE(I76:J76) | M76: =IF(INDEX(MO_SNA_IsHistoricalPeriod,,MATCH(F76,MO_Common_ColumnHeader,0)),"Actual","Estimate") | N76: =IFERROR(INDEX(INDIRECT(E76),0,MATCH(F76,MO_Common_ColumnHeader,0)),"N/A")*INDEX(MO_VA_FX_Average,0,MATCH(F76,MO_Common_ColumnHeader,0)) | P76: =IF(ISNUMBER(N76),N76-K76,"N/A") | Q76: =IFERROR(IF(ISNUMBER(N76),(N76-K76)/ABS(K76),"N/A"),"N/A") | S76: 45218 | T76: Transcript
A77: 179
A78: 178 | B78: =IF(INDEX(MO_SNA_IsHistoricalPeriod,,MATCH(F78,MO_Common_ColumnHeader,0)),"Historical","Forward") | D78: =INDEX(INDIRECT(E78),0,COLUMN(MO_Common_Column_A)) | E78: MO_RIS_REV | F78: Q4-2023 | I78: 18800 | J78: 19600 | K78: =AVERAGE(I78:J78) | M78: =IF(INDEX(MO_SNA_IsHistoricalPeriod,,MATCH(F78,MO_Common_ColumnHeader,0)),"Actual","Estimate") | N78: =IFERROR(INDEX(INDIRECT(E78),0,MATCH(F78,MO_Common_ColumnHeader,0)),"N/A")/30.8 | P78: =IF(ISNUMBER(N78),N78-K78,"N/A") | Q78: =IFERROR(IF(ISNUMBER(N78),(N78-K78)/ABS(K78),"N/A"),"N/A") | S78: 45218 | T78: Investor Presentation
A79: 177 | B79: =IF(INDEX(MO_SNA_IsHistoricalPeriod,,MATCH(F79,MO_Common_ColumnHeader,0)),"Historical","Forward") | D79: =INDEX(INDIRECT(E79),0,COLUMN(MO_Common_Column_A)) | E79: z_M2B13B0184_MO_OS_Weightedaverageforeignexchangedratereported | F79: Q4-2023 | I79: 32 | J79: 32 | K79: =AVERAGE(I79:J79) | M79: =IF(INDEX(MO_SNA_IsHistoricalPeriod,,MATCH(F79,MO_Common_ColumnHeader,0)),"Actual","Estimate") | N79: =IF(B79="Historical",INDEX(INDIRECT(E79),0,MATCH(F79,MO_Common_ColumnHeader,0)),"N/A") | P79: =IF(ISNUMBER(N79),N79-K79,"N/A") | Q79: =IFERROR(IF(ISNUMBER(N79),(N79-K79)/ABS(K79),"N/A"),"N/A") | S79: 45218 | T79: Investor Presentation
A80: 176 | B80: =IF(INDEX(MO_SNA_IsHistoricalPeriod,,MATCH(F80,MO_Common_ColumnHeader,0)),"Historical","Forward") | D80: =INDEX(INDIRECT(E80),0,COLUMN(MO_Common_Column_A)) | E80: MO_MA_GM | F80: Q4-2023 | I80: 0.515 | J80: 0.535 | K80: =AVERAGE(I80:J80) | M80: =IF(INDEX(MO_SNA_IsHistoricalPeriod,,MATCH(F80,MO_Common_ColumnHeader,0)),"Actual","Estimate") | N80: =IFERROR(INDEX(INDIRECT(E80),0,MATCH(F80,MO_Common_ColumnHeader,0)),"N/A") | P80: =IF(ISNUMBER(N80),N80-K80,"N/A") | Q80: =IFERROR(IF(ISNUMBER(N80),(N80-K80)/ABS(K80),"N/A"),"N/A") | S80: 45218 | T80: Investor Presentation
A81: 175 | B81: =IF(INDEX(MO_SNA_IsHistoricalPeriod,,MATCH(F81,MO_Common_ColumnHeader,0)),"Historical","Forward") | D81: Operating Profit Margin | F81: Q4-2023 | I81: 0.395 | J81: 0.415 | K81: =AVERAGE(I81:J81) | M81: =IF(INDEX(MO_SNA_IsHistoricalPeriod,,MATCH(F81,MO_Common_ColumnHeader,0)),"Actual","Estimate") | N81: =INDEX(MO_RIS_EBIT,0,MATCH(F81,MO_Common_ColumnHeader,0))/INDEX(MO_RIS_REV,0,MATCH(F81,MO_Common_ColumnHeader,0)) | P81: =IF(ISNUMBER(N81),N81-K81,"N/A") | Q81: =IFERROR(IF(ISNUMBER(N81),(N81-K81)/ABS(K81),"N/A"),"N/A") | S81: 45218 | T81: Investor Presentation
A82: 174
A83: 173 | B83: =IF(INDEX(MO_SNA_IsHistoricalPeriod,,MATCH(F83,MO_Common_ColumnHeader,0)),"Historical","Forward") | D83: =INDEX(INDIRECT(E83),0,COLUMN(MO_Common_Column_A)) | E83: MO_CFSum_Capex | F83: FY2023 | I83: -36000 | J83: -32000 | K83: =AVERAGE(I83:J83) | M83: =IF(INDEX(MO_SNA_IsHistoricalPeriod,,MATCH(F83,MO_Common_ColumnHeader,0)),"Actual","Estimate") | N83: =IFERROR(INDEX(INDIRECT(E83),0,MATCH(F83,MO_Common_ColumnHeader,0)),"N/A")*INDEX(MO_VA_FX_Average,0,MATCH(F83,MO_Common_ColumnHeader,0)) | P83: =IF(ISNUMBER(N83),N83-K83,"N/A") | Q83: =IFERROR(IF(ISNUMBER(N83),(N83-K83)/ABS(K83),"N/A"),"N/A") | S83: 45127 | T83: Transcript
A84: 172
A85: 171 | B85: =IF(INDEX(MO_SNA_IsHistoricalPeriod,,MATCH(F85,MO_Common_ColumnHeader,0)),"Historical","Forward") | D85: =INDEX(INDIRECT(E85),0,COLUMN(MO_Common_Column_A)) | E85: MO_RIS_REV | F85: Q3-2023 | I85: 16700 | J85: 17500 | K85: =AVERAGE(I85:J85) | M85: =IF(INDEX(MO_SNA_IsHistoricalPeriod,,MATCH(F85,MO_Common_ColumnHeader,0)),"Actual","Estimate") | N85: =IFERROR(INDEX(INDIRECT(E85),0,MATCH(F85,MO_Common_ColumnHeader,0)),"N/A")/INDEX(z_M2B13B0184_MO_OS_Weightedaverageforeignexchangedratereported,0,MATCH(F85,MO_Common_ColumnHeader,0)) | P85: =IF(ISNUMBER(N85),N85-K85,"N/A") | Q85: =IFERROR(IF(ISNUMBER(N85),(N85-K85)/ABS(K85),"N/A"),"N/A") | S85: 45127 | T85: Investor Presentation
A86: 170 | B86: =IF(INDEX(MO_SNA_IsHistoricalPeriod,,MATCH(F86,MO_Common_ColumnHeader,0)),"Historical","Forward") | D86: =INDEX(INDIRECT(E86),0,COLUMN(MO_Common_Column_A)) | E86: z_M2B13B0184_MO_OS_Weightedaverageforeignexchangedratereported | F86: Q3-2023 | I86: 30.8 | J86: 30.8 | K86: =AVERAGE(I86:J86) | M86: =IF(INDEX(MO_SNA_IsHistoricalPeriod,,MATCH(F86,MO_Common_ColumnHeader,0)),"Actual","Estimate") | N86: =IFERROR(INDEX(INDIRECT(E86),0,MATCH(F86,MO_Common_ColumnHeader,0)),"N/A") | P86: =IF(ISNUMBER(N86),N86-K86,"N/A") | Q86: =IFERROR(IF(ISNUMBER(N86),(N86-K86)/ABS(K86),"N/A"),"N/A") | S86: 45127 | T86: Investor Presentation
A87: 169 | B87: =IF(INDEX(MO_SNA_IsHistoricalPeriod,,MATCH(F87,MO_Common_ColumnHeader,0)),"Historical","Forward") | D87: =INDEX(INDIRECT(E87),0,COLUMN(MO_Common_Column_A)) | E87: MO_MA_GM | F87: Q3-2023 | I87: 0.515 | J87: 0.535 | K87: =AVERAGE(I87:J87) | M87: =IF(INDEX(MO_SNA_IsHistoricalPeriod,,MATCH(F87,MO_Common_ColumnHeader,0)),"Actual","Estimate") | N87: =IFERROR(INDEX(INDIRECT(E87),0,MATCH(F87,MO_Common_ColumnHeader,0)),"N/A") | P87: =IF(ISNUMBER(N87),N87-K87,"N/A") | Q87: =IFERROR(IF(ISNUMBER(N87),(N87-K87)/ABS(K87),"N/A"),"N/A") | S87: 45127 | T87: Investor Presentation
A88: 168 | B88: =IF(INDEX(MO_SNA_IsHistoricalPeriod,,MATCH(F88,MO_Common_ColumnHeader,0)),"Historical","Forward") | D88: Operating Profit Margin | F88: Q3-2023 | I88: 0.38 | J88: 0.4 | K88: =AVERAGE(I88:J88) | M88: =IF(INDEX(MO_SNA_IsHistoricalPeriod,,MATCH(F88,MO_Common_ColumnHeader,0)),"Actual","Estimate") | N88: =INDEX(MO_RIS_EBIT,0,MATCH(F88,MO_Common_ColumnHeader,0))/INDEX(MO_RIS_REV,0,MATCH(F88,MO_Common_ColumnHeader,0)) | P88: =IF(ISNUMBER(N88),N88-K88,"N/A") | Q88: =IFERROR(IF(ISNUMBER(N88),(N88-K88)/ABS(K88),"N/A"),"N/A") | S88: 45127 | T88: Investor Presentation
A89: 167
A90: 166 | B90: =IF(INDEX(MO_SNA_IsHistoricalPeriod,,MATCH(F90,MO_Common_ColumnHeader,0)),"Historical","Forward") | D90: =INDEX(INDIRECT(E90),0,COLUMN(MO_Common_Column_A)) | E90: MO_CFSum_Capex | F90: FY2023 | I90: -36000 | J90: -32000 | K90: =AVERAGE(I90:J90) | M90: =IF(INDEX(MO_SNA_IsHistoricalPeriod,,MATCH(F90,MO_Common_ColumnHeader,0)),"Actual","Estimate") | N90: =IFERROR(INDEX(INDIRECT(E90),0,MATCH(F90,MO_Common_ColumnHeader,0)),"N/A")*INDEX(MO_VA_FX_Average,0,MATCH(F90,MO_Common_ColumnHeader,0)) | P90: =IF(ISNUMBER(N90),N90-K90,"N/A") | Q90: =IFERROR(IF(ISNUMBER(N90),(N90-K90)/ABS(K90),"N/A"),"N/A") | S90: 45036 | T90: Transcript
A91: 165
A92: 164 | B92: =IF(INDEX(MO_SNA_IsHistoricalPeriod,,MATCH(F92,MO_Common_ColumnHeader,0)),"Historical","Forward") | D92: =INDEX(INDIRECT(E92),0,COLUMN(MO_Common_Column_A)) | E92: MO_RIS_REV | F92: Q2-2023 | I92: 15200 | J92: 16000 | K92: =AVERAGE(I92:J92) | M92: =IF(INDEX(MO_SNA_IsHistoricalPeriod,,MATCH(F92,MO_Common_ColumnHeader,0)),"Actual","Estimate") | N92: =IFERROR(INDEX(INDIRECT(E92),0,MATCH(F92,MO_Common_ColumnHeader,0)),"N/A")/INDEX(z_M2B13B0184_MO_OS_Weightedaverageforeignexchangedratereported,0,MATCH(F92,MO_Common_ColumnHeader,0)) | P92: =IF(ISNUMBER(N92),N92-K92,"N/A") | Q92: =IFERROR(IF(ISNUMBER(N92),(N92-K92)/ABS(K92),"N/A"),"N/A") | S92: 45036 | T92: Investor Presentation
A93: 163 | B93: =IF(INDEX(MO_SNA_IsHistoricalPeriod,,MATCH(F93,MO_Common_ColumnHeader,0)),"Historical","Forward") | D93: =INDEX(INDIRECT(E93),0,COLUMN(MO_Common_Column_A)) | E93: z_M2B13B0184_MO_OS_Weightedaverageforeignexchangedratereported | F93: Q2-2023 | I93: 30.4 | J93: 30.4 | K93: =AVERAGE(I93:J93) | M93: =IF(INDEX(MO_SNA_IsHistoricalPeriod,,MATCH(F93,MO_Common_ColumnHeader,0)),"Actual","Estimate") | N93: =IFERROR(INDEX(INDIRECT(E93),0,MATCH(F93,MO_Common_ColumnHeader,0)),"N/A") | P93: =IF(ISNUMBER(N93),N93-K93,"N/A") | Q93: =IFERROR(IF(ISNUMBER(N93),(N93-K93)/ABS(K93),"N/A"),"N/A") | S93: 45036 | T93: Investor Presentation
A94: 162 | B94: =IF(INDEX(MO_SNA_IsHistoricalPeriod,,MATCH(F94,MO_Common_ColumnHeader,0)),"Historical","Forward") | D94: =INDEX(INDIRECT(E94),0,COLUMN(MO_Common_Column_A)) | E94: MO_MA_GM | F94: Q2-2023 | I94: 0.52 | J94: 0.54 | K94: =AVERAGE(I94:J94) | M94: =IF(INDEX(MO_SNA_IsHistoricalPeriod,,MATCH(F94,MO_Common_ColumnHeader,0)),"Actual","Estimate") | N94: =IFERROR(INDEX(INDIRECT(E94),0,MATCH(F94,MO_Common_ColumnHeader,0)),"N/A") | P94: =IF(ISNUMBER(N94),N94-K94,"N/A") | Q94: =IFERROR(IF(ISNUMBER(N94),(N94-K94)/ABS(K94),"N/A"),"N/A") | S94: 45036 | T94: Investor Presentation
A95: 161 | B95: =IF(INDEX(MO_SNA_IsHistoricalPeriod,,MATCH(F95,MO_Common_ColumnHeader,0)),"Historical","Forward") | D95: Operating Profit Margin | F95: Q2-2023 | I95: 0.395 | J95: 0.415 | K95: =AVERAGE(I95:J95) | M95: =IF(INDEX(MO_SNA_IsHistoricalPeriod,,MATCH(F95,MO_Common_ColumnHeader,0)),"Actual","Estimate") | N95: =INDEX(MO_RIS_EBIT,0,MATCH(F95,MO_Common_ColumnHeader,0))/INDEX(MO_RIS_REV,0,MATCH(F95,MO_Common_ColumnHeader,0)) | P95: =IF(ISNUMBER(N95),N95-K95,"N/A") | Q95: =IFERROR(IF(ISNUMBER(N95),(N95-K95)/ABS(K95),"N/A"),"N/A") | S95: 45036 | T95: Investor Presentation
A96: 160
A97: 159 | B97: =IF(INDEX(MO_SNA_IsHistoricalPeriod,,MATCH(F97,MO_Common_ColumnHeader,0)),"Historical","Forward") | D97: =INDEX(INDIRECT(E97),0,COLUMN(MO_Common_Column_A)) | E97: MO_CFSum_Capex | F97: FY2023 | I97: -36000 | J97: -32000 | K97: =AVERAGE(I97:J97) | M97: =IF(INDEX(MO_SNA_IsHistoricalPeriod,,MATCH(F97,MO_Common_ColumnHeader,0)),"Actual","Estimate") | N97: =IFERROR(INDEX(INDIRECT(E97),0,MATCH(F97,MO_Common_ColumnHeader,0)),"N/A")*INDEX(MO_VA_FX_Average,0,MATCH(F97,MO_Common_ColumnHeader,0)) | P97: =IF(ISNUMBER(N97),N97-K97,"N/A") | Q97: =IFERROR(IF(ISNUMBER(N97),(N97-K97)/ABS(K97),"N/A"),"N/A") | S97: 44937 | T97: Transcript
A98: 158 | B98: =IF(INDEX(MO_SNA_IsHistoricalPeriod,,MATCH(F98,MO_Common_ColumnHeader,0)),"Historical","Forward") | D98: =INDEX(INDIRECT(E98),0,COLUMN(MO_Common_Column_A)) | E98: MO_RIS_TaxRate_Current | F98: FY2023 | I98: 0.15 | J98: 0.15 | K98: =AVERAGE(I98:J98) | M98: =IF(INDEX(MO_SNA_IsHistoricalPeriod,,MATCH(F98,MO_Common_ColumnHeader,0)),"Actual","Estimate") | N98: =IFERROR(INDEX(INDIRECT(E98),0,MATCH(F98,MO_Common_ColumnHeader,0)),"N/A") | P98: =IF(ISNUMBER(N98),N98-K98,"N/A") | Q98: =IFERROR(IF(ISNUMBER(N98),(N98-K98)/ABS(K98),"N/A"),"N/A") | S98: 44937 | T98: Transcript
A99: 157
A100: 156 | B100: =IF(INDEX(MO_SNA_IsHistoricalPeriod,,MATCH(F100,MO_Common_ColumnHeader,0)),"Historical","Forward") | D100: =INDEX(INDIRECT(E100),0,COLUMN(MO_Common_Column_A)) | E100: MO_RIS_REV | F100: Q1-2023 | I100: 16700 | J100: 17500 | K100: =AVERAGE(I100:J100) | M100: =IF(INDEX(MO_SNA_IsHistoricalPeriod,,MATCH(F100,MO_Common_ColumnHeader,0)),"Actual","Estimate") | N100: =IFERROR(INDEX(INDIRECT(E100),0,MATCH(F100,MO_Common_ColumnHeader,0)),"N/A")/INDEX(z_M2B13B0184_MO_OS_Weightedaverageforeignexchangedratereported,0,MATCH(F100,MO_Common_ColumnHeader,0)) | P100: =IF(ISNUMBER(N100),N100-K100,"N/A") | Q100: =IFERROR(IF(ISNUMBER(N100),(N100-K100)/ABS(K100),"N/A"),"N/A") | S100: 44937 | T100: Investor Presentation
A101: 155 | B101: =IF(INDEX(MO_SNA_IsHistoricalPeriod,,MATCH(F101,MO_Common_ColumnHeader,0)),"Historical","Forward") | D101: =INDEX(INDIRECT(E101),0,COLUMN(MO_Common_Column_A)) | E101: z_M2B13B0184_MO_OS_Weightedaverageforeignexchangedratereported | F101: Q1-2023 | I101: 30.7 | J101: 30.7 | K101: =AVERAGE(I101:J101) | M101: =IF(INDEX(MO_SNA_IsHistoricalPeriod,,MATCH(F101,MO_Common_ColumnHeader,0)),"Actual","Estimate") | N101: =IFERROR(INDEX(INDIRECT(E101),0,MATCH(F101,MO_Common_ColumnHeader,0)),"N/A") | P101: =IF(ISNUMBER(N101),N101-K101,"N/A") | Q101: =IFERROR(IF(ISNUMBER(N101),(N101-K101)/ABS(K101),"N/A"),"N/A") | S101: 44937 | T101: Investor Presentation
...

Sheet Summary Page
A1: =MO.CompanyName | C1: =INDEX(MO_Common_QEndDate,0,COLUMN()) | D1: =INDEX(MO_Common_QEndDate,0,COLUMN()) | E1: =INDEX(MO_Common_QEndDate,0,COLUMN()) | F1: =INDEX(MO_Common_QEndDate,0,COLUMN()) | G1: =INDEX(MO_Common_QEndDate,0,COLUMN()) | H1: =INDEX(MO_Common_QEndDate,0,COLUMN()) | I1: =INDEX(MO_Common_QEndDate,0,COLUMN()) | J1: =INDEX(MO_Common_QEndDate,0,COLUMN()) | ... CB1: =INDEX(MO_Common_QEndDate,0,COLUMN())
A2: Reports | B2: =MO.ReportFX | C2: =INDEX(MO_Common_ColumnHeader,0,COLUMN()) | D2: =INDEX(MO_Common_ColumnHeader,0,COLUMN()) | E2: =INDEX(MO_Common_ColumnHeader,0,COLUMN()) | F2: =INDEX(MO_Common_ColumnHeader,0,COLUMN()) | G2: =INDEX(MO_Common_ColumnHeader,0,COLUMN()) | H2: =INDEX(MO_Common_ColumnHeader,0,COLUMN()) | I2: =INDEX(MO_Common_ColumnHeader,0,COLUMN()) | J2: =INDEX(MO_Common_ColumnHeader,0,COLUMN()) | ... CB2: =INDEX(MO_Common_ColumnHeader,0,COLUMN())
A3: Capitalization Summary
A4: ="Stock Price - "&SP.ValuationToggle | B4: EoP | C4: =IF(INDEX(MO_SNA_IsHistoricalPeriod,1,COLUMN())=FALSE,MO.LastPrice/HP.MRFX,CHOOSE(VLOOKUP(SP.ValuationToggle,tb_ValuationToggle,COLUMNS(tb_ValuationToggle),FALSE),INDEX(MO_SPT_StockHigh,1,COLUMN()),INDEX(MO_SPT_StockLow,1,COLUMN()),INDEX(MO_SPT_StockAverage,1,COLUMN()),INDEX(MO_SPT_StockEoP,1,COLUMN()))/IF(SP.ValuationToggle="EoP",IF(INDEX(MO_SPT_FXEoP,1,COLUMN())=0,1,INDEX(MO_SPT_FXEoP,1,COLUMN())),IF(INDEX(MO_SPT_FXAverage,1,COLUMN())=0,1,INDEX(MO_SPT_FXAverage,1,COLUMN())))) | D4: =IF(INDEX(MO_SNA_IsHistoricalPeriod,1,COLUMN())=FALSE,MO.LastPrice/HP.MRFX,CHOOSE(VLOOKUP(SP.ValuationToggle,tb_ValuationToggle,COLUMNS(tb_ValuationToggle),FALSE),INDEX(MO_SPT_StockHigh,1,COLUMN()),INDEX(MO_SPT_StockLow,1,COLUMN()),INDEX(MO_SPT_StockAverage,1,COLUMN()),INDEX(MO_SPT_StockEoP,1,COLUMN()))/IF(SP.ValuationToggle="EoP",IF(INDEX(MO_SPT_FXEoP,1,COLUMN())=0,1,INDEX(MO_SPT_FXEoP,1,COLUMN())),IF(INDEX(MO_SPT_FXAverage,1,COLUMN())=0,1,INDEX(MO_SPT_FXAverage,1,COLUMN())))) | E4: =IF(INDEX(MO_SNA_IsHistoricalPeriod,1,COLUMN())=FALSE,MO.LastPrice/HP.MRFX,CHOOSE(VLOOKUP(SP.ValuationToggle,tb_ValuationToggle,COLUMNS(tb_ValuationToggle),FALSE),INDEX(MO_SPT_StockHigh,1,COLUMN()),INDEX(MO_SPT_StockLow,1,COLUMN()),INDEX(MO_SPT_StockAverage,1,COLUMN()),INDEX(MO_SPT_StockEoP,1,COLUMN()))/IF(SP.ValuationToggle="EoP",IF(INDEX(MO_SPT_FXEoP,1,COLUMN())=0,1,INDEX(MO_SPT_FXEoP,1,COLUMN())),IF(INDEX(MO_SPT_FXAverage,1,COLUMN())=0,1,INDEX(MO_SPT_FXAverage,1,COLUMN())))) | F4: =IF(INDEX(MO_SNA_IsHistoricalPeriod,1,COLUMN())=FALSE,MO.LastPrice/HP.MRFX,CHOOSE(VLOOKUP(SP.ValuationToggle,tb_ValuationToggle,COLUMNS(tb_ValuationToggle),FALSE),INDEX(MO_SPT_StockHigh,1,COLUMN()),INDEX(MO_SPT_StockLow,1,COLUMN()),INDEX(MO_SPT_StockAverage,1,COLUMN()),INDEX(MO_SPT_StockEoP,1,COLUMN()))/IF(SP.ValuationToggle="EoP",IF(INDEX(MO_SPT_FXEoP,1,COLUMN())=0,1,INDEX(MO_SPT_FXEoP,1,COLUMN())),IF(INDEX(MO_SPT_FXAverage,1,COLUMN())=0,1,INDEX(MO_SPT_FXAverage,1,COLUMN())))) | G4: =IF(INDEX(MO_SNA_IsHistoricalPeriod,1,COLUMN())=FALSE,MO.LastPrice/HP.MRFX,CHOOSE(VLOOKUP(SP.ValuationToggle,tb_ValuationToggle,COLUMNS(tb_ValuationToggle),FALSE),INDEX(MO_SPT_StockHigh,1,COLUMN()),INDEX(MO_SPT_StockLow,1,COLUMN()),INDEX(MO_SPT_StockAverage,1,COLUMN()),INDEX(MO_SPT_StockEoP,1,COLUMN()))/IF(SP.ValuationToggle="EoP",IF(INDEX(MO_SPT_FXEoP,1,COLUMN())=0,1,INDEX(MO_SPT_FXEoP,1,COLUMN())),IF(INDEX(MO_SPT_FXAverage,1,COLUMN())=0,1,INDEX(MO_SPT_FXAverage,1,COLUMN())))) | H4: =IF(INDEX(MO_SNA_IsHistoricalPeriod,1,COLUMN())=FALSE,MO.LastPrice/HP.MRFX,CHOOSE(VLOOKUP(SP.ValuationToggle,tb_ValuationToggle,COLUMNS(tb_ValuationToggle),FALSE),INDEX(MO_SPT_StockHigh,1,COLUMN()),INDEX(MO_SPT_StockLow,1,COLUMN()),INDEX(MO_SPT_StockAverage,1,COLUMN()),INDEX(MO_SPT_StockEoP,1,COLUMN()))/IF(SP.ValuationToggle="EoP",IF(INDEX(MO_SPT_FXEoP,1,COLUMN())=0,1,INDEX(MO_SPT_FXEoP,1,COLUMN())),IF(INDEX(MO_SPT_FXAverage,1,COLUMN())=0,1,INDEX(MO_SPT_FXAverage,1,COLUMN())))) | I4: =IF(INDEX(MO_SNA_IsHistoricalPeriod,1,COLUMN())=FALSE,MO.LastPrice/HP.MRFX,CHOOSE(VLOOKUP(SP.ValuationToggle,tb_ValuationToggle,COLUMNS(tb_ValuationToggle),FALSE),INDEX(MO_SPT_StockHigh,1,COLUMN()),INDEX(MO_SPT_StockLow,1,COLUMN()),INDEX(MO_SPT_StockAverage,1,COLUMN()),INDEX(MO_SPT_StockEoP,1,COLUMN()))/IF(SP.ValuationToggle="EoP",IF(INDEX(MO_SPT_FXEoP,1,COLUMN())=0,1,INDEX(MO_SPT_FXEoP,1,COLUMN())),IF(INDEX(MO_SPT_FXAverage,1,COLUMN())=0,1,INDEX(MO_SPT_FXAverage,1,COLUMN())))) | J4: =IF(INDEX(MO_SNA_IsHistoricalPeriod,1,COLUMN())=FALSE,MO.LastPrice/HP.MRFX,CHOOSE(VLOOKUP(SP.ValuationToggle,tb_ValuationToggle,COLUMNS(tb_ValuationToggle),FALSE),INDEX(MO_SPT_StockHigh,1,COLUMN()),INDEX(MO_SPT_StockLow,1,COLUMN()),INDEX(MO_SPT_StockAverage,1,COLUMN()),INDEX(MO_SPT_StockEoP,1,COLUMN()))/IF(SP.ValuationToggle="EoP",IF(INDEX(MO_SPT_FXEoP,1,COLUMN())=0,1,INDEX(MO_SPT_FXEoP,1,COLUMN())),IF(INDEX(MO_SPT_FXAverage,1,COLUMN())=0,1,INDEX(MO_SPT_FXAverage,1,COLUMN())))) | ... CB4: =IF(INDEX(MO_SNA_IsHistoricalPeriod,1,COLUMN())=FALSE,MO.LastPrice/HP.MRFX,CHOOSE(VLOOKUP(SP.ValuationToggle,tb_ValuationToggle,COLUMNS(tb_ValuationToggle),FALSE),INDEX(MO_SPT_StockHigh,1,COLUMN()),INDEX(MO_SPT_StockLow,1,COLUMN()),INDEX(MO_SPT_StockAverage,1,COLUMN()),INDEX(MO_SPT_StockEoP,1,COLUMN()))/IF(SP.ValuationToggle="EoP",IF(INDEX(MO_SPT_FXEoP,1,COLUMN())=0,1,INDEX(MO_SPT_FXEoP,1,COLUMN())),IF(INDEX(MO_SPT_FXAverage,1,COLUMN())=0,1,INDEX(MO_SPT_FXAverage,1,COLUMN()))))
A5: =INDEX(MO_SCA_ShareCount_EoP_Diluted,0,COLUMN()) | C5: =INDEX(MO_SCA_ShareCount_EoP_Diluted,0,COLUMN()) | D5: =INDEX(MO_SCA_ShareCount_EoP_Diluted,0,COLUMN()) | E5: =INDEX(MO_SCA_ShareCount_EoP_Diluted,0,COLUMN()) | F5: =INDEX(MO_SCA_ShareCount_EoP_Diluted,0,COLUMN()) | G5: =INDEX(MO_SCA_ShareCount_EoP_Diluted,0,COLUMN()) | H5: =INDEX(MO_SCA_ShareCount_EoP_Diluted,0,COLUMN()) | I5: =INDEX(MO_SCA_ShareCount_EoP_Diluted,0,COLUMN()) | J5: =INDEX(MO_SCA_ShareCount_EoP_Diluted,0,COLUMN()) | ... CB5: =INDEX(MO_SCA_ShareCount_EoP_Diluted,0,COLUMN())
A6: ="Market Cap - "&SP.ValuationToggle | C6: =INDEX(SP_CS_StockPrice,0,COLUMN())*INDEX(SP_CS_ShareCount_EoP_Diluted,0,COLUMN()) | D6: =INDEX(SP_CS_StockPrice,0,COLUMN())*INDEX(SP_CS_ShareCount_EoP_Diluted,0,COLUMN()) | E6: =INDEX(SP_CS_StockPrice,0,COLUMN())*INDEX(SP_CS_ShareCount_EoP_Diluted,0,COLUMN()) | F6: =INDEX(SP_CS_StockPrice,0,COLUMN())*INDEX(SP_CS_ShareCount_EoP_Diluted,0,COLUMN()) | G6: =INDEX(SP_CS_StockPrice,0,COLUMN())*INDEX(SP_CS_ShareCount_EoP_Diluted,0,COLUMN()) | H6: =INDEX(SP_CS_StockPrice,0,COLUMN())*INDEX(SP_CS_ShareCount_EoP_Diluted,0,COLUMN()) | I6: =INDEX(SP_CS_StockPrice,0,COLUMN())*INDEX(SP_CS_ShareCount_EoP_Diluted,0,COLUMN()) | J6: =INDEX(SP_CS_StockPrice,0,COLUMN())*INDEX(SP_CS_ShareCount_EoP_Diluted,0,COLUMN()) | ... CB6: =INDEX(SP_CS_StockPrice,0,COLUMN())*INDEX(SP_CS_ShareCount_EoP_Diluted,0,COLUMN())
A7: =INDEX(MO_BSS_Cash,0,COLUMN()) | C7: =INDEX(MO_BSS_Cash,0,COLUMN()) | D7: =INDEX(MO_BSS_Cash,0,COLUMN()) | E7: =INDEX(MO_BSS_Cash,0,COLUMN()) | F7: =INDEX(MO_BSS_Cash,0,COLUMN()) | G7: =INDEX(MO_BSS_Cash,0,COLUMN()) | H7: =INDEX(MO_BSS_Cash,0,COLUMN()) | I7: =INDEX(MO_BSS_Cash,0,COLUMN()) | J7: =INDEX(MO_BSS_Cash,0,COLUMN()) | ... CB7: =INDEX(MO_BSS_Cash,0,COLUMN())
A8: =INDEX(MO_BSS_Debt,0,COLUMN()) | C8: =INDEX(MO_BSS_Debt,0,COLUMN()) | D8: =INDEX(MO_BSS_Debt,0,COLUMN()) | E8: =INDEX(MO_BSS_Debt,0,COLUMN()) | F8: =INDEX(MO_BSS_Debt,0,COLUMN()) | G8: =INDEX(MO_BSS_Debt,0,COLUMN()) | H8: =INDEX(MO_BSS_Debt,0,COLUMN()) | I8: =INDEX(MO_BSS_Debt,0,COLUMN()) | J8: =INDEX(MO_BSS_Debt,0,COLUMN()) | ... CB8: =INDEX(MO_BSS_Debt,0,COLUMN())
A9: Operating Lease Liabilities | C9: =INDEX(MO_BSS_OL,0,COLUMN()) | D9: =INDEX(MO_BSS_OL,0,COLUMN()) | E9: =INDEX(MO_BSS_OL,0,COLUMN()) | F9: =INDEX(MO_BSS_OL,0,COLUMN()) | G9: =INDEX(MO_BSS_OL,0,COLUMN()) | H9: =INDEX(MO_BSS_OL,0,COLUMN()) | I9: =INDEX(MO_BSS_OL,0,COLUMN()) | J9: =INDEX(MO_BSS_OL,0,COLUMN()) | ... CB9: =INDEX(MO_BSS_OL,0,COLUMN())
A10: Other EV Components | C10: =INDEX(MO_VA_EVCalc_NCI,0,COLUMN())+INDEX(MO_VA_EVCalc_Prefs,0,COLUMN())+INDEX(MO_VA_EVCalc_Other,0,COLUMN()) | D10: =INDEX(MO_VA_EVCalc_NCI,0,COLUMN())+INDEX(MO_VA_EVCalc_Prefs,0,COLUMN())+INDEX(MO_VA_EVCalc_Other,0,COLUMN()) | E10: =INDEX(MO_VA_EVCalc_NCI,0,COLUMN())+INDEX(MO_VA_EVCalc_Prefs,0,COLUMN())+INDEX(MO_VA_EVCalc_Other,0,COLUMN()) | F10: =INDEX(MO_VA_EVCalc_NCI,0,COLUMN())+INDEX(MO_VA_EVCalc_Prefs,0,COLUMN())+INDEX(MO_VA_EVCalc_Other,0,COLUMN()) | G10: =INDEX(MO_VA_EVCalc_NCI,0,COLUMN())+INDEX(MO_VA_EVCalc_Prefs,0,COLUMN())+INDEX(MO_VA_EVCalc_Other,0,COLUMN()) | H10: =INDEX(MO_VA_EVCalc_NCI,0,COLUMN())+INDEX(MO_VA_EVCalc_Prefs,0,COLUMN())+INDEX(MO_VA_EVCalc_Other,0,COLUMN()) | I10: =INDEX(MO_VA_EVCalc_NCI,0,COLUMN())+INDEX(MO_VA_EVCalc_Prefs,0,COLUMN())+INDEX(MO_VA_EVCalc_Other,0,COLUMN()) | J10: =INDEX(MO_VA_EVCalc_NCI,0,COLUMN())+INDEX(MO_VA_EVCalc_Prefs,0,COLUMN())+INDEX(MO_VA_EVCalc_Other,0,COLUMN()) | ... CB10: =INDEX(MO_VA_EVCalc_NCI,0,COLUMN())+INDEX(MO_VA_EVCalc_Prefs,0,COLUMN())+INDEX(MO_VA_EVCalc_Other,0,COLUMN())
A11: ="Enterprise Value - "&SP.ValuationToggle | C11: =INDEX(SP_CS_MarketCap,0,COLUMN())-INDEX(SP_CS_Cash,0,COLUMN())+INDEX(SP_CS_Debt,0,COLUMN())+INDEX(SP_CS_OL,0,COLUMN())+INDEX(SP_CS_EVCalc_Other,0,COLUMN()) | D11: =INDEX(SP_CS_MarketCap,0,COLUMN())-INDEX(SP_CS_Cash,0,COLUMN())+INDEX(SP_CS_Debt,0,COLUMN())+INDEX(SP_CS_OL,0,COLUMN())+INDEX(SP_CS_EVCalc_Other,0,COLUMN()) | E11: =INDEX(SP_CS_MarketCap,0,COLUMN())-INDEX(SP_CS_Cash,0,COLUMN())+INDEX(SP_CS_Debt,0,COLUMN())+INDEX(SP_CS_OL,0,COLUMN())+INDEX(SP_CS_EVCalc_Other,0,COLUMN()) | F11: =INDEX(SP_CS_MarketCap,0,COLUMN())-INDEX(SP_CS_Cash,0,COLUMN())+INDEX(SP_CS_Debt,0,COLUMN())+INDEX(SP_CS_OL,0,COLUMN())+INDEX(SP_CS_EVCalc_Other,0,COLUMN()) | G11: =INDEX(SP_CS_MarketCap,0,COLUMN())-INDEX(SP_CS_Cash,0,COLUMN())+INDEX(SP_CS_Debt,0,COLUMN())+INDEX(SP_CS_OL,0,COLUMN())+INDEX(SP_CS_EVCalc_Other,0,COLUMN()) | H11: =INDEX(SP_CS_MarketCap,0,COLUMN())-INDEX(SP_CS_Cash,0,COLUMN())+INDEX(SP_CS_Debt,0,COLUMN())+INDEX(SP_CS_OL,0,COLUMN())+INDEX(SP_CS_EVCalc_Other,0,COLUMN()) | I11: =INDEX(SP_CS_MarketCap,0,COLUMN())-INDEX(SP_CS_Cash,0,COLUMN())+INDEX(SP_CS_Debt,0,COLUMN())+INDEX(SP_CS_OL,0,COLUMN())+INDEX(SP_CS_EVCalc_Other,0,COLUMN()) | J11: =INDEX(SP_CS_MarketCap,0,COLUMN())-INDEX(SP_CS_Cash,0,COLUMN())+INDEX(SP_CS_Debt,0,COLUMN())+INDEX(SP_CS_OL,0,COLUMN())+INDEX(SP_CS_EVCalc_Other,0,COLUMN()) | ... CB11: =INDEX(SP_CS_MarketCap,0,COLUMN())-INDEX(SP_CS_Cash,0,COLUMN())+INDEX(SP_CS_Debt,0,COLUMN())+INDEX(SP_CS_OL,0,COLUMN())+INDEX(SP_CS_EVCalc_Other,0,COLUMN())
A13: Company-Specific Operational Data
A14: =Model!A9 | AG14: =Model!AG9 | AH14: =Model!AH9 | AI14: =Model!AI9 | AJ14: =Model!AJ9 | AK14: =Model!AK9 | AL14: =Model!AL9 | AM14: =Model!AM9 | AN14: =Model!AN9 | ... CB14: =Model!CB9
A15: =Model!A12 | AG15: =Model!AG12 | AH15: =Model!AH12 | AI15: =Model!AI12 | AJ15: =Model!AJ12 | AK15: =Model!AK12 | AL15: =Model!AL12 | AM15: =Model!AM12 | AN15: =Model!AN12 | ... CB15: =Model!CB12
A16: =Model!A15 | AG16: =Model!AG15 | AH16: =Model!AH15 | AI16: =Model!AI15 | AJ16: =Model!AJ15 | AK16: =Model!AK15 | AL16: =Model!AL15 | AM16: =Model!AM15 | AN16: =Model!AN15 | ... CB16: =Model!CB15
A17: =Model!A18 | AG17: =Model!AG18 | AH17: =Model!AH18 | AI17: =Model!AI18 | AJ17: =Model!AJ18 | AK17: =Model!AK18 | AL17: =Model!AL18 | AM17: =Model!AM18 | AN17: =Model!AN18 | ... CB17: =Model!CB18
A18: =Model!A21 | AG18: =Model!AG21 | AH18: =Model!AH21 | AI18: =Model!AI21 | AJ18: =Model!AJ21 | AK18: =Model!AK21 | AL18: =Model!AL21 | AM18: =Model!AM21 | AN18: =Model!AN21 | ... CB18: =Model!CB21
A19: =Model!A24 | AG19: =Model!AG24 | AH19: =Model!AH24 | AI19: =Model!AI24 | AJ19: =Model!AJ24 | AK19: =Model!AK24 | AL19: =Model!AL24 | AM19: =Model!AM24 | AN19: =Model!AN24 | ... CB19: =Model!CB24
A20: =Model!A28 | C20: =Model!C28 | D20: =Model!D28 | E20: =Model!E28 | F20: =Model!F28 | G20: =Model!G28 | H20: =Model!H28 | I20: =Model!I28 | J20: =Model!J28 | ... CB20: =Model!CB28
A22: GAAP Financials
A23: =INDEX(MO_RIS_REV,0,COLUMN()) | C23: =INDEX(MO_RIS_REV,0,COLUMN()) | D23: =INDEX(MO_RIS_REV,0,COLUMN()) | E23: =INDEX(MO_RIS_REV,0,COLUMN()) | F23: =INDEX(MO_RIS_REV,0,COLUMN()) | G23: =INDEX(MO_RIS_REV,0,COLUMN()) | H23: =INDEX(MO_RIS_REV,0,COLUMN()) | I23: =INDEX(MO_RIS_REV,0,COLUMN()) | J23: =INDEX(MO_RIS_REV,0,COLUMN()) | ... CB23: =INDEX(MO_RIS_REV,0,COLUMN())
A24: =INDEX(MO_RIS_COGS,0,COLUMN()) | C24: =INDEX(MO_RIS_COGS,0,COLUMN()) | D24: =INDEX(MO_RIS_COGS,0,COLUMN()) | E24: =INDEX(MO_RIS_COGS,0,COLUMN()) | F24: =INDEX(MO_RIS_COGS,0,COLUMN()) | G24: =INDEX(MO_RIS_COGS,0,COLUMN()) | H24: =INDEX(MO_RIS_COGS,0,COLUMN()) | I24: =INDEX(MO_RIS_COGS,0,COLUMN()) | J24: =INDEX(MO_RIS_COGS,0,COLUMN()) | ... CB24: =INDEX(MO_RIS_COGS,0,COLUMN())
A25: =INDEX(MO_RIS_SGA,0,COLUMN()) | C25: =INDEX(MO_RIS_SGA,0,COLUMN()) | D25: =INDEX(MO_RIS_SGA,0,COLUMN()) | E25: =INDEX(MO_RIS_SGA,0,COLUMN()) | F25: =INDEX(MO_RIS_SGA,0,COLUMN()) | G25: =INDEX(MO_RIS_SGA,0,COLUMN()) | H25: =INDEX(MO_RIS_SGA,0,COLUMN()) | I25: =INDEX(MO_RIS_SGA,0,COLUMN()) | J25: =INDEX(MO_RIS_SGA,0,COLUMN()) | ... CB25: =INDEX(MO_RIS_SGA,0,COLUMN())
A26: =INDEX(MO_RIS_RD,0,COLUMN()) | C26: =INDEX(MO_RIS_RD,0,COLUMN()) | D26: =INDEX(MO_RIS_RD,0,COLUMN()) | E26: =INDEX(MO_RIS_RD,0,COLUMN()) | F26: =INDEX(MO_RIS_RD,0,COLUMN()) | G26: =INDEX(MO_RIS_RD,0,COLUMN()) | H26: =INDEX(MO_RIS_RD,0,COLUMN()) | I26: =INDEX(MO_RIS_RD,0,COLUMN()) | J26: =INDEX(MO_RIS_RD,0,COLUMN()) | ... CB26: =INDEX(MO_RIS_RD,0,COLUMN())
A27: =INDEX(MO_RIS_OPEX,0,COLUMN()) | C27: =INDEX(MO_RIS_OPEX,0,COLUMN()) | D27: =INDEX(MO_RIS_OPEX,0,COLUMN()) | E27: =INDEX(MO_RIS_OPEX,0,COLUMN()) | F27: =INDEX(MO_RIS_OPEX,0,COLUMN()) | G27: =INDEX(MO_RIS_OPEX,0,COLUMN()) | H27: =INDEX(MO_RIS_OPEX,0,COLUMN()) | I27: =INDEX(MO_RIS_OPEX,0,COLUMN()) | J27: =INDEX(MO_RIS_OPEX,0,COLUMN()) | ... CB27: =INDEX(MO_RIS_OPEX,0,COLUMN())
A28: =INDEX(MO_RIS_EBIT,0,COLUMN()) | C28: =IFERROR(INDEX(SP_GF_Rev,0,COLUMN()),0)-IFERROR(INDEX(SP_GF_COGS,0,COLUMN()),0)-IFERROR(INDEX(SP_GF_SGA,0,COLUMN()),0)-IFERROR(INDEX(SP_GF_OI_Operating,0,COLUMN()),0)-IFERROR(INDEX(SP_GF_DA_Operating,0,COLUMN()),0)-IFERROR(INDEX(SP_GF_OPEX,0,COLUMN()),0)-IFERROR(INDEX(SP_GF_RD,0,COLUMN()),0) | D28: =IFERROR(INDEX(SP_GF_Rev,0,COLUMN()),0)-IFERROR(INDEX(SP_GF_COGS,0,COLUMN()),0)-IFERROR(INDEX(SP_GF_SGA,0,COLUMN()),0)-IFERROR(INDEX(SP_GF_OI_Operating,0,COLUMN()),0)-IFERROR(INDEX(SP_GF_DA_Operating,0,COLUMN()),0)-IFERROR(INDEX(SP_GF_OPEX,0,COLUMN()),0)-IFERROR(INDEX(SP_GF_RD,0,COLUMN()),0) | E28: =IFERROR(INDEX(SP_GF_Rev,0,COLUMN()),0)-IFERROR(INDEX(SP_GF_COGS,0,COLUMN()),0)-IFERROR(INDEX(SP_GF_SGA,0,COLUMN()),0)-IFERROR(INDEX(SP_GF_OI_Operating,0,COLUMN()),0)-IFERROR(INDEX(SP_GF_DA_Operating,0,COLUMN()),0)-IFERROR(INDEX(SP_GF_OPEX,0,COLUMN()),0)-IFERROR(INDEX(SP_GF_RD,0,COLUMN()),0) | F28: =IFERROR(INDEX(SP_GF_Rev,0,COLUMN()),0)-IFERROR(INDEX(SP_GF_COGS,0,COLUMN()),0)-IFERROR(INDEX(SP_GF_SGA,0,COLUMN()),0)-IFERROR(INDEX(SP_GF_OI_Operating,0,COLUMN()),0)-IFERROR(INDEX(SP_GF_DA_Operating,0,COLUMN()),0)-IFERROR(INDEX(SP_GF_OPEX,0,COLUMN()),0)-IFERROR(INDEX(SP_GF_RD,0,COLUMN()),0) | G28: =IFERROR(INDEX(SP_GF_Rev,0,COLUMN()),0)-IFERROR(INDEX(SP_GF_COGS,0,COLUMN()),0)-IFERROR(INDEX(SP_GF_SGA,0,COLUMN()),0)-IFERROR(INDEX(SP_GF_OI_Operating,0,COLUMN()),0)-IFERROR(INDEX(SP_GF_DA_Operating,0,COLUMN()),0)-IFERROR(INDEX(SP_GF_OPEX,0,COLUMN()),0)-IFERROR(INDEX(SP_GF_RD,0,COLUMN()),0) | H28: =IFERROR(INDEX(SP_GF_Rev,0,COLUMN()),0)-IFERROR(INDEX(SP_GF_COGS,0,COLUMN()),0)-IFERROR(INDEX(SP_GF_SGA,0,COLUMN()),0)-IFERROR(INDEX(SP_GF_OI_Operating,0,COLUMN()),0)-IFERROR(INDEX(SP_GF_DA_Operating,0,COLUMN()),0)-IFERROR(INDEX(SP_GF_OPEX,0,COLUMN()),0)-IFERROR(INDEX(SP_GF_RD,0,COLUMN()),0) | I28: =IFERROR(INDEX(SP_GF_Rev,0,COLUMN()),0)-IFERROR(INDEX(SP_GF_COGS,0,COLUMN()),0)-IFERROR(INDEX(SP_GF_SGA,0,COLUMN()),0)-IFERROR(INDEX(SP_GF_OI_Operating,0,COLUMN()),0)-IFERROR(INDEX(SP_GF_DA_Operating,0,COLUMN()),0)-IFERROR(INDEX(SP_GF_OPEX,0,COLUMN()),0)-IFERROR(INDEX(SP_GF_RD,0,COLUMN()),0) | J28: =IFERROR(INDEX(SP_GF_Rev,0,COLUMN()),0)-IFERROR(INDEX(SP_GF_COGS,0,COLUMN()),0)-IFERROR(INDEX(SP_GF_SGA,0,COLUMN()),0)-IFERROR(INDEX(SP_GF_OI_Operating,0,COLUMN()),0)-IFERROR(INDEX(SP_GF_DA_Operating,0,COLUMN()),0)-IFERROR(INDEX(SP_GF_OPEX,0,COLUMN()),0)-IFERROR(INDEX(SP_GF_RD,0,COLUMN()),0) | ... CB28: =IFERROR(INDEX(SP_GF_Rev,0,COLUMN()),0)-IFERROR(INDEX(SP_GF_COGS,0,COLUMN()),0)-IFERROR(INDEX(SP_GF_SGA,0,COLUMN()),0)-IFERROR(INDEX(SP_GF_OI_Operating,0,COLUMN()),0)-IFERROR(INDEX(SP_GF_DA_Operating,0,COLUMN()),0)-IFERROR(INDEX(SP_GF_OPEX,0,COLUMN()),0)-IFERROR(INDEX(SP_GF_RD,0,COLUMN()),0)
A29: =INDEX(MO_RIS_IE_Net,0,COLUMN()) | C29: =IFERROR(INDEX(MO_RIS_IE_Net,0,COLUMN()),INDEX(MO_RIS_IE,0,COLUMN())+INDEX(MO_RIS_II,0,COLUMN())) | D29: =IFERROR(INDEX(MO_RIS_IE_Net,0,COLUMN()),INDEX(MO_RIS_IE,0,COLUMN())+INDEX(MO_RIS_II,0,COLUMN())) | E29: =IFERROR(INDEX(MO_RIS_IE_Net,0,COLUMN()),INDEX(MO_RIS_IE,0,COLUMN())+INDEX(MO_RIS_II,0,COLUMN())) | F29: =IFERROR(INDEX(MO_RIS_IE_Net,0,COLUMN()),INDEX(MO_RIS_IE,0,COLUMN())+INDEX(MO_RIS_II,0,COLUMN())) | G29: =IFERROR(INDEX(MO_RIS_IE_Net,0,COLUMN()),INDEX(MO_RIS_IE,0,COLUMN())+INDEX(MO_RIS_II,0,COLUMN())) | H29: =IFERROR(INDEX(MO_RIS_IE_Net,0,COLUMN()),INDEX(MO_RIS_IE,0,COLUMN())+INDEX(MO_RIS_II,0,COLUMN())) | I29: =IFERROR(INDEX(MO_RIS_IE_Net,0,COLUMN()),INDEX(MO_RIS_IE,0,COLUMN())+INDEX(MO_RIS_II,0,COLUMN())) | J29: =IFERROR(INDEX(MO_RIS_IE_Net,0,COLUMN()),INDEX(MO_RIS_IE,0,COLUMN())+INDEX(MO_RIS_II,0,COLUMN())) | ... CB29: =IFERROR(INDEX(MO_RIS_IE_Net,0,COLUMN()),INDEX(MO_RIS_IE,0,COLUMN())+INDEX(MO_RIS_II,0,COLUMN()))
A30: =INDEX(MO_RIS_EI,0,COLUMN()) | C30: =INDEX(MO_RIS_EI,0,COLUMN()) | D30: =INDEX(MO_RIS_EI,0,COLUMN()) | E30: =INDEX(MO_RIS_EI,0,COLUMN()) | F30: =INDEX(MO_RIS_EI,0,COLUMN()) | G30: =INDEX(MO_RIS_EI,0,COLUMN()) | H30: =INDEX(MO_RIS_EI,0,COLUMN()) | I30: =INDEX(MO_RIS_EI,0,COLUMN()) | J30: =INDEX(MO_RIS_EI,0,COLUMN()) | ... CB30: =INDEX(MO_RIS_EI,0,COLUMN())
A31: Other Items | C31: =INDEX(MO_RIS_OI,0,COLUMN())+INDEX(MO_RIS_OTI,0,COLUMN()) | D31: =INDEX(MO_RIS_OI,0,COLUMN())+INDEX(MO_RIS_OTI,0,COLUMN()) | E31: =INDEX(MO_RIS_OI,0,COLUMN())+INDEX(MO_RIS_OTI,0,COLUMN()) | F31: =INDEX(MO_RIS_OI,0,COLUMN())+INDEX(MO_RIS_OTI,0,COLUMN()) | G31: =INDEX(MO_RIS_OI,0,COLUMN())+INDEX(MO_RIS_OTI,0,COLUMN()) | H31: =INDEX(MO_RIS_OI,0,COLUMN())+INDEX(MO_RIS_OTI,0,COLUMN()) | I31: =INDEX(MO_RIS_OI,0,COLUMN())+INDEX(MO_RIS_OTI,0,COLUMN()) | J31: =INDEX(MO_RIS_OI,0,COLUMN())+INDEX(MO_RIS_OTI,0,COLUMN()) | ... CB31: =INDEX(MO_RIS_OI,0,COLUMN())+INDEX(MO_RIS_OTI,0,COLUMN())
A32: =INDEX(MO_RIS_EBT,0,COLUMN()) | C32: =INDEX(SP_GF_EBIT,0,COLUMN())-INDEX(SP_GF_IE,0,COLUMN())-INDEX(SP_GF_OI,0,COLUMN())-INDEX(SP_GF_EI,0,COLUMN()) | D32: =INDEX(SP_GF_EBIT,0,COLUMN())-INDEX(SP_GF_IE,0,COLUMN())-INDEX(SP_GF_OI,0,COLUMN())-INDEX(SP_GF_EI,0,COLUMN()) | E32: =INDEX(SP_GF_EBIT,0,COLUMN())-INDEX(SP_GF_IE,0,COLUMN())-INDEX(SP_GF_OI,0,COLUMN())-INDEX(SP_GF_EI,0,COLUMN()) | F32: =INDEX(SP_GF_EBIT,0,COLUMN())-INDEX(SP_GF_IE,0,COLUMN())-INDEX(SP_GF_OI,0,COLUMN())-INDEX(SP_GF_EI,0,COLUMN()) | G32: =INDEX(SP_GF_EBIT,0,COLUMN())-INDEX(SP_GF_IE,0,COLUMN())-INDEX(SP_GF_OI,0,COLUMN())-INDEX(SP_GF_EI,0,COLUMN()) | H32: =INDEX(SP_GF_EBIT,0,COLUMN())-INDEX(SP_GF_IE,0,COLUMN())-INDEX(SP_GF_OI,0,COLUMN())-INDEX(SP_GF_EI,0,COLUMN()) | I32: =INDEX(SP_GF_EBIT,0,COLUMN())-INDEX(SP_GF_IE,0,COLUMN())-INDEX(SP_GF_OI,0,COLUMN())-INDEX(SP_GF_EI,0,COLUMN()) | J32: =INDEX(SP_GF_EBIT,0,COLUMN())-INDEX(SP_GF_IE,0,COLUMN())-INDEX(SP_GF_OI,0,COLUMN())-INDEX(SP_GF_EI,0,COLUMN()) | ... CB32: =INDEX(SP_GF_EBIT,0,COLUMN())-INDEX(SP_GF_IE,0,COLUMN())-INDEX(SP_GF_OI,0,COLUMN())-INDEX(SP_GF_EI,0,COLUMN())
A33: Tax | C33: =INDEX(MO_RIS_Tax_Current,0,COLUMN())+INDEX(MO_RIS_Tax_Deferred,0,COLUMN()) | D33: =INDEX(MO_RIS_Tax_Current,0,COLUMN())+INDEX(MO_RIS_Tax_Deferred,0,COLUMN()) | E33: =INDEX(MO_RIS_Tax_Current,0,COLUMN())+INDEX(MO_RIS_Tax_Deferred,0,COLUMN()) | F33: =INDEX(MO_RIS_Tax_Current,0,COLUMN())+INDEX(MO_RIS_Tax_Deferred,0,COLUMN()) | G33: =INDEX(MO_RIS_Tax_Current,0,COLUMN())+INDEX(MO_RIS_Tax_Deferred,0,COLUMN()) | H33: =INDEX(MO_RIS_Tax_Current,0,COLUMN())+INDEX(MO_RIS_Tax_Deferred,0,COLUMN()) | I33: =INDEX(MO_RIS_Tax_Current,0,COLUMN())+INDEX(MO_RIS_Tax_Deferred,0,COLUMN()) | J33: =INDEX(MO_RIS_Tax_Current,0,COLUMN())+INDEX(MO_RIS_Tax_Deferred,0,COLUMN()) | ... CB33: =INDEX(MO_RIS_Tax_Current,0,COLUMN())+INDEX(MO_RIS_Tax_Deferred,0,COLUMN())
A34: =INDEX(MO_RIS_DisCont,0,COLUMN()) | C34: =INDEX(MO_RIS_DisCont,0,COLUMN()) | D34: =INDEX(MO_RIS_DisCont,0,COLUMN()) | E34: =INDEX(MO_RIS_DisCont,0,COLUMN()) | F34: =INDEX(MO_RIS_DisCont,0,COLUMN()) | G34: =INDEX(MO_RIS_DisCont,0,COLUMN()) | H34: =INDEX(MO_RIS_DisCont,0,COLUMN()) | I34: =INDEX(MO_RIS_DisCont,0,COLUMN()) | J34: =INDEX(MO_RIS_DisCont,0,COLUMN()) | ... CB34: =INDEX(MO_RIS_DisCont,0,COLUMN())
A35: =INDEX(MO_RIS_NCI,0,COLUMN()) | C35: =INDEX(MO_RIS_NCI,0,COLUMN()) | D35: =INDEX(MO_RIS_NCI,0,COLUMN()) | E35: =INDEX(MO_RIS_NCI,0,COLUMN()) | F35: =INDEX(MO_RIS_NCI,0,COLUMN()) | G35: =INDEX(MO_RIS_NCI,0,COLUMN()) | H35: =INDEX(MO_RIS_NCI,0,COLUMN()) | I35: =INDEX(MO_RIS_NCI,0,COLUMN()) | J35: =INDEX(MO_RIS_NCI,0,COLUMN()) | ... CB35: =INDEX(MO_RIS_NCI,0,COLUMN())
A36: =INDEX(MO_RIS_Dividend_Prefs,0,COLUMN()) | C36: =INDEX(MO_RIS_Dividend_Prefs,0,COLUMN()) | D36: =INDEX(MO_RIS_Dividend_Prefs,0,COLUMN()) | E36: =INDEX(MO_RIS_Dividend_Prefs,0,COLUMN()) | F36: =INDEX(MO_RIS_Dividend_Prefs,0,COLUMN()) | G36: =INDEX(MO_RIS_Dividend_Prefs,0,COLUMN()) | H36: =INDEX(MO_RIS_Dividend_Prefs,0,COLUMN()) | I36: =INDEX(MO_RIS_Dividend_Prefs,0,COLUMN()) | J36: =INDEX(MO_RIS_Dividend_Prefs,0,COLUMN()) | ... CB36: =INDEX(MO_RIS_Dividend_Prefs,0,COLUMN())
A37: =INDEX(MO_RIS_NI_GAAP_Basic,0,COLUMN()) | C37: =INDEX(MO_RIS_NI_GAAP_Basic,0,COLUMN()) | D37: =INDEX(MO_RIS_NI_GAAP_Basic,0,COLUMN()) | E37: =INDEX(MO_RIS_NI_GAAP_Basic,0,COLUMN()) | F37: =INDEX(MO_RIS_NI_GAAP_Basic,0,COLUMN()) | G37: =INDEX(MO_RIS_NI_GAAP_Basic,0,COLUMN()) | H37: =INDEX(MO_RIS_NI_GAAP_Basic,0,COLUMN()) | I37: =INDEX(MO_RIS_NI_GAAP_Basic,0,COLUMN()) | J37: =INDEX(MO_RIS_NI_GAAP_Basic,0,COLUMN()) | ... CB37: =INDEX(MO_RIS_NI_GAAP_Basic,0,COLUMN())
A38: =INDEX(MO_RIS_Adjustments_Dilution_GAAP,0,COLUMN()) | C38: =INDEX(MO_RIS_Adjustments_Dilution_GAAP,0,COLUMN()) | D38: =INDEX(MO_RIS_Adjustments_Dilution_GAAP,0,COLUMN()) | E38: =INDEX(MO_RIS_Adjustments_Dilution_GAAP,0,COLUMN()) | F38: =INDEX(MO_RIS_Adjustments_Dilution_GAAP,0,COLUMN()) | G38: =INDEX(MO_RIS_Adjustments_Dilution_GAAP,0,COLUMN()) | H38: =INDEX(MO_RIS_Adjustments_Dilution_GAAP,0,COLUMN()) | I38: =INDEX(MO_RIS_Adjustments_Dilution_GAAP,0,COLUMN()) | J38: =INDEX(MO_RIS_Adjustments_Dilution_GAAP,0,COLUMN()) | ... CB38: =INDEX(MO_RIS_Adjustments_Dilution_GAAP,0,COLUMN())
A39: =INDEX(MO_RIS_NI_GAAP_Diluted,0,COLUMN()) | C39: =INDEX(MO_RIS_NI_GAAP_Diluted,0,COLUMN()) | D39: =INDEX(MO_RIS_NI_GAAP_Diluted,0,COLUMN()) | E39: =INDEX(MO_RIS_NI_GAAP_Diluted,0,COLUMN()) | F39: =INDEX(MO_RIS_NI_GAAP_Diluted,0,COLUMN()) | G39: =INDEX(MO_RIS_NI_GAAP_Diluted,0,COLUMN()) | H39: =INDEX(MO_RIS_NI_GAAP_Diluted,0,COLUMN()) | I39: =INDEX(MO_RIS_NI_GAAP_Diluted,0,COLUMN()) | J39: =INDEX(MO_RIS_NI_GAAP_Diluted,0,COLUMN()) | ... CB39: =INDEX(MO_RIS_NI_GAAP_Diluted,0,COLUMN())
A40: =INDEX(MO_RIS_EPS_WAD,0,COLUMN()) | C40: =INDEX(MO_RIS_EPS_WAD,0,COLUMN()) | D40: =INDEX(MO_RIS_EPS_WAD,0,COLUMN()) | E40: =INDEX(MO_RIS_EPS_WAD,0,COLUMN()) | F40: =INDEX(MO_RIS_EPS_WAD,0,COLUMN()) | G40: =INDEX(MO_RIS_EPS_WAD,0,COLUMN()) | H40: =INDEX(MO_RIS_EPS_WAD,0,COLUMN()) | I40: =INDEX(MO_RIS_EPS_WAD,0,COLUMN()) | J40: =INDEX(MO_RIS_EPS_WAD,0,COLUMN()) | ... CB40: =INDEX(MO_RIS_EPS_WAD,0,COLUMN())
A41: =INDEX(MO_RIS_ShareCount_WAD_Adj,0,COLUMN()) | C41: =INDEX(MO_RIS_ShareCount_WAD_Adj,0,COLUMN()) | D41: =INDEX(MO_RIS_ShareCount_WAD_Adj,0,COLUMN()) | E41: =INDEX(MO_RIS_ShareCount_WAD_Adj,0,COLUMN()) | F41: =INDEX(MO_RIS_ShareCount_WAD_Adj,0,COLUMN()) | G41: =INDEX(MO_RIS_ShareCount_WAD_Adj,0,COLUMN()) | H41: =INDEX(MO_RIS_ShareCount_WAD_Adj,0,COLUMN()) | I41: =INDEX(MO_RIS_ShareCount_WAD_Adj,0,COLUMN()) | J41: =INDEX(MO_RIS_ShareCount_WAD_Adj,0,COLUMN()) | ... CB41: =INDEX(MO_RIS_ShareCount_WAD_Adj,0,COLUMN())
A43: Non-GAAP Financials
A44: =INDEX(MO_RIS_EBITDA_Adj,0,COLUMN()) | C44: =INDEX(MO_RIS_EBITDA_Adj,0,COLUMN()) | D44: =INDEX(MO_RIS_EBITDA_Adj,0,COLUMN()) | E44: =INDEX(MO_RIS_EBITDA_Adj,0,COLUMN()) | F44: =INDEX(MO_RIS_EBITDA_Adj,0,COLUMN()) | G44: =INDEX(MO_RIS_EBITDA_Adj,0,COLUMN()) | H44: =INDEX(MO_RIS_EBITDA_Adj,0,COLUMN()) | I44: =INDEX(MO_RIS_EBITDA_Adj,0,COLUMN()) | J44: =INDEX(MO_RIS_EBITDA_Adj,0,COLUMN()) | ... CB44: =INDEX(MO_RIS_EBITDA_Adj,0,COLUMN())
A45: =INDEX(MO_RIS_EBIT_Adj,0,COLUMN()) | C45: =INDEX(MO_RIS_EBIT_Adj,0,COLUMN()) | D45: =INDEX(MO_RIS_EBIT_Adj,0,COLUMN()) | E45: =INDEX(MO_RIS_EBIT_Adj,0,COLUMN()) | F45: =INDEX(MO_RIS_EBIT_Adj,0,COLUMN()) | G45: =INDEX(MO_RIS_EBIT_Adj,0,COLUMN()) | H45: =INDEX(MO_RIS_EBIT_Adj,0,COLUMN()) | I45: =INDEX(MO_RIS_EBIT_Adj,0,COLUMN()) | J45: =INDEX(MO_RIS_EBIT_Adj,0,COLUMN()) | ... CB45: =INDEX(MO_RIS_EBIT_Adj,0,COLUMN())
A46: =INDEX(MO_RIS_NI_NONGAAP_Diluted,0,COLUMN()) | C46: =INDEX(MO_RIS_NI_NONGAAP_Diluted,0,COLUMN()) | D46: =INDEX(MO_RIS_NI_NONGAAP_Diluted,0,COLUMN()) | E46: =INDEX(MO_RIS_NI_NONGAAP_Diluted,0,COLUMN()) | F46: =INDEX(MO_RIS_NI_NONGAAP_Diluted,0,COLUMN()) | G46: =INDEX(MO_RIS_NI_NONGAAP_Diluted,0,COLUMN()) | H46: =INDEX(MO_RIS_NI_NONGAAP_Diluted,0,COLUMN()) | I46: =INDEX(MO_RIS_NI_NONGAAP_Diluted,0,COLUMN()) | J46: =INDEX(MO_RIS_NI_NONGAAP_Diluted,0,COLUMN()) | ... CB46: =INDEX(MO_RIS_NI_NONGAAP_Diluted,0,COLUMN())
A47: =INDEX(MO_RIS_EPS_WAD_Adj,0,COLUMN()) | C47: =INDEX(MO_RIS_EPS_WAD_Adj,0,COLUMN()) | D47: =INDEX(MO_RIS_EPS_WAD_Adj,0,COLUMN()) | E47: =INDEX(MO_RIS_EPS_WAD_Adj,0,COLUMN()) | F47: =INDEX(MO_RIS_EPS_WAD_Adj,0,COLUMN()) | G47: =INDEX(MO_RIS_EPS_WAD_Adj,0,COLUMN()) | H47: =INDEX(MO_RIS_EPS_WAD_Adj,0,COLUMN()) | I47: =INDEX(MO_RIS_EPS_WAD_Adj,0,COLUMN()) | J47: =INDEX(MO_RIS_EPS_WAD_Adj,0,COLUMN()) | ... CB47: =INDEX(MO_RIS_EPS_WAD_Adj,0,COLUMN())
A49: Margin Analysis
A50: =INDEX(MO_MA_COGS,0,COLUMN()) | C50: =INDEX(MO_MA_COGS,0,COLUMN()) | D50: =INDEX(MO_MA_COGS,0,COLUMN()) | E50: =INDEX(MO_MA_COGS,0,COLUMN()) | F50: =INDEX(MO_MA_COGS,0,COLUMN()) | G50: =INDEX(MO_MA_COGS,0,COLUMN()) | H50: =INDEX(MO_MA_COGS,0,COLUMN()) | I50: =INDEX(MO_MA_COGS,0,COLUMN()) | J50: =INDEX(MO_MA_COGS,0,COLUMN()) | ... CB50: =INDEX(MO_MA_COGS,0,COLUMN())
A51: =INDEX(MO_MA_GA,0,COLUMN()) | C51: =INDEX(MO_MA_GA,0,COLUMN()) | D51: =INDEX(MO_MA_GA,0,COLUMN()) | E51: =INDEX(MO_MA_GA,0,COLUMN()) | F51: =INDEX(MO_MA_GA,0,COLUMN()) | G51: =INDEX(MO_MA_GA,0,COLUMN()) | H51: =INDEX(MO_MA_GA,0,COLUMN()) | I51: =INDEX(MO_MA_GA,0,COLUMN()) | J51: =INDEX(MO_MA_GA,0,COLUMN()) | ... CB51: =INDEX(MO_MA_GA,0,COLUMN())
A52: =INDEX(MO_MA_SM,0,COLUMN()) | C52: =INDEX(MO_MA_SM,0,COLUMN()) | D52: =INDEX(MO_MA_SM,0,COLUMN()) | E52: =INDEX(MO_MA_SM,0,COLUMN()) | F52: =INDEX(MO_MA_SM,0,COLUMN()) | G52: =INDEX(MO_MA_SM,0,COLUMN()) | H52: =INDEX(MO_MA_SM,0,COLUMN()) | I52: =INDEX(MO_MA_SM,0,COLUMN()) | J52: =INDEX(MO_MA_SM,0,COLUMN()) | ... CB52: =INDEX(MO_MA_SM,0,COLUMN())
A53: =INDEX(MO_MA_SGA,0,COLUMN()) | C53: =INDEX(SP_GF_SGA,0,COLUMN())/INDEX(SP_GF_Rev,0,COLUMN()) | D53: =INDEX(SP_GF_SGA,0,COLUMN())/INDEX(SP_GF_Rev,0,COLUMN()) | E53: =INDEX(SP_GF_SGA,0,COLUMN())/INDEX(SP_GF_Rev,0,COLUMN()) | F53: =INDEX(SP_GF_SGA,0,COLUMN())/INDEX(SP_GF_Rev,0,COLUMN()) | G53: =INDEX(SP_GF_SGA,0,COLUMN())/INDEX(SP_GF_Rev,0,COLUMN()) | H53: =INDEX(SP_GF_SGA,0,COLUMN())/INDEX(SP_GF_Rev,0,COLUMN()) | I53: =INDEX(SP_GF_SGA,0,COLUMN())/INDEX(SP_GF_Rev,0,COLUMN()) | J53: =INDEX(SP_GF_SGA,0,COLUMN())/INDEX(SP_GF_Rev,0,COLUMN()) | ... CB53: =INDEX(SP_GF_SGA,0,COLUMN())/INDEX(SP_GF_Rev,0,COLUMN())
A54: =INDEX(MO_MA_RD,0,COLUMN()) | C54: =INDEX(SP_GF_RD,0,COLUMN())/INDEX(SP_GF_Rev,0,COLUMN()) | D54: =INDEX(SP_GF_RD,0,COLUMN())/INDEX(SP_GF_Rev,0,COLUMN()) | E54: =INDEX(SP_GF_RD,0,COLUMN())/INDEX(SP_GF_Rev,0,COLUMN()) | F54: =INDEX(SP_GF_RD,0,COLUMN())/INDEX(SP_GF_Rev,0,COLUMN()) | G54: =INDEX(SP_GF_RD,0,COLUMN())/INDEX(SP_GF_Rev,0,COLUMN()) | H54: =INDEX(SP_GF_RD,0,COLUMN())/INDEX(SP_GF_Rev,0,COLUMN()) | I54: =INDEX(SP_GF_RD,0,COLUMN())/INDEX(SP_GF_Rev,0,COLUMN()) | J54: =INDEX(SP_GF_RD,0,COLUMN())/INDEX(SP_GF_Rev,0,COLUMN()) | ... CB54: =INDEX(SP_GF_RD,0,COLUMN())/INDEX(SP_GF_Rev,0,COLUMN())
A55: =INDEX(MO_MA_OI_Operating,0,COLUMN()) | C55: =INDEX(MO_MA_OI_Operating,0,COLUMN()) | D55: =INDEX(MO_MA_OI_Operating,0,COLUMN()) | E55: =INDEX(MO_MA_OI_Operating,0,COLUMN()) | F55: =INDEX(MO_MA_OI_Operating,0,COLUMN()) | G55: =INDEX(MO_MA_OI_Operating,0,COLUMN()) | H55: =INDEX(MO_MA_OI_Operating,0,COLUMN()) | I55: =INDEX(MO_MA_OI_Operating,0,COLUMN()) | J55: =INDEX(MO_MA_OI_Operating,0,COLUMN()) | ... CB55: =INDEX(MO_MA_OI_Operating,0,COLUMN())
A56: =INDEX(MO_MA_EBIT,0,COLUMN()) | C56: =INDEX(MO_MA_EBIT,0,COLUMN()) | D56: =INDEX(MO_MA_EBIT,0,COLUMN()) | E56: =INDEX(MO_MA_EBIT,0,COLUMN()) | F56: =INDEX(MO_MA_EBIT,0,COLUMN()) | G56: =INDEX(MO_MA_EBIT,0,COLUMN()) | H56: =INDEX(MO_MA_EBIT,0,COLUMN()) | I56: =INDEX(MO_MA_EBIT,0,COLUMN()) | J56: =INDEX(MO_MA_EBIT,0,COLUMN()) | ... CB56: =INDEX(MO_MA_EBIT,0,COLUMN())
A57: =INDEX(MO_MA_EBIT_Adj,0,COLUMN()) | C57: =INDEX(MO_MA_EBIT_Adj,0,COLUMN()) | D57: =INDEX(MO_MA_EBIT_Adj,0,COLUMN()) | E57: =INDEX(MO_MA_EBIT_Adj,0,COLUMN()) | F57: =INDEX(MO_MA_EBIT_Adj,0,COLUMN()) | G57: =INDEX(MO_MA_EBIT_Adj,0,COLUMN()) | H57: =INDEX(MO_MA_EBIT_Adj,0,COLUMN()) | I57: =INDEX(MO_MA_EBIT_Adj,0,COLUMN()) | J57: =INDEX(MO_MA_EBIT_Adj,0,COLUMN()) | ... CB57: =INDEX(MO_MA_EBIT_Adj,0,COLUMN())
A58: =INDEX(MO_MA_EBITDA,0,COLUMN()) | C58: =INDEX(MO_MA_EBITDA,0,COLUMN()) | D58: =INDEX(MO_MA_EBITDA,0,COLUMN()) | E58: =INDEX(MO_MA_EBITDA,0,COLUMN()) | F58: =INDEX(MO_MA_EBITDA,0,COLUMN()) | G58: =INDEX(MO_MA_EBITDA,0,COLUMN()) | H58: =INDEX(MO_MA_EBITDA,0,COLUMN()) | I58: =INDEX(MO_MA_EBITDA,0,COLUMN()) | J58: =INDEX(MO_MA_EBITDA,0,COLUMN()) | ... CB58: =INDEX(MO_MA_EBITDA,0,COLUMN())
A59: =INDEX(MO_MA_EBITDA_Adj,0,COLUMN()) | C59: =INDEX(SP_NGF_EBITDA,0,COLUMN())/INDEX(SP_GF_Rev,0,COLUMN()) | D59: =INDEX(SP_NGF_EBITDA,0,COLUMN())/INDEX(SP_GF_Rev,0,COLUMN()) | E59: =INDEX(SP_NGF_EBITDA,0,COLUMN())/INDEX(SP_GF_Rev,0,COLUMN()) | F59: =INDEX(SP_NGF_EBITDA,0,COLUMN())/INDEX(SP_GF_Rev,0,COLUMN()) | G59: =INDEX(SP_NGF_EBITDA,0,COLUMN())/INDEX(SP_GF_Rev,0,COLUMN()) | H59: =INDEX(SP_NGF_EBITDA,0,COLUMN())/INDEX(SP_GF_Rev,0,COLUMN()) | I59: =INDEX(SP_NGF_EBITDA,0,COLUMN())/INDEX(SP_GF_Rev,0,COLUMN()) | J59: =INDEX(SP_NGF_EBITDA,0,COLUMN())/INDEX(SP_GF_Rev,0,COLUMN()) | ... CB59: =INDEX(SP_NGF_EBITDA,0,COLUMN())/INDEX(SP_GF_Rev,0,COLUMN())
A61: Cash Flow Analysis
A62: =INDEX(MO_CFSum_CFO_BeforeWC,0,COLUMN()) | C62: =INDEX(MO_CFSum_CFO_BeforeWC,0,COLUMN()) | D62: =INDEX(MO_CFSum_CFO_BeforeWC,0,COLUMN()) | E62: =INDEX(MO_CFSum_CFO_BeforeWC,0,COLUMN()) | F62: =INDEX(MO_CFSum_CFO_BeforeWC,0,COLUMN()) | G62: =INDEX(MO_CFSum_CFO_BeforeWC,0,COLUMN()) | H62: =INDEX(MO_CFSum_CFO_BeforeWC,0,COLUMN()) | I62: =INDEX(MO_CFSum_CFO_BeforeWC,0,COLUMN()) | J62: =INDEX(MO_CFSum_CFO_BeforeWC,0,COLUMN()) | ... CB62: =INDEX(MO_CFSum_CFO_BeforeWC,0,COLUMN())
A63: Change in WC | C63: =SUM(OFFSET(INDEX(MO_CFS_CFO_BeforeWC,0,COLUMN()),1,0,ROW(INDEX(MO_CFS_CFO,0,COLUMN()))-ROW(INDEX(MO_CFS_CFO_BeforeWC,0,COLUMN()))-1,1)) | D63: =SUM(OFFSET(INDEX(MO_CFS_CFO_BeforeWC,0,COLUMN()),1,0,ROW(INDEX(MO_CFS_CFO,0,COLUMN()))-ROW(INDEX(MO_CFS_CFO_BeforeWC,0,COLUMN()))-1,1)) | E63: =SUM(OFFSET(INDEX(MO_CFS_CFO_BeforeWC,0,COLUMN()),1,0,ROW(INDEX(MO_CFS_CFO,0,COLUMN()))-ROW(INDEX(MO_CFS_CFO_BeforeWC,0,COLUMN()))-1,1)) | F63: =SUM(OFFSET(INDEX(MO_CFS_CFO_BeforeWC,0,COLUMN()),1,0,ROW(INDEX(MO_CFS_CFO,0,COLUMN()))-ROW(INDEX(MO_CFS_CFO_BeforeWC,0,COLUMN()))-1,1)) | G63: =SUM(OFFSET(INDEX(MO_CFS_CFO_BeforeWC,0,COLUMN()),1,0,ROW(INDEX(MO_CFS_CFO,0,COLUMN()))-ROW(INDEX(MO_CFS_CFO_BeforeWC,0,COLUMN()))-1,1)) | H63: =SUM(OFFSET(INDEX(MO_CFS_CFO_BeforeWC,0,COLUMN()),1,0,ROW(INDEX(MO_CFS_CFO,0,COLUMN()))-ROW(INDEX(MO_CFS_CFO_BeforeWC,0,COLUMN()))-1,1)) | I63: =SUM(OFFSET(INDEX(MO_CFS_CFO_BeforeWC,0,COLUMN()),1,0,ROW(INDEX(MO_CFS_CFO,0,COLUMN()))-ROW(INDEX(MO_CFS_CFO_BeforeWC,0,COLUMN()))-1,1)) | J63: =SUM(OFFSET(INDEX(MO_CFS_CFO_BeforeWC,0,COLUMN()),1,0,ROW(INDEX(MO_CFS_CFO,0,COLUMN()))-ROW(INDEX(MO_CFS_CFO_BeforeWC,0,COLUMN()))-1,1)) | ... CB63: =SUM(OFFSET(INDEX(MO_CFS_CFO_BeforeWC,0,COLUMN()),1,0,ROW(INDEX(MO_CFS_CFO,0,COLUMN()))-ROW(INDEX(MO_CFS_CFO_BeforeWC,0,COLUMN()))-1,1))
A64: Operating Cash Flow after WC | C64: =SUM(C62:C63) | D64: =SUM(D62:D63) | E64: =SUM(E62:E63) | F64: =SUM(F62:F63) | G64: =SUM(G62:G63) | H64: =SUM(H62:H63) | I64: =SUM(I62:I63) | J64: =SUM(J62:J63) | ... CB64: =SUM(CB62:CB63)
A65: =INDEX(MO_CFSum_Capex,0,COLUMN()) | C65: =INDEX(MO_CFSum_Capex,0,COLUMN()) | D65: =INDEX(MO_CFSum_Capex,0,COLUMN()) | E65: =INDEX(MO_CFSum_Capex,0,COLUMN()) | F65: =INDEX(MO_CFSum_Capex,0,COLUMN()) | G65: =INDEX(MO_CFSum_Capex,0,COLUMN()) | H65: =INDEX(MO_CFSum_Capex,0,COLUMN()) | I65: =INDEX(MO_CFSum_Capex,0,COLUMN()) | J65: =INDEX(MO_CFSum_Capex,0,COLUMN()) | ... CB65: =INDEX(MO_CFSum_Capex,0,COLUMN())
A66: Core FCF, Pre Div | C66: =SUM(C64:C65) | D66: =SUM(D64:D65) | E66: =SUM(E64:E65) | F66: =SUM(F64:F65) | G66: =SUM(G64:G65) | H66: =SUM(H64:H65) | I66: =SUM(I64:I65) | J66: =SUM(J64:J65) | ... CB66: =SUM(CB64:CB65)
A67: =INDEX(MO_CFSum_Dividend,0,COLUMN()) | C67: =INDEX(MO_CFSum_Dividend,0,COLUMN()) | D67: =INDEX(MO_CFSum_Dividend,0,COLUMN()) | E67: =INDEX(MO_CFSum_Dividend,0,COLUMN()) | F67: =INDEX(MO_CFSum_Dividend,0,COLUMN()) | G67: =INDEX(MO_CFSum_Dividend,0,COLUMN()) | H67: =INDEX(MO_CFSum_Dividend,0,COLUMN()) | I67: =INDEX(MO_CFSum_Dividend,0,COLUMN()) | J67: =INDEX(MO_CFSum_Dividend,0,COLUMN()) | ... CB67: =INDEX(MO_CFSum_Dividend,0,COLUMN())
A68: Core FCF, Post Div | C68: =SUM(C66:C67) | D68: =SUM(D66:D67) | E68: =SUM(E66:E67) | F68: =SUM(F66:F67) | G68: =SUM(G66:G67) | H68: =SUM(H66:H67) | I68: =SUM(I66:I67) | J68: =SUM(J66:J67) | ... CB68: =SUM(CB66:CB67)
A69: =INDEX(MO_CFSum_Acquisition,0,COLUMN()) | C69: =INDEX(MO_CFSum_Acquisition,0,COLUMN()) | D69: =INDEX(MO_CFSum_Acquisition,0,COLUMN()) | E69: =INDEX(MO_CFSum_Acquisition,0,COLUMN()) | F69: =INDEX(MO_CFSum_Acquisition,0,COLUMN()) | G69: =INDEX(MO_CFSum_Acquisition,0,COLUMN()) | H69: =INDEX(MO_CFSum_Acquisition,0,COLUMN()) | I69: =INDEX(MO_CFSum_Acquisition,0,COLUMN()) | J69: =INDEX(MO_CFSum_Acquisition,0,COLUMN()) | ... CB69: =INDEX(MO_CFSum_Acquisition,0,COLUMN())
A70: =INDEX(MO_CFSum_Divestiture,0,COLUMN()) | C70: =INDEX(MO_CFSum_Divestiture,0,COLUMN()) | D70: =INDEX(MO_CFSum_Divestiture,0,COLUMN()) | E70: =INDEX(MO_CFSum_Divestiture,0,COLUMN()) | F70: =INDEX(MO_CFSum_Divestiture,0,COLUMN()) | G70: =INDEX(MO_CFSum_Divestiture,0,COLUMN()) | H70: =INDEX(MO_CFSum_Divestiture,0,COLUMN()) | I70: =INDEX(MO_CFSum_Divestiture,0,COLUMN()) | J70: =INDEX(MO_CFSum_Divestiture,0,COLUMN()) | ... CB70: =INDEX(MO_CFSum_Divestiture,0,COLUMN())
A71: New Equity Issuance | C71: =INDEX(MO_CFSum_NetShares,0,COLUMN()) | D71: =INDEX(MO_CFSum_NetShares,0,COLUMN()) | E71: =INDEX(MO_CFSum_NetShares,0,COLUMN()) | F71: =INDEX(MO_CFSum_NetShares,0,COLUMN()) | G71: =INDEX(MO_CFSum_NetShares,0,COLUMN()) | H71: =INDEX(MO_CFSum_NetShares,0,COLUMN()) | I71: =INDEX(MO_CFSum_NetShares,0,COLUMN()) | J71: =INDEX(MO_CFSum_NetShares,0,COLUMN()) | ... CB71: =INDEX(MO_CFSum_NetShares,0,COLUMN())
A72: New Debt Issuance | C72: =INDEX(MO_CFSum_NetDebtIssuance,0,COLUMN()) | D72: =INDEX(MO_CFSum_NetDebtIssuance,0,COLUMN()) | E72: =INDEX(MO_CFSum_NetDebtIssuance,0,COLUMN()) | F72: =INDEX(MO_CFSum_NetDebtIssuance,0,COLUMN()) | G72: =INDEX(MO_CFSum_NetDebtIssuance,0,COLUMN()) | H72: =INDEX(MO_CFSum_NetDebtIssuance,0,COLUMN()) | I72: =INDEX(MO_CFSum_NetDebtIssuance,0,COLUMN()) | J72: =INDEX(MO_CFSum_NetDebtIssuance,0,COLUMN()) | ... CB72: =INDEX(MO_CFSum_NetDebtIssuance,0,COLUMN())
A73: Other Items | C73: =Model!C740+Model!C741+Model!C742+Model!C743+Model!C746+Model!C752+Model!C753+Model!C754+Model!C755+Model!C757+Model!C763+Model!C764+Model!C766+Model!C767+Model!C768+Model!C769+Model!C770+Model!C773+Model!C774+Model!C776+Model!C777+Model!C779+Model!C793+Model!C798+Model!C799+Model!C800+Model!C805+Model!C809+Model!C810+Model!C748+Model!C760+Model!C761+Model!C765+Model!C780+Model!C806+Model!C749+Model!C758+Model!C747+Model!C759+Model!C794+Model!C795+Model!C796+Model!C775+Model!C804+Model!C785+Model!C771+Model!C772 | D73: =Model!D740+Model!D741+Model!D742+Model!D743+Model!D746+Model!D752+Model!D753+Model!D754+Model!D755+Model!D757+Model!D763+Model!D764+Model!D766+Model!D767+Model!D768+Model!D769+Model!D770+Model!D773+Model!D774+Model!D776+Model!D777+Model!D779+Model!D793+Model!D798+Model!D799+Model!D800+Model!D805+Model!D809+Model!D810+Model!D748+Model!D760+Model!D761+Model!D765+Model!D780+Model!D806+Model!D749+Model!D758+Model!D747+Model!D759+Model!D794+Model!D795+Model!D796+Model!D775+Model!D804+Model!D785+Model!D771+Model!D772 | E73: =Model!E740+Model!E741+Model!E742+Model!E743+Model!E746+Model!E752+Model!E753+Model!E754+Model!E755+Model!E757+Model!E763+Model!E764+Model!E766+Model!E767+Model!E768+Model!E769+Model!E770+Model!E773+Model!E774+Model!E776+Model!E777+Model!E779+Model!E793+Model!E798+Model!E799+Model!E800+Model!E805+Model!E809+Model!E810+Model!E748+Model!E760+Model!E761+Model!E765+Model!E780+Model!E806+Model!E749+Model!E758+Model!E747+Model!E759+Model!E794+Model!E795+Model!E796+Model!E775+Model!E804+Model!E785+Model!E771+Model!E772 | F73: =Model!F740+Model!F741+Model!F742+Model!F743+Model!F746+Model!F752+Model!F753+Model!F754+Model!F755+Model!F757+Model!F763+Model!F764+Model!F766+Model!F767+Model!F768+Model!F769+Model!F770+Model!F773+Model!F774+Model!F776+Model!F777+Model!F779+Model!F793+Model!F798+Model!F799+Model!F800+Model!F805+Model!F809+Model!F810+Model!F748+Model!F760+Model!F761+Model!F765+Model!F780+Model!F806+Model!F749+Model!F758+Model!F747+Model!F759+Model!F794+Model!F795+Model!F796+Model!F775+Model!F804+Model!F785+Model!F771+Model!F772 | G73: =Model!G740+Model!G741+Model!G742+Model!G743+Model!G746+Model!G752+Model!G753+Model!G754+Model!G755+Model!G757+Model!G763+Model!G764+Model!G766+Model!G767+Model!G768+Model!G769+Model!G770+Model!G773+Model!G774+Model!G776+Model!G777+Model!G779+Model!G793+Model!G798+Model!G799+Model!G800+Model!G805+Model!G809+Model!G810+Model!G748+Model!G760+Model!G761+Model!G765+Model!G780+Model!G806+Model!G749+Model!G758+Model!G747+Model!G759+Model!G794+Model!G795+Model!G796+Model!G775+Model!G804+Model!G785+Model!G771+Model!G772 | H73: =Model!H740+Model!H741+Model!H742+Model!H743+Model!H746+Model!H752+Model!H753+Model!H754+Model!H755+Model!H757+Model!H763+Model!H764+Model!H766+Model!H767+Model!H768+Model!H769+Model!H770+Model!H773+Model!H774+Model!H776+Model!H777+Model!H779+Model!H793+Model!H798+Model!H799+Model!H800+Model!H805+Model!H809+Model!H810+Model!H748+Model!H760+Model!H761+Model!H765+Model!H780+Model!H806+Model!H749+Model!H758+Model!H747+Model!H759+Model!H794+Model!H795+Model!H796+Model!H775+Model!H804+Model!H785+Model!H771+Model!H772 | I73: =Model!I740+Model!I741+Model!I742+Model!I743+Model!I746+Model!I752+Model!I753+Model!I754+Model!I755+Model!I757+Model!I763+Model!I764+Model!I766+Model!I767+Model!I768+Model!I769+Model!I770+Model!I773+Model!I774+Model!I776+Model!I777+Model!I779+Model!I793+Model!I798+Model!I799+Model!I800+Model!I805+Model!I809+Model!I810+Model!I748+Model!I760+Model!I761+Model!I765+Model!I780+Model!I806+Model!I749+Model!I758+Model!I747+Model!I759+Model!I794+Model!I795+Model!I796+Model!I775+Model!I804+Model!I785+Model!I771+Model!I772 | J73: =Model!J740+Model!J741+Model!J742+Model!J743+Model!J746+Model!J752+Model!J753+Model!J754+Model!J755+Model!J757+Model!J763+Model!J764+Model!J766+Model!J767+Model!J768+Model!J769+Model!J770+Model!J773+Model!J774+Model!J776+Model!J777+Model!J779+Model!J793+Model!J798+Model!J799+Model!J800+Model!J805+Model!J809+Model!J810+Model!J748+Model!J760+Model!J761+Model!J765+Model!J780+Model!J806+Model!J749+Model!J758+Model!J747+Model!J759+Model!J794+Model!J795+Model!J796+Model!J775+Model!J804+Model!J785+Model!J771+Model!J772 | ... BE73: =Model!BE740+Model!BE741+Model!BE742+Model!BE743+Model!BE746+Model!BE752+Model!BE753+Model!BE754+Model!BE755+Model!BE757+Model!BE763+Model!BE764+Model!BE766+Model!BE767+Model!BE768+Model!BE769+Model!BE770+Model!BE773+Model!BE774+Model!BE776+Model!BE777+Model!BE779+Model!BE793+Model!BE798+Model!BE799+Model!BE800+Model!BE805+Model!BE809+Model!BE810+Model!BE748+Model!BE760+Model!BE761+Model!BE765+Model!BE780+Model!BE806+Model!BE749+Model!BE758+Model!BE747+Model!BE759+Model!BE794+Model!BE795+Model!BE796+Model!BE775+Model!BE804+Model!BE785+Model!BE771+Model!BE772 | BF73: =Model!BF740+Model!BF741+Model!BF742+Model!BF743+Model!BF746+Model!BF752+Model!BF753+Model!BF754+Model!BF755+Model!BF757+Model!BF763+Model!BF764+Model!BF766+Model!BF767+Model!BF768+Model!BF769+Model!BF770+Model!BF771+Model!BF772+Model!BF773+Model!BF774+Model!BF776+Model!BF777+Model!BF779+Model!BF793+Model!BF797+Model!BF798+Model!BF799+Model!BF800+Model!BF805+Model!BF809+Model!BF810+Model!BF748+Model!BF760+Model!BF761+Model!BF765+Model!BF780+Model!BF806+Model!BF749+Model!BF758+Model!BF747+Model!BF759+Model!BF794+Model!BF795+Model!BF796+Model!BF775+Model!BF804+Model!BF785+Model!BF751 | BG73: =Model!BG740+Model!BG741+Model!BG742+Model!BG743+Model!BG746+Model!BG752+Model!BG753+Model!BG754+Model!BG755+Model!BG757+Model!BG763+Model!BG764+Model!BG766+Model!BG767+Model!BG768+Model!BG769+Model!BG770+Model!BG771+Model!BG772+Model!BG773+Model!BG774+Model!BG776+Model!BG777+Model!BG779+Model!BG793+Model!BG797+Model!BG798+Model!BG799+Model!BG800+Model!BG805+Model!BG809+Model!BG810+Model!BG748+Model!BG760+Model!BG761+Model!BG765+Model!BG780+Model!BG806+Model!BG749+Model!BG758+Model!BG747+Model!BG759+Model!BG794+Model!BG795+Model!BG796+Model!BG775+Model!BG804+Model!BG785+Model!BG751 | BH73: =Model!BH740+Model!BH741+Model!BH742+Model!BH743+Model!BH746+Model!BH752+Model!BH753+Model!BH754+Model!BH755+Model!BH757+Model!BH763+Model!BH764+Model!BH766+Model!BH767+Model!BH768+Model!BH769+Model!BH770+Model!BH771+Model!BH772+Model!BH773+Model!BH774+Model!BH776+Model!BH777+Model!BH779+Model!BH793+Model!BH797+Model!BH798+Model!BH799+Model!BH800+Model!BH805+Model!BH809+Model!BH810+Model!BH748+Model!BH760+Model!BH761+Model!BH765+Model!BH780+Model!BH806+Model!BH749+Model!BH758+Model!BH747+Model!BH759+Model!BH794+Model!BH795+Model!BH796+Model!BH775+Model!BH804+Model!BH785+Model!BH751 | BI73: =Model!BI740+Model!BI741+Model!BI742+Model!BI743+Model!BI746+Model!BI752+Model!BI753+Model!BI754+Model!BI755+Model!BI757+Model!BI763+Model!BI764+Model!BI766+Model!BI767+Model!BI768+Model!BI769+Model!BI770+Model!BI771+Model!BI772+Model!BI773+Model!BI774+Model!BI776+Model!BI777+Model!BI779+Model!BI793+Model!BI797+Model!BI798+Model!BI799+Model!BI800+Model!BI805+Model!BI809+Model!BI810+Model!BI748+Model!BI760+Model!BI761+Model!BI765+Model!BI780+Model!BI806+Model!BI749+Model!BI758+Model!BI747+Model!BI759+Model!BI794+Model!BI795+Model!BI796+Model!BI775+Model!BI804+Model!BI785+Model!BI751 | BJ73: =Model!BJ740+Model!BJ741+Model!BJ742+Model!BJ743+Model!BJ746+Model!BJ752+Model!BJ753+Model!BJ754+Model!BJ755+Model!BJ757+Model!BJ763+Model!BJ764+Model!BJ766+Model!BJ767+Model!BJ768+Model!BJ769+Model!BJ770+Model!BJ771+Model!BJ772+Model!BJ773+Model!BJ774+Model!BJ776+Model!BJ777+Model!BJ779+Model!BJ793+Model!BJ797+Model!BJ798+Model!BJ799+Model!BJ800+Model!BJ805+Model!BJ809+Model!BJ810+Model!BJ748+Model!BJ760+Model!BJ761+Model!BJ765+Model!BJ780+Model!BJ806+Model!BJ749+Model!BJ758+Model!BJ747+Model!BJ759+Model!BJ794+Model!BJ795+Model!BJ796+Model!BJ775+Model!BJ804+Model!BJ785+Model!BJ751 | BK73: =Model!BK740+Model!BK741+Model!BK742+Model!BK743+Model!BK746+Model!BK752+Model!BK753+Model!BK754+Model!BK755+Model!BK757+Model!BK763+Model!BK764+Model!BK766+Model!BK767+Model!BK768+Model!BK769+Model!BK770+Model!BK771+Model!BK772+Model!BK773+Model!BK774+Model!BK776+Model!BK777+Model!BK779+Model!BK793+Model!BK797+Model!BK798+Model!BK799+Model!BK800+Model!BK805+Model!BK809+Model!BK810+Model!BK748+Model!BK760+Model!BK761+Model!BK765+Model!BK780+Model!BK806+Model!BK749+Model!BK758+Model!BK747+Model!BK759+Model!BK794+Model!BK795+Model!BK796+Model!BK775+Model!BK804+Model!BK785+Model!BK751+Model!BK750 | BL73: =Model!BL740+Model!BL741+Model!BL742+Model!BL743+Model!BL746+Model!BL752+Model!BL753+Model!BL754+Model!BL755+Model!BL757+Model!BL763+Model!BL764+Model!BL766+Model!BL767+Model!BL768+Model!BL769+Model!BL770+Model!BL771+Model!BL772+Model!BL773+Model!BL774+Model!BL776+Model!BL777+Model!BL779+Model!BL793+Model!BL797+Model!BL798+Model!BL799+Model!BL800+Model!BL805+Model!BL809+Model!BL810+Model!BL748+Model!BL760+Model!BL761+Model!BL765+Model!BL780+Model!BL806+Model!BL749+Model!BL758+Model!BL747+Model!BL759+Model!BL794+Model!BL795+Model!BL796+Model!BL775+Model!BL804+Model!BL785+Model!BL751+Model!BL750 | BM73: =Model!BM740+Model!BM741+Model!BM742+Model!BM743+Model!BM746+Model!BM752+Model!BM753+Model!BM754+Model!BM755+Model!BM757+Model!BM763+Model!BM764+Model!BM766+Model!BM767+Model!BM768+Model!BM769+Model!BM770+Model!BM771+Model!BM772+Model!BM773+Model!BM774+Model!BM776+Model!BM777+Model!BM779+Model!BM793+Model!BM797+Model!BM798+Model!BM799+Model!BM800+Model!BM805+Model!BM809+Model!BM810+Model!BM748+Model!BM760+Model!BM761+Model!BM765+Model!BM780+Model!BM806+Model!BM749+Model!BM758+Model!BM747+Model!BM759+Model!BM794+Model!BM795+Model!BM796+Model!BM775+Model!BM804+Model!BM785+Model!BM751+Model!BM750 | BN73: =Model!BN740+Model!BN741+Model!BN742+Model!BN743+Model!BN746+Model!BN752+Model!BN753+Model!BN754+Model!BN755+Model!BN757+Model!BN763+Model!BN764+Model!BN766+Model!BN767+Model!BN768+Model!BN769+Model!BN770+Model!BN771+Model!BN772+Model!BN773+Model!BN774+Model!BN776+Model!BN777+Model!BN779+Model!BN793+Model!BN797+Model!BN798+Model!BN799+Model!BN800+Model!BN805+Model!BN809+Model!BN810+Model!BN748+Model!BN760+Model!BN761+Model!BN765+Model!BN780+Model!BN806+Model!BN749+Model!BN758+Model!BN747+Model!BN759+Model!BN794+Model!BN795+Model!BN796+Model!BN775+Model!BN804+Model!BN785+Model!BN751+Model!BN750 | BO73: =Model!BO740+Model!BO741+Model!BO742+Model!BO743+Model!BO746+Model!BO752+Model!BO753+Model!BO754+Model!BO755+Model!BO757+Model!BO763+Model!BO764+Model!BO766+Model!BO767+Model!BO768+Model!BO769+Model!BO770+Model!BO771+Model!BO772+Model!BO773+Model!BO774+Model!BO776+Model!BO777+Model!BO779+Model!BO793+Model!BO797+Model!BO798+Model!BO799+Model!BO800+Model!BO805+Model!BO809+Model!BO810+Model!BO748+Model!BO760+Model!BO761+Model!BO765+Model!BO780+Model!BO806+Model!BO749+Model!BO758+Model!BO747+Model!BO759+Model!BO794+Model!BO795+Model!BO796+Model!BO775+Model!BO804+Model!BO785+Model!BO751+Model!BO750 | BP73: =Model!BP740+Model!BP741+Model!BP742+Model!BP743+Model!BP746+Model!BP752+Model!BP753+Model!BP754+Model!BP755+Model!BP757+Model!BP763+Model!BP764+Model!BP766+Model!BP767+Model!BP768+Model!BP769+Model!BP770+Model!BP771+Model!BP772+Model!BP773+Model!BP774+Model!BP776+Model!BP777+Model!BP779+Model!BP793+Model!BP797+Model!BP798+Model!BP799+Model!BP800+Model!BP805+Model!BP809+Model!BP810+Model!BP748+Model!BP760+Model!BP761+Model!BP765+Model!BP780+Model!BP806+Model!BP749+Model!BP758+Model!BP747+Model!BP759+Model!BP794+Model!BP795+Model!BP796+Model!BP775+Model!BP804+Model!BP785+Model!BP751+Model!BP750 | BQ73: =Model!BQ740+Model!BQ741+Model!BQ742+Model!BQ743+Model!BQ746+Model!BQ752+Model!BQ753+Model!BQ754+Model!BQ755+Model!BQ757+Model!BQ763+Model!BQ764+Model!BQ766+Model!BQ767+Model!BQ768+Model!BQ769+Model!BQ770+Model!BQ771+Model!BQ772+Model!BQ773+Model!BQ774+Model!BQ776+Model!BQ777+Model!BQ779+Model!BQ793+Model!BQ797+Model!BQ798+Model!BQ799+Model!BQ800+Model!BQ805+Model!BQ809+Model!BQ810+Model!BQ748+Model!BQ760+Model!BQ761+Model!BQ765+Model!BQ780+Model!BQ806+Model!BQ749+Model!BQ758+Model!BQ747+Model!BQ759+Model!BQ794+Model!BQ795+Model!BQ796+Model!BQ775+Model!BQ804+Model!BQ785+Model!BQ751+Model!BQ750 | BR73: =Model!BR740+Model!BR741+Model!BR742+Model!BR743+Model!BR746+Model!BR752+Model!BR753+Model!BR754+Model!BR755+Model!BR757+Model!BR763+Model!BR764+Model!BR766+Model!BR767+Model!BR768+Model!BR769+Model!BR770+Model!BR771+Model!BR772+Model!BR773+Model!BR774+Model!BR776+Model!BR777+Model!BR779+Model!BR793+Model!BR797+Model!BR798+Model!BR799+Model!BR800+Model!BR805+Model!BR809+Model!BR810+Model!BR748+Model!BR760+Model!BR761+Model!BR765+Model!BR780+Model!BR806+Model!BR749+Model!BR758+Model!BR747+Model!BR759+Model!BR794+Model!BR795+Model!BR796+Model!BR775+Model!BR804+Model!BR785+Model!BR751+Model!BR750 | ... CB73: =Model!CB740+Model!CB741+Model!CB742+Model!CB743+Model!CB746+Model!CB752+Model!CB753+Model!CB754+Model!CB755+Model!CB757+Model!CB763+Model!CB764+Model!CB766+Model!CB767+Model!CB768+Model!CB769+Model!CB770+Model!CB771+Model!CB772+Model!CB773+Model!CB774+Model!CB776+Model!CB777+Model!CB779+Model!CB793+Model!CB797+Model!CB798+Model!CB799+Model!CB800+Model!CB805+Model!CB809+Model!CB810+Model!CB748+Model!CB760+Model!CB761+Model!CB765+Model!CB780+Model!CB806+Model!CB749+Model!CB758+Model!CB747+Model!CB759+Model!CB794+Model!CB795+Model!CB796+Model!CB775+Model!CB804+Model!CB785+Model!CB751+Model!CB750
A74: Change in Cash Position | C74: =SUM(C68:C73) | D74: =SUM(D68:D73) | E74: =SUM(E68:E73) | F74: =SUM(F68:F73) | G74: =SUM(G68:G73) | H74: =SUM(H68:H73) | I74: =SUM(I68:I73) | J74: =SUM(J68:J73) | ... CB74: =SUM(CB68:CB73)
A76: Operating Cash Flow Per Share | C76: =INDEX(SP_CFA_CFO,0,COLUMN())/INDEX(SP_GF_ShareCount,0,COLUMN()) | D76: =INDEX(SP_CFA_CFO,0,COLUMN())/INDEX(SP_GF_ShareCount,0,COLUMN()) | E76: =INDEX(SP_CFA_CFO,0,COLUMN())/INDEX(SP_GF_ShareCount,0,COLUMN()) | F76: =INDEX(SP_CFA_CFO,0,COLUMN())/INDEX(SP_GF_ShareCount,0,COLUMN()) | G76: =INDEX(SP_CFA_CFO,0,COLUMN())/INDEX(SP_GF_ShareCount,0,COLUMN()) | H76: =INDEX(SP_CFA_CFO,0,COLUMN())/INDEX(SP_GF_ShareCount,0,COLUMN()) | I76: =INDEX(SP_CFA_CFO,0,COLUMN())/INDEX(SP_GF_ShareCount,0,COLUMN()) | J76: =INDEX(SP_CFA_CFO,0,COLUMN())/INDEX(SP_GF_ShareCount,0,COLUMN()) | ... CB76: =INDEX(SP_CFA_CFO,0,COLUMN())/INDEX(SP_GF_ShareCount,0,COLUMN())
A77: Core Free Cash Flow Per Share, Pre Div | C77: =INDEX(SP_CFA_FCF_PreDiv,0,COLUMN())/INDEX(SP_GF_ShareCount,0,COLUMN()) | D77: =INDEX(SP_CFA_FCF_PreDiv,0,COLUMN())/INDEX(SP_GF_ShareCount,0,COLUMN()) | E77: =INDEX(SP_CFA_FCF_PreDiv,0,COLUMN())/INDEX(SP_GF_ShareCount,0,COLUMN()) | F77: =INDEX(SP_CFA_FCF_PreDiv,0,COLUMN())/INDEX(SP_GF_ShareCount,0,COLUMN()) | G77: =INDEX(SP_CFA_FCF_PreDiv,0,COLUMN())/INDEX(SP_GF_ShareCount,0,COLUMN()) | H77: =INDEX(SP_CFA_FCF_PreDiv,0,COLUMN())/INDEX(SP_GF_ShareCount,0,COLUMN()) | I77: =INDEX(SP_CFA_FCF_PreDiv,0,COLUMN())/INDEX(SP_GF_ShareCount,0,COLUMN()) | J77: =INDEX(SP_CFA_FCF_PreDiv,0,COLUMN())/INDEX(SP_GF_ShareCount,0,COLUMN()) | ... CB77: =INDEX(SP_CFA_FCF_PreDiv,0,COLUMN())/INDEX(SP_GF_ShareCount,0,COLUMN())
A78: =INDEX(MO_CFSum_DPS,0,COLUMN()) | C78: =INDEX(MO_CFSum_DPS,0,COLUMN()) | D78: =INDEX(MO_CFSum_DPS,0,COLUMN()) | E78: =INDEX(MO_CFSum_DPS,0,COLUMN()) | F78: =INDEX(MO_CFSum_DPS,0,COLUMN()) | G78: =INDEX(MO_CFSum_DPS,0,COLUMN()) | H78: =INDEX(MO_CFSum_DPS,0,COLUMN()) | I78: =INDEX(MO_CFSum_DPS,0,COLUMN()) | J78: =INDEX(MO_CFSum_DPS,0,COLUMN()) | ... CB78: =INDEX(MO_CFSum_DPS,0,COLUMN())
A79: Dividend Payout Ratio vs Core FCF, Pre Div | C79: =C78/C77 | D79: =D78/D77 | E79: =E78/E77 | F79: =F78/F77 | G79: =G78/G77 | H79: =H78/H77 | I79: =I78/I77 | J79: =J78/J77 | ... CB79: =CB78/CB77
A80: Dividend Payout Ratio vs Earnings Per Share | C80: =C78/C47 | D80: =D78/D47 | E80: =E78/E47 | F80: =F78/F47 | G80: =G78/G47 | H80: =H78/H47 | I80: =I78/I47 | J80: =J78/J47 | ... CB80: =CB78/CB47
A82: Balance Sheet Ratios
A83: Net Debt / EBITDA | C83: =INDEX(MO_BSS_Debt_Net,0,COLUMN())/INDEX(SP_BSR_EBITDA_LTM,0,COLUMN()) | D83: =INDEX(MO_BSS_Debt_Net,0,COLUMN())/INDEX(SP_BSR_EBITDA_LTM,0,COLUMN()) | E83: =INDEX(MO_BSS_Debt_Net,0,COLUMN())/INDEX(SP_BSR_EBITDA_LTM,0,COLUMN()) | F83: =INDEX(MO_BSS_Debt_Net,0,COLUMN())/INDEX(SP_BSR_EBITDA_LTM,0,COLUMN()) | G83: =INDEX(MO_BSS_Debt_Net,0,COLUMN())/INDEX(SP_BSR_EBITDA_LTM,0,COLUMN()) | K83: =INDEX(MO_BSS_Debt_Net,0,COLUMN())/INDEX(SP_BSR_EBITDA_LTM,0,COLUMN()) | L83: =INDEX(MO_BSS_Debt_Net,0,COLUMN())/INDEX(SP_BSR_EBITDA_LTM,0,COLUMN()) | M83: =INDEX(MO_BSS_Debt_Net,0,COLUMN())/INDEX(SP_BSR_EBITDA_LTM,0,COLUMN()) | N83: =INDEX(MO_BSS_Debt_Net,0,COLUMN())/INDEX(SP_BSR_EBITDA_LTM,0,COLUMN()) | O83: =INDEX(MO_BSS_Debt_Net,0,COLUMN())/INDEX(SP_BSR_EBITDA_LTM,0,COLUMN()) | P83: =INDEX(MO_BSS_Debt_Net,0,COLUMN())/INDEX(SP_BSR_EBITDA_LTM,0,COLUMN()) | Q83: =INDEX(MO_BSS_Debt_Net,0,COLUMN())/INDEX(SP_BSR_EBITDA_LTM,0,COLUMN()) | R83: =INDEX(MO_BSS_Debt_Net,0,COLUMN())/INDEX(SP_BSR_EBITDA_LTM,0,COLUMN()) | ... CB83: =INDEX(MO_BSS_Debt_Net,0,COLUMN())/INDEX(SP_BSR_EBITDA_LTM,0,COLUMN())
A84: Net Debt / Cash Flow | C84: =INDEX(MO_BSS_Debt_Net,0,COLUMN())/INDEX(SP_BSR_CashFlow_LTM,0,COLUMN()) | D84: =INDEX(MO_BSS_Debt_Net,0,COLUMN())/INDEX(SP_BSR_CashFlow_LTM,0,COLUMN()) | E84: =INDEX(MO_BSS_Debt_Net,0,COLUMN())/INDEX(SP_BSR_CashFlow_LTM,0,COLUMN()) | F84: =INDEX(MO_BSS_Debt_Net,0,COLUMN())/INDEX(SP_BSR_CashFlow_LTM,0,COLUMN()) | G84: =INDEX(MO_BSS_Debt_Net,0,COLUMN())/INDEX(SP_BSR_CashFlow_LTM,0,COLUMN()) | K84: =INDEX(MO_BSS_Debt_Net,0,COLUMN())/INDEX(SP_BSR_CashFlow_LTM,0,COLUMN()) | L84: =INDEX(MO_BSS_Debt_Net,0,COLUMN())/INDEX(SP_BSR_CashFlow_LTM,0,COLUMN()) | M84: =INDEX(MO_BSS_Debt_Net,0,COLUMN())/INDEX(SP_BSR_CashFlow_LTM,0,COLUMN()) | N84: =INDEX(MO_BSS_Debt_Net,0,COLUMN())/INDEX(SP_BSR_CashFlow_LTM,0,COLUMN()) | O84: =INDEX(MO_BSS_Debt_Net,0,COLUMN())/INDEX(SP_BSR_CashFlow_LTM,0,COLUMN()) | P84: =INDEX(MO_BSS_Debt_Net,0,COLUMN())/INDEX(SP_BSR_CashFlow_LTM,0,COLUMN()) | Q84: =INDEX(MO_BSS_Debt_Net,0,COLUMN())/INDEX(SP_BSR_CashFlow_LTM,0,COLUMN()) | R84: =INDEX(MO_BSS_Debt_Net,0,COLUMN())/INDEX(SP_BSR_CashFlow_LTM,0,COLUMN()) | ... CB84: =INDEX(MO_BSS_Debt_Net,0,COLUMN())/INDEX(SP_BSR_CashFlow_LTM,0,COLUMN())
A85: Net Debt / Capital | C85: =INDEX(MO_BSS_Debt_Net,0,COLUMN())/SUM(INDEX(MO_BS_SE,0,COLUMN()),INDEX(MO_BSS_Debt,0,COLUMN()),IFERROR(INDEX(MO_BSS_OL,0,COLUMN()),0)) | D85: =INDEX(MO_BSS_Debt_Net,0,COLUMN())/SUM(INDEX(MO_BS_SE,0,COLUMN()),INDEX(MO_BSS_Debt,0,COLUMN()),IFERROR(INDEX(MO_BSS_OL,0,COLUMN()),0)) | E85: =INDEX(MO_BSS_Debt_Net,0,COLUMN())/SUM(INDEX(MO_BS_SE,0,COLUMN()),INDEX(MO_BSS_Debt,0,COLUMN()),IFERROR(INDEX(MO_BSS_OL,0,COLUMN()),0)) | F85: =INDEX(MO_BSS_Debt_Net,0,COLUMN())/SUM(INDEX(MO_BS_SE,0,COLUMN()),INDEX(MO_BSS_Debt,0,COLUMN()),IFERROR(INDEX(MO_BSS_OL,0,COLUMN()),0)) | G85: =INDEX(MO_BSS_Debt_Net,0,COLUMN())/SUM(INDEX(MO_BS_SE,0,COLUMN()),INDEX(MO_BSS_Debt,0,COLUMN()),IFERROR(INDEX(MO_BSS_OL,0,COLUMN()),0)) | K85: =INDEX(MO_BSS_Debt_Net,0,COLUMN())/SUM(INDEX(MO_BS_SE,0,COLUMN()),INDEX(MO_BSS_Debt,0,COLUMN()),IFERROR(INDEX(MO_BSS_OL,0,COLUMN()),0)) | L85: =INDEX(MO_BSS_Debt_Net,0,COLUMN())/SUM(INDEX(MO_BS_SE,0,COLUMN()),INDEX(MO_BSS_Debt,0,COLUMN()),IFERROR(INDEX(MO_BSS_OL,0,COLUMN()),0)) | M85: =INDEX(MO_BSS_Debt_Net,0,COLUMN())/SUM(INDEX(MO_BS_SE,0,COLUMN()),INDEX(MO_BSS_Debt,0,COLUMN()),IFERROR(INDEX(MO_BSS_OL,0,COLUMN()),0)) | N85: =INDEX(MO_BSS_Debt_Net,0,COLUMN())/SUM(INDEX(MO_BS_SE,0,COLUMN()),INDEX(MO_BSS_Debt,0,COLUMN()),IFERROR(INDEX(MO_BSS_OL,0,COLUMN()),0)) | O85: =INDEX(MO_BSS_Debt_Net,0,COLUMN())/SUM(INDEX(MO_BS_SE,0,COLUMN()),INDEX(MO_BSS_Debt,0,COLUMN()),IFERROR(INDEX(MO_BSS_OL,0,COLUMN()),0)) | P85: =INDEX(MO_BSS_Debt_Net,0,COLUMN())/SUM(INDEX(MO_BS_SE,0,COLUMN()),INDEX(MO_BSS_Debt,0,COLUMN()),IFERROR(INDEX(MO_BSS_OL,0,COLUMN()),0)) | Q85: =INDEX(MO_BSS_Debt_Net,0,COLUMN())/SUM(INDEX(MO_BS_SE,0,COLUMN()),INDEX(MO_BSS_Debt,0,COLUMN()),IFERROR(INDEX(MO_BSS_OL,0,COLUMN()),0)) | R85: =INDEX(MO_BSS_Debt_Net,0,COLUMN())/SUM(INDEX(MO_BS_SE,0,COLUMN()),INDEX(MO_BSS_Debt,0,COLUMN()),IFERROR(INDEX(MO_BSS_OL,0,COLUMN()),0)) | ... CB85: =INDEX(MO_BSS_Debt_Net,0,COLUMN())/SUM(INDEX(MO_BS_SE,0,COLUMN()),INDEX(MO_BSS_Debt,0,COLUMN()),IFERROR(INDEX(MO_BSS_OL,0,COLUMN()),0))
A86: LTM EBITDA | C86: =C44 | D86: =D44 | E86: =E44 | F86: =F44 | G86: =G44 | K86: =SUM(K44,J44,I44,H44) | L86: =L44 | M86: =SUM(M44,K44,J44,I44) | N86: =SUM(N44,M44,K44,J44) | O86: =SUM(O44,N44,M44,K44) | P86: =SUM(P44,O44,N44,M44) | Q86: =Q44 | R86: =SUM(R44,P44,O44,N44) | S86: =SUM(S44,R44,P44,O44) | T86: =SUM(T44,S44,R44,P44) | U86: =SUM(U44,T44,S44,R44) | V86: =V44 | W86: =SUM(W44,U44,T44,S44) | X86: =SUM(X44,W44,U44,T44) | Y86: =SUM(Y44,X44,W44,U44) | Z86: =SUM(Z44,Y44,X44,W44) | AA86: =AA44 | AB86: =SUM(AB44,Z44,Y44,X44) | AC86: =SUM(AC44,AB44,Z44,Y44) | AD86: =SUM(AD44,AC44,AB44,Z44) | AE86: =SUM(AE44,AD44,AC44,AB44) | AF86: =AF44 | AG86: =SUM(AG44,AE44,AD44,AC44) | AH86: =SUM(AH44,AG44,AE44,AD44) | AI86: =SUM(AI44,AH44,AG44,AE44) | AJ86: =SUM(AJ44,AI44,AH44,AG44) | AK86: =AK44 | AL86: =SUM(AL44,AJ44,AI44,AH44) | AM86: =SUM(AM44,AL44,AJ44,AI44) | AN86: =SUM(AN44,AM44,AL44,AJ44) | AO86: =SUM(AO44,AN44,AM44,AL44) | AP86: =AP44 | AQ86: =SUM(AQ44,AO44,AN44,AM44) | AR86: =SUM(AR44,AQ44,AO44,AN44) | AS86: =SUM(AS44,AR44,AQ44,AO44) | AT86: =SUM(AT44,AS44,AR44,AQ44) | AU86: =AU44 | AV86: =SUM(AV44,AT44,AS44,AR44) | AW86: =SUM(AW44,AV44,AT44,AS44) | AX86: =SUM(AX44,AW44,AV44,AT44) | AY86: =SUM(AY44,AX44,AW44,AV44) | AZ86: =AZ44 | BA86: =SUM(BA44,AY44,AX44,AW44) | BB86: =SUM(BB44,BA44,AY44,AX44) | BC86: =SUM(BC44,BB44,BA44,AY44) | BD86: =SUM(BD44,BC44,BB44,BA44) | BE86: =BE44 | BF86: =SUM(BF44,BD44,BC44,BB44) | BG86: =SUM(BG44,BF44,BD44,BC44) | BH86: =SUM(BH44,BG44,BF44,BD44) | BI86: =SUM(BI44,BH44,BG44,BF44) | BJ86: =BJ44 | BK86: =SUM(BK44,BI44,BH44,BG44) | BL86: =SUM(BL44,BK44,BI44,BH44) | BM86: =SUM(BM44,BL44,BK44,BI44) | BN86: =SUM(BN44,BM44,BL44,BK44) | BO86: =BO44 | BP86: =SUM(BP44,BN44,BM44,BL44) | BQ86: =SUM(BQ44,BP44,BN44,BM44) | BR86: =SUM(BR44,BQ44,BP44,BN44) | BS86: =SUM(BS44,BR44,BQ44,BP44) | BT86: =BT44 | BU86: =SUM(BU44,BS44,BR44,BQ44) | BV86: =SUM(BV44,BU44,BS44,BR44) | BW86: =SUM(BW44,BV44,BU44,BS44) | BX86: =SUM(BX44,BW44,BV44,BU44) | BY86: =BY44 | BZ86: =BZ44 | CA86: =CA44 | CB86: =CB44
A87: LTM Cash Flow | C87: =C64 | D87: =D64 | E87: =E64 | F87: =F64 | G87: =G64 | K87: =SUM(K64,J64,I64,H64) | L87: =L64 | M87: =SUM(M64,K64,J64,I64) | N87: =SUM(N64,M64,K64,J64) | O87: =SUM(O64,N64,M64,K64) | P87: =SUM(P64,O64,N64,M64) | Q87: =Q64 | R87: =SUM(R64,P64,O64,N64) | S87: =SUM(S64,R64,P64,O64) | T87: =SUM(T64,S64,R64,P64) | U87: =SUM(U64,T64,S64,R64) | V87: =V64 | W87: =SUM(W64,U64,T64,S64) | X87: =SUM(X64,W64,U64,T64) | Y87: =SUM(Y64,X64,W64,U64) | Z87: =SUM(Z64,Y64,X64,W64) | AA87: =AA64 | AB87: =SUM(AB64,Z64,Y64,X64) | AC87: =SUM(AC64,AB64,Z64,Y64) | AD87: =SUM(AD64,AC64,AB64,Z64) | AE87: =SUM(AE64,AD64,AC64,AB64) | AF87: =AF64 | AG87: =SUM(AG64,AE64,AD64,AC64) | AH87: =SUM(AH64,AG64,AE64,AD64) | AI87: =SUM(AI64,AH64,AG64,AE64) | AJ87: =SUM(AJ64,AI64,AH64,AG64) | AK87: =AK64 | AL87: =SUM(AL64,AJ64,AI64,AH64) | AM87: =SUM(AM64,AL64,AJ64,AI64) | AN87: =SUM(AN64,AM64,AL64,AJ64) | AO87: =SUM(AO64,AN64,AM64,AL64) | AP87: =AP64 | AQ87: =SUM(AQ64,AO64,AN64,AM64) | AR87: =SUM(AR64,AQ64,AO64,AN64) | AS87: =SUM(AS64,AR64,AQ64,AO64) | AT87: =SUM(AT64,AS64,AR64,AQ64) | AU87: =AU64 | AV87: =SUM(AV64,AT64,AS64,AR64) | AW87: =SUM(AW64,AV64,AT64,AS64) | AX87: =SUM(AX64,AW64,AV64,AT64) | AY87: =SUM(AY64,AX64,AW64,AV64) | AZ87: =AZ64 | BA87: =SUM(BA64,AY64,AX64,AW64) | BB87: =SUM(BB64,BA64,AY64,AX64) | BC87: =SUM(BC64,BB64,BA64,AY64) | BD87: =SUM(BD64,BC64,BB64,BA64) | BE87: =BE64 | BF87: =SUM(BF64,BD64,BC64,BB64) | BG87: =SUM(BG64,BF64,BD64,BC64) | BH87: =SUM(BH64,BG64,BF64,BD64) | BI87: =SUM(BI64,BH64,BG64,BF64) | BJ87: =BJ64 | BK87: =SUM(BK64,BI64,BH64,BG64) | BL87: =SUM(BL64,BK64,BI64,BH64) | BM87: =SUM(BM64,BL64,BK64,BI64) | BN87: =SUM(BN64,BM64,BL64,BK64) | BO87: =BO64 | BP87: =SUM(BP64,BN64,BM64,BL64) | BQ87: =SUM(BQ64,BP64,BN64,BM64) | BR87: =SUM(BR64,BQ64,BP64,BN64) | BS87: =SUM(BS64,BR64,BQ64,BP64) | BT87: =BT64 | BU87: =SUM(BU64,BS64,BR64,BQ64) | BV87: =SUM(BV64,BU64,BS64,BR64) | BW87: =SUM(BW64,BV64,BU64,BS64) | BX87: =SUM(BX64,BW64,BV64,BU64) | BY87: =BY64 | BZ87: =BZ64 | CA87: =CA64 | CB87: =CB64
A89: Profitability Ratios
A90: Net Income | C90: =INDEX(SP_NGF_NI,0,COLUMN()) | D90: =INDEX(SP_NGF_NI,0,COLUMN()) | E90: =INDEX(SP_NGF_NI,0,COLUMN()) | F90: =INDEX(SP_NGF_NI,0,COLUMN()) | G90: =INDEX(SP_NGF_NI,0,COLUMN()) | H90: =INDEX(SP_NGF_NI,0,COLUMN()) | I90: =INDEX(SP_NGF_NI,0,COLUMN()) | J90: =INDEX(SP_NGF_NI,0,COLUMN()) | ... CB90: =INDEX(SP_NGF_NI,0,COLUMN())
A91: LTM Net Income | C91: =C90 | D91: =D90 | E91: =E90 | F91: =F90 | G91: =G90 | K91: =SUM(K90,J90,I90,H90) | L91: =L90 | M91: =SUM(M90,K90,J90,I90) | N91: =SUM(N90,M90,K90,J90) | O91: =SUM(O90,N90,M90,K90) | P91: =SUM(P90,O90,N90,M90) | Q91: =Q90 | R91: =SUM(R90,P90,O90,N90) | S91: =SUM(S90,R90,P90,O90) | T91: =SUM(T90,S90,R90,P90) | U91: =SUM(U90,T90,S90,R90) | V91: =V90 | W91: =SUM(W90,U90,T90,S90) | X91: =SUM(X90,W90,U90,T90) | Y91: =SUM(Y90,X90,W90,U90) | Z91: =SUM(Z90,Y90,X90,W90) | AA91: =AA90 | AB91: =SUM(AB90,Z90,Y90,X90) | AC91: =SUM(AC90,AB90,Z90,Y90) | AD91: =SUM(AD90,AC90,AB90,Z90) | AE91: =SUM(AE90,AD90,AC90,AB90) | AF91: =AF90 | AG91: =SUM(AG90,AE90,AD90,AC90) | AH91: =SUM(AH90,AG90,AE90,AD90) | AI91: =SUM(AI90,AH90,AG90,AE90) | AJ91: =SUM(AJ90,AI90,AH90,AG90) | AK91: =AK90 | AL91: =SUM(AL90,AJ90,AI90,AH90) | AM91: =SUM(AM90,AL90,AJ90,AI90) | AN91: =SUM(AN90,AM90,AL90,AJ90) | AO91: =SUM(AO90,AN90,AM90,AL90) | AP91: =AP90 | AQ91: =SUM(AQ90,AO90,AN90,AM90) | AR91: =SUM(AR90,AQ90,AO90,AN90) | AS91: =SUM(AS90,AR90,AQ90,AO90) | AT91: =SUM(AT90,AS90,AR90,AQ90) | AU91: =AU90 | AV91: =SUM(AV90,AT90,AS90,AR90) | AW91: =SUM(AW90,AV90,AT90,AS90) | AX91: =SUM(AX90,AW90,AV90,AT90) | AY91: =SUM(AY90,AX90,AW90,AV90) | AZ91: =AZ90 | BA91: =SUM(BA90,AY90,AX90,AW90) | BB91: =SUM(BB90,BA90,AY90,AX90) | BC91: =SUM(BC90,BB90,BA90,AY90) | BD91: =SUM(BD90,BC90,BB90,BA90) | BE91: =BE90 | BF91: =SUM(BF90,BD90,BC90,BB90) | BG91: =SUM(BG90,BF90,BD90,BC90) | BH91: =SUM(BH90,BG90,BF90,BD90) | BI91: =SUM(BI90,BH90,BG90,BF90) | BJ91: =BJ90 | BK91: =SUM(BK90,BI90,BH90,BG90) | BL91: =SUM(BL90,BK90,BI90,BH90) | BM91: =SUM(BM90,BL90,BK90,BI90) | BN91: =SUM(BN90,BM90,BL90,BK90) | BO91: =BO90 | BP91: =SUM(BP90,BN90,BM90,BL90) | BQ91: =SUM(BQ90,BP90,BN90,BM90) | BR91: =SUM(BR90,BQ90,BP90,BN90) | BS91: =SUM(BS90,BR90,BQ90,BP90) | BT91: =BT90 | BU91: =SUM(BU90,BS90,BR90,BQ90) | BV91: =SUM(BV90,BU90,BS90,BR90) | BW91: =SUM(BW90,BV90,BU90,BS90) | BX91: =SUM(BX90,BW90,BV90,BU90) | BY91: =BY90 | BZ91: =BZ90 | CA91: =CA90 | CB91: =CB90
A92: Shareholder's Equity | C92: =INDEX(MO_BS_SE,0,COLUMN()) | D92: =INDEX(MO_BS_SE,0,COLUMN()) | E92: =INDEX(MO_BS_SE,0,COLUMN()) | F92: =INDEX(MO_BS_SE,0,COLUMN()) | G92: =INDEX(MO_BS_SE,0,COLUMN()) | H92: =INDEX(MO_BS_SE,0,COLUMN()) | I92: =INDEX(MO_BS_SE,0,COLUMN()) | J92: =INDEX(MO_BS_SE,0,COLUMN()) | ... CB92: =INDEX(MO_BS_SE,0,COLUMN())
A93: Average Shareholder's Equity | C93: =C92 | D93: =AVERAGE(D92,C92) | E93: =AVERAGE(E92,D92) | F93: =AVERAGE(F92,E92) | G93: =AVERAGE(G92,F92) | K93: =AVERAGE(K92,J92,I92,H92) | L93: =AVERAGE(L92,G92) | M93: =AVERAGE(M92,K92,J92,I92) | N93: =AVERAGE(N92,M92,K92,J92) | O93: =AVERAGE(O92,N92,M92,K92) | P93: =AVERAGE(P92,O92,N92,M92) | Q93: =AVERAGE(Q92,L92) | R93: =AVERAGE(R92,P92,O92,N92) | S93: =AVERAGE(S92,R92,P92,O92) | T93: =AVERAGE(T92,S92,R92,P92) | U93: =AVERAGE(U92,T92,S92,R92) | V93: =AVERAGE(V92,Q92) | W93: =AVERAGE(W92,U92,T92,S92) | X93: =AVERAGE(X92,W92,U92,T92) | Y93: =AVERAGE(Y92,X92,W92,U92) | Z93: =AVERAGE(Z92,Y92,X92,W92) | AA93: =AVERAGE(AA92,V92) | AB93: =AVERAGE(AB92,Z92,Y92,X92) | AC93: =AVERAGE(AC92,AB92,Z92,Y92) | AD93: =AVERAGE(AD92,AC92,AB92,Z92) | AE93: =AVERAGE(AE92,AD92,AC92,AB92) | AF93: =AVERAGE(AF92,AA92) | AG93: =AVERAGE(AG92,AE92,AD92,AC92) | AH93: =AVERAGE(AH92,AG92,AE92,AD92) | AI93: =AVERAGE(AI92,AH92,AG92,AE92) | AJ93: =AVERAGE(AJ92,AI92,AH92,AG92) | AK93: =AVERAGE(AK92,AF92) | AL93: =AVERAGE(AL92,AJ92,AI92,AH92) | AM93: =AVERAGE(AM92,AL92,AJ92,AI92) | AN93: =AVERAGE(AN92,AM92,AL92,AJ92) | AO93: =AVERAGE(AO92,AN92,AM92,AL92) | AP93: =AVERAGE(AP92,AK92) | AQ93: =AVERAGE(AQ92,AO92,AN92,AM92) | AR93: =AVERAGE(AR92,AQ92,AO92,AN92) | AS93: =AVERAGE(AS92,AR92,AQ92,AO92) | AT93: =AVERAGE(AT92,AS92,AR92,AQ92) | AU93: =AVERAGE(AU92,AP92) | AV93: =AVERAGE(AV92,AT92,AS92,AR92) | AW93: =AVERAGE(AW92,AV92,AT92,AS92) | AX93: =AVERAGE(AX92,AW92,AV92,AT92) | AY93: =AVERAGE(AY92,AX92,AW92,AV92) | AZ93: =AVERAGE(AZ92,AU92) | BA93: =AVERAGE(BA92,AY92,AX92,AW92) | BB93: =AVERAGE(BB92,BA92,AY92,AX92) | BC93: =AVERAGE(BC92,BB92,BA92,AY92) | BD93: =AVERAGE(BD92,BC92,BB92,BA92) | BE93: =AVERAGE(BE92,AZ92) | BF93: =AVERAGE(BF92,BD92,BC92,BB92) | BG93: =AVERAGE(BG92,BF92,BD92,BC92) | BH93: =AVERAGE(BH92,BG92,BF92,BD92) | BI93: =AVERAGE(BI92,BH92,BG92,BF92) | BJ93: =AVERAGE(BJ92,BE92) | BK93: =AVERAGE(BK92,BI92,BH92,BG92) | BL93: =AVERAGE(BL92,BK92,BI92,BH92) | BM93: =AVERAGE(BM92,BL92,BK92,BI92) | BN93: =AVERAGE(BN92,BM92,BL92,BK92) | BO93: =AVERAGE(BO92,BJ92) | BP93: =AVERAGE(BP92,BN92,BM92,BL92) | BQ93: =AVERAGE(BQ92,BP92,BN92,BM92) | BR93: =AVERAGE(BR92,BQ92,BP92,BN92) | BS93: =AVERAGE(BS92,BR92,BQ92,BP92) | BT93: =AVERAGE(BT92,BO92) | BU93: =AVERAGE(BU92,BS92,BR92,BQ92) | BV93: =AVERAGE(BV92,BU92,BS92,BR92) | BW93: =AVERAGE(BW92,BV92,BU92,BS92) | BX93: =AVERAGE(BX92,BW92,BV92,BU92) | BY93: =AVERAGE(BY92,BT92) | BZ93: =AVERAGE(BZ92,BY92) | CA93: =AVERAGE(CA92,BZ92) | CB93: =AVERAGE(CB92,CA92)
A94: ROE | C94: =IF(C93<0,"NMF",IF(ABS(C91/C93)>1,"NMF",C91/C93)) | D94: =IF(D93<0,"NMF",IF(ABS(D91/D93)>1,"NMF",D91/D93)) | E94: =IF(E93<0,"NMF",IF(ABS(E91/E93)>1,"NMF",E91/E93)) | F94: =IF(F93<0,"NMF",IF(ABS(F91/F93)>1,"NMF",F91/F93)) | G94: =IF(G93<0,"NMF",IF(ABS(G91/G93)>1,"NMF",G91/G93)) | L94: =IF(L93<0,"NMF",IF(ABS(L91/L93)>1,"NMF",L91/L93)) | M94: =IF(M93<0,"NMF",IF(ABS(M91/M93)>1,"NMF",M91/M93)) | N94: =IF(N93<0,"NMF",IF(ABS(N91/N93)>1,"NMF",N91/N93)) | O94: =IF(O93<0,"NMF",IF(ABS(O91/O93)>1,"NMF",O91/O93)) | P94: =IF(P93<0,"NMF",IF(ABS(P91/P93)>1,"NMF",P91/P93)) | Q94: =IF(Q93<0,"NMF",IF(ABS(Q91/Q93)>1,"NMF",Q91/Q93)) | R94: =IF(R93<0,"NMF",IF(ABS(R91/R93)>1,"NMF",R91/R93)) | S94: =IF(S93<0,"NMF",IF(ABS(S91/S93)>1,"NMF",S91/S93)) | ... CB94: =IF(CB93<0,"NMF",IF(ABS(CB91/CB93)>1,"NMF",CB91/CB93))
A95: NOPAT | C95: =INDEX(SP_GF_NI,0,COLUMN())+INDEX(SP_GF_IE,0,COLUMN())*(1-INDEX(SP_GF_Tax,0,COLUMN())/INDEX(SP_GF_EBT,0,COLUMN()))+INDEX(SP_GF_NCI,0,COLUMN()) | D95: =INDEX(SP_GF_NI,0,COLUMN())+INDEX(SP_GF_IE,0,COLUMN())*(1-INDEX(SP_GF_Tax,0,COLUMN())/INDEX(SP_GF_EBT,0,COLUMN()))+INDEX(SP_GF_NCI,0,COLUMN()) | E95: =INDEX(SP_GF_NI,0,COLUMN())+INDEX(SP_GF_IE,0,COLUMN())*(1-INDEX(SP_GF_Tax,0,COLUMN())/INDEX(SP_GF_EBT,0,COLUMN()))+INDEX(SP_GF_NCI,0,COLUMN()) | F95: =INDEX(SP_GF_NI,0,COLUMN())+INDEX(SP_GF_IE,0,COLUMN())*(1-INDEX(SP_GF_Tax,0,COLUMN())/INDEX(SP_GF_EBT,0,COLUMN()))+INDEX(SP_GF_NCI,0,COLUMN()) | G95: =INDEX(SP_GF_NI,0,COLUMN())+INDEX(SP_GF_IE,0,COLUMN())*(1-INDEX(SP_GF_Tax,0,COLUMN())/INDEX(SP_GF_EBT,0,COLUMN()))+INDEX(SP_GF_NCI,0,COLUMN()) | H95: =INDEX(SP_GF_NI,0,COLUMN())+INDEX(SP_GF_IE,0,COLUMN())*(1-INDEX(SP_GF_Tax,0,COLUMN())/INDEX(SP_GF_EBT,0,COLUMN()))+INDEX(SP_GF_NCI,0,COLUMN()) | I95: =INDEX(SP_GF_NI,0,COLUMN())+INDEX(SP_GF_IE,0,COLUMN())*(1-INDEX(SP_GF_Tax,0,COLUMN())/INDEX(SP_GF_EBT,0,COLUMN()))+INDEX(SP_GF_NCI,0,COLUMN()) | J95: =INDEX(SP_GF_NI,0,COLUMN())+INDEX(SP_GF_IE,0,COLUMN())*(1-INDEX(SP_GF_Tax,0,COLUMN())/INDEX(SP_GF_EBT,0,COLUMN()))+INDEX(SP_GF_NCI,0,COLUMN()) | ... CB95: =INDEX(SP_GF_NI,0,COLUMN())+INDEX(SP_GF_IE,0,COLUMN())*(1-INDEX(SP_GF_Tax,0,COLUMN())/INDEX(SP_GF_EBT,0,COLUMN()))+INDEX(SP_GF_NCI,0,COLUMN())
A96: LTM Net Operating Profit | C96: =C95 | D96: =D95 | E96: =E95 | F96: =F95 | G96: =G95 | K96: =SUM(K95,J95,I95,H95) | L96: =L95 | M96: =SUM(M95,K95,J95,I95) | N96: =SUM(N95,M95,K95,J95) | O96: =SUM(O95,N95,M95,K95) | P96: =SUM(P95,O95,N95,M95) | Q96: =Q95 | R96: =SUM(R95,P95,O95,N95) | S96: =SUM(S95,R95,P95,O95) | T96: =SUM(T95,S95,R95,P95) | U96: =SUM(U95,T95,S95,R95) | V96: =V95 | W96: =SUM(W95,U95,T95,S95) | X96: =SUM(X95,W95,U95,T95) | Y96: =SUM(Y95,X95,W95,U95) | Z96: =SUM(Z95,Y95,X95,W95) | AA96: =AA95 | AB96: =SUM(AB95,Z95,Y95,X95) | AC96: =SUM(AC95,AB95,Z95,Y95) | AD96: =SUM(AD95,AC95,AB95,Z95) | AE96: =SUM(AE95,AD95,AC95,AB95) | AF96: =AF95 | AG96: =SUM(AG95,AE95,AD95,AC95) | AH96: =SUM(AH95,AG95,AE95,AD95) | AI96: =SUM(AI95,AH95,AG95,AE95) | AJ96: =SUM(AJ95,AI95,AH95,AG95) | AK96: =AK95 | AL96: =SUM(AL95,AJ95,AI95,AH95) | AM96: =SUM(AM95,AL95,AJ95,AI95) | AN96: =SUM(AN95,AM95,AL95,AJ95) | AO96: =SUM(AO95,AN95,AM95,AL95) | AP96: =AP95 | AQ96: =SUM(AQ95,AO95,AN95,AM95) | AR96: =SUM(AR95,AQ95,AO95,AN95) | AS96: =SUM(AS95,AR95,AQ95,AO95) | AT96: =SUM(AT95,AS95,AR95,AQ95) | AU96: =AU95 | AV96: =SUM(AV95,AT95,AS95,AR95) | AW96: =SUM(AW95,AV95,AT95,AS95) | AX96: =SUM(AX95,AW95,AV95,AT95) | AY96: =SUM(AY95,AX95,AW95,AV95) | AZ96: =AZ95 | BA96: =SUM(BA95,AY95,AX95,AW95) | BB96: =SUM(BB95,BA95,AY95,AX95) | BC96: =SUM(BC95,BB95,BA95,AY95) | BD96: =SUM(BD95,BC95,BB95,BA95) | BE96: =BE95 | BF96: =SUM(BF95,BD95,BC95,BB95) | BG96: =SUM(BG95,BF95,BD95,BC95) | BH96: =SUM(BH95,BG95,BF95,BD95) | BI96: =SUM(BI95,BH95,BG95,BF95) | BJ96: =BJ95 | BK96: =SUM(BK95,BI95,BH95,BG95) | BL96: =SUM(BL95,BK95,BI95,BH95) | BM96: =SUM(BM95,BL95,BK95,BI95) | BN96: =SUM(BN95,BM95,BL95,BK95) | BO96: =BO95 | BP96: =SUM(BP95,BN95,BM95,BL95) | BQ96: =SUM(BQ95,BP95,BN95,BM95) | BR96: =SUM(BR95,BQ95,BP95,BN95) | BS96: =SUM(BS95,BR95,BQ95,BP95) | BT96: =BT95 | BU96: =SUM(BU95,BS95,BR95,BQ95) | BV96: =SUM(BV95,BU95,BS95,BR95) | BW96: =SUM(BW95,BV95,BU95,BS95) | BX96: =SUM(BX95,BW95,BV95,BU95) | BY96: =BY95 | BZ96: =BZ95 | CA96: =CA95 | CB96: =CB95
A97: Total Assets | C97: =INDEX(MO_BS_TA,0,COLUMN()) | D97: =INDEX(MO_BS_TA,0,COLUMN()) | E97: =INDEX(MO_BS_TA,0,COLUMN()) | F97: =INDEX(MO_BS_TA,0,COLUMN()) | G97: =INDEX(MO_BS_TA,0,COLUMN()) | H97: =INDEX(MO_BS_TA,0,COLUMN()) | I97: =INDEX(MO_BS_TA,0,COLUMN()) | J97: =INDEX(MO_BS_TA,0,COLUMN()) | ... CB97: =INDEX(MO_BS_TA,0,COLUMN())
A98: Average Total Assets | C98: =C97 | D98: =AVERAGE(D97,C97) | E98: =AVERAGE(E97,D97) | F98: =AVERAGE(F97,E97) | G98: =AVERAGE(G97,F97) | K98: =AVERAGE(K97,J97,I97,H97) | L98: =AVERAGE(L97,G97) | M98: =AVERAGE(M97,K97,J97,I97) | N98: =AVERAGE(N97,M97,K97,J97) | O98: =AVERAGE(O97,N97,M97,K97) | P98: =AVERAGE(P97,O97,N97,M97) | Q98: =AVERAGE(Q97,L97) | R98: =AVERAGE(R97,P97,O97,N97) | S98: =AVERAGE(S97,R97,P97,O97) | T98: =AVERAGE(T97,S97,R97,P97) | U98: =AVERAGE(U97,T97,S97,R97) | V98: =AVERAGE(V97,Q97) | W98: =AVERAGE(W97,U97,T97,S97) | X98: =AVERAGE(X97,W97,U97,T97) | Y98: =AVERAGE(Y97,X97,W97,U97) | Z98: =AVERAGE(Z97,Y97,X97,W97) | AA98: =AVERAGE(AA97,V97) | AB98: =AVERAGE(AB97,Z97,Y97,X97) | AC98: =AVERAGE(AC97,AB97,Z97,Y97) | AD98: =AVERAGE(AD97,AC97,AB97,Z97) | AE98: =AVERAGE(AE97,AD97,AC97,AB97) | AF98: =AVERAGE(AF97,AA97) | AG98: =AVERAGE(AG97,AE97,AD97,AC97) | AH98: =AVERAGE(AH97,AG97,AE97,AD97) | AI98: =AVERAGE(AI97,AH97,AG97,AE97) | AJ98: =AVERAGE(AJ97,AI97,AH97,AG97) | AK98: =AVERAGE(AK97,AF97) | AL98: =AVERAGE(AL97,AJ97,AI97,AH97) | AM98: =AVERAGE(AM97,AL97,AJ97,AI97) | AN98: =AVERAGE(AN97,AM97,AL97,AJ97) | AO98: =AVERAGE(AO97,AN97,AM97,AL97) | AP98: =AVERAGE(AP97,AK97) | AQ98: =AVERAGE(AQ97,AO97,AN97,AM97) | AR98: =AVERAGE(AR97,AQ97,AO97,AN97) | AS98: =AVERAGE(AS97,AR97,AQ97,AO97) | AT98: =AVERAGE(AT97,AS97,AR97,AQ97) | AU98: =AVERAGE(AU97,AP97) | AV98: =AVERAGE(AV97,AT97,AS97,AR97) | AW98: =AVERAGE(AW97,AV97,AT97,AS97) | AX98: =AVERAGE(AX97,AW97,AV97,AT97) | AY98: =AVERAGE(AY97,AX97,AW97,AV97) | AZ98: =AVERAGE(AZ97,AU97) | BA98: =AVERAGE(BA97,AY97,AX97,AW97) | BB98: =AVERAGE(BB97,BA97,AY97,AX97) | BC98: =AVERAGE(BC97,BB97,BA97,AY97) | BD98: =AVERAGE(BD97,BC97,BB97,BA97) | BE98: =AVERAGE(BE97,AZ97) | BF98: =AVERAGE(BF97,BD97,BC97,BB97) | BG98: =AVERAGE(BG97,BF97,BD97,BC97) | BH98: =AVERAGE(BH97,BG97,BF97,BD97) | BI98: =AVERAGE(BI97,BH97,BG97,BF97) | BJ98: =AVERAGE(BJ97,BE97) | BK98: =AVERAGE(BK97,BI97,BH97,BG97) | BL98: =AVERAGE(BL97,BK97,BI97,BH97) | BM98: =AVERAGE(BM97,BL97,BK97,BI97) | BN98: =AVERAGE(BN97,BM97,BL97,BK97) | BO98: =AVERAGE(BO97,BJ97) | BP98: =AVERAGE(BP97,BN97,BM97,BL97) | BQ98: =AVERAGE(BQ97,BP97,BN97,BM97) | BR98: =AVERAGE(BR97,BQ97,BP97,BN97) | BS98: =AVERAGE(BS97,BR97,BQ97,BP97) | BT98: =AVERAGE(BT97,BO97) | BU98: =AVERAGE(BU97,BS97,BR97,BQ97) | BV98: =AVERAGE(BV97,BU97,BS97,BR97) | BW98: =AVERAGE(BW97,BV97,BU97,BS97) | BX98: =AVERAGE(BX97,BW97,BV97,BU97) | BY98: =AVERAGE(BY97,BT97) | BZ98: =AVERAGE(BZ97,BY97) | CA98: =AVERAGE(CA97,BZ97) | CB98: =AVERAGE(CB97,CA97)
A99: After-tax ROA | C99: =IF(C98<0,"NMF",IF(ABS(C96/C98)>1,"NMF",C96/C98)) | D99: =IF(D98<0,"NMF",IF(ABS(D96/D98)>1,"NMF",D96/D98)) | E99: =IF(E98<0,"NMF",IF(ABS(E96/E98)>1,"NMF",E96/E98)) | F99: =IF(F98<0,"NMF",IF(ABS(F96/F98)>1,"NMF",F96/F98)) | G99: =IF(G98<0,"NMF",IF(ABS(G96/G98)>1,"NMF",G96/G98)) | L99: =IF(L98<0,"NMF",IF(ABS(L96/L98)>1,"NMF",L96/L98)) | M99: =IF(M98<0,"NMF",IF(ABS(M96/M98)>1,"NMF",M96/M98)) | N99: =IF(N98<0,"NMF",IF(ABS(N96/N98)>1,"NMF",N96/N98)) | O99: =IF(O98<0,"NMF",IF(ABS(O96/O98)>1,"NMF",O96/O98)) | P99: =IF(P98<0,"NMF",IF(ABS(P96/P98)>1,"NMF",P96/P98)) | Q99: =IF(Q98<0,"NMF",IF(ABS(Q96/Q98)>1,"NMF",Q96/Q98)) | R99: =IF(R98<0,"NMF",IF(ABS(R96/R98)>1,"NMF",R96/R98)) | S99: =IF(S98<0,"NMF",IF(ABS(S96/S98)>1,"NMF",S96/S98)) | ... CB99: =IF(CB98<0,"NMF",IF(ABS(CB96/CB98)>1,"NMF",CB96/CB98))
A100: Total Debt | C100: =INDEX(MO_BSS_Debt_Net,0,COLUMN())+INDEX(MO_BSS_Cash,0,COLUMN()) | D100: =INDEX(MO_BSS_Debt_Net,0,COLUMN())+INDEX(MO_BSS_Cash,0,COLUMN()) | E100: =INDEX(MO_BSS_Debt_Net,0,COLUMN())+INDEX(MO_BSS_Cash,0,COLUMN()) | F100: =INDEX(MO_BSS_Debt_Net,0,COLUMN())+INDEX(MO_BSS_Cash,0,COLUMN()) | G100: =INDEX(MO_BSS_Debt_Net,0,COLUMN())+INDEX(MO_BSS_Cash,0,COLUMN()) | H100: =INDEX(MO_BSS_Debt_Net,0,COLUMN())+INDEX(MO_BSS_Cash,0,COLUMN()) | I100: =INDEX(MO_BSS_Debt_Net,0,COLUMN())+INDEX(MO_BSS_Cash,0,COLUMN()) | J100: =INDEX(MO_BSS_Debt_Net,0,COLUMN())+INDEX(MO_BSS_Cash,0,COLUMN()) | ... CB100: =INDEX(MO_BSS_Debt_Net,0,COLUMN())+INDEX(MO_BSS_Cash,0,COLUMN())
A101: Average Book Value of Debt | C101: =C100 | D101: =AVERAGE(D100,C100) | E101: =AVERAGE(E100,D100) | F101: =AVERAGE(F100,E100) | G101: =AVERAGE(G100,F100) | K101: =AVERAGE(K100,J100,I100,H100) | L101: =AVERAGE(L100,G100) | M101: =AVERAGE(M100,K100,J100,I100) | N101: =AVERAGE(N100,M100,K100,J100) | O101: =AVERAGE(O100,N100,M100,K100) | P101: =AVERAGE(P100,O100,N100,M100) | Q101: =AVERAGE(Q100,L100) | R101: =AVERAGE(R100,P100,O100,N100) | S101: =AVERAGE(S100,R100,P100,O100) | T101: =AVERAGE(T100,S100,R100,P100) | U101: =AVERAGE(U100,T100,S100,R100) | V101: =AVERAGE(V100,Q100) | W101: =AVERAGE(W100,U100,T100,S100) | X101: =AVERAGE(X100,W100,U100,T100) | Y101: =AVERAGE(Y100,X100,W100,U100) | Z101: =AVERAGE(Z100,Y100,X100,W100) | AA101: =AVERAGE(AA100,V100) | AB101: =AVERAGE(AB100,Z100,Y100,X100) | AC101: =AVERAGE(AC100,AB100,Z100,Y100) | AD101: =AVERAGE(AD100,AC100,AB100,Z100) | AE101: =AVERAGE(AE100,AD100,AC100,AB100) | AF101: =AVERAGE(AF100,AA100) | AG101: =AVERAGE(AG100,AE100,AD100,AC100) | AH101: =AVERAGE(AH100,AG100,AE100,AD100) | AI101: =AVERAGE(AI100,AH100,AG100,AE100) | AJ101: =AVERAGE(AJ100,AI100,AH100,AG100) | AK101: =AVERAGE(AK100,AF100) | AL101: =AVERAGE(AL100,AJ100,AI100,AH100) | AM101: =AVERAGE(AM100,AL100,AJ100,AI100) | AN101: =AVERAGE(AN100,AM100,AL100,AJ100) | AO101: =AVERAGE(AO100,AN100,AM100,AL100) | AP101: =AVERAGE(AP100,AK100) | AQ101: =AVERAGE(AQ100,AO100,AN100,AM100) | AR101: =AVERAGE(AR100,AQ100,AO100,AN100) | AS101: =AVERAGE(AS100,AR100,AQ100,AO100) | AT101: =AVERAGE(AT100,AS100,AR100,AQ100) | AU101: =AVERAGE(AU100,AP100) | AV101: =AVERAGE(AV100,AT100,AS100,AR100) | AW101: =AVERAGE(AW100,AV100,AT100,AS100) | AX101: =AVERAGE(AX100,AW100,AV100,AT100) | AY101: =AVERAGE(AY100,AX100,AW100,AV100) | AZ101: =AVERAGE(AZ100,AU100) | BA101: =AVERAGE(BA100,AY100,AX100,AW100) | BB101: =AVERAGE(BB100,BA100,AY100,AX100) | BC101: =AVERAGE(BC100,BB100,BA100,AY100) | BD101: =AVERAGE(BD100,BC100,BB100,BA100) | BE101: =AVERAGE(BE100,AZ100) | BF101: =AVERAGE(BF100,BD100,BC100,BB100) | BG101: =AVERAGE(BG100,BF100,BD100,BC100) | BH101: =AVERAGE(BH100,BG100,BF100,BD100) | BI101: =AVERAGE(BI100,BH100,BG100,BF100) | BJ101: =AVERAGE(BJ100,BE100) | BK101: =AVERAGE(BK100,BI100,BH100,BG100) | BL101: =AVERAGE(BL100,BK100,BI100,BH100) | BM101: =AVERAGE(BM100,BL100,BK100,BI100) | BN101: =AVERAGE(BN100,BM100,BL100,BK100) | BO101: =AVERAGE(BO100,BJ100) | BP101: =AVERAGE(BP100,BN100,BM100,BL100) | BQ101: =AVERAGE(BQ100,BP100,BN100,BM100) | BR101: =AVERAGE(BR100,BQ100,BP100,BN100) | BS101: =AVERAGE(BS100,BR100,BQ100,BP100) | BT101: =AVERAGE(BT100,BO100) | BU101: =AVERAGE(BU100,BS100,BR100,BQ100) | BV101: =AVERAGE(BV100,BU100,BS100,BR100) | BW101: =AVERAGE(BW100,BV100,BU100,BS100) | BX101: =AVERAGE(BX100,BW100,BV100,BU100) | BY101: =AVERAGE(BY100,BT100) | BZ101: =AVERAGE(BZ100,BY100) | CA101: =AVERAGE(CA100,BZ100) | CB101: =AVERAGE(CB100,CA100)
A102: Average Invested Capital | C102: =SUM(INDEX(SP_BSR_Debt_Avg,0,COLUMN()),INDEX(SP_BSR_SE_Avg,0,COLUMN())) | D102: =SUM(INDEX(SP_BSR_Debt_Avg,0,COLUMN()),INDEX(SP_BSR_SE_Avg,0,COLUMN())) | E102: =SUM(INDEX(SP_BSR_Debt_Avg,0,COLUMN()),INDEX(SP_BSR_SE_Avg,0,COLUMN())) | F102: =SUM(INDEX(SP_BSR_Debt_Avg,0,COLUMN()),INDEX(SP_BSR_SE_Avg,0,COLUMN())) | G102: =SUM(INDEX(SP_BSR_Debt_Avg,0,COLUMN()),INDEX(SP_BSR_SE_Avg,0,COLUMN())) | H102: =SUM(INDEX(SP_BSR_Debt_Avg,0,COLUMN()),INDEX(SP_BSR_SE_Avg,0,COLUMN())) | I102: =SUM(INDEX(SP_BSR_Debt_Avg,0,COLUMN()),INDEX(SP_BSR_SE_Avg,0,COLUMN())) | J102: =SUM(INDEX(SP_BSR_Debt_Avg,0,COLUMN()),INDEX(SP_BSR_SE_Avg,0,COLUMN())) | ... CB102: =SUM(INDEX(SP_BSR_Debt_Avg,0,COLUMN()),INDEX(SP_BSR_SE_Avg,0,COLUMN()))
